Workbook

Sheet 収支予測
H1: =+#REF! -> #REF! | I1: =IF(H2=12,H1+1,H1) -> #REF! | J1: =IF(I2=12,I1+1,I1) -> #REF! | K1: 30 | L1: =IF(K2=12,K1+1,K1) -> 30 | M1: =IF(L2=12,L1+1,L1) -> 30 | N1: =IF(M2=12,M1+1,M1) -> 31 | O1: =IF(N2=12,N1+1,N1) -> 31 | P1: 31 | Q1: 31 | R1: 31 | S1: 31 | T1: 31 | U1: 31 | V1: 31 | W1: =IF(V2=12,V1+1,V1) -> 31 | X1: 31 | Y1: 31 | Z1: =IF(Y2=12,Y1+1,Y1) -> 32 | AA1: =IF(Z2=12,Z1+1,Z1) -> 32 | AB1: =IF(AA2=12,AA1+1,AA1) -> 32 | AC1: =IF(AB2=12,AB1+1,AB1) -> 32 | AD1: =IF(AC2=12,AC1+1,AC1) -> 32 | AE1: =IF(AD2=12,AD1+1,AD1) -> 32 | AF1: =IF(AE2=12,AE1+1,AE1) -> 32 | AG1: =IF(AF2=12,AF1+1,AF1) -> 32 | ... BO1: =IF(BN2=12,BN1+1,BN1) -> 35
H2: =+#REF! -> #REF! | I2: =IF(H2=12,1,H2+1) -> #REF! | J2: =IF(I2=12,1,I2+1) -> #REF! | K2: 10 | L2: =IF(K2=12,1,K2+1) -> 11 | M2: =IF(L2=12,1,L2+1) -> 12 | N2: =IF(M2=12,1,M2+1) -> 1 | O2: 2 | P2: 3 | Q2: 4 | R2: 5 | S2: 6 | T2: 7 | U2: 8 | V2: 9 | W2: =IF(V2=12,1,V2+1) -> 10 | X2: 11 | Y2: 12 | Z2: =IF(Y2=12,1,Y2+1) -> 1 | AA2: =IF(Z2=12,1,Z2+1) -> 2 | AB2: =IF(AA2=12,1,AA2+1) -> 3 | AC2: =IF(AB2=12,1,AB2+1) -> 4 | AD2: =IF(AC2=12,1,AC2+1) -> 5 | AE2: =IF(AD2=12,1,AD2+1) -> 6 | AF2: =IF(AE2=12,1,AE2+1) -> 7 | AG2: =IF(AF2=12,1,AF2+1) -> 8 | ... BO2: =IF(BN2=12,1,BN2+1) -> 6
H3: =+#REF! -> #REF! | I3: =+#REF! -> #REF! | J3: =+#REF! -> #REF! | K3: 4 | L3: =+#REF! -> #REF! | M3: =+#REF! -> #REF! | N3: =+#REF! -> #REF! | O3: 8 | P3: 9 | Q3: 10 | R3: 11 | S3: 12 | T3: 1 | U3: 2 | V3: 3 | W3: =+V3+1 -> 4 | X3: 5 | Y3: 6 | Z3: =+Y3+1 -> 7 | AA3: =+Z3+1 -> 8 | AB3: =+AA3+1 -> 9 | AC3: =+AB3+1 -> 10 | AD3: =+AC3+1 -> 11 | AE3: =+AD3+1 -> 12 | AF3: =+AE3+1 -> 13 | AG3: =+AF3+1 -> 14 | ... BO3: =+BN3+1 -> 48
T4: 1 | U4: 2 | V4: 3 | W4: 4 | X4: 5 | Y4: 6 | Z4: 7 | AA4: 8 | AB4: 9 | AC4: 10 | AD4: 11 | AE4: 12 | AF4: 13 | AG4: 14 | AH4: 15 | AI4: 15 | AJ4: 15 | AK4: 15 | AL4: 15 | AM4: 15 | AN4: 15 | AO4: 15 | AP4: 15 | AQ4: 15 | AR4: 15 | AS4: 15 | AT4: 15 | AU4: 15 | AV4: 15 | AW4: 15 | AX4: 15 | AY4: 15 | AZ4: 15 | BA4: 15 | BB4: 15 | BC4: 15 | BD4: 15 | BE4: 15 | BF4: 15 | BG4: 15 | BH4: 15 | BI4: 15 | BJ4: 15 | BK4: 15 | BL4: 15 | BM4: 15 | BN4: 15 | BO4: 15
F5: 収支予測表
F9: 勘定科目 | H9: =IF(H3>$F$4,H3-$F$4,"実績") -> #REF! | I9: =IF(I3>$F$4,I3-$F$4,"実績") -> #REF! | J9: 実績 | K9: 実績 | L9: 実績 | M9: 実績 | N9: =IF(N3>$F$4,N3-$F$4,"実績") -> #REF! | O9: =IF(O3>$F$4,O3-$F$4,"実績") -> 8 | P9: 実績 | Q9: 実績 | R9: 実績 | S9: 実績 | T9: 実績 | U9: 実績 | V9: 実績 | W9: 実績 | X9: 実績 | Y9: 実績 | Z9: 実績 | AA9: 実績 | AB9: 予算 | AC9: 予算 | AD9: 予算 | AE9: 予算 | AF9: 手入力 | AG9: 手入力 | AH9: 手入力 | AI9: 手入力 | AJ9: 手入力 | AK9: 手入力 | AL9: 手入力 | AM9: 手入力 | AN9: 手入力 | AO9: 手入力 | AP9: 手入力 | AQ9: 手入力 | AR9: 手入力 | AS9: 手入力 | AT9: 手入力 | AU9: 手入力 | AV9: 手入力 | AW9: 手入力 | AX9: 手入力 | AY9: 手入力 | AZ9: 手入力 | BA9: 手入力 | BB9: 手入力 | BC9: 手入力 | BD9: 手入力 | BE9: 手入力 | BF9: 手入力 | BG9: 手入力 | BH9: 手入力 | BI9: 手入力 | BJ9: 手入力 | BK9: 手入力 | BL9: 手入力 | BM9: 手入力 | BN9: 手入力 | BO9: 手入力
H10: =+H1+H2/100 -> #REF! | I10: =+I1+I2/100 -> #REF! | J10: 30.09 | K10: 30.1 | L10: 30.11 | M10: 30.12 | N10: =+N1+N2/100 -> 31.01 | O10: 31.02 | P10: 31.03 | Q10: 31.04 | R10: 31.05 | S10: 31.06 | T10: 31.07 | U10: 31.08 | V10: 31.09 | W10: 31.1 | X10: 31.11 | Y10: 31.12 | Z10: 32.01 | AA10: =+AA1+AA2/100 -> 32.02 | AB10: =+AB1+AB2/100 -> 32.03 | AC10: =+AC1+AC2/100 -> 32.04 | AD10: =+AD1+AD2/100 -> 32.05 | AE10: =+AE1+AE2/100 -> 32.06 | AF10: =+AF1+AF2/100 -> 32.07 | AG10: =+AG1+AG2/100 -> 32.08 | AH10: =+AH1+AH2/100 -> 32.09 | ... BO10: =+BO1+BO2/100 -> 35.06 | BP10: 2024.07 | BQ10: 2024.08 | BR10: 2024.09 | BS10: 2024.10. | BT10: 2024.11. | BU10: 2024.12. | BV10: 2025.01 | BW10: 2025.02 | BX10: 2025.03 | BY10: 2025.04 | BZ10: 2025.05 | CA10: 2025.06 | CB10: 2025.04 | CC10: 2025.05 | CD10: 2025.06 | CE10: 2025.07 | CF10: 2025.08 | CG10: 2025.09 | CH10: 2025.10. | CI10: 2025.11 | CJ10: 2025.12 | CK10: 2026.01 | CL10: 2026.02 | CM10: 2026.03 | CN10: 2026.04 | CO10: 2026.05
F11: 売上高 | G11: 国保連Ａ型 | H11: =IF($F$4>=H$3,AO11,BA11) -> #REF! | I11: =IF($F$4>=I$3,AP11,BB11) -> #REF! | J11: 11649 | K11: 13405 | L11: 13307 | M11: 19201 | N11: =IF($F$4>=N$3,AU11,BG11) -> #REF! | O11: 13355 | P11: 18202 | Q11: 13100 | R11: 12490 | S11: 13027 | T11: 12481 | U11: 14091 | V11: 13080 | W11: 11883 | X11: 12402 | AB11: 1227385 | AC11: ='予測PL'!L3 -> 780153 | AD11: ='予測PL'!M3 -> 514206 | AE11: ='予測PL'!N3 -> 334355 | AF11: ='予測PL'!C3 -> 955367 | AG11: ='予測PL'!D3 -> 818306 | AH11: ='予測PL'!E3 -> 760538 | AI11: ='予測PL'!F3 -> 903177 | AJ11: ='予測PL'!G3 -> 921683 | AK11: ='予測PL'!H3 -> 806522 | AL11: ='予測PL'!I3 -> 822486 | AM11: ='予測PL'!J3 -> 793307 | ... AQ11: ='予測PL'!N3 -> 334355 | AR11: ='予測PL (2021)'!C3 | AS11: ='予測PL (2021)'!D3 -> 82000 | AT11: ='予測PL (2021)'!E3 -> 119363 | AU11: ='予測PL (2021)'!F3 -> 388107 | AV11: ='予測PL (2021)'!G3 -> 297878 | AW11: ='予測PL (2021)'!H3 -> 321334 | AX11: ='予測PL (2021)'!I3 -> 326856 | AY11: ='予測PL (2021)'!J3 -> 310213 | ... BC11: ='予測PL (2021)'!N3 -> 316667 | BD11: ='予測PL (2023)'!C3 -> 507273 | BE11: ='予測PL (2023)'!D3 -> 367202 | BF11: ='予測PL (2023)'!E3 -> 355174 | BG11: ='予測PL (2023)'!F3 -> 343678 | BH11: ='予測PL (2023)'!G3 -> 310741 | BI11: ='予測PL (2023)'!H3 -> 305926 | BJ11: ='予測PL (2023)'!I3 -> 198380 | BK11: ='予測PL (2023)'!J3 | ... BO11: ='予測PL (2023)'!N3 | BP11: ='予測PL (2024)'!C4 -> 2522779 | BQ11: ='予測PL (2024)'!D4 -> 2548892 | BR11: ='予測PL (2024)'!E4 -> 1925694 | BS11: ='予測PL (2024)'!F4 -> 2380420 | BT11: ='予測PL (2024)'!G4 -> 1810499 | BU11: ='予測PL (2024)'!H4 -> 1671189 | BV11: ='予測PL (2024)'!I4 -> 1672457 | BW11: ='予測PL (2024)'!J4 -> 1488521 | ... CA11: ='予測PL (2024)'!N4 | CB11: ='予測PL (2025.04-)'!C4 -> 2216026 | CC11: ='予測PL (2025.04-)'!D4 -> 2153396 | CD11: ='予測PL (2025.04-)'!E4 -> 2068535 | CE11: ='予測PL (2025.04-)'!F4 -> 1924273 | CF11: ='予測PL (2025.04-)'!G4 -> 1821950 | CG11: ='予測PL (2025.04-)'!H4 -> 1892545 | CH11: ='予測PL (2025.04-)'!I4 -> 1754854 | CI11: ='予測PL (2025.04-)'!J4 -> 1586450 | ... CM11: ='予測PL (2025.04-)'!N4 -> 1952454
G12: 国保連Ｂ型 | H12: =IF($F$4>=H$3,AO12,BA12) -> #REF! | I12: =IF($F$4>=I$3,AP12,BB12) -> #REF! | J12: 6404 | K12: 8041 | L12: 8680 | M12: 11304 | N12: =IF($F$4>=N$3,AU12,BG12) -> #REF! | O12: 7404 | P12: 9786 | Q12: 7695 | R12: 7859 | S12: 7390 | T12: 7106 | U12: 8314 | V12: 7975 | W12: 8048 | X12: 7746 | BP12: ='予測PL (2024)'!C5 -> 0 | BQ12: ='予測PL (2024)'!D5 -> 0 | BR12: ='予測PL (2024)'!E5 -> 0 | BS12: ='予測PL (2024)'!F5 -> 0 | BT12: ='予測PL (2024)'!G5 -> 98373 | BU12: ='予測PL (2024)'!H5 -> 136927 | BV12: ='予測PL (2024)'!I5 -> 120493 | BW12: ='予測PL (2024)'!J5 -> 184887 | ... CA12: ='予測PL (2024)'!N5 | CB12: ='予測PL (2025.04-)'!C5 -> 363290 | CC12: ='予測PL (2025.04-)'!D5 -> 352012 | CD12: ='予測PL (2025.04-)'!E5 -> 411068 | CE12: ='予測PL (2025.04-)'!F5 -> 689889 | CF12: ='予測PL (2025.04-)'!G5 -> 478943 | CG12: ='予測PL (2025.04-)'!H5 -> 465733 | CH12: ='予測PL (2025.04-)'!I5 -> 603545 | CI12: ='予測PL (2025.04-)'!J5 -> 517528 | ... CM12: ='予測PL (2025.04-)'!N5 -> 1036612
G13: 処遇改善手当 | H13: =IF($F$4>=H$3,AO13,BA13) -> #REF! | I13: =IF($F$4>=I$3,AP13,BB13) -> #REF! | J13: 0 | K13: 0 | L13: 0 | M13: 0 | N13: =IF($F$4>=N$3,AU13,BG13) -> #REF! | O13: 0 | P13: 0 | Q13: 0 | R13: 0 | S13: 0 | T13: 0 | U13: 0 | V13: 0 | W13: 0 | X13: 0 | BP13: ='予測PL (2024)'!C6 | BQ13: ='予測PL (2024)'!D6 | BR13: ='予測PL (2024)'!E6 | BS13: ='予測PL (2024)'!F6 | BT13: ='予測PL (2024)'!G6 | BU13: ='予測PL (2024)'!H6 | BV13: ='予測PL (2024)'!I6 | BW13: ='予測PL (2024)'!J6 | ... CA13: ='予測PL (2024)'!N6 | CB13: ='予測PL (2025.04-)'!C6 -> 0 | CC13: ='予測PL (2025.04-)'!D6 -> 0 | CD13: ='予測PL (2025.04-)'!E6 -> 0 | CE13: ='予測PL (2025.04-)'!F6 -> 0 | CF13: ='予測PL (2025.04-)'!G6 -> 0 | CG13: ='予測PL (2025.04-)'!H6 -> 0 | CH13: ='予測PL (2025.04-)'!I6 -> 0 | CI13: ='予測PL (2025.04-)'!J6 -> 0 | ... CM13: ='予測PL (2025.04-)'!N6 -> 0
G14: 特開金 | BP14: ='予測PL (2024)'!C7 -> 0 | BQ14: ='予測PL (2024)'!D7 -> 0 | BR14: ='予測PL (2024)'!E7 -> 0 | BS14: ='予測PL (2024)'!F7 -> 0 | BT14: ='予測PL (2024)'!G7 | BU14: ='予測PL (2024)'!H7 -> 0 | BV14: ='予測PL (2024)'!I7 -> 0 | BW14: ='予測PL (2024)'!J7 -> 0 | ... CA14: ='予測PL (2024)'!N7 | CB14: ='予測PL (2025.04-)'!C7 -> 0 | CC14: ='予測PL (2025.04-)'!D7 -> 2333333 | CD14: ='予測PL (2025.04-)'!E7 -> 0 | CE14: ='予測PL (2025.04-)'!F7 -> 0 | CF14: ='予測PL (2025.04-)'!G7 -> 533333 | CG14: ='予測PL (2025.04-)'!H7 -> 0 | CH14: ='予測PL (2025.04-)'!I7 -> 200000 | CI14: ='予測PL (2025.04-)'!J7 -> 1300000 | ... CM14: ='予測PL (2025.04-)'!N7 -> 200000
C15: 月末売掛残高割合 | D15: 現金割合 | G15: 生産活動 | H15: =IF($F$4>=H$3,AO15,BA15) -> #REF! | I15: =IF($F$4>=I$3,AP15,BB15) -> #REF! | J15: 3531 | K15: 3025 | L15: 3591 | M15: 5315 | N15: =IF($F$4>=N$3,AU15,BG15) -> #REF! | O15: 3168 | P15: 4804 | Q15: 3967 | R15: 3565 | S15: 4107 | T15: 0 | U15: 0 | V15: 0 | W15: 0 | X15: 0 | BP15: ='予測PL (2024)'!C8 -> 644818 | BQ15: ='予測PL (2024)'!D8 -> 876136 | BR15: ='予測PL (2024)'!E8 -> 984805 | BS15: ='予測PL (2024)'!F8 -> 1237218 | BT15: ='予測PL (2024)'!G8 -> 965402 | BU15: ='予測PL (2024)'!H8 -> 792768 | BV15: ='予測PL (2024)'!I8 -> 742111 | BW15: ='予測PL (2024)'!J8 -> 870500 | ... CA15: ='予測PL (2024)'!N8 | CB15: ='予測PL (2025.04-)'!C8 -> 984127 | CC15: ='予測PL (2025.04-)'!D8 -> 1106034 | CD15: ='予測PL (2025.04-)'!E8 -> 1096306 | CE15: ='予測PL (2025.04-)'!F8 -> 1024244 | CF15: ='予測PL (2025.04-)'!G8 -> 1050190 | CG15: ='予測PL (2025.04-)'!H8 -> 1224773 | CH15: ='予測PL (2025.04-)'!I8 -> 1157279 | CI15: ='予測PL (2025.04-)'!J8+1 -> 1138273 | CJ15: ='予測PL (2025.04-)'!K8 -> 1238651 | CK15: ='予測PL (2025.04-)'!L8 -> 2667279 | CL15: ='予測PL (2025.04-)'!M8 -> 1021820 | CM15: ='予測PL (2025.04-)'!N8 -> 1038464
A16: 原価率 | C16: 1 | D16: =1-C16 -> 0 | G16: 合計 | H16: =SUM(H11:H15) -> #REF! | I16: =SUM(I11:I15) -> #REF! | J16: 21584 | K16: 24471 | L16: 25578 | M16: 35820 | N16: =SUM(N11:N15) -> #REF! | O16: 23927 | P16: 32792 | Q16: 24762 | R16: 23914 | S16: 24524 | T16: 19587 | U16: 22405 | V16: 21055 | W16: 19931 | X16: 20148 | AA16: =SUM(AA11:AA15) -> 0 | AB16: =SUM(AB11:AB15) -> 1227385 | AC16: =SUM(AC11:AC15) -> 780153 | AD16: =SUM(AD11:AD15) -> 514206 | AE16: =SUM(AE11:AE15) -> 334355 | AF16: =SUM(AF11:AF15) -> 955367 | AG16: =SUM(AG11:AG15) -> 818306 | AH16: =SUM(AH11:AH15) -> 760538 | ... CO16: =SUM(CO11:CO15) -> 0
A17: 0.3 | F17: 売上原価 | H17: =IF($F$4>=H$3,AO17,BA17) -> #REF! | I17: =IF($F$4>=I$3,AP17,BB17) -> #REF! | J17: 4020 | K17: 4666 | L17: 4472 | M17: 6232 | N17: =IF($F$4>=N$3,AU17,BG17) -> #REF! | O17: 4632 | P17: 6210 | Q17: 4766 | R17: 4484 | S17: 4508 | T17: 4688 | U17: 4399 | V17: 4287 | W17: 3521 | X17: 3939 | AS17: ='予測PL (2021)'!D4 -> 47991 | AT17: ='予測PL (2021)'!E4 -> 100227 | AU17: ='予測PL (2021)'!F4 -> 68268 | AV17: ='予測PL (2021)'!G4 -> 44669 | AW17: ='予測PL (2021)'!H4 -> 53656 | AX17: ='予測PL (2021)'!I4 -> -25789 | AY17: ='予測PL (2021)'!J4 -> 68015 | AZ17: ='予測PL (2021)'!K4 -> 9742 | ... BC17: ='予測PL (2021)'!N4 -> 9368 | BD17: ='予測PL (2023)'!C4 -> 47776 | BE17: ='予測PL (2023)'!D4 -> 20813 | BF17: ='予測PL (2023)'!E4 -> 7576 | BG17: ='予測PL (2023)'!F4 -> 21859 | BH17: ='予測PL (2023)'!G4 -> 14718 | BI17: ='予測PL (2023)'!H4 -> 31386 | BJ17: ='予測PL (2023)'!I4 -> 198380 | BK17: ='予測PL (2023)'!J4 | ... BO17: ='予測PL (2023)'!N4 | BP17: ='予測PL (2024)'!C9 | BQ17: ='予測PL (2024)'!D9 -> 2500 | BR17: ='予測PL (2024)'!E9 -> 55700 | BS17: ='予測PL (2024)'!F9 -> 100695 | BT17: ='予測PL (2024)'!G9 -> 5538 | BU17: ='予測PL (2024)'!H9 -> 15412 | BV17: ='予測PL (2024)'!I9 -> 25044 | BW17: ='予測PL (2024)'!J9 -> 17848 | ... CA17: ='予測PL (2024)'!N9 | CB17: ='予測PL (2025.04-)'!C9 -> 20830 | CC17: ='予測PL (2025.04-)'!D9 -> 119803 | CD17: ='予測PL (2025.04-)'!E9 -> 40602 | CE17: ='予測PL (2025.04-)'!F9 -> 34150 | CF17: ='予測PL (2025.04-)'!G9 -> 20247 | CG17: ='予測PL (2025.04-)'!H9 -> 44500 | CH17: ='予測PL (2025.04-)'!I9 -> 79387 | CI17: ='予測PL (2025.04-)'!J9 -> 6177 | ... CM17: ='予測PL (2025.04-)'!N9 -> 50466
A18: 0.34 | H18: =IF($F$4>=H$3,AO18,BA18) -> #REF! | I18: =IF($F$4>=I$3,AP18,BB18) -> #REF! | J18: 2173 | K18: 2613 | L18: 2735 | M18: 3642 | N18: =IF($F$4>=N$3,AU18,BG18) -> #REF! | O18: 2681 | P18: 3169 | Q18: 2537 | R18: 2684 | S18: 2415 | T18: 2395 | U18: 2566 | V18: 2408 | W18: 2459 | X18: 2423
A19: 0.32 | H19: =IF($F$4>=H$3,AO19,BA19) -> #REF! | I19: =IF($F$4>=I$3,AP19,BB19) -> #REF! | J19: 0 | K19: 0 | L19: 0 | M19: 0 | N19: =IF($F$4>=N$3,AU19,BG19) -> #REF! | O19: 0 | P19: 0 | Q19: 0 | R19: 0 | S19: 0 | T19: 0 | U19: 0 | V19: 0 | W19: 0 | X19: 0
A20: 0.34 | C20: 掛割合 | D20: 現金割合 | H20: =IF($F$4>=H$3,AO20,BA20) -> #REF! | I20: =IF($F$4>=I$3,AP20,BB20) -> #REF! | J20: 627 | K20: 622 | L20: 728 | M20: 1100 | N20: =IF($F$4>=N$3,AU20,BG20) -> #REF! | O20: 680 | P20: 801 | Q20: 769 | R20: 616 | S20: 734 | T20: 0 | U20: 0 | V20: 0 | W20: 0 | X20: 0
C21: 0.995 | D21: =1-C21 -> 0.005 | G21: 合計 | H21: =SUM(H17:H20) -> #REF! | I21: =SUM(I17:I20) -> #REF! | J21: 6820 | K21: 7901 | L21: 7935 | M21: 10974 | N21: =SUM(N17:N20) -> #REF! | O21: 7993 | P21: 10180 | Q21: 8072 | R21: 7784 | S21: 7657 | T21: 7083 | U21: 6965 | V21: 6695 | W21: 5980 | X21: 6362 | AA21: =SUM(AA17:AA20) -> 0 | AB21: =SUM(AB17:AB20) -> 0 | AC21: =SUM(AC17:AC20) -> 0 | AD21: =SUM(AD17:AD20) -> 0 | AE21: =SUM(AE17:AE20) -> 0 | AF21: =SUM(AF17:AF20) -> 0 | AG21: =SUM(AG17:AG20) -> 0 | AH21: =SUM(AH17:AH20) -> 0 | ... CO21: =SUM(CO17:CO20) -> 0
F22: 粗利益 | H22: =+H16-H21 -> #REF! | I22: =+I16-I21 -> #REF! | J22: 14764 | K22: 16570 | L22: 17643 | M22: 24846 | N22: =+N16-N21 -> #REF! | O22: 15934 | P22: 22612 | Q22: 16690 | R22: 16130 | S22: 16867 | T22: 12504 | U22: 15440 | V22: 14360 | W22: 13951 | X22: 13786 | AA22: =+AA16-AA21 -> 0 | AB22: =+AB16-AB21 -> 1227385 | AC22: =+AC16-AC21 -> 780153 | AD22: =+AD16-AD21 -> 514206 | AE22: =+AE16-AE21 -> 334355 | AF22: =+AF16-AF21 -> 955367 | AG22: =+AG16-AG21 -> 818306 | AH22: =+AH16-AH21 -> 760538 | ... CO22: =+CO16-CO21 -> 0
A23: 予測値 | H23: =+H22/H16 -> #REF! | I23: =+I22/I16 -> #REF! | J23: 0.6840252 | K23: 0.67712803 | L23: 0.68977246 | M23: 0.69363484 | N23: =+N22/N16 -> #REF! | O23: 0.66594224 | P23: 0.68955843 | Q23: 0.67401664 | R23: 0.67450029 | S23: 0.68777524 | T23: 0.6383826 | U23: 0.68913189 | V23: 0.68202327 | W23: 0.69996488 | X23: 0.68423665 | AA23: =+AA22/AA16 -> #DIV/0! | AB23: =+AB22/AB16 -> 1 | AC23: =+AC22/AC16 -> 1 | AD23: =+AD22/AD16 -> 1 | AE23: =+AE22/AE16 -> 1 | AF23: =+AF22/AF16 -> 1 | AG23: =+AG22/AG16 -> 1 | AH23: =+AH22/AH16 -> 1 | ... CO23: =+CO22/CO16 -> #DIV/0!
A24: 590 | B24: ＊＊＊＊ | F24: 人件費 | G24: 役員 | H24: =IF($F$4>=H$3,AO24,BA24) -> #REF! | I24: =IF($F$4>=I$3,AP24,BB24) -> #REF! | J24: 950 | K24: 950 | L24: 950 | M24: 950 | N24: =IF($F$4>=N$3,AU24,BG24) -> #REF! | O24: 950 | P24: 950 | Q24: 950 | R24: 950 | S24: 950 | T24: 1400 | U24: 1400 | V24: 1400 | W24: 1400 | X24: 1400 | AB24: 50000 | AC24: ='予測PL'!L7 | AD24: ='予測PL'!M7 | AE24: ='予測PL'!N7 | BP24: ='予測PL (2024)'!C12 -> 100000 | BQ24: ='予測PL (2024)'!D12 -> 100000 | BR24: ='予測PL (2024)'!E12 -> 100000 | BS24: ='予測PL (2024)'!F12 -> 100000 | BT24: ='予測PL (2024)'!G12 -> 100000 | BU24: ='予測PL (2024)'!H12 -> 100000 | BV24: ='予測PL (2024)'!I12 -> 100000 | BW24: ='予測PL (2024)'!J12 -> 100000 | ... CA24: ='予測PL (2024)'!N12 | CB24: ='予測PL (2025.04-)'!C12 -> 100000 | CC24: ='予測PL (2025.04-)'!D12 -> 100000 | CD24: ='予測PL (2025.04-)'!E12 -> 100000 | CE24: ='予測PL (2025.04-)'!F12 -> 100000 | CF24: ='予測PL (2025.04-)'!G12 -> 100000 | CG24: ='予測PL (2025.04-)'!H12 -> 100000 | CH24: ='予測PL (2025.04-)'!I12 -> 100000 | CI24: ='予測PL (2025.04-)'!J12 -> 100000 | ... CM24: ='予測PL (2025.04-)'!N12 -> 100000
B25: ＊＊＊＊ | G25: 給与手当（社員） | H25: =IF($F$4>=H$3,AO25,BA25) -> #REF! | I25: =IF($F$4>=I$3,AP25,BB25) -> #REF! | J25: 1669 | K25: 1729 | L25: 1686 | M25: 1699 | N25: =IF($F$4>=N$3,AU25,BG25) -> #REF! | O25: 1898 | P25: 1919 | Q25: 1914 | R25: 1889 | S25: 1904 | T25: 993 | U25: 1000 | V25: 1024 | W25: 999 | X25: 1006 | AR25: ='予測PL (2021)'!C34 -> 50000 | AS25: ='予測PL (2021)'!D34 -> 30000 | AT25: ='予測PL (2021)'!E34 -> 130000 | AU25: ='予測PL (2021)'!F34 -> 30000 | AV25: ='予測PL (2021)'!G34 -> 30000 | AW25: ='予測PL (2021)'!H34 -> 30000 | AX25: ='予測PL (2021)'!I34 -> 30000 | AY25: ='予測PL (2021)'!J34 -> 30000 | ... BC25: ='予測PL (2021)'!N34 -> 30000 | BD25: ='予測PL (2023)'!C34 -> 30000 | BE25: ='予測PL (2023)'!D34 -> 30000 | BF25: ='予測PL (2023)'!E34 -> 130000 | BG25: ='予測PL (2023)'!F34 -> 30000 | BH25: ='予測PL (2023)'!G34 -> 30000 | BI25: ='予測PL (2023)'!H34 -> 30000 | BJ25: ='予測PL (2023)'!I34 -> 30000 | BK25: ='予測PL (2023)'!J34 -> 30000 | ... BN25: ='予測PL (2023)'!M34 -> 30000 | BP25: ='予測PL (2024)'!C13 -> 990985 | BQ25: ='予測PL (2024)'!D13 -> 1012718 | BR25: ='予測PL (2024)'!E13 -> 1329766 | BS25: ='予測PL (2024)'!F13 -> 1546185 | BT25: ='予測PL (2024)'!G13 -> 1327564 | BU25: ='予測PL (2024)'!H13 -> 1340000 | BV25: ='予測PL (2024)'!I13 -> 1406600 | BW25: ='予測PL (2024)'!J13 -> 1355000 | ... CA25: ='予測PL (2024)'!N13 | CB25: ='予測PL (2025.04-)'!C13 -> 1618732 | CC25: ='予測PL (2025.04-)'!D13 -> 1671913 | CD25: ='予測PL (2025.04-)'!E13 -> 1681563 | CE25: 1855056 | CF25: 1840706 | CG25: 1949143 | CH25: 1854122 | CI25: 1556600 | CJ25: 1477525 | CK25: 1501650 | CL25: 1480172 | CM25: =1229900+885000 -> 2114900
A26: ＊＊＊＊ | B26: 0.11 | G26: 雑給（利用者） | H26: =IF($F$4>=H$3,AO26,BA26) -> #REF! | I26: =IF($F$4>=I$3,AP26,BB26) -> #REF! | J26: 173 | K26: 174 | L26: 204 | M26: 212 | N26: =IF($F$4>=N$3,AU26,BG26) -> #REF! | O26: 0 | P26: 0 | Q26: 0 | R26: 301 | S26: 348 | T26: 553 | U26: 600 | V26: 557 | W26: 759 | X26: 755 | AB26: 1223604 | AC26: ='予測PL'!L9 -> 599194 | AD26: ='予測PL'!M9 -> 328097 | AE26: ='予測PL'!N9 -> 315516 | AF26: ='予測PL'!C9 -> 929867 | AG26: ='予測PL'!D9 -> 791706 | AH26: ='予測PL'!E9 -> 735138 | AI26: ='予測PL'!F9 -> 874778 | AJ26: ='予測PL'!G9 -> 709883 | AK26: ='予測PL'!H9 -> 598522 | AL26: ='予測PL'!I9 -> 640544 | AM26: ='予測PL'!J9 -> 583508 | ... AQ26: ='予測PL'!N9 -> 315516 | AR26: ='予測PL (2021)'!C9 | AS26: ='予測PL (2021)'!D9 | AT26: ='予測PL (2021)'!E9 | AU26: ='予測PL (2021)'!F9 | AV26: ='予測PL (2021)'!G9 | AW26: ='予測PL (2021)'!H9 | AX26: ='予測PL (2021)'!I9 | AY26: ='予測PL (2021)'!J9 | ... BC26: ='予測PL (2021)'!N9 | BP26: ='予測PL (2024)'!C14 -> 1668580 | BQ26: ='予測PL (2024)'!D14 -> 1770640 | BR26: ='予測PL (2024)'!E14 -> 1302720 | BS26: ='予測PL (2024)'!F14 -> 1714646 | BT26: ='予測PL (2024)'!G14 -> 1620679 | BU26: ='予測PL (2024)'!H14 -> 1435431 | BV26: ='予測PL (2024)'!I14 -> 1324109 | BW26: ='予測PL (2024)'!J14 -> 1241742 | ... CA26: ='予測PL (2024)'!N14 | CB26: ='予測PL (2025.04-)'!C14 -> 1369774 | CC26: ='予測PL (2025.04-)'!D14 -> 1323908 | CD26: ='予測PL (2025.04-)'!E14 -> 1441193 | CE26: ='予測PL (2025.04-)'!F14 -> 1160059 | CF26: ='予測PL (2025.04-)'!G14 -> 1091031 | CG26: ='予測PL (2025.04-)'!H14 -> 1107705 | CH26: ='予測PL (2025.04-)'!I14 -> 1005377 | CI26: ='予測PL (2025.04-)'!J14 -> 1113862 | CJ26: 1153096 | CK26: ='予測PL (2025.04-)'!L14 -> 1117223 | CL26: 1023990 | CM26: ='予測PL (2025.04-)'!N14 -> 1240553
A27: ＊＊＊＊ | B27: 0.005 | G27: 法定福利費 | H27: =IF($F$4>=H$3,AO27,BA27) -> #REF! | I27: =IF($F$4>=I$3,AP27,BB27) -> #REF! | J27: 484 | K27: 408 | L27: 392 | M27: 411 | N27: =IF($F$4>=N$3,AU27,BG27) -> #REF! | O27: 360 | P27: 437 | Q27: 408 | R27: 406 | S27: 604 | T27: 490 | U27: 493 | V27: 481 | W27: 583 | X27: 597 | AB27: -640 | AC27: ='予測PL'!L10 -> -1120 | AD27: ='予測PL'!M10 -> -936 | AE27: ='予測PL'!N10 -> -725 | AF27: ='予測PL'!C10 -> -797 | AG27: ='予測PL'!D10 -> 31466 | AH27: ='予測PL'!E10 -> -552 | AI27: ='予測PL'!F10 -> -838 | AJ27: ='予測PL'!G10 -> -1465 | AK27: ='予測PL'!H10 -> -1400 | AL27: ='予測PL'!I10 -> -1353 | AM27: ='予測PL'!J10 -> -1344 | ... AQ27: ='予測PL'!N10 -> -725 | AR27: ='予測PL (2021)'!C10 -> 54574 | AS27: ='予測PL (2021)'!D10 | AT27: ='予測PL (2021)'!E10 | AU27: ='予測PL (2021)'!F10 | AV27: ='予測PL (2021)'!G10 | AW27: ='予測PL (2021)'!H10 | AX27: ='予測PL (2021)'!I10 | AY27: ='予測PL (2021)'!J10 | ... BC27: ='予測PL (2021)'!N10 | BP27: ='予測PL (2024)'!C15 -> 238453 | BQ27: ='予測PL (2024)'!D15 -> 173534 | BR27: ='予測PL (2024)'!E15 -> 197529 | BS27: ='予測PL (2024)'!F15 -> 192435 | BT27: ='予測PL (2024)'!G15 -> 246407 | BU27: ='予測PL (2024)'!H15 -> 247527 | BV27: ='予測PL (2024)'!I15 -> -288512 | BW27: ='予測PL (2024)'!J15 -> 180964 | ... CA27: ='予測PL (2024)'!N15 | CB27: ='予測PL (2025.04-)'!C15 -> 299728 | CC27: ='予測PL (2025.04-)'!D15 -> 111670 | CD27: ='予測PL (2025.04-)'!E15 -> 103259 | CE27: ='予測PL (2025.04-)'!F15 -> 1230856 | CF27: ='予測PL (2025.04-)'!G15 -> 454352 | CG27: ='予測PL (2025.04-)'!H15 -> 216106 | CH27: 357403 | CI27: ='予測PL (2025.04-)'!J15 -> 190986 | CJ27: 190987 | CK27: ='予測PL (2025.04-)'!L15 -> 361748 | CL27: 236847 | CM27: ='予測PL (2025.04-)'!N15 -> 101433
A28: 3780 | B28: ＊＊＊＊ | G28: 福利厚生費 | H28: =IF($F$4>=H$3,AO28,BA28) -> #REF! | I28: =IF($F$4>=I$3,AP28,BB28) -> #REF! | J28: 4719 | K28: 4578 | L28: 4696 | M28: 6936 | N28: =IF($F$4>=N$3,AU28,BG28) -> #REF! | O28: 4078 | P28: 6324 | Q28: 5375 | R28: 4747 | S28: 5173 | T28: 3004 | U28: 3305 | V28: 3130 | W28: 2981 | X28: 3014 | AB28: 55000 | AC28: ='予測PL'!L34*1.1 -> 55000 | AD28: ='予測PL'!M34*1.1 -> 55000 | AE28: ='予測PL'!N34*1.1 -> 55000 | AF28: ='予測PL'!C34 -> 50000 | AG28: ='予測PL'!D34 -> 50000 | AH28: ='予測PL'!E34 -> 150000 | AI28: ='予測PL'!F34 -> 57273 | AJ28: ='予測PL'!G34 -> 50000 | AK28: ='予測PL'!H34 -> 50000 | AL28: ='予測PL'!I34 -> 50000 | AM28: ='予測PL'!J34 -> 50000 | ... AQ28: ='予測PL'!N34 -> 50000 | AR28: ='予測PL (2021)'!C12 -> 181818 | AS28: ='予測PL (2021)'!D12 -> 181818 | AT28: ='予測PL (2021)'!E12 -> 181818 | AU28: ='予測PL (2021)'!F12 -> 227273 | AV28: ='予測PL (2021)'!G12 -> 227273 | AW28: ='予測PL (2021)'!H12 -> 227273 | AX28: ='予測PL (2021)'!I12 -> 272727 | AY28: ='予測PL (2021)'!J12 -> 272727 | ... BC28: ='予測PL (2021)'!N12 -> 272727 | BD28: ='予測PL (2022)'!C12 -> 227273 | BE28: ='予測PL (2022)'!D12 -> 227273 | BF28: ='予測PL (2022)'!E12 -> 227273 | BG28: ='予測PL (2022)'!F12 -> 227273 | BH28: ='予測PL (2022)'!G12 -> 227273 | BI28: ='予測PL (2022)'!H12 -> 227273 | BJ28: ='予測PL (2022)'!I12 -> 272727 | BK28: ='予測PL (2022)'!J12 -> 272727 | BL28: ='予測PL (2022)'!K12 -> 272727 | BP28: ='予測PL (2024)'!C16 -> 201852 | BQ28: ='予測PL (2024)'!D16 -> 253855 | BR28: ='予測PL (2024)'!E16 -> 184259 | BS28: ='予測PL (2024)'!F16 -> 214815 | BT28: ='予測PL (2024)'!G16 -> 205741 | BU28: ='予測PL (2024)'!H16 -> 194028 | BV28: ='予測PL (2024)'!I16 -> 186306 | BW28: ='予測PL (2024)'!J16 -> 154000 | ... CA28: ='予測PL (2024)'!N16 | CB28: ='予測PL (2025.04-)'!C16 -> 194593 | CC28: ='予測PL (2025.04-)'!D16 -> 129626 | CD28: ='予測PL (2025.04-)'!E16 -> 133704 | CE28: ='予測PL (2025.04-)'!F16 -> 176944 | CF28: ='予測PL (2025.04-)'!G16 -> 103241 | CG28: ='予測PL (2025.04-)'!H16 -> 143055 | CH28: ='予測PL (2025.04-)'!I16 -> 200139 | CI28: ='予測PL (2025.04-)'!J16 -> 129352 | ... CK28: ='予測PL (2025.04-)'!L16 -> 158750 | CL28: 298704 | CM28: ='予測PL (2025.04-)'!N16 -> 156297
A29: 予測値 | G29: 合計 | H29: =SUM(H24:H28) -> #REF! | I29: =SUM(I24:I28) -> #REF! | J29: 7995 | K29: 7839 | L29: 7928 | M29: 10208 | N29: =SUM(N24:N28) -> #REF! | O29: 7286 | P29: 9630 | Q29: 8647 | R29: 8293 | S29: 8979 | T29: 6440 | U29: 6798 | V29: 6592 | W29: 6722 | X29: 6772 | AA29: =SUM(AA24:AA28) -> 0 | AB29: =SUM(AB24:AB28) -> 1327964 | AC29: =SUM(AC24:AC28) -> 653074 | AD29: =SUM(AD24:AD28) -> 382161 | AE29: =SUM(AE24:AE28) -> 369791 | AF29: =SUM(AF24:AF28) -> 979070 | AG29: =SUM(AG24:AG28) -> 873172 | AH29: =SUM(AH24:AH28) -> 884586 | ... CO29: =SUM(CO24:CO28) -> 0
A30: 661 | B30: ＊＊＊＊ | F30: 販売費管理費 | G30: 地代家賃 | H30: =IF($F$4>=H$3,AO30,BA30) -> #REF! | I30: =IF($F$4>=I$3,AP30,BB30) -> #REF! | J30: 548 | K30: 548 | L30: 548 | M30: 548 | N30: =IF($F$4>=N$3,AU30,BG30) -> #REF! | O30: 548 | P30: 548 | Q30: 548 | R30: 548 | S30: 548 | T30: 464 | U30: 464 | V30: 464 | W30: 464 | X30: 464 | BP30: ='予測PL (2024)'!C27 -> 217000 | BQ30: ='予測PL (2024)'!D27 -> 217000 | BR30: ='予測PL (2024)'!E27 -> 217000 | BS30: ='予測PL (2024)'!F27 -> 217000 | BT30: ='予測PL (2024)'!G27 -> 367000 | BU30: ='予測PL (2024)'!H27 -> 367000 | BV30: ='予測PL (2024)'!I27 -> 367000 | BW30: ='予測PL (2024)'!J27 -> 367000 | ... CA30: ='予測PL (2024)'!N27 | CB30: ='予測PL (2025.04-)'!C27 -> 367000 | CC30: ='予測PL (2025.04-)'!D27 -> 367000 | CD30: ='予測PL (2025.04-)'!E27 -> 367000 | CE30: ='予測PL (2025.04-)'!F27 -> 367000 | CF30: ='予測PL (2025.04-)'!G27 -> 367000 | CG30: ='予測PL (2025.04-)'!H27 -> 367000 | CH30: ='予測PL (2025.04-)'!I27 -> 367000 | CI30: ='予測PL (2025.04-)'!J27 -> 367000 | ... CM30: ='予測PL (2025.04-)'!N27 -> 350000
A31: ＊＊＊＊ | B31: 0.06 | G31: 消耗品費 | H31: =IF($F$4>=H$3,AO31,BA31) -> #REF! | I31: =IF($F$4>=I$3,AP31,BB31) -> #REF! | J31: 1172 | K31: 860 | L31: 1309 | M31: 1313 | N31: =IF($F$4>=N$3,AU31,BG31) -> #REF! | O31: 1375 | P31: 1391 | Q31: 1106 | R31: 1061 | S31: 877 | T31: 928 | U31: 971 | V31: 1001 | W31: 716 | X31: 1100 | BP31: ='予測PL (2024)'!C32 -> 27530 | BQ31: ='予測PL (2024)'!D32 -> 29515 | BR31: ='予測PL (2024)'!E32 -> 11798 | BS31: ='予測PL (2024)'!F32 -> 11204 | BT31: ='予測PL (2024)'!G32 -> 12816 | BU31: ='予測PL (2024)'!H32 -> 12173 | BV31: ='予測PL (2024)'!I32 -> 2340 | BW31: ='予測PL (2024)'!J32 -> 100 | ... CA31: ='予測PL (2024)'!N32 | CB31: ='予測PL (2025.04-)'!C32 -> 6168 | CC31: ='予測PL (2025.04-)'!D32 -> 6484 | CD31: ='予測PL (2025.04-)'!E32 -> 28378 | CE31: ='予測PL (2025.04-)'!F32 -> 26228 | CF31: ='予測PL (2025.04-)'!G32 -> 7400 | CG31: ='予測PL (2025.04-)'!H32 -> 2600 | CH31: ='予測PL (2025.04-)'!I32 -> 16226 | CI31: ='予測PL (2025.04-)'!J32 -> 10723 | ... CM31: ='予測PL (2025.04-)'!N32 -> 9300
A32: ＊＊＊＊ | B32: 0.02 | G32: 保険料 | H32: =IF($F$4>=H$3,AO32,BA32) -> #REF! | I32: =IF($F$4>=I$3,AP32,BB32) -> #REF! | J32: 425 | K32: 631 | L32: 756 | M32: 877 | N32: =IF($F$4>=N$3,AU32,BG32) -> #REF! | O32: 740 | P32: 579 | Q32: 686 | R32: 418 | S32: 524 | T32: 504 | U32: 782 | V32: 356 | W32: 502 | X32: 463 | AB32: 30000 | AC32: ='予測PL'!L27*1.1 -> 0 | AD32: ='予測PL'!M27*1.1 -> 0 | AE32: ='予測PL'!N27*1.1 -> 0 | AF32: ='予測PL'!C27 | AG32: ='予測PL'!D27 | AH32: ='予測PL'!E27 | AI32: ='予測PL'!F27 | AJ32: ='予測PL'!G27 | AK32: ='予測PL'!H27 | AL32: ='予測PL'!I27 | AM32: ='予測PL'!J27 | ... AQ32: ='予測PL'!N27 | AS32: ='予測PL'!P27 -> 0 | AT32: ='予測PL'!Q27 | AU32: ='予測PL'!R27 | AV32: ='予測PL'!S27 | AW32: ='予測PL'!T27 | AX32: ='予測PL'!U27 | AY32: ='予測PL'!V27 | AZ32: ='予測PL'!W27 | ... BC32: ='予測PL'!Z27 | BP32: ='予測PL (2024)'!C30 -> 10270 | BQ32: ='予測PL (2024)'!D30 -> 10270 | BR32: ='予測PL (2024)'!E30 -> 10270 | BS32: ='予測PL (2024)'!F30 -> 10270 | BT32: ='予測PL (2024)'!G30 -> 10270 | BU32: ='予測PL (2024)'!H30 -> 10270 | BV32: ='予測PL (2024)'!I30 -> 10270 | BW32: ='予測PL (2024)'!J30 -> 10270 | ... CA32: ='予測PL (2024)'!N30 | CB32: ='予測PL (2025.04-)'!C30 -> 9360 | CC32: ='予測PL (2025.04-)'!D30 -> 8840 | CD32: ='予測PL (2025.04-)'!E30 -> 8840 | CE32: ='予測PL (2025.04-)'!F30 -> 8840 | CF32: ='予測PL (2025.04-)'!G30 -> 8840 | CG32: ='予測PL (2025.04-)'!H30 -> 8840 | CH32: ='予測PL (2025.04-)'!I30 -> 8840 | CI32: ='予測PL (2025.04-)'!J30 -> 8840 | ... CM32: ='予測PL (2025.04-)'!N30 -> 8840
A33: 1750 | B33: ＊＊＊＊ | C33: 0.07 | G33: 支払手数料 | H33: =IF($F$4>=H$3,AO33,BA33) -> #REF! | I33: =IF($F$4>=I$3,AP33,BB33) -> #REF! | J33: 0 | K33: 189 | L33: 1 | M33: 3 | N33: =IF($F$4>=N$3,AU33,BG33) -> #REF! | O33: 4 | P33: 3 | Q33: 1 | R33: 147 | S33: 3 | T33: 152 | U33: 0 | V33: 148 | W33: 2 | X33: 32 | AB33: 17589 | AC33: ='予測PL'!L15*1.1 -> 0 | AD33: ='予測PL'!M15*1.1 -> 0 | AE33: ='予測PL'!N15*1.1 -> 0 | AF33: ='予測PL'!C15 -> 20275 | AG33: ='予測PL'!D15 | AH33: ='予測PL'!E15 -> 23091 | AI33: ='予測PL'!F15 -> 473 | AJ33: ='予測PL'!G15 | AK33: ='予測PL'!H15 | AL33: ='予測PL'!I15 | AM33: ='予測PL'!J15 | ... AQ33: ='予測PL'!N15 | AS33: ='予測PL'!P15 -> 0.0047084466 | AT33: ='予測PL'!Q15 | AU33: ='予測PL'!R15 | AV33: ='予測PL'!S15 | AW33: ='予測PL'!T15 | AX33: ='予測PL'!U15 | AY33: ='予測PL'!V15 | AZ33: ='予測PL'!W15 | ... BC33: ='予測PL'!Z15 | BD33: ='予測PL (2023)'!C27 -> 8737 | BE33: ='予測PL (2023)'!D27 | BF33: ='予測PL (2023)'!E27 -> 5940 | BG33: ='予測PL (2023)'!F27 -> 45780 | BH33: ='予測PL (2023)'!G27 | BI33: ='予測PL (2023)'!H27 | BJ33: ='予測PL (2023)'!I27 | BK33: ='予測PL (2023)'!J27 | ... BM33: ='予測PL (2023)'!L27 | BN33: 13480 | BP33: ='予測PL (2024)'!C35 -> 5700 | BQ33: ='予測PL (2024)'!D35 -> 7550 | BR33: ='予測PL (2024)'!E35 -> 8000 | BS33: ='予測PL (2024)'!F35 -> 7850 | BT33: ='予測PL (2024)'!G35 -> 6850 | BU33: ='予測PL (2024)'!H35 -> 7250 | BV33: ='予測PL (2024)'!I35 -> 34150 | BW33: ='予測PL (2024)'!J35 -> 38930 | ... CA33: ='予測PL (2024)'!N35 | CB33: ='予測PL (2025.04-)'!C35 -> 38078 | CC33: ='予測PL (2025.04-)'!D35 -> 75349 | CD33: ='予測PL (2025.04-)'!E35 -> 74842 | CE33: ='予測PL (2025.04-)'!F35 -> 76493 | CF33: ='予測PL (2025.04-)'!G35 -> 49538 | CG33: ='予測PL (2025.04-)'!H35 -> 57097 | CH33: ='予測PL (2025.04-)'!I35 -> 48259 | CI33: ='予測PL (2025.04-)'!J35 -> 49243 | ... CM33: ='予測PL (2025.04-)'!N35 -> 125621
A34: 2758 | B34: ＊＊＊＊ | G34: 管理諸費 | H34: =IF($F$4>=H$3,AO34,BA34) -> #REF! | I34: =IF($F$4>=I$3,AP34,BB34) -> #REF! | J34: 2783 | K34: 2783 | L34: 2783 | M34: 2783 | N34: =IF($F$4>=N$3,AU34,BG34) -> #REF! | O34: 2783 | P34: 2783 | Q34: 2783 | R34: 2783 | S34: 2783 | T34: 2363 | U34: 2363 | V34: 2363 | W34: 2363 | X34: 2363 | AB34: 71758 | AC34: ='予測PL'!L17*1.1 -> 0 | AD34: ='予測PL'!M17*1.1 -> 0 | AE34: ='予測PL'!N17*1.1 -> 0 | AR34: ='予測PL (2021)'!C14 | AS34: ='予測PL (2021)'!D14 | AT34: ='予測PL (2021)'!E14 | AU34: ='予測PL (2021)'!F14 | AV34: ='予測PL (2021)'!G14 | AW34: ='予測PL (2021)'!H14 | AX34: ='予測PL (2021)'!I14 | AY34: ='予測PL (2021)'!J14 | ... BC34: ='予測PL (2021)'!N14 | BP34: ='予測PL (2024)'!C39 -> 30000 | BQ34: ='予測PL (2024)'!D39 -> 30000 | BR34: ='予測PL (2024)'!E39 -> 150000 | BS34: ='予測PL (2024)'!F39 -> 50000 | BT34: ='予測PL (2024)'!G39 -> 50000 | BU34: ='予測PL (2024)'!H39 -> 50000 | BV34: ='予測PL (2024)'!I39 -> 50000 | BW34: ='予測PL (2024)'!J39 -> 69000 | ... CA34: ='予測PL (2024)'!N39 | CB34: ='予測PL (2025.04-)'!C38 -> 418897 | CC34: ='予測PL (2025.04-)'!D38 -> 533082 | CD34: ='予測PL (2025.04-)'!E38 -> 687721 | CE34: 565597 | CF34: ='予測PL (2025.04-)'!G38 -> 541642 | CG34: ='予測PL (2025.04-)'!H38 -> 553455 | CH34: ='予測PL (2025.04-)'!I38 -> 553479 | CI34: ='予測PL (2025.04-)'!J38 -> 414542 | CJ34: ='予測PL (2025.04-)'!K38 -> 549875 | CK34: ='予測PL (2025.04-)'!L38 -> 694845 | CL34: ='予測PL (2025.04-)'!M38 -> 481502 | CM34: ='予測PL (2025.04-)'!N38 -> 625266
A35: 265 | B35: ＊＊＊＊ | H35: =IF($F$4>=H$3,AO35,BA35) -> #REF! | I35: =IF($F$4>=I$3,AP35,BB35) -> #REF! | J35: 317 | K35: 307 | L35: 324 | M35: 324 | N35: =IF($F$4>=N$3,AU35,BG35) -> #REF! | O35: 273 | P35: 273 | Q35: 230 | R35: 336 | S35: 255 | T35: 334 | U35: 299 | V35: 295 | W35: 295 | X35: 308 | AB35: 7480 | AC35: ='予測PL'!L30*1.1 -> 6380 | AD35: ='予測PL'!M30*1.1 -> 8360 | AE35: ='予測PL'!N30*1.1 -> 6490 | AF35: ='予測PL'!C30 -> 5200 | AG35: ='予測PL'!D30 -> 5200 | AH35: ='予測PL'!E30 -> 5400 | AI35: ='予測PL'!F30 -> 5700 | AJ35: ='予測PL'!G30 -> 8100 | AK35: ='予測PL'!H30 -> 5200 | AL35: ='予測PL'!I30 -> 11127 | AM35: ='予測PL'!J30 -> 5900 | ... AQ35: ='予測PL'!N30 -> 5900 | AR35: ='予測PL (2021)'!C30 -> 5800 | AS35: ='予測PL (2021)'!D30 -> 5600 | AT35: ='予測PL (2021)'!E30 -> 5900 | AU35: ='予測PL (2021)'!F30 -> 3350 | AV35: ='予測PL (2021)'!G30 -> 2600 | AW35: ='予測PL (2021)'!H30 -> 2300 | AX35: ='予測PL (2021)'!I30 -> 2150 | AY35: ='予測PL (2021)'!J30 -> 2150 | ... BC35: ='予測PL (2021)'!N30 -> 2400 | BD35: ='予測PL (2023)'!C30 -> 32650 | BE35: ='予測PL (2023)'!D30 -> 32300 | BF35: ='予測PL (2023)'!E30 -> 31800 | BG35: ='予測PL (2023)'!F30 -> 2100 | BH35: ='予測PL (2023)'!G30 -> 2100 | BI35: ='予測PL (2023)'!H30 -> 92709 | BJ35: ='予測PL (2023)'!I30 -> 1400 | BK35: ='予測PL (2023)'!J30 -> 1400 | ... BN35: ='予測PL (2023)'!M30 -> 1400
A36: 332 | B36: ＊＊＊＊ | H36: =IF($F$4>=H$3,AO36,BA36) -> #REF! | I36: =IF($F$4>=I$3,AP36,BB36) -> #REF! | J36: 189 | K36: 189 | L36: 209 | M36: 189 | N36: =IF($F$4>=N$3,AU36,BG36) -> #REF! | O36: 189 | P36: 189 | Q36: 189 | R36: 189 | S36: 189 | T36: 169 | U36: 169 | V36: 169 | W36: 169 | X36: 169
A37: 1800 | B37: ＊＊＊＊ | G37: その他 | H37: =+H38-#REF! -> #REF! | I37: =+I38-#REF! -> #REF! | J37: 3073 | K37: 3358 | L37: 3576 | M37: 3668 | N37: =+N38-#REF! -> #REF! | O37: 3014 | P37: 3737 | Q37: 3244 | R37: 2082 | S37: 3349 | T37: 2535 | U37: 2918 | V37: 2550 | W37: 2375 | X37: 2460 | AB37: 79824 | AC37: ='予測PL'!L37-'収支予測'!AC29-'収支予測'!AC32-'収支予測'!AC33-'収支予測'!AC34-'収支予測'!AC35 -> 364602 | AD37: ='予測PL'!M37-'収支予測'!AD29-'収支予測'!AD32-'収支予測'!AD33-'収支予測'!AD34-'収支予測'!AD35 -> 360785 | AE37: ='予測PL'!N37-'収支予測'!AE29-'収支予測'!AE32-'収支予測'!AE33-'収支予測'!AE34-'収支予測'!AE35 -> 364264 | AF37: =AF39-AF29-AF32-AF33-AF35 -> 23091 | AG37: =AG39-AG29-AG32-AG33-AG35 -> 24182 | AH37: =AH39-AH29-AH32-AH33-AH35 -> 350 | AI37: =AI39-AI29-AI32-AI33-AI35 -> 36298 | AJ37: =AJ39-AJ29-AJ32-AJ33-AJ35 -> 215236 | AK37: =AK39-AK29-AK32-AK33-AK35 -> 206182 | AL37: =AL39-AL29-AL32-AL33-AL35 -> 240116 | AM37: =AM39-AM29-AM32-AM33-AM35 -> 569982 | ... AQ37: =AQ39-AQ29-AQ32-AQ33-AQ35 -> 369854 | AR37: ='予測PL (2021)'!C37-'収支予測'!AR29-'収支予測'!AR34-'収支予測'!AR35 -> 0 | AS37: ='予測PL (2021)'!D37-'収支予測'!AS29-'収支予測'!AS34-'収支予測'!AS35 -> 4000 | AT37: ='予測PL (2021)'!E37-'収支予測'!AT29-'収支予測'!AT34-'収支予測'!AT35 -> 0 | AU37: ='予測PL (2021)'!F37-'収支予測'!AU29-'収支予測'!AU34-'収支予測'!AU35 -> 1000 | AV37: ='予測PL (2021)'!G37-'収支予測'!AV29-'収支予測'!AV34-'収支予測'!AV35 -> 0 | AW37: ='予測PL (2021)'!H37-'収支予測'!AW29-'収支予測'!AW34-'収支予測'!AW35 -> 0 | AX37: ='予測PL (2021)'!I37-'収支予測'!AX29-'収支予測'!AX34-'収支予測'!AX35 -> 0 | AY37: ='予測PL (2021)'!J37-'収支予測'!AY29-'収支予測'!AY34-'収支予測'!AY35 -> 0 | ... BC37: ='予測PL (2021)'!N37-'収支予測'!BC29-'収支予測'!BC34-'収支予測'!BC35 -> 9232 | BD37: ='予測PL (2023)'!C37-'収支予測'!BD29-'収支予測'!BD33-'収支予測'!BD34-'収支予測'!BD35 -> 45454 | BE37: ='予測PL (2023)'!D37-'収支予測'!BE29-'収支予測'!BE33-'収支予測'!BE34-'収支予測'!BE35 -> 90994 | BF37: ='予測PL (2023)'!E37-'収支予測'!BF29-'収支予測'!BF33-'収支予測'!BF34-'収支予測'!BF35 -> 90909 | BG37: ='予測PL (2023)'!F37-'収支予測'!BG29-'収支予測'!BG33-'収支予測'!BG34-'収支予測'!BG35 -> 90909 | BH37: ='予測PL (2023)'!G37-'収支予測'!BH29-'収支予測'!BH33-'収支予測'!BH34-'収支予測'!BH35 -> 90909 | BI37: ='予測PL (2023)'!H37-'収支予測'!BI29-'収支予測'!BI33-'収支予測'!BI34-'収支予測'!BI35 -> 90909 | BJ37: ='予測PL (2023)'!I37-'収支予測'!BJ29-'収支予測'!BJ33-'収支予測'!BJ34-'収支予測'!BJ35 -> -272727 | BK37: ='予測PL (2023)'!J37-'収支予測'!BK29-'収支予測'!BK33-'収支予測'!BK34-'収支予測'!BK35 -> -272727 | ... BN37: ='予測PL (2023)'!M37-'収支予測'!BN29-'収支予測'!BN33-'収支予測'!BN34-'収支予測'!BN35 -> 24940 | BP37: ='予測PL (2024)'!C42-'収支予測'!BP29-SUM('収支予測'!BP30:BP36) -> 84199 | BQ37: ='予測PL (2024)'!D42-'収支予測'!BQ29-SUM('収支予測'!BQ30:BQ36) -> 62289 | BR37: ='予測PL (2024)'!E42-'収支予測'!BR29-SUM('収支予測'!BR30:BR36) -> 90014 | BS37: ='予測PL (2024)'!F42-'収支予測'!BS29-SUM('収支予測'!BS30:BS36) -> 132989 | BT37: ='予測PL (2024)'!G42-'収支予測'!BT29-SUM('収支予測'!BT30:BT36) -> 34691 | BU37: ='予測PL (2024)'!H42-'収支予測'!BU29-SUM('収支予測'!BU30:BU36) -> 32429 | BV37: ='予測PL (2024)'!I42-'収支予測'!BV29-SUM('収支予測'!BV30:BV36) -> 66194 | BW37: ='予測PL (2024)'!J42-'収支予測'!BW29-SUM('収支予測'!BW30:BW36) -> 87541 | ... CA37: ='予測PL (2024)'!N42-'収支予測'!CA29-SUM('収支予測'!CA30:CA36) -> 0 | CB37: ='予測PL (2025.04-)'!C42-'収支予測'!CB30-'収支予測'!CB31-'収支予測'!CB32-'収支予測'!CB33-'収支予測'!CB34-'収支予測'!CB35-'収支予測'!CB36-CB29 -> 71180 | CC37: ='予測PL (2025.04-)'!D42-'収支予測'!CC30-'収支予測'!CC31-'収支予測'!CC32-'収支予測'!CC33-'収支予測'!CC34-'収支予測'!CC35-'収支予測'!CC36-CC29 -> 86030 | CD37: ='予測PL (2025.04-)'!E42-'収支予測'!CD30-'収支予測'!CD31-'収支予測'!CD32-'収支予測'!CD33-'収支予測'!CD34-'収支予測'!CD35-'収支予測'!CD36-CD29 -> 396015 | CE37: =54000+'予測PL (2025.04-)'!F42-'収支予測'!CE30-'収支予測'!CE31-'収支予測'!CE32-'収支予測'!CE33-'収支予測'!CE34-'収支予測'!CE35-'収支予測'!CE36-CE29 -> 139887 | CF37: =158000+'予測PL (2025.04-)'!G42-'収支予測'!CF30-'収支予測'!CF31-'収支予測'!CF32-'収支予測'!CF33-'収支予測'!CF34-'収支予測'!CF35-'収支予測'!CF36-CF29 -> 87123 | CG37: =158000+'予測PL (2025.04-)'!H42-'収支予測'!CG30-'収支予測'!CG31-'収支予測'!CG32-'収支予測'!CG33-'収支予測'!CG34-'収支予測'!CG35-'収支予測'!CG36-CG29 -> 77821 | CH37: =10000+49491+6135 -> 65626 | CI37: 106774 | CJ37: 98369 | CK37: 95634 | CL37: 76535 | CM37: 79997
G38: 合計 | H38: =+H39-H29 -> #REF! | I38: =+I39-I29 -> #REF! | J38: 8507 | K38: 8865 | L38: 9506 | M38: 9705 | N38: =+N39-N29 -> #REF! | O38: 9129 | P38: 9503 | Q38: 8787 | R38: 8456 | S38: 8528 | T38: 7449 | U38: 7966 | V38: 7346 | W38: 6886 | X38: 7359 | AA38: =SUM(AA30:AA37) -> 0 | AB38: =SUM(AB30:AB37) -> 206651 | AC38: =SUM(AC30:AC37) -> 370982 | AD38: =SUM(AD30:AD37) -> 369145 | AE38: =SUM(AE30:AE37) -> 370754 | AF38: =SUM(AF30:AF37) -> 48566 | AG38: =SUM(AG30:AG37) -> 29382 | AH38: =SUM(AH30:AH37) -> 28841 | ... CO38: =SUM(CO30:CO37) -> 0
F39: 経費合計 | H39: =IF($F$4>=H$3,AO39,BA39) -> #REF! | I39: =IF($F$4>=I$3,AP39,BB39) -> #REF! | J39: 16502 | K39: 16704 | L39: 17434 | M39: 19913 | N39: =IF($F$4>=N$3,AU39,BG39) -> #REF! | O39: 16415 | P39: 19133 | Q39: 17434 | R39: 16749 | S39: 17507 | T39: 13889 | U39: 14764 | V39: 13938 | W39: 13608 | X39: 14131 | AA39: =AA29+AA38 -> 0 | AB39: =AB29+AB38 -> 1534615 | AC39: =AC29+AC38 -> 1024056 | AD39: =AD29+AD38 -> 751306 | AE39: =AE29+AE38 -> 740545 | AF39: ='予測PL'!C37 -> 1027636 | AG39: ='予測PL'!D37 -> 902554 | AH39: ='予測PL'!E37 -> 913427 | AI39: ='予測PL'!F37 -> 973684 | AJ39: ='予測PL'!G37 -> 981754 | AK39: ='予測PL'!H37 -> 858504 | AL39: ='予測PL'!I37 -> 940434 | AM39: ='予測PL'!J37 -> 1208046 | ... AQ39: ='予測PL'!N37 -> 740545 | AR39: =AR29+AR38 -> 292192 | AS39: =AS29+AS38 -> 221418 | AT39: =AT29+AT38 -> 317718 | AU39: =AU29+AU38 -> 261623 | AV39: =AV29+AV38 -> 259873 | AW39: =AW29+AW38 -> 259573 | AX39: =AX29+AX38 -> 304877 | AY39: =AY29+AY38 -> 304877 | ... CO39: =CO29+CO38 -> 0
A40: 予測値 | F40: 営業利益 | H40: =+H22-H39 -> #REF! | I40: =+I22-I39 -> #REF! | J40: -1738 | K40: -134 | L40: 209 | M40: 4933 | N40: =+N22-N39 -> #REF! | O40: -481 | P40: 3479 | Q40: -744 | R40: -619 | S40: -640 | T40: -1385 | U40: 676 | V40: 422 | W40: 343 | X40: -345 | AA40: =+AA22-AA39 -> 0 | AB40: =+AB22-AB39 -> -307230 | AC40: =+AC22-AC39 -> -243903 | AD40: =+AD22-AD39 -> -237100 | AE40: =+AE22-AE39 -> -406190 | AF40: =+AF22-AF39 -> -72269 | AG40: =+AG22-AG39 -> -84248 | AH40: =+AH22-AH39 -> -152889 | ... CO40: =+CO22-CO39 -> 0
B41: ＊＊＊＊ | F41: 営業外収益 | H41: =IF($F$4>=H$3,AO41,+$A41+H42+H43) -> #REF! | I41: =IF($F$4>=I$3,AP41,+$A41+I42+I43) -> #REF! | J41: 0 | K41: 102 | L41: 570 | M41: 196 | N41: =IF($F$4>=N$3,AU41,+$A41+N42+N43) -> #REF! | O41: 180 | P41: 0 | Q41: 93 | R41: 0 | S41: 0 | T41: 38 | U41: 0 | V41: 0 | W41: 0 | X41: 0 | AB41: ='予測PL'!K39 | AC41: ='予測PL'!L39 | AD41: ='予測PL'!M39 | AE41: ='予測PL'!N39 | AF41: ='予測PL'!C41 -> 2019000 | AG41: ='予測PL'!D41 -> 7339 | AH41: ='予測PL'!E41 -> 149788 | AI41: ='予測PL'!F41 -> 100000 | AJ41: ='予測PL'!G41 | AK41: ='予測PL'!H41 | AL41: ='予測PL'!I41 | AM41: ='予測PL'!J41 -> 30 | ... AQ41: ='予測PL'!N41 | AR41: ='予測PL (2021)'!C41 -> 200000 | AS41: ='予測PL (2021)'!D41 -> 200034 | AT41: ='予測PL (2021)'!E41 -> 200000 | AU41: ='予測PL (2021)'!F41 -> 400000 | AV41: ='予測PL (2021)'!G41 | AW41: ='予測PL (2021)'!H41 | AX41: ='予測PL (2021)'!I41 | AY41: ='予測PL (2021)'!J41 -> 30 | ... BC41: ='予測PL (2021)'!N41 | BD41: ='予測PL'!AA41 | BE41: ='予測PL'!AB41 | BF41: ='予測PL'!AC41 | BG41: ='予測PL'!AD41 | BH41: ='予測PL'!AE41 | BI41: ='予測PL'!AF41 | BJ41: ='予測PL'!AG41 | BK41: ='予測PL'!AH41 | ... BN41: ='予測PL'!AK41 | BO41: 54 | BP41: ='予測PL (2024)'!C46 -> 77636 | BQ41: ='予測PL (2024)'!D46 -> 78459 | BR41: ='予測PL (2024)'!E46 -> 67823 | BS41: ='予測PL (2024)'!F46 -> 75273 | BT41: ='予測PL (2024)'!G46 -> 67636 | BU41: ='予測PL (2024)'!H46 -> 63273 | BV41: ='予測PL (2024)'!I46 -> 59091 | BW41: ='予測PL (2024)'!J46 -> 51561 | ... CA41: ='予測PL (2024)'!N46 | CB41: ='予測PL (2025.04-)'!C46 -> 19444 | CC41: ='予測PL (2025.04-)'!D46 -> 179264 | CD41: ='予測PL (2025.04-)'!E46 -> 155 | CE41: ='予測PL (2025.04-)'!F46 -> 101047 | CF41: ='予測PL (2025.04-)'!G46 -> 2783 | CG41: ='予測PL (2025.04-)'!H46 -> 0 | CH41: ='予測PL (2025.04-)'!I46 -> 0 | CI41: ='予測PL (2025.04-)'!J46 -> 0 | ... CM41: ='予測PL (2025.04-)'!N46 -> 0
T42: 0 | U42: 0 | V42: 0 | W42: 0 | X42: 0 | AA42: 0
T43: 0 | U43: 0 | V43: 0 | W43: 0 | X43: 0 | AA43: 0
A44: 76 | B44: ＊＊＊＊ | F44: 営業外費用 | H44: =IF($F$4>=H$3,AO44,+$A44) -> #REF! | I44: =IF($F$4>=I$3,AP44,+$A44) -> #REF! | J44: 58 | K44: 182 | L44: 55 | M44: 99 | N44: =IF($F$4>=N$3,AU44,+$A44) -> #REF! | O44: 59 | P44: 57 | Q44: 59 | R44: 44 | S44: 44 | T44: 79 | U44: 103 | V44: 321 | W44: 124 | X44: 77 | AR44: ='予測PL (2021)'!C39+'予測PL (2021)'!C40 -> 0 | AS44: ='予測PL (2021)'!D39+'予測PL (2021)'!D40 -> 0 | AT44: ='予測PL (2021)'!E39+'予測PL (2021)'!E40 -> 0 | AU44: ='予測PL (2021)'!F39+'予測PL (2021)'!F40 -> 0 | AV44: ='予測PL (2021)'!G39+'予測PL (2021)'!G40 -> 0 | AW44: ='予測PL (2021)'!H39+'予測PL (2021)'!H40 -> 0 | AX44: ='予測PL (2021)'!I39+'予測PL (2021)'!I40 -> 0 | AY44: ='予測PL (2021)'!J39+'予測PL (2021)'!J40 -> 0 | ... BC44: ='予測PL (2021)'!N39+'予測PL (2021)'!N40 -> 0 | BP44: ='予測PL (2024)'!C44+'予測PL (2024)'!C45 -> 10355 | BQ44: ='予測PL (2024)'!D44+'予測PL (2024)'!D45 -> 0 | BR44: ='予測PL (2024)'!E44+'予測PL (2024)'!E45 -> 9697 | BS44: ='予測PL (2024)'!F44+'予測PL (2024)'!F45 -> 5260 | BT44: ='予測PL (2024)'!G44+'予測PL (2024)'!G45 -> 0 | BU44: ='予測PL (2024)'!H44+'予測PL (2024)'!H45 -> 5753 | BV44: ='予測PL (2024)'!I44+'予測PL (2024)'!I45 -> 8711 | BW44: ='予測PL (2024)'!J44+'予測PL (2024)'!J45 -> 5095 | ... CA44: ='予測PL (2024)'!N44+'予測PL (2024)'!N45 -> 0 | CB44: ='予測PL (2025.04-)'!C44 -> 5424 | CC44: ='予測PL (2025.04-)'!D44 -> 0 | CD44: ='予測PL (2025.04-)'!E44 -> 9697 | CE44: ='予測PL (2025.04-)'!F44 -> 5260 | CF44: ='予測PL (2025.04-)'!G44 -> 0 | CG44: ='予測PL (2025.04-)'!H44 -> 9862 | CH44: ='予測PL (2025.04-)'!I44 -> 5095 | CI44: ='予測PL (2025.04-)'!J44 -> 0 | ... CM44: ='予測PL (2025.04-)'!N44 -> 9126
A45: 予測値 | F45: 経常利益 | H45: =+H40+H41-H44 -> #REF! | I45: =+I40+I41-I44 -> #REF! | J45: -1796 | K45: -214 | L45: 724 | M45: 5030 | N45: =+N40+N41-N44 -> #REF! | O45: -360 | P45: 3422 | Q45: -710 | R45: -663 | S45: -684 | T45: -1426 | U45: 573 | V45: 101 | W45: 219 | X45: -422 | AA45: =+AA40+AA41-AA44 -> 0 | AB45: =+AB40+AB41-AB44 -> -307230 | AC45: =+AC40+AC41-AC44 -> -243903 | AD45: =+AD40+AD41-AD44 -> -237100 | AE45: =+AE40+AE41-AE44 -> -406190 | AF45: =+AF40+AF41-AF44 -> 1946731 | AG45: =+AG40+AG41-AG44 -> -76909 | AH45: =+AH40+AH41-AH44 -> -3101 | ... CO45: =+CO40+CO41-CO44 -> 0
B46: ＊＊＊＊ | F46: 特別利益 | H46: =IF($F$4>=H$3,AO46,+$A46) -> #REF! | I46: =IF($F$4>=I$3,AP46,+$A46) -> #REF! | J46: 0 | K46: 0 | L46: 0 | M46: 3 | N46: =IF($F$4>=N$3,AU46,+$A46) -> #REF! | O46: 0 | P46: 0 | Q46: 0 | R46: 0 | S46: 0 | T46: 0 | U46: 0 | V46: 200 | W46: 0 | X46: 65 | AA46: 0 | AB46: ='予測PL'!K43 | AC46: ='予測PL'!L43 | AD46: ='予測PL'!M43 | AE46: ='予測PL'!N43 | AF46: ='予測PL'!O43 -> 11810 | AG46: ='予測PL'!P43 | AH46: ='予測PL'!Q43 | AI46: ='予測PL'!R43 | ... AP46: ='予測PL'!Y43 | AQ46: ='予測PL (2021)'!C43 | AR46: ='予測PL'!AA43 | AS46: ='予測PL'!AB43 | AT46: ='予測PL'!AC43 | AU46: ='予測PL'!AD43 | AV46: ='予測PL'!AE43 | AW46: ='予測PL'!AF43 | AX46: ='予測PL'!AG43 | AY46: ='予測PL'!AH43 | ... CM46: ='予測PL'!BV43
B47: ＊＊＊＊ | F47: 特別損失 | H47: =IF($F$4>=H$3,AO47,+$A47) -> #REF! | I47: =IF($F$4>=I$3,AP47,+$A47) -> #REF! | J47: 0 | K47: 87 | L47: 0 | M47: 0 | N47: =IF($F$4>=N$3,AU47,+$A47) -> #REF! | O47: 858 | P47: 167 | Q47: 0 | R47: 0 | S47: 0 | T47: 10 | U47: 0 | V47: 0 | W47: 30 | X47: 30 | AA47: 0 | AB47: ='予測PL'!K44 | AC47: ='予測PL'!L44 | AD47: ='予測PL'!M44 | AE47: ='予測PL'!N44 | AF47: ='予測PL'!O44 -> 0 | AG47: ='予測PL'!P44 | AH47: ='予測PL'!Q44 | AI47: ='予測PL'!R44 | ... CM47: ='予測PL'!BV44
F48: 税引前当期利益 | H48: =+H45+H46-H47 -> #REF! | I48: =+I45+I46-I47 -> #REF! | J48: -1796 | K48: -301 | L48: 724 | M48: 5033 | N48: =+N45+N46-N47 -> #REF! | O48: -1218 | P48: 3255 | Q48: -710 | R48: -663 | S48: -684 | T48: -1436 | U48: 573 | V48: 301 | W48: 189 | X48: -387 | AA48: =+AA45+AA46-AA47 -> 0 | AB48: =+AB45+AB46-AB47 -> -307230 | AC48: =+AC45+AC46-AC47 -> -243903 | AD48: =+AD45+AD46-AD47 -> -237100 | AE48: =+AE45+AE46-AE47 -> -406190 | AF48: =+AF45+AF46-AF47 -> 1958541 | AG48: =+AG45+AG46-AG47 -> -76909 | AH48: =+AH45+AH46-AH47 -> -3101 | ... CO48: =+CO45+CO46-CO47 -> 0
F49: 期間累計 | H49: =+G49+H48 -> #REF! | I49: =+H49+I48 -> #REF! | J49: -765 | K49: -1066 | L49: -342 | M49: 4691 | N49: =+M49+N48 -> #REF! | O49: 2327 | P49: 5582 | Q49: 4872 | R49: 4209 | S49: 3525 | T49: -1436 | U49: -863 | V49: -562 | W49: -373 | X49: -760 | AA49: 2468240 | AB49: =+AA49+AB48 -> 2161010 | AC49: =+AB49+AC48 -> 1917107 | AD49: =+AC49+AD48 -> 1680007 | AE49: =+AD49+AE48 -> 1273817 | AF49: =+AF48 -> 1958541 | AG49: =+AF49+AG48 -> 1881632 | AH49: =+AG49+AH48 -> 1878531 | AI49: =+AH49+AI48 -> 1908024 | AJ49: =+AI49+AJ48 -> 1847953 | AK49: =+AJ49+AK48 -> 1795971 | AL49: =+AK49+AL48 -> 1678023 | AM49: =+AL49+AM48 -> 1263314 | AN49: =+AM49+AN48 -> 1039565 | ... AP49: =+AO49+AP48 -> 558562 | AQ49: 106918 | AR49: =AR48 -> -92192 | AS49: =+AR49+AS48 -> -79567.005 | AT49: =+AS49+AT48 -> -178149 | AU49: =+AT49+AU48 -> 280067 | AV49: =+AU49+AV48 -> 273403 | AW49: =+AV49+AW48 -> 281508 | AX49: =+AW49+AX48 -> 329276 | AY49: =+AX49+AY48 -> 266627 | AZ49: =+AY49+AZ48 -> 274922 | BA49: =+AZ49+BA48 -> 55100.995 | BB49: 960688 | BC49: =+BB49+BC48 -> 953628 | BD49: =BD48 -> 115383 | BE49: =+BD49+BE48 -> 81205 | BF49: =+BE49+BF48 -> -57119 | BG49: =+BF49+BG48 -> -131362 | BH49: =+BG49+BH48 -> -185621 | BI49: =+BH49+BI48 -> -351972 | BJ49: =+BI49+BJ48 -> -383372 | BK49: =+BJ49+BK48 -> -414772 | BL49: =+BK49+BL48 -> -446172 | ... BO49: =+BN49+BO48 -> -321941 | BP49: =BP48 -> -339691 | BQ49: =+BP49+BQ48 -> -506075 | BR49: =+BQ49+BR48 -> -1194506 | BS49: =+BR49+BS48 -> -1804944 | BT49: =+BS49+BT48 -> -2850590 | BU49: =+BT49+BU48 -> -4003706 | BV49: =+BU49+BV48 -> -4701766 | BW49: =+BV49+BW48 -> -5733787 | BX49: =+BW49+BX48 -> -7923136 | ... CA49: =+BZ49+CA48 -> -7923136 | CB49: =CB48 -> -936877 | CC49: =+CB49+CC48 -> 653457 | CD49: =+CC49+CD48 -> -843293 | CE49: =+CD49+CE48 -> -2850210 | CF49: =+CE49+CF48 -> -3634131 | CG49: =+CF49+CG48 -> -4688264 | CH49: =+CG49+CH48 -> -5633539 | CI49: =+CH49+CI48 -> -5145387 | CJ49: =+CI49+CJ48 -> -4543192 | ... CM49: =+CL49+CM48 -> -3357052
F51: ＦＬ | H51: =+H21+H29 -> #REF! | I51: 17047 | J51: 14815 | K51: 17135 | L51: 16997 | M51: 24013 | N51: 17459 | O51: 16153 | P51: 20536 | Q51: 17329 | R51: 17286 | S51: 17444 | T51: 13523 | U51: 13763 | V51: 13287 | W51: 12702 | X51: 13134 | Y51: 15471 | Z51: 13458 | AA51: =+AA21+AA29 -> 0 | AB51: =+AB21+AB29 -> 1327964 | AC51: =+AC21+AC29 -> 653074 | AD51: =+AD21+AD29 -> 382161 | AE51: =+AE21+AE29 -> 369791 | AF51: =+AF21+AF29 -> 979070 | AG51: =+AG21+AG29 -> 873172 | AH51: =+AH21+AH29 -> 884586 | ... CO51: =+CO21+CO29 -> 0
H52: =+H51/H16 -> #REF! | I52: 0.63711533 | J52: 0.63711533 | K52: 0.63711533 | L52: 0.63711533 | M52: 0.63711533 | N52: 0.63711533 | O52: 0.63711533 | P52: 0.63711533 | Q52: 0.63711533 | R52: 0.63711533 | S52: 0.63711533 | T52: 0.6904069 | U52: 0.61428253 | V52: 0.63106151 | W52: 0.63729868 | X52: 0.65187612 | Y52: 0.53905923 | Z52: 0.65023917 | AA52: =+AA51/AA16 -> #DIV/0! | AB52: =+AB51/AB16 -> 1.0819458 | AC52: =+AC51/AC16 -> 0.83711016 | AD52: =+AD51/AD16 -> 0.74320603 | AE52: =+AE51/AE16 -> 1.1059832 | AF52: =+AF51/AF16 -> 1.0248104 | AG52: =+AG51/AG16 -> 1.0670483 | AH52: =+AH51/AH16 -> 1.1631056 | ... CO52: =+CO51/CO16 -> #DIV/0!
F55: 【資金収支予測】
F56: 項目 | H56: =+H9 -> #REF! | I56: 実績 | J56: 実績 | K56: 実績 | L56: 実績 | M56: 実績 | N56: =+N9 -> #REF! | O56: =+O9 -> 8 | P56: 実績 | Q56: 実績 | R56: 実績 | S56: 実績 | T56: 実績 | U56: 実績 | V56: 実績 | W56: 実績 | X56: 実績 | Y56: 実績 | Z56: 実績 | AA56: =+AA9 -> 実績 | AB56: =+AB9 -> 予算 | AC56: =+AC9 -> 予算 | AD56: =+AD9 -> 予算 | AE56: =+AE9 -> 予算 | AF56: =+AF9 -> 手入力 | AG56: =+AG9 -> 手入力 | AH56: =+AH9 -> 手入力 | ... CO56: =+CO9
H57: =+H10 -> #REF! | I57: =+I10 -> #REF! | J57: 30.09 | K57: =+K10 -> 30.1 | L57: 30.11 | M57: 30.12 | N57: =+N10 -> 31.01 | O57: =+O10 -> 31.02 | P57: 31.03 | Q57: 31.04 | R57: 31.05 | S57: 31.06 | T57: 31.07 | U57: 31.08 | V57: 31.09 | W57: 31.1 | X57: 31.11 | Y57: 31.12 | Z57: 32.01 | AA57: =+AA10 -> 32.02 | AB57: =+AB10 -> 32.03 | AC57: =+AC10 -> 32.04 | AD57: =+AD10 -> 32.05 | AE57: =+AE10 -> 32.06 | AF57: =+AF10 -> 32.07 | AG57: =+AG10 -> 32.08 | AH57: =AH10 -> 32.09 | AI57: =AI10 -> 32.1 | AJ57: =AJ10 -> 32.11 | AK57: =AK10 -> 32.12 | AL57: =AL10 -> 33.01 | AM57: =AM10 -> 33.02 | AN57: =AN10 -> 33.03 | AO57: =AO10 -> 33.04 | ... CO57: =CO10 -> 2026.05
F58: A.前月繰越金 | H58: 12372 | I58: =+H87 -> 14277 | J58: 5700.3983 | K58: 6047.935 | L58: 5625.63 | M58: 11196.06 | N58: =+M87 -> 20592.465 | O58: 12140.36 | P58: 12286.67 | Q58: 18233.835 | R58: 14652.175 | S58: 11925.215 | T58: 12755.85 | U58: 10625.87 | V58: 8173.61 | W58: 4154.46 | X58: 3899.835 | AB58: =+AA87 -> 4057182 | AC58: =+AB87+AB89 -> 3968109 | AD58: =+AC87+AC89 -> 3610744 | AE58: =+AD87+AD89 -> 3158494 | AF58: 3144196 | AG58: =AF88 -> 5335921 | AH58: =AG88 -> 4697613 | AI58: 4913932 | AJ58: 4865910 | AK58: 9861214 | AL58: 9424607 | AM58: 9466929 | AN58: 8954292 | AO58: 8736916 | AP58: 8576078 | AQ58: =AP88 -> 8285812 | AR58: 8066768 | AS58: =+AR87+AR89 -> 7636804 | AT58: =+AS87+AS89 -> 6810608 | AU58: =+AT87+AT89 -> 6122905 | AV58: =+AU87+AU89 -> 6380845 | AW58: =+AV87+AV89 -> 6926730 | AX58: =+AW87+AW89 -> 6836565 | AY58: =+AX87+AX89 -> 6852150 | AZ58: =+AY87+AY89 -> 6964034 | ... BE58: =+BD87+BD89 -> 7641687 | BF58: 7290061 | BG58: =+BF87+BF89 -> 7282296 | BH58: =+BG87+BG89 -> 4184250 | BI58: =+BH87+BH89 -> 4028550 | BJ58: =+BI87+BI89 -> 3979970 | BK58: =+BJ87+BJ89 -> 4265220 | BL58: =+BK87+BK89 -> 4230703 | BM58: =+BL87+BL89 -> 4399413 | BN58: =+BM87+BM89 -> 3693996 | BO58: =+BN87+BN89 -> 3638036 | BP58: 671260 | BQ58: 2023687 | BR58: =+BQ87+BQ89 -> 1257449 | BS58: =+BR87+BR89 -> 1016388 | BT58: =+BS87+BS89 -> 1261712 | BU58: 1153838 | BV58: 4266131 | BW58: =+BV87+BV89 -> 1370561 | BX58: 3046107 | BY58: =+BX87+BX89 -> 1885231 | BZ58: =+BY87+BY89 -> 1885231 | CA58: =+BZ87+BZ89 -> 1885231 | CB58: 0 | CC58: =+CB87+CB89 -> 2375095 | CD58: =+CC87+CC89 -> 5059346 | CE58: =+CD87+CD89 -> 4009152 | CF58: 1363824 | CG58: =+CF87+CF89 -> 1675586 | CH58: =+CG87+CG89 -> 589379 | CI58: =IF(CH88="",CH87,CH88) -> 950549 | CJ58: =IF(CI88="",CI87,CI88) -> 2427751 | CK58: =IF(CJ88="",CJ87,CJ88) -> 3121861 | CL58: =IF(CK88="",CK87,CK88) -> 3955759 | CM58: =IF(CL88="",CL87,CL88) -> 4382370 | CN58: =IF(CM88="",CM87,CM88) -> 1674873 | CO58: =IF(CN88="",CN87,CN88) -> 948701.33
F59: 営業収入 | G59: 現金売上 | H59: =25065-5027 -> 20038 | I59: =+I16*$D16+1531 -> #REF! | J59: 18020.2 | K59: 20391.8 | L59: 21469.4 | M59: 29101 | N59: =+N16*$D16+1431 -> #REF! | O59: 19632.6 | P59: 27075.6 | Q59: 19295.6 | R59: 19013.2 | S59: 19745.2 | T59: 16092.6 | U59: 18516 | V59: 16173 | W59: 16612.8 | X59: 15834.4 | AB59: =+AB16*$D16 -> 0 | AC59: =+AC16*$D16 -> 0 | AD59: =+AD16*$D16 -> 0 | AE59: =+AE16*$D16 -> 0 | AF59: =+AF16*$D16 -> 0 | AG59: =+AG16*$D16 -> 0 | AH59: =+AH16*$D16 -> 0 | AI59: =+AI16*$D16 -> 0 | ... AR59: =+AR16*$D16 -> 0 | AS59: 22640 | AT59: 11495 | AU59: 38560 | AV59: 28320 | AW59: =+AW16*$D16 -> 0 | AX59: 29005 | AY59: 2430 | AZ59: =+AZ16*$D16 -> 0 | BA59: =+BA16*$D16 -> 0 | BB59: =+BB16*$D16 -> 0 | BC59: =+BC16*$D16 -> 0 | BD59: =+BD16*$D16 -> 0 | BE59: =+BE16*$D16 -> 0 | BF59: 1700 | BG59: =+BG16*$D16 -> 0 | BH59: =+BH16*$D16 -> 0 | BI59: =+BI16*$D16 -> 0 | BJ59: =+BJ16*$D16 -> 0 | BK59: =+BK16*$D16 -> 0 | BL59: =+BL16*$D16 -> 0 | BM59: =+BM16*$D16 -> 0 | BN59: =+BN16*$D16 -> 0 | ... CJ59: =+CJ16*$D16 -> 0 | CK59: 1900000 | CL59: =+CL16*$D16 -> 0 | CM59: =+CM16*$D16 -> 0 | CN59: =+CN16*$D16 -> 0 | CO59: =+CO16*$D16 -> 0
G60: 売掛金入金 | H60: 5740 | I60: =+H16*$C16+606 -> #REF! | J60: 5431 | K60: 6290.8 | L60: 6150.2 | M60: 8725.6 | N60: =+M16*$C16-1282 -> 34538 | O60: 6506.6 | P60: 7029.4 | Q60: 7956.4 | R60: 7195.4 | S60: 6855.8 | T60: 5277.8 | U60: 5585.4 | V60: 6139 | W60: 5896 | X60: 6055.2 | AB60: 2466438 | AC60: =+AB16*$C16 -> 1227385 | AD60: 752228 | AE60: =+AD16*$C16 -> 514206 | AF60: 810545 | AG60: =+AF16*$C16 -> 955367 | AH60: =+AG16*$C16 -> 818306 | AI60: 836592 | AJ60: =+AI16*$C16 -> 903177 | AK60: 1013851 | AL60: 887174 | AM60: 914735 | AN60: 882638 | AO60: 980675 | AP60: 868168 | AQ60: 555627 | AR60: =+AQ16*$C16 -> 334355 | AS60: =+AR16*$C16 -> 0 | AT60: 0 | AU60: 194387 | AV60: 340000 | AW60: 281444 | AX60: 341000 | AY60: 492417 | AZ60: 297000 | BA60: =+AZ16*$C16 -> 323164 | BB60: 239721 | BC60: 337900 | BD60: 465092 | BE60: 428463 | BF60: 374528 | BG60: =+BF16*$C16 -> 355174 | BH60: 272472 | BI60: 330000 | BJ60: 330000 | BL60: 203250 | BM60: =+BL16*$C16 -> 0 | BN60: 0 | BO60: 350000 | BP60: =166427+640019 -> 806446 | BQ60: =687300+1202446 -> 1889746 | BR60: 3468789 | BS60: =812685+2589862 -> 3402547 | BT60: =BR16+1200000 -> 4110499 | BU60: =2421540+1211212 -> 3632752 | BV60: =682972+133978 -> 816950 | BW60: =BU16+BT11+BT12 -> 4509756 | BX60: =826356+1829735 -> 2656091 | CA60: =BY16 -> 0 | CB60: =1206560+1754733+194997 -> 3156290 | CC60: =1016700+2245429 -> 3262129 | CD60: =1144550+2622341 -> 3766891 | CE60: =817200+2545708 -> 3362908 | CF60: =1162425+2512633+33030 -> 3708088 | CG60: =1477741+2318047+110550 -> 3906338 | CH60: =1387194+2706046 -> 4093240 | CI60: =1539889+2249240 -> 3789129 | CJ60: =CH16-CH14 -> 3515678 | CK60: 3055624 | CL60: 5209864 | CM60: =625525+2601746 -> 3227271 | CN60: =CL16-CL14 -> 3335683 | CO60: =CM16 -> 4227530
G61: 営業外収益 | H61: 0 | I61: =+I41 -> #REF! | J61: 0 | K61: 102 | L61: 570 | M61: 196 | N61: =+N41 -> #REF! | O61: 180 | P61: 0 | Q61: 93 | R61: 0 | S61: 0 | T61: 38 | U61: 0 | V61: 0 | W61: 0 | X61: 0 | AB61: =+AB41 | AC61: =+AC41 | AD61: =+AD41 | AE61: =+AE41 | AF61: =+AF41 -> 2019000 | AG61: =+AG41 -> 7339 | AH61: =+AH41 -> 149788 | AI61: =+AI41 -> 100000 | ... BO61: =+BO41 -> 54 | BP61: 0 | BQ61: 0 | BR61: 0 | BS61: 0 | BT61: 0 | BU61: 0 | BV61: 0 | BW61: 0 | BX61: 0 | BY61: 0 | BZ61: 0 | CA61: 0 | CB61: 63818 | CC61: =CC14+241446 -> 2574779 | CD61: 66882 | CE61: =CE14 -> 0 | CF61: =CF14 -> 533333 | CG61: =CG14 -> 0 | CH61: =CH14 -> 200000 | CI61: =CI14 -> 1300000 | CJ61: =CJ14 -> 900000 | CK61: 0 | CL61: =CL14 -> 0 | CM61: =CM14 -> 200000 | CN61: =CN14 | CO61: =CO14
G62: ①合計 | H62: =SUM(H59:H61) -> 25778 | I62: =SUM(I59:I61) -> #REF! | J62: 23451.2 | K62: 26784.6 | L62: 28189.6 | M62: 38022.6 | N62: =SUM(N59:N61) -> #REF! | O62: 26319.2 | P62: 34105 | Q62: 27345 | R62: 26208.6 | S62: 26601 | T62: 21408.4 | U62: 24101.4 | V62: 22312 | W62: 22508.8 | X62: 21889.6 | AB62: =SUM(AB59:AB61) -> 2466438 | AC62: =SUM(AC59:AC61) -> 1227385 | AD62: =SUM(AD59:AD61) -> 752228 | AE62: =SUM(AE59:AE61) -> 514206 | AF62: =SUM(AF59:AF61) -> 2829545 | AG62: =SUM(AG59:AG61) -> 962706 | AH62: =SUM(AH59:AH61) -> 968094 | AI62: =SUM(AI59:AI61) -> 936592 | ... CO62: =SUM(CO59:CO61) -> 4227530
F63: 営業支出 | G63: 現金仕入 | H63: =8114-8047 -> 67 | I63: =+I21*$D21+81 -> #REF! | J63: 30.1 | K63: 98.505 | L63: 14.675 | M63: 83.87 | N63: =+N21*$D21+122 -> #REF! | O63: 156.965 | P63: 46.9 | Q63: 47.36 | R63: -313.08 | S63: 35.285 | T63: 8.415 | U63: 89.825 | V63: 93.475 | W63: 64.9 | X63: 180.81 | AB63: =+AB21*$D21 -> 0 | AC63: =+AC21*$D21 -> 0 | AD63: =+AD21*$D21 -> 0 | AE63: =+AE21*$D21 -> 0 | AF63: =+AF21*$D21 -> 0 | AG63: =+AG21*$D21 -> 0 | AH63: =+AH21*$D21 -> 0 | AI63: =+AI21*$D21 -> 0 | ... AR63: =+AR21*$D21 -> 0 | AS63: 0 | AT63: 0 | AU63: 1000 | AV63: 0 | AW63: =+AW21*$D21 -> 268.28 | AX63: 0 | AY63: 0 | AZ63: =+AZ21*$D21 -> 48.71 | BA63: =+BA21*$D21 -> 765.765 | BB63: 0 | BC63: =+BC21*$D21 -> 46.84 | BD63: =+BD21*$D21 -> 238.88 | BE63: =+BE21*$D21 -> 104.065 | BF63: 0 | BG63: =+BG21*$D21 -> 109.295 | BH63: =+BH21*$D21 -> 73.59 | BI63: 11600 | BJ63: =+BJ21*$D21 -> 991.9 | BK63: =+BK21*$D21 -> 0 | BL63: =+BL21*$D21 -> 0 | BM63: =+BM21*$D21 -> 0 | BN63: =+BN21*$D21 -> 0 | BO63: =+BO21*$D21 -> 0 | BP63: 123945 | BQ63: =+BQ21*$D21 -> 12.5 | BR63: =+BR21*$D21 -> 278.5 | BS63: =+BS21*$D21 -> 503.475 | BT63: =+BT21*$D21 -> 27.69 | BU63: 0 | BV63: 0 | BW63: =+BW21*$D21 -> 89.24 | BX63: =+BX21*$D21 -> 157.175 | BY63: =+BY21*$D21 -> 0 | BZ63: =+BZ21*$D21 -> 0 | CA63: =+CA21*$D21 -> 0 | CB63: 0 | CC63: 0 | CD63: 0 | CE63: =+CE21*$D21 -> 170.75 | CF63: 1430 | CG63: 0 | CH63: =+CH21*$D21 -> 396.935 | CI63: =+CI21*$D21 -> 30.885 | CJ63: =+CJ21*$D21 -> 0 | CK63: =+CK21*$D21 -> 256.98 | CL63: =+CL21*$D21 -> 218.545 | CM63: =+CM21*$D21 -> 252.33 | CN63: =+CN21*$D21 -> 0 | CO63: =+CO21*$D21 -> 0
G64: 買掛金支払 | H64: 5399 | I64: =+H21*$C21+4920 -> #REF! | J64: 8956.73 | K64: 12133.9 | L64: 8451.495 | M64: 9209.325 | N64: =+M21*$C21+1820+494 -> 13233.13 | O64: 7340.925 | P64: 9156.035 | Q64: 10720.1 | R64: 10139.64 | S64: 7905.08 | T64: 8487.715 | U64: 7453.585 | V64: 8241.175 | W64: 10504.525 | X64: 6861.1 | AB64: =+AA21*$C21 -> 0 | AC64: =+AB21*$C21 -> 0 | AD64: =+AC21*$C21 -> 0 | AE64: =+AD21*$C21 -> 0 | AF64: =+AE21*$C21 -> 0 | AG64: =+AF21*$C21 -> 0 | AH64: =+AG21*$C21 -> 0 | AI64: =+AH21*$C21 -> 0 | ... AS64: =+AR21*$C21 -> 0 | AT64: 432 | AU64: 124970 | AV64: 46195 | AW64: 8845 | AX64: 8272 | AY64: 8272 | AZ64: 0 | BA64: 63974 | BB64: 168232 | BC64: =+BB21*$C21 -> 79053.745 | BD64: 38960 | BE64: 40290 | BF64: 10013 | BG64: =+BF21*$C21 -> 7538.12 | BH64: 4104 | BI64: 0 | BL64: =+BK21*$C21 -> 0 | BM64: =+BL21*$C21 -> 0 | BN64: =+BM21*$C21 -> 0 | BO64: =+BN21*$C21 -> 0 | BP64: =+BO21*$C21 -> 0 | BQ64: =+BP21*$C21 -> 0 | BR64: =+BQ21*$C21 -> 2487.5 | BS64: 44770 | BT64: =+BS21*$C21 -> 100191.52 | BU64: 0 | BV64: =+BU21*$C21 -> 15334.94 | BW64: =+BV21*$C21 -> 24918.78 | BX64: =+BW21*$C21 -> 17758.76 | BZ64: =+BY21*$C21 -> 0 | CA64: =+BZ21*$C21 -> 0 | CB64: =+CA21*$C21 -> 0 | CC64: 0 | CD64: 0 | CE64: 6908 | CF64: 0 | CG64: 0 | CH64: 48950 | CI64: 75240 | CJ64: =+CI21*$C21 -> 6146.115 | CK64: =+CJ21*$C21 -> 0 | CL64: =+CK21*$C21 -> 51139.02 | CM64: =+CL21*$C21 -> 43490.455 | CN64: =+CM21*$C21 -> 50213.67 | CO64: =+CN21*$C21 -> 0
G65: 未払金支払 | H65: 13198 | I65: =+H29+H32+H37/2+1494+755 -> #REF! | J65: 12254.5 | K65: 12721.5 | L65: 12315 | M65: 12998 | N65: =+M29+M32+M37/2*1.2+1659+233 -> 15177.8 | O65: 11882 | P65: 12406.4 | Q65: 14335.2 | R65: 13121 | S65: 11644.5 | T65: 13014.75 | U65: 10063.25 | V65: 11628.5 | W65: 9327.5 | X65: 9191.25 | AB65: =2280374+264598 -> 2544972 | AC65: =+AB29+AB33+AB32+AB37 -> 1455377 | AD65: =900809+136896 -> 1037705 | AE65: =+AD29+AD33+AD32+AD37 -> 742946 | AF65: =80286+729155 -> 809441 | AG65: =+AF29+AF33+AF32+AF37 -> 1022436 | AH65: =+AG29+AG33+AG32+AG37 -> 897354 | AI65: =754556+74000 -> 828556 | AJ65: =+AI29+AI33+AI32+AI37 -> 967984 | AK65: 1439338 | AL65: 839132 | AM65: 1112531 | AN65: 1016694 | AO65: =+AN29+AN33+AN32+AN37 -> 1116663 | AP65: 1132244 | AQ65: 752521 | AR65: =+AQ29+AQ33+AQ32+AQ37 -> 734645 | AS65: 244000 | AT65: 692226 | AU65: 252242 | AV65: 322000 | AW65: 272000 | AX65: 346948 | AY65: 322000 | AZ65: 322000 | BA65: 322000 | BB65: 390626 | BC65: =+BB29+BB33+BB32+BB37 -> 312934 | BD65: 332155 | BE65: 381611 | BF65: 372000 | BG65: =+BF29+BF33+BF32+BF37 -> 454122 | BH65: 422358 | BI65: 372000 | BJ65: 33000 | BK65: 33000 | BL65: 33000 | BM65: 33000 | BN65: 33000 | BO65: 33000 | BP65: =1630675+546123+18376+11000+33000 -> 2239174 | BQ65: =2536844+36385 -> 2573229 | BR65: =+BQ29+BQ33+BQ32+BQ37 -> 3390856 | BS65: =2506625+558128 -> 3064753 | BT65: =+BS29+BS33+BS32+BS37 -> 3919190 | BU65: 3416095 | BV65: 3640905 | BW65: =+BV29+BV33+BV32+BV37 -> 2839117 | BX65: 3422139 | BZ65: =+BY29+BY33+BY32+BY37 -> 0 | CA65: =+BZ29+BZ33+BZ32+BZ37 -> 0 | CB65: =2969776+457712 -> 3427488 | CC65: =2750222+114993 -> 2865215 | CD65: =4028520+859089-300000 -> 4587609 | CE65: =3069563+2096231 -> 5165794 | CF65: 3850712 | CG65: =2770774+2201064 -> 4971838 | CH65: =2913903+662451 -> 3576354 | CI65: =2833338+654043 -> 3487381 | CJ65: =+CI29+CI33+CI32+CI37 -> 3255657 | CK65: 3689658 | CL65: 3251292 | CM65: 4127335 | CN65: =+CM29+CM33+CM32+CM37 -> 3927641 | CO65: =CN65 -> 3927641
G66: 現金経費 | H66: =3815-424 -> 3391 | I66: =+I31+I34+I35+I36+I37/3+$D66-580 -> #REF! | J66: 5257.3333 | K66: 4737 | L66: 4791 | M66: 4955 | N66: =+N31+N34+N35+N36+N37/2+$D66-544 -> #REF! | O66: 4157 | P66: 5190.5 | Q66: 4277 | R66: 5160 | S66: 4913.5 | T66: 4211.5 | U66: 3032 | V66: 4991 | W66: 4558.5 | X66: 4464 | AB66: =AB31+AB34+AB35+AB36 -> 79238 | AC66: =AC31+AC34+AC35+AC36 -> 6380 | AD66: =AD31+AD34+AD35+AD36 -> 8360 | AE66: =AE31+AE34+AE35+AE36 -> 6490 | AF66: =AF31+AF34+AF35+AF36 -> 5200 | AG66: =AG31+AG34+AG35+AG36 -> 5200 | AH66: =AH31+AH34+AH35+AH36 -> 5400 | AI66: =AI31+AI34+AI35+AI36 -> 5700 | ... AL66: =AL31+AL34+AL35+AL36 -> 11127 | AM66: 190000 | AN66: =AN31+AN34+AN35+AN36 -> 7700 | AO66: =AO31+AO34+AO35+AO36 -> 5800 | AP66: 0 | AQ66: =AQ31+AQ34+AQ35+AQ36 -> 5900 | AR66: =AR31+AR34+AR35+AR36 -> 5800 | AS66: =AS31+AS34+AS35+AS36 -> 5600 | AT66: 0 | AU66: 0 | AV66: 0 | AW66: =AW31+AW34+AW35+AW36 -> 2300 | AX66: 0 | AY66: =AY31+AY34+AY35+AY36 -> 2150 | AZ66: 2430 | BA66: =BA31+BA34+BA35+BA36 -> 2200 | BB66: 21810 | BC66: =BC31+BC34+BC35+BC36 -> 2400 | BD66: =BD31+BD34+BD35+BD36 -> 32650 | BE66: =BE31+BE34+BE35+BE36 -> 32300 | BF66: 0 | BG66: =BG31+BG34+BG35+BG36 -> 2100 | BH66: =BH31+BH34+BH35+BH36 -> 2100 | BI66: 0 | BJ66: =BJ31+BJ34+BJ35+BJ36 -> 1400 | BK66: =BK31+BK34+BK35+BK36 -> 1400 | BL66: =BL31+BL34+BL35+BL36 -> 1400 | BM66: =BM31+BM34+BM35+BM36 -> 40950 | BN66: =BN31+BN34+BN35+BN36 -> 1400 | BO66: 37400 | BP66: =10270+5700+18700 -> 34670 | BQ66: =43200 -> 43200 | BR66: 93025 | BS66: 35120 | BT66: =BT31+BT34+BT35+BT36 -> 62816 | BU66: 0 | BV66: 0 | BW66: =BW31+BW34+BW35+BW36 -> 69100 | BX66: 329303 | BY66: =BY31+BY34+BY35+BY36 -> 0 | BZ66: =BZ31+BZ34+BZ35+BZ36 -> 0 | CA66: =CA31+CA34+CA35+CA36 -> 0 | CB66: 75014 | CC66: 74458 | CD66: 59807 | CE66: 607785 | CF66: 49538 | CG66: 0 | CH66: =176283+48259 -> 224542 | CI66: 0 | CJ66: =CJ31+CJ34+CJ35+CJ36 -> 552675 | CK66: 167787 | CL66: 0 | CM66: 0 | CN66: =CN31+CN34+CN35+CN36 -> 0 | CO66: =CO31+CO34+CO35+CO36 -> 0
G67: 支払利息 | H67: 62 | I67: =+I44-13 -> #REF! | J67: 53 | K67: 53 | L67: 56 | M67: 57 | N67: =+N44-6 -> #REF! | O67: 48 | P67: 50 | Q67: 49 | R67: 44 | S67: 44 | T67: 79 | U67: 41 | V67: 39 | W67: 37 | X67: 77 | AB67: =+AB44 | AC67: =+AC44 | AD67: =+AD44 | AE67: =+AE44 | AF67: =+AF44 | AG67: =+AG44 | AH67: =+AH44 | AI67: =+AI44 | ... CO67: =+CO44
G68: ②合計 | H68: =SUM(H63:H67) -> 22117 | I68: =SUM(I63:I67) -> #REF! | J68: 26551.663 | K68: 29743.905 | L68: 25628.17 | M68: 27303.195 | N68: =SUM(N63:N67) -> #REF! | O68: 23584.89 | P68: 26849.835 | Q68: 29428.66 | R68: 28151.56 | S68: 24542.365 | T68: 25801.38 | U68: 20679.66 | V68: 24993.15 | W68: 24492.425 | X68: 20774.16 | AB68: =SUM(AB63:AB67) -> 2624210 | AC68: =SUM(AC63:AC67) -> 1461757 | AD68: =SUM(AD63:AD67) -> 1046065 | AE68: =SUM(AE63:AE67) -> 749436 | AF68: =SUM(AF63:AF67) -> 814641 | AG68: =SUM(AG63:AG67) -> 1027636 | AH68: =SUM(AH63:AH67) -> 902754 | AI68: =SUM(AI63:AI67) -> 834256 | ... CO68: =SUM(CO63:CO67) -> 3927641
F69: B.営業収支(①-②) | H69: =+H62-H68 -> 3661 | I69: =+I62-I68 -> #REF! | J69: -3100.4633 | K69: -2959.305 | L69: 2561.43 | M69: 10719.405 | N69: =+N62-N68 -> #REF! | O69: 2734.31 | P69: 7255.165 | Q69: -2083.66 | R69: -1942.96 | S69: 2058.635 | T69: -4392.98 | U69: 3421.74 | V69: -2681.15 | W69: -1983.625 | X69: 1115.44 | AB69: =+AB62-AB68 -> -157772 | AC69: =+AC62-AC68 -> -234372 | AD69: =+AD62-AD68 -> -293837 | AE69: =+AE62-AE68 -> -235230 | AF69: =+AF62-AF68 -> 2014904 | AG69: =+AG62-AG68 -> -64930 | AH69: =+AH62-AH68 -> 65340 | AI69: =+AI62-AI68 -> 102336 | ... CO69: =+CO62-CO68 -> 299889
F70: 財務収入 | G70: 短期借入 | J70: 3000 | K70: 2000 | BO70: 420000 | BP70: 3000000 | BU70: 3000000 | CB70: 1000000
G71: 長期借入 | L71: 5000 | AJ71: 5000000
G72: 貸付ノボリコタン | AF72: 184531
G73: 未収入支援金 | L73: 0 | M73: 0 | R73: 0 | S73: 0 | X73: 1377 | AH73: 149788 | AI73: -149788 | AV73: 600000
H74: 70 | I74: 161 | J74: 2161 | K74: 5098 | L74: 2331 | M74: 213 | N74: =67+627+176 -> 870 | O74: 131 | P74: 82 | Q74: 64 | R74: 862 | S74: 238 | T74: 3809 | U74: 493 | V74: 238 | W74: 3468 | X74: 934 | BB74: 2780640
G75: ③合計 | H75: =SUM(H70:H74) -> 70 | I75: =SUM(I70:I74) -> 161 | J75: 5161 | K75: 7098 | L75: 7331 | M75: 213 | N75: =SUM(N70:N74) -> 870 | O75: 131 | P75: 82 | Q75: 64 | R75: 862 | S75: 238 | T75: 3809 | U75: 493 | V75: 238 | W75: 3468 | X75: 2311 | AB75: =SUM(AB70:AB74) -> 0 | AC75: =SUM(AC70:AC74) -> 0 | AD75: =SUM(AD70:AD74) -> 0 | AE75: =SUM(AE70:AE74) -> 0 | AF75: =SUM(AF70:AF74) -> 184531 | AG75: =SUM(AG70:AG74) -> 0 | AH75: =SUM(AH70:AH74) -> 149788 | AI75: =SUM(AI70:AI74) -> -149788 | ... CO75: =SUM(CO70:CO74) -> 0
F76: 財務支出 | G76: エンター未払分 | O76: 858 | S76: 205 | BM76: 670272
G77: Ｓクリへ返済分 | I77: 4279 | J77: 80 | U77: 4301 | AG77: 526900 | AR77: 18762 | AS77: 418000 | BE77: 133000 | CL77: 1520218 | CM77: 1838882
G78: 交通費助成 | I78: 514 | J78: 225 | O78: 369 | U78: 497 | AG78: 70000 | AS78: 132800 | BE78: 217700
G79: 納税 | H79: 72 | I79: 65 | J79: 70 | K79: 85 | L79: 172 | M79: 61 | N79: 83 | O79: 64 | P79: 63 | Q79: 63 | R79: 64 | S79: 64 | U79: 227 | V79: 230 | W79: 246 | X79: 157 | AN79: 20460 | AO79: 6050 | AP79: 8030 | AQ79: 5000 | AR79: 5000 | AS79: 5000 | AW79: 23100 | AX79: 10210 | BJ79: 10210 | BP79: 48480 | BT79: 20000 | BU79: 76300 | BV79: 64385 | BW79: 20000 | CC79: =175200+52500 -> 227700 | CD79: 111600 | CE79: =201917+12965 -> 214882
G80: 消費税 | L80: 0 | M80: 0 | R80: 0 | S80: 0 | AJ80: =-92168+7974 -> -84194 | AN80: 3991 | AP80: 9006 | AQ80: 9140 | AS80: 43955 | AT80: 31770 | AW80: 5099 | AX80: 800 | AY80: 9154 | AZ80: -2355 | BA80: -19236 | BB80: -6657 | BC80: -2989 | BD80: 13508 | BE80: 4869 | BF80: 11178 | BH80: -4169 | BI80: -4524 | BL80: 3140 | BM80: -59211 | BN80: 30160 | BP80: 17735 | BQ80: 32372 | BR80: 15000 | BS80: 60550 | BT80: 15000 | BU80: -12350 | BV80: 11181 | BW80: 15000 | BX80: 36238 | CB80: =CB15*2% -> 19682.54 | CC80: -12538 | CD80: 20389 | CE80: -37028 | CF80: =CF15*2% -> 21003.8 | CG80: 80700 | CH80: =CH15*2% -> 23145.58 | CI80: =CI15*2% -> 22765.46 | CJ80: =CJ15*2% -> 24773.02 | CK80: 134921 | CL80: =CL15*2% -> 20436.4 | CM80: =CM15*2% -> 20769.28 | CN80: =CN15*2% -> 0 | CO80: =CO15*2% -> 0
BA81: 2780640 | BG81: 3000000
G82: 長期借入金返済 | H82: 1369 | I82: =SUM(I93:I100) -> 0 | J82: 1286 | K82: 1286 | L82: 1286 | M82: 1286 | N82: =SUM(N93:N100) -> 0 | O82: 1286 | P82: 1286 | Q82: 1390 | R82: 1350 | S82: 1156 | T82: 1156 | U82: 1156 | V82: 1156 | W82: 1156 | X82: 1156 | AB82: =SUM(AB93:AB103) -> 0 | AC82: =SUM(AC93:AC103) -> 0 | AD82: =SUM(AD93:AD103) -> 0 | AE82: =SUM(AE93:AE103) -> 0 | AF82: =SUM(AF93:AF103) -> 0 | AG82: =SUM(AG93:AG103) -> 0 | AH82: =SUM(AH93:AH103) -> 0 | AI82: =SUM(AI93:AI103) -> 0 | ... CJ82: =SUM(CJ93:CJ103) -> 0 | CK82: 84000 | CL82: 84000 | CM82: =84000+84000 -> 168000 | CN82: 84000 | CO82: 84000
G83: その他 | H83: =772-555-22+41+149 -> 385 | I83: =41+1000+74 -> 1115 | J83: 52 | K83: 3190 | L83: 2864 | M83: 189 | N83: =+M83+1 -> 190 | O83: 142 | P83: 41 | Q83: 109 | R83: 232 | S83: 41 | T83: 390 | U83: 186 | V83: 190 | W83: 337 | X83: 41 | AM83: 100000
G84: ④合計 | H84: =SUM(H76:H83) -> 1826 | I84: =SUM(I76:I83) -> 5973 | J84: 1713 | K84: 4561 | L84: 4322 | M84: 1536 | N84: =SUM(N76:N83) -> 273 | O84: 2719 | P84: 1390 | Q84: 1562 | R84: 1646 | S84: 1466 | T84: 1546 | U84: 6367 | V84: 1576 | W84: 1739 | X84: 1354 | AB84: =SUM(AB76:AB83) -> 0 | AC84: =SUM(AC76:AC83) -> 0 | AD84: =SUM(AD76:AD83) -> 0 | AE84: =SUM(AE76:AE83) -> 0 | AF84: =SUM(AF76:AF83) -> 0 | AG84: =SUM(AG76:AG83) -> 596900 | AH84: =SUM(AH76:AH83) -> 0 | AI84: =SUM(AI76:AI83) -> 0 | ... CO84: =SUM(CO76:CO83) -> 84000
F85: C.財務収支(③-④) | H85: =+H75-H84 -> -1756 | I85: =+I75-I84 -> -5812 | J85: 3448 | K85: 2537 | L85: 3009 | M85: -1323 | N85: =+N75-N84 -> 597 | O85: -2588 | P85: -1308 | Q85: -1498 | R85: -784 | S85: -1228 | T85: 2263 | U85: -5874 | V85: -1338 | W85: 1729 | X85: 957 | AB85: =+AB75-AB84 -> 0 | AC85: =+AC75-AC84 -> 0 | AD85: =+AD75-AD84 -> 0 | AE85: =+AE75-AE84 -> 0 | AF85: =+AF75-AF84 -> 184531 | AG85: =+AG75-AG84 -> -596900 | AH85: =+AH75-AH84 -> 149788 | AI85: =+AI75-AI84 -> -149788 | ... CO85: =+CO75-CO84 -> -84000
F86: D.月次資金収支(B+C) | H86: =+H69+H85 -> 1905 | I86: =+I69+I85 -> #REF! | J86: 347.53667 | K86: -422.305 | L86: 5570.43 | M86: 9396.405 | N86: =+N69+N85 -> #REF! | O86: 146.31 | P86: 5947.165 | Q86: -3581.66 | R86: -2726.96 | S86: 830.635 | T86: -2129.98 | U86: -2452.26 | V86: -4019.15 | W86: -254.625 | X86: 2072.44 | AB86: =+AB69+AB85 -> -157772 | AC86: =+AC69+AC85 -> -234372 | AD86: =+AD69+AD85 -> -293837 | AE86: =+AE69+AE85 -> -235230 | AF86: =+AF69+AF85 -> 2199435 | AG86: =+AG69+AG85 -> -661830 | AH86: =+AH69+AH85 -> 215128 | AI86: =+AI69+AI85 -> -47452 | ... CO86: =+CO69+CO85 -> 215889
F87: E.翌月繰越金(A+D) | H87: =+H58+H86 -> 14277 | I87: =+I58+I86 -> #REF! | J87: 6047.935 | K87: 5625.63 | L87: 11196.06 | M87: 20592.465 | N87: =+N58+N86 -> #REF! | O87: 12286.67 | P87: 18233.835 | Q87: 14652.175 | R87: 11925.215 | S87: 12755.85 | T87: 10625.87 | U87: 8173.61 | V87: 4154.46 | W87: 3899.835 | X87: 5972.275 | AA87: 4057182 | AB87: =+AB58+AB86 -> 3899410 | AC87: =+AC58+AC86 -> 3733737 | AD87: =+AD58+AD86 -> 3316907 | AE87: =+AE58+AE86 -> 2923264 | AF87: =+AF58+AF86 -> 5343631 | AG87: =+AG58+AG86 -> 4674091 | AH87: =+AH58+AH86 -> 4912741 | AI87: =+AI58+AI86 -> 4866480 | ... CO87: =+CO58+CO86 -> 1164590.3
G88: 実際 | AA88: 実際 | AB88: 3968109 | AC88: 3610744 | AD88: 3158494 | AE88: 3135165 | AF88: 5335921 | AG88: 4697613 | AH88: 4913932 | AI88: 4865910 | AJ88: 9851214 | AK88: 9424607 | AL88: 9466929 | AM88: 8954292 | AN88: 8736916 | AO88: 8576078 | AP88: 8285812 | AQ88: 8066768 | AR88: 7636804 | AS88: 6810608 | AT88: 6122905 | AU88: 6380845 | AV88: 6926730 | AW88: 6836565 | AX88: 6852150 | AY88: 6964034 | AZ88: 6950471 | BA88: 4118885 | BB88: 7619143 | BC88: 7560325 | BD88: 7641687 | BE88: 7290061 | BF88: 7282296 | BG88: 4184250 | BH88: 4028550 | BI88: 3979970 | BJ88: 4265220 | BK88: 4230703 | BL88: 4399413 | BM88: 3693996 | BN88: 3638036 | BP88: 1980487 | BQ88: 1257449 | BR88: 1016388 | BS88: 1261712 | BT88: 1180116 | BU88: 4267171 | BV88: 1370561 | BW88: =BW87 -> 2906997 | BX88: 1885231 | BY88: =BY87 -> 1885231 | BZ88: =BZ87 -> 1885231 | CA88: =CA87 -> 1885231 | CB88: 2375095 | CC88: 5059346 | CD88: 4009152 | CE88: 1363824 | CF88: 1675586 | CG88: 589379 | CH88: 950549 | CI88: 2427751 | CJ88: 3121861 | CK88: 3955759 | CL88: 4382370 | CM88: 1674873
G89: 差額 | T89: CF検証 | U89: 残期間に応じて都度集計 | AA89: 差額 | AB89: =AB88-AB87 -> 68699 | AC89: =AC88-AC87 -> -122993 | AD89: =AD88-AD87 -> -158413 | AE89: =AE88-AE87 -> 211901 | AF89: =AF87-AF88 -> 7710 | AG89: =AG87-AG88 -> -23522 | AH89: =AH87-AH88 -> -1191 | AI89: =AI87-AI88 -> 570 | AJ89: =AJ87-AJ88 -> 25983 | AK89: =AK87-AK88 -> 5920 | AL89: =AL87-AL88 -> -5407 | AM89: =AM87-AM88 -> 24871 | ... AQ89: =AQ87-AQ88 -> 2110 | AR89: =AR88-AR87 -> -200112 | AS89: =AS88-AS87 -> -199515 | AT89: =AT88-AT87 -> -174770 | AU89: =AU88-AU87 -> 3205 | AV89: =AV88-AV87 -> -54240 | AW89: =AW88-AW87 -> -59996.72 | AX89: =AX88-AX87 -> 11810 | AY89: =AY88-AY87 -> -41417 | ... CO89: =CO88-CO87 -> -1164590.3
T90: 期間CF予測 | U90: 882.79272 | V90: a
T91: 期間利益 | U91: 5287.558
C92: 長期借入金 | E92: 残高 | F92: 残月 | G92: 月額 | H92: 1 | I92: 2 | J92: 3 | K92: 4 | L92: 5 | M92: 6 | N92: 7 | O92: 8 | P92: 9 | Q92: 10 | R92: 11 | S92: 12 | T92: 13 | U92: 14 | V92: 15 | W92: 16 | X92: 17 | Y92: 1 | Z92: =+Y92+1 -> 2
D93: 毎月金額 | E93: 残高 | F93: 終了年月 | G93: 備考 | H93: =IF($F93>=H$92,$G93,0) -> 備考 | I93: =IF($F93>=I$92,$G93,0) -> 備考 | J93: =IF($F93>=J$92,$G93,0) -> 備考 | K93: 207 | L93: =IF($F93>=L$92,$G93,0) -> 備考 | M93: =IF($F93>=M$92,$G93,0) -> 備考 | N93: =IF($F93>=N$92,$G93,0) -> 備考 | O93: =IF($F93>=O$92,$G93,0) -> 備考 | P93: 207 | Q93: 207 | R93: 207 | S93: 207 | T93: 207 | U93: 207 | V93: 207 | W93: =IF($F93>=W$92,$G93,0) -> 備考 | X93: 207 | Z93: =IF($F93>=Z$92,$G93,0) -> 備考 | AA93: =IF($F93>=AA$92,$G93,0) -> 備考 | AB93: =IF($F93>=AB$92,$G93,0) -> 備考 | AC93: =IF($F93>=AC$92,$G93,0) -> 備考 | AD93: =IF($F93>=AD$92,$G93,0) -> 備考 | AE93: =IF($F93>=AE$92,$G93,0) -> 備考 | AF93: =IF($F93>=AF$92,$G93,0) -> 備考 | AG93: =IF($F93>=AG$92,$G93,0) -> 備考 | ... CO93: =IF($F93>=CO$92,$G93,0) -> 備考
C103: 合計 | D103: =SUM(D94:D102) -> 0 | E103: =SUM(E94:E102) -> 0

Sheet 単位計算
A1: 令和7年3月～ | C1: 単位 | G1: 単位 | M1: 処遇改善手当
A2: A型 | B2: 基本 | C2: 533 | E2: B型 | F2: 基本 | G2: 590
B3: 賃金向上 | C3: 70 | F3: 賃金向上 | G3: 0
B4: 食事提供 | C4: 30 | F4: 食事提供 | G4: 30
B5: 専門職員 | C5: 6 | F5: 専門職員 | G5: 6
B7: 合計 | C7: =SUM(C2:C5) -> 639 | F7: 合計 | G7: =SUM(G2:G5) -> 626
B8: 地域単価 | C8: 10.17 | F8: 地域単価 | G8: 10.17
B9: 一日一人あたり | C9: =C7*C8 -> 6498.63 | F9: 一日一人あたり | G9: =G7*G8 -> 6366.42
A14: 令和7年4月～ | C14: 単位 | G14: 単位
A15: A型 | B15: 基本 | C15: 533 | E15: B型 | F15: 基本 | G15: 590
B16: 賃金向上 | C16: 70 | F16: 賃金向上 | G16: 0
B17: 食事提供 | C17: 30 | F17: 食事提供 | G17: 30
B18: 専門職員 | C18: 6 | F18: 専門職員 | G18: 6
B19: 就労移行加算 | C19: 65 | F19: 就労移行加算 | G19: 0
B21: 合計 | C21: =SUM(C15:C19) -> 704 | F21: 合計 | G21: =SUM(G15:G19) -> 626
B22: 地域単価 | C22: 10.17 | F22: 地域単価 | G22: 10.17
B23: 一日一人あたり | C23: =C21*C22 -> 7159.68 | F23: 一日一人あたり | G23: =G21*G22 -> 6366.42
B25: 処遇改善手当 | C25: 0.096 | E25: 処遇改善手当 | G25: 0.093
A28: 令和8年4月～ | C28: 単位 | G28: 単位
A29: A型 | B29: 基本 | E29: B型 | F29: 基本
B30: 賃金向上 | C30: 70 | F30: 賃金向上 | G30: 0
B31: 食事提供 | C31: 30 | F31: 食事提供 | G31: 30
B32: 専門職員 | C32: 6 | F32: 専門職員 | G32: 6
B33: 就労移行加算 | C33: =65*3 -> 195 | D33: 3名 | F33: 就労移行加算 | M33: 就労移行加算
B35: 合計 | C35: =SUM(C29:C33) -> 301 | F35: 合計 | G35: =SUM(G29:G32) -> 36
B36: 地域単価 | C36: 10.17 | F36: 地域単価 | G36: 10.17
B37: 一日一人あたり | C37: =C35*C36 -> 3061.17 | F37: 一日一人あたり | G37: =G35*G36 -> 366.12
B39: 処遇改善手当 | C39: 0.096 | E39: 処遇改善手当 | G39: 0.093

Sheet 予測PL (2025.04-)
B1: 変動費率 | C1: 4月実績 | D1: 5月実績 | E1: 6月実績 | F1: 7月実績 | G1: 8月実績 | H1: 9月実績 | I1: 10月実績 | J1: 11月実績 | K1: 12月実績 | L1: 1月実績 | M1: 2月実績 | N1: 3月実績 | O1: 累計
O2: =SUM(C2:N2) -> 0
A3: 売上 | C3: =SUM(C4:C8) -> 3563443 | D3: =SUM(D4:D8) -> 5944775 | E3: =SUM(E4:E8) -> 3575909 | F3: =SUM(F4:F8) -> 3638406 | G3: =SUM(G4:G8) -> 3884416 | H3: =SUM(H4:H8) -> 3583051 | I3: =SUM(I4:I8) -> 3715678 | J3: =SUM(J4:J8) -> 4542250 | ... N3: =SUM(N4:N8) -> 4227530 | O3: =SUM(C3:N3) -> 50493228 | P3: =O3/$O$3 -> 1
A4: 国保連Ａ型 | C4: ='A型'!C4+'B型'!C4+'共通費'!C4 -> 2216026 | D4: ='A型'!D4+'B型'!D4+'共通費'!D4 -> 2153396 | E4: ='A型'!E4+'B型'!E4+'共通費'!E4 -> 2068535 | F4: ='A型'!F4+'B型'!F4+'共通費'!F4 -> 1924273 | G4: ='A型'!G4+'B型'!G4+'共通費'!G4 -> 1821950 | H4: ='A型'!H4+'B型'!H4+'共通費'!H4 -> 1892545 | I4: ='A型'!I4+'B型'!I4+'共通費'!I4 -> 1754854 | J4: ='A型'!J4+'B型'!J4+'共通費'!J4 -> 1586450 | ... N4: ='A型'!N4+'B型'!N4+'共通費'!N4 -> 1952454 | O4: =SUM(C4:N4) -> 22543362
A5: 国保連Ｂ型 | C5: ='A型'!C5+'B型'!C5+'共通費'!C5 -> 363290 | D5: ='A型'!D5+'B型'!D5+'共通費'!D5 -> 352012 | E5: ='A型'!E5+'B型'!E5+'共通費'!E5 -> 411068 | F5: ='A型'!F5+'B型'!F5+'共通費'!F5 -> 689889 | G5: ='A型'!G5+'B型'!G5+'共通費'!G5 -> 478943 | H5: ='A型'!H5+'B型'!H5+'共通費'!H5 -> 465733 | I5: ='A型'!I5+'B型'!I5+'共通費'!I5 -> 603545 | J5: ='A型'!J5+'B型'!J5+'共通費'!J5 -> 517528 | ... N5: ='A型'!N5+'B型'!N5+'共通費'!N5 -> 1036612 | O5: =SUM(C5:N5) -> 7235761
A6: 処遇改善手当 | C6: ='A型'!C6+'B型'!C6+'共通費'!C6 -> 0 | D6: ='A型'!D6+'B型'!D6+'共通費'!D6 -> 0 | E6: ='A型'!E6+'B型'!E6+'共通費'!E6 -> 0 | F6: ='A型'!F6+'B型'!F6+'共通費'!F6 -> 0 | G6: ='A型'!G6+'B型'!G6+'共通費'!G6 -> 0 | H6: ='A型'!H6+'B型'!H6+'共通費'!H6 -> 0 | I6: ='A型'!I6+'B型'!I6+'共通費'!I6 -> 0 | J6: ='A型'!J6+'B型'!J6+'共通費'!J6 -> 0 | ... N6: ='A型'!N6+'B型'!N6+'共通費'!N6 -> 0 | O6: =SUM(C6:N6) -> 0
A7: 特開金 | C7: ='A型'!C7+'B型'!C7+'共通費'!C7 -> 0 | D7: ='A型'!D7+'B型'!D7+'共通費'!D7 -> 2333333 | E7: ='A型'!E7+'B型'!E7+'共通費'!E7 -> 0 | F7: ='A型'!F7+'B型'!F7+'共通費'!F7 -> 0 | G7: ='A型'!G7+'B型'!G7+'共通費'!G7 -> 533333 | H7: ='A型'!H7+'B型'!H7+'共通費'!H7 -> 0 | I7: ='A型'!I7+'B型'!I7+'共通費'!I7 -> 200000 | J7: ='A型'!J7+'B型'!J7+'共通費'!J7 -> 1300000 | ... N7: ='A型'!N7+'B型'!N7+'共通費'!N7 -> 200000 | O7: =SUM(C7:N7) -> 5966666
A8: 生産活動 | C8: ='A型'!C8+'B型'!C8+'共通費'!C8 -> 984127 | D8: ='A型'!D8+'B型'!D8+'共通費'!D8 -> 1106034 | E8: ='A型'!E8+'B型'!E8+'共通費'!E8 -> 1096306 | F8: ='A型'!F8+'B型'!F8+'共通費'!F8 -> 1024244 | G8: ='A型'!G8+'B型'!G8+'共通費'!G8 -> 1050190 | H8: ='A型'!H8+'B型'!H8+'共通費'!H8 -> 1224773 | I8: ='A型'!I8+'B型'!I8+'共通費'!I8 -> 1157279 | J8: ='A型'!J8+'B型'!J8+'共通費'!J8 -> 1138272 | ... N8: ='A型'!N8+'B型'!N8+'共通費'!N8 -> 1038464 | O8: =SUM(C8:N8) -> 14747439
A9: 売上原価 | C9: ='A型'!C9+'B型'!C9+'共通費'!C9 -> 20830 | D9: ='A型'!D9+'B型'!D9+'共通費'!D9 -> 119803 | E9: ='A型'!E9+'B型'!E9+'共通費'!E9 -> 40602 | F9: ='A型'!F9+'B型'!F9+'共通費'!F9 -> 34150 | G9: ='A型'!G9+'B型'!G9+'共通費'!G9 -> 20247 | H9: ='A型'!H9+'B型'!H9+'共通費'!H9 -> 44500 | I9: ='A型'!I9+'B型'!I9+'共通費'!I9 -> 79387 | J9: ='A型'!J9+'B型'!J9+'共通費'!J9 -> 6177 | ... N9: ='A型'!N9+'B型'!N9+'共通費'!N9 -> 50466 | O9: =SUM(C9:N9) -> 511267 | P9: =O9/$O$3 -> 0.010125457
A10: 売上総利益 | C10: =C2+C3-C9 -> 3542613 | D10: =D2+D3-D9 -> 5824972 | E10: =E2+E3-E9 -> 3535307 | F10: =F2+F3-F9 -> 3604256 | G10: =G2+G3-G9 -> 3864169 | H10: =H2+H3-H9 -> 3538551 | I10: =I2+I3-I9 -> 3636291 | J10: =J2+J3-J9 -> 4536073 | ... N10: =N2+N3-N9 -> 4177064 | O10: =SUM(C10:N10) -> 49981961
A12: 役員報酬 | C12: ='A型'!C12+'B型'!C12+'共通費'!C12 -> 100000 | D12: ='A型'!D12+'B型'!D12+'共通費'!D12 -> 100000 | E12: ='A型'!E12+'B型'!E12+'共通費'!E12 -> 100000 | F12: ='A型'!F12+'B型'!F12+'共通費'!F12 -> 100000 | G12: ='A型'!G12+'B型'!G12+'共通費'!G12 -> 100000 | H12: ='A型'!H12+'B型'!H12+'共通費'!H12 -> 100000 | I12: ='A型'!I12+'B型'!I12+'共通費'!I12 -> 100000 | J12: ='A型'!J12+'B型'!J12+'共通費'!J12 -> 100000 | ... N12: ='A型'!N12+'B型'!N12+'共通費'!N12 -> 100000 | O12: =SUM(C12:N12) -> 1200000 | P12: =O12/$O$10 -> 0.024008662
A13: 給与手当 | C13: ='A型'!C13+'B型'!C13+'共通費'!C13 -> 1618732 | D13: ='A型'!D13+'B型'!D13+'共通費'!D13 -> 1671913 | E13: ='A型'!E13+'B型'!E13+'共通費'!E13 -> 1681563 | F13: ='A型'!F13+'B型'!F13+'共通費'!F13 -> 1801056 | G13: ='A型'!G13+'B型'!G13+'共通費'!G13 -> 1682706 | H13: ='A型'!H13+'B型'!H13+'共通費'!H13 -> 1791143 | I13: ='A型'!I13+'B型'!I13+'共通費'!I13 -> 1696122 | J13: ='A型'!J13+'B型'!J13+'共通費'!J13 -> 1398600 | ... N13: ='A型'!N13+'B型'!N13+'共通費'!N13 -> 2114900 | O13: =SUM(C13:N13) -> 19442082
A14: 雑給 | C14: ='A型'!C14+'B型'!C14+'共通費'!C14 -> 1369774 | D14: ='A型'!D14+'B型'!D14+'共通費'!D14 -> 1323908 | E14: ='A型'!E14+'B型'!E14+'共通費'!E14 -> 1441193 | F14: ='A型'!F14+'B型'!F14+'共通費'!F14 -> 1160059 | G14: ='A型'!G14+'B型'!G14+'共通費'!G14 -> 1091031 | H14: ='A型'!H14+'B型'!H14+'共通費'!H14 -> 1107705 | I14: ='A型'!I14+'B型'!I14+'共通費'!I14 -> 1005377 | J14: ='A型'!J14+'B型'!J14+'共通費'!J14 -> 1113862 | ... N14: ='A型'!N14+'B型'!N14+'共通費'!N14 -> 1240553 | O14: =SUM(C14:N14) -> 14137946 | P14: =O14/$O$10 -> 0.28286097
A15: 法定福利費 | B15: 0.15 | C15: ='A型'!C15+'B型'!C15+'共通費'!C15 -> 299728 | D15: ='A型'!D15+'B型'!D15+'共通費'!D15 -> 111670 | E15: ='A型'!E15+'B型'!E15+'共通費'!E15 -> 103259 | F15: ='A型'!F15+'B型'!F15+'共通費'!F15 -> 1230856 | G15: ='A型'!G15+'B型'!G15+'共通費'!G15 -> 454352 | H15: ='A型'!H15+'B型'!H15+'共通費'!H15 -> 216106 | I15: ='A型'!I15+'B型'!I15+'共通費'!I15 -> 474202 | J15: ='A型'!J15+'B型'!J15+'共通費'!J15 -> 190986 | ... N15: ='A型'!N15+'B型'!N15+'共通費'!N15 -> 101433 | O15: =SUM(C15:N15) -> 3972199
A16: 福利厚生費 | C16: ='A型'!C16+'B型'!C16+'共通費'!C16 -> 194593 | D16: ='A型'!D16+'B型'!D16+'共通費'!D16 -> 129626 | E16: ='A型'!E16+'B型'!E16+'共通費'!E16 -> 133704 | F16: ='A型'!F16+'B型'!F16+'共通費'!F16 -> 176944 | G16: ='A型'!G16+'B型'!G16+'共通費'!G16 -> 103241 | H16: ='A型'!H16+'B型'!H16+'共通費'!H16 -> 143055 | I16: ='A型'!I16+'B型'!I16+'共通費'!I16 -> 200139 | J16: ='A型'!J16+'B型'!J16+'共通費'!J16 -> 129352 | ... N16: ='A型'!N16+'B型'!N16+'共通費'!N16 -> 156297 | O16: =SUM(C16:N16) -> 1964817
A17: 業務委託費 | C17: ='A型'!C17+'B型'!C17+'共通費'!C17 -> 10000 | D17: ='A型'!D17+'B型'!D17+'共通費'!D17 -> 10000 | E17: ='A型'!E17+'B型'!E17+'共通費'!E17 -> 10000 | F17: ='A型'!F17+'B型'!F17+'共通費'!F17 -> 10000 | G17: ='A型'!G17+'B型'!G17+'共通費'!G17 -> 10000 | H17: ='A型'!H17+'B型'!H17+'共通費'!H17 -> 10000 | I17: ='A型'!I17+'B型'!I17+'共通費'!I17 -> 10000 | J17: ='A型'!J17+'B型'!J17+'共通費'!J17 -> 10000 | ... N17: ='A型'!N17+'B型'!N17+'共通費'!N17 -> 10000 | O17: =SUM(C17:N17) -> 120000
A18: 労務委託費 | C18: ='A型'!C18+'B型'!C18+'共通費'!C18 -> 0 | D18: ='A型'!D18+'B型'!D18+'共通費'!D18 -> 0 | E18: ='A型'!E18+'B型'!E18+'共通費'!E18 -> 0 | F18: ='A型'!F18+'B型'!F18+'共通費'!F18 -> 0 | G18: ='A型'!G18+'B型'!G18+'共通費'!G18 -> 0 | H18: ='A型'!H18+'B型'!H18+'共通費'!H18 -> 0 | I18: ='A型'!I18+'B型'!I18+'共通費'!I18 -> 0 | J18: ='A型'!J18+'B型'!J18+'共通費'!J18 -> 0 | ... N18: ='A型'!N18+'B型'!N18+'共通費'!N18 -> 0 | O18: =SUM(C18:N18) -> 0
A19: 旅費交通費 | C19: ='A型'!C19+'B型'!C19+'共通費'!C19 -> 55573 | D19: ='A型'!D19+'B型'!D19+'共通費'!D19 -> 54809 | E19: ='A型'!E19+'B型'!E19+'共通費'!E19 -> 66055 | F19: ='A型'!F19+'B型'!F19+'共通費'!F19 -> 69082 | G19: ='A型'!G19+'B型'!G19+'共通費'!G19 -> 61855 | H19: ='A型'!H19+'B型'!H19+'共通費'!H19 -> 66209 | I19: ='A型'!I19+'B型'!I19+'共通費'!I19 -> 49491 | J19: ='A型'!J19+'B型'!J19+'共通費'!J19 -> 43618 | ... N19: ='A型'!N19+'B型'!N19+'共通費'!N19 -> 60309 | O19: =SUM(C19:N19) -> 704783
A20: 通信費 | C20: ='A型'!C20+'B型'!C20+'共通費'!C20 -> 1607 | D20: ='A型'!D20+'B型'!D20+'共通費'!D20 -> 1821 | E20: ='A型'!E20+'B型'!E20+'共通費'!E20 -> 1178 | F20: ='A型'!F20+'B型'!F20+'共通費'!F20 -> 9905 | G20: ='A型'!G20+'B型'!G20+'共通費'!G20 -> 13432 | H20: ='A型'!H20+'B型'!H20+'共通費'!H20 -> 1612 | I20: ='A型'!I20+'B型'!I20+'共通費'!I20 -> 6135 | J20: ='A型'!J20+'B型'!J20+'共通費'!J20 -> 3356 | ... N20: ='A型'!N20+'B型'!N20+'共通費'!N20 -> 2235 | O20: =SUM(C20:N20) -> 103686 | P20: =O20/$O$10 -> 0.0020744684
A21: 研修採用費 | C21: ='A型'!C21+'B型'!C21+'共通費'!C21 -> 0 | D21: ='A型'!D21+'B型'!D21+'共通費'!D21 -> 0 | E21: ='A型'!E21+'B型'!E21+'共通費'!E21 -> 18182 | F21: ='A型'!F21+'B型'!F21+'共通費'!F21 -> 0 | G21: ='A型'!G21+'B型'!G21+'共通費'!G21 -> 0 | H21: ='A型'!H21+'B型'!H21+'共通費'!H21 -> 0 | I21: 0 | J21: ='A型'!J21+'B型'!J21+'共通費'!J21 -> 0 | K21: ='A型'!K21+'B型'!K22+'共通費'!K21 -> 0 | L21: ='A型'!L21+'B型'!L21+'共通費'!L21 -> 0 | M21: ='A型'!M21+'B型'!M21+'共通費'!M21 -> 0 | N21: ='A型'!N21+'B型'!N21+'共通費'!N21 -> 7273 | O21: =SUM(C21:N21) -> 25455
A22: 交際費 | C22: ='A型'!C22+'B型'!C22+'共通費'!C22 -> 0 | D22: ='A型'!D22+'B型'!D22+'共通費'!D22 -> 0 | E22: ='A型'!E22+'B型'!E22+'共通費'!E22 -> 0 | F22: ='A型'!F22+'B型'!F22+'共通費'!F22 -> 0 | G22: ='A型'!G22+'B型'!G22+'共通費'!G22 -> 0 | H22: ='A型'!H22+'B型'!H22+'共通費'!H22 -> 0 | I22: ='A型'!I22+'B型'!I22+'共通費'!I22 -> 0 | J22: ='A型'!J22+'B型'!J22+'共通費'!J22 -> 0 | ... N22: ='A型'!N22+'B型'!N22+'共通費'!N22 -> 0 | O22: =SUM(C22:N22) -> 0 | P22: =O22/$O$10 -> 0
A23: 会議費 | C23: ='A型'!C23+'B型'!C23+'共通費'!C23 -> 0 | D23: ='A型'!D23+'B型'!D23+'共通費'!D23 -> 0 | E23: ='A型'!E23+'B型'!E23+'共通費'!E23 -> 0 | F23: ='A型'!F23+'B型'!F23+'共通費'!F23 -> 0 | G23: ='A型'!G23+'B型'!G23+'共通費'!G23 -> 0 | H23: ='A型'!H23+'B型'!H23+'共通費'!H23 -> 0 | I23: ='A型'!I23+'B型'!I23+'共通費'!I23 -> 0 | J23: ='A型'!J23+'B型'!J23+'共通費'!J23 -> 0 | ... N23: ='A型'!N23+'B型'!N23+'共通費'!N23 -> 0 | O23: =SUM(C23:N23) -> 0
A24: 戦略費 | C24: ='A型'!C24+'B型'!C24+'共通費'!C24 -> 0 | D24: ='A型'!D24+'B型'!D24+'共通費'!D24 -> 0 | E24: ='A型'!E24+'B型'!E24+'共通費'!E24 -> 0 | F24: ='A型'!F24+'B型'!F24+'共通費'!F24 -> 0 | G24: ='A型'!G24+'B型'!G24+'共通費'!G24 -> 0 | H24: ='A型'!H24+'B型'!H24+'共通費'!H24 -> 0 | I24: ='A型'!I24+'B型'!I24+'共通費'!I24 -> 0 | J24: ='A型'!J24+'B型'!J24+'共通費'!J24 -> 0 | ... N24: ='A型'!N24+'B型'!N24+'共通費'!N24 -> 0 | O24: =SUM(C24:N24) -> 0 | P24: =O24/$O$10 -> 0
A25: 減価償却費 | C25: ='A型'!C25+'B型'!C25+'共通費'!C25 -> 0 | D25: ='A型'!D25+'B型'!D25+'共通費'!D25 -> 0 | E25: ='A型'!E25+'B型'!E25+'共通費'!E25 -> 0 | F25: ='A型'!F25+'B型'!F25+'共通費'!F25 -> 0 | G25: ='A型'!G25+'B型'!G25+'共通費'!G25 -> 0 | H25: ='A型'!H25+'B型'!H25+'共通費'!H25 -> 0 | I25: ='A型'!I25+'B型'!I25+'共通費'!I25 -> 0 | J25: ='A型'!J25+'B型'!J25+'共通費'!J25 -> 0 | ... N25: ='A型'!N25+'B型'!N25+'共通費'!N25 -> 0 | O25: =SUM(C25:N25) -> 0
A26: 賃借料 | C26: ='A型'!C26+'B型'!C26+'共通費'!C26 -> 0 | D26: ='A型'!D26+'B型'!D26+'共通費'!D26 -> 0 | E26: ='A型'!E26+'B型'!E26+'共通費'!E26 -> 0 | F26: ='A型'!F26+'B型'!F26+'共通費'!F26 -> 0 | G26: ='A型'!G26+'B型'!G26+'共通費'!G26 -> 0 | H26: ='A型'!H26+'B型'!H26+'共通費'!H26 -> 0 | I26: ='A型'!I26+'B型'!I26+'共通費'!I26 -> 0 | J26: ='A型'!J26+'B型'!J26+'共通費'!J26 -> 0 | ... N26: ='A型'!N26+'B型'!N26+'共通費'!N26 -> 0 | O26: =SUM(C26:N26) -> 0
A27: 地代家賃 | C27: ='A型'!C27+'B型'!C27+'共通費'!C27 -> 367000 | D27: ='A型'!D27+'B型'!D27+'共通費'!D27 -> 367000 | E27: ='A型'!E27+'B型'!E27+'共通費'!E27 -> 367000 | F27: ='A型'!F27+'B型'!F27+'共通費'!F27 -> 367000 | G27: ='A型'!G27+'B型'!G27+'共通費'!G27 -> 367000 | H27: ='A型'!H27+'B型'!H27+'共通費'!H27 -> 367000 | I27: ='A型'!I27+'B型'!I27+'共通費'!I27 -> 367000 | J27: ='A型'!J27+'B型'!J27+'共通費'!J27 -> 367000 | ... N27: ='A型'!N27+'B型'!N27+'共通費'!N27 -> 350000 | O27: =SUM(C27:N27) -> 4340600
A28: リース料 | C28: ='A型'!C28+'B型'!C28+'共通費'!C28 -> 0 | D28: ='A型'!D28+'B型'!D28+'共通費'!D28 -> 0 | E28: ='A型'!E28+'B型'!E28+'共通費'!E28 -> 0 | F28: ='A型'!F28+'B型'!F28+'共通費'!F28 -> 0 | G28: ='A型'!G28+'B型'!G28+'共通費'!G28 -> 0 | H28: ='A型'!H28+'B型'!H28+'共通費'!H28 -> 0 | I28: ='A型'!I28+'B型'!I28+'共通費'!I28 -> 0 | J28: ='A型'!J28+'B型'!J28+'共通費'!J28 -> 0 | ... N28: ='A型'!N28+'B型'!N28+'共通費'!N28 -> 0 | O28: =SUM(C28:N28) -> 0
A29: 修繕費 | C29: ='A型'!C29+'B型'!C29+'共通費'!C29 -> 0 | D29: ='A型'!D29+'B型'!D29+'共通費'!D29 -> 0 | E29: ='A型'!E29+'B型'!E29+'共通費'!E29 -> 0 | F29: ='A型'!F29+'B型'!F29+'共通費'!F29 -> 0 | G29: ='A型'!G29+'B型'!G29+'共通費'!G29 -> 0 | H29: ='A型'!H29+'B型'!H29+'共通費'!H29 -> 0 | I29: ='A型'!I29+'B型'!I29+'共通費'!I29 -> 0 | J29: ='A型'!J29+'B型'!J29+'共通費'!J29 -> 0 | ... N29: ='A型'!N29+'B型'!N29+'共通費'!N29 -> 0 | O29: =SUM(C29:N29) -> 0
A30: 保険料 | C30: ='A型'!C30+'B型'!C30+'共通費'!C30 -> 9360 | D30: ='A型'!D30+'B型'!D30+'共通費'!D30 -> 8840 | E30: ='A型'!E30+'B型'!E30+'共通費'!E30 -> 8840 | F30: ='A型'!F30+'B型'!F30+'共通費'!F30 -> 8840 | G30: ='A型'!G30+'B型'!G30+'共通費'!G30 -> 8840 | H30: ='A型'!H30+'B型'!H30+'共通費'!H30 -> 8840 | I30: ='A型'!I30+'B型'!I30+'共通費'!I30 -> 8840 | J30: ='A型'!J30+'B型'!J30+'共通費'!J30 -> 8840 | ... N30: ='A型'!N30+'B型'!N30+'共通費'!N30 -> 8840 | O30: =SUM(C30:N30) -> 106599
A31: 水道光熱費 | B31: 0 | C31: ='A型'!C31+'B型'!C31+'共通費'!C31 -> 0 | D31: ='A型'!D31+'B型'!D31+'共通費'!D31 -> 0 | E31: ='A型'!E31+'B型'!E31+'共通費'!E31 -> 0 | F31: ='A型'!F31+'B型'!F31+'共通費'!F31 -> 0 | G31: ='A型'!G31+'B型'!G31+'共通費'!G31 -> 0 | H31: ='A型'!H31+'B型'!H31+'共通費'!H31 -> 0 | I31: ='A型'!I31+'B型'!I31+'共通費'!I31 -> 0 | J31: ='A型'!J31+'B型'!J31+'共通費'!J31 -> 0 | ... N31: ='A型'!N31+'B型'!N31+'共通費'!N31 -> 0 | O31: =SUM(C31:N31) -> 0
A32: 消耗品費 | B32: 0 | C32: ='A型'!C32+'B型'!C32+'共通費'!C32 -> 6168 | D32: ='A型'!D32+'B型'!D32+'共通費'!D32 -> 6484 | E32: ='A型'!E32+'B型'!E32+'共通費'!E32 -> 28378 | F32: ='A型'!F32+'B型'!F32+'共通費'!F32 -> 26228 | G32: ='A型'!G32+'B型'!G32+'共通費'!G32 -> 7400 | H32: ='A型'!H32+'B型'!H32+'共通費'!H32 -> 2600 | I32: ='A型'!I32+'B型'!I32+'共通費'!I32 -> 16226 | J32: ='A型'!J32+'B型'!J32+'共通費'!J32 -> 10723 | ... N32: ='A型'!N32+'B型'!N32+'共通費'!N32 -> 9300 | O32: =SUM(C32:N32) -> 138413 | P32: =O32/$O$10 -> 0.0027692591
A33: 租税公課 | C33: ='A型'!C33+'B型'!C33+'共通費'!C33 -> 0 | D33: ='A型'!D33+'B型'!D33+'共通費'!D33 -> 14300 | E33: ='A型'!E33+'B型'!E33+'共通費'!E33 -> 600 | F33: ='A型'!F33+'B型'!F33+'共通費'!F33 -> 1100 | G33: ='A型'!G33+'B型'!G33+'共通費'!G33 -> 0 | H33: ='A型'!H33+'B型'!H33+'共通費'!H33 -> 0 | I33: ='A型'!I33+'B型'!I33+'共通費'!I33 -> 0 | J33: ='A型'!J33+'B型'!J33+'共通費'!J33 -> 0 | ... N33: ='A型'!N33+'B型'!N33+'共通費'!N33 -> 180 | O33: =SUM(C33:N33) -> 16180
A34: 広告宣伝費 | C34: ='A型'!C34+'B型'!C34+'共通費'!C34 -> 0 | D34: ='A型'!D34+'B型'!D34+'共通費'!D34 -> 5100 | E34: ='A型'!E34+'B型'!E34+'共通費'!E34 -> 0 | F34: ='A型'!F34+'B型'!F34+'共通費'!F34 -> 0 | G34: ='A型'!G34+'B型'!G34+'共通費'!G34 -> 0 | H34: ='A型'!H34+'B型'!H34+'共通費'!H34 -> 0 | I34: ='A型'!I34+'B型'!I34+'共通費'!I34 -> 0 | J34: ='A型'!J34+'B型'!J34+'共通費'!J34 -> 49800 | ... N34: ='A型'!N34+'B型'!N34+'共通費'!N34 -> 0 | O34: =SUM(C34:N34) -> 54900
A35: 支払手数料 | B35: 0 | C35: ='A型'!C35+'B型'!C35+'共通費'!C35 -> 38078 | D35: ='A型'!D35+'B型'!D35+'共通費'!D35 -> 75349 | E35: ='A型'!E35+'B型'!E35+'共通費'!E35 -> 74842 | F35: ='A型'!F35+'B型'!F35+'共通費'!F35 -> 76493 | G35: ='A型'!G35+'B型'!G35+'共通費'!G35 -> 49538 | H35: ='A型'!H35+'B型'!H35+'共通費'!H35 -> 57097 | I35: ='A型'!I35+'B型'!I35+'共通費'!I35 -> 48259 | J35: ='A型'!J35+'B型'!J35+'共通費'!J35 -> 49243 | ... N35: ='A型'!N35+'B型'!N35+'共通費'!N35 -> 125621 | O35: =SUM(C35:N35) -> 629296
A36: 教育費 | C36: ='A型'!C36+'B型'!C36+'共通費'!C36 -> 0 | D36: ='A型'!D36+'B型'!D36+'共通費'!D36 -> 0 | E36: ='A型'!E36+'B型'!E36+'共通費'!E36 -> 0 | F36: ='A型'!F36+'B型'!F36+'共通費'!F36 -> 0 | G36: ='A型'!G36+'B型'!G36+'共通費'!G36 -> 0 | H36: ='A型'!H36+'B型'!H36+'共通費'!H36 -> 0 | I36: ='A型'!I36+'B型'!I36+'共通費'!I36 -> 0 | J36: ='A型'!J36+'B型'!J36+'共通費'!J36 -> 0 | ... N36: ='A型'!N36+'B型'!N36+'共通費'!N36 -> 0 | O36: =SUM(C36:N36) -> 0
A37: 新聞図書費 | C37: ='A型'!C37+'B型'!C37+'共通費'!C37 -> 4000 | D37: ='A型'!D37+'B型'!D37+'共通費'!D37 -> 0 | E37: ='A型'!E37+'B型'!E37+'共通費'!E37 -> 0 | F37: ='A型'!F37+'B型'!F37+'共通費'!F37 -> 0 | G37: ='A型'!G37+'B型'!G37+'共通費'!G37 -> 1836 | H37: ='A型'!H37+'B型'!H37+'共通費'!H37 -> 0 | I37: ='A型'!I37+'B型'!I37+'共通費'!I37 -> 0 | J37: ='A型'!J37+'B型'!J37+'共通費'!J37 -> 0 | ... N37: ='A型'!N37+'B型'!N37+'共通費'!N37 -> 0 | O37: =SUM(C37:N37) -> 5836
A38: 管理諸費 | B38: 0.2 | C38: ='A型'!C38+'B型'!C38+'共通費'!C38 -> 418897 | D38: ='A型'!D38+'B型'!D38+'共通費'!D38 -> 533082 | E38: ='A型'!E38+'B型'!E38+'共通費'!E38 -> 687721 | F38: ='A型'!F38+'B型'!F38+'共通費'!F38 -> 615397 | G38: ='A型'!G38+'B型'!G38+'共通費'!G38 -> 541642 | H38: ='A型'!H38+'B型'!H38+'共通費'!H38 -> 553455 | I38: ='A型'!I38+'B型'!I38+'共通費'!I38 -> 553479 | J38: ='A型'!J38+'B型'!J38+'共通費'!J38 -> 414542 | ... N38: ='A型'!N38+'B型'!N38+'共通費'!N38 -> 625266 | O38: =SUM(C38:N38) -> 6669703
C39: ='A型'!C39+'B型'!C39+'共通費'!C39 -> 0 | D39: ='A型'!D39+'B型'!D39+'共通費'!D39 -> 0 | E39: ='A型'!E39+'B型'!E39+'共通費'!E39 -> 300000 | F39: ='A型'!F39+'B型'!F39+'共通費'!F39 -> 0 | G39: ='A型'!G39+'B型'!G39+'共通費'!G39 -> 0 | H39: ='A型'!H39+'B型'!H39+'共通費'!H39 -> 0 | I39: ='A型'!I39+'B型'!I39+'共通費'!I39 -> 0 | J39: ='A型'!J39+'B型'!J39+'共通費'!J39 -> 0 | ... N39: ='A型'!N39+'B型'!N39+'共通費'!N39 -> 0 | O39: =SUM(C39:N39) -> 300000 | P39: =O39/$O$10 -> 0.0060021655
C40: ='A型'!C40+'B型'!C40+'共通費'!C40 -> 0 | D40: ='A型'!D40+'B型'!D40+'共通費'!D40 -> 0 | E40: ='A型'!E40+'B型'!E40+'共通費'!E40 -> 0 | F40: ='A型'!F40+'B型'!F40+'共通費'!F40 -> 0 | G40: ='A型'!G40+'B型'!G40+'共通費'!G40 -> 0 | H40: ='A型'!H40+'B型'!H40+'共通費'!H40 -> 0 | I40: ='A型'!I40+'B型'!I40+'共通費'!I40 -> 0 | J40: ='A型'!J40+'B型'!J40+'共通費'!J40 -> 0 | ... N40: ='A型'!N40+'B型'!N40+'共通費'!N40 -> 0 | O40: =SUM(C40:N40) -> 0
C41: ='A型'!C41+'B型'!C41+'共通費'!C41 -> 0 | D41: ='A型'!D41+'B型'!D41+'共通費'!D41 -> 0 | E41: ='A型'!E41+'B型'!E41+'共通費'!E41 -> 0 | F41: ='A型'!F41+'B型'!F41+'共通費'!F41 -> 0 | G41: ='A型'!G41+'B型'!G41+'共通費'!G41 -> 0 | H41: ='A型'!H41+'B型'!H41+'共通費'!H41 -> 0 | I41: ='A型'!I41+'B型'!I41+'共通費'!I41 -> 0 | J41: ='A型'!J41+'B型'!J41+'共通費'!J41 -> 0 | ... N41: ='A型'!N41+'B型'!N41+'共通費'!N41 -> 0 | O41: =SUM(C41:N41) -> 0
A42: 販売管理費合計 | C42: =SUM(C12:C41) -> 4493510 | D42: =SUM(D12:D41) -> 4413902 | E42: =SUM(E12:E41) -> 5022515 | F42: =SUM(F12:F41) -> 5652960 | G42: =SUM(G12:G41) -> 4492873 | H42: =SUM(H12:H41) -> 4424822 | I42: =SUM(I12:I41) -> 4535270 | J42: =SUM(J12:J41) -> 3889922 | ... N42: =SUM(N12:N41) -> 4912207 | O42: =SUM(C42:N42) -> 53932495 | P42: =O42/$O$10 -> 1.0790392
A43: 営業利益 | C43: =C10-C42 -> -950897 | D43: =D10-D42 -> 1411070 | E43: =E10-E42 -> -1487208 | F43: =F10-F42 -> -2048704 | G43: =G10-G42 -> -628704 | H43: =H10-H42 -> -886271 | I43: =I10-I42 -> -898979 | J43: =J10-J42 -> 646151 | ... O43: =O10-O42 -> -3950534 | P43: =O43/$O$10 -> -0.079039196
A44: 支払利息 | C44: ='A型'!C44+'B型'!C44+'共通費'!C44 -> 5424 | D44: ='A型'!D44+'B型'!D44+'共通費'!D44 -> 0 | E44: ='A型'!E44+'B型'!E44+'共通費'!E44 -> 9697 | F44: ='A型'!F44+'B型'!F44+'共通費'!F44 -> 5260 | G44: ='A型'!G44+'B型'!G44+'共通費'!G44 -> 0 | H44: ='A型'!H44+'B型'!H44+'共通費'!H44 -> 9862 | I44: ='A型'!I44+'B型'!I44+'共通費'!I44 -> 5095 | J44: ='A型'!J44+'B型'!J44+'共通費'!J44 -> 0 | ... N44: ='A型'!N44+'B型'!N44+'共通費'!N44 -> 9126 | O44: =SUM(C44:N44) -> 59190
A45: 雑損失 | C45: ='A型'!C45+'B型'!C45+'共通費'!C45 -> 0 | D45: ='A型'!D45+'B型'!D45+'共通費'!D45 -> 0 | E45: ='A型'!E45+'B型'!E45+'共通費'!E45 -> 0 | F45: ='A型'!F45+'B型'!F45+'共通費'!F45 -> 0 | G45: ='A型'!G45+'B型'!G45+'共通費'!G45 -> 0 | H45: ='A型'!H45+'B型'!H45+'共通費'!H45 -> 0 | I45: ='A型'!I45+'B型'!I45+'共通費'!I45 -> 0 | J45: ='A型'!J45+'B型'!J45+'共通費'!J45 -> 0 | ... N45: ='A型'!N45+'B型'!N45+'共通費'!N45 -> 0 | O45: =SUM(C45:N45) -> 0
A46: 受取利息 雑収入 | C46: ='A型'!C46+'B型'!C46+'共通費'!C46 -> 19444 | D46: ='A型'!D46+'B型'!D46+'共通費'!D46 -> 179264 | E46: ='A型'!E46+'B型'!E46+'共通費'!E46 -> 155 | F46: ='A型'!F46+'B型'!F46+'共通費'!F46 -> 101047 | G46: ='A型'!G46+'B型'!G46+'共通費'!G46 -> 2783 | H46: ='A型'!H46+'B型'!H46+'共通費'!H46 -> 0 | I46: ='A型'!I46+'B型'!I46+'共通費'!I46 -> 0 | J46: ='A型'!J46+'B型'!J46+'共通費'!J46 -> 0 | ... N46: ='A型'!N46+'B型'!N46+'共通費'!N46 -> 0 | O46: =SUM(C46:N46) -> 1704726
A47: 経常利益 | C47: =C43-C44-C45+C46 -> -936877 | D47: =D43-D44-D45+D46 -> 1590334 | E47: =E43-E44-E45+E46 -> -1496750 | F47: =F43-F44-F45+F46 -> -1952917 | G47: =G43-G44-G45+G46 -> -625921 | H47: =H43-H44-H45+H46 -> -896133 | I47: =I43-I44-I45+I46 -> -904074 | J47: =J43-J44-J45+J46 -> 646151 | ... O47: =O43-O44-O45+O46 -> -2304998 | P47: =O47/$O$10 -> -0.046116598
A48: 特別利益 | O48: =SUM(C48:N48) -> 0
A49: 特別損失 | O49: =SUM(C49:N49) -> 0
A50: 税引前当期純利益 | C50: =C47+C48-C49 -> -936877 | D50: =D47+D48-D49 -> 1590334 | E50: =E47+E48-E49 -> -1496750 | F50: =F47+F48-F49 -> -1952917 | G50: =G47+G48-G49 -> -625921 | H50: =H47+H48-H49 -> -896133 | I50: =I47+I48-I49 -> -904074 | J50: =J47+J48-J49 -> 646151 | ... O50: =O47+O48-O49 -> -2304998 | P50: =O50/$O$10 -> -0.046116598
A51: 法人税 | B51: 0.33 | O51: =IF(O50>=0,O50*30%+70000,70000) -> 70000 | P51: =O51/$O$10 -> 0.0014005053
A52: 税引後当期純利益 | O52: =O50-O51 -> -2374998 | P52: =O52/$O$10 -> -0.047517103
B57: 月別 Ａ型 | C57: =C63*C64*C65*C66 -> 1512124.4 | D57: =D63*D64*D65*D66 -> 1443391.5 | E57: =E63*E64*E65*E66 -> 1638134.8 | F57: =F63*F64*F65*F66 -> 1580857.3 | G57: =G63*G64*G65*G66 -> 1580857.3 | H57: =H63*H64*H65*H66 -> 1580857.3 | I57: =I63*I64*I65*I66 -> 1443391.5 | J57: =J63*J64*J65*J66 -> 1374658.6 | ... N57: =N63*N64*N65*N66 -> 1512124.4
B58: 特開金対象人数 | C58: 11 | D58: 2 | E58: 1 | J58: 11 | K58: 3
B60: 月別 Ｂ型 | C60: =C70*C71*C72*C73 -> 350153.1 | D60: =D70*D71*D72*D73 -> 334237.05 | E60: =E70*E71*E72*E73 -> 700306.2 | F60: =F70*F71*F72*F73 -> 732138.3 | G60: =G70*G71*G72*G73 -> 732138.3 | H60: =H70*H71*H72*H73 -> 732138.3 | I60: =I70*I71*I72*I73 -> 668474.1 | J60: =J70*J71*J72*J73 -> 636642 | ... N60: =N70*N71*N72*N73 -> 700306.2
B62: A型
B63: 開所日数 | C63: 22 | D63: 21 | E63: 22 | F63: 23 | G63: 23 | H63: 23 | I63: 21 | J63: 20 | K63: 21 | L63: 22 | M63: 22 | N63: 22
B64: 出勤予測率 | C64: 0.8 | D64: 0.8 | E64: 0.8 | F64: 0.8 | G64: 0.8 | H64: 0.8 | I64: 0.8 | J64: 0.8 | K64: 0.8 | L64: 0.8 | M64: 0.8 | N64: 0.8
B65: 在籍Ａ型利用者数 | C65: ='A型'!C63 -> 12 | D65: ='A型'!D63 -> 12 | E65: ='A型'!E63 -> 13 | F65: ='A型'!F63 -> 12 | G65: ='A型'!G63 -> 12 | H65: ='A型'!H63 -> 12 | I65: ='A型'!I63 -> 12 | J65: ='A型'!J63 -> 12 | ... N65: ='A型'!N63 -> 12
B66: 一日当たり金額 | C66: ='単位計算'!$C$23 -> 7159.68 | D66: ='単位計算'!$C$23 -> 7159.68 | E66: ='単位計算'!$C$23 -> 7159.68 | F66: ='単位計算'!$C$23 -> 7159.68 | G66: ='単位計算'!$C$23 -> 7159.68 | H66: ='単位計算'!$C$23 -> 7159.68 | I66: ='単位計算'!$C$23 -> 7159.68 | J66: ='単位計算'!$C$23 -> 7159.68 | ... N66: ='単位計算'!$C$23 -> 7159.68
B67: １か月あたり単位 | C67: ='単位計算'!$C$21*'予測PL (2025.04-)'!C63*'予測PL (2025.04-)'!C64*'予測PL (2025.04-)'!C65 -> 148684.8 | D67: ='単位計算'!$C$21*'予測PL (2025.04-)'!D63*'予測PL (2025.04-)'!D64*'予測PL (2025.04-)'!D65 -> 141926.4 | E67: ='単位計算'!$C$21*'予測PL (2025.04-)'!E63*'予測PL (2025.04-)'!E64*'予測PL (2025.04-)'!E65 -> 161075.2 | F67: ='単位計算'!$C$21*'予測PL (2025.04-)'!F63*'予測PL (2025.04-)'!F64*'予測PL (2025.04-)'!F65 -> 155443.2 | G67: ='単位計算'!$C$21*'予測PL (2025.04-)'!G63*'予測PL (2025.04-)'!G64*'予測PL (2025.04-)'!G65 -> 155443.2 | H67: ='単位計算'!$C$21*'予測PL (2025.04-)'!H63*'予測PL (2025.04-)'!H64*'予測PL (2025.04-)'!H65 -> 155443.2 | I67: ='単位計算'!$C$21*'予測PL (2025.04-)'!I63*'予測PL (2025.04-)'!I64*'予測PL (2025.04-)'!I65 -> 141926.4 | J67: ='単位計算'!$C$21*'予測PL (2025.04-)'!J63*'予測PL (2025.04-)'!J64*'予測PL (2025.04-)'!J65 -> 135168 | ... N67: ='単位計算'!$C$21*'予測PL (2025.04-)'!N63*'予測PL (2025.04-)'!N64*'予測PL (2025.04-)'!N65 -> 148684.8
B69: Ｂ型
B70: 開所日数 | C70: 22 | D70: 21 | E70: 22 | F70: 23 | G70: 23 | H70: 23 | I70: 21 | J70: 20 | K70: 21 | L70: 22 | M70: 22 | N70: 22
B71: 出勤予測率 | C71: 0.5 | D71: 0.5 | E71: 0.5 | F71: 0.5 | G71: 0.5 | H71: 0.5 | I71: 0.5 | J71: 0.5 | K71: 0.5 | L71: 0.5 | M71: 0.5 | N71: 0.5
B72: 在籍Ｂ型利用者数 | C72: 5 | D72: 5 | E72: 10 | F72: 10 | G72: 10 | H72: 10 | I72: 10 | J72: 10 | K72: 10 | L72: 10 | M72: 10 | N72: 10
B73: 一日当たり単位 | C73: ='単位計算'!$G$23 -> 6366.42 | D73: ='単位計算'!$G$23 -> 6366.42 | E73: ='単位計算'!$G$23 -> 6366.42 | F73: ='単位計算'!$G$23 -> 6366.42 | G73: ='単位計算'!$G$23 -> 6366.42 | H73: ='単位計算'!$G$23 -> 6366.42 | I73: ='単位計算'!$G$23 -> 6366.42 | J73: ='単位計算'!$G$23 -> 6366.42 | ... N73: ='単位計算'!$G$23 -> 6366.42
B74: １か月あたり単位 | C74: =C70*C71*C72*'単位計算'!$G$21 -> 34430 | D74: =D70*D71*D72*'単位計算'!$G$21 -> 32865 | E74: =E70*E71*E72*'単位計算'!$G$21 -> 68860 | F74: =F70*F71*F72*'単位計算'!$G$21 -> 71990 | G74: =G70*G71*G72*'単位計算'!$G$21 -> 71990 | H74: =H70*H71*H72*'単位計算'!$G$21 -> 71990 | I74: =I70*I71*I72*'単位計算'!$G$21 -> 65730 | J74: =J70*J71*J72*'単位計算'!$G$21 -> 62600 | ... N74: =N70*N71*N72*'単位計算'!$G$21 -> 68860
B76: A型 処遇改善手当予測 | C76: =C67*'単位計算'!$C$25*'単位計算'!$C$22 -> 145163.94 | D76: =D67*'単位計算'!$C$25*'単位計算'!$C$22 -> 138565.58 | E76: =E67*'単位計算'!$C$25*'単位計算'!$C$22 -> 157260.94 | F76: =F67*'単位計算'!$C$25*'単位計算'!$C$22 -> 151762.3 | G76: =G67*'単位計算'!$C$25*'単位計算'!$C$22 -> 151762.3 | H76: =H67*'単位計算'!$C$25*'単位計算'!$C$22 -> 151762.3 | I76: =I67*'単位計算'!$C$25*'単位計算'!$C$22 -> 138565.58 | J76: =J67*'単位計算'!$C$25*'単位計算'!$C$22 -> 131967.22 | ... N76: =N67*'単位計算'!$C$25*'単位計算'!$C$22 -> 145163.94
B77: B型 処遇改善手当予測 | C77: =C74*'単位計算'!$G$25*'単位計算'!$G$22 -> 32564.238 | D77: =D74*'単位計算'!$G$25*'単位計算'!$G$22 -> 31084.046 | E77: =E74*'単位計算'!$G$25*'単位計算'!$G$22 -> 65128.477 | F77: =F74*'単位計算'!$G$25*'単位計算'!$G$22 -> 68088.862 | G77: =G74*'単位計算'!$G$25*'単位計算'!$G$22 -> 68088.862 | H77: =H74*'単位計算'!$G$25*'単位計算'!$G$22 -> 68088.862 | I77: =I74*'単位計算'!$G$25*'単位計算'!$G$22 -> 62168.091 | J77: =J74*'単位計算'!$G$25*'単位計算'!$G$22 -> 59207.706 | ... N77: =N74*'単位計算'!$G$25*'単位計算'!$G$22 -> 65128.477
B78: 受取済 処遇改善手当 | C78: 190625 | D78: 185228 | E78: 182512 | F78: 168408 | G78: 190526 | H78: 163119 | I78: 180459 | O78: 決定したら手入力
B79: 支給済 処遇改善手当 | C79: 54000 | D79: 54000 | E79: 54000 | F79: 54000 | G79: 158000 | H79: 164000 | I79: 164000 | J79: 164000 | K79: 164000 | L79: 164000 | M79: 164000 | N79: 164000
B80: 処遇改善手当残高 | C80: =C78-C79 -> 136625 | D80: =D78-D79 -> 131228 | E80: =E78-E79 -> 128512 | F80: =F78-F79 -> 114408 | G80: =G78-G79 -> 32526 | H80: =H78-H79 -> -881 | I80: =I78-I79 -> 16459 | J80: =J78-J79 -> -164000 | ... N80: =N78-N79 -> -164000 | O80: =SUM(C80:N80) -> -261123 | P80: 賞与予定
C83: 4月 | D83: 5月 | E83: 6月 | F83: 7月 | G83: 8月 | H83: 9月 | I83: 10月 | J83: 11月 | K83: 12月 | L83: 1月 | M83: 2月 | N83: 3月
B84: 昨年度の雇用人数

Sheet A型
B1: 変動費率 | C1: 4月実績 | D1: 5月実績 | E1: 6月実績 | F1: 7月実績 | G1: 8月実績 | H1: 9月実績 | I1: 10月実績 | J1: 11月実績 | K1: 12月実績 | L1: 1月実績 | M1: 2月実績 | N1: 3月 | O1: 累計
O2: =SUM(C2:N2) -> 0
A3: 売上 | C3: =SUM(C4:C8) -> 3101741 | D3: =SUM(D4:D8) -> 5482159 | E3: =SUM(E4:E8) -> 3055210 | F3: =SUM(F4:F8) -> 2846093 | G3: =SUM(G4:G8) -> 3300454 | H3: =SUM(H4:H8) -> 2994841 | I3: =SUM(I4:I8) -> 2996404 | J3: =SUM(J4:J8) -> 3910896 | ... N3: =SUM(N4:N8) -> 3118225 | O3: =SUM(C3:N3) -> 41813877 | P3: =O3/$O$3 -> 1
A4: 国保連Ａ型 | C4: 2216026 | D4: 2153396 | E4: 2068535 | F4: 1924273 | G4: 1821950 | H4: 1892545 | I4: 1754854 | J4: 1586450 | K4: 2029779 | L4: 1574937 | M4: 1568163 | N4: 1952454 | O4: =SUM(C4:N4) -> 22543362
A5: 国保連Ｂ型 | C5: =C58 -> 0 | D5: =D58 -> 0 | E5: =E58 -> 0 | F5: =F58 -> 0 | G5: =G58 -> 0 | H5: =H58 -> 0 | I5: =I58 -> 0 | J5: =J58 -> 0 | ... N5: =N58 -> 0 | O5: =SUM(C5:N5) -> 0
A6: 処遇改善手当 | C6: 0 | D6: 0 | E6: 0 | F6: 0 | G6: 0 | H6: 0 | I6: 0 | J6: 0 | K6: 0 | L6: 0 | M6: 0 | N6: 0 | O6: =SUM(C6:N6) -> 0
A7: 特開金 | C7: =C56*200000 -> 0 | D7: 2333333 | E7: =E56*200000 -> 0 | F7: 0 | G7: 533333 | H7: =H56*200000 -> 0 | I7: 200000 | J7: =J56*200000 -> 1300000 | K7: 900000 | L7: 500000 | M7: 0 | N7: 200000 | O7: =SUM(C7:N7) -> 5966666
A8: 生産活動 | C8: 885715 | D8: 995430 | E8: 986675 | F8: 921820 | G8: =663225+281946 -> 945171 | H8: =883882+218414 -> 1102296 | I8: =805710+235840 -> 1041550 | J8: =803414+221032 -> 1024446 | K8: =879379+235407 -> 1114786 | L8: =2213105+187446 -> 2400551 | M8: =755011+164627 -> 919638 | N8: =813590+152181 -> 965771 | O8: =SUM(C8:N8) -> 13303849
A9: 売上原価 | C9: 18747 | D9: 107823 | E9: 36542 | F9: 30735 | G9: 18222 | H9: 40050 | I9: 71448 | J9: 5560 | K9: 0 | L9: 46256 | M9: 39338 | N9: 46933 | O9: =SUM(C9:N9) -> 461654 | P9: =O9/$O$3 -> 0.011040689
A10: 売上総利益 | C10: =C2+C3-C9 -> 3082994 | D10: =D2+D3-D9 -> 5374336 | E10: =E2+E3-E9 -> 3018668 | F10: =F2+F3-F9 -> 2815358 | G10: =G2+G3-G9 -> 3282232 | H10: =H2+H3-H9 -> 2954791 | I10: =I2+I3-I9 -> 2924956 | J10: =J2+J3-J9 -> 3905336 | ... N10: =N2+N3-N9 -> 3071292 | O10: =SUM(C10:N10) -> 41352223
A11: 処遇改善手当 | C11: =C6 -> 0 | D11: =D6 -> 0 | E11: =E6 -> 0 | F11: =F6 -> 0 | G11: =G6 -> 0 | H11: =H6 -> 0 | I11: =I6 -> 0 | J11: =J6 -> 0 | K11: 0 | L11: 0 | O11: =SUM(C11:N11) -> 0
A12: 役員報酬 | C12: 0 | D12: 0 | E12: 0 | F12: 0 | G12: 0 | H12: 0 | I12: 0 | J12: 0 | K12: 0 | L12: 0 | O12: =SUM(C12:N12) -> 0 | P12: =O12/$O$10 -> 0
A13: 給与手当 | C13: 1456859 | D13: 1504722 | E13: 1513407 | F13: 1620950 | G13: 1514435 | H13: 1612029 | I13: 1526510 | J13: 1258740 | K13: 1187573 | L13: 1209285 | M13: 1189955 | N13: =1143807+823050 -> 1966857 | O13: =SUM(C13:N13) -> 17561322
A14: 雑給 | C14: 1324481 | D14: 1277428 | E14: 1390775 | F14: 1068683 | G14: 995721 | H14: 1009020 | I14: 890526 | J14: 990482 | K14: 1041839 | L14: 1013301 | M14: 953709 | N14: 1114601 | O14: =SUM(C14:N14) -> 13070566 | P14: =O14/$O$10 -> 0.31607892
A15: 法定福利費 | B15: 0.15 | C15: 269755 | D15: 100503 | E15: 92933 | F15: 1107770 | G15: 408917 | H15: 194495 | I15: 426782 | J15: 171887 | K15: 171921 | L15: 325573 | M15: 213152 | N15: 94333 | O15: =SUM(C15:N15) -> 3578021
A16: 福利厚生費 | B16: 昼食代 | C16: 175134 | D16: 116663 | E16: 120334 | F16: 159250 | G16: 92917 | H16: 128749 | I16: 180125 | J16: 116417 | K16: 125204 | L16: 142875 | M16: 270001 | N16: 145356 | O16: =SUM(C16:N16) -> 1773025
A17: 業務委託費 | B17: もりもりさん | C17: 9000 | D17: 9000 | E17: 9000 | F17: 9000 | G17: 9000 | H17: 9000 | I17: 9000 | J17: 9000 | K17: 9000 | L17: 9000 | M17: 9000 | N17: 9300 | O17: =SUM(C17:N17) -> 108300
A18: 労務委託費 | C18: 0 | D18: 0 | E18: 0 | F18: 0 | G18: 0 | H18: 0 | I18: 0 | J18: 0 | K18: 0 | L18: 0 | O18: =SUM(C18:N18) -> 0
A19: 旅費交通費 | C19: 50016 | D19: 49328 | E19: 59449 | F19: 62174 | G19: 55669 | H19: 59588 | I19: 44542 | J19: 39256 | K19: 41482 | L19: 62100 | M19: 56422 | N19: 56087 | O19: =SUM(C19:N19) -> 636113
A20: 通信費 | C20: 1446 | D20: 1639 | E20: 1060 | F20: 8914 | G20: 12089 | H20: 1451 | I20: 5522 | J20: 3020 | K20: 38050 | L20: 14656 | M20: 3459 | N20: 2079 | O20: =SUM(C20:N20) -> 93385 | P20: =O20/$O$10 -> 0.0022582825
A21: 研修採用費 | B21: 年間予算 | C21: 0 | D21: 0 | E21: 16364 | F21: 0 | G21: 0 | H21: 0 | I21: 0 | J21: 0 | K21: 0 | L21: 0 | M21: 0 | N21: 6764 | O21: =SUM(C21:N21) -> 23128
A22: 交際費 | C22: 0 | D22: 0 | E22: 0 | F22: 0 | G22: 0 | H22: 0 | I22: 0 | J22: 0 | K22: 0 | L22: 0 | M22: 0 | N22: 0 | O22: =SUM(C22:N22) -> 0 | P22: =O22/$O$10 -> 0
A23: 会議費 | C23: 0 | D23: 0 | E23: 0 | F23: 0 | G23: 0 | H23: 0 | I23: 0 | J23: 0 | K23: 0 | L23: 0 | M23: 0 | N23: 0 | O23: =SUM(C23:N23) -> 0
A24: 戦略費 | C24: 0 | D24: 0 | E24: 0 | F24: 0 | G24: 0 | H24: 0 | I24: 0 | J24: 0 | K24: 0 | L24: 0 | M24: 0 | N24: 0 | O24: =SUM(C24:N24) -> 0 | P24: =O24/$O$10 -> 0
A25: 減価償却費 | C25: 0 | D25: 0 | E25: 0 | F25: 0 | G25: 0 | H25: 0 | I25: 0 | J25: 0 | K25: 0 | L25: 0 | M25: 0 | N25: 0 | O25: =SUM(C25:N25) -> 0
A26: 賃借料 | C26: 0 | D26: 0 | E26: 0 | F26: 0 | G26: 0 | H26: 0 | I26: 0 | J26: 0 | K26: 0 | L26: 0 | M26: 0 | N26: 0 | O26: =SUM(C26:N26) -> 0
A27: 地代家賃 | C27: 200000 | D27: 200000 | E27: 200000 | F27: 200000 | G27: 200000 | H27: 200000 | I27: 200000 | J27: 200000 | K27: 200000 | L27: 200000 | M27: 200000 | N27: 200000 | O27: =SUM(C27:N27) -> 2400000
A28: リース料 | C28: 0 | D28: 0 | E28: 0 | F28: 0 | G28: 0 | H28: 0 | I28: 0 | J28: 0 | K28: 0 | L28: 0 | M28: 0 | N28: 0 | O28: =SUM(C28:N28) -> 0
A29: 修繕費 | C29: 0 | D29: 0 | E29: 0 | F29: 0 | G29: 0 | H29: 0 | I29: 0 | J29: 0 | K29: 0 | L29: 0 | M29: 0 | N29: 0 | O29: =SUM(C29:N29) -> 0
A30: 保険料 | C30: 8424 | D30: 7956 | E30: 7956 | F30: 7956 | G30: 7956 | H30: 7956 | I30: 7956 | J30: 7956 | K30: 7956 | L30: 7956 | M30: 7956 | N30: 8221 | O30: =SUM(C30:N30) -> 96205
A31: 水道光熱費 | C31: 0 | D31: 0 | E31: 0 | F31: 0 | G31: 0 | H31: 0 | I31: 0 | J31: 0 | K31: 0 | L31: 0 | M31: 0 | O31: =SUM(C31:N31) -> 0
A32: 消耗品費 | B32: 0 | C32: 5552 | D32: 5836 | E32: 25540 | F32: 23605 | G32: 6660 | H32: 2340 | I32: 14603 | J32: 9651 | K32: 2520 | L32: 16394 | M32: 3501 | N32: 8649 | O32: =SUM(C32:N32) -> 124851 | P32: =O32/$O$10 -> 0.0030192089
A33: 租税公課 | C33: 0 | D33: 12870 | E33: 540 | F33: 990 | G33: 0 | H33: 0 | I33: 0 | J33: 0 | K33: 0 | L33: 0 | M33: 0 | N33: 167 | O33: =SUM(C33:N33) -> 14567
A34: 広告宣伝費 | C34: 0 | D34: 4590 | E34: 0 | F34: 0 | G34: 0 | H34: 0 | I34: 0 | J34: 44820 | K34: 0 | L34: 0 | M34: 0 | N34: 0 | O34: =SUM(C34:N34) -> 49410
A35: 支払手数料 | C35: 34270 | D35: 67814 | E35: 67357 | F35: 68844 | G35: 44584 | H35: 51387 | I35: 43434 | J35: 44318 | K35: 11616 | L35: 8288 | M35: 11394 | N35: 116828 | O35: =SUM(C35:N35) -> 570134
A36: 教育費 | C36: 0 | D36: 0 | E36: 0 | F36: 0 | G36: 0 | H36: 0 | I36: 0 | J36: 0 | K36: 0 | L36: 0 | M36: 0 | N36: 0 | O36: =SUM(C36:N36) -> 0
A37: 新聞図書費 | C37: 3600 | D37: 0 | E37: 0 | F37: 0 | G37: 1652 | H37: 0 | I37: 0 | J37: 0 | K37: 0 | L37: 0 | M37: 0 | N37: 0 | O37: =SUM(C37:N37) -> 5252
A38: 管理諸費 | C38: 377007 | D38: 479774 | E38: 618949 | F38: 553857 | G38: 487477 | H38: 498110 | I38: 498131 | J38: 373087 | K38: 494888 | L38: 625360 | M38: 433353 | N38: 581497 | O38: =SUM(C38:N38) -> 6021490
A39: 賞与 | C39: 0 | D39: 0 | E39: 270000 | F39: 0 | G39: 0 | H39: 0 | I39: 0 | J39: 0 | K39: 0 | L39: 0 | M39: 0 | N39: 0 | O39: =SUM(C39:N39) -> 270000 | P39: =O39/$O$10 -> 0.0065292741
C40: 0 | D40: 0 | E40: 0 | F40: 0 | G40: 0 | H40: 0 | I40: 0 | J40: 0 | K40: 0 | L40: 0 | M40: 0 | N40: 0 | O40: =SUM(C40:N40) -> 0
C41: 0 | D41: 0 | E41: 0 | F41: 0 | G41: 0 | H41: 0 | I41: 0 | J41: 0 | K41: 0 | L41: 0 | M41: 0 | N41: 0 | O41: =SUM(C41:N41) -> 0
A42: 販売管理費合計 | C42: =SUM(C12:C41) -> 3915544 | D42: =SUM(D12:D41) -> 3838123 | E42: =SUM(E12:E41) -> 4393664 | F42: =SUM(F12:F41) -> 4891993 | G42: =SUM(G12:G41) -> 3837077 | H42: =SUM(H12:H41) -> 3774125 | I42: =SUM(I12:I41) -> 3847131 | J42: =SUM(J12:J41) -> 3268634 | ... N42: =SUM(N12:N41) -> 4310739 | O42: =SUM(C42:N42) -> 46395769 | P42: =O42/$O$10 -> 1.1219655
A43: 営業利益 | C43: =C10-C42 -> -832550 | D43: =D10-D42 -> 1536213 | E43: =E10-E42 -> -1374996 | F43: =F10-F42 -> -2076635 | G43: =G10-G42 -> -554845 | H43: =H10-H42 -> -819334 | I43: =I10-I42 -> -922175 | J43: =J10-J42 -> 636702 | ... O43: =O10-O42 -> -5043546 | P43: =O43/$O$10 -> -0.12196553
A44: 支払利息 | C44: 0 | D44: 0 | E44: 0 | F44: 0 | G44: 0 | H44: 0 | I44: 0 | J44: 0 | K44: 0 | O44: =SUM(C44:N44) -> 0
A45: 雑損失 | C45: 0 | D45: 0 | E45: 0 | F45: 0 | G45: 0 | H45: 0 | I45: 0 | J45: 0 | K45: 0 | O45: =SUM(C45:N45) -> 0
A46: 受取利息 雑収入 | B46: 昼食代 | C46: 0 | D46: 0 | E46: 0 | F46: 0 | G46: 0 | H46: 0 | I46: 0 | J46: 0 | K46: 0 | O46: =SUM(C46:N46) -> 0
A47: 経常利益 | C47: =C43-C44-C45+C46 -> -832550 | D47: =D43-D44-D45+D46 -> 1536213 | E47: =E43-E44-E45+E46 -> -1374996 | F47: =F43-F44-F45+F46 -> -2076635 | G47: =G43-G44-G45+G46 -> -554845 | H47: =H43-H44-H45+H46 -> -819334 | I47: =I43-I44-I45+I46 -> -922175 | J47: =J43-J44-J45+J46 -> 636702 | ... O47: =O43-O44-O45+O46 -> -5043546 | P47: =O47/$O$10 -> -0.12196553
A48: 特別利益 | C48: 0 | D48: 0 | E48: 0 | F48: 0 | G48: 0 | H48: 0 | I48: 0 | J48: 0 | K48: 0 | O48: =SUM(C48:N48) -> 0
A49: 特別損失 | C49: 0 | D49: 0 | E49: 0 | F49: 0 | G49: 0 | H49: 0 | I49: 0 | J49: 0 | K49: 0 | O49: =SUM(C49:N49) -> 0
A50: 税引前当期純利益 | C50: =C47+C48-C49 -> -832550 | D50: =D47+D48-D49 -> 1536213 | E50: =E47+E48-E49 -> -1374996 | F50: =F47+F48-F49 -> -2076635 | G50: =G47+G48-G49 -> -554845 | H50: =H47+H48-H49 -> -819334 | I50: =I47+I48-I49 -> -922175 | J50: =J47+J48-J49 -> 636702 | ... O50: =O47+O48-O49 -> -5043546 | P50: =O50/$O$10 -> -0.12196553
B55: 月別 Ａ型 | C55: =C61*C62*C63*C64 -> 1512124.4 | D55: =D61*D62*D63*D64 -> 1443391.5 | E55: =E61*E62*E63*E64 -> 1945285.1 | F55: =F61*F62*F63*F64 -> 1877268.1 | G55: =G61*G62*G63*G64 -> 1877268.1 | H55: =H61*H62*H63*H64 -> 1877268.1 | I55: =I61*I62*I63*I64 -> 1714027.4 | J55: =J61*J62*J63*J64 -> 1632407 | ... N55: =N61*N62*N63*N64 -> 1795647.7
B56: 特開金対象人数 | D56: 11 | G56: 2.5 | J56: 6.5 | K56: 0 | L56: 1 | M56: 1
B58: 月別 Ｂ型 | C58: =C68*C69*C70*C71 -> 0 | D58: =D68*D69*D70*D71 -> 0 | E58: =E68*E69*E70*E71 -> 0 | F58: =F68*F69*F70*F71 -> 0 | G58: =G68*G69*G70*G71 -> 0 | H58: =H68*H69*H70*H71 -> 0 | I58: =I68*I69*I70*I71 -> 0 | J58: =J68*J69*J70*J71 -> 0 | ... N58: =N68*N69*N70*N71 -> 0
B60: A型
B61: 開所日数 | C61: 22 | D61: 21 | E61: 22 | F61: 23 | G61: 23 | H61: 23 | I61: 21 | J61: 20 | K61: 21 | L61: 22 | M61: 22 | N61: 22
B62: 出勤予測率 | C62: 0.8 | D62: 0.8 | E62: 0.95 | F62: 0.95 | G62: 0.95 | H62: 0.95 | I62: 0.95 | J62: 0.95 | K62: 0.95 | L62: 0.95 | M62: 0.95 | N62: 0.95
B63: 在籍Ａ型利用者数 | C63: 12 | D63: 12 | E63: 13 | F63: 12 | G63: 12 | H63: 12 | I63: 12 | J63: 12 | K63: 12 | L63: 12 | M63: 12 | N63: 12
B64: 一日当たり金額 | C64: ='単位計算'!$C$23 -> 7159.68 | D64: ='単位計算'!$C$23 -> 7159.68 | E64: ='単位計算'!$C$23 -> 7159.68 | F64: ='単位計算'!$C$23 -> 7159.68 | G64: ='単位計算'!$C$23 -> 7159.68 | H64: ='単位計算'!$C$23 -> 7159.68 | I64: ='単位計算'!$C$23 -> 7159.68 | J64: ='単位計算'!$C$23 -> 7159.68 | ... N64: ='単位計算'!$C$23 -> 7159.68
B65: １か月あたり単位 | C65: ='単位計算'!$C$21*'A型'!C61*'A型'!C62*'A型'!C63 -> 148684.8 | D65: ='単位計算'!$C$21*'A型'!D61*'A型'!D62*'A型'!D63 -> 141926.4 | E65: ='単位計算'!$C$21*'A型'!E61*'A型'!E62*'A型'!E63 -> 191276.8 | F65: ='単位計算'!$C$21*'A型'!F61*'A型'!F62*'A型'!F63 -> 184588.8 | G65: ='単位計算'!$C$21*'A型'!G61*'A型'!G62*'A型'!G63 -> 184588.8 | H65: ='単位計算'!$C$21*'A型'!H61*'A型'!H62*'A型'!H63 -> 184588.8 | I65: ='単位計算'!$C$21*'A型'!I61*'A型'!I62*'A型'!I63 -> 168537.6 | J65: ='単位計算'!$C$21*'A型'!J61*'A型'!J62*'A型'!J63 -> 160512 | ... N65: ='単位計算'!$C$21*'A型'!N61*'A型'!N62*'A型'!N63 -> 176563.2
B67: Ｂ型
B68: 開所日数
B69: 出勤予測率
B70: 在籍Ｂ型利用者数
B71: 一日当たり単位
B72: １か月あたり単位
B74: A型 処遇改善手当予測 | C74: =C65*'単位計算'!$C$25*'単位計算'!$C$22 -> 145163.94 | D74: =D65*'単位計算'!$C$25*'単位計算'!$C$22 -> 138565.58 | E74: =E65*'単位計算'!$C$25*'単位計算'!$C$22 -> 186747.37 | F74: =F65*'単位計算'!$C$25*'単位計算'!$C$22 -> 180217.74 | G74: =G65*'単位計算'!$C$25*'単位計算'!$C$22 -> 180217.74 | H74: =H65*'単位計算'!$C$25*'単位計算'!$C$22 -> 180217.74 | I74: =I65*'単位計算'!$C$25*'単位計算'!$C$22 -> 164546.63 | J74: =J65*'単位計算'!$C$25*'単位計算'!$C$22 -> 156711.08 | ... N74: =N65*'単位計算'!$C$25*'単位計算'!$C$22 -> 172382.18
B75: B型 処遇改善手当予測 | C75: =C72*'単位計算'!$G$25*'単位計算'!$G$22 -> 0 | D75: =D72*'単位計算'!$G$25*'単位計算'!$G$22 -> 0 | E75: =E72*'単位計算'!$G$25*'単位計算'!$G$22 -> 0 | F75: =F72*'単位計算'!$G$25*'単位計算'!$G$22 -> 0 | G75: =G72*'単位計算'!$G$25*'単位計算'!$G$22 -> 0 | H75: =H72*'単位計算'!$G$25*'単位計算'!$G$22 -> 0 | I75: =I72*'単位計算'!$G$25*'単位計算'!$G$22 -> 0 | J75: =J72*'単位計算'!$G$25*'単位計算'!$G$22 -> 0 | ... N75: =N72*'単位計算'!$G$25*'単位計算'!$G$22 -> 0

Sheet B型
B1: 変動費率 | C1: ４月実績 | D1: 5月実績 | E1: ６月実績 | F1: ７月実績 | G1: ８月実績 | H1: ９月実績 | I1: １０月実績 | J1: １１月実績 | K1: １２月実績 | L1: １月実績 | M1: ２月 | N1: ３月 | O1: 累計
O2: =SUM(C2:N2) -> 0
A3: 売上 | C3: =SUM(C4:C8) -> 461702 | D3: =SUM(D4:D8) -> 462616 | E3: =SUM(E4:E8) -> 520699 | F3: =SUM(F4:F8) -> 792313 | G3: =SUM(G4:G8) -> 583962 | H3: =SUM(H4:H8) -> 588210 | I3: =SUM(I4:I8) -> 719273 | J3: =SUM(J4:J8) -> 631355 | ... N3: =SUM(N4:N8) -> 1109305 | O3: =SUM(C3:N3) -> 8679351 | P3: =O3/$O$3 -> 1
A4: 国保連Ａ型 | C4: 0 | D4: 0 | E4: 0 | F4: 0 | G4: 0 | H4: 0 | I4: 0 | J4: 0 | O4: =SUM(C4:N4) -> 0
A5: 国保連Ｂ型 | C5: 363290 | D5: 352012 | E5: 411068 | F5: 689889 | G5: 478943 | H5: 465733 | I5: 603545 | J5: 517528 | K5: 544632 | L5: 1026809 | M5: 745700 | N5: 1036612 | O5: =SUM(C5:N5) -> 7235761
A6: 処遇改善手当 | C6: 0 | D6: 0 | E6: 0 | F6: 0 | G6: 0 | H6: 0 | I6: 0 | J6: 0 | K6: 0 | L6: 0 | M6: 0 | N6: 0 | O6: =SUM(C6:N6) -> 0
A7: 特開金 | C7: 0 | D7: 0 | E7: =E56*200000 -> 0 | F7: =F56*200000 -> 0 | G7: =G56*200000 -> 0 | H7: =H56*200000 -> 0 | I7: =I56*200000 -> 0 | J7: =J56*200000 -> 0 | K7: =K56*200000 -> 0 | L7: =L56*200000 -> 0 | M7: 0 | N7: =N56*200000 -> 0 | O7: =SUM(C7:N7) -> 0
A8: 生産活動 | C8: 98412 | D8: 110604 | E8: 109631 | F8: 102424 | G8: 105019 | H8: 122477 | I8: 115728 | J8: =89268+24559 -> 113827 | K8: =97709+26156 -> 123865 | L8: =245901+20827 -> 266728 | M8: =83890+18292 -> 102182 | N8: =61238+11455 -> 72693 | O8: =SUM(C8:N8) -> 1443590
A9: 売上原価 | C9: 2083 | D9: 11980 | E9: 4060 | F9: 3415 | G9: 2025 | H9: 4450 | I9: 7939 | J9: 618 | K9: 0 | L9: 5140 | M9: 4371 | N9: 3533 | O9: =SUM(C9:N9) -> 49614 | P9: =O9/$O$3 -> 0.005716326
A10: 売上総利益 | C10: =C2+C3-C9 -> 459619 | D10: =D2+D3-D9 -> 450636 | E10: =E2+E3-E9 -> 516639 | F10: =F2+F3-F9 -> 788898 | G10: =G2+G3-G9 -> 581937 | H10: =H2+H3-H9 -> 583760 | I10: =I2+I3-I9 -> 711334 | J10: =J2+J3-J9 -> 630737 | ... N10: =N2+N3-N9 -> 1105772 | O10: =SUM(C10:N10) -> 8629737
A11: 処遇改善手当 | C11: =C6 -> 0 | D11: =D6 -> 0 | E11: =E6 -> 0 | F11: 0 | G11: 0 | H11: 0 | I11: 0 | J11: 0 | K11: 0 | L11: 0 | O11: =SUM(C11:N11) -> 0
A12: 役員報酬 | C12: 0 | D12: 0 | E12: 0 | F12: 0 | G12: 0 | H12: 0 | I12: 0 | J12: 0 | K12: 0 | L12: 0 | O12: =SUM(C12:N12) -> 0 | P12: =O12/$O$10 -> 0
A13: 給与手当 | C13: 161873 | D13: 167191 | E13: 168156 | F13: 180106 | G13: 168271 | H13: 179114 | I13: 169612 | J13: 139860 | K13: 131953 | L13: 134365 | M13: 132217 | N13: =86093+61950 -> 148043 | O13: =SUM(C13:N13) -> 1880761
A14: Ｂ型利用者報酬 | C14: 45293 | D14: 46480 | E14: 50418 | F14: 91376 | G14: 95310 | H14: 98685 | I14: 114851 | J14: 123380 | K14: 99282 | L14: 103922 | M14: 72431 | N14: 125952 | O14: =SUM(C14:N14) -> 1067380 | P14: =O14/$O$10 -> 0.12368627
A15: 法定福利費 | B15: 0.15 | C15: 29973 | D15: 11167 | E15: 10326 | F15: 123086 | G15: 45435 | H15: 21611 | I15: 47420 | J15: 19099 | K15: 19102 | L15: 36175 | M15: 23684 | N15: 7100 | O15: =SUM(C15:N15) -> 394178
A16: 福利厚生費 | C16: 19459 | D16: 12963 | E16: 13370 | F16: 17694 | G16: 10324 | H16: 14305 | I16: 20014 | J16: 12935 | K16: 13912 | L16: 15875 | M16: 30000 | N16: 10941 | O16: =SUM(C16:N16) -> 191792
A17: 業務委託費 | C17: 1000 | D17: 1000 | E17: 1000 | F17: 1000 | G17: 1000 | H17: 1000 | I17: 1000 | J17: 1000 | K17: 1000 | L17: 1000 | M17: 1000 | N17: 700 | O17: =SUM(C17:N17) -> 11700
A18: 労務委託費 | C18: 0 | D18: 0 | E18: 0 | F18: 0 | G18: 0 | H18: 0 | I18: 0 | J18: 0 | K18: 0 | L18: 0 | O18: =SUM(C18:N18) -> 0
A19: 旅費交通費 | B19: 2名分 | C19: 5557 | D19: 5481 | E19: 6605 | F19: 6908 | G19: 6185 | H19: 6621 | I19: 4949 | J19: 4362 | K19: 4609 | L19: 6900 | M19: 6269 | N19: 4222 | O19: =SUM(C19:N19) -> 68668
A20: 通信費 | C20: 161 | D20: 182 | E20: 118 | F20: 991 | G20: 1344 | H20: 161 | I20: 613 | J20: 336 | K20: 4228 | L20: 1628 | M20: 384 | N20: 156 | O20: =SUM(C20:N20) -> 10302 | P20: =O20/$O$10 -> 0.0011937791
A21: 研修採用費 | C21: 0 | D21: 0 | E21: 1818 | F21: 0 | G21: 0 | H21: 0 | I21: 0 | J21: 0 | K21: 0 | L21: 0 | M21: 0 | N21: 509 | O21: =SUM(C21:N21) -> 2327
A22: 交際費 | C22: 0 | D22: 0 | E22: 0 | F22: 0 | G22: 0 | H22: 0 | I22: 0 | J22: 0 | K22: 0 | L22: 0 | M22: 0 | N22: 0 | O22: =SUM(C22:N22) -> 0 | P22: =O22/$O$10 -> 0
A23: 会議費 | C23: 0 | D23: 0 | E23: 0 | F23: 0 | G23: 0 | H23: 0 | I23: 0 | J23: 0 | K23: 0 | L23: 0 | M23: 0 | N23: 0 | O23: =SUM(C23:N23) -> 0
A24: 戦略費 | C24: 0 | D24: 0 | E24: 0 | F24: 0 | G24: 0 | H24: 0 | I24: 0 | J24: 0 | K24: 0 | L24: 0 | M24: 0 | N24: 0 | O24: =SUM(C24:N24) -> 0 | P24: =O24/$O$10 -> 0
A25: 減価償却費 | C25: 0 | D25: 0 | E25: 0 | F25: 0 | G25: 0 | H25: 0 | I25: 0 | J25: 0 | K25: 0 | L25: 0 | M25: 0 | N25: 0 | O25: =SUM(C25:N25) -> 0
A26: 賃借料 | C26: 0 | D26: 0 | E26: 0 | F26: 0 | G26: 0 | H26: 0 | I26: 0 | J26: 0 | K26: 0 | L26: 0 | M26: 0 | N26: 0 | O26: =SUM(C26:N26) -> 0
A27: 地代家賃 | C27: 150000 | D27: 150000 | E27: 150000 | F27: 150000 | G27: 150000 | H27: 150000 | I27: 150000 | J27: 150000 | K27: 150000 | L27: 150000 | M27: 150000 | N27: 150000 | O27: =SUM(C27:N27) -> 1800000
A28: リース料 | C28: 0 | D28: 0 | E28: 0 | F28: 0 | G28: 0 | H28: 0 | I28: 0 | J28: 0 | K28: 0 | L28: 0 | M28: 0 | N28: 0 | O28: =SUM(C28:N28) -> 0
A29: 修繕費 | C29: 0 | D29: 0 | E29: 0 | F29: 0 | G29: 0 | H29: 0 | I29: 0 | J29: 0 | K29: 0 | L29: 0 | M29: 0 | N29: 0 | O29: =SUM(C29:N29) -> 0
A30: 保険料 | C30: 936 | D30: 884 | E30: 884 | F30: 884 | G30: 884 | H30: 884 | I30: 884 | J30: 884 | K30: 884 | L30: 884 | M30: 884 | N30: 619 | O30: =SUM(C30:N30) -> 10395
A31: 水道光熱費 | B31: 0 | C31: 0 | D31: 0 | E31: 0 | F31: 0 | G31: 0 | H31: 0 | I31: 0 | J31: 0 | K31: 0 | L31: 0 | M31: 0 | N31: 0 | O31: =SUM(C31:N31) -> 0
A32: 消耗品費 | B32: 0 | C32: 617 | D32: 648 | E32: 2838 | F32: 2623 | G32: 740 | H32: 260 | I32: 1623 | J32: 1073 | K32: 280 | L32: 1822 | M32: 389 | N32: 651 | O32: =SUM(C32:N32) -> 13564 | P32: =O32/$O$10 -> 0.0015717744
A33: 租税公課 | C33: 0 | D33: 1430 | E33: 60 | F33: 110 | G33: 0 | H33: 0 | I33: 0 | J33: 0 | K33: 0 | L33: 0 | M33: 0 | N33: 13 | O33: =SUM(C33:N33) -> 1613
A34: 広告宣伝費 | C34: 0 | D34: 510 | E34: 0 | F34: 0 | G34: 0 | H34: 0 | I34: 0 | J34: 4980 | K34: 0 | L34: 0 | M34: 0 | N34: 0 | O34: =SUM(C34:N34) -> 5490
A35: 支払手数料 | B35: 0 | C35: 3808 | D35: 7535 | E35: 7485 | F35: 7649 | G35: 4954 | H35: 5710 | I35: 4826 | J35: 4925 | K35: 1291 | L35: 921 | M35: 1266 | N35: 8793 | O35: =SUM(C35:N35) -> 59163
A36: 教育費 | C36: 0 | D36: 0 | E36: 0 | F36: 0 | G36: 0 | H36: 0 | I36: 0 | J36: 0 | K36: 0 | L36: 0 | M36: 0 | N36: 0 | O36: =SUM(C36:N36) -> 0
A37: 新聞図書費 | C37: 400 | D37: 0 | E37: 0 | F37: 0 | G37: 184 | H37: 0 | I37: 0 | J37: 0 | K37: 0 | L37: 0 | M37: 0 | N37: 0 | O37: =SUM(C37:N37) -> 584
A38: 管理諸費 | B38: 0.2 | C38: 41890 | D38: 53308 | E38: 68772 | F38: 61540 | G38: 54165 | H38: 55345 | I38: 55348 | J38: 41455 | K38: 54987 | L38: 69485 | M38: 48150 | N38: 43769 | O38: =SUM(C38:N38) -> 648214
A39: 賞与 | C39: 0 | D39: 0 | E39: 30000 | F39: 0 | G39: 0 | H39: 0 | I39: 0 | J39: 0 | K39: 0 | L39: 0 | M39: 0 | N39: 0 | O39: =SUM(C39:N39) -> 30000 | P39: =O39/$O$10 -> 0.0034763516
C40: 0 | D40: 0 | E40: 0 | F40: 0 | G40: 0 | H40: 0 | I40: 0 | J40: 0 | K40: 0 | L40: 0 | M40: 0 | N40: 0 | O40: =SUM(C40:N40) -> 0
C41: 0 | D41: 0 | E41: 0 | F41: 0 | G41: 0 | H41: 0 | I41: 0 | J41: 0 | K41: 0 | L41: 0 | M41: 0 | N41: 0 | O41: =SUM(C41:N41) -> 0
A42: 販売管理費合計 | C42: =SUM(C12:C41) -> 460967 | D42: =SUM(D12:D41) -> 458779 | E42: =SUM(E12:E41) -> 511850 | F42: =SUM(F12:F41) -> 643967 | G42: =SUM(G12:G41) -> 538796 | H42: =SUM(H12:H41) -> 533696 | I42: =SUM(I12:I41) -> 571140 | J42: =SUM(J12:J41) -> 504289 | ... N42: =SUM(N12:N41) -> 501468 | O42: =SUM(C42:N42) -> 6196131 | P42: =O42/$O$10 -> 0.71799766
A43: 営業利益 | C43: =C10-C42 -> -1348 | D43: =D10-D42 -> -8143 | E43: =E10-E42 -> 4789 | F43: =F10-F42 -> 144931 | G43: =G10-G42 -> 43141 | H43: =H10-H42 -> 50064 | I43: =I10-I42 -> 140194 | J43: =J10-J42 -> 126448 | ... O43: =O10-O42 -> 2433606 | P43: =O43/$O$10 -> 0.28200234
A44: 支払利息 | C44: 0 | D44: 0 | E44: 0 | F44: 0 | G44: 0 | H44: 0 | I44: 0 | J44: 0 | K44: 0 | L44: 0 | M44: 0 | O44: =SUM(C44:N44) -> 0
A45: 雑損失 | C45: 0 | D45: 0 | E45: 0 | F45: 0 | G45: 0 | H45: 0 | I45: 0 | J45: 0 | K45: 0 | L45: 0 | M45: 0 | O45: =SUM(C45:N45) -> 0
A46: 受取利息 雑収入 | B46: 社員分昼食代 | C46: 0 | D46: 0 | E46: 0 | F46: 0 | G46: 0 | H46: 0 | I46: 0 | J46: 0 | K46: 0 | L46: 0 | M46: 0 | O46: =SUM(C46:N46) -> 0
A47: 経常利益 | C47: =C43-C44-C45+C46 -> -1348 | D47: =D43-D44-D45+D46 -> -8143 | E47: =E43-E44-E45+E46 -> 4789 | F47: =F43-F44-F45+F46 -> 144931 | G47: =G43-G44-G45+G46 -> 43141 | H47: =H43-H44-H45+H46 -> 50064 | I47: =I43-I44-I45+I46 -> 140194 | J47: =J43-J44-J45+J46 -> 126448 | ... O47: =O43-O44-O45+O46 -> 2433606 | P47: =O47/$O$10 -> 0.28200234
A48: 特別利益 | C48: 0 | D48: 0 | E48: 0 | F48: 0 | G48: 0 | H48: 0 | I48: 0 | J48: 0 | K48: 0 | L48: 0 | M48: 0 | O48: =SUM(C48:N48) -> 0
A49: 特別損失 | C49: 0 | D49: 0 | E49: 0 | F49: 0 | G49: 0 | H49: 0 | I49: 0 | J49: 0 | K49: 0 | L49: 0 | M49: 0 | O49: =SUM(C49:N49) -> 0
A50: 税引前当期純利益 | C50: =C47+C48-C49 -> -1348 | D50: =D47+D48-D49 -> -8143 | E50: =E47+E48-E49 -> 4789 | F50: =F47+F48-F49 -> 144931 | G50: =G47+G48-G49 -> 43141 | H50: =H47+H48-H49 -> 50064 | I50: =I47+I48-I49 -> 140194 | J50: =J47+J48-J49 -> 126448 | ... O50: =O47+O48-O49 -> 2433606 | P50: =O50/$O$10 -> 0.28200234
B55: 月別 Ａ型 | C55: =C61*C62*C63*C64 -> 0 | D55: =D61*D62*D63*D64 -> 0 | E55: =E61*E62*E63*E64 -> 0 | F55: =F61*F62*F63*F64 -> 0 | G55: =G61*G62*G63*G64 -> 0 | H55: =H61*H62*H63*H64 -> 0 | I55: =I61*I62*I63*I64 -> 0 | J55: =J61*J62*J63*J64 -> 0 | ... N55: =N61*N62*N63*N64 -> 0
B56: 特開金対象人数
B58: 月別 Ｂ型 | C58: =C68*C69*C70*C71 -> 420183.72 | D58: =D68*D69*D70*D71 -> 401084.46 | E58: =E68*E69*E70*E71 -> 420183.72 | F58: =F68*F69*F70*F71 -> 732138.3 | G58: =G68*G69*G70*G71 -> 732138.3 | H58: =H68*H69*H70*H71 -> 732138.3 | I58: =I68*I69*I70*I71 -> 668474.1 | J58: =J68*J69*J70*J71 -> 636642 | ... N58: =N68*N69*N70*N71 -> 700306.2
B60: A型
B61: 開所日数
B62: 出勤予測率
B63: 在籍Ａ型利用者数
B64: 一日当たり金額
B65: １か月あたり単位
B67: Ｂ型
B68: 開所日数 | C68: 22 | D68: 21 | E68: 22 | F68: 23 | G68: 23 | H68: 23 | I68: 21 | J68: 20 | K68: 21 | L68: 22 | M68: 22 | N68: 22
B69: 出勤予測率 | C69: 0.5 | D69: 0.5 | E69: 0.5 | F69: 0.5 | G69: 0.5 | H69: 0.5 | I69: 0.5 | J69: 0.5 | K69: 0.5 | L69: 0.5 | M69: 0.5 | N69: 0.5
B70: 在籍Ｂ型利用者数 | C70: 6 | D70: 6 | E70: 6 | F70: 10 | G70: 10 | H70: 10 | I70: 10 | J70: 10 | K70: 10 | L70: 10 | M70: 10 | N70: 10
B71: 一日当たり単位 | C71: ='単位計算'!$G$23 -> 6366.42 | D71: ='単位計算'!$G$23 -> 6366.42 | E71: ='単位計算'!$G$23 -> 6366.42 | F71: ='単位計算'!$G$23 -> 6366.42 | G71: ='単位計算'!$G$23 -> 6366.42 | H71: ='単位計算'!$G$23 -> 6366.42 | I71: ='単位計算'!$G$23 -> 6366.42 | J71: ='単位計算'!$G$23 -> 6366.42 | ... N71: ='単位計算'!$G$23 -> 6366.42
B72: １か月あたり単位 | C72: =C68*C69*C70*'単位計算'!$G$21 -> 41316 | D72: =D68*D69*D70*'単位計算'!$G$21 -> 39438 | E72: =E68*E69*E70*'単位計算'!$G$21 -> 41316 | F72: =F68*F69*F70*'単位計算'!$G$21 -> 71990 | G72: =G68*G69*G70*'単位計算'!$G$21 -> 71990 | H72: =H68*H69*H70*'単位計算'!$G$21 -> 71990 | I72: =I68*I69*I70*'単位計算'!$G$21 -> 65730 | J72: =J68*J69*J70*'単位計算'!$G$21 -> 62600 | ... N72: =N68*N69*N70*'単位計算'!$G$21 -> 68860
B74: A型 処遇改善手当予測 | C74: =C65*'単位計算'!$C$25*'単位計算'!$C$22 -> 0 | D74: =D65*'単位計算'!$C$25*'単位計算'!$C$22 -> 0 | E74: =E65*'単位計算'!$C$25*'単位計算'!$C$22 -> 0 | F74: =F65*'単位計算'!$C$25*'単位計算'!$C$22 -> 0 | G74: =G65*'単位計算'!$C$25*'単位計算'!$C$22 -> 0 | H74: =H65*'単位計算'!$C$25*'単位計算'!$C$22 -> 0 | I74: =I65*'単位計算'!$C$25*'単位計算'!$C$22 -> 0 | J74: =J65*'単位計算'!$C$25*'単位計算'!$C$22 -> 0 | ... N74: =N65*'単位計算'!$C$25*'単位計算'!$C$22 -> 0
B75: B型 処遇改善手当予測 | C75: =C72*'単位計算'!$G$25*'単位計算'!$G$22 -> 39077.086 | D75: =D72*'単位計算'!$G$25*'単位計算'!$G$22 -> 37300.855 | E75: =E72*'単位計算'!$G$25*'単位計算'!$G$22 -> 39077.086 | F75: =F72*'単位計算'!$G$25*'単位計算'!$G$22 -> 68088.862 | G75: =G72*'単位計算'!$G$25*'単位計算'!$G$22 -> 68088.862 | H75: =H72*'単位計算'!$G$25*'単位計算'!$G$22 -> 68088.862 | I75: =I72*'単位計算'!$G$25*'単位計算'!$G$22 -> 62168.091 | J75: =J72*'単位計算'!$G$25*'単位計算'!$G$22 -> 59207.706 | ... N75: =N72*'単位計算'!$G$25*'単位計算'!$G$22 -> 65128.477
B78: Ｂ型平均工賃月額 | C78: 20000 | D78: 20000 | E78: 20000 | F78: 20000 | G78: 20000 | H78: 20000 | I78: 20000 | J78: 20000 | K78: 20000 | L78: 20000 | M78: 20000 | N78: 20000

Sheet 共通費
B1: 変動費率 | C1: 4月実績 | D1: 5月実績 | E1: 6月実績 | F1: 7月実績 | G1: 8月実績 | H1: 9月実績 | I1: 10月実績 | J1: 11月実績 | K1: 12月実績 | L1: 1月実績 | M1: 2月実績 | N1: 3月 | O1: 累計
O2: =SUM(C2:N2) -> 0
A3: 売上 | C3: =SUM(C4:C8) -> 0 | D3: =SUM(D4:D8) -> 0 | E3: =SUM(E4:E8) -> 0 | F3: =SUM(F4:F8) -> 0 | G3: =SUM(G4:G8) -> 0 | H3: =SUM(H4:H8) -> 0 | I3: =SUM(I4:I8) -> 1 | J3: =SUM(J4:J8) -> -1 | ... N3: =SUM(N4:N8) -> 0 | O3: =SUM(C3:N3) -> 0
A4: 国保連Ａ型 | C4: 0 | D4: 0 | E4: 0 | F4: 0 | G4: 0 | H4: 0 | I4: 0 | J4: 0 | K4: 0 | L4: 0 | M4: 0 | O4: =SUM(C4:N4) -> 0
A5: 国保連Ｂ型 | C5: 0 | D5: 0 | E5: 0 | F5: 0 | G5: 0 | H5: 0 | I5: 0 | J5: 0 | K5: 0 | L5: 0 | M5: 0 | O5: =SUM(C5:N5) -> 0
A6: 処遇改善手当 | C6: 0 | D6: 0 | E6: 0 | F6: 0 | G6: 0 | H6: 0 | I6: 0 | J6: 0 | K6: 0 | L6: 0 | M6: 0 | O6: =SUM(C6:N6) -> 0
A7: 特開金 | C7: 0 | D7: 0 | E7: 0 | F7: 0 | G7: 0 | H7: 0 | I7: 0 | J7: 0 | K7: 0 | L7: 0 | M7: 0 | O7: =SUM(C7:N7) -> 0
A8: 生産活動 | C8: 0 | D8: 0 | E8: 0 | F8: 0 | G8: 0 | H8: 0 | I8: 1 | J8: -1 | K8: 0 | L8: 0 | M8: 0 | O8: =SUM(C8:N8) -> 0
A9: 売上原価 | C9: 0 | D9: 0 | E9: 0 | F9: 0 | G9: 0 | H9: 0 | I9: 0 | J9: -1 | K9: 0 | L9: 0 | M9: 0 | O9: =SUM(C9:N9) -> -1
A10: 売上総利益 | C10: =C2+C3-C9 -> 0 | D10: =D2+D3-D9 -> 0 | E10: =E2+E3-E9 -> 0 | F10: =F2+F3-F9 -> 0 | G10: =G2+G3-G9 -> 0 | H10: =H2+H3-H9 -> 0 | I10: =I2+I3-I9 -> 1 | J10: =J2+J3-J9 -> 0 | ... N10: =N2+N3-N9 -> 0 | O10: =SUM(C10:N10) -> 1
A11: 処遇改善手当 | C11: =C6 -> 0 | D11: =D6 -> 0 | E11: =E6 -> 0 | F11: =F6 -> 0 | G11: =G6 -> 0 | H11: =H6 -> 0 | I11: =I6 -> 0 | J11: =J6 -> 0 | ... N11: =N6 | O11: =SUM(C11:N11) -> 0
A12: 役員報酬 | C12: 100000 | D12: 100000 | E12: 100000 | F12: 100000 | G12: 100000 | H12: 100000 | I12: 100000 | J12: 100000 | K12: 100000 | L12: 100000 | M12: 100000 | N12: 100000 | O12: =SUM(C12:N12) -> 1200000
A13: 給与手当 | B13: 1名 | C13: 0 | D13: 0 | E13: 0 | F13: 0 | G13: 0 | H13: 0 | I13: 0 | J13: 0 | K13: -1 | L13: 0 | M13: 0 | O13: =SUM(C13:N13) -> -1
A14: 雑給 | C14: 0 | D14: 0 | E14: 0 | F14: 0 | G14: 0 | H14: 0 | I14: 0 | J14: 0 | K14: 0 | L14: 0 | M14: 0 | O14: =SUM(C14:N14) -> 0
A15: 法定福利費 | B15: 0.15 | C15: 0 | D15: 0 | E15: 0 | F15: 0 | G15: 0 | H15: 0 | I15: 0 | J15: 0 | K15: 0 | L15: 0 | M15: 0 | O15: =SUM(C15:N15) -> 0
A16: 福利厚生費 | C16: 0 | D16: 0 | E16: 0 | F16: 0 | G16: 0 | H16: 1 | I16: 0 | J16: 0 | K16: -1 | L16: 0 | M16: 0 | O16: =SUM(C16:N16) -> 0
A17: 業務委託費 | C17: 0 | D17: 0 | E17: 0 | F17: 0 | G17: 0 | H17: 0 | I17: 0 | J17: 0 | K17: 0 | L17: 0 | M17: 0 | O17: =SUM(C17:N17) -> 0
A18: 労務委託費 | C18: 0 | D18: 0 | E18: 0 | F18: 0 | G18: 0 | H18: 0 | I18: 0 | J18: 0 | K18: 0 | L18: 0 | M18: 0 | O18: =SUM(C18:N18) -> 0
A19: 旅費交通費 | C19: 0 | D19: 0 | E19: 1 | F19: 0 | G19: 1 | H19: 0 | I19: 0 | J19: 0 | K19: 0 | L19: 0 | M19: 0 | O19: =SUM(C19:N19) -> 2
A20: 通信費 | C20: 0 | D20: 0 | E20: 0 | F20: 0 | G20: -1 | H20: 0 | I20: 0 | J20: 0 | K20: 0 | L20: 0 | M20: 0 | O20: =SUM(C20:N20) -> -1
A21: 研修採用費 | C21: 0 | D21: 0 | E21: 0 | F21: 0 | G21: 0 | H21: 0 | I21: 0 | J21: 0 | K21: 0 | L21: 0 | M21: 0 | O21: =SUM(C21:N21) -> 0
A22: 交際費 | C22: 0 | D22: 0 | E22: 0 | F22: 0 | G22: 0 | H22: 0 | I22: 0 | J22: 0 | K22: 0 | L22: 0 | M22: 0 | O22: =SUM(C22:N22) -> 0
A23: 会議費 | C23: 0 | D23: 0 | E23: 0 | F23: 0 | G23: 0 | H23: 0 | I23: 0 | J23: 0 | K23: 0 | L23: 0 | M23: 0 | O23: =SUM(C23:N23) -> 0
A24: 戦略費 | C24: 0 | D24: 0 | E24: 0 | F24: 0 | G24: 0 | H24: 0 | I24: 0 | J24: 0 | K24: 0 | L24: 0 | M24: 0 | O24: =SUM(C24:N24) -> 0
A25: 減価償却費 | C25: 0 | D25: 0 | E25: 0 | F25: 0 | G25: 0 | H25: 0 | I25: 0 | J25: 0 | K25: 0 | L25: 0 | M25: 0 | O25: =SUM(C25:N25) -> 0
A26: 賃借料 | C26: 0 | D26: 0 | E26: 0 | F26: 0 | G26: 0 | H26: 0 | I26: 0 | J26: 0 | K26: 0 | L26: 0 | M26: 0 | O26: =SUM(C26:N26) -> 0
A27: 地代家賃 | C27: 17000 | D27: 17000 | E27: 17000 | F27: 17000 | G27: 17000 | H27: 17000 | I27: 17000 | J27: 17000 | K27: 21600 | L27: -17000 | M27: 0 | O27: =SUM(C27:N27) -> 140600
... A30: 保険料 | C30: 0 | D30: 0 | E30: 0 | F30: 0 | G30: 0 | H30: 0 | I30: 0 | J30: 0 | K30: 0 | L30: 0 | M30: -1 | O30: =SUM(C30:N30) -> -1
A31: 水道光熱費 | B31: 0 | C31: 0 | D31: 0 | E31: 0 | F31: 0 | G31: 0 | H31: 0 | I31: 0 | J31: 0 | K31: 0 | L31: 0 | M31: 0 | O31: =SUM(C31:N31) -> 0
A32: 消耗品費 | B32: 0 | C32: -1 | D32: 0 | E32: 0 | F32: 0 | G32: 0 | H32: 0 | I32: 0 | J32: -1 | K32: 0 | L32: 0 | M32: 0 | O32: =SUM(C32:N32) -> -2
A33: 租税公課 | C33: 0 | D33: 0 | E33: 0 | F33: 0 | G33: 0 | H33: 0 | I33: 0 | J33: 0 | K33: 0 | L33: 0 | M33: 0 | O33: =SUM(C33:N33) -> 0
A34: 広告宣伝費 | C34: 0 | D34: 0 | E34: 0 | F34: 0 | G34: 0 | H34: 0 | I34: 0 | J34: 0 | K34: 0 | L34: 0 | M34: 0 | O34: =SUM(C34:N34) -> 0
A35: 支払手数料 | B35: 0 | C35: 0 | D35: 0 | E35: 0 | F35: 0 | G35: 0 | H35: 0 | I35: -1 | J35: 0 | K35: 0 | L35: 0 | M35: 0 | O35: =SUM(C35:N35) -> -1
A36: 教育費 | C36: 0 | D36: 0 | E36: 0 | F36: 0 | G36: 0 | H36: 0 | I36: 0 | J36: 0 | K36: 0 | L36: 0 | M36: 0 | O36: =SUM(C36:N36) -> 0
A37: 新聞図書費 | C37: 0 | D37: 0 | E37: 0 | F37: 0 | G37: 0 | H37: 0 | I37: 0 | J37: 0 | K37: 0 | L37: 0 | M37: 0 | O37: =SUM(C37:N37) -> 0
A38: 管理諸費 | B38: 長田・池田・高畑 | C38: 0 | D38: 0 | E38: 0 | F38: 0 | G38: 0 | H38: 0 | I38: 0 | J38: 0 | K38: 0 | L38: 0 | M38: -1 | O38: =SUM(C38:N38) -> -1
C39: 0 | D39: 0 | E39: 0 | F39: 0 | G39: 0 | H39: 0 | I39: 0 | J39: 0 | K39: 0 | L39: 0 | M39: 0 | O39: =SUM(C39:N39) -> 0
C40: 0 | D40: 0 | E40: 0 | F40: 0 | G40: 0 | H40: 0 | I40: 0 | J40: 0 | K40: 0 | L40: 0 | M40: 0 | O40: =SUM(C40:N40) -> 0
C41: 0 | D41: 0 | E41: 0 | F41: 0 | G41: 0 | H41: 0 | I41: 0 | J41: 0 | K41: 0 | L41: 0 | M41: 0 | O41: =SUM(C41:N41) -> 0
A42: 販売管理費合計 | C42: =SUM(C12:C41) -> 116999 | D42: =SUM(D12:D41) -> 117000 | E42: =SUM(E12:E41) -> 117001 | F42: =SUM(F12:F41) -> 117000 | G42: =SUM(G12:G41) -> 117000 | H42: =SUM(H12:H41) -> 117001 | I42: =SUM(I12:I41) -> 116999 | J42: =SUM(J12:J41) -> 116999 | ... N42: =SUM(N12:N41) -> 100000 | O42: =SUM(C42:N42) -> 1340595
A43: 営業利益 | C43: =C10-C42 -> -116999 | D43: =D10-D42 -> -117000 | E43: =E10-E42 -> -117001 | F43: =F10-F42 -> -117000 | G43: =G10-G42 -> -117000 | H43: =H10-H42 -> -117001 | I43: =I10-I42 -> -116998 | J43: =J10-J42 -> -116999 | ... O43: =O10-O42 -> -1340594
A44: 支払利息 | C44: 5424 | D44: 0 | E44: 9697 | F44: 5260 | G44: 0 | H44: 9862 | I44: 5095 | J44: 0 | K44: 5753 | L44: 4525 | M44: 4448 | N44: 9126 | O44: =SUM(C44:N44) -> 59190
A45: 雑損失 | C45: 0 | D45: 0 | E45: 0 | F45: 0 | G45: 0 | H45: 0 | I45: 0 | J45: 0 | K45: 0 | O45: =SUM(C45:N45) -> 0
A46: 受取利息 雑収入 | C46: 19444 | D46: 179264 | E46: 155 | F46: 101047 | G46: 2783 | H46: 0 | I46: 0 | J46: 0 | K46: 0 | L46: 1400000 | M46: 2033 | O46: =SUM(C46:N46) -> 1704726
A47: 経常利益 | C47: =C43-C44-C45+C46 -> -102979 | D47: =D43-D44-D45+D46 -> 62264 | E47: =E43-E44-E45+E46 -> -126543 | F47: =F43-F44-F45+F46 -> -21213 | G47: =G43-G44-G45+G46 -> -114217 | H47: =H43-H44-H45+H46 -> -126863 | I47: =I43-I44-I45+I46 -> -122093 | J47: =J43-J44-J45+J46 -> -116999 | ... O47: =O43-O44-O45+O46 -> 304942
A48: 特別利益 | C48: 0 | D48: 0 | E48: 0 | F48: 0 | G48: 0 | H48: 0 | I48: 0 | J48: 0 | K48: 0 | O48: =SUM(C48:N48) -> 0
A49: 特別損失 | C49: 0 | D49: 0 | E49: 0 | F49: 0 | G49: 0 | H49: 0 | I49: 0 | J49: 0 | K49: 0 | O49: =SUM(C49:N49) -> 0
A50: 税引前当期純利益 | C50: =C47+C48-C49 -> -102979 | D50: =D47+D48-D49 -> 62264 | E50: =E47+E48-E49 -> -126543 | F50: =F47+F48-F49 -> -21213 | G50: =G47+G48-G49 -> -114217 | H50: =H47+H48-H49 -> -126863 | I50: =I47+I48-I49 -> -122093 | J50: =J47+J48-J49 -> -116999 | ... O50: =O47+O48-O49 -> 304942

Sheet 予測PL (2024)
B1: 変動費率 | C1: 7月実績 | D1: 8月実績 | E1: 9月実績 | F1: 10月実績 | G1: 11月実績 | H1: 12月実績 | I1: 1月実績 | J1: 2月実績 | K1: 3月実績 | L1: 4月 | M1: 5月 | N1: 6月 | O1: 累計
O2: =SUM(C2:N2) -> 0
A3: 売上 | C3: =SUM(C4:C8) -> 3167597 | D3: =SUM(D4:D8) -> 3425028 | E3: =SUM(E4:E8) -> 2910499 | F3: =SUM(F4:F8) -> 3617638 | G3: =SUM(G4:G8) -> 2874274 | H3: =SUM(H4:H8) -> 2600884 | I3: =SUM(I4:I8) -> 2535061 | J3: =SUM(J4:J8) -> 2543908 | K3: =SUM(K4:K8) -> 3151749 | O3: =SUM(C3:N3) -> 26826638 | P3: =O3/$O$3 -> 1
A4: 国保連Ａ型 | C4: 2522779 | D4: 2548892 | E4: 1925694 | F4: 2380420 | G4: 1810499 | H4: 1671189 | I4: 1672457 | J4: 1488521 | K4: 1868452 | O4: =SUM(C4:N4) -> 17888903
A5: 国保連Ｂ型 | C5: 0 | D5: 0 | E5: 0 | F5: 0 | G5: 98373 | H5: 136927 | I5: 120493 | J5: 184887 | K5: 233237 | O5: =SUM(C5:N5) -> 773917
O6: =SUM(C6:N6) -> 0
A7: 特開金 | C7: 0 | D7: 0 | E7: 0 | F7: 0 | H7: =H58*200000 -> 0 | I7: =I58*200000 -> 0 | J7: 0 | K7: =K58*200000 -> 0 | O7: =SUM(C7:N7) -> 0
A8: 生産活動 | C8: 644818 | D8: 876136 | E8: 984805 | F8: 1237218 | G8: 965402 | H8: 792768 | I8: 742111 | J8: 870500 | K8: 1050060 | O8: =SUM(C8:N8) -> 8163818
A9: 売上原価 | D9: 2500 | E9: 55700 | F9: 100695 | G9: 5538 | H9: 15412 | I9: 25044 | J9: 17848 | K9: 31435 | O9: =SUM(C9:N9) -> 254172 | P9: =O9/$O$3 -> 0.0094746125
A10: 売上総利益 | C10: =C2+C3-C9 -> 3167597 | D10: =D2+D3-D9 -> 3422528 | E10: =E2+E3-E9 -> 2854799 | F10: =F2+F3-F9 -> 3516943 | G10: =G2+G3-G9 -> 2868736 | H10: =H2+H3-H9 -> 2585472 | I10: =I2+I3-I9 -> 2510017 | J10: =J2+J3-J9 -> 2526060 | ... N10: =N2+N3-N9 -> 0 | O10: =SUM(C10:N10) -> 26572466
O11: =SUM(C11:N11) -> 0
A12: 役員報酬 | C12: 100000 | D12: 100000 | E12: 100000 | F12: 100000 | G12: 100000 | H12: 100000 | I12: 100000 | J12: 100000 | K12: 100000 | O12: =SUM(C12:N12) -> 900000 | P12: =O12/$O$10 -> 0.033869645
A13: 給与手当 | C13: 990985 | D13: 1012718 | E13: 1329766 | F13: 1546185 | G13: 1327564 | H13: 1340000 | I13: 1406600 | J13: 1355000 | K13: =1130000+1622465 -> 2752465 | O13: =SUM(C13:N13) -> 13061283
A14: 雑給 | C14: 1668580 | D14: 1770640 | E14: 1302720 | F14: 1714646 | G14: 1620679 | H14: 1435431 | I14: 1324109 | J14: 1241742 | K14: 1351432 | O14: =SUM(C14:N14) -> 13429979 | P14: =O14/$O$10 -> 0.50540958
A15: 法定福利費 | B15: 0 | C15: 238453 | D15: 173534 | E15: 197529 | F15: 192435 | G15: 246407 | H15: 247527 | I15: -288512 | J15: 180964 | K15: 395837 | O15: =SUM(C15:N15) -> 1584174
A16: 福利厚生費 | C16: 201852 | D16: 253855 | E16: 184259 | F16: 214815 | G16: 205741 | H16: 194028 | I16: 186306 | J16: 154000 | K16: 192500 | O16: =SUM(C16:N16) -> 1787356
A17: 業務委託費 | C17: 10000 | D17: 10000 | E17: 70000 | F17: 10000 | G17: 10000 | H17: 10000 | I17: 10000 | J17: 10000 | K17: 10000 | O17: =SUM(C17:N17) -> 150000
A18: 労務委託費 | O18: =SUM(C18:N18) -> 0
A19: 旅費交通費 | C19: 11585 | D19: 20109 | E19: 17000 | F19: 22591 | G19: 20636 | H19: 20946 | I19: 23501 | J19: 20091 | K19: 54027 | O19: =SUM(C19:N19) -> 210486
A20: 通信費 | C20: 16341 | D20: 13271 | E20: 1650 | F20: 5125 | G20: 4055 | H20: 1483 | I20: 14511 | J20: 2905 | K20: 3042 | O20: =SUM(C20:N20) -> 62383 | P20: =O20/$O$10 -> 0.0023476557
A21: 研修採用費 | F21: 9091 | I21: 18182 | J21: 54545 | K21: 18182 | O21: =SUM(C21:N21) -> 100000
A22: 交際費 | C22: 39273 | D22: 18909 | O22: =SUM(C22:N22) -> 58182 | P22: =O22/$O$10 -> 0.0021895597
A23: 会議費 | O23: =SUM(C23:N23) -> 0
A24: 戦略費 | O24: =SUM(C24:N24) -> 0 | P24: =O24/$O$10 -> 0
A25: 減価償却費 | O25: =SUM(C25:N25) -> 0
A26: 賃借料 | O26: =SUM(C26:N26) -> 0
A27: 地代家賃 | C27: 217000 | D27: 217000 | E27: 217000 | F27: 217000 | G27: 367000 | H27: 367000 | I27: 367000 | J27: 367000 | K27: 367000 | O27: =SUM(C27:N27) -> 2703000
A28: リース料 | O28: =SUM(C28:N28) -> 0
A29: 修繕費 | O29: =SUM(C29:N29) -> 0
A30: 保険料 | C30: 10270 | D30: 10270 | E30: 10270 | F30: 10270 | G30: 10270 | H30: 10270 | I30: 10270 | J30: 10270 | K30: 10270 | O30: =SUM(C30:N30) -> 92430
A31: 水道光熱費 | B31: 0 | O31: =SUM(C31:N31) -> 0
A32: 消耗品費 | B32: 0 | C32: 27530 | D32: 29515 | E32: 11798 | F32: 11204 | G32: 12816 | H32: 12173 | I32: 2340 | J32: 100 | K32: 12290 | O32: =SUM(C32:N32) -> 119766 | P32: =O32/$O$10 -> 0.0045071466
A33: 租税公課 | C33: 7000 | O33: =SUM(C33:N33) -> 7000
A34: 広告宣伝費 | O34: =SUM(C34:N34) -> 0
A35: 支払手数料 | B35: 0 | C35: 5700 | D35: 7550 | E35: 8000 | F35: 7850 | G35: 6850 | H35: 7250 | I35: 34150 | J35: 38930 | K35: 38960 | O35: =SUM(C35:N35) -> 155240
A36: 教育費 | O36: =SUM(C36:N36) -> 0
A37: 新聞図書費 | F37: 86182 | O37: =SUM(C37:N37) -> 86182
B38: 0 | O38: =SUM(C38:N38) -> 0
A39: 管理諸費 | C39: 30000 | D39: 30000 | E39: 150000 | F39: 50000 | G39: 50000 | H39: 50000 | I39: 50000 | J39: 69000 | K39: 62000 | O39: =SUM(C39:N39) -> 541000 | P39: =O39/$O$10 -> 0.02035942
A40: 雑費 | E40: 1364 | O40: =SUM(C40:N40) -> 1364
O41: =SUM(C41:N41) -> 0
A42: 販売管理費合計 | C42: =SUM(C12:C41) -> 3574569 | D42: =SUM(D12:D41) -> 3667371 | E42: =SUM(E12:E41) -> 3601356 | F42: =SUM(F12:F41) -> 4197394 | G42: =SUM(G12:G41) -> 3982018 | H42: =SUM(H12:H41) -> 3796108 | I42: =SUM(I12:I41) -> 3258457 | J42: =SUM(J12:J41) -> 3604547 | ... N42: =SUM(N12:N41) -> 0 | O42: =SUM(C42:N42) -> 35049825 | P42: =O42/$O$10 -> 1.3190279
A43: 営業利益 | C43: =C10-C42 -> -406972 | D43: =D10-D42 -> -244843 | E43: =E10-E42 -> -746557 | F43: =F10-F42 -> -680451 | G43: =G10-G42 -> -1113282 | H43: =H10-H42 -> -1210636 | I43: =I10-I42 -> -748440 | J43: =J10-J42 -> -1078487 | ... O43: =O10-O42 -> -8477359 | P43: =O43/$O$10 -> -0.31902794
A44: 支払利息 | C44: 10355 | E44: 9697 | F44: 5260 | H44: 5753 | I44: 8711 | J44: 5095 | K44: 4931 | O44: =SUM(C44:N44) -> 49802
A45: 雑損失 | O45: =SUM(C45:N45) -> 0
A46: 受取利息 雑収入 | C46: 77636 | D46: 78459 | E46: 67823 | F46: 75273 | G46: 67636 | H46: 63273 | I46: 59091 | J46: 51561 | K46: 63273 | O46: =SUM(C46:N46) -> 604025
A47: 経常利益 | C47: =C43-C44-C45+C46 -> -339691 | D47: =D43-D44-D45+D46 -> -166384 | E47: =E43-E44-E45+E46 -> -688431 | F47: =F43-F44-F45+F46 -> -610438 | G47: =G43-G44-G45+G46 -> -1045646 | H47: =H43-H44-H45+H46 -> -1153116 | I47: =I43-I44-I45+I46 -> -698060 | J47: =J43-J44-J45+J46 -> -1032021 | ... O47: =O43-O44-O45+O46 -> -7923136 | P47: =O47/$O$10 -> -0.2981709
A48: 特別利益 | O48: =SUM(C48:N48) -> 0
A49: 特別損失 | O49: =SUM(C49:N49) -> 0
A50: 税引前当期純利益 | C50: =C47+C48-C49 -> -339691 | D50: =D47+D48-D49 -> -166384 | E50: =E47+E48-E49 -> -688431 | F50: =F47+F48-F49 -> -610438 | G50: =G47+G48-G49 -> -1045646 | H50: =H47+H48-H49 -> -1153116 | I50: =I47+I48-I49 -> -698060 | J50: =J47+J48-J49 -> -1032021 | ... O50: =O47+O48-O49 -> -7923136 | P50: =O50/$O$10 -> -0.2981709
A51: 法人税 | B51: 0.33 | O51: =IF(O50>=0,O50*30%+70000,70000) -> 70000 | P51: =O51/$O$10 -> 0.0026343058
A52: 税引後当期純利益 | O52: =O50-O51 -> -7993136 | P52: =O52/$O$10 -> -0.3008052
B57: 月別 Ａ型 | C57: 18 | D57: 23 | E57: 18 | F57: 18 | G57: 17 | H57: 20 | I57: 20 | J57: 14 | K57: =K63*K64*K65*K66 -> 1528477.8 | L57: =L63*L64*L65*L66 -> 1601262.4 | M57: =M63*M64*M65*M66 -> 1601262.4 | N57: =N63*N64*N65*N66 -> 1601262.4
B58: 特開金対象人数 | L58: 11 | M58: 2 | N58: 1
B60: 月別 Ｂ型 | H60: 2 | I60: 3 | J60: 3 | K60: =K69*K70*K71*K72 -> 334237.05 | L60: =L69*L70*L71*L72 -> 350153.1 | M60: =M69*M70*M71*M72 -> 350153.1 | N60: =N69*N70*N71*N72 -> 350153.1
B62: A型
B63: 開所日数 | K63: 21 | L63: 22 | M63: 22 | N63: 22
B64: 出勤予測率 | K64: 0.8 | L64: 0.8 | M64: 0.8 | N64: 0.8
B65: 在籍Ａ型利用者数 | K65: 14 | L65: 14 | M65: 14 | N65: 14
B66: 一日当たり単位 | K66: ='単位計算'!$C$9 -> 6498.63 | L66: ='単位計算'!$C$9 -> 6498.63 | M66: ='単位計算'!$C$9 -> 6498.63 | N66: ='単位計算'!$C$9 -> 6498.63
B68: Ｂ型
B69: 開所日数 | K69: 21 | L69: 22 | M69: 22 | N69: 22
B70: 出勤予測率 | K70: 0.5 | L70: 0.5 | M70: 0.5 | N70: 0.5
B71: 在籍Ｂ型利用者数 | K71: 5 | L71: 5 | M71: 5 | N71: 5
B72: 一日当たり単位 | K72: ='単位計算'!$G$9 -> 6366.42 | L72: ='単位計算'!$G$9 -> 6366.42 | M72: ='単位計算'!$G$9 -> 6366.42 | N72: ='単位計算'!$G$9 -> 6366.42
B75: 処遇改善手当予測

Sheet 予測PL (2023)
B1: 変動費率 | C1: 7月実績 | D1: 8月実績 | E1: 9月実績 | F1: 10月実績 | G1: 11月実績 | H1: 12月実績 | I1: 1月実績 | J1: 2月実績 | K1: 3月実績 | L1: 4月実績 | M1: 5月実績 | N1: 6月 | O1: 累計
O2: =SUM(C2:N2) -> 0
A3: 売上 | C3: 507273 | D3: 367202 | E3: 355174 | F3: 343678 | G3: 310741 | H3: 305926 | I3: 198380 | L3: 318182 | O3: =SUM(C3:N3) -> 2706556 | P3: =O3/$O$3 -> 1
A4: 売上原価 | C4: 47776 | D4: 20813 | E4: 7576 | F4: 21859 | G4: 14718 | H4: 31386 | I4: 198380 | O4: =SUM(C4:N4) -> 342508 | P4: =O4/$O$3 -> 0.12654754
A5: 売上総利益 | C5: =C2+C3-C4 -> 459497 | D5: =D2+D3-D4 -> 346389 | E5: =E2+E3-E4 -> 347598 | F5: =F2+F3-F4 -> 321819 | G5: =G2+G3-G4 -> 296023 | H5: =H2+H3-H4 -> 274540 | I5: =I2+I3-I4 -> 0 | J5: =J2+J3-J4 -> 0 | ... N5: =N2+N3-N4 -> 0 | O5: =SUM(C5:N5) -> 2364048
O6: =SUM(C6:N6) -> 0
A7: 役員報酬 | O7: =SUM(C7:N7) -> 0 | P7: =O7/$O$5 -> 0
A8: 給与手当 | O8: =SUM(C8:N8) -> 0
A9: 雑給 | O9: =SUM(C9:N9) -> 0 | P9: =O9/$O$5 -> 0
A10: 法定福利費 | B10: 0 | O10: =SUM(C10:N10) -> 0
A11: 福利厚生費 | O11: =SUM(C11:N11) -> 0
A12: 業務委託費 | C12: 272727 | D12: 318182 | E12: 318182 | F12: 318182 | G12: 318182 | H12: 318182 | O12: =SUM(C12:N12) -> 1863637
A13: 労務委託費 | O13: =SUM(C13:N13) -> 0
A14: 旅費交通費 | O14: =SUM(C14:N14) -> 0
A15: 通信費 | D15: 85 | O15: =SUM(C15:N15) -> 85 | P15: =O15/$O$5 -> 3.5955277e-05
A16: 開発費 | O16: =SUM(C16:N16) -> 0
A17: 交際費 | O17: =SUM(C17:N17) -> 0 | P17: =O17/$O$5 -> 0
A18: 会議費 | O18: =SUM(C18:N18) -> 0
A19: 戦略費 | O19: =SUM(C19:N19) -> 0 | P19: =O19/$O$5 -> 0
A20: 減価償却費 | O20: =SUM(C20:N20) -> 0
A21: 賃借料 | O21: =SUM(C21:N21) -> 0
A22: 地代家賃 | L22: 26065 | M22: 17000 | N22: 17000 | O22: =SUM(C22:N22) -> 60065
A23: リース料 | O23: =SUM(C23:N23) -> 0
A24: 修繕費 | O24: =SUM(C24:N24) -> 0
A25: 保険料 | L25: 13480 | M25: 21420 | N25: 10710 | O25: =SUM(C25:N25) -> 45610
A26: 水道光熱費 | B26: 0 | O26: =SUM(C26:N26) -> 0
A27: 消耗品費 | B27: 0 | C27: 8737 | E27: 5940 | F27: 45780 | O27: =SUM(C27:N27) -> 60457 | P27: =O27/$O$5 -> 0.025573508
A28: 租税公課 | L28: 13690 | O28: =SUM(C28:N28) -> 13690
A29: 広告宣伝費 | O29: =SUM(C29:N29) -> 0
A30: 支払手数料 | B30: 0 | C30: 32650 | D30: 32300 | E30: 31800 | F30: 2100 | G30: 2100 | H30: 92709 | I30: 1400 | J30: 1400 | K30: 1400 | L30: 40950 | M30: 1400 | N30: 1750 | O30: =SUM(C30:N30) -> 241959
A31: 教育費 | O31: =SUM(C31:N31) -> 0
A32: 新聞図書費 | O32: =SUM(C32:N32) -> 0
A33: 備品費 | B33: 0 | O33: =SUM(C33:N33) -> 0
A34: 管理諸費 エスクリエイト | C34: 30000 | D34: 30000 | E34: 130000 | F34: 30000 | G34: 30000 | H34: 30000 | I34: 30000 | J34: 30000 | K34: 30000 | L34: 30000 | M34: 30000 | N34: 30000 | O34: =SUM(C34:N34) -> 460000 | P34: =O34/$O$5 -> 0.1945815
A35: 雑費 | O35: =SUM(C35:N35) -> 0
O36: =SUM(C36:N36) -> 0
A37: 販売管理費合計 | C37: =SUM(C7:C36) -> 344114 | D37: =SUM(D7:D36) -> 380567 | E37: =SUM(E7:E36) -> 485922 | F37: =SUM(F7:F36) -> 396062 | G37: =SUM(G7:G36) -> 350282 | H37: =SUM(H7:H36) -> 440891 | I37: =SUM(I7:I36) -> 31400 | J37: =SUM(J7:J36) -> 31400 | ... N37: =SUM(N7:N36) -> 59460 | O37: =SUM(C37:N37) -> 2745503 | P37: =O37/$O$5 -> 1.1613567
A38: 営業利益 | C38: =C5-C37 -> 115383 | D38: =D5-D37 -> -34178 | E38: =E5-E37 -> -138324 | F38: =F5-F37 -> -74243 | G38: =G5-G37 -> -54259 | H38: =H5-H37 -> -166351 | I38: =I5-I37 -> -31400 | J38: =J5-J37 -> -31400 | ... O38: =O5-O37 -> -381455 | P38: =O38/$O$5 -> -0.16135671
A39: 支払利息 | O39: =SUM(C39:N39) -> 0
A40: 雑損失 | O40: =SUM(C40:N40) -> 0
A41: 受取利息 雑収入 | D41: 31 | J41: 23 | O41: =SUM(C41:N41) -> 54
A42: 経常利益 | C42: =C38-C39-C40+C41 -> 115383 | D42: =D38-D39-D40+D41 -> -34147 | E42: =E38-E39-E40+E41 -> -138324 | F42: =F38-F39-F40+F41 -> -74243 | G42: =G38-G39-G40+G41 -> -54259 | H42: =H38-H39-H40+H41 -> -166351 | I42: =I38-I39-I40+I41 -> -31400 | J42: =J38-J39-J40+J41 -> -31377 | ... O42: =O38-O39-O40+O41 -> -381401 | P42: =O42/$O$5 -> -0.16133386
A43: 特別利益 | O43: =SUM(C43:N43) -> 0
A44: 特別損失 | O44: =SUM(C44:N44) -> 0
A45: 税引前当期純利益 | C45: =C42+C43-C44 -> 115383 | D45: =D42+D43-D44 -> -34147 | E45: =E42+E43-E44 -> -138324 | F45: =F42+F43-F44 -> -74243 | G45: =G42+G43-G44 -> -54259 | H45: =H42+H43-H44 -> -166351 | I45: =I42+I43-I44 -> -31400 | J45: =J42+J43-J44 -> -31377 | ... O45: =O42+O43-O44 -> -381401 | P45: =O45/$O$5 -> -0.16133386
A46: 法人税 | B46: 0.33 | P46: =O46/$O$5 -> 0
A47: 税引後当期純利益 | O47: =O45-O46 -> -381401 | P47: =O47/$O$5 -> -0.16133386
A50: 変動費率 | B50: =SUM(B4:B36) -> 0 | R50: 消費税
A51: 固定比率 | B51: =100%-B50 -> 1 | R51: 売上 | S51: =O3 -> 2706556
R52: 国税 | S52: =S51*T52 -> 211111.37 | T52: 0.078
R53: 仕入 | S53: =S52*T53 -> 126666.82 | T53: 0.6
R54: 差し引き税額 | S54: =S52-S53 -> 84444.547
A55: 売上内訳 | B55: ｅｓエンター | R55: 地方消費税 | S55: =S54*22/78 -> 23817.693

Sheet 予測PL (2022)
B1: 変動費率 | C1: 7月実際 | D1: 8月実際 | E1: 9月実際 | F1: 10月実際 | G1: 11月実際 | H1: 12月実際 | I1: 1月実際 | J1: 2月実際 | K1: 3月実際 | L1: 4月実際 | M1: 5月 | N1: 6月 | O1: 累計
O2: =SUM(C2:N2) -> 0
A3: 売上 | C3: 320000 | D3: 320000 | E3: 320000 | F3: 320000 | G3: 320000 | H3: 320000 | I3: 320000 | J3: 320000 | K3: 320000 | L3: 320000 | M3: 320000 | N3: 320000 | O3: =SUM(C3:N3) -> 3840000 | P3: =O3/$O$3 -> 1
A4: 売上原価 | C4: 10000 | D4: 10000 | E4: 10000 | F4: 10000 | G4: 10000 | H4: 10000 | I4: 10000 | J4: 10000 | K4: 10000 | L4: 10000 | M4: 10000 | N4: 10000 | O4: =SUM(C4:N4) -> 120000 | P4: =O4/$O$3 -> 0.03125
A5: 売上総利益 | C5: =C2+C3-C4 -> 310000 | D5: =D2+D3-D4 -> 310000 | E5: =E2+E3-E4 -> 310000 | F5: =F2+F3-F4 -> 310000 | G5: =G2+G3-G4 -> 310000 | H5: =H2+H3-H4 -> 310000 | I5: 352645 | J5: =J2+J3-J4 -> 310000 | K5: 313422 | L5: 167041 | M5: 222771 | N5: 307299 | O5: =O2+O3-O4 -> 3720000
O6: =SUM(C6:N6) -> 0
A7: 役員報酬 | O7: =SUM(C7:N7) -> 0 | P7: =O7/$O$5 -> 0
A8: 給与手当 | O8: =SUM(C8:N8) -> 0
A9: 雑給 | O9: =SUM(C9:N9) -> 0 | P9: =O9/$O$5 -> 0
A10: 法定福利費 | B10: 0 | O10: =SUM(C10:N10) -> 0
A11: 福利厚生費 | O11: =SUM(C11:N11) -> 0
A12: 業務委託費 | C12: 227273 | D12: 227273 | E12: 227273 | F12: 227273 | G12: 227273 | H12: 227273 | I12: 272727 | J12: 272727 | K12: 272727 | L12: 272727 | M12: 272727 | N12: 272727 | O12: =SUM(C12:N12) -> 3000000
A13: 労務委託費 | O13: =SUM(C13:N13) -> 0
A14: 旅費交通費 | O14: =SUM(C14:N14) -> 0
A15: 通信費 | O15: =SUM(C15:N15) -> 0 | P15: =O15/$O$5 -> 0
A16: 開発費 | O16: =SUM(C16:N16) -> 0
A17: 交際費 | O17: =SUM(C17:N17) -> 0 | P17: =O17/$O$5 -> 0
A18: 会議費 | O18: =SUM(C18:N18) -> 0
A19: 戦略費 | O19: =SUM(C19:N19) -> 0 | P19: =O19/$O$5 -> 0
A20: 減価償却費 | O20: =SUM(C20:N20) -> 0
A21: 賃借料 | O21: =SUM(C21:N21) -> 0
A22: 地代家賃 | O22: =SUM(C22:N22) -> 0
A23: リース料 | O23: =SUM(C23:N23) -> 0
A24: 修繕費 | O24: =SUM(C24:N24) -> 0
A25: 保険料 | O25: =SUM(C25:N25) -> 0
A26: 水道光熱費 | B26: 0 | O26: =SUM(C26:N26) -> 0
A27: 消耗品費 | B27: 0 | L27: 64507 | M27: 10207 | N27: 9232 | O27: =SUM(C27:N27) -> 83946 | P27: =O27/$O$5 -> 0.022566129
A28: 租税公課 | D28: 4000 | F28: 1000 | K28: 600 | O28: =SUM(C28:N28) -> 5600
A29: 広告宣伝費 | O29: =SUM(C29:N29) -> 0
A30: 支払手数料 | B30: 0 | C30: 5800 | D30: 5600 | E30: 5900 | F30: 3350 | G30: 2600 | H30: 2300 | I30: 2150 | J30: 2150 | K30: 1800 | L30: 2200 | M30: 2850 | N30: 2400 | O30: =SUM(C30:N30) -> 39100
A31: 教育費 | O31: =SUM(C31:N31) -> 0
A32: 新聞図書費 | O32: =SUM(C32:N32) -> 0
A33: 備品費 | B33: 0 | O33: =SUM(C33:N33) -> 0
A34: 管理諸費 エスクリエイト | C34: 30000 | D34: 30000 | E34: 130000 | F34: 30000 | G34: 30000 | H34: 30000 | I34: 30000 | J34: 30000 | K34: 30000 | L34: 30000 | M34: 30000 | N34: 30000 | O34: =SUM(C34:N34) -> 460000 | P34: =O34/$O$5 -> 0.12365591
A35: 雑費 | L35: 17428 | O35: =SUM(C35:N35) -> 17428
A37: 販売管理費合計 | C37: =SUM(C7:C36) -> 263073 | D37: =SUM(D7:D36) -> 266873 | E37: =SUM(E7:E36) -> 363173 | F37: =SUM(F7:F36) -> 261623 | G37: =SUM(G7:G36) -> 259873 | H37: =SUM(H7:H36) -> 259573 | I37: =SUM(I7:I36) -> 304877 | J37: =SUM(J7:J36) -> 304877 | ... O37: =SUM(O7:O36) -> 3606074 | P37: =O37/$O$5 -> 0.96937473
A38: 営業利益 | C38: =C5-C37 -> 46927 | D38: =D5-D37 -> 43127 | E38: =E5-E37 -> -53173 | F38: =F5-F37 -> 48377 | G38: =G5-G37 -> 50127 | H38: =H5-H37 -> 50427 | I38: 47768 | J38: =J5-J37 -> 5123 | K38: 8295 | L38: -219821 | M38: -93013 | N38: -7060 | O38: =O5-O37 -> 113926 | P38: =O38/$O$5 -> 0.030625269
A39: 支払利息 | O39: =SUM(C39:N39) -> 0
A40: 雑損失 | O40: =SUM(C40:N40) -> 0
A41: 受取利息 雑収入 | J41: 30 | O41: =SUM(C41:N41) -> 30
A42: 経常利益 | C42: =C38-C39-C40+C41 -> 46927 | D42: =D38-D39-D40+D41 -> 43127 | E42: =E38-E39-E40+E41 -> -53173 | F42: =F38-F39-F40+F41 -> 48377 | G42: =G38-G39-G40+G41 -> 50127 | H42: =H38-H39-H40+H41 -> 50427 | I42: 47768 | J42: =J38-J39-J40+J41 -> 5153 | K42: 8295 | L42: -219821 | M42: 906987 | N42: -7060 | O42: =O38-O39-O40+O41 -> 113956 | P42: =O42/$O$5 -> 0.030633333
A43: 特別利益 | O43: =SUM(C43:N43) -> 0
A44: 特別損失 | O44: =SUM(C44:N44) -> 0
A45: 税引前当期純利益 | C45: =C42+C43-C44 -> 46927 | D45: =D42+D43-D44 -> 43127 | E45: =E42+E43-E44 -> -53173 | F45: =F42+F43-F44 -> 48377 | G45: =G42+G43-G44 -> 50127 | H45: =H42+H43-H44 -> 50427 | I45: 47768 | J45: =J42+J43-J44 -> 5153 | K45: 8295 | L45: -219821 | M45: 906987 | N45: -7060 | O45: =O42+O43-O44 -> 113956 | P45: =O45/$O$5 -> 0.030633333
A46: 法人税 | B46: 0.33 | P46: =O46/$O$5 -> 0
A47: 税引後当期純利益 | O47: =O45-O46 -> 113956 | P47: =O47/$O$5 -> 0.030633333
A50: 変動費率 | B50: =SUM(B4:B36) -> 0 | R50: 消費税
A51: 固定比率 | B51: =100%-B50 -> 1 | R51: 売上 | S51: =O3 -> 3840000
R52: 国税 | S52: =S51*T52 -> 299520 | T52: 0.078
R53: 仕入 | S53: =S52*T53 -> 179712 | T53: 0.6
R54: 差し引き税額 | S54: =S52-S53 -> 119808
A55: 売上内訳 | B55: ｅｓエンター | C55: 2604212 | D55: 2946348 | E55: 2777697 | R55: 地方消費税 | S55: =S54*22/78 -> 33792

Sheet 予測PL (2021)
B1: 変動費率 | C1: 7月実際 | D1: 8月実際 | E1: 9月実際 | F1: 10月実際 | G1: 11月実際 | H1: 12月実際 | I1: 1月実際 | J1: 2月実際 | K1: 3月実際 | L1: 4月実際 | M1: 5月 | N1: 6月 | O1: 累計
O2: =SUM(C2:N2) -> 0
A3: 売上 | D3: 82000 | E3: 119363 | F3: 388107 | G3: 297878 | H3: 321334 | I3: 326856 | J3: 310213 | K3: 323164 | L3: 320194 | M3: 302222 | N3: 316667 | O3: =SUM(C3:N3) -> 3107998 | P3: =O3/$O$3 -> 1
A4: 売上原価 | D4: 47991 | E4: 100227 | F4: 68268 | G4: 44669 | H4: 53656 | I4: -25789 | J4: 68015 | K4: 9742 | L4: 153153 | M4: 79451 | N4: 9368 | O4: =SUM(C4:N4) -> 608751 | P4: =O4/$O$3 -> 0.19586596
A5: 売上総利益 | C5: =C2+C3-C4 -> 0 | D5: =D2+D3-D4 -> 34009 | E5: =E2+E3-E4 -> 19136 | F5: =F2+F3-F4 -> 319839 | G5: =G2+G3-G4 -> 253209 | H5: =H2+H3-H4 -> 267678 | I5: 352645 | J5: =J2+J3-J4 -> 242198 | K5: 313422 | L5: 167041 | M5: 222771 | N5: 307299 | O5: =O2+O3-O4 -> 2499247
O6: =SUM(C6:N6) -> 0
A7: 役員報酬 | O7: =SUM(C7:N7) -> 0 | P7: =O7/$O$5 -> 0
A8: 給与手当 | O8: =SUM(C8:N8) -> 0
A9: 雑給 | O9: =SUM(C9:N9) -> 0 | P9: =O9/$O$5 -> 0
A10: 法定福利費 | B10: 0 | C10: 54574 | O10: =SUM(C10:N10) -> 54574
A11: 福利厚生費 | O11: =SUM(C11:N11) -> 0
A12: 業務委託費 | C12: 181818 | D12: 181818 | E12: 181818 | F12: 227273 | G12: 227273 | H12: 227273 | I12: 272727 | J12: 272727 | K12: 272727 | L12: 272727 | M12: 272727 | N12: 272727 | O12: =SUM(C12:N12) -> 2863635
A13: 労務委託費 | O13: =SUM(C13:N13) -> 0
A14: 旅費交通費 | O14: =SUM(C14:N14) -> 0
A15: 通信費 | O15: =SUM(C15:N15) -> 0 | P15: =O15/$O$5 -> 0
A16: 開発費 | O16: =SUM(C16:N16) -> 0
A17: 交際費 | O17: =SUM(C17:N17) -> 0 | P17: =O17/$O$5 -> 0
A18: 会議費 | O18: =SUM(C18:N18) -> 0
A19: 戦略費 | O19: =SUM(C19:N19) -> 0 | P19: =O19/$O$5 -> 0
A20: 減価償却費 | O20: =SUM(C20:N20) -> 0
A21: 賃借料 | O21: =SUM(C21:N21) -> 0
A22: 地代家賃 | O22: =SUM(C22:N22) -> 0
A23: リース料 | O23: =SUM(C23:N23) -> 0
A24: 修繕費 | O24: =SUM(C24:N24) -> 0
A25: 保険料 | O25: =SUM(C25:N25) -> 0
A26: 水道光熱費 | B26: 0 | O26: =SUM(C26:N26) -> 0
A27: 消耗品費 | B27: 0 | L27: 64507 | M27: 10207 | N27: 9232 | O27: =SUM(C27:N27) -> 83946 | P27: =O27/$O$5 -> 0.033588517
A28: 租税公課 | D28: 4000 | F28: 1000 | K28: 600 | O28: =SUM(C28:N28) -> 5600
A29: 広告宣伝費 | O29: =SUM(C29:N29) -> 0
A30: 支払手数料 | B30: 0 | C30: 5800 | D30: 5600 | E30: 5900 | F30: 3350 | G30: 2600 | H30: 2300 | I30: 2150 | J30: 2150 | K30: 1800 | L30: 2200 | M30: 2850 | N30: 2400 | O30: =SUM(C30:N30) -> 39100
A31: 教育費 | O31: =SUM(C31:N31) -> 0
A32: 新聞図書費 | O32: =SUM(C32:N32) -> 0
A33: 備品費 | B33: 0 | O33: =SUM(C33:N33) -> 0
A34: 管理諸費 エスクリエイト | C34: 50000 | D34: 30000 | E34: 130000 | F34: 30000 | G34: 30000 | H34: 30000 | I34: 30000 | J34: 30000 | K34: 30000 | L34: 30000 | M34: 30000 | N34: 30000 | O34: =SUM(C34:N34) -> 480000 | P34: =O34/$O$5 -> 0.19205785
A35: 雑費 | L35: 17428 | O35: =SUM(C35:N35) -> 17428
A37: 販売管理費合計 | C37: =SUM(C7:C36) -> 292192 | D37: =SUM(D7:D36) -> 221418 | E37: =SUM(E7:E36) -> 317718 | F37: =SUM(F7:F36) -> 261623 | G37: =SUM(G7:G36) -> 259873 | H37: =SUM(H7:H36) -> 259573 | I37: =SUM(I7:I36) -> 304877 | J37: =SUM(J7:J36) -> 304877 | ... O37: =SUM(O7:O36) -> 3544283 | P37: =O37/$O$5 -> 1.4181403
A38: 営業利益 | C38: =C5-C37 -> -292192 | D38: =D5-D37 -> -187409 | E38: =E5-E37 -> -298582 | F38: =F5-F37 -> 58216 | G38: =G5-G37 -> -6664 | H38: =H5-H37 -> 8105 | I38: 47768 | J38: =J5-J37 -> -62679 | K38: 8295 | L38: -219821 | M38: -93013 | N38: -7060 | O38: =O5-O37 -> -1045036 | P38: =O38/$O$5 -> -0.41814034
A39: 支払利息 | O39: =SUM(C39:N39) -> 0
A40: 雑損失 | O40: =SUM(C40:N40) -> 0
A41: 受取利息 雑収入 | C41: 200000 | D41: 200034 | E41: 200000 | F41: 400000 | J41: 30 | M41: 1000000 | O41: =SUM(C41:N41) -> 2000064
A42: 経常利益 | C42: =C38-C39-C40+C41 -> -92192 | D42: =D38-D39-D40+D41 -> 12625 | E42: =E38-E39-E40+E41 -> -98582 | F42: =F38-F39-F40+F41 -> 458216 | G42: =G38-G39-G40+G41 -> -6664 | H42: =H38-H39-H40+H41 -> 8105 | I42: 47768 | J42: =J38-J39-J40+J41 -> -62649 | K42: 8295 | L42: -219821 | M42: 906987 | N42: -7060 | O42: =O38-O39-O40+O41 -> 955028 | P42: =O42/$O$5 -> 0.3821263
A43: 特別利益 | O43: =SUM(C43:N43) -> 0
A44: 特別損失 | O44: =SUM(C44:N44) -> 0
A45: 税引前当期純利益 | C45: =C42+C43-C44 -> -92192 | D45: =D42+D43-D44 -> 12625 | E45: =E42+E43-E44 -> -98582 | F45: =F42+F43-F44 -> 458216 | G45: =G42+G43-G44 -> -6664 | H45: =H42+H43-H44 -> 8105 | I45: 47768 | J45: =J42+J43-J44 -> -62649 | K45: 8295 | L45: -219821 | M45: 906987 | N45: -7060 | O45: =O42+O43-O44 -> 955028 | P45: =O45/$O$5 -> 0.3821263
A46: 法人税 | B46: 0.33 | P46: =O46/$O$5 -> 0
A47: 税引後当期純利益 | O47: =O45-O46 -> 955028 | P47: =O47/$O$5 -> 0.3821263
A50: 変動費率 | B50: =SUM(B4:B36) -> 0 | R50: 消費税
A51: 固定比率 | B51: =100%-B50 -> 1 | R51: 売上 | S51: =O3 -> 3107998
R52: 国税 | S52: =S51*T52 -> 242423.84 | T52: 0.078
R53: 仕入 | S53: =S52*T53 -> 145454.31 | T53: 0.6
R54: 差し引き税額 | S54: =S52-S53 -> 96969.538
A55: 売上内訳 | B55: ｅｓエンター | C55: 2604212 | D55: 2946348 | E55: 2777697 | R55: 地方消費税 | S55: =S54*22/78 -> 27350.382

Sheet 予算PL (2021)
A1: 税抜き | B1: 変動費率 | C1: 7月 | D1: 8月 | E1: 9月 | F1: 10月 | G1: 11月 | H1: 12月 | I1: 1月 | J1: 2月 | K1: 3月 | L1: 4月 | M1: 5月 | N1: 6月 | O1: 累計
A3: 売上 | H3: 400000 | I3: 400000 | J3: 300000 | K3: 300000 | O3: =SUM(C3:N3) -> 1400000 | P3: =O3/$O$3 -> 1
A4: 売上原価 | B4: 0.2 | C4: =C3*$B$4 -> 0 | D4: =D3*$B$4 -> 0 | E4: =E3*$B$4 -> 0 | F4: =F3*$B$4 -> 0 | G4: =G3*$B$4 -> 0 | H4: =H3*$B$4 -> 80000 | I4: =I3*$B$4 -> 80000 | O4: =SUM(C4:N4) -> 160000 | P4: =O4/$O$3 -> 0.11428571
A5: 売上総利益 | C5: =C2+C3-C4 -> 0 | D5: =D2+D3-D4 -> 0 | E5: =E2+E3-E4 -> 0 | F5: =F2+F3-F4 -> 0 | G5: =G2+G3-G4 -> 0 | H5: =H2+H3-H4 -> 320000 | I5: =I2+I3-I4 -> 320000 | J5: =J2+J3-J4 -> 300000 | ... O5: =O2+O3-O4 -> 1240000
O6: =SUM(C6:N6) -> 0
A7: 役員報酬 | O7: =SUM(C7:N7) -> 0 | P7: =O7/$O$5 -> 0
A8: 給与手当 | O8: =SUM(C8:N8) -> 0
A9: 雑給 | O9: =SUM(C9:N9) -> 0 | P9: =O9/$O$5 -> 0
A10: 法定福利費 | B10: 0 | O10: =SUM(C10:N10) -> 0
A11: 福利厚生費 | O11: =SUM(C11:N11) -> 0
A12: 業務委託費 | C12: 181818 | D12: 181818 | E12: 181818 | F12: 181818 | G12: 181818 | H12: 227272 | I12: 227272 | J12: 227272 | K12: 227272 | O12: =SUM(C12:N12) -> 1818178
A13: 労務委託費 | O13: =SUM(C13:N13) -> 0
A14: 旅費交通費 | O14: =SUM(C14:N14) -> 0
A15: 通信費 | O15: =SUM(C15:N15) -> 0 | P15: =O15/$O$5 -> 0
A16: 開発費 | O16: =SUM(C16:N16) -> 0
A17: 交際費 | O17: =SUM(C17:N17) -> 0 | P17: =O17/$O$5 -> 0
A18: 会議費 | O18: =SUM(C18:N18) -> 0
A19: 戦略費 | O19: =SUM(C19:N19) -> 0 | P19: =O19/$O$5 -> 0
A20: 減価償却費 | O20: =SUM(C20:N20) -> 0
A21: 賃借料 | O21: =SUM(C21:N21) -> 0
A22: 地代家賃 | O22: =SUM(C22:N22) -> 0
A23: リース料 | O23: =SUM(C23:N23) -> 0
A24: 修繕費 | O24: =SUM(C24:N24) -> 0
A25: 保険料 | O25: =SUM(C25:N25) -> 0
A26: 水道光熱費 | B26: 0 | O26: =SUM(C26:N26) -> 0
A27: 消耗品費 | B27: 0 | O27: =SUM(C27:N27) -> 0 | P27: =O27/$O$5 -> 0
A28: 租税公課 | O28: =SUM(C28:N28) -> 0
A29: 広告宣伝費 | O29: =SUM(C29:N29) -> 0
A30: 支払手数料 | C30: 5000 | D30: 5000 | E30: 5000 | F30: 5000 | G30: 5000 | H30: 5000 | I30: 5000 | J30: 5000 | K30: 5000 | L30: 5000 | M30: 5000 | N30: 5000 | O30: =SUM(C30:N30) -> 60000
A31: 教育費 | O31: =SUM(C31:N31) -> 0
A32: 新聞図書費 | O32: =SUM(C32:N32) -> 0
A33: 備品費 | B33: 0 | O33: =SUM(C33:N33) -> 0
A34: 管理諸費 エスクリエイト | C34: 50000 | D34: 50000 | E34: 50000 | F34: 50000 | G34: 50000 | H34: 30000 | I34: 30000 | J34: 30000 | K34: 30000 | L34: 30000 | M34: 30000 | N34: 30000 | O34: =SUM(C34:N34) -> 460000 | P34: =O34/$O$5 -> 0.37096774
A35: 雑費 | O35: =SUM(C35:N35) -> 0
A37: 販売管理費合計 | C37: =SUM(C7:C36) -> 236818 | D37: =SUM(D7:D36) -> 236818 | E37: =SUM(E7:E36) -> 236818 | F37: =SUM(F7:F36) -> 236818 | G37: =SUM(G7:G36) -> 236818 | H37: =SUM(H7:H36) -> 262272 | I37: =SUM(I7:I36) -> 262272 | J37: =SUM(J7:J36) -> 262272 | ... O37: =SUM(O7:O36) -> 2338178 | P37: =O37/$O$5 -> 1.8856274
A38: 営業利益 | C38: =C5-C37 -> -236818 | D38: =D5-D37 -> -236818 | E38: =E5-E37 -> -236818 | F38: =F5-F37 -> -236818 | G38: =G5-G37 -> -236818 | H38: =H5-H37 -> 57728 | I38: =I5-I37 -> 57728 | J38: =J5-J37 -> 37728 | ... O38: =O5-O37 -> -1098178 | P38: =O38/$O$5 -> -0.88562742
A39: 支払利息 | O39: =SUM(C39:N39) -> 0
A40: 雑損失 | O40: =SUM(C40:N40) -> 0
A41: 受取利息 雑収入 | M41: 1000000 | O41: =SUM(C41:N41) -> 1000000
A42: 経常利益 | C42: =C38-C39-C40+C41 -> -236818 | D42: =D38-D39-D40+D41 -> -236818 | E42: =E38-E39-E40+E41 -> -236818 | F42: =F38-F39-F40+F41 -> -236818 | G42: =G38-G39-G40+G41 -> -236818 | H42: =H38-H39-H40+H41 -> 57728 | I42: =I38-I39-I40+I41 -> 57728 | J42: =J38-J39-J40+J41 -> 37728 | ... O42: =O38-O39-O40+O41 -> -98178 | P42: =O42/$O$5 -> -0.079175806
A43: 特別利益 | O43: =SUM(C43:N43) -> 0
A44: 特別損失 | O44: =SUM(C44:N44) -> 0
A45: 税引前当期純利益 | C45: =C42+C43-C44 -> -236818 | D45: =D42+D43-D44 -> -236818 | E45: =E42+E43-E44 -> -236818 | F45: =F42+F43-F44 -> -236818 | G45: =G42+G43-G44 -> -236818 | H45: =H42+H43-H44 -> 57728 | I45: =I42+I43-I44 -> 57728 | J45: =J42+J43-J44 -> 37728 | ... O45: =O42+O43-O44 -> -98178 | P45: =O45/$O$5 -> -0.079175806
A46: 法人税 | B46: 0.33 | P46: =O46/$O$5 -> 0
A47: 税引後当期純利益 | O47: =O45-O46 -> -98178 | P47: =O47/$O$5 -> -0.079175806
A50: 変動費率 | B50: =SUM(B4:B36) -> 0.2 | I50: 事業復活支援金2019年12月の | J50: 12266344
A51: 固定比率 | B51: =100%-B50 -> 0.8 | I51: 2021年12がつの | J51: 321334
J52: =J51*5 -> 1606670
J53: =J50-J52 -> 10659674

Sheet 実際PL  (2021)
A1: 税抜 | B1: 変動費率 | C1: 7月実際 | D1: 8月実際 | E1: 9月実際 | F1: 10月実際 | G1: 11月実際 | H1: 12月実際 | I1: 1月実際 | J1: 2月実際 | K1: 3月実際 | L1: 4月実際 | M1: 5月実際 | N1: 6月実際 | O1: 累計
O2: =SUM(C2:N2) -> 0
A3: 売上 | D3: 82000 | E3: 119363 | F3: 392130 | G3: 297878 | H3: 321334 | I3: 326856 | J3: 315769 | K3: 323164 | L3: 320194 | M3: 302222 | N3: 316667 | O3: =SUM(C3:N3) -> 3117577 | P3: =O3/$O$3 -> 1
A4: 売上原価 | D4: 84310 | E4: 100227 | F4: 68268 | G4: 44669 | H4: 53656 | I4: -25789 | J4: 68015 | K4: 9742 | L4: 153153 | M4: 79451 | N4: 9368 | O4: =SUM(C4:N4) -> 645070 | P4: =O4/$O$3 -> 0.20691389
A5: 売上総利益 | C5: =C2+C3-C4 -> 0 | D5: =D2+D3-D4 -> -2310 | E5: =E2+E3-E4 -> 19136 | F5: =F2+F3-F4 -> 323862 | G5: =G2+G3-G4 -> 253209 | H5: =H2+H3-H4 -> 267678 | I5: =I2+I3-I4 -> 352645 | J5: =J2+J3-J4 -> 247754 | ... O5: =O2+O3-O4 -> 2472507
O6: =SUM(C6:N6) -> 0
A7: 役員報酬 | O7: =SUM(C7:N7) -> 0 | P7: =O7/$O$5 -> 0
A8: 給与手当 | O8: =SUM(C8:N8) -> 0
A9: 雑給 | O9: =SUM(C9:N9) -> 0 | P9: =O9/$O$5 -> 0
A10: 法定福利費 | B10: 0 | C10: 54574 | O10: =SUM(C10:N10) -> 54574
A11: 福利厚生費 | O11: =SUM(C11:N11) -> 0
A12: 業務委託費 | C12: 181818 | D12: 181818 | E12: 181818 | F12: 227273 | G12: 227273 | H12: 227273 | I12: 272727 | J12: 272727 | K12: 272727 | L12: 272727 | M12: 272727 | N12: 272727 | O12: =SUM(C12:N12) -> 2863635
A13: 労務委託費 | O13: =SUM(C13:N13) -> 0
A14: 旅費交通費 | O14: =SUM(C14:N14) -> 0
A15: 通信費 | O15: =SUM(C15:N15) -> 0 | P15: =O15/$O$5 -> 0
A16: 開発費 | O16: =SUM(C16:N16) -> 0
A17: 交際費 | O17: =SUM(C17:N17) -> 0 | P17: =O17/$O$5 -> 0
A18: 会議費 | O18: =SUM(C18:N18) -> 0
A19: 戦略費 | O19: =SUM(C19:N19) -> 0 | P19: =O19/$O$5 -> 0
A20: 減価償却費 | O20: =SUM(C20:N20) -> 0
A21: 賃借料 | O21: =SUM(C21:N21) -> 0
A22: 地代家賃 | O22: =SUM(C22:N22) -> 0
A23: リース料 | O23: =SUM(C23:N23) -> 0
A24: 修繕費 | O24: =SUM(C24:N24) -> 0
A25: 保険料 | O25: =SUM(C25:N25) -> 0
A26: 水道光熱費 | B26: 0 | O26: =SUM(C26:N26) -> 0
A27: 消耗品費 | B27: 0 | L27: 64507 | M27: 10207 | N27: 9232 | O27: =SUM(C27:N27) -> 83946 | P27: =O27/$O$5 -> 0.033951774
A28: 租税公課 | D28: 4000 | F28: 1000 | K28: 600 | O28: =SUM(C28:N28) -> 5600
A29: 広告宣伝費 | O29: =SUM(C29:N29) -> 0
A30: 支払手数料 | B30: 0 | C30: 5800 | D30: 5600 | E30: 5900 | F30: 3350 | G30: 2600 | H30: 2250 | I30: 2150 | J30: 2150 | K30: 1800 | L30: 2200 | M30: 2850 | N30: 2400 | O30: =SUM(C30:N30) -> 39050
A31: 教育費 | O31: =SUM(C31:N31) -> 0
A32: 新聞図書費 | O32: =SUM(C32:N32) -> 0
A33: 備品費 | B33: 0 | O33: =SUM(C33:N33) -> 0
A34: 管理諸費 エスクリエイト | C34: 50000 | D34: 30000 | E34: 130000 | F34: 30000 | G34: 30000 | H34: 30000 | I34: 30000 | J34: 30000 | K34: 30000 | L34: 30000 | M34: 30000 | N34: 30000 | O34: =SUM(C34:N34) -> 480000 | P34: =O34/$O$5 -> 0.19413494
A35: 雑費 | L35: 17428 | O35: =SUM(C35:N35) -> 17428
A37: 販売管理費合計 | C37: =SUM(C7:C36) -> 292192 | D37: =SUM(D7:D36) -> 221418 | E37: =SUM(E7:E36) -> 317718 | F37: =SUM(F7:F36) -> 261623 | G37: =SUM(G7:G36) -> 259873 | H37: =SUM(H7:H36) -> 259523 | I37: =SUM(I7:I36) -> 304877 | J37: =SUM(J7:J36) -> 304877 | ... O37: =SUM(O7:O36) -> 3544233 | P37: =O37/$O$5 -> 1.4334572
A38: 営業利益 | C38: =C5-C37 -> -292192 | D38: =D5-D37 -> -223728 | E38: =E5-E37 -> -298582 | F38: =F5-F37 -> 62239 | G38: =G5-G37 -> -6664 | H38: =H5-H37 -> 8155 | I38: =I5-I37 -> 47768 | J38: =J5-J37 -> -57123 | ... O38: =O5-O37 -> -1071726 | P38: =O38/$O$5 -> -0.43345722
A39: 支払利息 | O39: =SUM(C39:N39) -> 0
A40: 雑損失 | O40: =SUM(C40:N40) -> 0
A41: 受取利息 雑収入 | C41: 200000 | D41: 200034 | E41: 200000 | F41: 400000 | J41: 30 | M41: 1000000 | O41: =SUM(C41:N41) -> 2000064
A42: 経常利益 | C42: =C38-C39-C40+C41 -> -92192 | D42: =D38-D39-D40+D41 -> -23694 | E42: =E38-E39-E40+E41 -> -98582 | F42: =F38-F39-F40+F41 -> 462239 | G42: =G38-G39-G40+G41 -> -6664 | H42: =H38-H39-H40+H41 -> 8155 | I42: =I38-I39-I40+I41 -> 47768 | J42: =J38-J39-J40+J41 -> -57093 | ... O42: =O38-O39-O40+O41 -> 928338 | P42: =O42/$O$5 -> 0.37546426
A43: 特別利益 | O43: =SUM(C43:N43) -> 0
A44: 特別損失 | O44: =SUM(C44:N44) -> 0
A45: 税引前当期純利益 | C45: =C42+C43-C44 -> -92192 | D45: =D42+D43-D44 -> -23694 | E45: =E42+E43-E44 -> -98582 | F45: =F42+F43-F44 -> 462239 | G45: =G42+G43-G44 -> -6664 | H45: =H42+H43-H44 -> 8155 | I45: =I42+I43-I44 -> 47768 | J45: =J42+J43-J44 -> -57093 | ... O45: =O42+O43-O44 -> 928338 | P45: =O45/$O$5 -> 0.37546426
A46: 法人税 | B46: 0.33 | P46: =O46/$O$5 -> 0
A47: 税引後当期純利益 | O47: =O45-O46 -> 928338 | P47: =O47/$O$5 -> 0.37546426
A50: 変動費率 | B50: =SUM(B4:B36) -> 0
A51: 固定比率 | B51: =100%-B50 -> 1
A55: 売上内訳 | B55: ｅｓエンター | C55: 2604212 | D55: 2946348 | E55: 2777697
B56: goカンパニー | C56: =92593+5000 -> 97593 | D56: 97593 | E56: 97593

Sheet 予算PL
B1: 変動費率 | C1: 7月 | D1: 8月 | E1: 9月 | F1: 10月 | G1: 11月 | H1: 12月 | I1: 1月 | J1: 2月 | K1: 3月 | L1: 4月 | M1: 5月 | N1: 6月 | O1: 累計 | S1: 変動費率 | T1: 7月 | U1: 8月 | V1: 9月 | W1: 10月 | X1: 11月 | Y1: 12月 | Z1: 1月 | AA1: 2月 | AB1: 3月 | AC1: 4月 | AD1: 5月 | AE1: 6月 | AF1: 累計
A3: 売上 | C3: 800000 | D3: 800000 | E3: 800000 | F3: 800000 | G3: 800000 | H3: 800000 | I3: 800000 | J3: 800000 | K3: 800000 | L3: 800000 | M3: 800000 | N3: 500000 | O3: =SUM(C3:N3) -> 9300000 | P3: =O3/$O$3 -> 1 | R3: 売上 | T3: =292592+5000 -> 297592 | U3: 297592 | V3: 297592 | W3: 297592 | X3: 297592 | Y3: 297592 | Z3: 245909 | AA3: 245909 | AB3: 245909 | AC3: 120000 | AF3: =SUM(T3:AE3) -> 2643279
A4: 売上原価 | C4: =C3*$B$4 -> 0 | D4: =D3*$B$4 -> 0 | E4: =E3*$B$4 -> 0 | F4: =F3*$B$4 -> 0 | G4: =G3*$B$4 -> 0 | H4: =H3*$B$4 -> 0 | I4: =I3*$B$4 -> 0 | J4: =J3*$B$4 -> 0 | ... N4: =N3*$B$4 -> 0 | O4: =SUM(C4:N4) -> 0 | P4: =O4/$O$3 -> 0 | R4: 売上原価 | T4: =T3*$B$4 -> 0 | U4: 0 | V4: 0 | W4: 0 | X4: 0 | Y4: 0 | Z4: 0 | AA4: 0 | AB4: 0 | AC4: 0 | AF4: =SUM(T4:AE4) -> 0
A5: 売上総利益 | C5: =C2+C3-C4 -> 800000 | D5: =D2+D3-D4 -> 800000 | E5: =E2+E3-E4 -> 800000 | F5: =F2+F3-F4 -> 800000 | G5: =G2+G3-G4 -> 800000 | H5: =H2+H3-H4 -> 800000 | I5: =I2+I3-I4 -> 800000 | J5: =J2+J3-J4 -> 800000 | ... O5: =O2+O3-O4 -> 9300000 | R5: 売上総利益 | T5: =T2+T3-T4 -> 297592 | U5: 2826825 | V5: 2636983 | W5: 3152392 | X5: 3170592 | Y5: 4376992 | Z5: 2999309 | AA5: 3003209 | AB5: 4158909 | AC5: 920000 | AF5: =AF2+AF3-AF4 -> 2643279
O6: =SUM(C6:N6) -> 0 | AF6: =SUM(T6:AE6) -> 0
A7: 役員報酬 | O7: =SUM(C7:N7) -> 0 | P7: =O7/$O$5 -> 0 | R7: 役員報酬 | T7: 50000 | U7: 50000 | V7: 50000 | W7: 50000 | X7: 50000 | Y7: 50000 | Z7: 50000 | AA7: 50000 | AB7: 50000 | AC7: 50000 | AF7: =SUM(T7:AE7) -> 500000
A8: 給与手当 | O8: =SUM(C8:N8) -> 0 | R8: 給与手当 | AF8: =SUM(T8:AE8) -> 0
A9: 雑給 | C9: 720000 | D9: 720000 | E9: 720000 | F9: 720000 | G9: 720000 | H9: 720000 | I9: 720000 | J9: 720000 | K9: 720000 | L9: 720000 | M9: 720000 | N9: 300000 | O9: =SUM(C9:N9) -> 8220000 | P9: =O9/$O$5 -> 0.88387097 | R9: 雑給 | T9: =T2-100000 -> -100000 | U9: 2429233 | V9: 2239391 | W9: 2754800 | X9: 2773000 | Y9: 3979400 | Z9: 2653400 | AA9: 2657300 | AB9: 3813000 | AC9: 800000 | AF9: =SUM(T9:AE9) -> 23999524
A10: 法定福利費 | B10: 0 | C10: =SUM(C7:C9)*$B$10 -> 0 | D10: =SUM(D7:D9)*$B$10 -> 0 | E10: =SUM(E7:E9)*$B$10 -> 0 | F10: =SUM(F7:F9)*$B$10 -> 0 | G10: =SUM(G7:G9)*$B$10 -> 0 | H10: =SUM(H7:H9)*$B$10 -> 0 | I10: =SUM(I7:I9)*$B$10 -> 0 | J10: =SUM(J7:J9)*$B$10 -> 0 | ... N10: =SUM(N7:N9)*$B$10 -> 0 | O10: =SUM(C10:N10) -> 0 | R10: 法定福利費 | S10: 0 | T10: =SUM(T7:T9)*$B$10 -> 0 | U10: 0 | V10: 0 | W10: 0 | X10: 0 | Y10: 0 | Z10: 0 | AA10: 0 | AB10: 0 | AC10: 0 | AF10: =SUM(T10:AE10) -> 0
A11: 福利厚生費 | O11: =SUM(C11:N11) -> 0 | R11: 福利厚生費 | AF11: =SUM(T11:AE11) -> 0
A12: 業務委託費 | J12: 190000 | K12: 190000 | L12: 190000 | M12: 190000 | N12: 190000 | O12: =SUM(C12:N12) -> 950000 | R12: 業務委託費 | AF12: =SUM(T12:AE12) -> 0
A13: 労務委託費 | O13: =SUM(C13:N13) -> 0 | R13: 労務委託費 | AF13: =SUM(T13:AE13) -> 0
A14: 旅費交通費 | C14: 80000 | D14: 80000 | E14: 80000 | F14: 80000 | G14: 80000 | H14: 80000 | I14: 80000 | J14: 80000 | K14: 80000 | L14: 80000 | M14: 80000 | N14: 80000 | O14: =SUM(C14:N14) -> 960000 | R14: 旅費交通費 | V14: 80000 | W14: 80000 | X14: 80000 | Y14: 80000 | Z14: 80000 | AA14: 80000 | AB14: 80000 | AC14: 80000 | AF14: =SUM(T14:AE14) -> 640000
A15: 通信費 | O15: =SUM(C15:N15) -> 0 | P15: =O15/$O$5 -> 0 | R15: 通信費 | T15: 18000 | U15: 18000 | V15: 18000 | W15: 18000 | X15: 18000 | Y15: 18000 | Z15: 15000 | AA15: 15000 | AB15: 15000 | AC15: 15000 | AF15: =SUM(T15:AE15) -> 168000
A16: 開発費 | O16: =SUM(C16:N16) -> 0 | R16: 開発費 | AF16: =SUM(T16:AE16) -> 0
A17: 交際費 | O17: =SUM(C17:N17) -> 0 | P17: =O17/$O$5 -> 0 | R17: 交際費 | T17: 50000 | U17: 50000 | V17: 70000 | W17: 70000 | X17: 70000 | Y17: 70000 | Z17: 70000 | AA17: 70000 | AB17: 70000 | AC17: 70000 | AF17: =SUM(T17:AE17) -> 660000
A18: 会議費 | O18: =SUM(C18:N18) -> 0 | R18: 会議費 | U18: 30000 | W18: 30000 | X18: 30000 | AC18: 30000 | AF18: =SUM(T18:AE18) -> 120000
A19: 戦略費 | O19: =SUM(C19:N19) -> 0 | P19: =O19/$O$5 -> 0 | R19: 戦略費 | T19: 50000 | U19: 50000 | V19: 30000 | W19: 30000 | X19: 30000 | Y19: 30000 | Z19: 30000 | AA19: 30000 | AB19: 30000 | AC19: 30000 | AF19: =SUM(T19:AE19) -> 340000
A20: 減価償却費 | O20: =SUM(C20:N20) -> 0 | R20: 減価償却費 | AF20: =SUM(T20:AE20) -> 0
A21: 賃借料 | O21: =SUM(C21:N21) -> 0 | R21: 賃借料 | AF21: =SUM(T21:AE21) -> 0
A22: 地代家賃 | O22: =SUM(C22:N22) -> 0 | R22: 地代家賃 | AF22: =SUM(T22:AE22) -> 0
A23: リース料 | O23: =SUM(C23:N23) -> 0 | R23: リース料 | AF23: =SUM(T23:AE23) -> 0
A24: 修繕費 | O24: =SUM(C24:N24) -> 0 | R24: 修繕費 | AF24: =SUM(T24:AE24) -> 0
A25: 保険料 | O25: =SUM(C25:N25) -> 0 | R25: 保険料 | AC25: 11810 | AF25: =SUM(T25:AE25) -> 11810
A26: 水道光熱費 | B26: 0 | C26: =C3*$B$26 -> 0 | D26: =D3*$B$26 -> 0 | E26: =E3*$B$26 -> 0 | F26: =F3*$B$26 -> 0 | G26: =G3*$B$26 -> 0 | H26: =H3*$B$26 -> 0 | I26: =I3*$B$26 -> 0 | J26: =J3*$B$26 -> 0 | ... N26: =N3*$B$26 -> 0 | O26: =SUM(C26:N26) -> 0 | R26: 水道光熱費 | S26: 0 | T26: =T3*$B$26 -> 0 | U26: 0 | V26: 0 | W26: 0 | X26: 0 | Y26: 0 | Z26: 0 | AA26: 0 | AB26: 0 | AC26: 0 | AF26: =SUM(T26:AE26) -> 0
A27: 消耗品費 | B27: 0 | O27: =SUM(C27:N27) -> 0 | P27: =O27/$O$5 -> 0 | R27: 消耗品費 | S27: 0 | T27: 2000 | U27: 2000 | V27: 1000 | W27: 1000 | X27: 1000 | Y27: 1000 | Z27: 1000 | AA27: 1000 | AB27: 1000 | AC27: 1000 | AF27: =SUM(T27:AE27) -> 12000
A28: 租税公課 | O28: =SUM(C28:N28) -> 0 | R28: 租税公課 | AF28: =SUM(T28:AE28) -> 0
A29: 広告宣伝費 | O29: =SUM(C29:N29) -> 0 | R29: 広告宣伝費 | V29: 80000 | X29: 80000 | AB29: 80000 | AF29: =SUM(T29:AE29) -> 240000
A30: 支払手数料 | C30: 10000 | D30: 10000 | E30: 10000 | F30: 10000 | G30: 10000 | H30: 10000 | I30: 10000 | J30: 10000 | K30: 10000 | L30: 10000 | M30: 10000 | N30: 10000 | O30: =SUM(C30:N30) -> 120000 | R30: 支払手数料 | S30: 0 | T30: =T3*$B$30 -> 0 | U30: 0 | V30: 11903.68 | W30: 11903.68 | X30: 11903.68 | Y30: 11903.68 | Z30: 9836.36 | AA30: 9836.36 | AB30: 9836.36 | AC30: 4800 | AF30: =SUM(T30:AE30) -> 81923.8
A31: 教育費 | O31: =SUM(C31:N31) -> 0 | R31: 教育費 | AF31: =SUM(T31:AE31) -> 0
A32: 新聞図書費 | O32: =SUM(C32:N32) -> 0 | R32: 新聞図書費 | V32: 2000 | W32: 2000 | X32: 2000 | Y32: 2000 | Z32: 2000 | AA32: 2000 | AB32: 2000 | AC32: 2000 | AF32: =SUM(T32:AE32) -> 16000
A33: 備品費 | B33: 0 | C33: =C3*$B$33 -> 0 | D33: =D3*$B$33 -> 0 | E33: =E3*$B$33 -> 0 | F33: =F3*$B$33 -> 0 | G33: =G3*$B$33 -> 0 | H33: =H3*$B$33 -> 0 | I33: =I3*$B$33 -> 0 | J33: =J3*$B$33 -> 0 | ... N33: =N3*$B$33 -> 0 | O33: =SUM(C33:N33) -> 0 | R33: 備品費 | S33: 0 | T33: =T3*$B$33 -> 0 | U33: 0 | V33: 0 | W33: 0 | X33: 0 | Y33: 0 | Z33: 0 | AA33: 0 | AB33: 0 | AC33: 0 | AF33: =SUM(T33:AE33) -> 0
A34: 管理諸費 エスクリエイト | C34: 50000 | D34: 50000 | E34: 50000 | F34: 50000 | G34: 50000 | H34: 50000 | I34: 50000 | J34: 50000 | K34: 50000 | L34: 50000 | M34: 50000 | N34: 50000 | O34: =SUM(C34:N34) -> 600000 | P34: =O34/$O$5 -> 0.064516129 | R34: 管理諸費 エスクリエイト | T34: 50000 | U34: 50000 | V34: 50000 | W34: 50000 | X34: 50000 | Y34: 50000 | Z34: 50000 | AA34: 50000 | AB34: 50000 | AC34: 50000 | AF34: =SUM(T34:AE34) -> 500000
A35: 雑費 | O35: =SUM(C35:N35) -> 0 | R35: 雑費 | T35: 90000 | AF35: =SUM(T35:AE35) -> 90000
A37: 販売管理費合計 | C37: =SUM(C7:C36) -> 860000 | D37: =SUM(D7:D36) -> 860000 | E37: =SUM(E7:E36) -> 860000 | F37: =SUM(F7:F36) -> 860000 | G37: =SUM(G7:G36) -> 860000 | H37: =SUM(H7:H36) -> 860000 | I37: =SUM(I7:I36) -> 860000 | J37: =SUM(J7:J36) -> 1050000 | ... O37: =SUM(O7:O36) -> 10850000 | P37: =O37/$O$5 -> 1.1666667 | R37: 販売管理費合計 | T37: =SUM(T7:T36) -> 210000 | U37: 2679233 | V37: 2632294.7 | W37: 3097703.7 | X37: 3195903.7 | Y37: 4292303.7 | Z37: 2961236.4 | AA37: 2965136.4 | AB37: 4200836.4 | AC37: 1144610 | AF37: =SUM(AF7:AF36) -> 27379258
A38: 営業利益 | C38: =C5-C37 -> -60000 | D38: =D5-D37 -> -60000 | E38: =E5-E37 -> -60000 | F38: =F5-F37 -> -60000 | G38: =G5-G37 -> -60000 | H38: =H5-H37 -> -60000 | I38: =I5-I37 -> -60000 | J38: =J5-J37 -> -250000 | ... O38: =O5-O37 -> -1550000 | P38: =O38/$O$5 -> -0.16666667 | R38: 営業利益 | T38: =T5-T37 -> 87592 | U38: 147592 | V38: 4688.32 | W38: 54688.32 | X38: -25311.68 | Y38: 84688.32 | Z38: 38072.64 | AA38: 38072.64 | AB38: -41927.36 | AC38: -224610 | AF38: =AF5-AF37 -> -24735979
A39: 支払利息 | O39: =SUM(C39:N39) -> 0 | R39: 支払利息 | AF39: =SUM(T39:AE39) -> 0
A40: 雑損失 | O40: =SUM(C40:N40) -> 0 | R40: 雑損失 | AF40: =SUM(T40:AE40) -> 0
A41: 受取利息 雑収入 | C41: 2000000 | O41: =SUM(C41:N41) -> 2000000 | R41: 受取利息 雑収入 | AF41: =SUM(T41:AE41) -> 0
A42: 経常利益 | C42: =C38-C39-C40+C41 -> 1940000 | D42: =D38-D39-D40+D41 -> -60000 | E42: =E38-E39-E40+E41 -> -60000 | F42: =F38-F39-F40+F41 -> -60000 | G42: =G38-G39-G40+G41 -> -60000 | H42: =H38-H39-H40+H41 -> -60000 | I42: =I38-I39-I40+I41 -> -60000 | J42: =J38-J39-J40+J41 -> -250000 | ... O42: =O38-O39-O40+O41 -> 450000 | P42: =O42/$O$5 -> 0.048387097 | R42: 経常利益 | T42: =T38-T39-T40+T41 -> 87592 | U42: 147592 | V42: 4688.32 | W42: 54688.32 | X42: -25311.68 | Y42: 84688.32 | Z42: 38072.64 | AA42: 38072.64 | AB42: -41927.36 | AC42: -224610 | AF42: =AF38-AF39-AF40+AF41 -> -24735979
A43: 特別利益 | O43: =SUM(C43:N43) -> 0 | R43: 特別利益 | AF43: =SUM(T43:AE43) -> 0
A44: 特別損失 | O44: =SUM(C44:N44) -> 0 | R44: 特別損失 | AF44: =SUM(T44:AE44) -> 0
A45: 税引前当期純利益 | C45: =C42+C43-C44 -> 1940000 | D45: =D42+D43-D44 -> -60000 | E45: =E42+E43-E44 -> -60000 | F45: =F42+F43-F44 -> -60000 | G45: =G42+G43-G44 -> -60000 | H45: =H42+H43-H44 -> -60000 | I45: =I42+I43-I44 -> -60000 | J45: =J42+J43-J44 -> -250000 | ... O45: =O42+O43-O44 -> 450000 | P45: =O45/$O$5 -> 0.048387097 | R45: 税引前当期純利益 | T45: =T42+T43-T44 -> 87592 | U45: 147592 | V45: 4688.32 | W45: 54688.32 | X45: -25311.68 | Y45: 84688.32 | Z45: 38072.64 | AA45: 38072.64 | AB45: -41927.36 | AC45: -224610 | AF45: =AF42+AF43-AF44 -> -24735979
A46: 法人税 | B46: 0.33 | P46: =O46/$O$5 -> 0 | R46: 法人税 | S46: 0.33 | AF46: =O46
A47: 税引後当期純利益 | O47: =O45-O46 -> 450000 | P47: =O47/$O$5 -> 0.048387097 | R47: 税引後当期純利益 | AF47: =O47 -> 450000
A50: 変動費率 | B50: =SUM(B4:B36) -> 0
A51: 固定比率 | B51: =100%-B50 -> 1

Sheet 実際PL 
A1: 税抜 | B1: 変動費率 | C1: 7月 | D1: 8月 | E1: 9月 | F1: 10月 | G1: 11月 | H1: 12月 | I1: 1月 | J1: 2月 | K1: 3月 | L1: 4月 | M1: 5月 | N1: 6月 | O1: 累計
O2: =SUM(C2:N2) -> 0
A3: 売上 | C3: 955367 | D3: 818306 | E3: 760538 | F3: 903177 | G3: 921683 | H3: 806522 | I3: 822486 | J3: 793307 | K3: 900614 | L3: 780153 | M3: 514206 | N3: 334355 | O3: =SUM(C3:N3) -> 9310714 | P3: =O3/$O$3 -> 1
A4: 売上原価 | O4: =SUM(C4:N4) -> 0 | P4: =O4/$O$3 -> 0
A5: 売上総利益 | C5: =C2+C3-C4 -> 955367 | D5: =D2+D3-D4 -> 818306 | E5: =E2+E3-E4 -> 760538 | F5: =F2+F3-F4 -> 903177 | G5: =G2+G3-G4 -> 921683 | H5: =H2+H3-H4 -> 806522 | I5: =I2+I3-I4 -> 822486 | J5: =J2+J3-J4 -> 793307 | ... O5: =O2+O3-O4 -> 9310714
O6: =SUM(C6:N6) -> 0
A7: 役員報酬 | O7: =SUM(C7:N7) -> 0 | P7: =O7/$O$5 -> 0
A8: 給与手当 | G8: 188000 | H8: 188000 | I8: 188000 | J8: 188000 | O8: =SUM(C8:N8) -> 752000
A9: 雑給 | C9: 929867 | D9: 791706 | E9: 735138 | F9: 874778 | G9: 709883 | H9: 598522 | I9: 640544 | J9: 583508 | K9: 737614 | L9: 599194 | M9: 328097 | N9: 315516 | O9: =SUM(C9:N9) -> 7844367 | P9: =O9/$O$5 -> 0.84250972
A10: 法定福利費 | B10: 0 | C10: -797 | D10: 31466 | E10: -552 | F10: -838 | G10: -1465 | H10: -1400 | I10: -1353 | J10: -1344 | K10: -951 | L10: -1120 | M10: -936 | N10: -725 | O10: =SUM(C10:N10) -> 19985
A11: 福利厚生費 | O11: =SUM(C11:N11) -> 0
A12: 業務委託費 | J12: 362164 | K12: 352727 | L12: 352727 | M12: 352727 | N12: 352727 | O12: =SUM(C12:N12) -> 1773072
A13: 労務委託費 | O13: =SUM(C13:N13) -> 0
A14: 旅費交通費 | C14: 23091 | D14: 24182 | F14: 25818 | G14: 21636 | H14: 18182 | I14: 21636 | J14: 19818 | K14: 22727 | L14: 17455 | M14: 13818 | N14: 17127 | O14: =SUM(C14:N14) -> 225490
A15: 通信費 | C15: 20275 | E15: 23091 | F15: 473 | O15: =SUM(C15:N15) -> 43839 | P15: =O15/$O$5 -> 0.0047084466
A16: 開発費 | O16: =SUM(C16:N16) -> 0
A17: 交際費 | O17: =SUM(C17:N17) -> 0 | P17: =O17/$O$5 -> 0
A18: 会議費 | O18: =SUM(C18:N18) -> 0
A19: 戦略費 | O19: =SUM(C19:N19) -> 0 | P19: =O19/$O$5 -> 0
A20: 減価償却費 | O20: =SUM(C20:N20) -> 0
A21: 賃借料 | O21: =SUM(C21:N21) -> 0
A22: 地代家賃 | O22: =SUM(C22:N22) -> 0
A23: リース料 | O23: =SUM(C23:N23) -> 0
A24: 修繕費 | O24: =SUM(C24:N24) -> 0
A25: 保険料 | O25: =SUM(C25:N25) -> 0
A26: 水道光熱費 | B26: 0 | O26: =SUM(C26:N26) -> 0
A27: 消耗品費 | B27: 0 | O27: =SUM(C27:N27) -> 0 | P27: =O27/$O$5 -> 0
A28: 租税公課 | E28: 350 | F28: 10480 | G28: 5600 | I28: 30480 | O28: =SUM(C28:N28) -> 46910
A29: 広告宣伝費 | O29: =SUM(C29:N29) -> 0
A30: 支払手数料 | B30: 0 | C30: 5200 | D30: 5200 | E30: 5400 | F30: 5700 | G30: 8100 | H30: 5200 | I30: 11127 | J30: 5900 | K30: 7700 | L30: 5800 | M30: 7600 | N30: 5900 | O30: =SUM(C30:N30) -> 78827
A31: 教育費 | O31: =SUM(C31:N31) -> 0
A32: 新聞図書費 | O32: =SUM(C32:N32) -> 0
A33: 備品費 | B33: 0 | O33: =SUM(C33:N33) -> 0
A34: 管理諸費 エスクリエイト | C34: 50000 | D34: 50000 | E34: 150000 | F34: 57273 | G34: 50000 | H34: 50000 | I34: 50000 | J34: 50000 | K34: 50000 | L34: 50000 | M34: 50000 | N34: 50000 | O34: =SUM(C34:N34) -> 707273 | P34: =O34/$O$5 -> 0.075963347
A35: 雑費 | O35: =SUM(C35:N35) -> 0
A37: 販売管理費合計 | C37: =SUM(C7:C36) -> 1027636 | D37: =SUM(D7:D36) -> 902554 | E37: =SUM(E7:E36) -> 913427 | F37: =SUM(F7:F36) -> 973684 | G37: =SUM(G7:G36) -> 981754 | H37: =SUM(H7:H36) -> 858504 | I37: =SUM(I7:I36) -> 940434 | J37: =SUM(J7:J36) -> 1208046 | ... O37: =SUM(O7:O36) -> 11491763 | P37: =O37/$O$5 -> 1.2342515
A38: 営業利益 | C38: =C5-C37 -> -72269 | D38: =D5-D37 -> -84248 | E38: =E5-E37 -> -152889 | F38: =F5-F37 -> -70507 | G38: =G5-G37 -> -60071 | H38: =H5-H37 -> -51982 | I38: =I5-I37 -> -117948 | J38: =J5-J37 -> -414739 | ... O38: =O5-O37 -> -2181049 | P38: =O38/$O$5 -> -0.23425153
A39: 支払利息 | O39: =SUM(C39:N39) -> 0
A40: 雑損失 | O40: =SUM(C40:N40) -> 0
A41: 受取利息 雑収入 | C41: 2019000 | D41: 7339 | E41: 149788 | F41: 100000 | J41: 30 | O41: =SUM(C41:N41) -> 2276157
A42: 経常利益 | C42: =C38-C39-C40+C41 -> 1946731 | D42: =D38-D39-D40+D41 -> -76909 | E42: =E38-E39-E40+E41 -> -3101 | F42: =F38-F39-F40+F41 -> 29493 | G42: =G38-G39-G40+G41 -> -60071 | H42: =H38-H39-H40+H41 -> -51982 | I42: =I38-I39-I40+I41 -> -117948 | J42: =J38-J39-J40+J41 -> -414709 | ... O42: =O38-O39-O40+O41 -> 95108 | P42: =O42/$O$5 -> 0.010214899
A43: 特別利益 | C43: 11810 | O43: =SUM(C43:N43) -> 11810
A44: 特別損失 | O44: =SUM(C44:N44) -> 0
A45: 税引前当期純利益 | C45: =C42+C43-C44 -> 1958541 | D45: =D42+D43-D44 -> -76909 | E45: =E42+E43-E44 -> -3101 | F45: =F42+F43-F44 -> 29493 | G45: =G42+G43-G44 -> -60071 | H45: =H42+H43-H44 -> -51982 | I45: =I42+I43-I44 -> -117948 | J45: =J42+J43-J44 -> -414709 | ... O45: =O42+O43-O44 -> 106918 | P45: =O45/$O$5 -> 0.01148333
A46: 法人税 | B46: 0.33 | P46: =O46/$O$5 -> 0
A47: 税引後当期純利益 | O47: =O45-O46 -> 106918 | P47: =O47/$O$5 -> 0.01148333
A50: 変動費率 | B50: =SUM(B4:B36) -> 0
A51: 固定比率 | B51: =100%-B50 -> 1
A55: 売上内訳 | B55: ｅｓエンター | C55: 2604212 | D55: 2946348 | E55: 2777697
B56: goカンパニー | C56: =92593+5000 -> 97593 | D56: 97593 | E56: 97593

Sheet 予測PL
B1: 変動費率 | C1: 7月 | D1: 8月 | E1: 9月 | F1: 10月 | G1: 11月 | H1: 12月 | I1: 1月 | J1: 2月 | K1: 3月 | L1: 4月 | M1: 5月 | N1: 6月 | O1: 累計
O2: =SUM(C2:N2) -> 0
A3: 売上 | C3: 955367 | D3: 818306 | E3: 760538 | F3: 903177 | G3: 921683 | H3: 806522 | I3: 822486 | J3: 793307 | K3: 900614 | L3: 780153 | M3: 514206 | N3: 334355 | O3: =SUM(C3:N3) -> 9310714 | P3: =O3/$O$3 -> 1
A4: 売上原価 | O4: =SUM(C4:N4) -> 0 | P4: =O4/$O$3 -> 0
A5: 売上総利益 | C5: 955367 | D5: 818306 | E5: 760538 | F5: =F2+F3-F4 -> 903177 | G5: =G2+G3-G4 -> 921683 | H5: 806522 | I5: =I2+I3-I4 -> 822486 | J5: 793307 | K5: 900614 | L5: 780153 | M5: 514206 | N5: 334355 | O5: =O2+O3-O4 -> 9310714
O6: =SUM(C6:N6) -> 0
A7: 役員報酬 | O7: =SUM(C7:N7) -> 0 | P7: =O7/$O$5 -> 0
A8: 給与手当 | G8: 188000 | H8: 188000 | I8: 188000 | J8: 188000 | O8: =SUM(C8:N8) -> 752000
A9: 雑給 | C9: 929867 | D9: 791706 | E9: 735138 | F9: 874778 | G9: 709883 | H9: 598522 | I9: 640544 | J9: 583508 | K9: 737614 | L9: 599194 | M9: 328097 | N9: 315516 | O9: =SUM(C9:N9) -> 7844367 | P9: =O9/$O$5 -> 0.84250972
A10: 法定福利費 | B10: 0 | C10: -797 | D10: 31466 | E10: -552 | F10: -838 | G10: -1465 | H10: -1400 | I10: -1353 | J10: -1344 | K10: -951 | L10: -1120 | M10: -936 | N10: -725 | O10: =SUM(C10:N10) -> 19985
A11: 福利厚生費 | O11: =SUM(C11:N11) -> 0
A12: 業務委託費 | J12: 362164 | K12: 307273 | L12: 352727 | M12: 352727 | N12: 352727 | O12: =SUM(C12:N12) -> 1727618
A13: 労務委託費 | O13: =SUM(C13:N13) -> 0
A14: 旅費交通費 | C14: 23091 | D14: 24182 | F14: 25818 | G14: 21636 | H14: 18182 | I14: 21636 | J14: 19818 | K14: 22727 | L14: 17455 | M14: 13818 | N14: 17127 | O14: =SUM(C14:N14) -> 225490
A15: 通信費 | C15: 20275 | E15: 23091 | F15: 473 | O15: =SUM(C15:N15) -> 43839 | P15: =O15/$O$5 -> 0.0047084466
A16: 開発費 | O16: =SUM(C16:N16) -> 0
A17: 交際費 | O17: =SUM(C17:N17) -> 0 | P17: =O17/$O$5 -> 0
A18: 会議費 | O18: =SUM(C18:N18) -> 0
A19: 戦略費 | O19: =SUM(C19:N19) -> 0 | P19: =O19/$O$5 -> 0
A20: 減価償却費 | O20: =SUM(C20:N20) -> 0
A21: 賃借料 | O21: =SUM(C21:N21) -> 0
A22: 地代家賃 | O22: =SUM(C22:N22) -> 0
A23: リース料 | O23: =SUM(C23:N23) -> 0
A24: 修繕費 | O24: =SUM(C24:N24) -> 0
A25: 保険料 | O25: =SUM(C25:N25) -> 0
A26: 水道光熱費 | B26: 0 | O26: =SUM(C26:N26) -> 0
A27: 消耗品費 | B27: 0 | O27: =SUM(C27:N27) -> 0 | P27: =O27/$O$5 -> 0
A28: 租税公課 | E28: 350 | F28: 10480 | G28: 5600 | I28: 30480 | O28: =SUM(C28:N28) -> 46910
A29: 広告宣伝費 | O29: =SUM(C29:N29) -> 0
A30: 支払手数料 | B30: 0 | C30: 5200 | D30: 5200 | E30: 5400 | F30: 5700 | G30: 8100 | H30: 5200 | I30: 11127 | J30: 5900 | K30: 7700 | L30: 5800 | M30: 7600 | N30: 5900 | O30: =SUM(C30:N30) -> 78827
A31: 教育費 | O31: =SUM(C31:N31) -> 0
A32: 新聞図書費 | O32: =SUM(C32:N32) -> 0
A33: 備品費 | B33: 0 | O33: =SUM(C33:N33) -> 0
A34: 管理諸費 エスクリエイト | C34: 50000 | D34: 50000 | E34: 150000 | F34: 57273 | G34: 50000 | H34: 50000 | I34: 50000 | J34: 50000 | K34: 50000 | L34: 50000 | M34: 50000 | N34: 50000 | O34: =SUM(C34:N34) -> 707273 | P34: =O34/$O$5 -> 0.075963347
A35: 雑費 | O35: =SUM(C35:N35) -> 0
A37: 販売管理費合計 | C37: 1027636 | D37: 902554 | E37: 913427 | F37: =SUM(F7:F36) -> 973684 | G37: =SUM(G7:G36) -> 981754 | H37: 858504 | I37: =SUM(I7:I36) -> 940434 | J37: 1208046 | K37: 1124363 | L37: 1024056 | M37: 751306 | N37: 740545 | O37: =SUM(O7:O36) -> 11446309 | P37: =O37/$O$5 -> 1.2293696
A38: 営業利益 | C38: -72269 | D38: -84248 | E38: -152889 | F38: =F5-F37 -> -70507 | G38: =G5-G37 -> -60071 | H38: -51982 | I38: =I5-I37 -> -117948 | J38: -414739 | K38: -223749 | L38: -243903 | M38: -237100 | N38: -406190 | O38: =O5-O37 -> -2135595 | P38: =O38/$O$5 -> -0.22936963
A39: 支払利息 | O39: =SUM(C39:N39) -> 0
A40: 雑損失 | O40: =SUM(C40:N40) -> 0
A41: 受取利息 雑収入 | C41: 2019000 | D41: 7339 | E41: 149788 | F41: 100000 | J41: 30 | O41: =SUM(C41:N41) -> 2276157
A42: 経常利益 | C42: 1946731 | D42: -76909 | E42: -3101 | F42: =F38-F39-F40+F41 -> 29493 | G42: =G38-G39-G40+G41 -> -60071 | H42: -51982 | I42: =I38-I39-I40+I41 -> -117948 | J42: -414709 | K42: -223749 | L42: -243903 | M42: -237100 | N42: -406190 | O42: =O38-O39-O40+O41 -> 140562 | P42: =O42/$O$5 -> 0.015096801
A43: 特別利益 | C43: 11810 | O43: =SUM(C43:N43) -> 11810
A44: 特別損失 | O44: =SUM(C44:N44) -> 0
A45: 税引前当期純利益 | C45: 1958541 | D45: -76909 | E45: -3101 | F45: =F42+F43-F44 -> 29493 | G45: =G42+G43-G44 -> -60071 | H45: -51982 | I45: =I42+I43-I44 -> -117948 | J45: -414709 | K45: -223749 | L45: -243903 | M45: -237100 | N45: -406190 | O45: =O42+O43-O44 -> 152372 | P45: =O45/$O$5 -> 0.016365233
A46: 法人税 | B46: 0.33 | O46: =O45*B46 -> 50282.76 | P46: =O46/$O$5 -> 0.0054005267
A47: 税引後当期純利益 | O47: =O45-O46 -> 102089.24 | P47: =O47/$O$5 -> 0.010964706
A50: 変動費率 | B50: =SUM(B4:B36) -> 0 | R50: 消費税
A51: 固定比率 | B51: =100%-B50 -> 1 | R51: 売上 | S51: =O3 -> 9310714
R52: 国税 | S52: =S51*T52 -> 726235.69 | T52: 0.078
R53: 仕入 | S53: =S52*T53 -> 435741.42 | T53: 0.6
R54: 差し引き税額 | S54: =S52-S53 -> 290494.28
A55: 売上内訳 | B55: ｅｓエンター | C55: 2604212 | D55: 2946348 | E55: 2777697 | R55: 地方消費税 | S55: =S54*22/78 -> 81934.283

Sheet 前期実際PL
A1: 税抜 | B1: 変動費率 | C1: 7月 | D1: 8月 | E1: 9月 | F1: 10月 | G1: 11月 | H1: 12月 | I1: 1月 | J1: 2月 | K1: 3月 | L1: 4月 | M1: 5月 | N1: 6月 | O1: 累計
O2: =SUM(C2:N2) -> 0
A3: 売上 | C3: =C55+C56 -> 2701805 | D3: =D55+D56 -> 3043941 | E3: =E55+E56 -> 2875290 | F3: 2725869 | G3: 2767215 | H3: 3399649 | I3: 2741722 | J3: 2241953 | K3: 1115805 | L3: 698680 | M3: 745280 | N3: 736859 | O3: =SUM(C3:N3) -> 25794068 | P3: =O3/$O$3 -> 1
A4: 売上原価 | C4: =C3*$B$4 -> 0 | D4: 4800 | E4: 15750 | F4: =F3*$B$4 -> 0 | G4: =G3*$B$4 -> 0 | H4: =H3*$B$4 -> 0 | I4: =I3*$B$4 -> 0 | J4: =J3*$B$4 -> 0 | K4: =K3*$B$4 -> 0 | L4: =L3*$B$4 -> 0 | M4: =M3*$B$4 -> 0 | N4: =N3*$B$4 -> 0 | O4: =SUM(C4:N4) -> 20550 | P4: =O4/$O$3 -> 0.00079669481
A5: 売上総利益 | C5: =C2+C3-C4 -> 2701805 | D5: =D2+D3-D4 -> 3039141 | E5: =E2+E3-E4 -> 2859540 | F5: =F2+F3-F4 -> 2725869 | G5: =G2+G3-G4 -> 2767215 | H5: =H2+H3-H4 -> 3399649 | I5: =I2+I3-I4 -> 2741722 | J5: =J2+J3-J4 -> 2241953 | ... O5: =O2+O3-O4 -> 25773518
O6: =SUM(C6:N6) -> 0
A7: 役員報酬 | C7: 50000 | D7: 50000 | E7: 50000 | F7: 50000 | G7: 50000 | H7: 50000 | I7: 50000 | J7: 50000 | K7: 50000 | L7: 50000 | M7: 50000 | N7: 0 | O7: =SUM(C7:N7) -> 550000 | P7: =O7/$O$5 -> 0.021339733
A8: 給与手当 | O8: =SUM(C8:N8) -> 0
A9: 雑給 | C9: 2498602 | D9: 2517647 | E9: 2581636 | F9: 2121030 | G9: 2208553 | H9: 2897358 | I9: 2316424 | J9: 2171650 | K9: 1335048 | L9: 840778 | M9: 661990 | N9: 714259 | O9: =SUM(C9:N9) -> 22864975 | P9: =O9/$O$5 -> 0.88714994
A10: 法定福利費 | B10: 0 | C10: 66590 | D10: -1149 | E10: -868 | F10: -640 | G10: -845 | H10: -830 | I10: -705 | J10: -683 | K10: -640 | L10: -598 | M10: -633 | N10: -744 | O10: =SUM(C10:N10) -> 58255
A11: 福利厚生費 | D11: 27778 | O11: =SUM(C11:N11) -> 27778
A12: 業務委託費 | O12: =SUM(C12:N12) -> 0
A13: 労務委託費 | O13: =SUM(C13:N13) -> 0
A14: 旅費交通費 | C14: 0 | D14: 75371 | E14: 77407 | F14: 93386 | G14: 65091 | H14: 77818 | I14: 68536 | J14: 81510 | K14: =29455-3205 -> 26250 | L14: 11909 | M14: 21909 | N14: 20545 | O14: =SUM(C14:N14) -> 619732
A15: 通信費 | C15: 0 | D15: 26080 | E15: 11282 | F15: 12539 | G15: 14486 | H15: 15649 | I15: 14232 | J15: 14928 | K15: 15990 | L15: 21101 | N15: 22987 | O15: =SUM(C15:N15) -> 169274 | P15: =O15/$O$5 -> 0.0065677491
A16: 開発費 | O16: =SUM(C16:N16) -> 0
A17: 交際費 | C17: 900 | D17: 13426 | E17: 65947 | F17: 65731 | G17: =60230-917 -> 59313 | H17: 53402 | I17: 41307 | J17: 46737 | K17: 64463 | L17: 0 | O17: =SUM(C17:N17) -> 411226 | P17: =O17/$O$5 -> 0.015955369
A18: 会議費 | C18: 78350 | D18: 99412 | E18: 0 | F18: 9710 | G18: 8383 | H18: 0 | I18: 0 | J18: -431 | K18: 0 | L18: 0 | O18: =SUM(C18:N18) -> 195424
A19: 戦略費 | E19: 24435 | H19: 22728 | I19: 6405 | J19: 14263 | K19: 3318 | O19: =SUM(C19:N19) -> 71149 | P19: =O19/$O$5 -> 0.0027605467
A20: 減価償却費 | O20: =SUM(C20:N20) -> 0
A21: 賃借料 | O21: =SUM(C21:N21) -> 0
A22: 地代家賃 | O22: =SUM(C22:N22) -> 0
A23: リース料 | O23: =SUM(C23:N23) -> 0
A24: 修繕費 | O24: =SUM(C24:N24) -> 0
A25: 保険料 | N25: 11810 | O25: =SUM(C25:N25) -> 11810
A26: 水道光熱費 | B26: 0 | O26: =SUM(C26:N26) -> 0
A27: 消耗品費 | B27: 0 | I27: 12673 | K27: 27273 | O27: =SUM(C27:N27) -> 39946 | P27: =O27/$O$5 -> 0.0015498854
A28: 租税公課 | O28: =SUM(C28:N28) -> 0
A29: 広告宣伝費 | C29: 20221 | D29: 26675 | E29: 46000 | F29: 9091 | G29: 98000 | H29: 1800 | I29: -16 | J29: 46000 | K29: 43000 | O29: =SUM(C29:N29) -> 290771
A30: 支払手数料 | B30: 0 | C30: 39080 | D30: 7300 | E30: 6900 | F30: 7609 | G30: 6100 | H30: 6500 | I30: 6100 | J30: 5900 | K30: 6800 | L30: 10200 | M30: 6400 | N30: 6100 | O30: =SUM(C30:N30) -> 114989
A31: 教育費 | O31: =SUM(C31:N31) -> 0
A32: 新聞図書費 | D32: 1800 | G32: 3300 | O32: =SUM(C32:N32) -> 5100
A33: 備品費 | B33: 0 | O33: =SUM(C33:N33) -> 0
A34: 管理諸費 エスクリエイト | C34: 50000 | D34: 50000 | E34: 110000 | F34: 50000 | G34: 50000 | H34: 50000 | I34: 50000 | J34: 50000 | K34: 50000 | L34: 50000 | M34: 50000 | N34: 50000 | O34: =SUM(C34:N34) -> 660000 | P34: =O34/$O$5 -> 0.02560768
A35: 雑費 | J35: 31000 | O35: =SUM(C35:N35) -> 31000
A37: 販売管理費合計 | C37: =SUM(C7:C36) -> 2803743 | D37: =SUM(D7:D36) -> 2894340 | E37: =SUM(E7:E36) -> 2972739 | F37: =SUM(F7:F36) -> 2418456 | G37: =SUM(G7:G36) -> 2562381 | H37: =SUM(H7:H36) -> 3174425 | I37: =SUM(I7:I36) -> 2564956 | J37: =SUM(J7:J36) -> 2510874 | ... O37: =SUM(O7:O36) -> 26121429 | P37: =O37/$O$5 -> 1.0134988
A38: 営業利益 | C38: =C5-C37 -> -101938 | D38: =D5-D37 -> 144801 | E38: =E5-E37 -> -113199 | F38: =F5-F37 -> 307413 | G38: =G5-G37 -> 204834 | H38: =H5-H37 -> 225224 | I38: =I5-I37 -> 176766 | J38: =J5-J37 -> -268921 | ... O38: =O5-O37 -> -347911 | P38: =O38/$O$5 -> -0.013498778
A39: 支払利息 | O39: =SUM(C39:N39) -> 0
A40: 雑損失 | N40: 364 | O40: =SUM(C40:N40) -> 364
A41: 受取利息 雑収入 | D41: 12 | J41: 13 | O41: =SUM(C41:N41) -> 25
A42: 経常利益 | C42: =C38-C39-C40+C41 -> -101938 | D42: =D38-D39-D40+D41 -> 144813 | E42: =E38-E39-E40+E41 -> -113199 | F42: =F38-F39-F40+F41 -> 307413 | G42: =G38-G39-G40+G41 -> 204834 | H42: =H38-H39-H40+H41 -> 225224 | I42: =I38-I39-I40+I41 -> 176766 | J42: =J38-J39-J40+J41 -> -268908 | ... O42: =O38-O39-O40+O41 -> -348250 | P42: =O42/$O$5 -> -0.013511931
A43: 特別利益 | O43: =SUM(C43:N43) -> 0
A44: 特別損失 | C44: 4400 | O44: =SUM(C44:N44) -> 4400
A45: 税引前当期純利益 | C45: =C42+C43-C44 -> -106338 | D45: =D42+D43-D44 -> 144813 | E45: =E42+E43-E44 -> -113199 | F45: =F42+F43-F44 -> 307413 | G45: =G42+G43-G44 -> 204834 | H45: =H42+H43-H44 -> 225224 | I45: =I42+I43-I44 -> 176766 | J45: =J42+J43-J44 -> -268908 | ... O45: =O42+O43-O44 -> -352650 | P45: =O45/$O$5 -> -0.013682649
A46: 法人税 | B46: 0.33 | P46: =O46/$O$5 -> 0
A47: 税引後当期純利益 | O47: =O45-O46 -> -352650 | P47: =O47/$O$5 -> -0.013682649
A50: 変動費率 | B50: =SUM(B4:B36) -> 0
A51: 固定比率 | B51: =100%-B50 -> 1
A55: 売上内訳 | B55: ｅｓエンター | C55: 2604212 | D55: 2946348 | E55: 2777697
B56: goカンパニー | C56: =92593+5000 -> 97593 | D56: 97593 | E56: 97593

Sheet 税込PL
A1: 税込み | B1: 変動費率 | C1: 7月 | D1: 8月 | E1: 9月 | F1: 10月 | G1: 11月 | H1: 12月 | I1: 1月 | J1: 2月 | K1: 3月 | L1: 4月 | M1: 5月 | N1: 6月 | O1: 累計
O2: =SUM(C2:N2) -> 0
A3: 売上 | C3: 2917948 | D3: 3287455 | E3: 3105313 | F3: 2998456 | G3: 3043937 | H3: 3739614 | I3: 3015894 | J3: 2466148 | K3: 1227385 | L3: 781748 | M3: 819808 | N3: 810545 | O3: =SUM(C3:N3) -> 28214251 | P3: =O3/$O$3 -> 1
A4: 売上原価 | D4: 5184 | E4: 17010 | M4: =M3*$B$4 -> 0 | N4: =N3*$B$4 -> 0 | O4: =SUM(C4:N4) -> 22194 | P4: =O4/$O$3 -> 0.00078662375
A5: 売上総利益 | C5: =C2+C3-C4 -> 2917948 | D5: =D2+D3-D4 -> 3282271 | E5: =E2+E3-E4 -> 3088303 | F5: =F2+F3-F4 -> 2998456 | G5: =G2+G3-G4 -> 3043937 | H5: =H2+H3-H4 -> 3739614 | I5: =I2+I3-I4 -> 3015894 | J5: =J2+J3-J4 -> 2466148 | ... O5: =O2+O3-O4 -> 28192057
O6: =SUM(C6:N6) -> 0
A7: 役員報酬 | C7: 50000 | D7: 50000 | E7: 50000 | F7: 50000 | G7: 50000 | H7: 50000 | I7: 50000 | J7: 50000 | K7: 50000 | L7: 50000 | M7: 50000 | N7: 0 | O7: =SUM(C7:N7) -> 550000 | P7: =O7/$O$5 -> 0.019509041
A8: 給与手当 | C8: 2498602 | D8: 2517647 | E8: 2581636 | F8: 2121030 | G8: 2208553 | H8: 2897358 | I8: 2316424 | J8: 2171650 | K8: 1335048 | L8: 840778 | M8: 661990 | N8: 714259 | O8: =SUM(C8:N8) -> 22864975
A9: 雑給 | O9: =SUM(C9:N9) -> 0 | P9: =O9/$O$5 -> 0
A10: 法定福利費 | B10: 0 | C10: 66590 | D10: -1149 | E10: -868 | F10: -640 | G10: -845 | H10: -830 | I10: -705 | J10: -683 | K10: -640 | L10: -598 | M10: -633 | N10: -744 | O10: =SUM(C10:N10) -> 58255
A11: 福利厚生費 | D11: 30000 | O11: =SUM(C11:N11) -> 30000
A12: 業務委託費 | O12: =SUM(C12:N12) -> 0
A13: 労務委託費 | O13: =SUM(C13:N13) -> 0
A14: 旅費交通費 | C14: 0 | D14: 81400 | E14: 83600 | F14: 102725 | G14: 71600 | H14: 85600 | I14: 75390 | J14: 89660 | K14: 28874 | L14: 13100 | M14: 24100 | N14: 22600 | O14: =SUM(C14:N14) -> 678649
A15: 通信費 | C15: 0 | D15: 28166 | E15: 12185 | F15: 13793 | G15: 15935 | H15: 17214 | I15: 15655 | J15: 16421 | K15: 17589 | L15: 23212 | N15: 25286 | O15: =SUM(C15:N15) -> 185456 | P15: =O15/$O$5 -> 0.0065783068
A16: 開発費 | O16: =SUM(C16:N16) -> 0
A17: 交際費 | C17: 972 | D17: 14500 | E17: 71222 | F17: 72304 | G17: 65245 | H17: 58741 | I17: 45438 | J17: 51412 | K17: 70909 | O17: =SUM(C17:N17) -> 450743 | P17: =O17/$O$5 -> 0.015988298
A18: 会議費 | C18: 84615 | D18: 107356 | E18: 0 | F18: 10681 | G18: 9221 | H18: 0 | I18: 0 | J18: -474 | O18: =SUM(C18:N18) -> 211399
A19: 戦略費 | E19: 26390 | H19: 25001 | I19: 7046 | J19: 15690 | K19: 3650 | O19: =SUM(C19:N19) -> 77777 | P19: =O19/$O$5 -> 0.0027588267
A20: 減価償却費 | O20: =SUM(C20:N20) -> 0
A21: 賃借料 | O21: =SUM(C21:N21) -> 0
A22: 地代家賃 | O22: =SUM(C22:N22) -> 0
A23: リース料 | O23: =SUM(C23:N23) -> 0
A24: 修繕費 | O24: =SUM(C24:N24) -> 0
A25: 保険料 | N25: 11810 | O25: =SUM(C25:N25) -> 11810
A26: 水道光熱費 | B26: 0 | O26: =SUM(C26:N26) -> 0
A27: 消耗品費 | B27: 0 | I27: 13940 | K27: 30000 | O27: =SUM(C27:N27) -> 43940 | P27: =O27/$O$5 -> 0.001558595
A28: 租税公課 | O28: =SUM(C28:N28) -> 0
A29: 広告宣伝費 | C29: 21838 | D29: 28808 | E29: 49680 | F29: 10000 | G29: 107800 | H29: 1980 | I29: -18 | J29: 50600 | K29: 47300 | O29: =SUM(C29:N29) -> 317988
A30: 支払手数料 | B30: 0 | C30: 42206 | D30: 7884 | E30: 7452 | F30: 8370 | G30: 6710 | H30: 7150 | I30: 6710 | J30: 6490 | K30: 7480 | L30: 11220 | M30: 7040 | N30: 6710 | O30: =SUM(C30:N30) -> 125422
A31: 教育費 | O31: =SUM(C31:N31) -> 0
A32: 新聞図書費 | D32: 1944 | G32: 3630 | O32: =SUM(C32:N32) -> 5574
A33: 備品費 | B33: 0 | O33: =SUM(C33:N33) -> 0
A34: 管理諸費 エスクリエイト | C34: 54000 | D34: 54000 | E34: 118800 | F34: 55000 | G34: 55000 | H34: 55000 | I34: 55000 | J34: 55000 | K34: 55000 | L34: 55000 | M34: 55000 | N34: 55000 | O34: =SUM(C34:N34) -> 721800 | P34: =O34/$O$5 -> 0.025602956
A35: 雑費 | J35: 34100 | O35: =SUM(C35:N35) -> 34100
A37: 販売管理費合計 | C37: =SUM(C7:C36) -> 2818823 | D37: =SUM(D7:D36) -> 2920556 | E37: =SUM(E7:E36) -> 3000097 | F37: =SUM(F7:F36) -> 2443263 | G37: =SUM(G7:G36) -> 2592849 | H37: =SUM(H7:H36) -> 3197214 | I37: =SUM(I7:I36) -> 2584880 | J37: =SUM(J7:J36) -> 2539866 | ... O37: =SUM(O7:O36) -> 26367888 | P37: =O37/$O$5 -> 0.93529493
A38: 営業利益 | C38: =C5-C37 -> 99125 | D38: =D5-D37 -> 361715 | E38: =E5-E37 -> 88206 | F38: =F5-F37 -> 555193 | G38: =G5-G37 -> 451088 | H38: =H5-H37 -> 542400 | I38: =I5-I37 -> 431014 | J38: =J5-J37 -> -73718 | ... O38: =O5-O37 -> 1824169 | P38: =O38/$O$5 -> 0.064705069
A39: 支払利息 | O39: =SUM(C39:N39) -> 0
A40: 雑損失 | N40: 400 | O40: =SUM(C40:N40) -> 400
A41: 受取利息 雑収入 | D41: 12 | J41: 13 | O41: =SUM(C41:N41) -> 25
A42: 経常利益 | C42: =C38-C39-C40+C41 -> 99125 | D42: =D38-D39-D40+D41 -> 361727 | E42: =E38-E39-E40+E41 -> 88206 | F42: =F38-F39-F40+F41 -> 555193 | G42: =G38-G39-G40+G41 -> 451088 | H42: =H38-H39-H40+H41 -> 542400 | I42: =I38-I39-I40+I41 -> 431014 | J42: =J38-J39-J40+J41 -> -73705 | ... O42: =O38-O39-O40+O41 -> 1823794 | P42: =O42/$O$5 -> 0.064691768
A43: 特別利益 | O43: =SUM(C43:N43) -> 0
A44: 特別損失 | C44: 4400 | O44: =SUM(C44:N44) -> 4400
A45: 税引前当期純利益 | C45: =C42+C43-C44 -> 94725 | D45: =D42+D43-D44 -> 361727 | E45: =E42+E43-E44 -> 88206 | F45: =F42+F43-F44 -> 555193 | G45: =G42+G43-G44 -> 451088 | H45: =H42+H43-H44 -> 542400 | I45: =I42+I43-I44 -> 431014 | J45: =J42+J43-J44 -> -73705 | ... O45: =O42+O43-O44 -> 1819394 | P45: =O45/$O$5 -> 0.064535695
A46: 法人税 | B46: 0.33 | O46: =O45*B46 -> 600400.02 | P46: =O46/$O$5 -> 0.021296779
A47: 税引後当期純利益 | O47: =O45-O46 -> 1218994 | P47: =O47/$O$5 -> 0.043238916
A50: 変動費率 | B50: =SUM(B4:B36) -> 0
A51: 固定比率 | B51: =100%-B50 -> 1
A55: 売上内訳 | B55: ｅｓエンター | C55: 2604212 | D55: 2946348 | E55: 2777697
B56: goカンパニー | C56: =92593+5000 -> 97593 | D56: 97593 | E56: 97593
