Workbook

Sheet 月次BS
B1: 勘定科目 | C1: 期首残 | D1: 7 | E1: =IF(D1=12,1,D1+1) -> 8 | F1: =IF(E1=12,1,E1+1) -> 9 | G1: =IF(F1=12,1,F1+1) -> 10 | H1: =IF(G1=12,1,G1+1) -> 11 | I1: =IF(H1=12,1,H1+1) -> 12 | J1: =IF(I1=12,1,I1+1) -> 1 | K1: =IF(J1=12,1,J1+1) -> 2 | L1: =IF(K1=12,1,K1+1) -> 3 | ... O1: =IF(N1=12,1,N1+1) -> 6
A2: 資産の部
A3: 流動資産
A4: 現金及び預金
B5: 現金
B6: 普通預金
A7: 現金及び預金合計 | C7: 2348989 | D7: 2725169 | E7: 1998006 | F7: 2031109 | G7: 1400195 | H7: 1532912 | I7: 1488143 | J7: 1217238 | K7: 2273568 | L7: 5469239 | M7: 5065984 | N7: 4720980 | O7: 4131529
A8: 売上債権
B9: 売掛金 | C9: 2838186 | D9: 3314302 | E9: 3820128 | F9: 4338949 | G9: 4857796 | H9: 5278592 | I9: 5913222 | J9: 6433571 | K9: 6896344 | L9: 6377513 | M9: 7291191 | N9: 7999295 | O9: 8976617
A10: 売上債権合計 | C10: 2838186 | D10: 3314302 | E10: 3820128 | F10: 4338949 | G10: 4857796 | H10: 5278592 | I10: 5913222 | J10: 6433571 | K10: 6896344 | L10: 6377513 | M10: 7291191 | N10: 7999295 | O10: 8976617
A11: 有価証券
A12: 有価証券合計
A13: 棚卸資産
B14: 商品
B15: 貯蔵品
A16: 棚卸資産合計
A17: その他流動資産
B18: 前払費用
B19: 立替金 | C19: 39666 | D19: 39666 | E19: 39666 | F19: 39666 | G19: 39666 | H19: 39666 | I19: 39666 | J19: 39666 | K19: 39666 | L19: 0 | M19: 0 | N19: 0 | O19: 0
B20: 短期貸付金 | C20: 7300000 | D20: 6277710 | E20: 6277710 | F20: 5771884 | G20: 5771884 | H20: 5196768 | I20: 4710947 | J20: 4159100 | K20: 2638882 | L20: 0 | M20: 0 | N20: 0 | O20: 0
B21: 仮払金 | C21: 0 | D21: 0 | E21: 0 | F21: 0 | G21: 0 | H21: 0 | I21: 0 | J21: 0 | K21: 0 | L21: 0 | M21: 0 | N21: 0 | O21: 4504
B22: 仮払消費税 | C22: 0 | D22: 75177 | E22: 109421 | F22: 151629 | G22: 200980 | H22: 230515 | I22: 277017 | J22: 320754 | K22: 360471 | L22: 402132 | M22: 438440 | N22: 483285 | O22: 526662
A23: その他流動資産合計 | C23: 7339666 | D23: 6392553 | E23: 6426797 | F23: 5963179 | G23: 6012530 | H23: 5466949 | I23: 5027630 | J23: 4519520 | K23: 3039019 | L23: 402132 | M23: 438440 | N23: 483285 | O23: 531166
A24: 流動資産合計 | C24: 12526841 | D24: 12432024 | E24: 12244931 | F24: 12333237 | G24: 12270521 | H24: 12278453 | I24: 12428995 | J24: 12170329 | K24: 12208931 | L24: 12248884 | M24: 12795615 | N24: 13203560 | O24: 13639312
A25: 固定資産
A26: 有形固定資産
B27: 建物
B28: 車両運搬具
B29: 工具器具備品
B30: 一括償却資産
B31: 減価償却累計額
A32: 有形固定資産合計
A33: 無形固定資産
B34: ソフトウェア | C34: 795000 | D34: 768500 | E34: 742000 | F34: 715500 | G34: 689000 | H34: 662500 | I34: 636000 | J34: 609500 | K34: 583000 | L34: 556500 | M34: 530000 | N34: 503500 | O34: 477000
A35: 無形固定資産合計 | C35: 795000 | D35: 768500 | E35: 742000 | F35: 715500 | G35: 689000 | H35: 662500 | I35: 636000 | J35: 609500 | K35: 583000 | L35: 556500 | M35: 530000 | N35: 503500 | O35: 477000
A36: 投資その他の資産
B37: 出資金 | C37: 6600000 | D37: 6600000 | E37: 6600000 | F37: 6600000 | G37: 6600000 | H37: 6600000 | I37: 6600000 | J37: 6600000 | K37: 6600000 | L37: 6600000 | M37: 6600000 | N37: 6600000 | O37: 6600000
B38: 長期前払費用 | C38: 114983 | D38: 114983 | E38: 114983 | F38: 114983 | G38: 114983 | H38: 114983 | I38: 114983 | J38: 114983 | K38: 114983 | L38: 114983 | M38: 114983 | N38: 114983 | O38: 114983
B39: 敷金
B40: 預託金
A41: 投資その他の資産合計 | C41: 6714983 | D41: 6714983 | E41: 6714983 | F41: 6714983 | G41: 6714983 | H41: 6714983 | I41: 6714983 | J41: 6714983 | K41: 6714983 | L41: 6714983 | M41: 6714983 | N41: 6714983 | O41: 6714983
A42: 固定資産合計 | C42: 7509983 | D42: 7483483 | E42: 7456983 | F42: 7430483 | G42: 7403983 | H42: 7377483 | I42: 7350983 | J42: 7324483 | K42: 7297983 | L42: 7271483 | M42: 7244983 | N42: 7218483 | O42: 7191983
A43: 繰延資産
A44: 繰延資産合計
A45: 諸口
A46: 諸口合計
A47: 資産の部合計 | C47: 20036824 | D47: 19915507 | E47: 19701914 | F47: 19763720 | G47: 19674504 | H47: 19655936 | I47: 19779978 | J47: 19494812 | K47: 19506914 | L47: 19520367 | M47: 20040598 | N47: 20422043 | O47: 20831295
A48: 負債の部
A49: 流動負債
A50: 仕入債務
B51: 買掛金
A52: 仕入債務合計
A53: その他流動負債
B54: 短期借入金
B55: 未払金 | C55: 250000 | D55: 250000 | E55: 349280 | F55: 349280 | G55: 349280 | H55: 349280 | I55: 301677 | J55: 301677 | K55: 301677 | L55: 301677 | M55: 315252 | N55: 301677 | O55: 271677
B56: 未払費用 | C56: 154397 | D56: 277182 | E56: 174937 | F56: 256413 | G56: 233345 | H56: 201349 | I56: 346833 | J56: 214413 | K56: 179884 | L56: 215524 | M56: 194764 | N56: 261959 | O56: 299367
B57: 預り金 | C57: 0 | D57: 0 | E57: 720 | F57: 1440 | G57: 14412 | H57: 15132 | I57: 18195 | J57: 6126 | K57: 9189 | L57: 12252 | M57: 15315 | N57: 18378 | O57: 21441
B58: 仮受金 | C58: 21421 | D58: -1101 | E58: -48041 | F58: -35820 | G58: -10303 | H58: 5031 | I58: 106718 | J58: 18300 | K58: 70307 | L58: -185 | M58: 0 | N58: 30000 | O58: 11080
B59: 未払消費税 | C59: 135600 | D59: 135600 | E59: 0 | F59: 0 | G59: 0 | H59: 0 | I59: 0 | J59: 0 | K59: 0 | L59: 0 | M59: 0 | N59: 0 | O59: 0
B60: 未払法人税等 | C60: 70000 | D60: 70000 | E60: 0 | F60: 0 | G60: 0 | H60: 0 | I60: 0 | J60: 0 | K60: 0 | L60: 0 | M60: 0 | N60: 0 | O60: 0
B61: 仮受消費税 | C61: 0 | D61: 62283 | E61: 118267 | F61: 175432 | G61: 232599 | H61: 280853 | I61: 337660 | J61: 394964 | K61: 451579 | L61: 515925 | M61: 618986 | N61: 708026 | O61: 806873
B62: 助成引当
B63: 一年以内返済長期借入金 | C63: 1200000 | D63: 1200000 | E63: 1200000 | F63: 1200000 | G63: 1200000 | H63: 1200000 | I63: 1200000 | J63: 1200000 | K63: 1200000 | L63: 1200000 | M63: 0 | N63: 0 | O63: 0
A64: その他流動負債合計 | C64: 1831418 | D64: 1993964 | E64: 1795163 | F64: 1946745 | G64: 2019333 | H64: 2051645 | I64: 2311083 | J64: 2135480 | K64: 2212636 | L64: 2245193 | M64: 1144317 | N64: 1320040 | O64: 1410438
A65: 流動負債合計 | C65: 1831418 | D65: 1993964 | E65: 1795163 | F65: 1946745 | G65: 2019333 | H65: 2051645 | I65: 2311083 | J65: 2135480 | K65: 2212636 | L65: 2245193 | M65: 1144317 | N65: 1320040 | O65: 1410438
A66: 固定負債
B67: 長期借入金 | C67: 8800000 | D67: 8800000 | E67: 8800000 | F67: 8800000 | G67: 8800000 | H67: 8800000 | I67: 8800000 | J67: 8800000 | K67: 8800000 | L67: 8800000 | M67: 10000000 | N67: 10000000 | O67: 10000000
A68: 固定負債合計 | C68: 8800000 | D68: 8800000 | E68: 8800000 | F68: 8800000 | G68: 8800000 | H68: 8800000 | I68: 8800000 | J68: 8800000 | K68: 8800000 | L68: 8800000 | M68: 10000000 | N68: 10000000 | O68: 10000000
A69: 負債の部合計 | C69: 10631418 | D69: 10793964 | E69: 10595163 | F69: 10746745 | G69: 10819333 | H69: 10851645 | I69: 11111083 | J69: 10935480 | K69: 11012636 | L69: 11045193 | M69: 11144317 | N69: 11320040 | O69: 11410438
A70: 純資産の部
A71: 株主資本
A72: 資本金
B73: 資本金 | C73: 3000000 | D73: 3000000 | E73: 3000000 | F73: 3000000 | G73: 3000000 | H73: 3000000 | I73: 3000000 | J73: 3000000 | K73: 3000000 | L73: 3000000 | M73: 3000000 | N73: 3000000 | O73: 3000000
A74: 資本金合計 | C74: 3000000 | D74: 3000000 | E74: 3000000 | F74: 3000000 | G74: 3000000 | H74: 3000000 | I74: 3000000 | J74: 3000000 | K74: 3000000 | L74: 3000000 | M74: 3000000 | N74: 3000000 | O74: 3000000
A75: 新株式申込証拠金
A76: 新株式申込証拠金合計 | D76: 0 | E76: 0 | F76: 0 | G76: 0 | H76: 0 | I76: 0 | J76: 0 | K76: 0 | L76: 0 | M76: 0 | N76: 0 | O76: 0
A77: 資本剰余金
A78: 資本剰余金合計 | D78: 0 | E78: 0 | F78: 0 | G78: 0 | H78: 0 | I78: 0 | J78: 0 | K78: 0 | L78: 0 | M78: 0 | N78: 0 | O78: 0
A79: 利益剰余金
A80: 繰越利益剰余金 | C80: 6405406 | D80: 6121543 | E80: 6106751 | F80: 6016975 | G80: 5855171 | H80: 5804291 | I80: 5668895 | J80: 5559332 | K80: 5494278 | L80: 5475174 | M80: 5896281 | N80: 6102003 | O80: 6420857
A81: （うち当期純利益） | D81: -283863 | E81: -298655 | F81: -388431 | G81: -550235 | H81: -601115 | I81: -736511 | J81: -846074 | K81: -911128 | L81: -930232 | M81: -509125 | N81: -303403 | O81: 15451
A82: 利益剰余金合計 | C82: 6405406 | D82: 6121543 | E82: 6106751 | F82: 6016975 | G82: 5855171 | H82: 5804291 | I82: 5668895 | J82: 5559332 | K82: 5494278 | L82: 5475174 | M82: 5896281 | N82: 6102003 | O82: 6420857
A83: 自己株式
A84: 自己株式合計
A85: 自己株式申込証拠金
A86: 自己株式申込証拠金合計
A87: 株主資本合計 | C87: 9405406 | D87: 9121543 | E87: 9106751 | F87: 9016975 | G87: 8855171 | H87: 8804291 | I87: 8668895 | J87: 8559332 | K87: 8494278 | L87: 8475174 | M87: 8896281 | N87: 9102003 | O87: 9420857
A88: 評価・換算差額等
A89: 評価・換算差額等合計 | D89: 0 | E89: 0 | F89: 0 | G89: 0 | H89: 0 | I89: 0 | J89: 0 | K89: 0 | L89: 0 | M89: 0 | N89: 0 | O89: 0
A90: 新株予約権
A91: 新株予約権合計 | D91: 0 | E91: 0 | F91: 0 | G91: 0 | H91: 0 | I91: 0 | J91: 0 | K91: 0 | L91: 0 | M91: 0 | N91: 0 | O91: 0
A92: 純資産の部合計 | C92: 9405406 | D92: 9121543 | E92: 9106751 | F92: 9016975 | G92: 8855171 | H92: 8804291 | I92: 8668895 | J92: 8559332 | K92: 8494278 | L92: 8475174 | M92: 8896281 | N92: 9102003 | O92: 9420857
A93: 負債・純資産の部合計 | C93: 20036824 | D93: 19915507 | E93: 19701914 | F93: 19763720 | G93: 19674504 | H93: 19655936 | I93: 19779978 | J93: 19494812 | K93: 19506914 | L93: 19520367 | M93: 20040598 | N93: 20422043 | O93: 20831295
B94: [B/S CK] | C94: =IF(C93<>0,+IF(C47=C93,"OK",C47-C93),"") -> OK | D94: =IF(D93<>0,+IF(D47=D93,"OK",D47-D93),"") -> OK | E94: =IF(E93<>0,+IF(E47=E93,"OK",E47-E93),"") -> OK | F94: =IF(F93<>0,+IF(F47=F93,"OK",F47-F93),"") -> OK | G94: =IF(G93<>0,+IF(G47=G93,"OK",G47-G93),"") -> OK | H94: =IF(H93<>0,+IF(H47=H93,"OK",H47-H93),"") -> OK | I94: =IF(I93<>0,+IF(I47=I93,"OK",I47-I93),"") -> OK | J94: =IF(J93<>0,+IF(J47=J93,"OK",J47-J93),"") -> OK | ... O94: =IF(O93<>0,+IF(O47=O93,"OK",O47-O93),"") -> OK

Sheet BS千円
B1: 勘定科目 | C1: 期首残 | D1: 7月 | E1: 8月 | F1: =+月次BS!F1 -> 9 | G1: =+月次BS!G1 -> 10 | H1: =+月次BS!H1 -> 11 | I1: =+月次BS!I1 -> 12 | J1: =+月次BS!J1 -> 1 | K1: =+月次BS!K1 -> 2 | L1: =+月次BS!L1 -> 3 | M1: =+月次BS!M1 -> 4 | ... O1: =+月次BS!O1 -> 6
A2: =+月次BS!A2 -> 資産の部
A3: =+月次BS!A3 -> 流動資産
A4: =+月次BS!A4 -> 現金及び預金
A5: =+月次BS!A5 -> 0 | B5: =+月次BS!B5 -> 現金 | C5: =+月次BS!C5/1000 -> 0 | D5: =+月次BS!D5/1000 -> 0 | E5: =+月次BS!E5/1000 -> 0 | F5: =+月次BS!F5/1000 -> 0 | G5: =+月次BS!G5/1000 -> 0 | H5: =+月次BS!H5/1000 -> 0 | I5: =+月次BS!I5/1000 -> 0 | J5: =+月次BS!J5/1000 -> 0 | ... O5: =+月次BS!O5/1000 -> 0
A6: =+月次BS!A6 -> 0 | B6: =+月次BS!B6 -> 普通預金 | C6: =+月次BS!C6/1000 -> 0 | D6: =+月次BS!D6/1000 -> 0 | E6: =+月次BS!E6/1000 -> 0 | F6: =+月次BS!F6/1000 -> 0 | G6: =+月次BS!G6/1000 -> 0 | H6: =+月次BS!H6/1000 -> 0 | I6: =+月次BS!I6/1000 -> 0 | J6: =+月次BS!J6/1000 -> 0 | ... O6: =+月次BS!O6/1000 -> 0
A7: =+月次BS!A7 -> 現金及び預金合計 | B7: =+月次BS!B7 -> 0 | C7: =+月次BS!C7/1000 -> 2348.989 | D7: =+月次BS!D7/1000 -> 2725.169 | E7: =+月次BS!E7/1000 -> 1998.006 | F7: =+月次BS!F7/1000 -> 2031.109 | G7: =+月次BS!G7/1000 -> 1400.195 | H7: =+月次BS!H7/1000 -> 1532.912 | I7: =+月次BS!I7/1000 -> 1488.143 | J7: =+月次BS!J7/1000 -> 1217.238 | ... O7: =+月次BS!O7/1000 -> 4131.529
A8: =+月次BS!A8 -> 売上債権 | B8: =+月次BS!B8 -> 0 | C8: =+月次BS!C8/1000 -> 0 | D8: =+月次BS!D8/1000 -> 0 | E8: =+月次BS!E8/1000 -> 0 | F8: =+月次BS!F8/1000 -> 0 | G8: =+月次BS!G8/1000 -> 0 | H8: =+月次BS!H8/1000 -> 0 | I8: =+月次BS!I8/1000 -> 0 | J8: =+月次BS!J8/1000 -> 0 | ... O8: =+月次BS!O8/1000 -> 0
A9: =+月次BS!A9 -> 0 | B9: =+月次BS!B9 -> 売掛金 | C9: =+月次BS!C9/1000 -> 2838.186 | D9: =+月次BS!D9/1000 -> 3314.302 | E9: =+月次BS!E9/1000 -> 3820.128 | F9: =+月次BS!F9/1000 -> 4338.949 | G9: =+月次BS!G9/1000 -> 4857.796 | H9: =+月次BS!H9/1000 -> 5278.592 | I9: =+月次BS!I9/1000 -> 5913.222 | J9: =+月次BS!J9/1000 -> 6433.571 | ... O9: =+月次BS!O9/1000 -> 8976.617
A10: =+月次BS!A10 -> 売上債権合計 | B10: =+月次BS!B10 -> 0 | C10: =+月次BS!C10/1000 -> 2838.186 | D10: =+月次BS!D10/1000 -> 3314.302 | E10: =+月次BS!E10/1000 -> 3820.128 | F10: =+月次BS!F10/1000 -> 4338.949 | G10: =+月次BS!G10/1000 -> 4857.796 | H10: =+月次BS!H10/1000 -> 5278.592 | I10: =+月次BS!I10/1000 -> 5913.222 | J10: =+月次BS!J10/1000 -> 6433.571 | ... O10: =+月次BS!O10/1000 -> 8976.617
A11: =+月次BS!A11 -> 有価証券 | B11: =+月次BS!B11 -> 0 | C11: =+月次BS!C11/1000 -> 0 | D11: =+月次BS!D11/1000 -> 0 | E11: =+月次BS!E11/1000 -> 0 | F11: =+月次BS!F11/1000 -> 0 | G11: =+月次BS!G11/1000 -> 0 | H11: =+月次BS!H11/1000 -> 0 | I11: =+月次BS!I11/1000 -> 0 | J11: =+月次BS!J11/1000 -> 0 | ... O11: =+月次BS!O11/1000 -> 0
A12: =+月次BS!A12 -> 有価証券合計 | B12: =+月次BS!B12 -> 0 | C12: =+月次BS!C12/1000 -> 0 | D12: =+月次BS!D12/1000 -> 0 | E12: =+月次BS!E12/1000 -> 0 | F12: =+月次BS!F12/1000 -> 0 | G12: =+月次BS!G12/1000 -> 0 | H12: =+月次BS!H12/1000 -> 0 | I12: =+月次BS!I12/1000 -> 0 | J12: =+月次BS!J12/1000 -> 0 | ... O12: =+月次BS!O12/1000 -> 0
A13: =+月次BS!A13 -> 棚卸資産 | B13: =+月次BS!B13 -> 0 | C13: =+月次BS!C13/1000 -> 0 | D13: =+月次BS!D13/1000 -> 0 | E13: =+月次BS!E13/1000 -> 0 | F13: =+月次BS!F13/1000 -> 0 | G13: =+月次BS!G13/1000 -> 0 | H13: =+月次BS!H13/1000 -> 0 | I13: =+月次BS!I13/1000 -> 0 | J13: =+月次BS!J13/1000 -> 0 | ... O13: =+月次BS!O13/1000 -> 0
A14: =+月次BS!A14 -> 0 | B14: =+月次BS!B14 -> 商品 | C14: =+月次BS!C14/1000 -> 0 | D14: =+月次BS!D14/1000 -> 0 | E14: =+月次BS!E14/1000 -> 0 | F14: =+月次BS!F14/1000 -> 0 | G14: =+月次BS!G14/1000 -> 0 | H14: =+月次BS!H14/1000 -> 0 | I14: =+月次BS!I14/1000 -> 0 | J14: =+月次BS!J14/1000 -> 0 | ... O14: =+月次BS!O14/1000 -> 0
A15: =+月次BS!A15 -> 0 | B15: =+月次BS!B15 -> 貯蔵品 | C15: =+月次BS!C15/1000 -> 0 | D15: =+月次BS!D15/1000 -> 0 | E15: =+月次BS!E15/1000 -> 0 | F15: =+月次BS!F15/1000 -> 0 | G15: =+月次BS!G15/1000 -> 0 | H15: =+月次BS!H15/1000 -> 0 | I15: =+月次BS!I15/1000 -> 0 | J15: =+月次BS!J15/1000 -> 0 | ... O15: =+月次BS!O15/1000 -> 0
A16: =+月次BS!A16 -> 棚卸資産合計 | B16: =+月次BS!B16 -> 0 | C16: =+月次BS!C16/1000 -> 0 | D16: =+月次BS!D16/1000 -> 0 | E16: =+月次BS!E16/1000 -> 0 | F16: =+月次BS!F16/1000 -> 0 | G16: =+月次BS!G16/1000 -> 0 | H16: =+月次BS!H16/1000 -> 0 | I16: =+月次BS!I16/1000 -> 0 | J16: =+月次BS!J16/1000 -> 0 | ... O16: =+月次BS!O16/1000 -> 0
... A53: =+月次BS!A53 -> その他流動負債 | B53: =+月次BS!B53 -> 0 | C53: =+月次BS!C53/1000 -> 0 | D53: =+月次BS!D53/1000 -> 0 | E53: =+月次BS!E53/1000 -> 0 | F53: =+月次BS!F53/1000 -> 0 | G53: =+月次BS!G53/1000 -> 0 | H53: =+月次BS!H53/1000 -> 0 | I53: =+月次BS!I53/1000 -> 0 | J53: =+月次BS!J53/1000 -> 0 | ... O53: =+月次BS!O53/1000 -> 0
B54: =+月次BS!B54 -> 短期借入金 | C54: =+月次BS!C54/1000 -> 0 | D54: =+月次BS!D54/1000 -> 0 | E54: =+月次BS!E54/1000 -> 0 | F54: =+月次BS!F54/1000 -> 0 | G54: =+月次BS!G54/1000 -> 0 | H54: =+月次BS!H54/1000 -> 0 | I54: =+月次BS!I54/1000 -> 0 | J54: =+月次BS!J54/1000 -> 0 | ... O54: =+月次BS!O54/1000 -> 0
A55: =+月次BS!A55 -> 0 | B55: =+月次BS!B55 -> 未払金 | C55: =+月次BS!C55/1000 -> 250 | D55: =+月次BS!D55/1000 -> 250 | E55: =+月次BS!E55/1000 -> 349.28 | F55: =+月次BS!F55/1000 -> 349.28 | G55: =+月次BS!G55/1000 -> 349.28 | H55: =+月次BS!H55/1000 -> 349.28 | I55: =+月次BS!I55/1000 -> 301.677 | J55: =+月次BS!J55/1000 -> 301.677 | ... O55: =+月次BS!O55/1000 -> 271.677
A56: =+月次BS!A56 -> 0 | B56: =+月次BS!B56 -> 未払費用 | C56: =+月次BS!C56/1000 -> 154.397 | D56: =+月次BS!D56/1000 -> 277.182 | E56: =+月次BS!E56/1000 -> 174.937 | F56: =+月次BS!F56/1000 -> 256.413 | G56: =+月次BS!G56/1000 -> 233.345 | H56: =+月次BS!H56/1000 -> 201.349 | I56: =+月次BS!I56/1000 -> 346.833 | J56: =+月次BS!J56/1000 -> 214.413 | ... O56: =+月次BS!O56/1000 -> 299.367
A57: =+月次BS!A57 -> 0 | B57: =+月次BS!B57 -> 預り金 | C57: =+月次BS!C57/1000 -> 0 | D57: =+月次BS!D57/1000 -> 0 | E57: =+月次BS!E57/1000 -> 0.72 | F57: =+月次BS!F57/1000 -> 1.44 | G57: =+月次BS!G57/1000 -> 14.412 | H57: =+月次BS!H57/1000 -> 15.132 | I57: =+月次BS!I57/1000 -> 18.195 | J57: =+月次BS!J57/1000 -> 6.126 | ... O57: =+月次BS!O57/1000 -> 21.441
A58: =+月次BS!A58 -> 0 | B58: =+月次BS!B58 -> 仮受金 | C58: =+月次BS!C58/1000 -> 21.421 | D58: =+月次BS!D58/1000 -> -1.101 | E58: =+月次BS!E58/1000 -> -48.041 | F58: =+月次BS!F58/1000 -> -35.82 | G58: =+月次BS!G58/1000 -> -10.303 | H58: =+月次BS!H58/1000 -> 5.031 | I58: =+月次BS!I58/1000 -> 106.718 | J58: =+月次BS!J58/1000 -> 18.3 | ... O58: =+月次BS!O58/1000 -> 11.08
A59: =+月次BS!A59 -> 0 | B59: =+月次BS!B59 -> 未払消費税 | C59: =+月次BS!C59/1000 -> 135.6 | D59: =+月次BS!D59/1000 -> 135.6 | E59: =+月次BS!E59/1000 -> 0 | F59: =+月次BS!F59/1000 -> 0 | G59: =+月次BS!G59/1000 -> 0 | H59: =+月次BS!H59/1000 -> 0 | I59: =+月次BS!I59/1000 -> 0 | J59: =+月次BS!J59/1000 -> 0 | ... O59: =+月次BS!O59/1000 -> 0
A60: =+月次BS!A60 -> 0 | B60: =+月次BS!B60 -> 未払法人税等 | C60: =+月次BS!C60/1000 -> 70 | D60: =+月次BS!D60/1000 -> 70 | E60: =+月次BS!E60/1000 -> 0 | F60: =+月次BS!F60/1000 -> 0 | G60: =+月次BS!G60/1000 -> 0 | H60: =+月次BS!H60/1000 -> 0 | I60: =+月次BS!I60/1000 -> 0 | J60: =+月次BS!J60/1000 -> 0 | ... O60: =+月次BS!O60/1000 -> 0
A61: =+月次BS!A61 -> 0 | B61: =+月次BS!B61 -> 仮受消費税 | C61: =+月次BS!C61/1000 -> 0 | D61: =+月次BS!D61/1000 -> 62.283 | E61: =+月次BS!E61/1000 -> 118.267 | F61: =+月次BS!F61/1000 -> 175.432 | G61: =+月次BS!G61/1000 -> 232.599 | H61: =+月次BS!H61/1000 -> 280.853 | I61: =+月次BS!I61/1000 -> 337.66 | J61: =+月次BS!J61/1000 -> 394.964 | ... O61: =+月次BS!O61/1000 -> 806.873
A62: =+月次BS!A62 -> 0 | B62: =+月次BS!B62 -> 助成引当 | C62: =+月次BS!C62/1000 -> 0 | D62: =+月次BS!D62/1000 -> 0 | E62: =+月次BS!E62/1000 -> 0 | F62: =+月次BS!F62/1000 -> 0 | G62: =+月次BS!G62/1000 -> 0 | H62: =+月次BS!H62/1000 -> 0 | I62: =+月次BS!I62/1000 -> 0 | J62: =+月次BS!J62/1000 -> 0 | ... O62: =+月次BS!O62/1000 -> 0
A63: =+月次BS!A63 -> 0 | B63: =+月次BS!B63 -> 一年以内返済長期借入金 | C63: =+月次BS!C63/1000 -> 1200 | D63: =+月次BS!D63/1000 -> 1200 | E63: =+月次BS!E63/1000 -> 1200 | F63: =+月次BS!F63/1000 -> 1200 | G63: =+月次BS!G63/1000 -> 1200 | H63: =+月次BS!H63/1000 -> 1200 | I63: =+月次BS!I63/1000 -> 1200 | J63: =+月次BS!J63/1000 -> 1200 | ... O63: =+月次BS!O63/1000 -> 0
A64: =+月次BS!A64 -> その他流動負債合計 | B64: =+月次BS!B64 -> 0 | C64: =+月次BS!C64/1000 -> 1831.418 | D64: =+月次BS!D64/1000 -> 1993.964 | E64: =+月次BS!E64/1000 -> 1795.163 | F64: =+月次BS!F64/1000 -> 1946.745 | G64: =+月次BS!G64/1000 -> 2019.333 | H64: =+月次BS!H64/1000 -> 2051.645 | I64: =+月次BS!I64/1000 -> 2311.083 | J64: =+月次BS!J64/1000 -> 2135.48 | ... O64: =+月次BS!O64/1000 -> 1410.438
A65: =+月次BS!A65 -> 流動負債合計 | B65: =+月次BS!B65 -> 0 | C65: =+月次BS!C65/1000 -> 1831.418 | D65: =+月次BS!D65/1000 -> 1993.964 | E65: =+月次BS!E65/1000 -> 1795.163 | F65: =+月次BS!F65/1000 -> 1946.745 | G65: =+月次BS!G65/1000 -> 2019.333 | H65: =+月次BS!H65/1000 -> 2051.645 | I65: =+月次BS!I65/1000 -> 2311.083 | J65: =+月次BS!J65/1000 -> 2135.48 | ... O65: =+月次BS!O65/1000 -> 1410.438
A66: =+月次BS!A66 -> 固定負債 | B66: =+月次BS!B66 -> 0 | C66: =+月次BS!C66/1000 -> 0 | D66: =+月次BS!D66/1000 -> 0 | E66: =+月次BS!E66/1000 -> 0 | F66: =+月次BS!F66/1000 -> 0 | G66: =+月次BS!G66/1000 -> 0 | H66: =+月次BS!H66/1000 -> 0 | I66: =+月次BS!I66/1000 -> 0 | J66: =+月次BS!J66/1000 -> 0 | ... O66: =+月次BS!O66/1000 -> 0
... A93: =+月次BS!A93 -> 負債・純資産の部合計 | B93: =+月次BS!B93 -> 0 | C93: =+月次BS!C93/1000 -> 20036.824 | D93: =+月次BS!D93/1000 -> 19915.507 | E93: =+月次BS!E93/1000 -> 19701.914 | F93: =+月次BS!F93/1000 -> 19763.72 | G93: =+月次BS!G93/1000 -> 19674.504 | H93: =+月次BS!H93/1000 -> 19655.936 | I93: =+月次BS!I93/1000 -> 19779.978 | J93: =+月次BS!J93/1000 -> 19494.812 | ... O93: =+月次BS!O93/1000 -> 20831.295
A94: =+月次BS!A95 -> 0 | B94: =+月次BS!B95 -> 0 | C94: =+月次BS!C95/1000 -> 0 | D94: =+月次BS!D95/1000 -> 0 | E94: =+月次BS!E95/1000 -> 0 | F94: =+月次BS!F95/1000 -> 0 | G94: =+月次BS!G95/1000 -> 0 | H94: =+月次BS!H95/1000 -> 0 | I94: =+月次BS!I95/1000 -> 0 | J94: =+月次BS!J95/1000 -> 0 | ... O94: =+月次BS!O95/1000 -> 0
A95: =+月次BS!A96 -> 0 | B95: 買掛未払債務 | C95: =+C51+C55+C56 -> 404.397 | D95: =+D51+D55+D56 -> 527.182 | E95: =+E51+E55+E56 -> 524.217 | F95: =+F51+F55+F56 -> 605.693 | G95: =+G51+G55+G56 -> 582.625 | H95: =+H51+H55+H56 -> 550.629 | I95: =+I51+I55+I56 -> 648.51 | J95: =+J51+J55+J56 -> 516.09 | ... O95: =+O51+O55+O56 -> 571.044
A96: =+月次BS!A97 -> 0 | B96: その他流動負債 | C96: =+C57+C58+C62+C61 -> 21.421 | D96: =+D57+D58+D62+D61 -> 61.182 | E96: =+E57+E58+E62+E61 -> 70.946 | F96: =+F57+F58+F62+F61 -> 141.052 | G96: =+G57+G58+G62+G61 -> 236.708 | H96: =+H57+H58+H62+H61 -> 301.016 | I96: =+I57+I58+I62+I61 -> 462.573 | J96: =+J57+J58+J62+J61 -> 419.39 | ... O96: =+O57+O58+O62+O61 -> 839.394
A97: =+月次BS!A98 -> 0 | B97: 有形・無形固定資産 | C97: =+C32+C35 -> 795 | D97: =+D32+D35 -> 768.5 | E97: =+E32+E35 -> 742 | F97: =+F32+F35 -> 715.5 | G97: =+G32+G35 -> 689 | H97: =+H32+H35 -> 662.5 | I97: =+I32+I35 -> 636 | J97: =+J32+J35 -> 609.5 | ... O97: =+O32+O35 -> 477
A98: =+月次BS!A99 -> 0 | B98: 長期借入金 | C98: =+C63+C67 -> 10000 | D98: =+D63+D67 -> 10000 | E98: =+E63+E67 -> 10000 | F98: =+F63+F67 -> 10000 | G98: =+G63+G67 -> 10000 | H98: =+H63+H67 -> 10000 | I98: =+I63+I67 -> 10000 | J98: =+J63+J67 -> 10000 | ... O98: =+O63+O67 -> 10000
A99: =+月次BS!A100 -> 0 | B99: =+B54 -> 短期借入金 | C99: =+C54 -> 0 | D99: =+D54 -> 0 | E99: =+E54 -> 0 | F99: =+F54 -> 0 | G99: =+G54 -> 0 | H99: =+H54 -> 0 | I99: =+I54 -> 0 | ... O99: =+O54 -> 0
A100: =+月次BS!A101 -> 0 | B100: 貸付金 | C100: =+月次BS!C101/1000 -> 0 | D100: =+月次BS!D101/1000 -> 0 | E100: =+月次BS!E101/1000 -> 0 | F100: =+月次BS!F101/1000 -> 0 | G100: =+月次BS!G101/1000 -> 0 | H100: =+月次BS!H101/1000 -> 0 | I100: =+月次BS!I101/1000 -> 0 | J100: =+月次BS!J101/1000 -> 0 | ... O100: =+月次BS!O101/1000 -> 0
A101: =+月次BS!A102 -> 0 | B101: =+月次BS!B102 -> 0 | C101: =+月次BS!C102/1000 -> 0 | D101: =+月次BS!D102/1000 -> 0 | E101: =+月次BS!E102/1000 -> 0 | F101: =+月次BS!F102/1000 -> 0 | G101: =+月次BS!G102/1000 -> 0 | H101: =+月次BS!H102/1000 -> 0 | I101: =+月次BS!I102/1000 -> 0 | J101: =+月次BS!J102/1000 -> 0 | ... O101: =+月次BS!O102/1000 -> 0
A102: =+月次BS!A103 -> 0 | B102: =+月次BS!B103 -> 0 | C102: =+月次BS!C103/1000 -> 0 | D102: =+月次BS!D103/1000 -> 0 | E102: =+月次BS!E103/1000 -> 0 | F102: =+月次BS!F103/1000 -> 0 | G102: =+月次BS!G103/1000 -> 0 | H102: =+月次BS!H103/1000 -> 0 | I102: =+月次BS!I103/1000 -> 0 | J102: =+月次BS!J103/1000 -> 0 | ... O102: =+月次BS!O103/1000 -> 0
A103: =+月次BS!A104 -> 0 | B103: =+月次BS!B104 -> 0 | C103: =+月次BS!C104/1000 -> 0 | D103: =+月次BS!D104/1000 -> 0 | E103: =+月次BS!E104/1000 -> 0 | F103: =+月次BS!F104/1000 -> 0 | G103: =+月次BS!G104/1000 -> 0 | H103: =+月次BS!H104/1000 -> 0 | I103: =+月次BS!I104/1000 -> 0 | J103: =+月次BS!J104/1000 -> 0 | ... O103: =+月次BS!O104/1000 -> 0

Sheet 月次PL
B1: 勘定科目 | C1: =+月次BS!D1 -> 7 | D1: =+月次BS!E1 -> 8 | E1: =+月次BS!F1 -> 9 | F1: =+月次BS!G1 -> 10 | G1: =+月次BS!H1 -> 11 | H1: =+月次BS!I1 -> 12 | I1: =+月次BS!J1 -> 1 | J1: =+月次BS!K1 -> 2 | ... N1: =+月次BS!O1 -> 6 | O1: 累計
A2: 売上高
B3: 売上高 | C3: 622833 | D3: 559842 | E3: 571656 | F3: 571680 | G3: 482542 | H3: 568075 | I3: 573045 | J3: 566158 | K3: 643467 | L3: 1030617 | M3: 890404 | N3: 988475 | O3: =SUM(C3:N3) -> 8068794
O4: =SUM(C4:N4) -> 0
O5: =SUM(C5:N5) -> 0
O6: =SUM(C6:N6) -> 0
O7: =SUM(C7:N7) -> 0
A8: 売上高合計 | C8: =+SUM(C3:C7) -> 622833 | D8: =+SUM(D3:D7) -> 559842 | E8: =+SUM(E3:E7) -> 571656 | F8: =+SUM(F3:F7) -> 571680 | G8: =+SUM(G3:G7) -> 482542 | H8: =+SUM(H3:H7) -> 568075 | I8: =+SUM(I3:I7) -> 573045 | J8: =+SUM(J3:J7) -> 566158 | ... N8: =+SUM(N3:N7) -> 988475 | O8: =SUM(C8:N8) -> 8068794
A9: 売上原価 | O9: =SUM(C9:N9) -> 0
O10: =SUM(C10:N10) -> 0
O11: =SUM(C11:N11) -> 0
O12: =SUM(C12:N12) -> 0
O13: =SUM(C13:N13) -> 0
O14: =SUM(C14:N14) -> 0
A15: 売上原価 | C15: =+C10+C11+C12-C13-C14 -> 0 | D15: =+D10+D11+D12-D13-D14 -> 0 | E15: =+E10+E11+E12-E13-E14 -> 0 | F15: =+F10+F11+F12-F13-F14 -> 0 | G15: =+G10+G11+G12-G13-G14 -> 0 | H15: =+H10+H11+H12-H13-H14 -> 0 | I15: =+I10+I11+I12-I13-I14 -> 0 | J15: =+J10+J11+J12-J13-J14 -> 0 | ... N15: =+N10+N11+N12-N13-N14 -> 0 | O15: =SUM(C15:N15) -> 0
A16: 売上総利益 | C16: =+C8-C15 -> 622833 | D16: =+D8-D15 -> 559842 | E16: =+E8-E15 -> 571656 | F16: =+F8-F15 -> 571680 | G16: =+G8-G15 -> 482542 | H16: =+H8-H15 -> 568075 | I16: =+I8-I15 -> 573045 | J16: =+J8-J15 -> 566158 | ... N16: =+N8-N15 -> 988475 | O16: =SUM(C16:N16) -> 8068794
A17: 販売費及び一般管理費 | O17: =SUM(C17:N17) -> 0
B18: 役員報酬 | C18: 0 | D18: 100000 | E18: 100000 | F18: 100000 | G18: 100000 | H18: 100000 | I18: 100000 | J18: 100000 | K18: 100000 | L18: 100000 | M18: 100000 | N18: 100000 | O18: =SUM(C18:N18) -> 1100000
B19: 給料賃金 | O19: =SUM(C19:N19) -> 0
B20: 賞与 | O20: =SUM(C20:N20) -> 0
B21: 雑給 | O21: =SUM(C21:N21) -> 0
B22: 法定福利費 | O22: =SUM(C22:N22) -> 0
B23: 福利厚生費 | O23: =SUM(C23:N23) -> 0
B24: 研修採用費
B25: 業務委託費 | C25: 535456 | D25: 231819 | E25: 231819 | F25: 231819 | G25: 231819 | H25: 231819 | I25: 231819 | J25: 231819 | K25: 231819 | L25: 231819 | M25: 231819 | N25: 231819 | O25: =SUM(C25:N25) -> 3085465
B26: 広告宣伝費 | O26: =SUM(C26:N26) -> 0
B27: 接待交際費 | C27: 13438 | D27: 50137 | E27: 103900 | F27: 12119 | G27: 30000 | H27: 158371 | I27: 87515 | J27: 113663 | K27: 172618 | L27: 89768 | M27: 95002 | N27: 111724 | O27: =SUM(C27:N27) -> 1038255
B28: 旅費交通費 | C28: 9720 | D28: 5371 | E28: 8966 | F28: 74104 | G28: 6693 | H28: 1928 | I28: 101043 | J28: 5547 | K28: 1091 | L28: 0 | M28: 57464 | N28: 24862 | O28: =SUM(C28:N28) -> 296789
B29: 通信費 | C29: 1200 | D29: 55560 | E29: 54960 | F29: 1200 | G29: 1200 | H29: 78960 | I29: 3837 | J29: 57597 | K29: 18513 | L29: 27326 | M29: 71599 | N29: 62331 | O29: =SUM(C29:N29) -> 434283
B30: 水道光熱費 | O30: =SUM(C30:N30) -> 0
B31: 修繕費 | O31: =SUM(C31:N31) -> 0
B32: 消耗品費 | C32: 4797 | D32: 0 | E32: 0 | F32: 0 | G32: 0 | H32: 0 | I32: 0 | J32: 0 | K32: 0 | L32: 39584 | M32: 10200 | N32: 0 | O32: =SUM(C32:N32) -> 54581
B33: リース料 | O33: =SUM(C33:N33) -> 0
B34: 地代家賃 | C34: 44500 | D34: 44500 | E34: 44500 | F34: 44500 | G34: 44500 | H34: 44500 | I34: 44500 | J34: 44500 | K34: 44500 | L34: 44500 | M34: 44500 | N34: 44500 | O34: =SUM(C34:N34) -> 534000
B35: 賃借料 | O35: =SUM(C35:N35) -> 0
B36: 保険料 | C36: 5000 | D36: 5000 | E36: 5000 | F36: 5000 | G36: 5000 | H36: 5000 | I36: 5000 | J36: 5000 | K36: 5000 | L36: 5000 | M36: 5000 | N36: 5000 | O36: =SUM(C36:N36) -> 60000
B37: 租税公課 | C37: 0 | D37: 0 | E37: 0 | F37: 0 | G37: 1200 | H37: 0 | I37: 600 | J37: 0 | K37: 0 | L37: 0 | M37: 0 | N37: 0 | O37: =SUM(C37:N37) -> 1800
B38: 支払手数料 | C38: 12455 | D38: 1955 | E38: 2105 | F38: 2255 | G38: 7469 | H38: 4353 | I38: 4694 | J38: 2155 | K38: 2255 | L38: 2105 | M38: 2105 | N38: 2105 | O38: =SUM(C38:N38) -> 46011
B39: 会議費 | C39: 84497 | D39: 10447 | E39: 11637 | F39: 67568 | G39: 49291 | H39: 22016 | I39: 45376 | J39: 13067 | K39: 27771 | L39: 13158 | M39: 10469 | N39: 27614 | O39: =SUM(C39:N39) -> 382911
B40: 新聞図書費 | C40: 0 | D40: 1990 | E40: 1990 | F40: 891 | G40: 891 | H40: 891 | I40: 891 | J40: 3919 | K40: 891 | L40: 891 | M40: 891 | N40: 0 | O40: =SUM(C40:N40) -> 14136
B41: 減価償却費 | C41: 26500 | D41: 26500 | E41: 26500 | F41: 26500 | G41: 26500 | H41: 26500 | I41: 26500 | J41: 26500 | K41: 26500 | L41: 26500 | M41: 26500 | N41: 26500 | O41: =SUM(C41:N41) -> 318000
B42: 雑費 | C42: 640 | D42: 640 | E42: 640 | F42: 19035 | G42: 640 | H42: 640 | I42: 2340 | J42: 640 | K42: 3640 | L42: 640 | M42: 640 | N42: 5186 | O42: =SUM(C42:N42) -> 35321
B43: 管理諸費 | C43: 20000 | D43: 20000 | E43: 20000 | F43: 140000 | G43: 20000 | H43: 20000 | I43: 20000 | J43: 20000 | K43: 20000 | L43: 20000 | M43: 20000 | N43: 20000 | O43: =SUM(C43:N43) -> 360000
B44: 市場調査費 | C44: 140000 | D44: 14004 | E44: 42383 | F44: 0 | G44: 0 | H44: 0 | I44: 0 | J44: 0 | K44: 0 | L44: 0 | M44: 0 | N44: 0 | O44: =SUM(C44:N44) -> 196387
A45: 販売費及び一般管理費合計 | C45: =+SUM(C18:C44) -> 898203 | D45: =+SUM(D18:D44) -> 567923 | E45: =+SUM(E18:E44) -> 654400 | F45: =+SUM(F18:F44) -> 724991 | G45: =+SUM(G18:G44) -> 525203 | H45: =+SUM(H18:H44) -> 694978 | I45: =+SUM(I18:I44) -> 674115 | J45: =+SUM(J18:J44) -> 624407 | ... N45: =+SUM(N18:N44) -> 661641 | O45: =SUM(C45:N45) -> 7957939
A46: 営業利益 | C46: =+C16-C45 -> -275370 | D46: =+D16-D45 -> -8081 | E46: =+E16-E45 -> -82744 | F46: =+F16-F45 -> -153311 | G46: =+G16-G45 -> -42661 | H46: =+H16-H45 -> -126903 | I46: =+I16-I45 -> -101070 | J46: =+J16-J45 -> -58249 | ... N46: =+N16-N45 -> 326834 | O46: =SUM(C46:N46) -> 110855
A47: 営業外収益 | O47: =SUM(C47:N47) -> 0
B48: 受取利息 | C48: 0 | D48: 1782 | E48: 560 | F48: 0 | G48: 0 | H48: 0 | I48: 0 | J48: 866 | K48: 520 | L48: 0 | M48: 0 | N48: 0 | O48: =SUM(C48:N48) -> 3728
B49: 受取配当金 | C49: 0 | D49: 0 | E49: 0 | F49: 0 | G49: 0 | H49: 0 | I49: 0 | J49: 0 | K49: 0 | L49: 0 | M49: 0 | N49: 239 | O49: =SUM(C49:N49) -> 239
B50: 雑収入 | C50: 0 | D50: 0 | E50: 627 | F50: 0 | G50: 0 | H50: 0 | I50: 0 | J50: 0 | K50: 0 | L50: 0 | M50: 0 | N50: 0 | O50: =SUM(C50:N50) -> 627
A51: 営業外収益合計 | C51: 0 | D51: 1782 | E51: 1187 | F51: 0 | G51: 0 | H51: 0 | I51: 0 | J51: 866 | K51: 520 | L51: 0 | M51: 0 | N51: 239 | O51: =SUM(C51:N51) -> 4594
A52: 営業外費用 | O52: =SUM(C52:N52) -> 0
B53: 支払利息 | C53: 8493 | D53: 8493 | E53: 8219 | F53: 8493 | G53: 8219 | H53: 8493 | I53: 8493 | J53: 7671 | K53: 8493 | L53: 8219 | M53: 8493 | N53: 8219 | O53: =SUM(C53:N53) -> 99998
B54: 雑損失 | O54: =SUM(C54:N54) -> 0
B55: 補助事業費 | O55: =SUM(C55:N55) -> 0
A56: 営業外費用合計 | C56: 8493 | D56: 8493 | E56: 8219 | F56: 8493 | G56: 8219 | H56: 8493 | I56: 8493 | J56: 7671 | K56: 8493 | L56: 8219 | M56: 8493 | N56: 8219 | O56: =SUM(C56:N56) -> 99998
A57: 経常利益 | C57: =+C46+C51-C56 -> -283863 | D57: =+D46+D51-D56 -> -14792 | E57: =+E46+E51-E56 -> -89776 | F57: =+F46+F51-F56 -> -161804 | G57: =+G46+G51-G56 -> -50880 | H57: =+H46+H51-H56 -> -135396 | I57: =+I46+I51-I56 -> -109563 | J57: =+J46+J51-J56 -> -65054 | ... N57: =+N46+N51-N56 -> 318854 | O57: =SUM(C57:N57) -> 15451
A58: 特別利益 | O58: =SUM(C58:N58) -> 0
A59: 特別利益合計 | O59: =SUM(C59:N59) -> 0
A60: 特別損失 | O60: =SUM(C60:N60) -> 0
A61: 特別損失合計 | O61: =SUM(C61:N61) -> 0
A62: 当期純損益 | O62: =SUM(C62:N62) -> 0
A63: 税引前当期純利益 | C63: =+C57+C59-C61 -> -283863 | D63: =+D57+D59-D61 -> -14792 | E63: =+E57+E59-E61 -> -89776 | F63: =+F57+F59-F61 -> -161804 | G63: =+G57+G59-G61 -> -50880 | H63: =+H57+H59-H61 -> -135396 | I63: =+I57+I59-I61 -> -109563 | J63: =+J57+J59-J61 -> -65054 | ... N63: =+N57+N59-N61 -> 318854 | O63: =SUM(C63:N63) -> 15451
B64: 法人税等 | C64: 0 | D64: 0 | E64: 0 | F64: 0 | G64: 0 | H64: 0 | I64: 0 | J64: 0 | O64: =SUM(C64:N64) -> 0
A65: 当期純利益 | C65: =+C63-C64 -> -283863 | D65: =+D63-D64 -> -14792 | E65: =+E63-E64 -> -89776 | F65: =+F63-F64 -> -161804 | G65: =+G63-G64 -> -50880 | H65: =+H63-H64 -> -135396 | I65: =+I63-I64 -> -109563 | J65: =+J63-J64 -> -65054 | ... N65: =+N63-N64 -> 318854 | O65: =SUM(C65:N65) -> 15451

Sheet 決算予測
A1: ■決算着地予測
B2: 勘定科目 | C2: =+月次BS!D1 -> 7 | D2: =+月次BS!E1 -> 8 | E2: =+月次BS!F1 -> 9 | F2: =+月次BS!G1 -> 10 | G2: =+月次BS!H1 -> 11 | H2: =+月次BS!I1 -> 12 | I2: =+月次BS!J1 -> 1 | J2: =+月次BS!K1 -> 2 | ... N2: =+月次BS!O1 -> 6 | O2: 累計
A3: 売上高
B4: 売上高 | C4: =+月次PL!C3 -> 622833 | D4: =+月次PL!D3 -> 559842 | E4: =+月次PL!E3 -> 571656 | F4: =+月次PL!F3 -> 571680 | G4: =+月次PL!G3 -> 482542 | H4: =+月次PL!H3 -> 568075 | I4: =+月次PL!I3 -> 573045 | J4: =+月次PL!J3 -> 566158 | ... M4: =+月次PL!M3 -> 890404 | N4: =932914+100000 -> 1032914 | O4: =SUM(C4:N4) -> 8113233 | P4: ライフワーク計画値
O5: =SUM(C5:N5) -> 0
O6: =SUM(C6:N6) -> 0
O7: =SUM(C7:N7) -> 0
O8: =SUM(C8:N8) -> 0
A9: 売上高合計 | C9: =+SUM(C4:C8) -> 622833 | D9: =+SUM(D4:D8) -> 559842 | E9: =+SUM(E4:E8) -> 571656 | F9: =+SUM(F4:F8) -> 571680 | G9: =+SUM(G4:G8) -> 482542 | H9: =+SUM(H4:H8) -> 568075 | I9: =+SUM(I4:I8) -> 573045 | J9: =+SUM(J4:J8) -> 566158 | ... N9: =+SUM(N4:N8) -> 1032914 | O9: =SUM(C9:N9) -> 8113233
A10: 売上原価 | O10: =SUM(C10:N10) -> 0
O11: =SUM(C11:N11) -> 0
O12: =SUM(C12:N12) -> 0
O13: =SUM(C13:N13) -> 0
O14: =SUM(C14:N14) -> 0
O15: =SUM(C15:N15) -> 0
A16: 売上原価 | C16: =+C11+C12+C13-C14-C15 -> 0 | D16: =+D11+D12+D13-D14-D15 -> 0 | E16: =+E11+E12+E13-E14-E15 -> 0 | F16: =+F11+F12+F13-F14-F15 -> 0 | G16: =+G11+G12+G13-G14-G15 -> 0 | H16: =+H11+H12+H13-H14-H15 -> 0 | I16: =+I11+I12+I13-I14-I15 -> 0 | J16: =+J11+J12+J13-J14-J15 -> 0 | ... N16: =+N11+N12+N13-N14-N15 -> 0 | O16: =SUM(C16:N16) -> 0
A17: 売上総利益 | C17: =+C9-C16 -> 622833 | D17: =+D9-D16 -> 559842 | E17: =+E9-E16 -> 571656 | F17: =+F9-F16 -> 571680 | G17: =+G9-G16 -> 482542 | H17: =+H9-H16 -> 568075 | I17: =+I9-I16 -> 573045 | J17: =+J9-J16 -> 566158 | ... N17: =+N9-N16 -> 1032914 | O17: =SUM(C17:N17) -> 8113233
A18: 販売費及び一般管理費 | O18: =SUM(C18:N18) -> 0
B19: 役員報酬 | C19: =+月次PL!C18 -> 0 | D19: =+月次PL!D18 -> 100000 | E19: =+月次PL!E18 -> 100000 | F19: =+月次PL!F18 -> 100000 | G19: =+月次PL!G18 -> 100000 | H19: =+月次PL!H18 -> 100000 | I19: =+月次PL!I18 -> 100000 | J19: =+月次PL!J18 -> 100000 | ... M19: =+月次PL!M18 -> 100000 | N19: =+M19 -> 100000 | O19: =SUM(C19:N19) -> 1100000 | P19: 前月実績値
B20: 給料賃金 | O20: =SUM(C20:N20) -> 0
B21: 賞与 | O21: =SUM(C21:N21) -> 0
B22: 雑給 | O22: =SUM(C22:N22) -> 0
B23: 法定福利費 | O23: =SUM(C23:N23) -> 0
B24: 福利厚生費 | O24: =SUM(C24:N24) -> 0
B25: 研修採用費
B26: 業務委託費 | C26: =+月次PL!C25 -> 535456 | D26: =+月次PL!D25 -> 231819 | E26: =+月次PL!E25 -> 231819 | F26: =+月次PL!F25 -> 231819 | G26: =+月次PL!G25 -> 231819 | H26: =+月次PL!H25 -> 231819 | I26: =+月次PL!I25 -> 231819 | J26: =+月次PL!J25 -> 231819 | ... M26: =+月次PL!M25 -> 231819 | N26: =+M26 -> 231819 | O26: =SUM(C26:N26) -> 3085465 | P26: 前月実績値
B27: 広告宣伝費 | O27: =SUM(C27:N27) -> 0 | P27: 今期実績平均
B28: 接待交際費 | C28: =+月次PL!C27 -> 13438 | D28: =+月次PL!D27 -> 50137 | E28: =+月次PL!E27 -> 103900 | F28: =+月次PL!F27 -> 12119 | G28: =+月次PL!G27 -> 30000 | H28: =+月次PL!H27 -> 158371 | I28: =+月次PL!I27 -> 87515 | J28: =+月次PL!J27 -> 113663 | ... M28: =+月次PL!M27 -> 95002 | N28: =+P28 -> 84230.091 | O28: =SUM(C28:N28) -> 1010761.1 | P28: =SUM(C28:M28)/11 -> 84230.091
B29: 旅費交通費 | C29: =+月次PL!C28 -> 9720 | D29: =+月次PL!D28 -> 5371 | E29: =+月次PL!E28 -> 8966 | F29: =+月次PL!F28 -> 74104 | G29: =+月次PL!G28 -> 6693 | H29: =+月次PL!H28 -> 1928 | I29: =+月次PL!I28 -> 101043 | J29: =+月次PL!J28 -> 5547 | ... M29: =+月次PL!M28 -> 57464 | N29: =+P29 -> 24720.636 | O29: =SUM(C29:N29) -> 296647.64 | P29: =SUM(C29:M29)/11 -> 24720.636
B30: 通信費 | C30: =+月次PL!C29 -> 1200 | D30: =+月次PL!D29 -> 55560 | E30: =+月次PL!E29 -> 54960 | F30: =+月次PL!F29 -> 1200 | G30: =+月次PL!G29 -> 1200 | H30: =+月次PL!H29 -> 78960 | I30: =+月次PL!I29 -> 3837 | J30: =+月次PL!J29 -> 57597 | ... M30: =+月次PL!M29 -> 71599 | N30: =+P30 -> 33813.818 | O30: =SUM(C30:N30) -> 405765.82 | P30: =SUM(C30:M30)/11 -> 33813.818
B31: 水道光熱費 | C31: =+月次PL!C30 -> 0 | D31: =+月次PL!D30 -> 0 | E31: =+月次PL!E30 -> 0 | F31: =+月次PL!F30 -> 0 | G31: =+月次PL!G30 -> 0 | H31: =+月次PL!H30 -> 0 | I31: =+月次PL!I30 -> 0 | J31: =+月次PL!J30 -> 0 | ... M31: =+月次PL!M30 -> 0 | N31: =+P31 -> 0 | O31: =SUM(C31:N31) -> 0 | P31: =SUM(C31:M31)/11 -> 0
B32: 修繕費 | C32: =+月次PL!C31 -> 0 | D32: =+月次PL!D31 -> 0 | E32: =+月次PL!E31 -> 0 | F32: =+月次PL!F31 -> 0 | G32: =+月次PL!G31 -> 0 | H32: =+月次PL!H31 -> 0 | I32: =+月次PL!I31 -> 0 | J32: =+月次PL!J31 -> 0 | ... M32: =+月次PL!M31 -> 0 | N32: =+P32 -> 0 | O32: =SUM(C32:N32) -> 0 | P32: =SUM(C32:M32)/11 -> 0
B33: 消耗品費 | C33: =+月次PL!C32 -> 4797 | D33: =+月次PL!D32 -> 0 | E33: =+月次PL!E32 -> 0 | F33: =+月次PL!F32 -> 0 | G33: =+月次PL!G32 -> 0 | H33: =+月次PL!H32 -> 0 | I33: =+月次PL!I32 -> 0 | J33: =+月次PL!J32 -> 0 | ... M33: =+月次PL!M32 -> 10200 | N33: =+P33 -> 4961.9091 | O33: =SUM(C33:N33) -> 59542.909 | P33: =SUM(C33:M33)/11 -> 4961.9091
B34: リース料 | C34: =+月次PL!C33 -> 0 | D34: =+月次PL!D33 -> 0 | E34: =+月次PL!E33 -> 0 | F34: =+月次PL!F33 -> 0 | G34: =+月次PL!G33 -> 0 | H34: =+月次PL!H33 -> 0 | I34: =+月次PL!I33 -> 0 | J34: =+月次PL!J33 -> 0 | ... M34: =+月次PL!M33 -> 0 | N34: =+P34 -> 0 | O34: =SUM(C34:N34) -> 0 | P34: =SUM(C34:M34)/11 -> 0
B35: 地代家賃 | C35: =+月次PL!C34 -> 44500 | D35: =+月次PL!D34 -> 44500 | E35: =+月次PL!E34 -> 44500 | F35: =+月次PL!F34 -> 44500 | G35: =+月次PL!G34 -> 44500 | H35: =+月次PL!H34 -> 44500 | I35: =+月次PL!I34 -> 44500 | J35: =+月次PL!J34 -> 44500 | ... M35: =+月次PL!M34 -> 44500 | N35: =+P35 -> 44500 | O35: =SUM(C35:N35) -> 534000 | P35: =SUM(C35:M35)/11 -> 44500
B36: 賃借料 | C36: =+月次PL!C35 -> 0 | D36: =+月次PL!D35 -> 0 | E36: =+月次PL!E35 -> 0 | F36: =+月次PL!F35 -> 0 | G36: =+月次PL!G35 -> 0 | H36: =+月次PL!H35 -> 0 | I36: =+月次PL!I35 -> 0 | J36: =+月次PL!J35 -> 0 | ... M36: =+月次PL!M35 -> 0 | N36: =+P36 -> 0 | O36: =SUM(C36:N36) -> 0 | P36: =SUM(C36:M36)/11 -> 0
B37: 保険料 | C37: =+月次PL!C36 -> 5000 | D37: =+月次PL!D36 -> 5000 | E37: =+月次PL!E36 -> 5000 | F37: =+月次PL!F36 -> 5000 | G37: =+月次PL!G36 -> 5000 | H37: =+月次PL!H36 -> 5000 | I37: =+月次PL!I36 -> 5000 | J37: =+月次PL!J36 -> 5000 | ... M37: =+月次PL!M36 -> 5000 | N37: =+P37 -> 5000 | O37: =SUM(C37:N37) -> 60000 | P37: =SUM(C37:M37)/11 -> 5000
B38: 租税公課 | C38: =+月次PL!C37 -> 0 | D38: =+月次PL!D37 -> 0 | E38: =+月次PL!E37 -> 0 | F38: =+月次PL!F37 -> 0 | G38: =+月次PL!G37 -> 1200 | H38: =+月次PL!H37 -> 0 | I38: =+月次PL!I37 -> 600 | J38: =+月次PL!J37 -> 0 | ... M38: =+月次PL!M37 -> 0 | N38: =+P38 -> 163.63636 | O38: =SUM(C38:N38) -> 1963.6364 | P38: =SUM(C38:M38)/11 -> 163.63636
B39: 支払手数料 | C39: =+月次PL!C38 -> 12455 | D39: =+月次PL!D38 -> 1955 | E39: =+月次PL!E38 -> 2105 | F39: =+月次PL!F38 -> 2255 | G39: =+月次PL!G38 -> 7469 | H39: =+月次PL!H38 -> 4353 | I39: =+月次PL!I38 -> 4694 | J39: =+月次PL!J38 -> 2155 | ... M39: =+月次PL!M38 -> 2105 | N39: =+P39 -> 3991.4545 | O39: =SUM(C39:N39) -> 47897.455 | P39: =SUM(C39:M39)/11 -> 3991.4545
... B45: 市場調査費 | C45: =+月次PL!C44 -> 140000 | D45: =+月次PL!D44 -> 14004 | E45: =+月次PL!E44 -> 42383 | F45: =+月次PL!F44 -> 0 | G45: =+月次PL!G44 -> 0 | H45: =+月次PL!H44 -> 0 | I45: =+月次PL!I44 -> 0 | J45: =+月次PL!J44 -> 0 | ... M45: =+月次PL!M44 -> 0 | N45: =+P45 -> 17853.364 | O45: =SUM(C45:N45) -> 214240.36 | P45: =SUM(C45:M45)/11 -> 17853.364
A46: 販売費及び一般管理費合計 | C46: =+SUM(C19:C45) -> 898203 | D46: =+SUM(D19:D45) -> 567923 | E46: =+SUM(E19:E45) -> 654400 | F46: =+SUM(F19:F45) -> 724991 | G46: =+SUM(G19:G45) -> 525203 | H46: =+SUM(H19:H45) -> 694978 | I46: =+SUM(I19:I45) -> 674115 | J46: =+SUM(J19:J45) -> 624407 | ... N46: =+SUM(N19:N45) -> 644787.36 | O46: =SUM(C46:N46) -> 7941085.4
A47: 営業利益 | C47: =+C17-C46 -> -275370 | D47: =+D17-D46 -> -8081 | E47: =+E17-E46 -> -82744 | F47: =+F17-F46 -> -153311 | G47: =+G17-G46 -> -42661 | H47: =+H17-H46 -> -126903 | I47: =+I17-I46 -> -101070 | J47: =+J17-J46 -> -58249 | ... N47: =+N17-N46 -> 388126.64 | O47: =SUM(C47:N47) -> 172147.64
A48: 営業外収益 | O48: =SUM(C48:N48) -> 0
B49: 受取利息 | C49: =+月次PL!C48 -> 0 | D49: =+月次PL!D48 -> 1782 | E49: =+月次PL!E48 -> 560 | F49: =+月次PL!F48 -> 0 | G49: =+月次PL!G48 -> 0 | H49: =+月次PL!H48 -> 0 | I49: =+月次PL!I48 -> 0 | J49: =+月次PL!J48 -> 866 | ... M49: =+月次PL!M48 -> 0 | O49: =SUM(C49:N49) -> 3728 | P49: =SUM(C49:M49)/11 -> 338.90909
B50: 受取配当金 | O50: =SUM(C50:N50) -> 0 | P50: =SUM(C50:M50)/11 -> 0
B51: 雑収入 | C51: =+月次PL!C50 -> 0 | D51: =+月次PL!D50 -> 0 | E51: =+月次PL!E50 -> 627 | F51: =+月次PL!F50 -> 0 | G51: =+月次PL!G50 -> 0 | H51: =+月次PL!H50 -> 0 | I51: =+月次PL!I50 -> 0 | J51: =+月次PL!J50 -> 0 | ... M51: =+月次PL!M50 -> 0 | O51: =SUM(C51:N51) -> 627 | P51: =SUM(C51:M51)/11 -> 57
A52: 営業外収益合計 | C52: =+月次PL!C51 -> 0 | D52: =+月次PL!D51 -> 1782 | E52: =+月次PL!E51 -> 1187 | F52: =+月次PL!F51 -> 0 | G52: =+月次PL!G51 -> 0 | H52: =+月次PL!H51 -> 0 | I52: =+月次PL!I51 -> 0 | J52: =+月次PL!J51 -> 866 | ... M52: =+月次PL!M51 -> 0 | O52: =SUM(C52:N52) -> 4355
A53: 営業外費用 | O53: =SUM(C53:N53) -> 0
B54: 支払利息 | C54: =+月次PL!C53 -> 8493 | D54: =+月次PL!D53 -> 8493 | E54: =+月次PL!E53 -> 8219 | F54: =+月次PL!F53 -> 8493 | G54: =+月次PL!G53 -> 8219 | H54: =+月次PL!H53 -> 8493 | I54: =+月次PL!I53 -> 8493 | J54: =+月次PL!J53 -> 7671 | ... M54: =+月次PL!M53 -> 8493 | N54: =+P54 -> 8343.5455 | O54: =SUM(C54:N54) -> 100122.55 | P54: =SUM(C54:M54)/11 -> 8343.5455
B55: 雑損失 | O55: =SUM(C55:N55) -> 0 | P55: =SUM(C55:L55) -> 0
B56: 補助事業費 | O56: =SUM(C56:N56) -> 0 | P56: =SUM(C56:L56) -> 0
A57: 営業外費用合計 | C57: =+月次PL!C56 -> 8493 | D57: =+月次PL!D56 -> 8493 | E57: =+月次PL!E56 -> 8219 | F57: =+月次PL!F56 -> 8493 | G57: =+月次PL!G56 -> 8219 | H57: =+月次PL!H56 -> 8493 | I57: =+月次PL!I56 -> 8493 | J57: =+月次PL!J56 -> 7671 | ... M57: =+月次PL!M56 -> 8493 | N57: =+N54 -> 8343.5455 | O57: =SUM(C57:N57) -> 100122.55
A58: 経常利益 | C58: =+C47+C52-C57 -> -283863 | D58: =+D47+D52-D57 -> -14792 | E58: =+E47+E52-E57 -> -89776 | F58: =+F47+F52-F57 -> -161804 | G58: =+G47+G52-G57 -> -50880 | H58: =+H47+H52-H57 -> -135396 | I58: =+I47+I52-I57 -> -109563 | J58: =+J47+J52-J57 -> -65054 | ... N58: =+N47+N52-N57 -> 379783.09 | O58: =SUM(C58:N58) -> 76380.091
A59: 特別利益 | O59: =SUM(C59:N59) -> 0
A60: 特別利益合計 | O60: =SUM(C60:N60) -> 0
A61: 特別損失 | O61: =SUM(C61:N61) -> 0
A62: 特別損失合計 | O62: =SUM(C62:N62) -> 0
A63: 当期純損益 | O63: =SUM(C63:N63) -> 0
A64: 税引前当期純利益 | C64: =+C58+C60-C62 -> -283863 | D64: =+D58+D60-D62 -> -14792 | E64: =+E58+E60-E62 -> -89776 | F64: =+F58+F60-F62 -> -161804 | G64: =+G58+G60-G62 -> -50880 | H64: =+H58+H60-H62 -> -135396 | I64: =+I58+I60-I62 -> -109563 | J64: =+J58+J60-J62 -> -65054 | ... N64: =+N58+N60-N62 -> 379783.09 | O64: =SUM(C64:N64) -> 76380.091
B65: 法人税等 | C65: 0 | D65: 0 | E65: 0 | F65: 0 | G65: 0 | H65: 0 | I65: 0 | J65: 0 | O65: =SUM(C65:N65) -> 0
A66: 当期純利益 | C66: =+C64-C65 -> -283863 | D66: =+D64-D65 -> -14792 | E66: =+E64-E65 -> -89776 | F66: =+F64-F65 -> -161804 | G66: =+G64-G65 -> -50880 | H66: =+H64-H65 -> -135396 | I66: =+I64-I65 -> -109563 | J66: =+J64-J65 -> -65054 | ... N66: =+N64-N65 -> 379783.09 | O66: =SUM(C66:N66) -> 76380.091

Sheet PL推移
B2: CK | C2: 売上高 | D2: =IF(D10<>0,IF(D10=月次PL!C8/1000,"OK",PL推移!D10-月次PL!C8/1000),"nd") -> OK | F2: =IF(F10<>0,IF(月次PL!D8/1000=PL推移!F10,"OK",PL推移!F10-月次PL!D8/1000),"nd") -> OK | H2: =IF(H10<>0,IF(月次PL!E8/1000=PL推移!H10,"OK",PL推移!H10-月次PL!E8/1000),"nd") -> OK | J2: =IF(J10<>0,IF(月次PL!F8/1000=PL推移!J10,"OK",PL推移!J10-月次PL!F8/1000),"nd") -> OK | L2: =IF(L10<>0,IF(月次PL!G8/1000=PL推移!L10,"OK",PL推移!L10-月次PL!G8/1000),"nd") -> OK | N2: =IF(N10<>0,IF(月次PL!H8/1000=PL推移!N10,"OK",PL推移!N10-月次PL!H8/1000),"nd") -> OK | P2: =IF(P10<>0,IF(月次PL!I8/1000=PL推移!P10,"OK",PL推移!P10-月次PL!I8/1000),"nd") -> OK | R2: =IF(R10<>0,IF(月次PL!J8/1000=PL推移!R10,"OK",PL推移!R10-月次PL!J8/1000),"nd") -> OK | T2: =IF(T10<>0,IF(月次PL!K8/1000=PL推移!T10,"OK",PL推移!T10-月次PL!K8/1000),"nd") -> OK | V2: =IF(V10<>0,IF(月次PL!L8/1000=PL推移!V10,"OK",PL推移!V10-月次PL!L8/1000),"nd") -> OK | X2: =IF(X10<>0,IF(月次PL!M8/1000=PL推移!X10,"OK",PL推移!X10-月次PL!M8/1000),"nd") -> OK | Z2: =IF(Z10<>0,IF(月次PL!N8/1000=PL推移!Z10,"OK",PL推移!Z10-月次PL!N8/1000),"nd") -> OK
C3: 粗利益 | D3: =IF(D22<>0,IF(D22=月次PL!C16/1000,"OK",PL推移!D22-月次PL!C16/1000),"nd") -> OK | F3: =IF(F22<>0,IF(F22=月次PL!D16/1000,"OK",PL推移!F22-月次PL!D16/1000),"nd") -> OK | H3: =IF(H22<>0,IF(H22=月次PL!E16/1000,"OK",PL推移!H22-月次PL!E16/1000),"nd") -> OK | J3: =IF(J22<>0,IF(J22=月次PL!F16/1000,"OK",PL推移!J22-月次PL!F16/1000),"nd") -> OK | L3: =IF(L22<>0,IF(L22=月次PL!G16/1000,"OK",PL推移!L22-月次PL!G16/1000),"nd") -> OK | N3: =IF(N22<>0,IF(N22=月次PL!H16/1000,"OK",PL推移!N22-月次PL!H16/1000),"nd") -> OK | P3: =IF(P22<>0,IF(P22=月次PL!I16/1000,"OK",PL推移!P22-月次PL!I16/1000),"nd") -> OK | R3: =IF(R22<>0,IF(R22=月次PL!J16/1000,"OK",PL推移!R22-月次PL!J16/1000),"nd") -> OK | T3: =IF(T22<>0,IF(T22=月次PL!K16/1000,"OK",PL推移!T22-月次PL!K16/1000),"nd") -> OK | V3: =IF(V22<>0,IF(V22=月次PL!L16/1000,"OK",PL推移!V22-月次PL!L16/1000),"nd") -> OK | X3: =IF(X22<>0,IF(X22=月次PL!M16/1000,"OK",PL推移!X22-月次PL!M16/1000),"nd") -> OK | Z3: =IF(Z22<>0,IF(Z22=月次PL!N16/1000,"OK",PL推移!Z22-月次PL!N16/1000),"nd") -> OK
C4: 販管費 | D4: =IF(D28<>0,IF(D28=月次PL!C45/1000,"OK",PL推移!D28-月次PL!C45/1000),"nd") -> OK | F4: =IF(F28<>0,IF(F28=月次PL!D45/1000,"OK",PL推移!F28-月次PL!D45/1000),"nd") -> OK | H4: =IF(H28<>0,IF(H28=月次PL!E45/1000,"OK",PL推移!H28-月次PL!E45/1000),"nd") -> OK | J4: =IF(J28<>0,IF(J28=月次PL!F45/1000,"OK",PL推移!J28-月次PL!F45/1000),"nd") -> OK | L4: =IF(L28<>0,IF(L28=月次PL!G45/1000,"OK",PL推移!L28-月次PL!G45/1000),"nd") -> OK | N4: =IF(N28<>0,IF(N28=月次PL!H45/1000,"OK",PL推移!N28-月次PL!H45/1000),"nd") -> OK | P4: =IF(P28<>0,IF(P28=月次PL!I45/1000,"OK",PL推移!P28-月次PL!I45/1000),"nd") -> OK | R4: =IF(R28<>0,IF(R28=月次PL!J45/1000,"OK",PL推移!R28-月次PL!J45/1000),"nd") -> OK | T4: =IF(T28<>0,IF(T28=月次PL!K45/1000,"OK",PL推移!T28-月次PL!K45/1000),"nd") -> OK | V4: =IF(V28<>0,IF(V28=月次PL!L45/1000,"OK",PL推移!V28-月次PL!L45/1000),"nd") -> OK | X4: =IF(X28<>0,IF(X28=月次PL!M45/1000,"OK",PL推移!X28-月次PL!M45/1000),"nd") -> OK | Z4: =IF(Z28<>0,IF(Z28=月次PL!N45/1000,"OK",PL推移!Z28-月次PL!N45/1000),"nd") -> OK
C5: 営業利益 | D5: =IF(D50<>0,IF(D50=月次PL!C46/1000,"OK",PL推移!D50-月次PL!C46/1000),"nd") -> OK | F5: =IF(F50<>0,IF(F50=月次PL!D46/1000,"OK",PL推移!F50-月次PL!D46/1000),"nd") -> -1.7763568e-14 | H5: =IF(H50<>0,IF(H50=月次PL!E46/1000,"OK",PL推移!H50-月次PL!E46/1000),"nd") -> OK | J5: =IF(J50<>0,IF(J50=月次PL!F46/1000,"OK",PL推移!J50-月次PL!F46/1000),"nd") -> OK | L5: =IF(L50<>0,IF(L50=月次PL!G46/1000,"OK",PL推移!L50-月次PL!G46/1000),"nd") -> OK | N5: =IF(N50<>0,IF(N50=月次PL!H46/1000,"OK",PL推移!N50-月次PL!H46/1000),"nd") -> OK | P5: =IF(P50<>0,IF(P50=月次PL!I46/1000,"OK",PL推移!P50-月次PL!I46/1000),"nd") -> OK | R5: =IF(R50<>0,IF(R50=月次PL!J46/1000,"OK",PL推移!R50-月次PL!J46/1000),"nd") -> 9.2370556e-14 | T5: =IF(T50<>0,IF(T50=月次PL!K46/1000,"OK",PL推移!T50-月次PL!K46/1000),"nd") -> 1.4210855e-13 | V5: =IF(V50<>0,IF(V50=月次PL!L46/1000,"OK",PL推移!V50-月次PL!L46/1000),"nd") -> OK | X5: =IF(X50<>0,IF(X50=月次PL!M46/1000,"OK",PL推移!X50-月次PL!M46/1000),"nd") -> OK | Z5: =IF(Z50<>0,IF(Z50=月次PL!N46/1000,"OK",PL推移!Z50-月次PL!N46/1000),"nd") -> OK
C6: 経常利益 | D6: =IF(D54<>0,IF(D54=月次PL!C57/1000,"OK",PL推移!D54-月次PL!C57/1000),"nd") -> OK | F6: =IF(F54<>0,IF(F54=月次PL!D57/1000,"OK",PL推移!F54-月次PL!D57/1000),"nd") -> OK | H6: =IF(H54<>0,IF(H54=月次PL!E57/1000,"OK",PL推移!H54-月次PL!E57/1000),"nd") -> OK | J6: =IF(J54<>0,IF(J54=月次PL!F57/1000,"OK",PL推移!J54-月次PL!F57/1000),"nd") -> OK | L6: =IF(L54<>0,IF(L54=月次PL!G57/1000,"OK",PL推移!L54-月次PL!G57/1000),"nd") -> OK | N6: =IF(N54<>0,IF(N54=月次PL!H57/1000,"OK",PL推移!N54-月次PL!H57/1000),"nd") -> OK | P6: =IF(P54<>0,IF(P54=月次PL!I57/1000,"OK",PL推移!P54-月次PL!I57/1000),"nd") -> OK | R6: =IF(R54<>0,IF(R54=月次PL!J57/1000,"OK",PL推移!R54-月次PL!J57/1000),"nd") -> 8.5265128e-14 | T6: =IF(T54<>0,IF(T54=月次PL!K57/1000,"OK",PL推移!T54-月次PL!K57/1000),"nd") -> 1.4210855e-13 | V6: =IF(V54<>0,IF(V54=月次PL!L57/1000,"OK",PL推移!V54-月次PL!L57/1000),"nd") -> OK | X6: =IF(X54<>0,IF(X54=月次PL!M57/1000,"OK",PL推移!X54-月次PL!M57/1000),"nd") -> OK | Z6: =IF(Z54<>0,IF(Z54=月次PL!N57/1000,"OK",PL推移!Z54-月次PL!N57/1000),"nd") -> OK
B7: ■月次報告PL | D7: ㈱Ｓクリエイト | AH7: 注意事項 | AI7: 概算値 | AJ7: 異常値 | AK7: 特記事項 | AL7: 予算検討
B8: 2025 | C8: 年度 | D8: 単位：千円 | F8: 注意事項 | G8: 概算値 | H8: 異常値 | I8: 処理検討 | J8: 予算検討
B9: 項目 | D9: =+月次PL!C1 -> 7 | F9: =+月次PL!D1 -> 8 | H9: =+月次PL!E1 -> 9 | J9: =+月次PL!F1 -> 10 | L9: =+月次PL!G1 -> 11 | N9: =+月次PL!H1 -> 12 | P9: =+月次PL!I1 -> 1 | R9: =+月次PL!J1 -> 2 | T9: =+月次PL!K1 -> 3 | V9: =+月次PL!L1 -> 4 | X9: =+月次PL!M1 -> 5 | Z9: =+月次PL!N1 -> 6
B10: 売上高 | D10: =+月次PL!C8/1000 -> 622.833 | E10: =IF(D$10<>0,D10/D$10,0) -> 1 | F10: =+月次PL!D8/1000 -> 559.842 | G10: =IF(F$10<>0,F10/F$10,0) -> 1 | H10: =+月次PL!E8/1000 -> 571.656 | I10: =IF(H$10<>0,H10/H$10,0) -> 1 | J10: =+月次PL!F8/1000 -> 571.68 | K10: =IF(J$10<>0,J10/J$10,0) -> 1 | L10: =SUM(L11:L15) -> 482.542 | M10: =IF(L$10<>0,L10/L$10,0) -> 1 | N10: =SUM(N11:N15) -> 568.075 | O10: =IF(N$10<>0,N10/N$10,0) -> 1 | P10: =+月次PL!I8/1000 -> 573.045 | Q10: =IF(P$10<>0,P10/P$10,0) -> 1 | R10: =+月次PL!J8/1000 -> 566.158 | S10: =IF(R$10<>0,R10/R$10,0) -> 1 | T10: =+月次PL!K8/1000 -> 643.467 | U10: =IF(T$10<>0,T10/T$10,0) -> 1 | V10: =+月次PL!L3/1000 -> 1030.617 | W10: =IF(V$10<>0,V10/V$10,0) -> 1 | X10: =SUM(X11:X15) -> 890.404 | Y10: =IF(X$10<>0,X10/X$10,0) -> 1 | Z10: =+月次PL!N8/1000 -> 988.475 | AA10: =IF(Z$10<>0,Z10/Z$10,0) -> 1
C11: =+月次PL!B3 -> 売上高 | D11: =+月次PL!C3/1000 -> 622.833 | E11: =IF(D$10<>0,D11/D$10,0) -> 1 | F11: =+月次PL!D3/1000 -> 559.842 | G11: =IF(F$10<>0,F11/F$10,0) -> 1 | H11: =+月次PL!E3/1000 -> 571.656 | I11: =IF(H$10<>0,H11/H$10,0) -> 1 | J11: =+月次PL!F3/1000 -> 571.68 | K11: =IF(J$10<>0,J11/J$10,0) -> 1 | L11: =+月次PL!G3/1000 -> 482.542 | M11: =IF(L$10<>0,L11/L$10,0) -> 1 | N11: =+月次PL!H3/1000 -> 568.075 | O11: =IF(N$10<>0,N11/N$10,0) -> 1 | P11: =+月次PL!I3/1000 -> 573.045 | Q11: =IF(P$10<>0,P11/P$10,0) -> 1 | R11: =+月次PL!J3/1000 -> 566.158 | S11: =IF(R$10<>0,R11/R$10,0) -> 1 | T11: =+月次PL!K3/1000 -> 643.467 | U11: =IF(T$10<>0,T11/T$10,0) -> 1 | V11: =+月次PL!L8/1000 -> 1030.617 | W11: =IF(V$10<>0,V11/V$10,0) -> 1 | X11: =+月次PL!M3/1000 -> 890.404 | Y11: =IF(X$10<>0,X11/X$10,0) -> 1 | AA11: =IF(Z$10<>0,Z11/Z$10,0) -> 0
C12: =+月次PL!B4 -> 0 | D12: =+月次PL!C4/1000 -> 0 | E12: =IF(D$10<>0,D12/D$10,0) -> 0 | F12: =+月次PL!D4/1000 -> 0 | G12: =IF(F$10<>0,F12/F$10,0) -> 0 | H12: =+月次PL!E4/1000 -> 0 | I12: =IF(H$10<>0,H12/H$10,0) -> 0 | J12: =+月次PL!F4/1000 -> 0 | K12: =IF(J$10<>0,J12/J$10,0) -> 0 | L12: =+月次PL!G4/1000 -> 0 | M12: =IF(L$10<>0,L12/L$10,0) -> 0 | O12: =IF(N$10<>0,N12/N$10,0) -> 0 | Q12: =IF(P$10<>0,P12/P$10,0) -> 0 | S12: =IF(R$10<>0,R12/R$10,0) -> 0 | U12: =IF(T$10<>0,T12/T$10,0) -> 0 | W12: =IF(V$10<>0,V12/V$10,0) -> 0 | Y12: =IF(X$10<>0,X12/X$10,0) -> 0 | AA12: =IF(Z$10<>0,Z12/Z$10,0) -> 0
C13: =+月次PL!B5 -> 0 | D13: =+月次PL!C5/1000 -> 0 | E13: =IF(D$10<>0,D13/D$10,0) -> 0 | F13: =+月次PL!D5/1000 -> 0 | G13: =IF(F$10<>0,F13/F$10,0) -> 0 | H13: =+月次PL!E5/1000 -> 0 | I13: =IF(H$10<>0,H13/H$10,0) -> 0 | J13: =+月次PL!F5/1000 -> 0 | K13: =IF(J$10<>0,J13/J$10,0) -> 0 | L13: =+月次PL!G5/1000 -> 0 | M13: =IF(L$10<>0,L13/L$10,0) -> 0 | O13: =IF(N$10<>0,N13/N$10,0) -> 0 | Q13: =IF(P$10<>0,P13/P$10,0) -> 0 | S13: =IF(R$10<>0,R13/R$10,0) -> 0 | U13: =IF(T$10<>0,T13/T$10,0) -> 0 | W13: =IF(V$10<>0,V13/V$10,0) -> 0 | Y13: =IF(X$10<>0,X13/X$10,0) -> 0 | AA13: =IF(Z$10<>0,Z13/Z$10,0) -> 0
C14: =+月次PL!B6 -> 0 | D14: =+月次PL!C6/1000 -> 0 | E14: =IF(D$10<>0,D14/D$10,0) -> 0 | F14: =+月次PL!D6/1000 -> 0 | G14: =IF(F$10<>0,F14/F$10,0) -> 0 | H14: =+月次PL!E6/1000 -> 0 | I14: =IF(H$10<>0,H14/H$10,0) -> 0 | J14: =+月次PL!F6/1000 -> 0 | K14: =IF(J$10<>0,J14/J$10,0) -> 0 | L14: =+月次PL!G6/1000 -> 0 | M14: =IF(L$10<>0,L14/L$10,0) -> 0 | O14: =IF(N$10<>0,N14/N$10,0) -> 0 | Q14: =IF(P$10<>0,P14/P$10,0) -> 0 | S14: =IF(R$10<>0,R14/R$10,0) -> 0 | U14: =IF(T$10<>0,T14/T$10,0) -> 0 | W14: =IF(V$10<>0,V14/V$10,0) -> 0 | Y14: =IF(X$10<>0,X14/X$10,0) -> 0 | AA14: =IF(Z$10<>0,Z14/Z$10,0) -> 0
C15: =+月次PL!B7 -> 0 | D15: =+月次PL!C7/1000 -> 0 | E15: =IF(D$10<>0,D15/D$10,0) -> 0 | F15: =+月次PL!D7/1000 -> 0 | G15: =IF(F$10<>0,F15/F$10,0) -> 0 | H15: =+月次PL!E7/1000 -> 0 | I15: =IF(H$10<>0,H15/H$10,0) -> 0 | J15: =+月次PL!F7/1000 -> 0 | K15: =IF(J$10<>0,J15/J$10,0) -> 0 | L15: =+月次PL!G7/1000 -> 0 | M15: =IF(L$10<>0,L15/L$10,0) -> 0 | O15: =IF(N$10<>0,N15/N$10,0) -> 0 | Q15: =IF(P$10<>0,P15/P$10,0) -> 0 | S15: =IF(R$10<>0,R15/R$10,0) -> 0 | U15: =IF(T$10<>0,T15/T$10,0) -> 0 | W15: =IF(V$10<>0,V15/V$10,0) -> 0 | Y15: =IF(X$10<>0,X15/X$10,0) -> 0 | AA15: =IF(Z$10<>0,Z15/Z$10,0) -> 0
B16: 売上原価 | D16: =+月次PL!C15/1000 -> 0 | E16: =IF(D$10<>0,D16/D$10,0) -> 0 | F16: =+月次PL!D15/1000 -> 0 | G16: =IF(F$10<>0,F16/F$10,0) -> 0 | H16: =+月次PL!E15/1000 -> 0 | I16: =IF(H$10<>0,H16/H$10,0) -> 0 | J16: =+月次PL!F15/1000 -> 0 | K16: =IF(J$10<>0,J16/J$10,0) -> 0 | L16: =+月次PL!G15/1000 -> 0 | M16: =IF(L$10<>0,L16/L$10,0) -> 0 | N16: =+月次PL!H15/1000 -> 0 | O16: =IF(N$10<>0,N16/N$10,0) -> 0 | P16: =+月次PL!I15/1000 -> 0 | Q16: =IF(P$10<>0,P16/P$10,0) -> 0 | R16: =+月次PL!J15/1000 -> 0 | S16: =IF(R$10<>0,R16/R$10,0) -> 0 | T16: =+月次PL!K15/1000 -> 0 | U16: =IF(T$10<>0,T16/T$10,0) -> 0 | V16: =+月次PL!L15/1000 -> 0 | W16: =IF(V$10<>0,V16/V$10,0) -> 0 | X16: =+月次PL!M15/1000 -> 0 | Y16: =IF(X$10<>0,X16/X$10,0) -> 0 | Z16: =+月次PL!N15/1000 -> 0 | AA16: =IF(Z$10<>0,Z16/Z$10,0) -> 0
C17: =+月次PL!B10 -> 0 | D17: =+月次PL!C10/1000 -> 0 | E17: =IF(D11<>0,D17/D11,0) -> 0 | F17: =+月次PL!D10/1000 -> 0 | G17: =IF(F11<>0,F17/F11,0) -> 0 | H17: =+月次PL!E10/1000 -> 0 | I17: =IF(H11<>0,H17/H11,0) -> 0 | J17: =+月次PL!F10/1000 -> 0 | K17: =IF(J11<>0,J17/J11,0) -> 0 | L17: =+月次PL!G10/1000 -> 0 | M17: =IF(L11<>0,L17/L11,0) -> 0 | O17: =IF(N11<>0,N17/N11,0) -> 0 | Q17: =IF(P11<>0,P17/P11,0) -> 0 | S17: =IF(R11<>0,R17/R11,0) -> 0 | U17: =IF(T11<>0,T17/T11,0) -> 0 | W17: =IF(V11<>0,V17/V11,0) -> 0 | Y17: =IF(X11<>0,X17/X11,0) -> 0 | AA17: =IF(Z11<>0,Z17/Z11,0) -> 0
E18: =IF(D12<>0,D18/D12,0) -> 0 | G18: =IF(F12<>0,F18/F12,0) -> 0 | I18: =IF(H12<>0,H18/H12,0) -> 0 | K18: =IF(J12<>0,J18/J12,0) -> 0 | M18: =IF(L12<>0,L18/L12,0) -> 0 | O18: =IF(N12<>0,N18/N12,0) -> 0 | Q18: =IF(P12<>0,P18/P12,0) -> 0 | S18: =IF(R12<>0,R18/R12,0) -> 0 | U18: =IF(T12<>0,T18/T12,0) -> 0 | W18: =IF(V12<>0,V18/V12,0) -> 0 | Y18: =IF(X12<>0,X18/X12,0) -> 0 | AA18: =IF(Z12<>0,Z18/Z12,0) -> 0
E19: =IF(D13<>0,D19/D13,0) -> 0 | G19: =IF(F13<>0,F19/F13,0) -> 0 | I19: =IF(H13<>0,H19/H13,0) -> 0 | K19: =IF(J13<>0,J19/J13,0) -> 0 | M19: =IF(L13<>0,L19/L13,0) -> 0 | O19: =IF(N13<>0,N19/N13,0) -> 0 | Q19: =IF(P13<>0,P19/P13,0) -> 0 | S19: =IF(R13<>0,R19/R13,0) -> 0 | U19: =IF(T13<>0,T19/T13,0) -> 0 | W19: =IF(V13<>0,V19/V13,0) -> 0 | Y19: =IF(X13<>0,X19/X13,0) -> 0 | AA19: =IF(Z13<>0,Z19/Z13,0) -> 0
E20: =IF(D14<>0,D20/D14,0) -> 0 | G20: =IF(F14<>0,F20/F14,0) -> 0 | I20: =IF(H14<>0,H20/H14,0) -> 0 | K20: =IF(J14<>0,J20/J14,0) -> 0 | M20: =IF(L14<>0,L20/L14,0) -> 0 | O20: =IF(N14<>0,N20/N14,0) -> 0 | Q20: =IF(P14<>0,P20/P14,0) -> 0 | S20: =IF(R14<>0,R20/R14,0) -> 0 | U20: =IF(T14<>0,T20/T14,0) -> 0 | W20: =IF(V14<>0,V20/V14,0) -> 0 | Y20: =IF(X14<>0,X20/X14,0) -> 0 | AA20: =IF(Z14<>0,Z20/Z14,0) -> 0
E21: =IF(D15<>0,D21/D15,0) -> 0 | G21: =IF(F15<>0,F21/F15,0) -> 0 | I21: =IF(H15<>0,H21/H15,0) -> 0 | K21: =IF(J15<>0,J21/J15,0) -> 0 | M21: =IF(L15<>0,L21/L15,0) -> 0 | O21: =IF(N15<>0,N21/N15,0) -> 0 | Q21: =IF(P15<>0,P21/P15,0) -> 0 | S21: =IF(R15<>0,R21/R15,0) -> 0 | U21: =IF(T15<>0,T21/T15,0) -> 0 | W21: =IF(V15<>0,V21/V15,0) -> 0 | Y21: =IF(X15<>0,X21/X15,0) -> 0 | AA21: =IF(Z15<>0,Z21/Z15,0) -> 0
B22: 粗利益 | D22: =+D10-D16 -> 622.833 | E22: =IF(D$10<>0,D22/D$10,0) -> 1 | F22: =+F10-F16 -> 559.842 | G22: =IF(F$10<>0,F22/F$10,0) -> 1 | H22: =+H10-H16 -> 571.656 | I22: =IF(H$10<>0,H22/H$10,0) -> 1 | J22: =+J10-J16 -> 571.68 | K22: =IF(J$10<>0,J22/J$10,0) -> 1 | L22: =+L10-L16 -> 482.542 | M22: =IF(L$10<>0,L22/L$10,0) -> 1 | N22: =+N10-N16 -> 568.075 | O22: =IF(N$10<>0,N22/N$10,0) -> 1 | P22: =+P10-P16 -> 573.045 | Q22: =IF(P$10<>0,P22/P$10,0) -> 1 | R22: =+R10-R16 -> 566.158 | S22: =IF(R$10<>0,R22/R$10,0) -> 1 | T22: =+T10-T16 -> 643.467 | U22: =IF(T$10<>0,T22/T$10,0) -> 1 | V22: =+V10-V16 -> 1030.617 | W22: =IF(V$10<>0,V22/V$10,0) -> 1 | X22: =+X10-X16 -> 890.404 | Y22: =IF(X$10<>0,X22/X$10,0) -> 1 | Z22: =+Z10-Z16 -> 988.475 | AA22: =IF(Z$10<>0,Z22/Z$10,0) -> 1
E23: =IF(D11<>0,D23/D11,0) -> 0 | F23: =+F11-F17 -> 559.842 | G23: =IF(F11<>0,F23/F11,0) -> 1 | H23: =+H11-H17 -> 571.656 | I23: =IF(H11<>0,H23/H11,0) -> 1 | J23: =+J11-J17 -> 571.68 | K23: =IF(J11<>0,J23/J11,0) -> 1 | L23: =+L11-L17 -> 482.542 | M23: =IF(L11<>0,L23/L11,0) -> 1 | N23: =+N11-N17 -> 568.075 | O23: =IF(N11<>0,N23/N11,0) -> 1 | P23: =+P11-P17 -> 573.045 | Q23: =IF(P11<>0,P23/P11,0) -> 1 | R23: =+R11-R17 -> 566.158 | S23: =IF(R11<>0,R23/R11,0) -> 1 | T23: =+T11-T17 -> 643.467 | U23: =IF(T11<>0,T23/T11,0) -> 1 | V23: =+V11-V17 -> 1030.617 | W23: =IF(V11<>0,V23/V11,0) -> 1 | X23: =+X11-X17 -> 890.404 | Y23: =IF(X11<>0,X23/X11,0) -> 1 | Z23: =+Z11-Z17 -> 0 | AA23: =IF(Z11<>0,Z23/Z11,0) -> 0
E24: =IF(D12<>0,D24/D12,0) -> 0 | F24: =+F12-F18 -> 0 | G24: =IF(F12<>0,F24/F12,0) -> 0 | H24: =+H12-H18 -> 0 | I24: =IF(H12<>0,H24/H12,0) -> 0 | J24: =+J12-J18 -> 0 | K24: =IF(J12<>0,J24/J12,0) -> 0 | L24: =+L12-L18 -> 0 | M24: =IF(L12<>0,L24/L12,0) -> 0 | N24: =+N12-N18 -> 0 | O24: =IF(N12<>0,N24/N12,0) -> 0 | P24: =+P12-P18 -> 0 | Q24: =IF(P12<>0,P24/P12,0) -> 0 | R24: =+R12-R18 -> 0 | S24: =IF(R12<>0,R24/R12,0) -> 0 | T24: =+T12-T18 -> 0 | U24: =IF(T12<>0,T24/T12,0) -> 0 | V24: =+V12-V18 -> 0 | W24: =IF(V12<>0,V24/V12,0) -> 0 | X24: =+X12-X18 -> 0 | Y24: =IF(X12<>0,X24/X12,0) -> 0 | Z24: =+Z12-Z18 -> 0 | AA24: =IF(Z12<>0,Z24/Z12,0) -> 0
E25: =IF(D13<>0,D25/D13,0) -> 0 | F25: =+F13-F19 -> 0 | G25: =IF(F13<>0,F25/F13,0) -> 0 | H25: =+H13-H19 -> 0 | I25: =IF(H13<>0,H25/H13,0) -> 0 | J25: =+J13-J19 -> 0 | K25: =IF(J13<>0,J25/J13,0) -> 0 | L25: =+L13-L19 -> 0 | M25: =IF(L13<>0,L25/L13,0) -> 0 | N25: =+N13-N19 -> 0 | O25: =IF(N13<>0,N25/N13,0) -> 0 | P25: =+P13-P19 -> 0 | Q25: =IF(P13<>0,P25/P13,0) -> 0 | R25: =+R13-R19 -> 0 | S25: =IF(R13<>0,R25/R13,0) -> 0 | T25: =+T13-T19 -> 0 | U25: =IF(T13<>0,T25/T13,0) -> 0 | V25: =+V13-V19 -> 0 | W25: =IF(V13<>0,V25/V13,0) -> 0 | X25: =+X13-X19 -> 0 | Y25: =IF(X13<>0,X25/X13,0) -> 0 | Z25: =+Z13-Z19 -> 0 | AA25: =IF(Z13<>0,Z25/Z13,0) -> 0
E26: =IF(D14<>0,D26/D14,0) -> 0 | F26: =+F14-F20 -> 0 | G26: =IF(F14<>0,F26/F14,0) -> 0 | H26: =+H14-H20 -> 0 | I26: =IF(H14<>0,H26/H14,0) -> 0 | J26: =+J14-J20 -> 0 | K26: =IF(J14<>0,J26/J14,0) -> 0 | L26: =+L14-L20 -> 0 | M26: =IF(L14<>0,L26/L14,0) -> 0 | N26: =+N14-N20 -> 0 | O26: =IF(N14<>0,N26/N14,0) -> 0 | P26: =+P14-P20 -> 0 | Q26: =IF(P14<>0,P26/P14,0) -> 0 | R26: =+R14-R20 -> 0 | S26: =IF(R14<>0,R26/R14,0) -> 0 | T26: =+T14-T20 -> 0 | U26: =IF(T14<>0,T26/T14,0) -> 0 | V26: =+V14-V20 -> 0 | W26: =IF(V14<>0,V26/V14,0) -> 0 | X26: =+X14-X20 -> 0 | Y26: =IF(X14<>0,X26/X14,0) -> 0 | Z26: =+Z14-Z20 -> 0 | AA26: =IF(Z14<>0,Z26/Z14,0) -> 0
E27: =IF(D15<>0,D27/D15,0) -> 0 | F27: =+F15-F21 -> 0 | G27: =IF(F15<>0,F27/F15,0) -> 0 | H27: =+H15-H21 -> 0 | I27: =IF(H15<>0,H27/H15,0) -> 0 | J27: =+J15-J21 -> 0 | K27: =IF(J15<>0,J27/J15,0) -> 0 | L27: =+L15-L21 -> 0 | M27: =IF(L15<>0,L27/L15,0) -> 0 | N27: =+N15-N21 -> 0 | O27: =IF(N15<>0,N27/N15,0) -> 0 | P27: =+P15-P21 -> 0 | Q27: =IF(P15<>0,P27/P15,0) -> 0 | R27: =+R15-R21 -> 0 | S27: =IF(R15<>0,R27/R15,0) -> 0 | T27: =+T15-T21 -> 0 | U27: =IF(T15<>0,T27/T15,0) -> 0 | V27: =+V15-V21 -> 0 | W27: =IF(V15<>0,V27/V15,0) -> 0 | X27: =+X15-X21 -> 0 | Y27: =IF(X15<>0,X27/X15,0) -> 0 | Z27: =+Z15-Z21 -> 0 | AA27: =IF(Z15<>0,Z27/Z15,0) -> 0
B28: 販売管理費 | D28: =SUM(D29:D49) -> 898.203 | E28: =IF(D$10<>0,D28/D$10,0) -> 1.4421249 | F28: =SUM(F29:F49) -> 567.923 | G28: =IF(F$10<>0,F28/F$10,0) -> 1.0144344 | H28: =SUM(H29:H49) -> 654.4 | I28: =IF(H$10<>0,H28/H$10,0) -> 1.1447444 | J28: =SUM(J29:J49) -> 724.991 | K28: =IF(J$10<>0,J28/J$10,0) -> 1.2681763 | L28: =SUM(L29:L49) -> 525.203 | M28: =IF(L$10<>0,L28/L$10,0) -> 1.0884089 | N28: =SUM(N29:N49) -> 694.978 | O28: =IF(N$10<>0,N28/N$10,0) -> 1.2233913 | P28: =SUM(P29:P49) -> 674.115 | Q28: =IF(P$10<>0,P28/P$10,0) -> 1.1763736 | R28: =SUM(R29:R49) -> 624.407 | S28: =IF(R$10<>0,R28/R$10,0) -> 1.1028847 | T28: =SUM(T29:T49) -> 654.598 | U28: =IF(T$10<>0,T28/T$10,0) -> 1.0172985 | V28: =SUM(V29:V49) -> 601.291 | W28: =IF(V$10<>0,V28/V$10,0) -> 0.58342818 | X28: =SUM(X29:X49) -> 676.189 | Y28: =IF(X$10<>0,X28/X$10,0) -> 0.7594182 | Z28: =SUM(Z29:Z49) -> 661.641 | AA28: =IF(Z$10<>0,Z28/Z$10,0) -> 0.66935532
C29: 人件費 | D29: =SUM(月次PL!C18:C25)/1000 -> 535.456 | E29: =IF(D$10<>0,D29/D$10,0) -> 0.85971039 | F29: =SUM(月次PL!D18:D25)/1000 -> 331.819 | G29: =IF(F$10<>0,F29/F$10,0) -> 0.59270115 | H29: =SUM(月次PL!E18:E25)/1000 -> 331.819 | I29: =IF(H$10<>0,H29/H$10,0) -> 0.58045223 | J29: =SUM(月次PL!F18:F25)/1000 -> 331.819 | K29: =IF(J$10<>0,J29/J$10,0) -> 0.58042786 | L29: =SUM(月次PL!G18:G25)/1000 -> 331.819 | M29: =IF(L$10<>0,L29/L$10,0) -> 0.68764791 | N29: =SUM(月次PL!H18:H25)/1000 -> 331.819 | O29: =IF(N$10<>0,N29/N$10,0) -> 0.58411125 | P29: =SUM(月次PL!I18:I25)/1000 -> 331.819 | Q29: =IF(P$10<>0,P29/P$10,0) -> 0.57904528 | R29: =SUM(月次PL!J18:J25)/1000 -> 331.819 | S29: =IF(R$10<>0,R29/R$10,0) -> 0.58608904 | T29: =SUM(月次PL!K18:K25)/1000 -> 331.819 | U29: =IF(T$10<>0,T29/T$10,0) -> 0.51567369 | V29: =SUM(月次PL!L18:L25)/1000 -> 331.819 | W29: =IF(V$10<>0,V29/V$10,0) -> 0.3219615 | X29: =SUM(月次PL!M18:M25)/1000 -> 331.819 | Y29: =IF(X$10<>0,X29/X$10,0) -> 0.37266117 | Z29: =SUM(月次PL!N18:N25)/1000 -> 331.819 | AA29: =IF(Z$10<>0,Z29/Z$10,0) -> 0.3356878
C30: 旅費交通費 | D30: =+月次PL!C28/1000 -> 9.72 | E30: =IF(D$10<>0,D30/D$10,0) -> 0.01560611 | F30: =+月次PL!D28/1000 -> 5.371 | G30: =IF(F$10<>0,F30/F$10,0) -> 0.0095937782 | H30: =+月次PL!E28/1000 -> 8.966 | I30: =IF(H$10<>0,H30/H$10,0) -> 0.015684258 | J30: =+月次PL!F28/1000 -> 74.104 | K30: =IF(J$10<>0,J30/J$10,0) -> 0.12962497 | L30: =+月次PL!G28/1000 -> 6.693 | M30: =IF(L$10<>0,L30/L$10,0) -> 0.013870295 | N30: =+月次PL!H28/1000 -> 1.928 | O30: =IF(N$10<>0,N30/N$10,0) -> 0.0033939181 | P30: =+月次PL!I28/1000 -> 101.043 | Q30: =IF(P$10<>0,P30/P$10,0) -> 0.17632647 | R30: =+月次PL!J28/1000 -> 5.547 | S30: =IF(R$10<>0,R30/R$10,0) -> 0.0097976183 | T30: =+月次PL!K28/1000 -> 1.091 | U30: =IF(T$10<>0,T30/T$10,0) -> 0.0016955026 | V30: =+月次PL!L28/1000 -> 0 | W30: =IF(V$10<>0,V30/V$10,0) -> 0 | X30: =+月次PL!M28/1000 -> 57.464 | Y30: =IF(X$10<>0,X30/X$10,0) -> 0.064536997 | Z30: =+月次PL!N28/1000 -> 24.862 | AA30: =IF(Z$10<>0,Z30/Z$10,0) -> 0.025151875
C31: 通信費 | D31: =+月次PL!C29/1000 -> 1.2 | E31: =IF(D$10<>0,D31/D$10,0) -> 0.0019266802 | F31: =+月次PL!D29/1000 -> 55.56 | G31: =IF(F$10<>0,F31/F$10,0) -> 0.099242286 | H31: =+月次PL!E29/1000 -> 54.96 | I31: =IF(H$10<>0,H31/H$10,0) -> 0.096141736 | J31: =+月次PL!F29/1000 -> 1.2 | K31: =IF(J$10<>0,J31/J$10,0) -> 0.0020990764 | L31: =+月次PL!G29/1000 -> 1.2 | M31: =IF(L$10<>0,L31/L$10,0) -> 0.0024868302 | N31: =+月次PL!H29/1000 -> 78.96 | O31: =IF(N$10<>0,N31/N$10,0) -> 0.13899573 | P31: =+月次PL!I29/1000 -> 3.837 | Q31: =IF(P$10<>0,P31/P$10,0) -> 0.0066958092 | R31: =+月次PL!J29/1000 -> 57.597 | S31: =IF(R$10<>0,R31/R$10,0) -> 0.10173309 | T31: =+月次PL!K29/1000 -> 18.513 | U31: =IF(T$10<>0,T31/T$10,0) -> 0.028770706 | V31: =+月次PL!L29/1000 -> 27.326 | W31: =IF(V$10<>0,V31/V$10,0) -> 0.026514214 | X31: =+月次PL!M29/1000 -> 71.599 | Y31: =IF(X$10<>0,X31/X$10,0) -> 0.080411813 | Z31: =+月次PL!N29/1000 -> 62.331 | AA31: =IF(Z$10<>0,Z31/Z$10,0) -> 0.06305774
C32: 市場調査費 | D32: =+月次PL!C44/1000 -> 140 | E32: =IF(D$10<>0,D32/D$10,0) -> 0.22477935 | F32: =+月次PL!D44/1000 -> 14.004 | G32: =IF(F$10<>0,F32/F$10,0) -> 0.0250142 | H32: =+月次PL!E44/1000 -> 42.383 | I32: =IF(H$10<>0,H32/H$10,0) -> 0.074140742 | J32: =+月次PL!F44/1000 -> 0 | K32: =IF(J$10<>0,J32/J$10,0) -> 0 | L32: =+月次PL!G44/1000 -> 0 | M32: =IF(L$10<>0,L32/L$10,0) -> 0 | N32: =+月次PL!H44/1000 -> 0 | O32: =IF(N$10<>0,N32/N$10,0) -> 0 | P32: =+月次PL!I44/1000 -> 0 | Q32: =IF(P$10<>0,P32/P$10,0) -> 0 | R32: =+月次PL!J44/1000 -> 0 | S32: =IF(R$10<>0,R32/R$10,0) -> 0 | T32: =+月次PL!K44/1000 -> 0 | U32: =IF(T$10<>0,T32/T$10,0) -> 0 | V32: =+月次PL!L44/1000 -> 0 | W32: =IF(V$10<>0,V32/V$10,0) -> 0 | X32: =+月次PL!M44/1000 -> 0 | Y32: =IF(X$10<>0,X32/X$10,0) -> 0 | Z32: =+月次PL!N44/1000 -> 0 | AA32: =IF(Z$10<>0,Z32/Z$10,0) -> 0
C33: 交際費 | D33: =+月次PL!C27/1000 -> 13.438 | E33: =IF(D$10<>0,D33/D$10,0) -> 0.021575607 | F33: =+月次PL!D27/1000 -> 50.137 | G33: =IF(F$10<>0,F33/F$10,0) -> 0.089555625 | H33: =+月次PL!E27/1000 -> 103.9 | I33: =IF(H$10<>0,H33/H$10,0) -> 0.18175266 | J33: =+月次PL!F27/1000 -> 12.119 | K33: =IF(J$10<>0,J33/J$10,0) -> 0.021198922 | L33: =+月次PL!G27/1000 -> 30 | M33: =IF(L$10<>0,L33/L$10,0) -> 0.062170754 | N33: =+月次PL!H27/1000 -> 158.371 | O33: =IF(N$10<>0,N33/N$10,0) -> 0.27878537 | P33: =+月次PL!I27/1000 -> 87.515 | Q33: =IF(P$10<>0,P33/P$10,0) -> 0.15271925 | R33: =+月次PL!J27/1000 -> 113.663 | S33: =IF(R$10<>0,R33/R$10,0) -> 0.20076198 | T33: =+月次PL!K27/1000 -> 172.618 | U33: =IF(T$10<>0,T33/T$10,0) -> 0.2682624 | V33: =+月次PL!L27/1000 -> 89.768 | W33: =IF(V$10<>0,V33/V$10,0) -> 0.087101222 | X33: =+月次PL!M27/1000 -> 95.002 | Y33: =IF(X$10<>0,X33/X$10,0) -> 0.10669539 | Z33: =+月次PL!N27/1000 -> 111.724 | AA33: =IF(Z$10<>0,Z33/Z$10,0) -> 0.11302663
C34: 会議費 | D34: =+月次PL!C39/1000 -> 84.497 | E34: =IF(D$10<>0,D34/D$10,0) -> 0.13566558 | F34: =+月次PL!D39/1000 -> 10.447 | G34: =IF(F$10<>0,F34/F$10,0) -> 0.018660622 | H34: =+月次PL!E39/1000 -> 11.637 | I34: =IF(H$10<>0,H34/H$10,0) -> 0.020356648 | J34: =+月次PL!F39/1000 -> 67.568 | K34: =IF(J$10<>0,J34/J$10,0) -> 0.118192 | L34: =+月次PL!G39/1000 -> 49.291 | M34: =IF(L$10<>0,L34/L$10,0) -> 0.10214862 | N34: =+月次PL!H39/1000 -> 22.016 | O34: =IF(N$10<>0,N34/N$10,0) -> 0.038755446 | P34: =+月次PL!I39/1000 -> 45.376 | Q34: =IF(P$10<>0,P34/P$10,0) -> 0.079184008 | R34: =+月次PL!J39/1000 -> 13.067 | S34: =IF(R$10<>0,R34/R$10,0) -> 0.02308013 | T34: =+月次PL!K39/1000 -> 27.771 | U34: =IF(T$10<>0,T34/T$10,0) -> 0.04315839 | V34: =+月次PL!L39/1000 -> 13.158 | W34: =IF(V$10<>0,V34/V$10,0) -> 0.012767109 | X34: =+月次PL!M39/1000 -> 10.469 | Y34: =IF(X$10<>0,X34/X$10,0) -> 0.011757584 | Z34: =+月次PL!N39/1000 -> 27.614 | AA34: =IF(Z$10<>0,Z34/Z$10,0) -> 0.027935962
C35: 減価償却費 | D35: =+月次PL!C41/1000 -> 26.5 | E35: =IF(D$10<>0,D35/D$10,0) -> 0.042547521 | F35: =+月次PL!D41/1000 -> 26.5 | G35: =IF(F$10<>0,F35/F$10,0) -> 0.047334784 | H35: =+月次PL!E41/1000 -> 26.5 | I35: =IF(H$10<>0,H35/H$10,0) -> 0.04635655 | J35: =+月次PL!F41/1000 -> 26.5 | K35: =IF(J$10<>0,J35/J$10,0) -> 0.046354604 | L35: =+月次PL!G41/1000 -> 26.5 | M35: =IF(L$10<>0,L35/L$10,0) -> 0.054917499 | N35: =+月次PL!H41/1000 -> 26.5 | O35: =IF(N$10<>0,N35/N$10,0) -> 0.04664877 | P35: =+月次PL!I41/1000 -> 26.5 | Q35: =IF(P$10<>0,P35/P$10,0) -> 0.046244187 | R35: =+月次PL!J41/1000 -> 26.5 | S35: =IF(R$10<>0,R35/R$10,0) -> 0.046806722 | T35: =+月次PL!K41/1000 -> 26.5 | U35: =IF(T$10<>0,T35/T$10,0) -> 0.041183153 | V35: =+月次PL!L41/1000 -> 26.5 | W35: =IF(V$10<>0,V35/V$10,0) -> 0.025712753 | X35: =+月次PL!M41/1000 -> 26.5 | Y35: =IF(X$10<>0,X35/X$10,0) -> 0.029761771 | Z35: =+月次PL!N41/1000 -> 26.5 | AA35: =IF(Z$10<>0,Z35/Z$10,0) -> 0.026808973
C36: 賃借料 | D36: =+月次PL!C35/1000 -> 0 | E36: =IF(D$10<>0,D36/D$10,0) -> 0 | F36: =+月次PL!D35/1000 -> 0 | G36: =IF(F$10<>0,F36/F$10,0) -> 0 | H36: =+月次PL!E35/1000 -> 0 | I36: =IF(H$10<>0,H36/H$10,0) -> 0 | J36: =+月次PL!F35/1000 -> 0 | K36: =IF(J$10<>0,J36/J$10,0) -> 0 | L36: =+月次PL!G35/1000 -> 0 | M36: =IF(L$10<>0,L36/L$10,0) -> 0 | N36: =+月次PL!H35/1000 -> 0 | O36: =IF(N$10<>0,N36/N$10,0) -> 0 | P36: =+月次PL!I35/1000 -> 0 | Q36: =IF(P$10<>0,P36/P$10,0) -> 0 | R36: =+月次PL!J35/1000 -> 0 | S36: =IF(R$10<>0,R36/R$10,0) -> 0 | T36: =+月次PL!K35/1000 -> 0 | U36: =IF(T$10<>0,T36/T$10,0) -> 0 | V36: =+月次PL!L35/1000 -> 0 | W36: =IF(V$10<>0,V36/V$10,0) -> 0 | X36: =+月次PL!M35/1000 -> 0 | Y36: =IF(X$10<>0,X36/X$10,0) -> 0 | Z36: =+月次PL!N35/1000 -> 0 | AA36: =IF(Z$10<>0,Z36/Z$10,0) -> 0
C37: 地代家賃 | D37: =+月次PL!C34/1000 -> 44.5 | E37: =IF(D$10<>0,D37/D$10,0) -> 0.071447724 | F37: =+月次PL!D34/1000 -> 44.5 | G37: =IF(F$10<>0,F37/F$10,0) -> 0.079486712 | H37: =+月次PL!E34/1000 -> 44.5 | I37: =IF(H$10<>0,H37/H$10,0) -> 0.077844018 | J37: =+月次PL!F34/1000 -> 44.5 | K37: =IF(J$10<>0,J37/J$10,0) -> 0.07784075 | L37: =+月次PL!G34/1000 -> 44.5 | M37: =IF(L$10<>0,L37/L$10,0) -> 0.092219952 | N37: =+月次PL!H34/1000 -> 44.5 | O37: =IF(N$10<>0,N37/N$10,0) -> 0.078334727 | P37: =+月次PL!I34/1000 -> 44.5 | Q37: =IF(P$10<>0,P37/P$10,0) -> 0.077655332 | R37: =+月次PL!J34/1000 -> 44.5 | S37: =IF(R$10<>0,R37/R$10,0) -> 0.078599967 | T37: =+月次PL!K34/1000 -> 44.5 | U37: =IF(T$10<>0,T37/T$10,0) -> 0.069156616 | V37: =+月次PL!L34/1000 -> 44.5 | W37: =IF(V$10<>0,V37/V$10,0) -> 0.043178019 | X37: =+月次PL!M34/1000 -> 44.5 | Y37: =IF(X$10<>0,X37/X$10,0) -> 0.049977314 | Z37: =+月次PL!N34/1000 -> 44.5 | AA37: =IF(Z$10<>0,Z37/Z$10,0) -> 0.045018842
C38: リース料 | D38: =+月次PL!C33/1000 -> 0 | E38: =IF(D$10<>0,D38/D$10,0) -> 0 | F38: =+月次PL!D33/1000 -> 0 | G38: =IF(F$10<>0,F38/F$10,0) -> 0 | H38: =+月次PL!E33/1000 -> 0 | I38: =IF(H$10<>0,H38/H$10,0) -> 0 | J38: =+月次PL!F33/1000 -> 0 | K38: =IF(J$10<>0,J38/J$10,0) -> 0 | L38: =+月次PL!G33/1000 -> 0 | M38: =IF(L$10<>0,L38/L$10,0) -> 0 | N38: =+月次PL!H33/1000 -> 0 | O38: =IF(N$10<>0,N38/N$10,0) -> 0 | P38: =+月次PL!I33/1000 -> 0 | Q38: =IF(P$10<>0,P38/P$10,0) -> 0 | R38: =+月次PL!J33/1000 -> 0 | S38: =IF(R$10<>0,R38/R$10,0) -> 0 | T38: =+月次PL!K33/1000 -> 0 | U38: =IF(T$10<>0,T38/T$10,0) -> 0 | V38: =+月次PL!L33/1000 -> 0 | W38: =IF(V$10<>0,V38/V$10,0) -> 0 | X38: =+月次PL!M33/1000 -> 0 | Y38: =IF(X$10<>0,X38/X$10,0) -> 0 | Z38: =+月次PL!N33/1000 -> 0 | AA38: =IF(Z$10<>0,Z38/Z$10,0) -> 0
C39: 修繕費 | D39: =+月次PL!C31/1000 -> 0 | E39: =IF(D$10<>0,D39/D$10,0) -> 0 | F39: =+月次PL!D31/1000 -> 0 | G39: =IF(F$10<>0,F39/F$10,0) -> 0 | H39: =+月次PL!E31/1000 -> 0 | I39: =IF(H$10<>0,H39/H$10,0) -> 0 | J39: =+月次PL!F31/1000 -> 0 | K39: =IF(J$10<>0,J39/J$10,0) -> 0 | L39: =+月次PL!G31/1000 -> 0 | M39: =IF(L$10<>0,L39/L$10,0) -> 0 | N39: =+月次PL!H31/1000 -> 0 | O39: =IF(N$10<>0,N39/N$10,0) -> 0 | P39: =+月次PL!I31/1000 -> 0 | Q39: =IF(P$10<>0,P39/P$10,0) -> 0 | R39: =+月次PL!J31/1000 -> 0 | S39: =IF(R$10<>0,R39/R$10,0) -> 0 | T39: =+月次PL!K31/1000 -> 0 | U39: =IF(T$10<>0,T39/T$10,0) -> 0 | V39: =+月次PL!L31/1000 -> 0 | W39: =IF(V$10<>0,V39/V$10,0) -> 0 | X39: =+月次PL!M31/1000 -> 0 | Y39: =IF(X$10<>0,X39/X$10,0) -> 0 | Z39: =+月次PL!N31/1000 -> 0 | AA39: =IF(Z$10<>0,Z39/Z$10,0) -> 0
C40: 保険料 | D40: =+月次PL!C36/1000 -> 5 | E40: =IF(D$10<>0,D40/D$10,0) -> 0.0080278341 | F40: =+月次PL!D36/1000 -> 5 | G40: =IF(F$10<>0,F40/F$10,0) -> 0.0089310913 | H40: =+月次PL!E36/1000 -> 5 | I40: =IF(H$10<>0,H40/H$10,0) -> 0.0087465189 | J40: =+月次PL!F36/1000 -> 5 | K40: =IF(J$10<>0,J40/J$10,0) -> 0.0087461517 | L40: =+月次PL!G36/1000 -> 5 | M40: =IF(L$10<>0,L40/L$10,0) -> 0.010361792 | N40: =+月次PL!H36/1000 -> 5 | O40: =IF(N$10<>0,N40/N$10,0) -> 0.0088016547 | P40: =+月次PL!I36/1000 -> 5 | Q40: =IF(P$10<>0,P40/P$10,0) -> 0.0087253183 | R40: =+月次PL!J36/1000 -> 5 | S40: =IF(R$10<>0,R40/R$10,0) -> 0.0088314569 | T40: =+月次PL!K36/1000 -> 5 | U40: =IF(T$10<>0,T40/T$10,0) -> 0.0077704063 | V40: =+月次PL!L36/1000 -> 5 | W40: =IF(V$10<>0,V40/V$10,0) -> 0.0048514628 | X40: =+月次PL!M36/1000 -> 5 | Y40: =IF(X$10<>0,X40/X$10,0) -> 0.0056154285 | Z40: =+月次PL!N36/1000 -> 5 | AA40: =IF(Z$10<>0,Z40/Z$10,0) -> 0.0050582969
C41: 水道光熱費 | D41: =+月次PL!C30/1000 -> 0 | E41: =IF(D$10<>0,D41/D$10,0) -> 0 | F41: =+月次PL!D30/1000 -> 0 | G41: =IF(F$10<>0,F41/F$10,0) -> 0 | H41: =+月次PL!E30/1000 -> 0 | I41: =IF(H$10<>0,H41/H$10,0) -> 0 | J41: =+月次PL!F30/1000 -> 0 | K41: =IF(J$10<>0,J41/J$10,0) -> 0 | L41: =+月次PL!G30/1000 -> 0 | M41: =IF(L$10<>0,L41/L$10,0) -> 0 | N41: =+月次PL!H30/1000 -> 0 | O41: =IF(N$10<>0,N41/N$10,0) -> 0 | P41: =+月次PL!I30/1000 -> 0 | Q41: =IF(P$10<>0,P41/P$10,0) -> 0 | R41: =+月次PL!J30/1000 -> 0 | S41: =IF(R$10<>0,R41/R$10,0) -> 0 | T41: =+月次PL!K30/1000 -> 0 | U41: =IF(T$10<>0,T41/T$10,0) -> 0 | V41: =+月次PL!L30/1000 -> 0 | W41: =IF(V$10<>0,V41/V$10,0) -> 0 | X41: =+月次PL!M30/1000 -> 0 | Y41: =IF(X$10<>0,X41/X$10,0) -> 0 | Z41: =+月次PL!N30/1000 -> 0 | AA41: =IF(Z$10<>0,Z41/Z$10,0) -> 0
C42: 消耗品費 | D42: =+月次PL!C32/1000 -> 4.797 | E42: =IF(D$10<>0,D42/D$10,0) -> 0.007701904 | F42: =+月次PL!D32/1000 -> 0 | G42: =IF(F$10<>0,F42/F$10,0) -> 0 | H42: =+月次PL!E32/1000 -> 0 | I42: =IF(H$10<>0,H42/H$10,0) -> 0 | J42: =+月次PL!F32/1000 -> 0 | K42: =IF(J$10<>0,J42/J$10,0) -> 0 | L42: =+月次PL!G32/1000 -> 0 | M42: =IF(L$10<>0,L42/L$10,0) -> 0 | N42: =+月次PL!H32/1000 -> 0 | O42: =IF(N$10<>0,N42/N$10,0) -> 0 | P42: =+月次PL!I32/1000 -> 0 | Q42: =IF(P$10<>0,P42/P$10,0) -> 0 | R42: =+月次PL!J32/1000 -> 0 | S42: =IF(R$10<>0,R42/R$10,0) -> 0 | T42: =+月次PL!K32/1000 -> 0 | U42: =IF(T$10<>0,T42/T$10,0) -> 0 | V42: =+月次PL!L32/1000 -> 39.584 | W42: =IF(V$10<>0,V42/V$10,0) -> 0.03840806 | X42: =+月次PL!M32/1000 -> 10.2 | Y42: =IF(X$10<>0,X42/X$10,0) -> 0.011455474 | Z42: =+月次PL!N32/1000 -> 0 | AA42: =IF(Z$10<>0,Z42/Z$10,0) -> 0
C43: 租税公課 | D43: =+月次PL!C37/1000 -> 0 | E43: =IF(D$10<>0,D43/D$10,0) -> 0 | F43: =+月次PL!D37/1000 -> 0 | G43: =IF(F$10<>0,F43/F$10,0) -> 0 | H43: =+月次PL!E37/1000 -> 0 | I43: =IF(H$10<>0,H43/H$10,0) -> 0 | J43: =+月次PL!F37/1000 -> 0 | K43: =IF(J$10<>0,J43/J$10,0) -> 0 | L43: =+月次PL!G37/1000 -> 1.2 | M43: =IF(L$10<>0,L43/L$10,0) -> 0.0024868302 | N43: =+月次PL!H37/1000 -> 0 | O43: =IF(N$10<>0,N43/N$10,0) -> 0 | P43: =+月次PL!I37/1000 -> 0.6 | Q43: =IF(P$10<>0,P43/P$10,0) -> 0.0010470382 | R43: =+月次PL!J37/1000 -> 0 | S43: =IF(R$10<>0,R43/R$10,0) -> 0 | T43: =+月次PL!K37/1000 -> 0 | U43: =IF(T$10<>0,T43/T$10,0) -> 0 | V43: =+月次PL!L37/1000 -> 0 | W43: =IF(V$10<>0,V43/V$10,0) -> 0 | X43: =+月次PL!M37/1000 -> 0 | Y43: =IF(X$10<>0,X43/X$10,0) -> 0 | Z43: =+月次PL!N37/1000 -> 0 | AA43: =IF(Z$10<>0,Z43/Z$10,0) -> 0
C44: 広告宣伝費 | D44: =+月次PL!C26/1000 -> 0 | E44: =IF(D$10<>0,D44/D$10,0) -> 0 | F44: =+月次PL!D26/1000 -> 0 | G44: =IF(F$10<>0,F44/F$10,0) -> 0 | H44: =+月次PL!E26/1000 -> 0 | I44: =IF(H$10<>0,H44/H$10,0) -> 0 | J44: =+月次PL!F26/1000 -> 0 | K44: =IF(J$10<>0,J44/J$10,0) -> 0 | L44: =+月次PL!G26/1000 -> 0 | M44: =IF(L$10<>0,L44/L$10,0) -> 0 | N44: =+月次PL!H26/1000 -> 0 | O44: =IF(N$10<>0,N44/N$10,0) -> 0 | P44: =+月次PL!I26/1000 -> 0 | Q44: =IF(P$10<>0,P44/P$10,0) -> 0 | R44: =+月次PL!J26/1000 -> 0 | S44: =IF(R$10<>0,R44/R$10,0) -> 0 | T44: =+月次PL!K26/1000 -> 0 | U44: =IF(T$10<>0,T44/T$10,0) -> 0 | V44: =+月次PL!L26/1000 -> 0 | W44: =IF(V$10<>0,V44/V$10,0) -> 0 | X44: =+月次PL!M26/1000 -> 0 | Y44: =IF(X$10<>0,X44/X$10,0) -> 0 | Z44: =+月次PL!N26/1000 -> 0 | AA44: =IF(Z$10<>0,Z44/Z$10,0) -> 0
C45: 支払手数料 | D45: =+月次PL!C38/1000 -> 12.455 | E45: =IF(D$10<>0,D45/D$10,0) -> 0.019997335 | F45: =+月次PL!D38/1000 -> 1.955 | G45: =IF(F$10<>0,F45/F$10,0) -> 0.0034920567 | H45: =+月次PL!E38/1000 -> 2.105 | I45: =IF(H$10<>0,H45/H$10,0) -> 0.0036822845 | J45: =+月次PL!F38/1000 -> 2.255 | K45: =IF(J$10<>0,J45/J$10,0) -> 0.0039445144 | L45: =+月次PL!G38/1000 -> 7.469 | M45: =IF(L$10<>0,L45/L$10,0) -> 0.015478445 | N45: =+月次PL!H38/1000 -> 4.353 | O45: =IF(N$10<>0,N45/N$10,0) -> 0.0076627206 | P45: =+月次PL!I38/1000 -> 4.694 | Q45: =IF(P$10<>0,P45/P$10,0) -> 0.0081913288 | R45: =+月次PL!J38/1000 -> 2.155 | S45: =IF(R$10<>0,R45/R$10,0) -> 0.0038063579 | T45: =+月次PL!K38/1000 -> 2.255 | U45: =IF(T$10<>0,T45/T$10,0) -> 0.0035044532 | V45: =+月次PL!L38/1000 -> 2.105 | W45: =IF(V$10<>0,V45/V$10,0) -> 0.0020424658 | X45: =+月次PL!M38/1000 -> 2.105 | Y45: =IF(X$10<>0,X45/X$10,0) -> 0.0023640954 | Z45: =+月次PL!N38/1000 -> 2.105 | AA45: =IF(Z$10<>0,Z45/Z$10,0) -> 0.002129543
C46: 新聞図書費 | D46: =+月次PL!C40/1000 -> 0 | E46: =IF(D$10<>0,D46/D$10,0) -> 0 | F46: =+月次PL!D40/1000 -> 1.99 | G46: =IF(F$10<>0,F46/F$10,0) -> 0.0035545743 | H46: =+月次PL!E40/1000 -> 1.99 | I46: =IF(H$10<>0,H46/H$10,0) -> 0.0034811145 | J46: =+月次PL!F40/1000 -> 0.891 | K46: =IF(J$10<>0,J46/J$10,0) -> 0.0015585642 | L46: =+月次PL!G40/1000 -> 0.891 | M46: =IF(L$10<>0,L46/L$10,0) -> 0.0018464714 | N46: =+月次PL!H40/1000 -> 0.891 | O46: =IF(N$10<>0,N46/N$10,0) -> 0.0015684549 | P46: =+月次PL!I40/1000 -> 0.891 | Q46: =IF(P$10<>0,P46/P$10,0) -> 0.0015548517 | R46: =+月次PL!J40/1000 -> 3.919 | S46: =IF(R$10<>0,R46/R$10,0) -> 0.006922096 | T46: =+月次PL!K40/1000 -> 0.891 | U46: =IF(T$10<>0,T46/T$10,0) -> 0.0013846864 | V46: =+月次PL!L40/1000 -> 0.891 | W46: =IF(V$10<>0,V46/V$10,0) -> 0.00086453066 | X46: =+月次PL!M40/1000 -> 0.891 | Y46: =IF(X$10<>0,X46/X$10,0) -> 0.0010006694 | Z46: =+月次PL!N40/1000 -> 0 | AA46: =IF(Z$10<>0,Z46/Z$10,0) -> 0
C47: 管理諸費 | D47: =+月次PL!C43/1000 -> 20 | E47: =IF(D$10<>0,D47/D$10,0) -> 0.032111336 | F47: =+月次PL!D43/1000 -> 20 | G47: =IF(F$10<>0,F47/F$10,0) -> 0.035724365 | H47: =+月次PL!E43/1000 -> 20 | I47: =IF(H$10<>0,H47/H$10,0) -> 0.034986076 | J47: =+月次PL!F43/1000 -> 140 | K47: =IF(J$10<>0,J47/J$10,0) -> 0.24489225 | L47: =+月次PL!G43/1000 -> 20 | M47: =IF(L$10<>0,L47/L$10,0) -> 0.041447169 | N47: =+月次PL!H43/1000 -> 20 | O47: =IF(N$10<>0,N47/N$10,0) -> 0.035206619 | P47: =+月次PL!I43/1000 -> 20 | Q47: =IF(P$10<>0,P47/P$10,0) -> 0.034901273 | R47: =+月次PL!J43/1000 -> 20 | S47: =IF(R$10<>0,R47/R$10,0) -> 0.035325828 | T47: =+月次PL!K43/1000 -> 20 | U47: =IF(T$10<>0,T47/T$10,0) -> 0.031081625 | V47: =+月次PL!L43/1000 -> 20 | W47: =IF(V$10<>0,V47/V$10,0) -> 0.019405851 | X47: =+月次PL!M43/1000 -> 20 | Y47: =IF(X$10<>0,X47/X$10,0) -> 0.022461714 | Z47: =+月次PL!N43/1000 -> 20 | AA47: =IF(Z$10<>0,Z47/Z$10,0) -> 0.020233187
C48: 雑費 | D48: =+月次PL!C42/1000 -> 0.64 | E48: =IF(D$10<>0,D48/D$10,0) -> 0.0010275628 | F48: =+月次PL!D42/1000 -> 0.64 | G48: =IF(F$10<>0,F48/F$10,0) -> 0.0011431797 | H48: =+月次PL!E42/1000 -> 0.64 | I48: =IF(H$10<>0,H48/H$10,0) -> 0.0011195544 | J48: =+月次PL!F42/1000 -> 19.035 | K48: =IF(J$10<>0,J48/J$10,0) -> 0.033296599 | L48: =+月次PL!G42/1000 -> 0.64 | M48: =IF(L$10<>0,L48/L$10,0) -> 0.0013263094 | N48: =+月次PL!H42/1000 -> 0.64 | O48: =IF(N$10<>0,N48/N$10,0) -> 0.0011266118 | P48: =+月次PL!I42/1000 -> 2.34 | Q48: =IF(P$10<>0,P48/P$10,0) -> 0.0040834489 | R48: =+月次PL!J42/1000 -> 0.64 | S48: =IF(R$10<>0,R48/R$10,0) -> 0.0011304265 | T48: =+月次PL!K42/1000 -> 3.64 | U48: =IF(T$10<>0,T48/T$10,0) -> 0.0056568558 | V48: =+月次PL!L42/1000 -> 0.64 | W48: =IF(V$10<>0,V48/V$10,0) -> 0.00062098723 | X48: =+月次PL!M42/1000 -> 0.64 | Y48: =IF(X$10<>0,X48/X$10,0) -> 0.00071877485 | Z48: =+月次PL!N42/1000 -> 5.186 | AA48: =IF(Z$10<>0,Z48/Z$10,0) -> 0.0052464655
E49: =IF(D$10<>0,D49/D$10,0) -> 0 | G49: =IF(F$10<>0,F49/F$10,0) -> 0 | I49: =IF(H$10<>0,H49/H$10,0) -> 0 | K49: =IF(J$10<>0,J49/J$10,0) -> 0 | M49: =IF(L$10<>0,L49/L$10,0) -> 0 | O49: =IF(N$10<>0,N49/N$10,0) -> 0 | Q49: =IF(P$10<>0,P49/P$10,0) -> 0 | S49: =IF(R$10<>0,R49/R$10,0) -> 0 | U49: =IF(T$10<>0,T49/T$10,0) -> 0 | W49: =IF(V$10<>0,V49/V$10,0) -> 0 | Y49: =IF(X$10<>0,X49/X$10,0) -> 0 | AA49: =IF(Z$10<>0,Z49/Z$10,0) -> 0
B50: 営業損益 | D50: =+D22-D28 -> -275.37 | E50: =IF(D$10<>0,D50/D$10,0) -> -0.44212494 | F50: =+F22-F28 -> -8.081 | G50: =IF(F$10<>0,F50/F$10,0) -> -0.01443443 | H50: =+H22-H28 -> -82.744 | I50: =IF(H$10<>0,H50/H$10,0) -> -0.14474439 | J50: =+J22-J28 -> -153.311 | K50: =IF(J$10<>0,J50/J$10,0) -> -0.26817625 | L50: =+L22-L28 -> -42.661 | M50: =IF(L$10<>0,L50/L$10,0) -> -0.088408885 | N50: =+N22-N28 -> -126.903 | O50: =IF(N$10<>0,N50/N$10,0) -> -0.22339128 | P50: =+P22-P28 -> -101.07 | Q50: =IF(P$10<>0,P50/P$10,0) -> -0.17637358 | R50: =+R22-R28 -> -58.249 | S50: =IF(R$10<>0,R50/R$10,0) -> -0.10288471 | T50: =+T22-T28 -> -11.131 | U50: =IF(T$10<>0,T50/T$10,0) -> -0.017298478 | V50: =+V22-V28 -> 429.326 | W50: =IF(V$10<>0,V50/V$10,0) -> 0.41657182 | X50: =+X22-X28 -> 214.215 | Y50: =IF(X$10<>0,X50/X$10,0) -> 0.2405818 | Z50: =+Z22-Z28 -> 326.834 | AA50: =IF(Z$10<>0,Z50/Z$10,0) -> 0.33064468
C51: 期中累計 | D51: =+D50 -> -275.37 | F51: =+D51+F50 -> -283.451 | H51: =+F51+H50 -> -366.195 | J51: =+H51+J50 -> -519.506 | L51: =+J51+L50 -> -562.167 | N51: =+L51+N50 -> -689.07 | P51: =+N51+P50 -> -790.14 | R51: =+P51+R50 -> -848.389 | T51: =+R51+T50 -> -859.52 | V51: =+T51+V50 -> -430.194 | X51: =+V51+X50 -> -215.979 | Z51: =+X51+Z50 -> 110.855
B52: 営業外収益 | D52: =+月次PL!C51/1000 -> 0 | E52: =IF(D$10<>0,D52/D$10,0) -> 0 | F52: =+月次PL!D51/1000 -> 1.782 | G52: =IF(F$10<>0,F52/F$10,0) -> 0.0031830409 | H52: =+月次PL!E51/1000 -> 1.187 | I52: =IF(H$10<>0,H52/H$10,0) -> 0.0020764236 | J52: =+月次PL!F51/1000 -> 0 | K52: =IF(J$10<>0,J52/J$10,0) -> 0 | L52: =+月次PL!G51/1000 -> 0 | M52: =IF(L$10<>0,L52/L$10,0) -> 0 | N52: =+月次PL!H51/1000 -> 0 | O52: =IF(N$10<>0,N52/N$10,0) -> 0 | P52: =+月次PL!I51/1000 -> 0 | Q52: =IF(P$10<>0,P52/P$10,0) -> 0 | R52: =+月次PL!J51/1000 -> 0.866 | S52: =IF(R$10<>0,R52/R$10,0) -> 0.0015296083 | T52: =+月次PL!K51/1000 -> 0.52 | U52: =IF(T$10<>0,T52/T$10,0) -> 0.00080812225 | V52: =+月次PL!L51/1000 -> 0 | W52: =IF(V$10<>0,V52/V$10,0) -> 0 | X52: =+月次PL!M51/1000 -> 0 | Y52: =IF(X$10<>0,X52/X$10,0) -> 0 | Z52: =+月次PL!N51/1000 -> 0.239 | AA52: =IF(Z$10<>0,Z52/Z$10,0) -> 0.00024178659
B53: 営業外費用 | D53: =+月次PL!C56/1000 -> 8.493 | E53: =IF(D$10<>0,D53/D$10,0) -> 0.013636079 | F53: =+月次PL!D56/1000 -> 8.493 | G53: =IF(F$10<>0,F53/F$10,0) -> 0.015170352 | H53: =+月次PL!E56/1000 -> 8.219 | I53: =IF(H$10<>0,H53/H$10,0) -> 0.014377528 | J53: =+月次PL!F56/1000 -> 8.493 | K53: =IF(J$10<>0,J53/J$10,0) -> 0.014856213 | L53: =+月次PL!G56/1000 -> 8.219 | M53: =IF(L$10<>0,L53/L$10,0) -> 0.017032714 | N53: =+月次PL!H56/1000 -> 8.493 | O53: =IF(N$10<>0,N53/N$10,0) -> 0.014950491 | P53: =+月次PL!I56/1000 -> 8.493 | Q53: =IF(P$10<>0,P53/P$10,0) -> 0.014820826 | R53: =+月次PL!J56/1000 -> 7.671 | S53: =IF(R$10<>0,R53/R$10,0) -> 0.013549221 | T53: =+月次PL!K56/1000 -> 8.493 | U53: =IF(T$10<>0,T53/T$10,0) -> 0.013198812 | V53: =+月次PL!L56/1000 -> 8.219 | W53: =IF(V$10<>0,V53/V$10,0) -> 0.0079748345 | X53: =+月次PL!M56/1000 -> 8.493 | Y53: =IF(X$10<>0,X53/X$10,0) -> 0.0095383669 | Z53: =+月次PL!N56/1000 -> 8.219 | AA53: =IF(Z$10<>0,Z53/Z$10,0) -> 0.0083148284
B54: 経常損益 | D54: =+D50+D52-D53 -> -283.863 | E54: =IF(D$10<>0,D54/D$10,0) -> -0.45576101 | F54: =+F50+F52-F53 -> -14.792 | G54: =IF(F$10<>0,F54/F$10,0) -> -0.02642174 | H54: =+H50+H52-H53 -> -89.776 | I54: =IF(H$10<>0,H54/H$10,0) -> -0.1570455 | J54: =+J50+J52-J53 -> -161.804 | K54: =IF(J$10<>0,J54/J$10,0) -> -0.28303247 | L54: =+L50+L52-L53 -> -50.88 | M54: =IF(L$10<>0,L54/L$10,0) -> -0.1054416 | N54: =+N50+N52-N53 -> -135.396 | O54: =IF(N$10<>0,N54/N$10,0) -> -0.23834177 | P54: =+P50+P52-P53 -> -109.563 | Q54: =IF(P$10<>0,P54/P$10,0) -> -0.19119441 | R54: =+R50+R52-R53 -> -65.054 | S54: =IF(R$10<>0,R54/R$10,0) -> -0.11490432 | T54: =+T50+T52-T53 -> -19.104 | U54: =IF(T$10<>0,T54/T$10,0) -> -0.029689168 | V54: =+V50+V52-V53 -> 421.107 | W54: =IF(V$10<>0,V54/V$10,0) -> 0.40859699 | X54: =+X50+X52-X53 -> 205.722 | Y54: =IF(X$10<>0,X54/X$10,0) -> 0.23104344 | Z54: =+Z50+Z52-Z53 -> 318.854 | AA54: =IF(Z$10<>0,Z54/Z$10,0) -> 0.32257164
C55: 期中累計 | D55: =+D54 -> -283.863 | F55: =+D55+F54 -> -298.655 | H55: =+F55+H54 -> -388.431 | J55: =+H55+J54 -> -550.235 | L55: =+J55+L54 -> -601.115 | N55: =+L55+N54 -> -736.511 | P55: =+N55+P54 -> -846.074 | R55: =+P55+R54 -> -911.128 | T55: =+R55+T54 -> -930.232 | V55: =+T55+V54 -> -509.125 | X55: =+V55+X54 -> -303.403 | Z55: =+X55+Z54 -> 15.451
B56: 繰越利益剰余金(BS) | D56: =+BS千円!D80 -> 6121.543 | E56: =+D56/BS千円!D93 -> 0.3073757 | F56: =+BS千円!E80 -> 6106.751 | G56: =+F56/BS千円!E93 -> 0.30995725 | H56: =+BS千円!F80 -> 6016.975 | I56: =+H56/BS千円!F93 -> 0.30444547 | J56: =+BS千円!G80 -> 5855.171 | K56: =+J56/BS千円!G93 -> 0.29760196 | L56: =+BS千円!H80 -> 5804.291 | M56: =+L56/BS千円!H93 -> 0.29529456 | N56: =+BS千円!I80 -> 5668.895 | O56: =+N56/BS千円!I93 -> 0.28659764 | P56: =+BS千円!J80 -> 5559.332 | Q56: =+P56/BS千円!J93 -> 0.28516982 | R56: =+BS千円!K80 -> 5494.278 | S56: =+R56/BS千円!K93 -> 0.28165798 | T56: =+BS千円!L80 -> 5475.174 | U56: =+T56/BS千円!L93 -> 0.2804852 | V56: =+BS千円!M80 -> 5896.281 | W56: =+V56/BS千円!M93 -> 0.29421682 | X56: =+BS千円!N80 -> 6102.003 | Y56: =+X56/BS千円!N93 -> 0.29879493 | Z56: =+BS千円!O80 -> 6420.857 | AA56: =+Z56/BS千円!O47 -> 0.30823129

Sheet PL予実対比
A7: ■月次PL予実対比 | BB7: =+PL推移!D7 -> ㈱Ｓクリエイト
A8: =+PL推移!B8 -> 2025 | B8: 年度 | BB8: 単位：千円
A9: 項目 | C9: =+PL推移!D9 -> 7 | G9: =+PL推移!F9 -> 8 | K9: =+PL推移!H9 -> 9 | O9: =+PL推移!J9 -> 10 | S9: =+PL推移!L9 -> 11 | W9: =+PL推移!N9 -> 12 | AA9: =+PL推移!P9 -> 1 | AE9: =+PL推移!R9 -> 2 | AI9: =+PL推移!T9 -> 3 | AM9: =+PL推移!V9 -> 4 | AQ9: =+PL推移!X9 -> 5 | AU9: =+PL推移!Z9 -> 6 | AY9: 累計
C10: 計画 | D10: 実績 | E10: 差異 | F10: 計画比 | G10: 計画 | H10: 実績 | I10: 差異 | J10: 計画比 | K10: 計画 | L10: 実績 | M10: 差異 | N10: 計画比 | O10: 計画 | P10: 実績 | Q10: 差異 | R10: 計画比 | S10: 計画 | T10: 実績 | U10: 差異 | V10: 計画比 | W10: 計画 | X10: 実績 | Y10: 差異 | Z10: 計画比 | AA10: 計画 | AB10: 実績 | AC10: 差異 | AD10: 計画比 | AE10: 計画 | AF10: 実績 | AG10: 差異 | AH10: 計画比 | AI10: 計画 | AJ10: 実績 | AK10: 差異 | AL10: 計画比 | AM10: 計画 | AN10: 実績 | AO10: 差異 | AP10: 計画比 | AQ10: 計画 | AR10: 実績 | AS10: 差異 | AT10: 計画比 | AU10: 計画 | AV10: 実績 | AW10: 差異 | AX10: 計画比 | AY10: 計画 | AZ10: 実績 | BA10: 差異 | BB10: 計画比
A11: 売上高 | C11: =+収支計画!G17/1000 -> 622.833 | D11: =+PL推移!D10 -> 622.833 | E11: =SUM(E12:E16) -> 0 | F11: =IF(C11<>0,D11/C11,"-") -> 1 | G11: =+収支計画!H17/1000 -> 559.842 | H11: =SUM(H12:H16) -> 559.842 | I11: =SUM(I12:I16) -> 0 | J11: =IF(G11<>0,H11/G11,"-") -> 1 | K11: =SUM(K12:K16) -> 621.88128 | L11: =+PL推移!H10 -> 571.656 | M11: =SUM(M12:M16) -> -50.225279 | N11: =IF(K11<>0,L11/K11,"-") -> 0.91923655 | O11: =SUM(O12:O16) -> 576.5003 | P11: =+PL推移!J10 -> 571.68 | Q11: =SUM(Q12:Q16) -> -4.8202984 | R11: =IF(O11<>0,P11/O11,"-") -> 0.99163869 | S11: =SUM(S12:S16) -> 553.80981 | T11: =+PL推移!L10 -> 482.542 | U11: =SUM(U12:U16) -> -71.267808 | V11: =IF(S11<>0,T11/S11,"-") -> 0.87131357 | W11: =+収支計画!L17/1000 -> 576.5003 | X11: =+PL推移!N10 -> 568.075 | Y11: =SUM(Y12:Y16) -> -8.4252984 | Z11: =IF(W11<>0,X11/W11,"-") -> 0.98538544 | AA11: =+収支計画!M17/1000 -> 599.19079 | AB11: =+PL推移!P10 -> 573.045 | AC11: =SUM(AC12:AC16) -> -26.145789 | AD11: =IF(AA11<>0,AB11/AA11,"-") -> 0.95636484 | AE11: =+収支計画!N17/1000 -> 599.19079 | AF11: =+PL推移!R10 -> 566.158 | AG11: =SUM(AG12:AG16) -> -33.032789 | AH11: =IF(AE11<>0,AF11/AE11,"-") -> 0.944871 | AI11: =+収支計画!O17/1000 -> 599.19079 | AJ11: =+PL推移!T10 -> 643.467 | AK11: =SUM(AK12:AK16) -> 44.276211 | AL11: =IF(AI11<>0,AJ11/AI11,"-") -> 1.0738933 | AM11: =+収支計画!P17/1000 -> 793.196 | AN11: =+PL推移!V10 -> 1030.617 | AO11: =+AN11-AM11 -> 237.421 | AP11: =IF(AM11<>0,AN11/AM11,"-") -> 1.299322 | AQ11: =+収支計画!Q17/1000 -> 761.687 | AR11: =+PL推移!X10 -> 890.404 | AS11: =+AR11-AQ11 -> 128.717 | AT11: =IF(AQ11<>0,AR11/AQ11,"-") -> 1.1689894 | AU11: =+収支計画!R17/1000 -> 793.196 | AV11: =+PL推移!Z10 -> 988.475 | AW11: =+AV11-AU11 -> 195.279 | AX11: =IF(AU11<>0,AV11/AU11,"-") -> 1.2461926 | AY11: =+C11+G11+K11+O11+S11+W11+AA11+AE11+AI11+AM11+AQ11+AU11 -> 7657.0181 | AZ11: =+D11+H11+L11+P11+T11+X11+AB11+AF11+AJ11+AN11+AR11+AV11 -> 8068.794 | BA11: =+AZ11-AY11 -> 411.77595 | BB11: =IF(AY11<>0,AZ11/AY11,"-") -> 1.0537776
B12: =+PL推移!C11 -> 売上高 | C12: =+収支計画!G11/1000 -> 622.833 | D12: =+PL推移!D11 -> 622.833 | E12: =+D12-C12 -> 0 | F12: =IF(C12<>0,D12/C12,"-") -> 1 | G12: =+収支計画!H11/1000 -> 559.842 | H12: =+PL推移!F11 -> 559.842 | I12: =+H12-G12 -> 0 | J12: =IF(G12<>0,H12/G12,"-") -> 1 | K12: =+収支計画!I11/1000 -> 621.88128 | L12: =+PL推移!H11 -> 571.656 | M12: =+L12-K12 -> -50.225279 | N12: =IF(K12<>0,L12/K12,"-") -> 0.91923655 | O12: =+収支計画!J11/1000 -> 576.5003 | P12: =+PL推移!J11 -> 571.68 | Q12: =+P12-O12 -> -4.8202984 | R12: =IF(O12<>0,P12/O12,"-") -> 0.99163869 | S12: =+収支計画!K11/1000 -> 553.80981 | T12: =+PL推移!L11 -> 482.542 | U12: =+T12-S12 -> -71.267808 | V12: =IF(S12<>0,T12/S12,"-") -> 0.87131357 | W12: =+収支計画!L11/1000 -> 576.5003 | X12: =+PL推移!N11 -> 568.075 | Y12: =+X12-W12 -> -8.4252984 | Z12: =IF(W12<>0,X12/W12,"-") -> 0.98538544 | AA12: =+収支計画!M11/1000 -> 599.19079 | AB12: =+PL推移!P11 -> 573.045 | AC12: =+AB12-AA12 -> -26.145789 | AD12: =IF(AA12<>0,AB12/AA12,"-") -> 0.95636484 | AE12: =+収支計画!O17/1000 -> 599.19079 | AF12: =+PL推移!R11 -> 566.158 | AG12: =+AF12-AE12 -> -33.032789 | AH12: =IF(AE12<>0,AF12/AE12,"-") -> 0.944871 | AI12: =+収支計画!O11/1000 -> 599.19079 | AJ12: =+PL推移!T11 -> 643.467 | AK12: =+AJ12-AI12 -> 44.276211 | AL12: =IF(AI12<>0,AJ12/AI12,"-") -> 1.0738933 | AM12: =+収支計画!P11/1000 -> 793.196 | AN12: =+PL推移!V11 -> 1030.617 | AO12: =+AN12-AM12 -> 237.421 | AP12: =IF(AM12<>0,AN12/AM12,"-") -> 1.299322 | AQ12: =+収支計画!Q11/1000 -> 761.687 | AR12: =+PL推移!X11 -> 890.404 | AS12: =+AR12-AQ12 -> 128.717 | AT12: =IF(AQ12<>0,AR12/AQ12,"-") -> 1.1689894 | AU12: =+収支計画!R11/1000 -> 793.196 | AV12: =+PL推移!Z11 -> 0 | AW12: =+AV12-AU12 -> -793.196 | AX12: =IF(AU12<>0,AV12/AU12,"-") -> 0 | AY12: =+C12+G12+K12+O12+S12+W12+AA12+AE12+AI12+AM12+AQ12+AU12 -> 7657.0181 | AZ12: =+D12+H12+L12+P12+T12+X12+AB12+AF12+AJ12+AN12+AR12+AV12 -> 7080.319 | BA12: =+AZ12-AY12 -> -576.69905 | BB12: =IF(AY12<>0,AZ12/AY12,"-") -> 0.9246836
B13: =+PL推移!C12 -> 0 | C13: =+収支計画!G12/1000 -> 0 | D13: =+PL推移!D12 -> 0 | E13: =+D13-C13 -> 0 | F13: =IF(C13<>0,D13/C13,"-") -> - | G13: =+収支計画!H12/1000 -> 0 | H13: =+PL推移!F12 -> 0 | I13: =+H13-G13 -> 0 | J13: =IF(G13<>0,H13/G13,"-") -> - | K13: =+収支計画!I12/1000 -> 0 | L13: =+PL推移!H12 -> 0 | M13: =+L13-K13 -> 0 | N13: =IF(K13<>0,L13/K13,"-") -> - | O13: =+収支計画!J12/1000 -> 0 | P13: =+PL推移!J12 -> 0 | Q13: =+P13-O13 -> 0 | R13: =IF(O13<>0,P13/O13,"-") -> - | S13: =+収支計画!K12/1000 -> 0 | T13: =+PL推移!L12 -> 0 | U13: =+T13-S13 -> 0 | V13: =IF(S13<>0,T13/S13,"-") -> - | W13: =+収支計画!W12/1000 -> 0 | X13: =+PL推移!N12 -> 0 | Y13: =+X13-W13 -> 0 | Z13: =IF(W13<>0,X13/W13,"-") -> - | AA13: =+収支計画!AA12/1000 -> 0 | AB13: =+PL推移!P12 -> 0 | AC13: =+AB13-AA13 -> 0 | AD13: =IF(AA13<>0,AB13/AA13,"-") -> - | AE13: =+収支計画!AA12/1000 -> 0 | AF13: =+PL推移!R12 -> 0 | AG13: =+AF13-AE13 -> 0 | AH13: =IF(AE13<>0,AF13/AE13,"-") -> - | AI13: =+収支計画!AC12/1000 -> 0 | AJ13: =+PL推移!T12 -> 0 | AK13: =+AJ13-AI13 -> 0 | AL13: =IF(AI13<>0,AJ13/AI13,"-") -> - | AM13: =+収支計画!AG12/1000 -> 0 | AN13: =+PL推移!V12 -> 0 | AO13: =+AN13-AM13 -> 0 | AP13: =IF(AM13<>0,AN13/AM13,"-") -> - | AQ13: =+収支計画!AG12/1000 -> 0 | AR13: =+PL推移!X12 -> 0 | AS13: =+AR13-AQ13 -> 0 | AT13: =IF(AQ13<>0,AR13/AQ13,"-") -> - | AU13: =+収支計画!AI12/1000 -> 0 | AV13: =+PL推移!Z12 -> 0 | AW13: =+AV13-AU13 -> 0 | AX13: =IF(AU13<>0,AV13/AU13,"-") -> - | AY13: =+C13+G13+K13+O13+S13+W13+AA13+AE13+AI13+AM13+AQ13+AU13 -> 0 | AZ13: =+D13+H13+L13+P13+T13+X13+AB13+AF13+AJ13+AN13+AR13+AV13 -> 0 | BA13: =+AZ13-AY13 -> 0 | BB13: =IF(AY13<>0,AZ13/AY13,"-") -> -
B14: =+PL推移!C13 -> 0 | C14: =+収支計画!G13/1000 -> 0 | D14: =+PL推移!D13 -> 0 | E14: =+D14-C14 -> 0 | F14: =IF(C14<>0,D14/C14,"-") -> - | G14: =+収支計画!H13/1000 -> 0 | H14: =+PL推移!F13 -> 0 | I14: =+H14-G14 -> 0 | J14: =IF(G14<>0,H14/G14,"-") -> - | K14: =+収支計画!I13/1000 -> 0 | L14: =+PL推移!H13 -> 0 | M14: =+L14-K14 -> 0 | N14: =IF(K14<>0,L14/K14,"-") -> - | O14: =+収支計画!J13/1000 -> 0 | P14: =+PL推移!J13 -> 0 | Q14: =+P14-O14 -> 0 | R14: =IF(O14<>0,P14/O14,"-") -> - | S14: =+収支計画!K13/1000 -> 0 | T14: =+PL推移!L13 -> 0 | U14: =+T14-S14 -> 0 | V14: =IF(S14<>0,T14/S14,"-") -> - | W14: =+収支計画!W13/1000 -> 0 | X14: =+PL推移!N13 -> 0 | Y14: =+X14-W14 -> 0 | Z14: =IF(W14<>0,X14/W14,"-") -> - | AA14: =+収支計画!AA13/1000 -> 0 | AB14: =+PL推移!P13 -> 0 | AC14: =+AB14-AA14 -> 0 | AD14: =IF(AA14<>0,AB14/AA14,"-") -> - | AE14: =+収支計画!AA13/1000 -> 0 | AF14: =+PL推移!R13 -> 0 | AG14: =+AF14-AE14 -> 0 | AH14: =IF(AE14<>0,AF14/AE14,"-") -> - | AI14: =+収支計画!AC13/1000 -> 0 | AJ14: =+PL推移!T13 -> 0 | AK14: =+AJ14-AI14 -> 0 | AL14: =IF(AI14<>0,AJ14/AI14,"-") -> - | AM14: =+収支計画!AG13/1000 -> 0 | AN14: =+PL推移!V13 -> 0 | AO14: =+AN14-AM14 -> 0 | AP14: =IF(AM14<>0,AN14/AM14,"-") -> - | AQ14: =+収支計画!AG13/1000 -> 0 | AR14: =+PL推移!X13 -> 0 | AS14: =+AR14-AQ14 -> 0 | AT14: =IF(AQ14<>0,AR14/AQ14,"-") -> - | AU14: =+収支計画!AI13/1000 -> 0 | AV14: =+PL推移!Z13 -> 0 | AW14: =+AV14-AU14 -> 0 | AX14: =IF(AU14<>0,AV14/AU14,"-") -> - | AY14: =+C14+G14+K14+O14+S14+W14+AA14+AE14+AI14+AM14+AQ14+AU14 -> 0 | AZ14: =+D14+H14+L14+P14+T14+X14+AB14+AF14+AJ14+AN14+AR14+AV14 -> 0 | BA14: =+AZ14-AY14 -> 0 | BB14: =IF(AY14<>0,AZ14/AY14,"-") -> -
B15: =+PL推移!C14 -> 0 | C15: =+収支計画!G14/1000 -> 0 | D15: =+PL推移!D14 -> 0 | E15: =+D15-C15 -> 0 | F15: =IF(C15<>0,D15/C15,"-") -> - | G15: =+収支計画!H14/1000 -> 0 | H15: =+PL推移!F14 -> 0 | I15: =+H15-G15 -> 0 | J15: =IF(G15<>0,H15/G15,"-") -> - | K15: =+収支計画!I14/1000 -> 0 | L15: =+PL推移!H14 -> 0 | M15: =+L15-K15 -> 0 | N15: =IF(K15<>0,L15/K15,"-") -> - | O15: =+収支計画!J14/1000 -> 0 | P15: =+PL推移!J14 -> 0 | Q15: =+P15-O15 -> 0 | R15: =IF(O15<>0,P15/O15,"-") -> - | S15: =+収支計画!K14/1000 -> 0 | T15: =+PL推移!L14 -> 0 | U15: =+T15-S15 -> 0 | V15: =IF(S15<>0,T15/S15,"-") -> - | W15: =+収支計画!W14/1000 -> 0 | X15: =+PL推移!N14 -> 0 | Y15: =+X15-W15 -> 0 | Z15: =IF(W15<>0,X15/W15,"-") -> - | AA15: =+収支計画!AA14/1000 -> 0 | AB15: =+PL推移!P14 -> 0 | AC15: =+AB15-AA15 -> 0 | AD15: =IF(AA15<>0,AB15/AA15,"-") -> - | AE15: =+収支計画!AA14/1000 -> 0 | AF15: =+PL推移!R14 -> 0 | AG15: =+AF15-AE15 -> 0 | AH15: =IF(AE15<>0,AF15/AE15,"-") -> - | AI15: =+収支計画!AC14/1000 -> 0 | AJ15: =+PL推移!T14 -> 0 | AK15: =+AJ15-AI15 -> 0 | AL15: =IF(AI15<>0,AJ15/AI15,"-") -> - | AM15: =+収支計画!AG14/1000 -> 0 | AN15: =+PL推移!V14 -> 0 | AO15: =+AN15-AM15 -> 0 | AP15: =IF(AM15<>0,AN15/AM15,"-") -> - | AQ15: =+収支計画!AG14/1000 -> 0 | AR15: =+PL推移!X14 -> 0 | AS15: =+AR15-AQ15 -> 0 | AT15: =IF(AQ15<>0,AR15/AQ15,"-") -> - | AU15: =+収支計画!AI14/1000 -> 0 | AV15: =+PL推移!Z14 -> 0 | AW15: =+AV15-AU15 -> 0 | AX15: =IF(AU15<>0,AV15/AU15,"-") -> - | AY15: =+C15+G15+K15+O15+S15+W15+AA15+AE15+AI15+AM15+AQ15+AU15 -> 0 | AZ15: =+D15+H15+L15+P15+T15+X15+AB15+AF15+AJ15+AN15+AR15+AV15 -> 0 | BA15: =+AZ15-AY15 -> 0 | BB15: =IF(AY15<>0,AZ15/AY15,"-") -> -
B16: =+PL推移!C15 -> 0 | C16: =+収支計画!G15/1000 -> 0 | D16: =+PL推移!D15 -> 0 | E16: =+D16-C16 -> 0 | F16: =IF(C16<>0,D16/C16,"-") -> - | G16: =+収支計画!H15/1000 -> 0 | H16: =+PL推移!F15 -> 0 | I16: =+H16-G16 -> 0 | J16: =IF(G16<>0,H16/G16,"-") -> - | K16: =+収支計画!I15/1000 -> 0 | L16: =+PL推移!H15 -> 0 | M16: =+L16-K16 -> 0 | N16: =IF(K16<>0,L16/K16,"-") -> - | O16: =+収支計画!J15/1000 -> 0 | P16: =+PL推移!J15 -> 0 | Q16: =+P16-O16 -> 0 | R16: =IF(O16<>0,P16/O16,"-") -> - | S16: =+収支計画!K15/1000 -> 0 | T16: =+PL推移!L15 -> 0 | U16: =+T16-S16 -> 0 | V16: =IF(S16<>0,T16/S16,"-") -> - | W16: =+収支計画!W15/1000 -> 0 | X16: =+PL推移!N15 -> 0 | Y16: =+X16-W16 -> 0 | Z16: =IF(W16<>0,X16/W16,"-") -> - | AA16: =+収支計画!AA15/1000 -> 0 | AB16: =+PL推移!P15 -> 0 | AC16: =+AB16-AA16 -> 0 | AD16: =IF(AA16<>0,AB16/AA16,"-") -> - | AE16: =+収支計画!AA15/1000 -> 0 | AF16: =+PL推移!R15 -> 0 | AG16: =+AF16-AE16 -> 0 | AH16: =IF(AE16<>0,AF16/AE16,"-") -> - | AI16: =+収支計画!AC15/1000 -> 0 | AJ16: =+PL推移!T15 -> 0 | AK16: =+AJ16-AI16 -> 0 | AL16: =IF(AI16<>0,AJ16/AI16,"-") -> - | AM16: =+収支計画!AG15/1000 -> 0 | AN16: =+PL推移!V15 -> 0 | AO16: =+AN16-AM16 -> 0 | AP16: =IF(AM16<>0,AN16/AM16,"-") -> - | AQ16: =+収支計画!AG15/1000 -> 0 | AR16: =+PL推移!X15 -> 0 | AS16: =+AR16-AQ16 -> 0 | AT16: =IF(AQ16<>0,AR16/AQ16,"-") -> - | AU16: =+収支計画!AI15/1000 -> 0 | AV16: =+PL推移!Z15 -> 0 | AW16: =+AV16-AU16 -> 0 | AX16: =IF(AU16<>0,AV16/AU16,"-") -> - | AY16: =+C16+G16+K16+O16+S16+W16+AA16+AE16+AI16+AM16+AQ16+AU16 -> 0 | AZ16: =+D16+H16+L16+P16+T16+X16+AB16+AF16+AJ16+AN16+AR16+AV16 -> 0 | BA16: =+AZ16-AY16 -> 0 | BB16: =IF(AY16<>0,AZ16/AY16,"-") -> -
A17: 売上原価 | C17: =SUM(C18:C22) -> 0 | D17: =+PL推移!D16 -> 0 | E17: =SUM(E18:E22) -> 0 | F17: =IF(C17<>0,D17/C17,"-") -> - | G17: =+収支計画!H24/1000 -> 0 | H17: =+PL推移!F16 -> 0 | I17: =SUM(I18:I22) -> 0 | J17: =IF(G17<>0,H17/G17,"-") -> - | K17: =SUM(K18:K22) -> 0 | L17: =+PL推移!H16 -> 0 | M17: =SUM(M18:M22) -> 0 | N17: =IF(K17<>0,L17/K17,"-") -> - | O17: =SUM(O18:O22) -> 0 | P17: =+PL推移!J16 -> 0 | Q17: =SUM(Q18:Q22) -> 0 | R17: =IF(O17<>0,P17/O17,"-") -> - | S17: =SUM(S18:S22) -> 0 | T17: =+PL推移!L16 -> 0 | U17: =SUM(U18:U22) -> 0 | V17: =IF(S17<>0,T17/S17,"-") -> - | W17: =SUM(W18:W22) -> 0 | X17: =+PL推移!N16 -> 0 | Y17: =SUM(Y18:Y22) -> 0 | Z17: =IF(W17<>0,X17/W17,"-") -> - | AA17: =SUM(AA18:AA22) -> 0 | AB17: =+PL推移!P16 -> 0 | AC17: =SUM(AC18:AC22) -> 0 | AD17: =IF(AA17<>0,AB17/AA17,"-") -> - | AE17: =SUM(AE18:AE22) -> 0 | AF17: =+PL推移!R16 -> 0 | AG17: =SUM(AG18:AG22) -> 0 | AH17: =IF(AE17<>0,AF17/AE17,"-") -> - | AI17: =SUM(AI18:AI22) -> 0 | AJ17: =+PL推移!T16 -> 0 | AK17: =SUM(AK18:AK22) -> 0 | AL17: =IF(AI17<>0,AJ17/AI17,"-") -> - | AM17: =SUM(AM18:AM22) -> 0 | AN17: =+PL推移!V16 -> 0 | AO17: =+AN17-AM17 -> 0 | AP17: =IF(AM17<>0,AN17/AM17,"-") -> - | AQ17: =SUM(AQ18:AQ22) -> 0 | AR17: =+PL推移!X16 -> 0 | AS17: =+AR17-AQ17 -> 0 | AT17: =IF(AQ17<>0,AR17/AQ17,"-") -> - | AU17: =+収支計画!AI24/1000 -> 0 | AV17: =+PL推移!Z16 -> 0 | AW17: =+AV17-AU17 -> 0 | AX17: =IF(AU17<>0,AV17/AU17,"-") -> - | AY17: =+C17+G17+K17+O17+S17+W17+AA17+AE17+AI17+AM17+AQ17+AU17 -> 0 | AZ17: =+D17+H17+L17+P17+T17+X17+AB17+AF17+AJ17+AN17+AR17+AV17 -> 0 | BA17: =+AZ17-AY17 -> 0 | BB17: =IF(AY17<>0,AZ17/AY17,"-") -> -
B18: =+PL推移!C17 -> 0 | C18: =+収支計画!G18/1000 -> 0 | D18: =+PL推移!D17 -> 0 | E18: =+D18-C18 -> 0 | F18: =IF(C18<>0,D18/C18,"-") -> - | G18: =+収支計画!H18/1000 -> 0 | H18: =+PL推移!F17 -> 0 | I18: =+H18-G18 -> 0 | J18: =IF(G18<>0,H18/G18,"-") -> - | K18: =+収支計画!I18/1000 -> 0 | L18: =+PL推移!H17 -> 0 | M18: =+L18-K18 -> 0 | N18: =IF(K18<>0,L18/K18,"-") -> - | O18: =+収支計画!J18/1000 -> 0 | P18: =+PL推移!J17 -> 0 | Q18: =+P18-O18 -> 0 | R18: =IF(O18<>0,P18/O18,"-") -> - | S18: =+収支計画!K18/1000 -> 0 | T18: =+PL推移!L17 -> 0 | U18: =+T18-S18 -> 0 | V18: =IF(S18<>0,T18/S18,"-") -> - | W18: =+収支計画!W18/1000 -> 0 | X18: =+PL推移!N17 -> 0 | Y18: =+X18-W18 -> 0 | Z18: =IF(W18<>0,X18/W18,"-") -> - | AA18: =+収支計画!Y18/1000 -> 0 | AB18: =+PL推移!P17 -> 0 | AC18: =+AB18-AA18 -> 0 | AD18: =IF(AA18<>0,AB18/AA18,"-") -> - | AE18: =+収支計画!AA18/1000 -> 0 | AF18: =+PL推移!R17 -> 0 | AG18: =+AF18-AE18 -> 0 | AH18: =IF(AE18<>0,AF18/AE18,"-") -> - | AI18: =+収支計画!AC18/1000 -> 0 | AJ18: =+PL推移!T17 -> 0 | AK18: =+AJ18-AI18 -> 0 | AL18: =IF(AI18<>0,AJ18/AI18,"-") -> - | AM18: =+収支計画!AG18/1000 -> 0 | AN18: =+PL推移!V17 -> 0 | AO18: =+AN18-AM18 -> 0 | AP18: =IF(AM18<>0,AN18/AM18,"-") -> - | AQ18: =+収支計画!AG18/1000 -> 0 | AR18: =+PL推移!X17 -> 0 | AS18: =+AR18-AQ18 -> 0 | AT18: =IF(AQ18<>0,AR18/AQ18,"-") -> - | AU18: =+収支計画!AI18/1000 -> 0 | AV18: =+PL推移!Z17 -> 0 | AW18: =+AV18-AU18 -> 0 | AX18: =IF(AU18<>0,AV18/AU18,"-") -> - | AY18: =+C18+G18+K18+O18+S18+W18+AA18+AE18+AI18+AM18+AQ18+AU18 -> 0 | AZ18: =+D18+H18+L18+P18+T18+X18+AB18+AF18+AJ18+AN18+AR18+AV18 -> 0 | BA18: =+AZ18-AY18 -> 0 | BB18: =IF(AY18<>0,AZ18/AY18,"-") -> -
B19: =+PL推移!C18 -> 0 | C19: =+収支計画!G19/1000 -> 0 | D19: =+PL推移!D18 -> 0 | E19: =+D19-C19 -> 0 | F19: =IF(C19<>0,D19/C19,"-") -> - | G19: =+収支計画!H19/1000 -> 0 | H19: =+PL推移!F18 -> 0 | I19: =+H19-G19 -> 0 | J19: =IF(G19<>0,H19/G19,"-") -> - | K19: =+収支計画!O19/1000 -> 0 | L19: =+PL推移!H18 -> 0 | M19: =+L19-K19 -> 0 | N19: =IF(K19<>0,L19/K19,"-") -> - | O19: =+収支計画!S19/1000 -> 0 | P19: =+PL推移!J18 -> 0 | Q19: =+P19-O19 -> 0 | R19: =IF(O19<>0,P19/O19,"-") -> - | S19: =+収支計画!U19/1000 -> 0 | T19: =+PL推移!L18 -> 0 | U19: =+T19-S19 -> 0 | V19: =IF(S19<>0,T19/S19,"-") -> - | W19: =+収支計画!W19/1000 -> 0 | X19: =+PL推移!N18 -> 0 | Y19: =+X19-W19 -> 0 | Z19: =IF(W19<>0,X19/W19,"-") -> - | AA19: =+収支計画!Y19/1000 -> 0 | AB19: =+PL推移!P18 -> 0 | AC19: =+AB19-AA19 -> 0 | AD19: =IF(AA19<>0,AB19/AA19,"-") -> - | AE19: =+収支計画!AA19/1000 -> 0 | AF19: =+PL推移!R18 -> 0 | AG19: =+AF19-AE19 -> 0 | AH19: =IF(AE19<>0,AF19/AE19,"-") -> - | AI19: =+収支計画!AC19/1000 -> 0 | AJ19: =+PL推移!T18 -> 0 | AK19: =+AJ19-AI19 -> 0 | AL19: =IF(AI19<>0,AJ19/AI19,"-") -> - | AM19: =+収支計画!AG19/1000 -> 0 | AN19: =+PL推移!V18 -> 0 | AO19: =+AN19-AM19 -> 0 | AP19: =IF(AM19<>0,AN19/AM19,"-") -> - | AQ19: =+収支計画!AG19/1000 -> 0 | AR19: =+PL推移!X18 -> 0 | AS19: =+AR19-AQ19 -> 0 | AT19: =IF(AQ19<>0,AR19/AQ19,"-") -> - | AU19: =+収支計画!AI19/1000 -> 0 | AV19: =+PL推移!Z18 -> 0 | AW19: =+AV19-AU19 -> 0 | AX19: =IF(AU19<>0,AV19/AU19,"-") -> - | AY19: =+C19+G19+K19+O19+S19+W19+AA19+AE19+AI19+AM19+AQ19+AU19 -> 0 | AZ19: =+D19+H19+L19+P19+T19+X19+AB19+AF19+AJ19+AN19+AR19+AV19 -> 0 | BA19: =+AZ19-AY19 -> 0 | BB19: =IF(AY19<>0,AZ19/AY19,"-") -> -
B20: =+PL推移!C19 -> 0 | C20: =+収支計画!G20/1000 -> 0 | D20: =+PL推移!D19 -> 0 | E20: =+D20-C20 -> 0 | F20: =IF(C20<>0,D20/C20,"-") -> - | G20: =+収支計画!H20/1000 -> 0 | H20: =+PL推移!F19 -> 0 | I20: =+H20-G20 -> 0 | J20: =IF(G20<>0,H20/G20,"-") -> - | K20: =+収支計画!O20/1000 -> 0 | L20: =+PL推移!H19 -> 0 | M20: =+L20-K20 -> 0 | N20: =IF(K20<>0,L20/K20,"-") -> - | O20: =+収支計画!S20/1000 -> 0 | P20: =+PL推移!J19 -> 0 | Q20: =+P20-O20 -> 0 | R20: =IF(O20<>0,P20/O20,"-") -> - | S20: =+収支計画!U20/1000 -> 0 | T20: =+PL推移!L19 -> 0 | U20: =+T20-S20 -> 0 | V20: =IF(S20<>0,T20/S20,"-") -> - | W20: =+収支計画!W20/1000 -> 0 | X20: =+PL推移!N19 -> 0 | Y20: =+X20-W20 -> 0 | Z20: =IF(W20<>0,X20/W20,"-") -> - | AA20: =+収支計画!Y20/1000 -> 0 | AB20: =+PL推移!P19 -> 0 | AC20: =+AB20-AA20 -> 0 | AD20: =IF(AA20<>0,AB20/AA20,"-") -> - | AE20: =+収支計画!AA20/1000 -> 0 | AF20: =+PL推移!R19 -> 0 | AG20: =+AF20-AE20 -> 0 | AH20: =IF(AE20<>0,AF20/AE20,"-") -> - | AI20: =+収支計画!AC20/1000 -> 0 | AJ20: =+PL推移!T19 -> 0 | AK20: =+AJ20-AI20 -> 0 | AL20: =IF(AI20<>0,AJ20/AI20,"-") -> - | AM20: =+収支計画!AG20/1000 -> 0 | AN20: =+PL推移!V19 -> 0 | AO20: =+AN20-AM20 -> 0 | AP20: =IF(AM20<>0,AN20/AM20,"-") -> - | AQ20: =+収支計画!AG20/1000 -> 0 | AR20: =+PL推移!X19 -> 0 | AS20: =+AR20-AQ20 -> 0 | AT20: =IF(AQ20<>0,AR20/AQ20,"-") -> - | AU20: =+収支計画!AI20/1000 -> 0 | AV20: =+PL推移!Z19 -> 0 | AW20: =+AV20-AU20 -> 0 | AX20: =IF(AU20<>0,AV20/AU20,"-") -> - | AY20: =+C20+G20+K20+O20+S20+W20+AA20+AE20+AI20+AM20+AQ20+AU20 -> 0 | AZ20: =+D20+H20+L20+P20+T20+X20+AB20+AF20+AJ20+AN20+AR20+AV20 -> 0 | BA20: =+AZ20-AY20 -> 0 | BB20: =IF(AY20<>0,AZ20/AY20,"-") -> -
B21: =+PL推移!C20 -> 0 | C21: =+収支計画!G21/1000 -> 0 | D21: =+PL推移!D20 -> 0 | E21: =+D21-C21 -> 0 | F21: =IF(C21<>0,D21/C21,"-") -> - | G21: =+収支計画!H21/1000 -> 0 | H21: =+PL推移!F20 -> 0 | I21: =+H21-G21 -> 0 | J21: =IF(G21<>0,H21/G21,"-") -> - | K21: =+収支計画!O21/1000 -> 0 | L21: =+PL推移!H20 -> 0 | M21: =+L21-K21 -> 0 | N21: =IF(K21<>0,L21/K21,"-") -> - | O21: =+収支計画!S21/1000 -> 0 | P21: =+PL推移!J20 -> 0 | Q21: =+P21-O21 -> 0 | R21: =IF(O21<>0,P21/O21,"-") -> - | S21: =+収支計画!U21/1000 -> 0 | T21: =+PL推移!L20 -> 0 | U21: =+T21-S21 -> 0 | V21: =IF(S21<>0,T21/S21,"-") -> - | W21: =+収支計画!W21/1000 -> 0 | X21: =+PL推移!N20 -> 0 | Y21: =+X21-W21 -> 0 | Z21: =IF(W21<>0,X21/W21,"-") -> - | AA21: =+収支計画!Y21/1000 -> 0 | AB21: =+PL推移!P20 -> 0 | AC21: =+AB21-AA21 -> 0 | AD21: =IF(AA21<>0,AB21/AA21,"-") -> - | AE21: =+収支計画!AA21/1000 -> 0 | AF21: =+PL推移!R20 -> 0 | AG21: =+AF21-AE21 -> 0 | AH21: =IF(AE21<>0,AF21/AE21,"-") -> - | AI21: =+収支計画!AC21/1000 -> 0 | AJ21: =+PL推移!T20 -> 0 | AK21: =+AJ21-AI21 -> 0 | AL21: =IF(AI21<>0,AJ21/AI21,"-") -> - | AM21: =+収支計画!AG21/1000 -> 0 | AN21: =+PL推移!V20 -> 0 | AO21: =+AN21-AM21 -> 0 | AP21: =IF(AM21<>0,AN21/AM21,"-") -> - | AQ21: =+収支計画!AG21/1000 -> 0 | AR21: =+PL推移!X20 -> 0 | AS21: =+AR21-AQ21 -> 0 | AT21: =IF(AQ21<>0,AR21/AQ21,"-") -> - | AU21: =+収支計画!AI21/1000 -> 0 | AV21: =+PL推移!Z20 -> 0 | AW21: =+AV21-AU21 -> 0 | AX21: =IF(AU21<>0,AV21/AU21,"-") -> - | AY21: =+C21+G21+K21+O21+S21+W21+AA21+AE21+AI21+AM21+AQ21+AU21 -> 0 | AZ21: =+D21+H21+L21+P21+T21+X21+AB21+AF21+AJ21+AN21+AR21+AV21 -> 0 | BA21: =+AZ21-AY21 -> 0 | BB21: =IF(AY21<>0,AZ21/AY21,"-") -> -
B22: =+PL推移!C21 -> 0 | C22: =+収支計画!G22/1000 -> 0 | D22: =+PL推移!D21 -> 0 | E22: =+D22-C22 -> 0 | F22: =IF(C22<>0,D22/C22,"-") -> - | G22: =+収支計画!H22/1000 -> 0 | H22: =+PL推移!F21 -> 0 | I22: =+H22-G22 -> 0 | J22: =IF(G22<>0,H22/G22,"-") -> - | K22: =+収支計画!O22/1000 -> 0 | L22: =+PL推移!H21 -> 0 | M22: =+L22-K22 -> 0 | N22: =IF(K22<>0,L22/K22,"-") -> - | O22: =+収支計画!S22/1000 -> 0 | P22: =+PL推移!J21 -> 0 | Q22: =+P22-O22 -> 0 | R22: =IF(O22<>0,P22/O22,"-") -> - | S22: =+収支計画!U22/1000 -> 0 | T22: =+PL推移!L21 -> 0 | U22: =+T22-S22 -> 0 | V22: =IF(S22<>0,T22/S22,"-") -> - | W22: =+収支計画!W22/1000 -> 0 | X22: =+PL推移!N21 -> 0 | Y22: =+X22-W22 -> 0 | Z22: =IF(W22<>0,X22/W22,"-") -> - | AA22: =+収支計画!Y22/1000 -> 0 | AB22: =+PL推移!P21 -> 0 | AC22: =+AB22-AA22 -> 0 | AD22: =IF(AA22<>0,AB22/AA22,"-") -> - | AE22: =+収支計画!AA22/1000 -> 0 | AF22: =+PL推移!R21 -> 0 | AG22: =+AF22-AE22 -> 0 | AH22: =IF(AE22<>0,AF22/AE22,"-") -> - | AI22: =+収支計画!AC22/1000 -> 0 | AJ22: =+PL推移!T21 -> 0 | AK22: =+AJ22-AI22 -> 0 | AL22: =IF(AI22<>0,AJ22/AI22,"-") -> - | AM22: =+収支計画!AG22/1000 -> 0 | AN22: =+PL推移!V21 -> 0 | AO22: =+AN22-AM22 -> 0 | AP22: =IF(AM22<>0,AN22/AM22,"-") -> - | AQ22: =+収支計画!AG22/1000 -> 0 | AR22: =+PL推移!X21 -> 0 | AS22: =+AR22-AQ22 -> 0 | AT22: =IF(AQ22<>0,AR22/AQ22,"-") -> - | AU22: =+収支計画!AI22/1000 -> 0 | AV22: =+PL推移!Z21 -> 0 | AW22: =+AV22-AU22 -> 0 | AX22: =IF(AU22<>0,AV22/AU22,"-") -> - | AY22: =+C22+G22+K22+O22+S22+W22+AA22+AE22+AI22+AM22+AQ22+AU22 -> 0 | AZ22: =+D22+H22+L22+P22+T22+X22+AB22+AF22+AJ22+AN22+AR22+AV22 -> 0 | BA22: =+AZ22-AY22 -> 0 | BB22: =IF(AY22<>0,AZ22/AY22,"-") -> -
A23: 粗利益 | C23: =+C11-C17 -> 622.833 | D23: =+D11-D17 -> 622.833 | E23: =+E11-E17 -> 0 | F23: =IF(C23<>0,D23/C23,"-") -> 1 | G23: =+収支計画!H25/1000 -> 559.842 | H23: =+PL推移!F22 -> 559.842 | I23: =+I11-I17 -> 0 | J23: =IF(G23<>0,H23/G23,"-") -> 1 | K23: =SUM(K24:K28) -> 621.88128 | L23: =+PL推移!H22 -> 571.656 | M23: =+M11-M17 -> -50.225279 | N23: =IF(K23<>0,L23/K23,"-") -> 0.91923655 | O23: =SUM(O24:O28) -> 576.5003 | P23: =+PL推移!J22 -> 571.68 | Q23: =+Q11-Q17 -> -4.8202984 | R23: =IF(O23<>0,P23/O23,"-") -> 0.99163869 | S23: =SUM(S24:S28) -> 553.80981 | T23: =+T11-T17 -> 482.542 | U23: =+U11-U17 -> -71.267808 | V23: =IF(S23<>0,T23/S23,"-") -> 0.87131357 | W23: =SUM(W24:W28) -> 576.5003 | X23: =+X11-X17 -> 568.075 | Y23: =+Y11-Y17 -> -8.4252984 | Z23: =IF(W23<>0,X23/W23,"-") -> 0.98538544 | AA23: =+AA11-AA17 -> 599.19079 | AB23: =+AB11-AB17 -> 573.045 | AC23: =+AC11-AC17 -> -26.145789 | AD23: =IF(AA23<>0,AB23/AA23,"-") -> 0.95636484 | AE23: =SUM(AE24:AE28) -> 599.19079 | AF23: =+PL推移!R22 -> 566.158 | AG23: =+AG11-AG17 -> -33.032789 | AH23: =IF(AE23<>0,AF23/AE23,"-") -> 0.944871 | AI23: =SUM(AI24:AI28) -> 599.19079 | AJ23: =+AJ11-AJ17 -> 643.467 | AK23: =+AK11-AK17 -> 44.276211 | AL23: =IF(AI23<>0,AJ23/AI23,"-") -> 1.0738933 | AM23: =+AM11-AM17 -> 793.196 | AN23: =+AN11-AN17 -> 1030.617 | AO23: =+AN23-AM23 -> 237.421 | AP23: =IF(AM23<>0,AN23/AM23,"-") -> 1.299322 | AQ23: =+AQ11-AQ17 -> 761.687 | AR23: =+AR11-AR17 -> 890.404 | AS23: =+AR23-AQ23 -> 128.717 | AT23: =IF(AQ23<>0,AR23/AQ23,"-") -> 1.1689894 | AU23: =+AU11-AU17 -> 793.196 | AV23: =+AV11-AV17 -> 988.475 | AW23: =+AV23-AU23 -> 195.279 | AX23: =IF(AU23<>0,AV23/AU23,"-") -> 1.2461926 | AY23: =+C23+G23+K23+O23+S23+W23+AA23+AE23+AI23+AM23+AQ23+AU23 -> 7657.0181 | AZ23: =+D23+H23+L23+P23+T23+X23+AB23+AF23+AJ23+AN23+AR23+AV23 -> 8068.794 | BA23: =+AZ23-AY23 -> 411.77595 | BB23: =IF(AY23<>0,AZ23/AY23,"-") -> 1.0537776
D24: =+PL推移!D23 -> 0 | E24: =+D24-C24 -> 0 | F24: =IF(C24<>0,D24/C24,"-") -> - | I24: =+H24-G24 -> 0 | J24: =IF(G24<>0,H24/G24,"-") -> - | K24: =+K12-K18 -> 621.88128 | L24: =+PL推移!H23 -> 571.656 | M24: =+L24-K24 -> -50.225279 | N24: =IF(K24<>0,L24/K24,"-") -> 0.91923655 | O24: =+O12-O18 -> 576.5003 | P24: =+PL推移!J23 -> 571.68 | Q24: =+P24-O24 -> -4.8202984 | R24: =IF(O24<>0,P24/O24,"-") -> 0.99163869 | S24: =+S12-S18 -> 553.80981 | T24: =+T12-T18 -> 482.542 | U24: =+T24-S24 -> -71.267808 | V24: =IF(S24<>0,T24/S24,"-") -> 0.87131357 | W24: =+W12-W18 -> 576.5003 | X24: =+X12-X18 -> 568.075 | Y24: =+X24-W24 -> -8.4252984 | Z24: =IF(W24<>0,X24/W24,"-") -> 0.98538544 | AA24: =+AA12-AA18 -> 599.19079 | AB24: =+AB12-AB18 -> 573.045 | AC24: =+AB24-AA24 -> -26.145789 | AD24: =IF(AA24<>0,AB24/AA24,"-") -> 0.95636484 | AE24: =+AE12-AE18 -> 599.19079 | AF24: =+PL推移!R23 -> 566.158 | AG24: =+AF24-AE24 -> -33.032789 | AH24: =IF(AE24<>0,AF24/AE24,"-") -> 0.944871 | AI24: =+AI12-AI18 -> 599.19079 | AJ24: =+AJ12-AJ18 -> 643.467 | AK24: =+AJ24-AI24 -> 44.276211 | AL24: =IF(AI24<>0,AJ24/AI24,"-") -> 1.0738933 | AM24: =+AM12-AM18 -> 793.196 | AN24: =+AN12-AN18 -> 1030.617 | AO24: =+AN24-AM24 -> 237.421 | AP24: =IF(AM24<>0,AN24/AM24,"-") -> 1.299322 | AQ24: =+AQ12-AQ18 -> 761.687 | AR24: =+AR12-AR18 -> 890.404 | AS24: =+AR24-AQ24 -> 128.717 | AT24: =IF(AQ24<>0,AR24/AQ24,"-") -> 1.1689894 | AU24: =+AU12-AU18 -> 793.196 | AV24: =+AV12-AV18 -> 0 | AW24: =+AV24-AU24 -> -793.196 | AX24: =IF(AU24<>0,AV24/AU24,"-") -> 0 | AY24: =+C24+G24+K24+O24+S24+W24+AA24+AE24+AI24+AM24+AQ24+AU24 -> 6474.3431 | AZ24: =+D24+H24+L24+P24+T24+X24+AB24+AF24+AJ24+AN24+AR24+AV24 -> 5897.644 | BA24: =+AZ24-AY24 -> -576.69905 | BB24: =IF(AY24<>0,AZ24/AY24,"-") -> 0.91092547
D25: =+PL推移!D24 -> 0 | E25: =+D25-C25 -> 0 | F25: =IF(C25<>0,D25/C25,"-") -> - | I25: =+H25-G25 -> 0 | J25: =IF(G25<>0,H25/G25,"-") -> - | K25: =+K13-K19 -> 0 | L25: =+PL推移!H24 -> 0 | M25: =+L25-K25 -> 0 | N25: =IF(K25<>0,L25/K25,"-") -> - | O25: =+O13-O19 -> 0 | P25: =+PL推移!J24 -> 0 | Q25: =+P25-O25 -> 0 | R25: =IF(O25<>0,P25/O25,"-") -> - | S25: =+S13-S19 -> 0 | T25: =+T13-T19 -> 0 | U25: =+T25-S25 -> 0 | V25: =IF(S25<>0,T25/S25,"-") -> - | W25: =+W13-W19 -> 0 | X25: =+X13-X19 -> 0 | Y25: =+X25-W25 -> 0 | Z25: =IF(W25<>0,X25/W25,"-") -> - | AA25: =+AA13-AA19 -> 0 | AB25: =+AB13-AB19 -> 0 | AC25: =+AB25-AA25 -> 0 | AD25: =IF(AA25<>0,AB25/AA25,"-") -> - | AE25: =+AE13-AE19 -> 0 | AF25: =+PL推移!R24 -> 0 | AG25: =+AF25-AE25 -> 0 | AH25: =IF(AE25<>0,AF25/AE25,"-") -> - | AI25: =+AI13-AI19 -> 0 | AJ25: =+AJ13-AJ19 -> 0 | AK25: =+AJ25-AI25 -> 0 | AL25: =IF(AI25<>0,AJ25/AI25,"-") -> - | AM25: =+AM13-AM19 -> 0 | AN25: =+AN13-AN19 -> 0 | AO25: =+AN25-AM25 -> 0 | AP25: =IF(AM25<>0,AN25/AM25,"-") -> - | AQ25: =+AQ13-AQ19 -> 0 | AR25: =+AR13-AR19 -> 0 | AS25: =+AR25-AQ25 -> 0 | AT25: =IF(AQ25<>0,AR25/AQ25,"-") -> - | AU25: =+AU13-AU19 -> 0 | AV25: =+AV13-AV19 -> 0 | AW25: =+AV25-AU25 -> 0 | AX25: =IF(AU25<>0,AV25/AU25,"-") -> - | AY25: =+C25+G25+K25+O25+S25+W25+AA25+AE25+AI25+AM25+AQ25+AU25 -> 0 | AZ25: =+D25+H25+L25+P25+T25+X25+AB25+AF25+AJ25+AN25+AR25+AV25 -> 0 | BA25: =+AZ25-AY25 -> 0 | BB25: =IF(AY25<>0,AZ25/AY25,"-") -> -
D26: =+PL推移!D25 -> 0 | E26: =+D26-C26 -> 0 | F26: =IF(C26<>0,D26/C26,"-") -> - | I26: =+H26-G26 -> 0 | J26: =IF(G26<>0,H26/G26,"-") -> - | K26: =+K14-K20 -> 0 | L26: =+PL推移!H25 -> 0 | M26: =+L26-K26 -> 0 | N26: =IF(K26<>0,L26/K26,"-") -> - | O26: =+O14-O20 -> 0 | P26: =+PL推移!J25 -> 0 | Q26: =+P26-O26 -> 0 | R26: =IF(O26<>0,P26/O26,"-") -> - | S26: =+S14-S20 -> 0 | T26: =+T14-T20 -> 0 | U26: =+T26-S26 -> 0 | V26: =IF(S26<>0,T26/S26,"-") -> - | W26: =+W14-W20 -> 0 | X26: =+X14-X20 -> 0 | Y26: =+X26-W26 -> 0 | Z26: =IF(W26<>0,X26/W26,"-") -> - | AA26: =+AA14-AA20 -> 0 | AB26: =+AB14-AB20 -> 0 | AC26: =+AB26-AA26 -> 0 | AD26: =IF(AA26<>0,AB26/AA26,"-") -> - | AE26: =+AE14-AE20 -> 0 | AF26: =+PL推移!R25 -> 0 | AG26: =+AF26-AE26 -> 0 | AH26: =IF(AE26<>0,AF26/AE26,"-") -> - | AI26: =+AI14-AI20 -> 0 | AJ26: =+AJ14-AJ20 -> 0 | AK26: =+AJ26-AI26 -> 0 | AL26: =IF(AI26<>0,AJ26/AI26,"-") -> - | AM26: =+AM14-AM20 -> 0 | AN26: =+AN14-AN20 -> 0 | AO26: =+AN26-AM26 -> 0 | AP26: =IF(AM26<>0,AN26/AM26,"-") -> - | AQ26: =+AQ14-AQ20 -> 0 | AR26: =+AR14-AR20 -> 0 | AS26: =+AR26-AQ26 -> 0 | AT26: =IF(AQ26<>0,AR26/AQ26,"-") -> - | AU26: =+AU14-AU20 -> 0 | AV26: =+AV14-AV20 -> 0 | AW26: =+AV26-AU26 -> 0 | AX26: =IF(AU26<>0,AV26/AU26,"-") -> - | AY26: =+C26+G26+K26+O26+S26+W26+AA26+AE26+AI26+AM26+AQ26+AU26 -> 0 | AZ26: =+D26+H26+L26+P26+T26+X26+AB26+AF26+AJ26+AN26+AR26+AV26 -> 0 | BA26: =+AZ26-AY26 -> 0 | BB26: =IF(AY26<>0,AZ26/AY26,"-") -> -
D27: =+PL推移!D26 -> 0 | E27: =+D27-C27 -> 0 | F27: =IF(C27<>0,D27/C27,"-") -> - | I27: =+H27-G27 -> 0 | J27: =IF(G27<>0,H27/G27,"-") -> - | K27: =+K15-K21 -> 0 | L27: =+PL推移!H26 -> 0 | M27: =+L27-K27 -> 0 | N27: =IF(K27<>0,L27/K27,"-") -> - | O27: =+O15-O21 -> 0 | P27: =+PL推移!J26 -> 0 | Q27: =+P27-O27 -> 0 | R27: =IF(O27<>0,P27/O27,"-") -> - | S27: =+S15-S21 -> 0 | T27: =+T15-T21 -> 0 | U27: =+T27-S27 -> 0 | V27: =IF(S27<>0,T27/S27,"-") -> - | W27: =+W15-W21 -> 0 | X27: =+X15-X21 -> 0 | Y27: =+X27-W27 -> 0 | Z27: =IF(W27<>0,X27/W27,"-") -> - | AA27: =+AA15-AA21 -> 0 | AB27: =+AB15-AB21 -> 0 | AC27: =+AB27-AA27 -> 0 | AD27: =IF(AA27<>0,AB27/AA27,"-") -> - | AE27: =+AE15-AE21 -> 0 | AF27: =+PL推移!R26 -> 0 | AG27: =+AF27-AE27 -> 0 | AH27: =IF(AE27<>0,AF27/AE27,"-") -> - | AI27: =+AI15-AI21 -> 0 | AJ27: =+AJ15-AJ21 -> 0 | AK27: =+AJ27-AI27 -> 0 | AL27: =IF(AI27<>0,AJ27/AI27,"-") -> - | AM27: =+AM15-AM21 -> 0 | AN27: =+AN15-AN21 -> 0 | AO27: =+AN27-AM27 -> 0 | AP27: =IF(AM27<>0,AN27/AM27,"-") -> - | AQ27: =+AQ15-AQ21 -> 0 | AR27: =+AR15-AR21 -> 0 | AS27: =+AR27-AQ27 -> 0 | AT27: =IF(AQ27<>0,AR27/AQ27,"-") -> - | AU27: =+AU15-AU21 -> 0 | AV27: =+AV15-AV21 -> 0 | AW27: =+AV27-AU27 -> 0 | AX27: =IF(AU27<>0,AV27/AU27,"-") -> - | AY27: =+C27+G27+K27+O27+S27+W27+AA27+AE27+AI27+AM27+AQ27+AU27 -> 0 | AZ27: =+D27+H27+L27+P27+T27+X27+AB27+AF27+AJ27+AN27+AR27+AV27 -> 0 | BA27: =+AZ27-AY27 -> 0 | BB27: =IF(AY27<>0,AZ27/AY27,"-") -> -
D28: =+PL推移!D27 -> 0 | E28: =+D28-C28 -> 0 | F28: =IF(C28<>0,D28/C28,"-") -> - | I28: =+H28-G28 -> 0 | J28: =IF(G28<>0,H28/G28,"-") -> - | K28: =+K16-K22 -> 0 | L28: =+PL推移!H27 -> 0 | M28: =+L28-K28 -> 0 | N28: =IF(K28<>0,L28/K28,"-") -> - | O28: =+O16-O22 -> 0 | P28: =+PL推移!J27 -> 0 | Q28: =+P28-O28 -> 0 | R28: =IF(O28<>0,P28/O28,"-") -> - | S28: =+S16-S22 -> 0 | T28: =+T16-T22 -> 0 | U28: =+T28-S28 -> 0 | V28: =IF(S28<>0,T28/S28,"-") -> - | W28: =+W16-W22 -> 0 | X28: =+X16-X22 -> 0 | Y28: =+X28-W28 -> 0 | Z28: =IF(W28<>0,X28/W28,"-") -> - | AA28: =+AA16-AA22 -> 0 | AB28: =+AB16-AB22 -> 0 | AC28: =+AB28-AA28 -> 0 | AD28: =IF(AA28<>0,AB28/AA28,"-") -> - | AE28: =+AE16-AE22 -> 0 | AF28: =+PL推移!R27 -> 0 | AG28: =+AF28-AE28 -> 0 | AH28: =IF(AE28<>0,AF28/AE28,"-") -> - | AI28: =+AI16-AI22 -> 0 | AJ28: =+AJ16-AJ22 -> 0 | AK28: =+AJ28-AI28 -> 0 | AL28: =IF(AI28<>0,AJ28/AI28,"-") -> - | AM28: =+AM16-AM22 -> 0 | AN28: =+AN16-AN22 -> 0 | AO28: =+AN28-AM28 -> 0 | AP28: =IF(AM28<>0,AN28/AM28,"-") -> - | AQ28: =+AQ16-AQ22 -> 0 | AR28: =+AR16-AR22 -> 0 | AS28: =+AR28-AQ28 -> 0 | AT28: =IF(AQ28<>0,AR28/AQ28,"-") -> - | AU28: =+AU16-AU22 -> 0 | AV28: =+AV16-AV22 -> 0 | AW28: =+AV28-AU28 -> 0 | AX28: =IF(AU28<>0,AV28/AU28,"-") -> - | AY28: =+C28+G28+K28+O28+S28+W28+AA28+AE28+AI28+AM28+AQ28+AU28 -> 0 | AZ28: =+D28+H28+L28+P28+T28+X28+AB28+AF28+AJ28+AN28+AR28+AV28 -> 0 | BA28: =+AZ28-AY28 -> 0 | BB28: =IF(AY28<>0,AZ28/AY28,"-") -> -
A29: 販売管理費 | C29: =SUM(C30:C50) -> 898.203 | D29: =SUM(D30:D50) -> 898.203 | E29: =SUM(E30:E50) -> 0 | F29: =IF(C29<>0,D29/C29,"-") -> 1 | G29: =SUM(G30:G50) -> 567.923 | H29: =+PL推移!F28 -> 567.923 | I29: =SUM(I30:I50) -> 0 | J29: =IF(G29<>0,H29/G29,"-") -> 1 | K29: =SUM(K30:K50) -> 690.135 | L29: =+PL推移!H28 -> 654.4 | M29: =SUM(M30:M50) -> -35.735 | N29: =IF(K29<>0,L29/K29,"-") -> 0.94822028 | O29: =SUM(O30:O50) -> 570.135 | P29: =+PL推移!J28 -> 724.991 | Q29: =SUM(Q30:Q50) -> 154.856 | R29: =IF(O29<>0,P29/O29,"-") -> 1.2716129 | S29: =SUM(S30:S50) -> 570.135 | T29: =+PL推移!L28 -> 525.203 | U29: =SUM(U30:U50) -> -44.932 | V29: =IF(S29<>0,T29/S29,"-") -> 0.9211906 | W29: =+収支計画!L56/1000 -> 570.135 | X29: =+PL推移!P28 -> 674.115 | Y29: =SUM(Y30:Y50) -> 151.393 | Z29: =IF(W29<>0,X29/W29,"-") -> 1.1823779 | AA29: =+収支計画!M56/1000 -> 503.469 | AB29: =+PL推移!P28 -> 674.115 | AC29: =SUM(AC30:AC50) -> 197.196 | AD29: =IF(AA29<>0,AB29/AA29,"-") -> 1.3389404 | AE29: =+収支計画!N56/1000 -> 503.469 | AF29: =+PL推移!R28 -> 624.407 | AG29: =SUM(AG30:AG50) -> 197.488 | AH29: =IF(AE29<>0,AF29/AE29,"-") -> 1.2402094 | AI29: =+収支計画!O56/1000 -> 503.469 | AJ29: =+PL推移!T28 -> 654.598 | AK29: =SUM(AK30:AK50) -> 177.679 | AL29: =IF(AI29<>0,AJ29/AI29,"-") -> 1.3001754 | AM29: =+収支計画!P56/1000 -> 529.969 | AN29: =+PL推移!V28 -> 601.291 | AO29: =+AN29-AM29 -> 71.322 | AP29: =IF(AM29<>0,AN29/AM29,"-") -> 1.1345777 | AQ29: =+収支計画!Q56/1000 -> 529.969 | AR29: =+PL推移!X28 -> 676.189 | AS29: =+AR29-AQ29 -> 146.22 | AT29: =IF(AQ29<>0,AR29/AQ29,"-") -> 1.2759029 | AU29: =+収支計画!R56/1000 -> 529.919 | AV29: =+PL推移!Z28 -> 661.641 | AW29: =+AV29-AU29 -> 131.722 | AX29: =IF(AU29<>0,AV29/AU29,"-") -> 1.2485701 | AY29: =+C29+G29+K29+O29+S29+W29+AA29+AE29+AI29+AM29+AQ29+AU29 -> 6966.93 | AZ29: =+D29+H29+L29+P29+T29+X29+AB29+AF29+AJ29+AN29+AR29+AV29 -> 7937.076 | BA29: =+AZ29-AY29 -> 970.146 | BB29: =IF(AY29<>0,AZ29/AY29,"-") -> 1.1392501
B30: 人件費 | C30: =+収支計画!G34/1000 -> 535.456 | D30: =+PL推移!D29 -> 535.456 | E30: =+D30-C30 -> 0 | F30: =IF(C30<>0,D30/C30,"-") -> 1 | G30: =+収支計画!H34/1000 -> 331.819 | H30: =+PL推移!F29 -> 331.819 | I30: =+H30-G30 -> 0 | J30: =IF(G30<>0,H30/G30,"-") -> 1 | K30: =+収支計画!I34/1000 -> 331.819 | L30: =+PL推移!H29 -> 331.819 | M30: =+L30-K30 -> 0 | N30: =IF(K30<>0,L30/K30,"-") -> 1 | O30: =+収支計画!J34/1000 -> 331.819 | P30: =+PL推移!J29 -> 331.819 | Q30: =+P30-O30 -> 0 | R30: =IF(O30<>0,P30/O30,"-") -> 1 | S30: =+収支計画!K34/1000 -> 331.819 | T30: =+PL推移!L29 -> 331.819 | U30: =+T30-S30 -> 0 | V30: =IF(S30<>0,T30/S30,"-") -> 1 | W30: =+収支計画!L34/1000 -> 331.819 | X30: =+PL推移!N29 -> 331.819 | Y30: =+X30-W30 -> 0 | Z30: =IF(W30<>0,X30/W30,"-") -> 1 | AA30: =+収支計画!M34/1000 -> 331.819 | AB30: =+PL推移!P29 -> 331.819 | AC30: =+AB30-AA30 -> 0 | AD30: =IF(AA30<>0,AB30/AA30,"-") -> 1 | AE30: =+収支計画!N34/1000 -> 331.819 | AF30: =+PL推移!R29 -> 331.819 | AG30: =+AF30-AE30 -> 0 | AH30: =IF(AE30<>0,AF30/AE30,"-") -> 1 | AI30: =+収支計画!O34/1000 -> 331.819 | AJ30: =+PL推移!T29 -> 331.819 | AK30: =+AJ30-AI30 -> 0 | AL30: =IF(AI30<>0,AJ30/AI30,"-") -> 1 | AM30: =+収支計画!P34/1000 -> 331.819 | AN30: =+PL推移!V29 -> 331.819 | AO30: =+AN30-AM30 -> 0 | AP30: =IF(AM30<>0,AN30/AM30,"-") -> 1 | AQ30: =+収支計画!Q34/1000 -> 331.819 | AR30: =+PL推移!X29 -> 331.819 | AS30: =+AR30-AQ30 -> 0 | AT30: =IF(AQ30<>0,AR30/AQ30,"-") -> 1 | AU30: =+収支計画!R34/1000 -> 331.819 | AV30: =+PL推移!Z29 -> 331.819 | AW30: =+AV30-AU30 -> 0 | AX30: =IF(AU30<>0,AV30/AU30,"-") -> 1 | AY30: =+C30+G30+K30+O30+S30+W30+AA30+AE30+AI30+AM30+AQ30+AU30 -> 4185.465 | AZ30: =+D30+H30+L30+P30+T30+X30+AB30+AF30+AJ30+AN30+AR30+AV30 -> 4185.465 | BA30: =+AZ30-AY30 -> 0 | BB30: =IF(AY30<>0,AZ30/AY30,"-") -> 1
B31: 旅費交通費 | C31: =+収支計画!G35/1000 -> 9.72 | D31: =+PL推移!D30 -> 9.72 | E31: =+D31-C31 -> 0 | F31: =IF(C31<>0,D31/C31,"-") -> 1 | G31: =+収支計画!H35/1000 -> 5.371 | H31: =+PL推移!F30 -> 5.371 | I31: =+H31-G31 -> 0 | J31: =IF(G31<>0,H31/G31,"-") -> 1 | K31: =+収支計画!I35/1000 -> 50 | L31: =+PL推移!H30 -> 8.966 | M31: =+L31-K31 -> -41.034 | N31: =IF(K31<>0,L31/K31,"-") -> 0.17932 | O31: =+収支計画!J35/1000 -> 50 | P31: =+PL推移!J30 -> 74.104 | Q31: =+P31-O31 -> 24.104 | R31: =IF(O31<>0,P31/O31,"-") -> 1.48208 | S31: =+収支計画!K35/1000 -> 50 | T31: =+PL推移!L30 -> 6.693 | U31: =+T31-S31 -> -43.307 | V31: =IF(S31<>0,T31/S31,"-") -> 0.13386 | W31: =+収支計画!L35/1000 -> 50 | X31: =+PL推移!N30 -> 1.928 | Y31: =+X31-W31 -> -48.072 | Z31: =IF(W31<>0,X31/W31,"-") -> 0.03856 | AA31: =+収支計画!M35/1000 -> 50 | AB31: =+PL推移!P30 -> 101.043 | AC31: =+AB31-AA31 -> 51.043 | AD31: =IF(AA31<>0,AB31/AA31,"-") -> 2.02086 | AE31: =+収支計画!N35/1000 -> 50 | AF31: =+PL推移!R30 -> 5.547 | AG31: =+AF31-AE31 -> -44.453 | AH31: =IF(AE31<>0,AF31/AE31,"-") -> 0.11094 | AI31: =+収支計画!O35/1000 -> 50 | AJ31: =+PL推移!T30 -> 1.091 | AK31: =+AJ31-AI31 -> -48.909 | AL31: =IF(AI31<>0,AJ31/AI31,"-") -> 0.02182 | AM31: =+収支計画!P35/1000 -> 50 | AN31: =+PL推移!V30 -> 0 | AO31: =+AN31-AM31 -> -50 | AP31: =IF(AM31<>0,AN31/AM31,"-") -> 0 | AQ31: =+収支計画!Q35/1000 -> 50 | AR31: =+PL推移!X30 -> 57.464 | AS31: =+AR31-AQ31 -> 7.464 | AT31: =IF(AQ31<>0,AR31/AQ31,"-") -> 1.14928 | AU31: =+収支計画!R35/1000 -> 50 | AV31: =+PL推移!Z30 -> 24.862 | AW31: =+AV31-AU31 -> -25.138 | AX31: =IF(AU31<>0,AV31/AU31,"-") -> 0.49724 | AY31: =+C31+G31+K31+O31+S31+W31+AA31+AE31+AI31+AM31+AQ31+AU31 -> 515.091 | AZ31: =+D31+H31+L31+P31+T31+X31+AB31+AF31+AJ31+AN31+AR31+AV31 -> 296.789 | BA31: =+AZ31-AY31 -> -218.302 | BB31: =IF(AY31<>0,AZ31/AY31,"-") -> 0.57618751
B32: 通信費 | C32: =+収支計画!G36/1000 -> 1.2 | D32: =+PL推移!D31 -> 1.2 | E32: =+D32-C32 -> 0 | F32: =IF(C32<>0,D32/C32,"-") -> 1 | G32: =+収支計画!H36/1000 -> 55.56 | H32: =+PL推移!F31 -> 55.56 | I32: =+H32-G32 -> 0 | J32: =IF(G32<>0,H32/G32,"-") -> 1 | K32: =+収支計画!I36/1000 -> 0.6 | L32: =+PL推移!H31 -> 54.96 | M32: =+L32-K32 -> 54.36 | N32: =IF(K32<>0,L32/K32,"-") -> 91.6 | O32: =+収支計画!J36/1000 -> 0.6 | P32: =+PL推移!J31 -> 1.2 | Q32: =+P32-O32 -> 0.6 | R32: =IF(O32<>0,P32/O32,"-") -> 2 | S32: =+収支計画!K36/1000 -> 0.6 | T32: =+PL推移!L31 -> 1.2 | U32: =+T32-S32 -> 0.6 | V32: =IF(S32<>0,T32/S32,"-") -> 2 | W32: =+収支計画!L36/1000 -> 0.6 | X32: =+PL推移!N31 -> 78.96 | Y32: =+X32-W32 -> 78.36 | Z32: =IF(W32<>0,X32/W32,"-") -> 131.6 | AA32: =+収支計画!M36/1000 -> 0.6 | AB32: =+PL推移!P31 -> 3.837 | AC32: =+AB32-AA32 -> 3.237 | AD32: =IF(AA32<>0,AB32/AA32,"-") -> 6.395 | AE32: =+収支計画!N36/1000 -> 0.6 | AF32: =+PL推移!R31 -> 57.597 | AG32: =+AF32-AE32 -> 56.997 | AH32: =IF(AE32<>0,AF32/AE32,"-") -> 95.995 | AI32: =+収支計画!O36/1000 -> 0.6 | AJ32: =+PL推移!T31 -> 18.513 | AK32: =+AJ32-AI32 -> 17.913 | AL32: =IF(AI32<>0,AJ32/AI32,"-") -> 30.855 | AM32: =+収支計画!P36/1000 -> 0.6 | AN32: =+PL推移!V31 -> 27.326 | AO32: =+AN32-AM32 -> 26.726 | AP32: =IF(AM32<>0,AN32/AM32,"-") -> 45.543333 | AQ32: =+収支計画!Q36/1000 -> 0.6 | AR32: =+PL推移!X31 -> 71.599 | AS32: =+AR32-AQ32 -> 70.999 | AT32: =IF(AQ32<>0,AR32/AQ32,"-") -> 119.33167 | AU32: =+収支計画!R36/1000 -> 0.6 | AV32: =+PL推移!Z31 -> 62.331 | AW32: =+AV32-AU32 -> 61.731 | AX32: =IF(AU32<>0,AV32/AU32,"-") -> 103.885 | AY32: =+C32+G32+K32+O32+S32+W32+AA32+AE32+AI32+AM32+AQ32+AU32 -> 62.76 | AZ32: =+D32+H32+L32+P32+T32+X32+AB32+AF32+AJ32+AN32+AR32+AV32 -> 434.283 | BA32: =+AZ32-AY32 -> 371.523 | BB32: =IF(AY32<>0,AZ32/AY32,"-") -> 6.9197419
B33: 開発費 | C33: =+収支計画!G37/1000 -> 0 | D33: =+PL推移!D32 -> 140 | E33: =+D33-C33 -> 140 | F33: =IF(C33<>0,D33/C33,"-") -> - | G33: =+収支計画!H37/1000 -> 0 | H33: =+PL推移!F32 -> 14.004 | I33: =+H33-G33 -> 14.004 | J33: =IF(G33<>0,H33/G33,"-") -> - | K33: =+収支計画!I37/1000 -> 0 | L33: =+PL推移!H32 -> 42.383 | M33: =+L33-K33 -> 42.383 | N33: =IF(K33<>0,L33/K33,"-") -> - | O33: =+収支計画!J37/1000 -> 0 | P33: =+PL推移!J32 -> 0 | Q33: =+P33-O33 -> 0 | R33: =IF(O33<>0,P33/O33,"-") -> - | S33: =+収支計画!K37/1000 -> 0 | T33: =+PL推移!L32 -> 0 | U33: =+T33-S33 -> 0 | V33: =IF(S33<>0,T33/S33,"-") -> - | W33: =+収支計画!L37/1000 -> 0 | X33: =+PL推移!N32 -> 0 | Y33: =+X33-W33 -> 0 | Z33: =IF(W33<>0,X33/W33,"-") -> - | AA33: =+収支計画!M37/1000 -> 0 | AB33: =+PL推移!P32 -> 0 | AC33: =+AB33-AA33 -> 0 | AD33: =IF(AA33<>0,AB33/AA33,"-") -> - | AE33: =+収支計画!AA43/1000 -> 0 | AF33: =+PL推移!R32 -> 0 | AG33: =+AF33-AE33 -> 0 | AH33: =IF(AE33<>0,AF33/AE33,"-") -> - | AI33: =+収支計画!O37/1000 -> 0 | AJ33: =+PL推移!T32 -> 0 | AK33: =+AJ33-AI33 -> 0 | AL33: =IF(AI33<>0,AJ33/AI33,"-") -> - | AM33: =+収支計画!P37/1000 -> 0 | AN33: =+PL推移!V32 -> 0 | AO33: =+AN33-AM33 -> 0 | AP33: =IF(AM33<>0,AN33/AM33,"-") -> - | AQ33: =+収支計画!Q37/1000 -> 0 | AR33: =+PL推移!X32 -> 0 | AS33: =+AR33-AQ33 -> 0 | AT33: =IF(AQ33<>0,AR33/AQ33,"-") -> - | AU33: =+収支計画!R37/1000 -> 0 | AV33: =+PL推移!Z32 -> 0 | AW33: =+AV33-AU33 -> 0 | AX33: =IF(AU33<>0,AV33/AU33,"-") -> - | AY33: =+C33+G33+K33+O33+S33+W33+AA33+AE33+AI33+AM33+AQ33+AU33 -> 0 | AZ33: =+D33+H33+L33+P33+T33+X33+AB33+AF33+AJ33+AN33+AR33+AV33 -> 196.387 | BA33: =+AZ33-AY33 -> 196.387 | BB33: =IF(AY33<>0,AZ33/AY33,"-") -> -
B34: 交際費 | C34: =+収支計画!G38/1000 -> 13.438 | D34: =+PL推移!D33 -> 13.438 | E34: =+D34-C34 -> 0 | F34: =IF(C34<>0,D34/C34,"-") -> 1 | G34: =+収支計画!H38/1000 -> 50.137 | H34: =+PL推移!F33 -> 50.137 | I34: =+H34-G34 -> 0 | J34: =IF(G34<>0,H34/G34,"-") -> 1 | K34: =+収支計画!I38/1000 -> 50 | L34: =+PL推移!H33 -> 103.9 | M34: =+L34-K34 -> 53.9 | N34: =IF(K34<>0,L34/K34,"-") -> 2.078 | O34: =+収支計画!J38/1000 -> 50 | P34: =+PL推移!J33 -> 12.119 | Q34: =+P34-O34 -> -37.881 | R34: =IF(O34<>0,P34/O34,"-") -> 0.24238 | S34: =+収支計画!K38/1000 -> 50 | T34: =+PL推移!L33 -> 30 | U34: =+T34-S34 -> -20 | V34: =IF(S34<>0,T34/S34,"-") -> 0.6 | W34: =+収支計画!L38/1000 -> 50 | X34: =+PL推移!N33 -> 158.371 | Y34: =+X34-W34 -> 108.371 | Z34: =IF(W34<>0,X34/W34,"-") -> 3.16742 | AA34: =+収支計画!M38/1000 -> 50 | AB34: =+PL推移!P33 -> 87.515 | AC34: =+AB34-AA34 -> 37.515 | AD34: =IF(AA34<>0,AB34/AA34,"-") -> 1.7503 | AE34: =+収支計画!AA44/1000 -> 0 | AF34: =+PL推移!R33 -> 113.663 | AG34: =+AF34-AE34 -> 113.663 | AH34: =IF(AE34<>0,AF34/AE34,"-") -> - | AI34: =+収支計画!O38/1000 -> 50 | AJ34: =+PL推移!T33 -> 172.618 | AK34: =+AJ34-AI34 -> 122.618 | AL34: =IF(AI34<>0,AJ34/AI34,"-") -> 3.45236 | AM34: =+収支計画!P38/1000 -> 50 | AN34: =+PL推移!V33 -> 89.768 | AO34: =+AN34-AM34 -> 39.768 | AP34: =IF(AM34<>0,AN34/AM34,"-") -> 1.79536 | AQ34: =+収支計画!Q38/1000 -> 50 | AR34: =+PL推移!X33 -> 95.002 | AS34: =+AR34-AQ34 -> 45.002 | AT34: =IF(AQ34<>0,AR34/AQ34,"-") -> 1.90004 | AU34: =+収支計画!R38/1000 -> 50 | AV34: =+PL推移!Z33 -> 111.724 | AW34: =+AV34-AU34 -> 61.724 | AX34: =IF(AU34<>0,AV34/AU34,"-") -> 2.23448 | AY34: =+C34+G34+K34+O34+S34+W34+AA34+AE34+AI34+AM34+AQ34+AU34 -> 513.575 | AZ34: =+D34+H34+L34+P34+T34+X34+AB34+AF34+AJ34+AN34+AR34+AV34 -> 1038.255 | BA34: =+AZ34-AY34 -> 524.68 | BB34: =IF(AY34<>0,AZ34/AY34,"-") -> 2.0216229
B35: 会議費 | C35: =+収支計画!G39/1000 -> 0 | D35: =+PL推移!D34 -> 84.497 | E35: =+D35-C35 -> 84.497 | F35: =IF(C35<>0,D35/C35,"-") -> - | G35: =+収支計画!H39/1000 -> 0 | H35: =+PL推移!F34 -> 10.447 | I35: =+H35-G35 -> 10.447 | J35: =IF(G35<>0,H35/G35,"-") -> - | K35: =+収支計画!I39/1000 -> 0 | L35: =+PL推移!H34 -> 11.637 | M35: =+L35-K35 -> 11.637 | N35: =IF(K35<>0,L35/K35,"-") -> - | O35: =+収支計画!J39/1000 -> 0 | P35: =+PL推移!J34 -> 67.568 | Q35: =+P35-O35 -> 67.568 | R35: =IF(O35<>0,P35/O35,"-") -> - | S35: =+収支計画!K39/1000 -> 0 | T35: =+PL推移!L34 -> 49.291 | U35: =+T35-S35 -> 49.291 | V35: =IF(S35<>0,T35/S35,"-") -> - | W35: =+収支計画!L39/1000 -> 0 | X35: =+PL推移!N34 -> 22.016 | Y35: =+X35-W35 -> 22.016 | Z35: =IF(W35<>0,X35/W35,"-") -> - | AA35: =+収支計画!M39/1000 -> 0 | AB35: =+PL推移!P34 -> 45.376 | AC35: =+AB35-AA35 -> 45.376 | AD35: =IF(AA35<>0,AB35/AA35,"-") -> - | AE35: =+収支計画!AA45/1000 -> 0 | AF35: =+PL推移!R34 -> 13.067 | AG35: =+AF35-AE35 -> 13.067 | AH35: =IF(AE35<>0,AF35/AE35,"-") -> - | AI35: =+収支計画!O39/1000 -> 0 | AJ35: =+PL推移!T34 -> 27.771 | AK35: =+AJ35-AI35 -> 27.771 | AL35: =IF(AI35<>0,AJ35/AI35,"-") -> - | AM35: =+収支計画!P39/1000 -> 0 | AN35: =+PL推移!V34 -> 13.158 | AO35: =+AN35-AM35 -> 13.158 | AP35: =IF(AM35<>0,AN35/AM35,"-") -> - | AQ35: =+収支計画!Q39/1000 -> 0 | AR35: =+PL推移!X34 -> 10.469 | AS35: =+AR35-AQ35 -> 10.469 | AT35: =IF(AQ35<>0,AR35/AQ35,"-") -> - | AU35: =+収支計画!R39/1000 -> 0 | AV35: =+PL推移!Z34 -> 27.614 | AW35: =+AV35-AU35 -> 27.614 | AX35: =IF(AU35<>0,AV35/AU35,"-") -> - | AY35: =+C35+G35+K35+O35+S35+W35+AA35+AE35+AI35+AM35+AQ35+AU35 -> 0 | AZ35: =+D35+H35+L35+P35+T35+X35+AB35+AF35+AJ35+AN35+AR35+AV35 -> 382.911 | BA35: =+AZ35-AY35 -> 382.911 | BB35: =IF(AY35<>0,AZ35/AY35,"-") -> -
B36: 減価償却費 | C36: =+収支計画!G40/1000 -> 26.5 | D36: =+PL推移!D35 -> 26.5 | E36: =+D36-C36 -> 0 | F36: =IF(C36<>0,D36/C36,"-") -> 1 | G36: =+収支計画!H40/1000 -> 26.5 | H36: =+PL推移!F35 -> 26.5 | I36: =+H36-G36 -> 0 | J36: =IF(G36<>0,H36/G36,"-") -> 1 | K36: =+収支計画!I40/1000 -> 66.666 | L36: =+PL推移!H35 -> 26.5 | M36: =+L36-K36 -> -40.166 | N36: =IF(K36<>0,L36/K36,"-") -> 0.39750398 | O36: =+収支計画!J40/1000 -> 66.666 | P36: =+PL推移!J35 -> 26.5 | Q36: =+P36-O36 -> -40.166 | R36: =IF(O36<>0,P36/O36,"-") -> 0.39750398 | S36: =+収支計画!K40/1000 -> 66.666 | T36: =+PL推移!L35 -> 26.5 | U36: =+T36-S36 -> -40.166 | V36: =IF(S36<>0,T36/S36,"-") -> 0.39750398 | W36: =+収支計画!L40/1000 -> 66.666 | X36: =+PL推移!N35 -> 26.5 | Y36: =+X36-W36 -> -40.166 | Z36: =IF(W36<>0,X36/W36,"-") -> 0.39750398 | AA36: =+収支計画!M40/1000 -> 0 | AB36: =+PL推移!P35 -> 26.5 | AC36: =+AB36-AA36 -> 26.5 | AD36: =IF(AA36<>0,AB36/AA36,"-") -> - | AE36: =+収支計画!AA46/1000 -> 0 | AF36: =+PL推移!R35 -> 26.5 | AG36: =+AF36-AE36 -> 26.5 | AH36: =IF(AE36<>0,AF36/AE36,"-") -> - | AI36: =+収支計画!O40/1000 -> 0 | AJ36: =+PL推移!T35 -> 26.5 | AK36: =+AJ36-AI36 -> 26.5 | AL36: =IF(AI36<>0,AJ36/AI36,"-") -> - | AM36: =+収支計画!P40/1000 -> 26.5 | AN36: =+PL推移!V35 -> 26.5 | AO36: =+AN36-AM36 -> 0 | AP36: =IF(AM36<>0,AN36/AM36,"-") -> 1 | AQ36: =+収支計画!Q40/1000 -> 26.5 | AR36: =+PL推移!X35 -> 26.5 | AS36: =+AR36-AQ36 -> 0 | AT36: =IF(AQ36<>0,AR36/AQ36,"-") -> 1 | AU36: =+収支計画!R40/1000 -> 26.5 | AV36: =+PL推移!Z35 -> 26.5 | AW36: =+AV36-AU36 -> 0 | AX36: =IF(AU36<>0,AV36/AU36,"-") -> 1 | AY36: =+C36+G36+K36+O36+S36+W36+AA36+AE36+AI36+AM36+AQ36+AU36 -> 399.164 | AZ36: =+D36+H36+L36+P36+T36+X36+AB36+AF36+AJ36+AN36+AR36+AV36 -> 318 | BA36: =+AZ36-AY36 -> -81.164 | BB36: =IF(AY36<>0,AZ36/AY36,"-") -> 0.79666503
B37: 賃借料 | C37: =+収支計画!G41/1000 -> 0 | D37: =+PL推移!D36 -> 0 | E37: =+D37-C37 -> 0 | F37: =IF(C37<>0,D37/C37,"-") -> - | G37: =+収支計画!H41/1000 -> 0 | H37: =+PL推移!F36 -> 0 | I37: =+H37-G37 -> 0 | J37: =IF(G37<>0,H37/G37,"-") -> - | K37: =+収支計画!I41/1000 -> 0 | L37: =+PL推移!H36 -> 0 | M37: =+L37-K37 -> 0 | N37: =IF(K37<>0,L37/K37,"-") -> - | O37: =+収支計画!J41/1000 -> 0 | P37: =+PL推移!J36 -> 0 | Q37: =+P37-O37 -> 0 | R37: =IF(O37<>0,P37/O37,"-") -> - | S37: =+収支計画!K41/1000 -> 0 | T37: =+PL推移!L36 -> 0 | U37: =+T37-S37 -> 0 | V37: =IF(S37<>0,T37/S37,"-") -> - | W37: =+収支計画!L41/1000 -> 0 | X37: =+PL推移!N36 -> 0 | Y37: =+X37-W37 -> 0 | Z37: =IF(W37<>0,X37/W37,"-") -> - | AA37: =+収支計画!M41/1000 -> 0 | AB37: =+PL推移!P36 -> 0 | AC37: =+AB37-AA37 -> 0 | AD37: =IF(AA37<>0,AB37/AA37,"-") -> - | AE37: =+収支計画!AA47/1000 -> 0 | AF37: =+PL推移!R36 -> 0 | AG37: =+AF37-AE37 -> 0 | AH37: =IF(AE37<>0,AF37/AE37,"-") -> - | AI37: =+収支計画!O41/1000 -> 0 | AJ37: =+PL推移!T36 -> 0 | AK37: =+AJ37-AI37 -> 0 | AL37: =IF(AI37<>0,AJ37/AI37,"-") -> - | AM37: =+収支計画!P41/1000 -> 0 | AN37: =+PL推移!V36 -> 0 | AO37: =+AN37-AM37 -> 0 | AP37: =IF(AM37<>0,AN37/AM37,"-") -> - | AQ37: =+収支計画!Q41/1000 -> 0 | AR37: =+PL推移!X36 -> 0 | AS37: =+AR37-AQ37 -> 0 | AT37: =IF(AQ37<>0,AR37/AQ37,"-") -> - | AU37: =+収支計画!R41/1000 -> 0 | AV37: =+PL推移!Z36 -> 0 | AW37: =+AV37-AU37 -> 0 | AX37: =IF(AU37<>0,AV37/AU37,"-") -> - | AY37: =+C37+G37+K37+O37+S37+W37+AA37+AE37+AI37+AM37+AQ37+AU37 -> 0 | AZ37: =+D37+H37+L37+P37+T37+X37+AB37+AF37+AJ37+AN37+AR37+AV37 -> 0 | BA37: =+AZ37-AY37 -> 0 | BB37: =IF(AY37<>0,AZ37/AY37,"-") -> -
B38: 地代家賃 | C38: =+収支計画!G42/1000 -> 44.5 | D38: =+PL推移!D37 -> 44.5 | E38: =+D38-C38 -> 0 | F38: =IF(C38<>0,D38/C38,"-") -> 1 | G38: =+収支計画!H42/1000 -> 44.5 | H38: =+PL推移!F37 -> 44.5 | I38: =+H38-G38 -> 0 | J38: =IF(G38<>0,H38/G38,"-") -> 1 | K38: =+収支計画!I42/1000 -> 44.5 | L38: =+PL推移!H37 -> 44.5 | M38: =+L38-K38 -> 0 | N38: =IF(K38<>0,L38/K38,"-") -> 1 | O38: =+収支計画!J42/1000 -> 44.5 | P38: =+PL推移!J37 -> 44.5 | Q38: =+P38-O38 -> 0 | R38: =IF(O38<>0,P38/O38,"-") -> 1 | S38: =+収支計画!K42/1000 -> 44.5 | T38: =+PL推移!L37 -> 44.5 | U38: =+T38-S38 -> 0 | V38: =IF(S38<>0,T38/S38,"-") -> 1 | W38: =+収支計画!L42/1000 -> 44.5 | X38: =+PL推移!N37 -> 44.5 | Y38: =+X38-W38 -> 0 | Z38: =IF(W38<>0,X38/W38,"-") -> 1 | AA38: =+収支計画!M42/1000 -> 44.5 | AB38: =+PL推移!P37 -> 44.5 | AC38: =+AB38-AA38 -> 0 | AD38: =IF(AA38<>0,AB38/AA38,"-") -> 1 | AE38: =+収支計画!N42/1000 -> 44.5 | AF38: =+PL推移!R37 -> 44.5 | AG38: =+AF38-AE38 -> 0 | AH38: =IF(AE38<>0,AF38/AE38,"-") -> 1 | AI38: =+収支計画!O42/1000 -> 44.5 | AJ38: =+PL推移!T37 -> 44.5 | AK38: =+AJ38-AI38 -> 0 | AL38: =IF(AI38<>0,AJ38/AI38,"-") -> 1 | AM38: =+収支計画!P42/1000 -> 44.5 | AN38: =+PL推移!V37 -> 44.5 | AO38: =+AN38-AM38 -> 0 | AP38: =IF(AM38<>0,AN38/AM38,"-") -> 1 | AQ38: =+収支計画!Q42/1000 -> 44.5 | AR38: =+PL推移!X37 -> 44.5 | AS38: =+AR38-AQ38 -> 0 | AT38: =IF(AQ38<>0,AR38/AQ38,"-") -> 1 | AU38: =+収支計画!R42/1000 -> 44.5 | AV38: =+PL推移!Z37 -> 44.5 | AW38: =+AV38-AU38 -> 0 | AX38: =IF(AU38<>0,AV38/AU38,"-") -> 1 | AY38: =+C38+G38+K38+O38+S38+W38+AA38+AE38+AI38+AM38+AQ38+AU38 -> 534 | AZ38: =+D38+H38+L38+P38+T38+X38+AB38+AF38+AJ38+AN38+AR38+AV38 -> 534 | BA38: =+AZ38-AY38 -> 0 | BB38: =IF(AY38<>0,AZ38/AY38,"-") -> 1
B39: リース料 | C39: =+収支計画!G43/1000 -> 0 | D39: =+PL推移!D38 -> 0 | E39: =+D39-C39 -> 0 | F39: =IF(C39<>0,D39/C39,"-") -> - | G39: =+収支計画!H43/1000 -> 0 | H39: =+PL推移!F38 -> 0 | I39: =+H39-G39 -> 0 | J39: =IF(G39<>0,H39/G39,"-") -> - | K39: =+収支計画!I43/1000 -> 0 | L39: =+PL推移!H38 -> 0 | M39: =+L39-K39 -> 0 | N39: =IF(K39<>0,L39/K39,"-") -> - | O39: =+収支計画!J43/1000 -> 0 | P39: =+PL推移!J38 -> 0 | Q39: =+P39-O39 -> 0 | R39: =IF(O39<>0,P39/O39,"-") -> - | S39: =+収支計画!K43/1000 -> 0 | T39: =+PL推移!L38 -> 0 | U39: =+T39-S39 -> 0 | V39: =IF(S39<>0,T39/S39,"-") -> - | W39: =+収支計画!L43/1000 -> 0 | X39: =+PL推移!N38 -> 0 | Y39: =+X39-W39 -> 0 | Z39: =IF(W39<>0,X39/W39,"-") -> - | AA39: =+収支計画!M43/1000 -> 0 | AB39: =+PL推移!P38 -> 0 | AC39: =+AB39-AA39 -> 0 | AD39: =IF(AA39<>0,AB39/AA39,"-") -> - | AE39: =+収支計画!AA49/1000 -> 0 | AF39: =+PL推移!R38 -> 0 | AG39: =+AF39-AE39 -> 0 | AH39: =IF(AE39<>0,AF39/AE39,"-") -> - | AI39: =+収支計画!O43/1000 -> 0 | AJ39: =+PL推移!T38 -> 0 | AK39: =+AJ39-AI39 -> 0 | AL39: =IF(AI39<>0,AJ39/AI39,"-") -> - | AM39: =+収支計画!P43/1000 -> 0 | AN39: =+PL推移!V38 -> 0 | AO39: =+AN39-AM39 -> 0 | AP39: =IF(AM39<>0,AN39/AM39,"-") -> - | AQ39: =+収支計画!Q43/1000 -> 0 | AR39: =+PL推移!X38 -> 0 | AS39: =+AR39-AQ39 -> 0 | AT39: =IF(AQ39<>0,AR39/AQ39,"-") -> - | AU39: =+収支計画!R43/1000 -> 0 | AV39: =+PL推移!Z38 -> 0 | AW39: =+AV39-AU39 -> 0 | AX39: =IF(AU39<>0,AV39/AU39,"-") -> - | AY39: =+C39+G39+K39+O39+S39+W39+AA39+AE39+AI39+AM39+AQ39+AU39 -> 0 | AZ39: =+D39+H39+L39+P39+T39+X39+AB39+AF39+AJ39+AN39+AR39+AV39 -> 0 | BA39: =+AZ39-AY39 -> 0 | BB39: =IF(AY39<>0,AZ39/AY39,"-") -> -
B40: 修繕費 | C40: =+収支計画!G44/1000 -> 0 | D40: =+PL推移!D39 -> 0 | E40: =+D40-C40 -> 0 | F40: =IF(C40<>0,D40/C40,"-") -> - | G40: =+収支計画!H44/1000 -> 0 | H40: =+PL推移!F39 -> 0 | I40: =+H40-G40 -> 0 | J40: =IF(G40<>0,H40/G40,"-") -> - | K40: =+収支計画!I44/1000 -> 0 | L40: =+PL推移!H39 -> 0 | M40: =+L40-K40 -> 0 | N40: =IF(K40<>0,L40/K40,"-") -> - | O40: =+収支計画!J44/1000 -> 0 | P40: =+PL推移!J39 -> 0 | Q40: =+P40-O40 -> 0 | R40: =IF(O40<>0,P40/O40,"-") -> - | S40: =+収支計画!K44/1000 -> 0 | T40: =+PL推移!L39 -> 0 | U40: =+T40-S40 -> 0 | V40: =IF(S40<>0,T40/S40,"-") -> - | W40: =+収支計画!L44/1000 -> 0 | X40: =+PL推移!N39 -> 0 | Y40: =+X40-W40 -> 0 | Z40: =IF(W40<>0,X40/W40,"-") -> - | AA40: =+収支計画!M44/1000 -> 0 | AB40: =+PL推移!P39 -> 0 | AC40: =+AB40-AA40 -> 0 | AD40: =IF(AA40<>0,AB40/AA40,"-") -> - | AE40: =+収支計画!AA50/1000 -> 0 | AF40: =+PL推移!R39 -> 0 | AG40: =+AF40-AE40 -> 0 | AH40: =IF(AE40<>0,AF40/AE40,"-") -> - | AI40: =+収支計画!O44/1000 -> 0 | AJ40: =+PL推移!T39 -> 0 | AK40: =+AJ40-AI40 -> 0 | AL40: =IF(AI40<>0,AJ40/AI40,"-") -> - | AM40: =+収支計画!P44/1000 -> 0 | AN40: =+PL推移!V39 -> 0 | AO40: =+AN40-AM40 -> 0 | AP40: =IF(AM40<>0,AN40/AM40,"-") -> - | AQ40: =+収支計画!Q44/1000 -> 0 | AR40: =+PL推移!X39 -> 0 | AS40: =+AR40-AQ40 -> 0 | AT40: =IF(AQ40<>0,AR40/AQ40,"-") -> - | AU40: =+収支計画!R44/1000 -> 0 | AV40: =+PL推移!Z39 -> 0 | AW40: =+AV40-AU40 -> 0 | AX40: =IF(AU40<>0,AV40/AU40,"-") -> - | AY40: =+C40+G40+K40+O40+S40+W40+AA40+AE40+AI40+AM40+AQ40+AU40 -> 0 | AZ40: =+D40+H40+L40+P40+T40+X40+AB40+AF40+AJ40+AN40+AR40+AV40 -> 0 | BA40: =+AZ40-AY40 -> 0 | BB40: =IF(AY40<>0,AZ40/AY40,"-") -> -
B41: 保険料 | C41: =+収支計画!G45/1000 -> 0 | D41: =+PL推移!D40 -> 5 | E41: =+D41-C41 -> 5 | F41: =IF(C41<>0,D41/C41,"-") -> - | G41: =+収支計画!H45/1000 -> 0 | H41: =+PL推移!F40 -> 5 | I41: =+H41-G41 -> 5 | J41: =IF(G41<>0,H41/G41,"-") -> - | K41: =+収支計画!I45/1000 -> 0 | L41: =+PL推移!H40 -> 5 | M41: =+L41-K41 -> 5 | N41: =IF(K41<>0,L41/K41,"-") -> - | O41: =+収支計画!J45/1000 -> 0 | P41: =+PL推移!J40 -> 5 | Q41: =+P41-O41 -> 5 | R41: =IF(O41<>0,P41/O41,"-") -> - | S41: =+収支計画!K45/1000 -> 0 | T41: =+PL推移!L40 -> 5 | U41: =+T41-S41 -> 5 | V41: =IF(S41<>0,T41/S41,"-") -> - | W41: =+収支計画!L45/1000 -> 0 | X41: =+PL推移!N40 -> 5 | Y41: =+X41-W41 -> 5 | Z41: =IF(W41<>0,X41/W41,"-") -> - | AA41: =+収支計画!M45/1000 -> 0 | AB41: =+PL推移!P40 -> 5 | AC41: =+AB41-AA41 -> 5 | AD41: =IF(AA41<>0,AB41/AA41,"-") -> - | AE41: =+収支計画!AA51/1000 -> 0 | AF41: =+PL推移!R40 -> 5 | AG41: =+AF41-AE41 -> 5 | AH41: =IF(AE41<>0,AF41/AE41,"-") -> - | AI41: =+収支計画!O45/1000 -> 0 | AJ41: =+PL推移!T40 -> 5 | AK41: =+AJ41-AI41 -> 5 | AL41: =IF(AI41<>0,AJ41/AI41,"-") -> - | AM41: =+収支計画!P45/1000 -> 0 | AN41: =+PL推移!V40 -> 5 | AO41: =+AN41-AM41 -> 5 | AP41: =IF(AM41<>0,AN41/AM41,"-") -> - | AQ41: =+収支計画!Q45/1000 -> 0 | AR41: =+PL推移!X40 -> 5 | AS41: =+AR41-AQ41 -> 5 | AT41: =IF(AQ41<>0,AR41/AQ41,"-") -> - | AU41: =+収支計画!R45/1000 -> 0 | AV41: =+PL推移!Z40 -> 5 | AW41: =+AV41-AU41 -> 5 | AX41: =IF(AU41<>0,AV41/AU41,"-") -> - | AY41: =+C41+G41+K41+O41+S41+W41+AA41+AE41+AI41+AM41+AQ41+AU41 -> 0 | AZ41: =+D41+H41+L41+P41+T41+X41+AB41+AF41+AJ41+AN41+AR41+AV41 -> 60 | BA41: =+AZ41-AY41 -> 60 | BB41: =IF(AY41<>0,AZ41/AY41,"-") -> -
B42: 水道光熱費 | C42: =+収支計画!G46/1000 -> 0 | D42: =+PL推移!D41 -> 0 | E42: =+D42-C42 -> 0 | F42: =IF(C42<>0,D42/C42,"-") -> - | G42: =+収支計画!H46/1000 -> 0 | H42: =+PL推移!F41 -> 0 | I42: =+H42-G42 -> 0 | J42: =IF(G42<>0,H42/G42,"-") -> - | K42: =+収支計画!I46/1000 -> 0 | L42: =+PL推移!H41 -> 0 | M42: =+L42-K42 -> 0 | N42: =IF(K42<>0,L42/K42,"-") -> - | O42: =+収支計画!J46/1000 -> 0 | P42: =+PL推移!J41 -> 0 | Q42: =+P42-O42 -> 0 | R42: =IF(O42<>0,P42/O42,"-") -> - | S42: =+収支計画!K46/1000 -> 0 | T42: =+PL推移!L41 -> 0 | U42: =+T42-S42 -> 0 | V42: =IF(S42<>0,T42/S42,"-") -> - | W42: =+収支計画!L46/1000 -> 0 | X42: =+PL推移!N41 -> 0 | Y42: =+X42-W42 -> 0 | Z42: =IF(W42<>0,X42/W42,"-") -> - | AA42: =+収支計画!M46/1000 -> 0 | AB42: =+PL推移!P41 -> 0 | AC42: =+AB42-AA42 -> 0 | AD42: =IF(AA42<>0,AB42/AA42,"-") -> - | AE42: =+収支計画!AA52/1000 -> 0 | AF42: =+PL推移!R41 -> 0 | AG42: =+AF42-AE42 -> 0 | AH42: =IF(AE42<>0,AF42/AE42,"-") -> - | AI42: =+収支計画!O46/1000 -> 0 | AJ42: =+PL推移!T41 -> 0 | AK42: =+AJ42-AI42 -> 0 | AL42: =IF(AI42<>0,AJ42/AI42,"-") -> - | AM42: =+収支計画!P46/1000 -> 0 | AN42: =+PL推移!V41 -> 0 | AO42: =+AN42-AM42 -> 0 | AP42: =IF(AM42<>0,AN42/AM42,"-") -> - | AQ42: =+収支計画!Q46/1000 -> 0 | AR42: =+PL推移!X41 -> 0 | AS42: =+AR42-AQ42 -> 0 | AT42: =IF(AQ42<>0,AR42/AQ42,"-") -> - | AU42: =+収支計画!R46/1000 -> 0 | AV42: =+PL推移!Z41 -> 0 | AW42: =+AV42-AU42 -> 0 | AX42: =IF(AU42<>0,AV42/AU42,"-") -> - | AY42: =+C42+G42+K42+O42+S42+W42+AA42+AE42+AI42+AM42+AQ42+AU42 -> 0 | AZ42: =+D42+H42+L42+P42+T42+X42+AB42+AF42+AJ42+AN42+AR42+AV42 -> 0 | BA42: =+AZ42-AY42 -> 0 | BB42: =IF(AY42<>0,AZ42/AY42,"-") -> -
B43: 消耗品費 | C43: =+収支計画!G47/1000 -> 4.797 | D43: =+PL推移!D42 -> 4.797 | E43: =+D43-C43 -> 0 | F43: =IF(C43<>0,D43/C43,"-") -> 1 | G43: =+収支計画!H47/1000 -> 0 | H43: =+PL推移!F42 -> 0 | I43: =+H43-G43 -> 0 | J43: =IF(G43<>0,H43/G43,"-") -> - | K43: =+収支計画!I47/1000 -> 0 | L43: =+PL推移!H42 -> 0 | M43: =+L43-K43 -> 0 | N43: =IF(K43<>0,L43/K43,"-") -> - | O43: =+収支計画!J47/1000 -> 0 | P43: =+PL推移!J42 -> 0 | Q43: =+P43-O43 -> 0 | R43: =IF(O43<>0,P43/O43,"-") -> - | S43: =+収支計画!K47/1000 -> 0 | T43: =+PL推移!L42 -> 0 | U43: =+T43-S43 -> 0 | V43: =IF(S43<>0,T43/S43,"-") -> - | W43: =+収支計画!L47/1000 -> 0 | X43: =+PL推移!N42 -> 0 | Y43: =+X43-W43 -> 0 | Z43: =IF(W43<>0,X43/W43,"-") -> - | AA43: =+収支計画!M47/1000 -> 0 | AB43: =+PL推移!P42 -> 0 | AC43: =+AB43-AA43 -> 0 | AD43: =IF(AA43<>0,AB43/AA43,"-") -> - | AE43: =+収支計画!AA53/1000 -> 0 | AF43: =+PL推移!R42 -> 0 | AG43: =+AF43-AE43 -> 0 | AH43: =IF(AE43<>0,AF43/AE43,"-") -> - | AI43: =+収支計画!O47/1000 -> 0 | AJ43: =+PL推移!T42 -> 0 | AK43: =+AJ43-AI43 -> 0 | AL43: =IF(AI43<>0,AJ43/AI43,"-") -> - | AM43: =+収支計画!P47/1000 -> 0 | AN43: =+PL推移!V42 -> 39.584 | AO43: =+AN43-AM43 -> 39.584 | AP43: =IF(AM43<>0,AN43/AM43,"-") -> - | AQ43: =+収支計画!Q47/1000 -> 0 | AR43: =+PL推移!X42 -> 10.2 | AS43: =+AR43-AQ43 -> 10.2 | AT43: =IF(AQ43<>0,AR43/AQ43,"-") -> - | AU43: =+収支計画!R47/1000 -> 0 | AV43: =+PL推移!Z42 -> 0 | AW43: =+AV43-AU43 -> 0 | AX43: =IF(AU43<>0,AV43/AU43,"-") -> - | AY43: =+C43+G43+K43+O43+S43+W43+AA43+AE43+AI43+AM43+AQ43+AU43 -> 4.797 | AZ43: =+D43+H43+L43+P43+T43+X43+AB43+AF43+AJ43+AN43+AR43+AV43 -> 54.581 | BA43: =+AZ43-AY43 -> 49.784 | BB43: =IF(AY43<>0,AZ43/AY43,"-") -> 11.378153
B44: 租税公課 | C44: =+収支計画!G48/1000 -> 0 | D44: =+PL推移!D43 -> 0 | E44: =+D44-C44 -> 0 | F44: =IF(C44<>0,D44/C44,"-") -> - | G44: =+収支計画!H48/1000 -> 0 | H44: =+PL推移!F43 -> 0 | I44: =+H44-G44 -> 0 | J44: =IF(G44<>0,H44/G44,"-") -> - | K44: =+収支計画!I48/1000 -> 0 | L44: =+PL推移!H43 -> 0 | M44: =+L44-K44 -> 0 | N44: =IF(K44<>0,L44/K44,"-") -> - | O44: =+収支計画!J48/1000 -> 0 | P44: =+PL推移!J43 -> 0 | Q44: =+P44-O44 -> 0 | R44: =IF(O44<>0,P44/O44,"-") -> - | S44: =+収支計画!K48/1000 -> 0 | T44: =+PL推移!L43 -> 1.2 | U44: =+T44-S44 -> 1.2 | V44: =IF(S44<>0,T44/S44,"-") -> - | W44: =+収支計画!L48/1000 -> 0 | X44: =+PL推移!N43 -> 0 | Y44: =+X44-W44 -> 0 | Z44: =IF(W44<>0,X44/W44,"-") -> - | AA44: =+収支計画!M48/1000 -> 0 | AB44: =+PL推移!P43 -> 0.6 | AC44: =+AB44-AA44 -> 0.6 | AD44: =IF(AA44<>0,AB44/AA44,"-") -> - | AE44: =+収支計画!AA54/1000 -> 0 | AF44: =+PL推移!R43 -> 0 | AG44: =+AF44-AE44 -> 0 | AH44: =IF(AE44<>0,AF44/AE44,"-") -> - | AI44: =+収支計画!O48/1000 -> 0 | AJ44: =+PL推移!T43 -> 0 | AK44: =+AJ44-AI44 -> 0 | AL44: =IF(AI44<>0,AJ44/AI44,"-") -> - | AM44: =+収支計画!P48/1000 -> 0 | AN44: =+PL推移!V43 -> 0 | AO44: =+AN44-AM44 -> 0 | AP44: =IF(AM44<>0,AN44/AM44,"-") -> - | AQ44: =+収支計画!Q48/1000 -> 0 | AR44: =+PL推移!X43 -> 0 | AS44: =+AR44-AQ44 -> 0 | AT44: =IF(AQ44<>0,AR44/AQ44,"-") -> - | AU44: =+収支計画!R48/1000 -> 0 | AV44: =+PL推移!Z43 -> 0 | AW44: =+AV44-AU44 -> 0 | AX44: =IF(AU44<>0,AV44/AU44,"-") -> - | AY44: =+C44+G44+K44+O44+S44+W44+AA44+AE44+AI44+AM44+AQ44+AU44 -> 0 | AZ44: =+D44+H44+L44+P44+T44+X44+AB44+AF44+AJ44+AN44+AR44+AV44 -> 1.8 | BA44: =+AZ44-AY44 -> 1.8 | BB44: =IF(AY44<>0,AZ44/AY44,"-") -> -
B45: 広告宣伝費 | C45: =+収支計画!G49/1000 -> 0 | D45: =+PL推移!D44 -> 0 | E45: =+D45-C45 -> 0 | F45: =IF(C45<>0,D45/C45,"-") -> - | G45: =+収支計画!H49/1000 -> 0 | H45: =+PL推移!F44 -> 0 | I45: =+H45-G45 -> 0 | J45: =IF(G45<>0,H45/G45,"-") -> - | K45: =+収支計画!I49/1000 -> 0 | L45: =+PL推移!H44 -> 0 | M45: =+L45-K45 -> 0 | N45: =IF(K45<>0,L45/K45,"-") -> - | O45: =+収支計画!J49/1000 -> 0 | P45: =+PL推移!J44 -> 0 | Q45: =+P45-O45 -> 0 | R45: =IF(O45<>0,P45/O45,"-") -> - | S45: =+収支計画!K49/1000 -> 0 | T45: =+PL推移!L44 -> 0 | U45: =+T45-S45 -> 0 | V45: =IF(S45<>0,T45/S45,"-") -> - | W45: =+収支計画!L49/1000 -> 0 | X45: =+PL推移!N44 -> 0 | Y45: =+X45-W45 -> 0 | Z45: =IF(W45<>0,X45/W45,"-") -> - | AA45: =+収支計画!M49/1000 -> 0 | AB45: =+PL推移!P44 -> 0 | AC45: =+AB45-AA45 -> 0 | AD45: =IF(AA45<>0,AB45/AA45,"-") -> - | AE45: =+収支計画!AA55/1000 -> 0 | AF45: =+PL推移!R44 -> 0 | AG45: =+AF45-AE45 -> 0 | AH45: =IF(AE45<>0,AF45/AE45,"-") -> - | AI45: =+収支計画!O49/1000 -> 0 | AJ45: =+PL推移!T44 -> 0 | AK45: =+AJ45-AI45 -> 0 | AL45: =IF(AI45<>0,AJ45/AI45,"-") -> - | AM45: =+収支計画!P49/1000 -> 0 | AN45: =+PL推移!V44 -> 0 | AO45: =+AN45-AM45 -> 0 | AP45: =IF(AM45<>0,AN45/AM45,"-") -> - | AQ45: =+収支計画!Q49/1000 -> 0 | AR45: =+PL推移!X44 -> 0 | AS45: =+AR45-AQ45 -> 0 | AT45: =IF(AQ45<>0,AR45/AQ45,"-") -> - | AU45: =+収支計画!R49/1000 -> 0 | AV45: =+PL推移!Z44 -> 0 | AW45: =+AV45-AU45 -> 0 | AX45: =IF(AU45<>0,AV45/AU45,"-") -> - | AY45: =+C45+G45+K45+O45+S45+W45+AA45+AE45+AI45+AM45+AQ45+AU45 -> 0 | AZ45: =+D45+H45+L45+P45+T45+X45+AB45+AF45+AJ45+AN45+AR45+AV45 -> 0 | BA45: =+AZ45-AY45 -> 0 | BB45: =IF(AY45<>0,AZ45/AY45,"-") -> -
B46: 支払手数料 | C46: =+収支計画!G50/1000 -> 12.455 | D46: =+PL推移!D45 -> 12.455 | E46: =+D46-C46 -> 0 | F46: =IF(C46<>0,D46/C46,"-") -> 1 | G46: =+収支計画!H50/1000 -> 1.955 | H46: =+PL推移!F45 -> 1.955 | I46: =+H46-G46 -> 0 | J46: =IF(G46<>0,H46/G46,"-") -> 1 | K46: =+収支計画!I50/1000 -> 0 | L46: =+PL推移!H45 -> 2.105 | M46: =+L46-K46 -> 2.105 | N46: =IF(K46<>0,L46/K46,"-") -> - | O46: =+収支計画!J50/1000 -> 0 | P46: =+PL推移!J45 -> 2.255 | Q46: =+P46-O46 -> 2.255 | R46: =IF(O46<>0,P46/O46,"-") -> - | S46: =+収支計画!K50/1000 -> 0 | T46: =+PL推移!L45 -> 7.469 | U46: =+T46-S46 -> 7.469 | V46: =IF(S46<>0,T46/S46,"-") -> - | W46: =+収支計画!L50/1000 -> 0 | X46: =+PL推移!N45 -> 4.353 | Y46: =+X46-W46 -> 4.353 | Z46: =IF(W46<>0,X46/W46,"-") -> - | AA46: =+収支計画!M50/1000 -> 0 | AB46: =+PL推移!P45 -> 4.694 | AC46: =+AB46-AA46 -> 4.694 | AD46: =IF(AA46<>0,AB46/AA46,"-") -> - | AE46: =+収支計画!AA56/1000 -> 0 | AF46: =+PL推移!R45 -> 2.155 | AG46: =+AF46-AE46 -> 2.155 | AH46: =IF(AE46<>0,AF46/AE46,"-") -> - | AI46: =+収支計画!O50/1000 -> 0 | AJ46: =+PL推移!T45 -> 2.255 | AK46: =+AJ46-AI46 -> 2.255 | AL46: =IF(AI46<>0,AJ46/AI46,"-") -> - | AM46: =+収支計画!P50/1000 -> 0 | AN46: =+PL推移!V45 -> 2.105 | AO46: =+AN46-AM46 -> 2.105 | AP46: =IF(AM46<>0,AN46/AM46,"-") -> - | AQ46: =+収支計画!Q50/1000 -> 0 | AR46: =+PL推移!X45 -> 2.105 | AS46: =+AR46-AQ46 -> 2.105 | AT46: =IF(AQ46<>0,AR46/AQ46,"-") -> - | AU46: =+収支計画!R50/1000 -> 0 | AV46: =+PL推移!Z45 -> 2.105 | AW46: =+AV46-AU46 -> 2.105 | AX46: =IF(AU46<>0,AV46/AU46,"-") -> - | AY46: =+C46+G46+K46+O46+S46+W46+AA46+AE46+AI46+AM46+AQ46+AU46 -> 14.41 | AZ46: =+D46+H46+L46+P46+T46+X46+AB46+AF46+AJ46+AN46+AR46+AV46 -> 46.011 | BA46: =+AZ46-AY46 -> 31.601 | BB46: =IF(AY46<>0,AZ46/AY46,"-") -> 3.192991
B47: 新聞図書費 | C47: =+収支計画!G51/1000 -> 0 | D47: =+PL推移!D46 -> 0 | E47: =+D47-C47 -> 0 | F47: =IF(C47<>0,D47/C47,"-") -> - | G47: =+収支計画!H51/1000 -> 0 | H47: =+PL推移!F46 -> 1.99 | I47: =+H47-G47 -> 1.99 | J47: =IF(G47<>0,H47/G47,"-") -> - | K47: =+収支計画!I51/1000 -> 0 | L47: =+PL推移!H46 -> 1.99 | M47: =+L47-K47 -> 1.99 | N47: =IF(K47<>0,L47/K47,"-") -> - | O47: =+収支計画!J51/1000 -> 0 | P47: =+PL推移!J46 -> 0.891 | Q47: =+P47-O47 -> 0.891 | R47: =IF(O47<>0,P47/O47,"-") -> - | S47: =+収支計画!K51/1000 -> 0 | T47: =+PL推移!L46 -> 0.891 | U47: =+T47-S47 -> 0.891 | V47: =IF(S47<>0,T47/S47,"-") -> - | W47: =+収支計画!L51/1000 -> 0 | X47: =+PL推移!N46 -> 0.891 | Y47: =+X47-W47 -> 0.891 | Z47: =IF(W47<>0,X47/W47,"-") -> - | AA47: =+収支計画!M51/1000 -> 0 | AB47: =+PL推移!P46 -> 0.891 | AC47: =+AB47-AA47 -> 0.891 | AD47: =IF(AA47<>0,AB47/AA47,"-") -> - | AE47: =+収支計画!AA57/1000 -> 0 | AF47: =+PL推移!R46 -> 3.919 | AG47: =+AF47-AE47 -> 3.919 | AH47: =IF(AE47<>0,AF47/AE47,"-") -> - | AI47: =+収支計画!O51/1000 -> 0 | AJ47: =+PL推移!T46 -> 0.891 | AK47: =+AJ47-AI47 -> 0.891 | AL47: =IF(AI47<>0,AJ47/AI47,"-") -> - | AM47: =+収支計画!P51/1000 -> 0 | AN47: =+PL推移!V46 -> 0.891 | AO47: =+AN47-AM47 -> 0.891 | AP47: =IF(AM47<>0,AN47/AM47,"-") -> - | AQ47: =+収支計画!Q51/1000 -> 0 | AR47: =+PL推移!X46 -> 0.891 | AS47: =+AR47-AQ47 -> 0.891 | AT47: =IF(AQ47<>0,AR47/AQ47,"-") -> - | AU47: =+収支計画!R51/1000 -> 0 | AV47: =+PL推移!Z46 -> 0 | AW47: =+AV47-AU47 -> 0 | AX47: =IF(AU47<>0,AV47/AU47,"-") -> - | AY47: =+C47+G47+K47+O47+S47+W47+AA47+AE47+AI47+AM47+AQ47+AU47 -> 0 | AZ47: =+D47+H47+L47+P47+T47+X47+AB47+AF47+AJ47+AN47+AR47+AV47 -> 14.136 | BA47: =+AZ47-AY47 -> 14.136 | BB47: =IF(AY47<>0,AZ47/AY47,"-") -> -
B48: 管理諸費 | C48: =+収支計画!G52/1000 -> 0 | D48: =+PL推移!D47 -> 20 | E48: =+D48-C48 -> 20 | F48: =IF(C48<>0,D48/C48,"-") -> - | G48: =+収支計画!H52/1000 -> 0 | H48: =+PL推移!F47 -> 20 | I48: =+H48-G48 -> 20 | J48: =IF(G48<>0,H48/G48,"-") -> - | K48: =+収支計画!I52/1000 -> 0 | L48: =+PL推移!H47 -> 20 | M48: =+L48-K48 -> 20 | N48: =IF(K48<>0,L48/K48,"-") -> - | O48: =+収支計画!J52/1000 -> 0 | P48: =+PL推移!J47 -> 140 | Q48: =+P48-O48 -> 140 | R48: =IF(O48<>0,P48/O48,"-") -> - | S48: =+収支計画!K52/1000 -> 0 | T48: =+PL推移!L47 -> 20 | U48: =+T48-S48 -> 20 | V48: =IF(S48<>0,T48/S48,"-") -> - | W48: =+収支計画!L52/1000 -> 0 | X48: =+PL推移!N47 -> 20 | Y48: =+X48-W48 -> 20 | Z48: =IF(W48<>0,X48/W48,"-") -> - | AA48: =+収支計画!M52/1000 -> 0 | AB48: =+PL推移!P47 -> 20 | AC48: =+AB48-AA48 -> 20 | AD48: =IF(AA48<>0,AB48/AA48,"-") -> - | AE48: =+収支計画!AA58/1000 -> 0 | AF48: =+PL推移!R47 -> 20 | AG48: =+AF48-AE48 -> 20 | AH48: =IF(AE48<>0,AF48/AE48,"-") -> - | AI48: =+収支計画!O52/1000 -> 0 | AJ48: =+PL推移!T47 -> 20 | AK48: =+AJ48-AI48 -> 20 | AL48: =IF(AI48<>0,AJ48/AI48,"-") -> - | AM48: =+収支計画!P52/1000 -> 0 | AN48: =+PL推移!V47 -> 20 | AO48: =+AN48-AM48 -> 20 | AP48: =IF(AM48<>0,AN48/AM48,"-") -> - | AQ48: =+収支計画!Q52/1000 -> 0 | AR48: =+PL推移!X47 -> 20 | AS48: =+AR48-AQ48 -> 20 | AT48: =IF(AQ48<>0,AR48/AQ48,"-") -> - | AU48: =+収支計画!R52/1000 -> 0 | AV48: =+PL推移!Z47 -> 20 | AW48: =+AV48-AU48 -> 20 | AX48: =IF(AU48<>0,AV48/AU48,"-") -> - | AY48: =+C48+G48+K48+O48+S48+W48+AA48+AE48+AI48+AM48+AQ48+AU48 -> 0 | AZ48: =+D48+H48+L48+P48+T48+X48+AB48+AF48+AJ48+AN48+AR48+AV48 -> 360 | BA48: =+AZ48-AY48 -> 360 | BB48: =IF(AY48<>0,AZ48/AY48,"-") -> -
B49: 雑費 | C49: =+収支計画!G53/1000 -> 0 | D49: =+PL推移!D48 -> 0.64 | E49: =+D49-C49 -> 0.64 | F49: =IF(C49<>0,D49/C49,"-") -> - | G49: =+収支計画!H53/1000 -> 0 | H49: =+PL推移!F48 -> 0.64 | I49: =+H49-G49 -> 0.64 | J49: =IF(G49<>0,H49/G49,"-") -> - | K49: =+収支計画!I53/1000 -> 0 | L49: =+PL推移!H48 -> 0.64 | M49: =+L49-K49 -> 0.64 | N49: =IF(K49<>0,L49/K49,"-") -> - | O49: =+収支計画!J53/1000 -> 0 | P49: =+PL推移!J48 -> 19.035 | Q49: =+P49-O49 -> 19.035 | R49: =IF(O49<>0,P49/O49,"-") -> - | S49: =+収支計画!K53/1000 -> 0 | T49: =+PL推移!L48 -> 0.64 | U49: =+T49-S49 -> 0.64 | V49: =IF(S49<>0,T49/S49,"-") -> - | W49: =+収支計画!L53/1000 -> 0 | X49: =+PL推移!N48 -> 0.64 | Y49: =+X49-W49 -> 0.64 | Z49: =IF(W49<>0,X49/W49,"-") -> - | AA49: =+収支計画!M53/1000 -> 0 | AB49: =+PL推移!P48 -> 2.34 | AC49: =+AB49-AA49 -> 2.34 | AD49: =IF(AA49<>0,AB49/AA49,"-") -> - | AE49: =+収支計画!AA59/1000 -> 0 | AF49: =+PL推移!R48 -> 0.64 | AG49: =+AF49-AE49 -> 0.64 | AH49: =IF(AE49<>0,AF49/AE49,"-") -> - | AI49: =+収支計画!O53/1000 -> 0 | AJ49: =+PL推移!T48 -> 3.64 | AK49: =+AJ49-AI49 -> 3.64 | AL49: =IF(AI49<>0,AJ49/AI49,"-") -> - | AM49: =+収支計画!P53/1000 -> 0 | AN49: =+PL推移!V48 -> 0.64 | AO49: =+AN49-AM49 -> 0.64 | AP49: =IF(AM49<>0,AN49/AM49,"-") -> - | AQ49: =+収支計画!Q53/1000 -> 0 | AR49: =+PL推移!X48 -> 0.64 | AS49: =+AR49-AQ49 -> 0.64 | AT49: =IF(AQ49<>0,AR49/AQ49,"-") -> - | AU49: =+収支計画!R53/1000 -> 0 | AV49: =+PL推移!Z48 -> 5.186 | AW49: =+AV49-AU49 -> 5.186 | AX49: =IF(AU49<>0,AV49/AU49,"-") -> - | AY49: =+C49+G49+K49+O49+S49+W49+AA49+AE49+AI49+AM49+AQ49+AU49 -> 0 | AZ49: =+D49+H49+L49+P49+T49+X49+AB49+AF49+AJ49+AN49+AR49+AV49 -> 35.321 | BA49: =+AZ49-AY49 -> 35.321 | BB49: =IF(AY49<>0,AZ49/AY49,"-") -> -
C50: =+収支計画!G54/1000 -> 250.137 | E50: =+D50-C50 -> -250.137 | F50: =IF(C50<>0,D50/C50,"-") -> 0 | G50: =+収支計画!H54/1000 -> 52.081 | H50: =+PL推移!F49 -> 0 | I50: =+H50-G50 -> -52.081 | J50: =IF(G50<>0,H50/G50,"-") -> 0 | K50: =+収支計画!I54/1000 -> 146.55 | L50: =+PL推移!H49 -> 0 | M50: =+L50-K50 -> -146.55 | N50: =IF(K50<>0,L50/K50,"-") -> 0 | O50: =+収支計画!J54/1000 -> 26.55 | P50: =+PL推移!J49 -> 0 | Q50: =+P50-O50 -> -26.55 | R50: =IF(O50<>0,P50/O50,"-") -> 0 | S50: =+収支計画!K54/1000 -> 26.55 | T50: =+PL推移!N49 -> 0 | U50: =+T50-S50 -> -26.55 | V50: =IF(S50<>0,T50/S50,"-") -> 0 | X50: =+PL推移!R49 -> 0 | Z50: =IF(W50<>0,X50/W50,"-") -> - | AB50: =+PL推移!V49 -> 0 | AD50: =IF(AA50<>0,AB50/AA50,"-") -> - | AF50: =+PL推移!Z49 -> 0 | AH50: =IF(AE50<>0,AF50/AE50,"-") -> - | AJ50: =+PL推移!AD49 -> 0 | AL50: =IF(AI50<>0,AJ50/AI50,"-") -> - | AN50: =+PL推移!AH49 -> 0 | AO50: =+AN50-AM50 -> 0 | AP50: =IF(AM50<>0,AN50/AM50,"-") -> - | AR50: =+PL推移!AL49 -> 0 | AS50: =+AR50-AQ50 -> 0 | AT50: =IF(AQ50<>0,AR50/AQ50,"-") -> - | AV50: =+PL推移!AP49 -> 0 | AW50: =+AV50-AU50 -> 0 | AX50: =IF(AU50<>0,AV50/AU50,"-") -> - | AY50: =+C50+G50+K50+O50+S50+W50+AA50+AE50+AI50+AM50+AQ50+AU50 -> 501.868 | AZ50: =+D50+H50+L50+P50+T50+X50+AB50+AF50+AJ50+AN50+AR50+AV50 -> 0 | BA50: =+AZ50-AY50 -> -501.868 | BB50: =IF(AY50<>0,AZ50/AY50,"-") -> 0
A51: 営業損益 | C51: =+C23-C29 -> -275.37 | D51: =+D23-D29 -> -275.37 | E51: =+E23-E29 -> 0 | F51: =IF(C51<>0,D51/C51,"-") -> 1 | G51: =+G23-G29 -> -8.081 | H51: =+PL推移!F50 -> -8.081 | I51: =+I23-I29 -> 0 | J51: =IF(G51<>0,H51/G51,"-") -> 1 | K51: =+K23-K29 -> -68.253721 | L51: =+PL推移!H50 -> -82.744 | M51: =+M23-M29 -> -14.490279 | N51: =IF(K51<>0,L51/K51,"-") -> 1.2123002 | O51: =+O23-O29 -> 6.3652984 | P51: =+PL推移!J50 -> -153.311 | Q51: =+Q23-Q29 -> -159.6763 | R51: =IF(O51<>0,P51/O51,"-") -> -24.085438 | S51: =+S23-S29 -> -16.325192 | T51: =+PL推移!L50 -> -42.661 | U51: =+U23-U29 -> -26.335808 | V51: =IF(S51<>0,T51/S51,"-") -> 2.6132005 | W51: =+W23-W29 -> 6.3652984 | X51: =+PL推移!N50 -> -126.903 | Y51: =+Y23-Y29 -> -159.8183 | Z51: =IF(W51<>0,X51/W51,"-") -> -19.936693 | AA51: =+AA23-AA29 -> 95.721789 | AB51: =+AB23-AB29 -> -101.07 | AC51: =+AC23-AC29 -> -223.34179 | AD51: =IF(AA51<>0,AB51/AA51,"-") -> -1.0558725 | AE51: =+AE23-AE29 -> 95.721789 | AF51: =+AF23-AF29 -> -58.249 | AG51: =+AG23-AG29 -> -230.52079 | AH51: =IF(AE51<>0,AF51/AE51,"-") -> -0.60852394 | AI51: =+AI23-AI29 -> 95.721789 | AJ51: =+AJ23-AJ29 -> -11.131 | AK51: =+AK23-AK29 -> -133.40279 | AL51: =IF(AI51<>0,AJ51/AI51,"-") -> -0.11628491 | AM51: =+AM23-AM29 -> 263.227 | AN51: =+AN23-AN29 -> 429.326 | AO51: =+AN51-AM51 -> 166.099 | AP51: =IF(AM51<>0,AN51/AM51,"-") -> 1.6310105 | AQ51: =+AQ23-AQ29 -> 231.718 | AR51: =+AR23-AR29 -> 214.215 | AS51: =+AR51-AQ51 -> -17.503 | AT51: =IF(AQ51<>0,AR51/AQ51,"-") -> 0.92446422 | AU51: =+AU23-AU29 -> 263.277 | AV51: =+AV23-AV29 -> 326.834 | AW51: =+AV51-AU51 -> 63.557 | AX51: =IF(AU51<>0,AV51/AU51,"-") -> 1.2414073 | AY51: =+C51+G51+K51+O51+S51+W51+AA51+AE51+AI51+AM51+AQ51+AU51 -> 690.08805 | AZ51: =+D51+H51+L51+P51+T51+X51+AB51+AF51+AJ51+AN51+AR51+AV51 -> 110.855 | BA51: =+AZ51-AY51 -> -579.23305 | BB51: =IF(AY51<>0,AZ51/AY51,"-") -> 0.16063892
B52: 期中累計 | C52: =+C51 -> -275.37 | D52: =+D51 -> -275.37 | E52: =+E51 -> 0 | F52: =IF(C52<>0,D52/C52,"-") -> 1 | G52: =+C52+G51 -> -283.451 | H52: =+D52+H51 -> -283.451 | I52: =+H52-G52 -> 0 | J52: =IF(G52<>0,H52/G52,"-") -> 1 | K52: =+G52+K51 -> -351.70472 | L52: =+H52+L51 -> -366.195 | M52: =+L52-K52 -> -14.490279 | N52: =IF(K52<>0,L52/K52,"-") -> 1.0412001 | O52: =+K52+O51 -> -345.33942 | P52: =+L52+P51 -> -519.506 | Q52: =+P52-O52 -> -174.16658 | R52: =IF(O52<>0,P52/O52,"-") -> 1.5043345 | S52: =+O52+S51 -> -361.66461 | T52: =+P52+T51 -> -562.167 | U52: =+T52-S52 -> -200.50239 | V52: =IF(S52<>0,T52/S52,"-") -> 1.5543876 | W52: =+S52+W51 -> -355.29932 | X52: =+T52+X51 -> -689.07 | Y52: =+X52-W52 -> -333.77068 | Z52: =IF(W52<>0,X52/W52,"-") -> 1.9394071 | AA52: =+W52+AA51 -> -259.57753 | AB52: =+X52+AB51 -> -790.14 | AC52: =+AB52-AA52 -> -530.56247 | AD52: =IF(AA52<>0,AB52/AA52,"-") -> 3.0439461 | AE52: =+AA52+AE51 -> -163.85574 | AF52: =+AB52+AF51 -> -848.389 | AG52: =+AF52-AE52 -> -684.53326 | AH52: =IF(AE52<>0,AF52/AE52,"-") -> 5.1776582 | AI52: =+AE52+AI51 -> -68.13395 | AJ52: =+AF52+AJ51 -> -859.52 | AK52: =+AJ52-AI52 -> -791.38605 | AL52: =IF(AI52<>0,AJ52/AI52,"-") -> 12.61515 | AM52: =+AI52+AM51 -> 195.09305 | AN52: =+AJ52+AN51 -> -430.194 | AO52: =+AN52-AM52 -> -625.28705 | AP52: =IF(AM52<>0,AN52/AM52,"-") -> -2.2050709 | AQ52: =+AM52+AQ51 -> 426.81105 | AR52: =+AN52+AR51 -> -215.979 | AS52: =+AR52-AQ52 -> -642.79005 | AT52: =IF(AQ52<>0,AR52/AQ52,"-") -> -0.50602954 | AU52: =+AQ52+AU51 -> 690.08805 | AV52: =+AR52+AV51 -> 110.855 | AW52: =+AV52-AU52 -> -579.23305 | AX52: =IF(AU52<>0,AV52/AU52,"-") -> 0.16063892
A53: 営業外収益 | C53: =+収支計画!G58/1000 -> 0 | D53: =+PL推移!D52 -> 0 | E53: =+D53-C53 -> 0 | F53: =IF(C53<>0,D53/C53,"-") -> - | G53: =+収支計画!H58/1000 -> 1.782 | H53: =+PL推移!F52 -> 1.782 | I53: =+H53-G53 -> 0 | J53: =IF(G53<>0,H53/G53,"-") -> 1 | K53: =+収支計画!I58/1000 -> 0 | L53: =+PL推移!H52 -> 1.187 | M53: =+L53-K53 -> 1.187 | N53: =IF(K53<>0,L53/K53,"-") -> - | O53: =+収支計画!J58/1000 -> 0 | P53: =+PL推移!J52 -> 0 | Q53: =+P53-O53 -> 0 | R53: =IF(O53<>0,P53/O53,"-") -> - | S53: =+収支計画!K58/1000 -> 0 | T53: =+PL推移!L52 -> 0 | U53: =+T53-S53 -> 0 | V53: =IF(S53<>0,T53/S53,"-") -> - | W53: =+収支計画!AA65/1000 -> 0 | X53: =+PL推移!N52 -> 0 | Y53: =+X53-W53 -> 0 | Z53: =IF(W53<>0,X53/W53,"-") -> - | AA53: =+収支計画!AE65/1000 -> 0 | AB53: =+PL推移!P52 -> 0 | AC53: =+AB53-AA53 -> 0 | AD53: =IF(AA53<>0,AB53/AA53,"-") -> - | AE53: =+収支計画!AI65/1000 -> 0 | AF53: =+PL推移!R52 -> 0.866 | AG53: =+AF53-AE53 -> 0.866 | AH53: =IF(AE53<>0,AF53/AE53,"-") -> - | AI53: =+収支計画!AM65/1000 -> 0 | AJ53: =+PL推移!T52 -> 0.52 | AK53: =+AJ53-AI53 -> 0.52 | AL53: =IF(AI53<>0,AJ53/AI53,"-") -> - | AM53: =+収支計画!AQ65/1000 -> 0 | AN53: =+PL推移!V52 -> 0 | AO53: =+AN53-AM53 -> 0 | AP53: =IF(AM53<>0,AN53/AM53,"-") -> - | AQ53: =+収支計画!AG65/1000 -> 0 | AR53: =+PL推移!X52 -> 0 | AS53: =+AR53-AQ53 -> 0 | AT53: =IF(AQ53<>0,AR53/AQ53,"-") -> - | AU53: =+収支計画!AI65/1000 -> 0 | AV53: =+PL推移!Z52 -> 0.239 | AW53: =+AV53-AU53 -> 0.239 | AX53: =IF(AU53<>0,AV53/AU53,"-") -> - | AY53: =+C53+G53+K53+O53+S53+W53+AA53+AE53+AI53+AM53+AQ53+AU53 -> 1.782 | AZ53: =+D53+H53+L53+P53+T53+X53+AB53+AF53+AJ53+AN53+AR53+AV53 -> 4.594 | BA53: =+AZ53-AY53 -> 2.812 | BB53: =IF(AY53<>0,AZ53/AY53,"-") -> 2.5780022
A54: 営業外費用 | C54: =+収支計画!G59/1000 -> 8.493 | D54: =+PL推移!D53 -> 8.493 | E54: =+D54-C54 -> 0 | F54: =IF(C54<>0,D54/C54,"-") -> 1 | G54: =+収支計画!H59/1000 -> 8.493 | H54: =+PL推移!F53 -> 8.493 | I54: =+H54-G54 -> 0 | J54: =IF(G54<>0,H54/G54,"-") -> 1 | K54: =+収支計画!I59/1000 -> 8 | L54: =+PL推移!H53 -> 8.219 | M54: =+L54-K54 -> 0.219 | N54: =IF(K54<>0,L54/K54,"-") -> 1.027375 | O54: =+収支計画!J59/1000 -> 8 | P54: =+PL推移!J53 -> 8.493 | Q54: =+P54-O54 -> 0.493 | R54: =IF(O54<>0,P54/O54,"-") -> 1.061625 | S54: =+収支計画!K59/1000 -> 8 | T54: =+PL推移!L53 -> 8.219 | U54: =+T54-S54 -> 0.219 | V54: =IF(S54<>0,T54/S54,"-") -> 1.027375 | W54: =+収支計画!Y66/1000 -> 0 | X54: =+PL推移!N53 -> 8.493 | Y54: =+X54-W54 -> 8.493 | Z54: =IF(W54<>0,X54/W54,"-") -> - | AA54: =+収支計画!Y66/1000 -> 0 | AB54: =+PL推移!P53 -> 8.493 | AC54: =+AB54-AA54 -> 8.493 | AD54: =IF(AA54<>0,AB54/AA54,"-") -> - | AE54: =+収支計画!AA66/1000 -> 0 | AF54: =+PL推移!R53 -> 7.671 | AG54: =+AF54-AE54 -> 7.671 | AH54: =IF(AE54<>0,AF54/AE54,"-") -> - | AI54: =+収支計画!O59/1000 -> 8 | AJ54: =+PL推移!T53 -> 8.493 | AK54: =+AJ54-AI54 -> 0.493 | AL54: =IF(AI54<>0,AJ54/AI54,"-") -> 1.061625 | AM54: =+収支計画!AI66/1000 -> 0 | AN54: =+PL推移!V53 -> 8.219 | AO54: =+AN54-AM54 -> 8.219 | AP54: =IF(AM54<>0,AN54/AM54,"-") -> - | AQ54: =+収支計画!AG66/1000 -> 0 | AR54: =+PL推移!X53 -> 8.493 | AS54: =+AR54-AQ54 -> 8.493 | AT54: =IF(AQ54<>0,AR54/AQ54,"-") -> - | AU54: =+収支計画!AI66/1000 -> 0 | AV54: =+PL推移!Z53 -> 8.219 | AW54: =+AV54-AU54 -> 8.219 | AX54: =IF(AU54<>0,AV54/AU54,"-") -> - | AY54: =+C54+G54+K54+O54+S54+W54+AA54+AE54+AI54+AM54+AQ54+AU54 -> 48.986 | AZ54: =+D54+H54+L54+P54+T54+X54+AB54+AF54+AJ54+AN54+AR54+AV54 -> 99.998 | BA54: =+AZ54-AY54 -> 51.012 | BB54: =IF(AY54<>0,AZ54/AY54,"-") -> 2.0413588
A55: 経常損益 | C55: =+C51+C53-C54 -> -283.863 | D55: =+D51+D53-D54 -> -283.863 | E55: =+E51+E53-E54 -> 0 | F55: =IF(C55<>0,D55/C55,"-") -> 1 | G55: =+G51+G53-G54 -> -14.792 | H55: =+PL推移!F54 -> -14.792 | I55: =+I51+I53-I54 -> 0 | J55: =IF(G55<>0,H55/G55,"-") -> 1 | K55: =+K51+K53-K54 -> -76.253721 | L55: =+PL推移!H54 -> -89.776 | M55: =+M51+M53-M54 -> -13.522279 | N55: =IF(K55<>0,L55/K55,"-") -> 1.1773327 | O55: =+O51+O53-O54 -> -1.6347016 | P55: =+PL推移!J54 -> -161.804 | Q55: =+Q51+Q53-Q54 -> -160.1693 | R55: =IF(O55<>0,P55/O55,"-") -> 98.980756 | S55: =+S51+S53-S54 -> -24.325192 | T55: =+PL推移!L54 -> -50.88 | U55: =+U51+U53-U54 -> -26.554808 | V55: =IF(S55<>0,T55/S55,"-") -> 2.0916587 | W55: =+W51+W53-W54 -> 6.3652984 | X55: =+PL推移!N54 -> -135.396 | Y55: =+Y51+Y53-Y54 -> -168.3113 | Z55: =IF(W55<>0,X55/W55,"-") -> -21.270959 | AA55: =+AA51+AA53-AA54 -> 95.721789 | AB55: =+AB51+AB53-AB54 -> -109.563 | AC55: =+AC51+AC53-AC54 -> -231.83479 | AD55: =IF(AA55<>0,AB55/AA55,"-") -> -1.1445983 | AE55: =+AE51+AE53-AE54 -> 95.721789 | AF55: =+AF51+AF53-AF54 -> -65.054 | AG55: =+AG51+AG53-AG54 -> -237.32579 | AH55: =IF(AE55<>0,AF55/AE55,"-") -> -0.67961538 | AI55: =+AI51+AI53-AI54 -> 87.721789 | AJ55: =+AJ51+AJ53-AJ54 -> -19.104 | AK55: =+AK51+AK53-AK54 -> -133.37579 | AL55: =IF(AI55<>0,AJ55/AI55,"-") -> -0.21777942 | AM55: =+AM51+AM53-AM54 -> 263.227 | AN55: =+AN51+AN53-AN54 -> 421.107 | AO55: =+AN55-AM55 -> 157.88 | AP55: =IF(AM55<>0,AN55/AM55,"-") -> 1.5997865 | AQ55: =+AQ51+AQ53-AQ54 -> 231.718 | AR55: =+AR51+AR53-AR54 -> 205.722 | AS55: =+AR55-AQ55 -> -25.996 | AT55: =IF(AQ55<>0,AR55/AQ55,"-") -> 0.88781191 | AU55: =+AU51+AU53-AU54 -> 263.277 | AV55: =+AV51+AV53-AV54 -> 318.854 | AW55: =+AV55-AU55 -> 55.577 | AX55: =IF(AU55<>0,AV55/AU55,"-") -> 1.2110971 | AY55: =+C55+G55+K55+O55+S55+W55+AA55+AE55+AI55+AM55+AQ55+AU55 -> 642.88405 | AZ55: =+D55+H55+L55+P55+T55+X55+AB55+AF55+AJ55+AN55+AR55+AV55 -> 15.451 | BA55: =+AZ55-AY55 -> -627.43305 | BB55: =IF(AY55<>0,AZ55/AY55,"-") -> 0.024033883
B56: 期中累計 | C56: =+C55 -> -283.863 | D56: =+D55 -> -283.863 | E56: =+E55 -> 0 | F56: =IF(C56<>0,D56/C56,"-") -> 1 | G56: =+C56+G55 -> -298.655 | H56: =+D56+H55 -> -298.655 | I56: =+H56-G56 -> 0 | J56: =IF(G56<>0,H56/G56,"-") -> 1 | K56: =+G56+K55 -> -374.90872 | L56: =+H56+L55 -> -388.431 | M56: =+L56-K56 -> -13.522279 | N56: =IF(K56<>0,L56/K56,"-") -> 1.0360682 | O56: =+K56+O55 -> -376.54342 | P56: =+PL推移!J55 -> -550.235 | Q56: =+P56-O56 -> -173.69158 | R56: =IF(O56<>0,P56/O56,"-") -> 1.461279 | S56: =+O56+S55 -> -400.86861 | T56: =+P56+T55 -> -601.115 | U56: =+T56-S56 -> -200.24639 | V56: =IF(S56<>0,T56/S56,"-") -> 1.4995312 | W56: =+S56+W55 -> -394.50332 | X56: =+T56+X55 -> -736.511 | Y56: =+X56-W56 -> -342.00768 | Z56: =IF(W56<>0,X56/W56,"-") -> 1.8669323 | AA56: =+W56+AA55 -> -298.78153 | AB56: =+X56+AB55 -> -846.074 | AC56: =+AB56-AA56 -> -547.29247 | AD56: =IF(AA56<>0,AB56/AA56,"-") -> 2.831748 | AE56: =+AA56+AE55 -> -203.05974 | AF56: =+AB56+AF55 -> -911.128 | AG56: =+AF56-AE56 -> -708.06826 | AH56: =IF(AE56<>0,AF56/AE56,"-") -> 4.4869948 | AI56: =+AE56+AI55 -> -115.33795 | AJ56: =+AF56+AJ55 -> -930.232 | AK56: =+AJ56-AI56 -> -814.89405 | AL56: =IF(AI56<>0,AJ56/AI56,"-") -> 8.0652726 | AM56: =+AI56+AM55 -> 147.88905 | AN56: =+AJ56+AN55 -> -509.125 | AO56: =+AN56-AM56 -> -657.01405 | AP56: =IF(AM56<>0,AN56/AM56,"-") -> -3.4426146 | AQ56: =+AM56+AQ55 -> 379.60705 | AR56: =+AN56+AR55 -> -303.403 | AS56: =+AR56-AQ56 -> -683.01005 | AT56: =IF(AQ56<>0,AR56/AQ56,"-") -> -0.79925544 | AU56: =+AQ56+AU55 -> 642.88405 | AV56: =+AR56+AV55 -> 15.451 | AW56: =+AV56-AU56 -> -627.43305 | AX56: =IF(AU56<>0,AV56/AU56,"-") -> 0.024033883 | BB56: =IF(AY56<>0,AZ56/AY56,"-") -> -
AU58: 決算整理 | AV58: 信用保証料振替 | AX58: -27
AV60: R8/6決算見込 | AX60: =+AZ55+AX58+AX59 -> -11.549

Sheet CF推移
E1: 改善 | F1: 不確定含む | G1: 要検証
B2: ■月次報告CF | E2: =+PL推移!D7 -> ㈱Ｓクリエイト
B4: =+PL推移!B8 -> 2025 | C4: 年度 | D4: 単位：千円 | E4: =+月次PL!C1 -> 7 | F4: =+月次PL!D1 -> 8 | G4: =+BS千円!F1 -> 9 | H4: =+BS千円!G1 -> 10 | I4: =+BS千円!H1 -> 11 | J4: =+BS千円!I1 -> 12 | K4: =+BS千円!J1 -> 1 | L4: =+BS千円!K1 -> 2 | M4: =+BS千円!L1 -> 3 | N4: =+BS千円!M1 -> 4 | ... P4: =+BS千円!O1 -> 6
B5: １．営業活動CF | E5: =+E6-E7+E8-E9-E10-E11+E12+E13 -> 376.18 | F5: =+F6-F7+F8-F9-F10-F11+F12+F13 -> -727.163 | G5: =+G6-G7+G8-G9-G10-G11+G12+G13 -> 33.103 | H5: =+H6-H7+H8-H9-H10-H11+H12+H13 -> -630.914 | I5: =+I6-I7+I8-I9-I10-I11+I12+I13 -> 132.717 | J5: =+J6-J7+J8-J9-J10-J11+J12+J13 -> -44.769 | K5: =+K6-K7+K8-K9-K10-K11+K12+K13 -> -270.905 | L5: =+L6-L7+L8-L9-L10-L11+L12+L13 -> 1056.33 | ... P5: =+P6-P7+P8-P9-P10-P11+P12+P13 -> -589.451
C6: 税引前利益 | D6: ＋ | E6: =+月次PL!C63/1000 -> -283.863 | F6: =+月次PL!D63/1000 -> -14.792 | G6: =+月次PL!E63/1000 -> -89.776 | H6: =+月次PL!F63/1000 -> -161.804 | I6: =+月次PL!G63/1000 -> -50.88 | J6: =+月次PL!H63/1000 -> -135.396 | K6: =+月次PL!I63/1000 -> -109.563 | L6: =+月次PL!J63/1000 -> -65.054 | ... P6: =+月次PL!N63/1000 -> 318.854
C7: 決算関係納税 | D7: － | E7: =+月次PL!C64/1000+BS千円!C59+BS千円!C60-BS千円!D59-BS千円!D60 -> 0 | F7: =+月次PL!D64/1000+BS千円!D59+BS千円!D60-BS千円!E59-BS千円!E60 -> 205.6 | G7: =+月次PL!E64/1000+BS千円!E59+BS千円!E60-BS千円!F59-BS千円!F60 -> 0 | H7: 0 | I7: 0 | J7: 0 | K7: 0 | L7: 0 | M7: 0 | N7: 0 | O7: 0 | P7: 0
C8: 減価償却費 | D8: ＋ | E8: =+月次PL!C41/1000 -> 26.5 | F8: =+月次PL!D41/1000 -> 26.5 | G8: =+月次PL!E41/1000 -> 26.5 | H8: =+月次PL!F41/1000 -> 26.5 | I8: =+月次PL!G41/1000 -> 26.5 | J8: =+月次PL!H41/1000 -> 26.5 | K8: =+月次PL!I41/1000 -> 26.5 | L8: =+月次PL!J41/1000 -> 26.5 | ... P8: =+月次PL!N41/1000 -> 26.5
C9: 売掛債権 | D9: － | E9: =+BS千円!D10-BS千円!C10 -> 476.116 | F9: =+BS千円!E10-BS千円!D10 -> 505.826 | G9: =+BS千円!F10-BS千円!E10 -> 518.821 | H9: =+BS千円!G10-BS千円!F10 -> 518.847 | I9: =+BS千円!H10-BS千円!G10 -> 420.796 | J9: =+BS千円!I10-BS千円!H10 -> 634.63 | K9: =+BS千円!J10-BS千円!I10 -> 520.349 | L9: =+BS千円!K10-BS千円!J10 -> 462.773 | ... P9: =+BS千円!O10-BS千円!N10 -> 977.322
C10: 棚卸資産 | D10: － | E10: =+BS千円!D16-BS千円!C16 -> 0 | F10: =+BS千円!E16-BS千円!D16 -> 0 | G10: =+BS千円!F16-BS千円!E16 -> 0 | H10: =+BS千円!G16-BS千円!F16 -> 0 | I10: =+BS千円!H16-BS千円!G16 -> 0 | J10: =+BS千円!I16-BS千円!H16 -> 0 | K10: =+BS千円!J16-BS千円!I16 -> 0 | L10: =+BS千円!K16-BS千円!J16 -> 0 | ... P10: =+BS千円!O16-BS千円!N16 -> 0
C11: その他流動資産 | D11: － | E11: =+BS千円!D23-BS千円!C23-E16 -> -947.113 | F11: =+BS千円!E23-BS千円!D23-F16 -> 34.244 | G11: =+BS千円!F23-BS千円!E23-G16 -> -463.618 | H11: =+BS千円!G23-BS千円!F23 -> 49.351 | I11: =+BS千円!H23-BS千円!G23 -> -545.581 | J11: =+BS千円!I23-BS千円!H23 -> -439.319 | K11: =+BS千円!J23-BS千円!I23 -> -508.11 | L11: =+BS千円!K23-BS千円!J23 -> -1480.501 | M11: =+BS千円!L23-BS千円!K23 -> -2636.887 | N11: =+BS千円!M23-BS千円!L23 -> 36.308 | O11: =+BS千円!N23-BS千円!M23 -> 44.845 | P11: =+BS千円!O23-BS千円!N23 -> 47.881
C12: 買掛未払債務 | D12: ＋ | E12: =+BS千円!D95-BS千円!C95 -> 122.785 | F12: =+BS千円!E95-BS千円!D95 -> -2.965 | G12: =+BS千円!F95-BS千円!E95 -> 81.476 | H12: =+BS千円!G95-BS千円!F95 -> -23.068 | I12: =+BS千円!H95-BS千円!G95 -> -31.996 | J12: =+BS千円!I95-BS千円!H95 -> 97.881 | K12: =+BS千円!J95-BS千円!I95 -> -132.42 | L12: =+BS千円!K95-BS千円!J95 -> -34.529 | ... P12: =+BS千円!O95-BS千円!N95 -> 7.408
C13: その他流動負債 | D13: ＋ | E13: =+BS千円!D96-BS千円!C96 -> 39.761 | F13: =+BS千円!E96-BS千円!D96 -> 9.764 | G13: =+BS千円!F96-BS千円!E96 -> 70.106 | H13: =+BS千円!G96-BS千円!F96 -> 95.656 | I13: =+BS千円!H96-BS千円!G96 -> 64.308 | J13: =+BS千円!I96-BS千円!H96 -> 161.557 | K13: =+BS千円!J96-BS千円!I96 -> -43.183 | L13: =+BS千円!K96-BS千円!J96 -> 111.685 | ... P13: =+BS千円!O96-BS千円!N96 -> 82.99
B14: ２．投資活動CF | E14: =-E15-E16-E17 -> 0 | F14: =-F15-F16-F17 -> 0 | G14: =-G15-G16-G17 -> 0 | H14: =-H15-H16-H17 -> 0 | I14: =-I15-I16-I17 -> 0 | J14: =-J15-J16-J17 -> 0 | K14: =-K15-K16-K17 -> 0 | L14: =-L15-L16-L17 -> 0 | ... P14: =-P15-P16-P17 -> 0
C15: 固定資産への投資 | D15: － | E15: =+BS千円!D97-BS千円!C97+CF推移!E8 -> 0 | F15: =+BS千円!E97-BS千円!D97+CF推移!F8 -> 0 | G15: =+BS千円!F97-BS千円!E97+CF推移!G8 -> 0 | H15: =+BS千円!G97-BS千円!F97+CF推移!H8 -> 0 | I15: =+BS千円!H97-BS千円!G97+CF推移!I8 -> 0 | J15: =+BS千円!I97-BS千円!H97+CF推移!J8 -> 0 | K15: =+BS千円!J97-BS千円!I97+CF推移!K8 -> 0 | L15: =+BS千円!K97-BS千円!J97+CF推移!L8 -> 0 | ... P15: =+BS千円!O97-BS千円!N97+CF推移!P8 -> 0
C16: 貸付金 | D16: － | E16: =+BS千円!D21-BS千円!C21 -> 0 | F16: =+BS千円!E21-BS千円!D21 -> 0 | G16: =+BS千円!F21-BS千円!E21 -> 0 | H16: 0 | I16: 0 | J16: 0 | K16: 0 | L16: 0 | M16: 0 | N16: 0 | O16: 0 | P16: 0
C17: 投資勘定への支出 | D17: － | E17: =+BS千円!D41-BS千円!C41 -> 0 | F17: =+BS千円!E41-BS千円!D41 -> 0 | G17: =+BS千円!F41-BS千円!E41 -> 0 | H17: =+BS千円!G41-BS千円!F41 -> 0 | I17: =+BS千円!H41-BS千円!G41 -> 0 | J17: =+BS千円!I41-BS千円!H41 -> 0 | K17: =+BS千円!J41-BS千円!I41 -> 0 | L17: =+BS千円!K41-BS千円!J41 -> 0 | ... P17: =+BS千円!O41-BS千円!N41 -> 0
B18: ３．財務活動CF | E18: =+E19+E20-E21+E22+E23 -> 0 | F18: =+F19+F20-F21+F22+F23 -> 0 | G18: =+G19+G20-G21+G22+G23 -> 0 | H18: =+H19+H20-H21+H22+H23 -> 0 | I18: =+I19+I20-I21+I22+I23 -> 0 | J18: =+J19+J20-J21+J22+J23 -> 0 | K18: =+K19+K20-K21+K22+K23 -> 0 | L18: =+L19+L20-L21+L22+L23 -> 0 | ... P18: =+P19+P20-P21+P22+P23 -> 0
C19: 短期借入金 | D19: ＋ | E19: =+BS千円!D99-BS千円!C99 -> 0 | F19: =+BS千円!E99-BS千円!D99 -> 0 | G19: =+BS千円!F99-BS千円!E99 -> 0 | H19: =+BS千円!G99-BS千円!F99 -> 0 | I19: =+BS千円!H99-BS千円!G99 -> 0 | J19: =+BS千円!I99-BS千円!H99 -> 0 | K19: =+BS千円!J99-BS千円!I99 -> 0 | L19: =+BS千円!K99-BS千円!J99 -> 0 | ... P19: =+BS千円!O99-BS千円!N99 -> 0
C20: 長期借入金調達 | D20: ＋ | E20: 0 | F20: 0 | G20: 0 | H20: 0 | I20: 0 | J20: 0 | K20: 0 | L20: 0 | M20: 0 | N20: 0 | O20: 0 | P20: 0
C21: 長期借入金返済 | D21: － | E21: =+BS千円!C98-BS千円!D98+CF推移!E20 -> 0 | F21: =+BS千円!D98-BS千円!E98+CF推移!F20 -> 0 | G21: =+BS千円!E98-BS千円!F98+CF推移!G20 -> 0 | H21: =+BS千円!F98-BS千円!G98+CF推移!H20 -> 0 | I21: =+BS千円!G98-BS千円!H98+CF推移!I20 -> 0 | J21: =+BS千円!H98-BS千円!I98+CF推移!J20 -> 0 | K21: =+BS千円!I98-BS千円!J98+CF推移!K20 -> 0 | L21: =+BS千円!J98-BS千円!K98+CF推移!L20 -> 0 | ... P21: =+BS千円!N98-BS千円!O98+CF推移!P20 -> 0
C22: 資本の増減 | D22: ＋ | E22: =+BS千円!D72-BS千円!C72 -> 0 | F22: =+BS千円!E72-BS千円!D72 -> 0 | G22: =+BS千円!F72-BS千円!E72 -> 0 | H22: =+BS千円!G72-BS千円!F72 -> 0 | I22: =+BS千円!H72-BS千円!G72 -> 0 | J22: =+BS千円!I72-BS千円!H72 -> 0 | K22: =+BS千円!J72-BS千円!I72 -> 0 | L22: =+BS千円!K72-BS千円!J72 -> 0 | ... P22: =+BS千円!O72-BS千円!N72 -> 0
C23: その他 | D23: ＋ | E23: 0 | F23: 0 | G23: 0 | H23: 0 | I23: 0 | J23: 0 | K23: 0 | L23: 0 | M23: 0 | N23: 0 | O23: 0 | P23: 0
B24: ４．月次CF | E24: =+E5+E14+E18 -> 376.18 | F24: =+F5+F14+F18 -> -727.163 | G24: =+G5+G14+G18 -> 33.103 | H24: =+H5+H14+H18 -> -630.914 | I24: =+I5+I14+I18 -> 132.717 | J24: =+J5+J14+J18 -> -44.769 | K24: =+K5+K14+K18 -> -270.905 | L24: =+L5+L14+L18 -> 1056.33 | ... P24: =+P5+P14+P18 -> -589.451
C26: 現金預金の増減額 | E26: =+BS千円!D7-BS千円!C7 -> 376.18 | F26: =+BS千円!E7-BS千円!D7 -> -727.163 | G26: =+BS千円!F7-BS千円!E7 -> 33.103 | H26: =+BS千円!G7-BS千円!F7 -> -630.914 | I26: =+BS千円!H7-BS千円!G7 -> 132.717 | J26: =+BS千円!I7-BS千円!H7 -> -44.769 | K26: =+BS千円!J7-BS千円!I7 -> -270.905 | L26: =+BS千円!K7-BS千円!J7 -> 1056.33 | ... P26: =+BS千円!O7-BS千円!N7 -> -589.451
D27: CF:CK | E27: =+E24-E26 -> 4.5474735e-13 | F27: =+F24-F26 -> 0 | G27: =+G24-G26 -> 2.2737368e-13 | H27: =+H24-H26 -> 0 | I27: =+I24-I26 -> 5.968559e-13 | J27: =+J24-J26 -> -4.5474735e-13 | K27: =+K24-K26 -> -5.1159077e-13 | L27: =+L24-L26 -> 0 | ... P27: =+P24-P26 -> -9.094947e-13
B28: □ＣＦ特記事項等
C29: CF計画比 | E29: =+E26-収支計画!G104/1000 -> 80.577 | F29: =+F26-収支計画!H104/1000 -> -15.143 | G29: =+G26-収支計画!I104/1000 -> 41.184 | H29: =+CF推移!H26-収支計画!J104/1000 -> -562.66028 | I29: =+I26-収支計画!K104/1000 -> 293.3517 | J29: =+J26-収支計画!L104/1000 -> 138.55619 | K29: =+K26-収支計画!M104/1000 -> -110.2703 | L29: =+L26-収支計画!N104/1000 -> 1120.6082 | M29: =+M26-収支計画!O104/1000 -> 3266.9492 | N29: =+N26-収支計画!P104/1000 -> -331.97679 | O29: =+O26-収支計画!Q104/1000 -> -273.72579 | P29: =+CF推移!P26-収支計画!R104/1000 -> -518.17279
D30: 計画利益差異 | N30: =+PL予実対比!AO51 -> 166.099 | O30: =+PL予実対比!AS55 -> -25.996 | P30: =+PL予実対比!AW55 -> 55.577
C31: 現金売上・売掛回収 | H31: -519 | I31: 110 | L31: -520 | M31: =1226-463 -> 763 | N31: -808 | O31: -862 | P31: =-869+161 -> -708 | Q31: ﾗｲﾌﾜｰｸ未回収
C32: 現金仕入・買掛未払 | N32: 110 | Q32: R7/9ｸﾘｴｲﾄ9 未払 | S32: 支払消滅戻し
C33: 経費支出 | I33: 48
C34: 納税その他 | I34: 167 | L34: 1520 | M34: 2638 | N34: 167 | O34: 167 | P34: 167 | Q34: 借入金返済

Sheet 収支計画
E5: 収支予測表
F8: 更新日 | K8: 2025.8.21 | L8: 2025.9.17
E9: 勘定科目 | S9: 手入力 | T9: 手入力
G10: =+月次PL!C1 -> 7 | H10: =+月次PL!D1 -> 8 | I10: =+月次PL!E1 -> 9 | J10: =+月次PL!F1 -> 10 | K10: =+月次PL!G1 -> 11 | L10: =+月次PL!H1 -> 12 | M10: =+月次PL!I1 -> 1 | N10: =+月次PL!J1 -> 2 | ... R10: =+月次PL!N1 -> 6 | S10: =+[1]収支予測!CN$10 -> 2026.04 | T10: R8.08 | U10: R8.09 | V10: R8.10 | W10: R8.11 | X10: R8.12 | Y10: R9.01 | Z10: R9.02
E11: 売上高 | G11: 622833 | H11: 559842 | I11: 621881.28 | J11: 576500.3 | K11: 553809.81 | L11: 576500.3 | M11: 599190.79 | N11: 599190.79 | O11: 599190.79 | P11: 793196 | Q11: 761687 | R11: 793196
B16: 月末売掛残高割合 | C16: 現金割合
A17: 原価率 | B17: 0.34 | C17: =1-B17 -> 0.66 | F17: 合計 | G17: =SUM(G11:G16) -> 622833 | H17: =SUM(H11:H16) -> 559842 | I17: =SUM(I11:I16) -> 621881.28 | J17: =SUM(J11:J16) -> 576500.3 | K17: =SUM(K11:K16) -> 553809.81 | L17: =SUM(L11:L16) -> 576500.3 | M17: =SUM(M11:M16) -> 599190.79 | N17: =SUM(N11:N16) -> 599190.79 | ... Z17: =SUM(Z11:Z16) -> 0
A18: 0.3 | E18: 売上原価
A19: 0.34
A21: 0.32
A23: 0.34 | B23: 掛割合 | C23: 現金割合
B24: 0.99 | C24: =1-B24 -> 0.01 | F24: 合計 | G24: =SUM(G18:G23) -> 0 | H24: =SUM(H18:H23) -> 0 | I24: =SUM(I18:I23) -> 0 | J24: =SUM(J18:J23) -> 0 | K24: =SUM(K18:K23) -> 0 | L24: =SUM(L18:L23) -> 0 | M24: =SUM(M18:M23) -> 0 | N24: =SUM(N18:N23) -> 0 | ... Z24: =SUM(Z18:Z23) -> 0
E25: 粗利益 | G25: =G17-G24 -> 622833 | H25: =H17-H24 -> 559842 | I25: =I17-I24 -> 621881.28 | J25: =J17-J24 -> 576500.3 | K25: =K17-K24 -> 553809.81 | L25: =L17-L24 -> 576500.3 | M25: =M17-M24 -> 599190.79 | N25: =N17-N24 -> 599190.79 | ... Z25: =Z17-Z24 -> 0
A26: 予測値 | G26: =G25/G17 -> 1 | H26: =H25/H17 -> 1 | I26: =I25/I17 -> 1 | J26: =J25/J17 -> 1 | K26: =K25/K17 -> 1 | L26: =L25/L17 -> 1 | M26: =M25/M17 -> 1 | N26: =N25/N17 -> 1 | ... Z26: =Z25/Z17 -> #DIV/0!
A27: 590 | E27: 人件費 | F27: 役員報酬 | G27: 0 | H27: 100000 | I27: 100000 | J27: 100000 | K27: 100000 | L27: 100000 | M27: 100000 | N27: 100000 | O27: 100000 | P27: 100000 | Q27: 100000 | R27: 100000
F28: 給与手当
A29: ＊＊＊＊ | F29: 雑給
A30: ＊＊＊＊ | F30: 法定福利費
F31: 業務委託費 | G31: 535456 | H31: 231819 | I31: 231819 | J31: 231819 | K31: 231819 | L31: 231819 | M31: 231819 | N31: 231819 | O31: 231819 | P31: 231819 | Q31: 231819 | R31: 231819
A33: 3780
A34: 予測値 | F34: 合計 | G34: =SUM(G27:G33) -> 535456 | H34: =SUM(H27:H33) -> 331819 | I34: =SUM(I27:I33) -> 331819 | J34: =SUM(J27:J33) -> 331819 | K34: =SUM(K27:K33) -> 331819 | L34: =SUM(L27:L33) -> 331819 | M34: =SUM(M27:M33) -> 331819 | N34: =SUM(N27:N33) -> 331819 | ... Z34: =SUM(Z27:Z33) -> 0
A35: 661 | E35: 販売費管理費 | F35: 旅費交通費 | G35: 9720 | H35: 5371 | I35: 50000 | J35: 50000 | K35: 50000 | L35: 50000 | M35: 50000 | N35: 50000 | O35: 50000 | P35: 50000 | Q35: 50000 | R35: 50000
A36: ＊＊＊＊ | F36: 通信費 | G36: 1200 | H36: 55560 | I36: 600 | J36: 600 | K36: 600 | L36: 600 | M36: 600 | N36: 600 | O36: 600 | P36: 600 | Q36: 600 | R36: 600
A37: ＊＊＊＊ | F37: 開発費 | P37: 0 | Q37: 0 | R37: 0
F38: 交際費 | G38: 13438 | H38: 50137 | I38: 50000 | J38: 50000 | K38: 50000 | L38: 50000 | M38: 50000 | N38: 50000 | O38: 50000 | P38: 50000 | Q38: 50000 | R38: 50000
F39: 会議費
F40: 減価償却費 | G40: 26500 | H40: 26500 | I40: 66666 | J40: 66666 | K40: 66666 | L40: 66666 | M40: 0 | N40: 0 | O40: 0 | P40: 26500 | Q40: 26500 | R40: 26500
F41: 賃借料
F42: 地代家賃 | G42: 44500 | H42: 44500 | I42: 44500 | J42: 44500 | K42: 44500 | L42: 44500 | M42: 44500 | N42: 44500 | O42: 44500 | P42: 44500 | Q42: 44500 | R42: 44500
F43: リース料
F44: 修繕費
F45: 保険料
F46: 水道光熱費
F47: 消耗品費 | G47: 4797 | H47: 0 | I47: 0 | J47: 0 | K47: 0 | L47: 0 | M47: 0 | N47: 0 | O47: 0 | P47: 0 | Q47: 0 | R47: 0
F48: 租税公課
A49: 1750 | F49: 広告宣伝費
F50: 支払手数料 | G50: 12455 | H50: 1955 | I50: 0 | J50: 0 | K50: 0 | L50: 0 | M50: 0 | N50: 0 | O50: 0 | P50: 0 | Q50: 0 | R50: 0
F51: 新聞図書費
F52: 管理諸費
F53: 雑費
A54: 2758 | F54: その他 | G54: 250137 | H54: 52081 | I54: 146550 | J54: 26550 | K54: 26550 | L54: 26550 | M54: 26550 | N54: 26550 | O54: 26550 | P54: 26550 | Q54: 26550 | R54: 26500
F55: 合計 | G55: =SUM(G35:G54) -> 362747 | H55: =SUM(H35:H54) -> 236104 | I55: =SUM(I35:I54) -> 358316 | J55: =SUM(J35:J54) -> 238316 | K55: =SUM(K35:K54) -> 238316 | L55: =SUM(L35:L54) -> 238316 | M55: =SUM(M35:M54) -> 171650 | N55: =SUM(N35:N54) -> 171650 | ... Z55: =SUM(Z35:Z54) -> 0
E56: 経費合計 | G56: =G34+G55 -> 898203 | H56: =H34+H55 -> 567923 | I56: =I34+I55 -> 690135 | J56: =J34+J55 -> 570135 | K56: =K34+K55 -> 570135 | L56: =L34+L55 -> 570135 | M56: =M34+M55 -> 503469 | N56: =N34+N55 -> 503469 | ... Z56: =Z34+Z55 -> 0
A57: 予測値 | E57: 営業利益 | G57: =G25-G56 -> -275370 | H57: =H25-H56 -> -8081 | I57: =I25-I56 -> -68253.721 | J57: =J25-J56 -> 6365.2984 | K57: =K25-K56 -> -16325.192 | L57: =L25-L56 -> 6365.2984 | M57: =M25-M56 -> 95721.789 | N57: =N25-N56 -> 95721.789 | ... Z57: =Z25-Z56 -> 0
E58: 営業外収益 | G58: 0 | H58: 1782 | I58: 0 | J58: 0 | K58: 0 | L58: 0 | M58: 0 | N58: 0 | O58: 0 | P58: 0 | Q58: 0 | R58: 0
A59: 76 | E59: 営業外費用 | G59: 8493 | H59: 8493 | I59: 8000 | J59: 8000 | K59: 8000 | L59: 8000 | M59: 8000 | N59: 8000 | O59: 8000 | P59: 8000 | Q59: 8000 | R59: 8000
A60: 予測値 | E60: 経常利益 | G60: =G57+G58-G59 -> -283863 | H60: =H57+H58-H59 -> -14792 | I60: =I57+I58-I59 -> -76253.721 | J60: =J57+J58-J59 -> -1634.7016 | K60: =K57+K58-K59 -> -24325.192 | L60: =L57+L58-L59 -> -1634.7016 | M60: =M57+M58-M59 -> 87721.789 | N60: =N57+N58-N59 -> 87721.789 | ... Z60: =Z57+Z58-Z59 -> 0
E61: 特別利益
E62: 特別損失
E63: 税引前当期利益 | G63: =G60+G61-G62 -> -283863 | H63: =H60+H61-H62 -> -14792 | I63: =I60+I61-I62 -> -76253.721 | J63: =J60+J61-J62 -> -1634.7016 | K63: =K60+K61-K62 -> -24325.192 | L63: =L60+L61-L62 -> -1634.7016 | M63: =M60+M61-M62 -> 87721.789 | N63: =N60+N61-N62 -> 87721.789 | ... Z63: =Z60+Z61-Z62 -> 0
E64: 期間累計 | G64: =G63 -> -283863 | H64: =+G64+H63 -> -298655 | I64: =+H64+I63 -> -374908.72 | J64: =+I64+J63 -> -376543.42 | K64: =+J64+K63 -> -400868.61 | L64: =+K64+L63 -> -402503.32 | M64: =+L64+M63 -> -314781.53 | N64: =+M64+N63 -> -227059.74 | O64: =+N64+O63 -> -139337.95 | ... R64: =+Q64+R63 -> 594884.05 | S64: =S63 -> 0 | T64: =+S64+T63 -> 0 | U64: =+T64+U63 -> 0 | V64: =+U64+V63 -> 0 | W64: =+V64+W63 -> 0 | X64: =+W64+X63 -> 0 | Y64: =+X64+Y63 -> 0 | Z64: =+Y64+Z63 -> 0
E66: ＦＬ | G66: =+G24+G34 -> 535456 | H66: =+H24+H34 -> 331819 | I66: =+I24+I34 -> 331819 | J66: =+J24+J34 -> 331819 | K66: =+K24+K34 -> 331819 | L66: =+L24+L34 -> 331819 | M66: =+M24+M34 -> 331819 | N66: =+N24+N34 -> 331819 | ... Z66: =+Z24+Z34 -> 0
G67: =+G66/G17 -> 0.85971039 | H67: =+H66/H17 -> 0.59270115 | I67: =+I66/I17 -> 0.5335729 | J67: =+J66/J17 -> 0.57557472 | K67: =+K66/K17 -> 0.59915696 | L67: =+L66/L17 -> 0.57557472 | M67: =+M66/M17 -> 0.55377854 | N67: =+N66/N17 -> 0.55377854 | ... Z67: =+Z66/Z17 -> #DIV/0!
F68: 除サウナ | G68: =+G66-G22 -> 535456 | H68: =+H66-H22 -> 331819 | I68: =+I66-I22 -> 331819 | J68: =+J66-J22 -> 331819 | K68: =+K66-K22 -> 331819 | L68: =+L66-L22 -> 331819 | M68: =+M66-M22 -> 331819 | N68: =+N66-N22 -> 331819 | ... T68: =+T66-T22 -> 0
G69: =+G68/(G17-G15) -> 0.85971039 | H69: =+H68/(H17-H15) -> 0.59270115 | I69: =+I68/(I17-I15) -> 0.5335729 | J69: =+J68/(J17-J15) -> 0.57557472 | K69: =+K68/(K17-K15) -> 0.59915696 | L69: =+L68/(L17-L15) -> 0.57557472 | M69: =+M68/(M17-M15) -> 0.55377854 | N69: =+N68/(N17-N15) -> 0.55377854 | ... T69: =+T68/(T17-T15) -> #DIV/0!
E73: 【資金収支予測】
E74: 項目 | G74: 1 | H74: =+H9 -> 0 | I74: =+I9 -> 0 | J74: =+J9 -> 0 | K74: =+K9 -> 0 | L74: =+L9 -> 0 | M74: =+M9 -> 0 | N74: =+N9 -> 0 | O74: =+O9 -> 0 | ... Z74: =+Z9 -> 0
G75: =+G10 -> 7 | H75: =H10 -> 8 | I75: =I10 -> 9 | J75: =J10 -> 10 | K75: =K10 -> 11 | L75: =L10 -> 12 | M75: =M10 -> 1 | N75: =N10 -> 2 | O75: =O10 -> 3 | ... Z75: =Z10 -> R9.02
E76: A.前月繰越金 | G76: 2348989 | H76: =+G105 -> 2644592 | I76: =+H105 -> 1932572 | J76: =+I105 -> 1924491 | K76: =+J105 -> 1856237.3 | L76: =+K105 -> 1695602.6 | M76: =+L105 -> 1512277.4 | N76: =+M105 -> 1351642.7 | O76: =+N105 -> 1287364.5 | ... R76: =+Q105 -> 1073529.8 | S76: =R105 -> 1002251.6 | T76: =S108 -> -29213.372 | U76: =T108 -> -236382.37 | V76: =U108 -> -237958.37 | W76: =V108 -> -239697.37 | X76: =W108 -> -241051.37 | Y76: =X108 -> -241051.37 | Z76: =Y108 -> -241051.37
E77: 営業収入 | F77: 現金売上 | G77: 0 | H77: 0 | I77: 0 | J77: 0 | K77: 0 | L77: 0 | M77: 0 | N77: 7000 | O77: 0 | P77: 0 | Q77: 0 | R77: 0 | T77: =+T17*$C17 -> 0 | U77: =+U17*$C17 -> 0 | V77: =+V17*$C17 -> 0 | W77: =+W17*$C17 -> 0 | X77: =+X17*$C17 -> 0 | Y77: =+Y17*$C17 -> 0 | Z77: =+Z17*$C17 -> 0
F78: 売掛金入金 | G78: 1200000 | H78: 110000 | I78: 559842 | J78: 621881.28 | K78: 576500.3 | L78: 553809.81 | M78: 576500.3 | N78: 599190.79 | O78: 599190.79 | P78: 599190.79 | Q78: 599190.79 | R78: 599190.79 | T78: =+S17*$B17 -> 0 | U78: =+T17*$B17 -> 0 | V78: =+U17*$B17 -> 0 | W78: =+V17*$B17 -> 0 | X78: =+W17*$B17 -> 0 | Y78: =+X17*$B17 -> 0 | Z78: =+Y17*$B17 -> 0
F79: 営業外収益 | G79: 0 | H79: 1782 | I79: 0 | J79: 0 | K79: 0 | L79: 0 | M79: 0 | N79: 0 | O79: 0 | P79: 0 | Q79: 0 | R79: 0 | T79: =+T58 -> 0 | U79: =+U58 -> 0 | V79: =+V58 -> 0 | W79: =+W58 -> 0 | X79: =+X58 -> 0 | Y79: =+Y58 -> 0 | Z79: =+Z58 -> 0
F80: ①合計 | G80: =SUM(G77:G79) -> 1200000 | H80: =SUM(H77:H79) -> 111782 | I80: =SUM(I77:I79) -> 559842 | J80: =SUM(J77:J79) -> 621881.28 | K80: =SUM(K77:K79) -> 576500.3 | L80: =SUM(L77:L79) -> 553809.81 | M80: =SUM(M77:M79) -> 576500.3 | N80: =SUM(N77:N79) -> 606190.79 | ... Z80: =SUM(Z77:Z79) -> 0
E81: 営業支出 | F81: 現金仕入 | G81: 0 | H81: 0 | I81: 0 | J81: 0 | K81: 0 | L81: 0 | M81: 0 | N81: 0 | O81: 0 | P81: 0 | Q81: 0 | R81: 0 | S81: =+S24*$C24 -> 0 | T81: =+T24*$C24 -> 0 | U81: =+U24*$C24 -> 0 | V81: =+V24*$C24 -> 0 | W81: =+W24*$C24 -> 0 | X81: =+X24*$C24 -> 0 | Y81: =+Y24*$C24 -> 0 | Z81: =+Z24*$C24 -> 0
F82: 買掛金支払 | G82: 0 | H82: 0 | I82: 0 | J82: 0 | K82: 0 | L82: 0 | M82: 0 | N82: 0 | O82: 0 | P82: 0 | Q82: 0 | R82: 0 | S82: =+R24*$B24 -> 0 | T82: =+S24*$B24 -> 0 | U82: =+T24*$B24 -> 0 | V82: =+U24*$B24 -> 0 | W82: =+V24*$B24 -> 0 | X82: =+W24*$B24 -> 0 | Y82: =+X24*$B24 -> 0 | Z82: =+Y24*$B24 -> 0
F83: 未払金支払 | G83: 404397 | H83: 618202 | I83: 567923 | J83: 690135 | K83: 570135 | L83: 570135 | M83: 570135 | N83: 503469 | O83: 503469 | P83: 503469 | Q83: 503469 | R83: 503469 | S83: =R34+R55-R84+S40 -> 529919 | T83: =S34+S55-S84+T40 -> 0 | U83: =T34+T55-T84+U40 -> 0 | V83: =U34+U55-U84 -> 0 | W83: =V34+V55-V84 -> 0 | X83: =W34+W55-W84 -> 0 | Y83: =X34+X55-X84 -> 0 | Z83: =Y34+Y55-Y84 -> 0
F84: 現金経費 | S84: =S36+S54+S46+S47+S38+S49+S42+S43+S45+S41+S39+S48+S50+S51+S53 -> 0 | T84: =T36+T54+T46+T47+T38+T49+T42+T43+T45+T41+T39+T48+T50+T51+T53 -> 0 | U84: =U36+U54+U46+U47+U38+U49+U42+U43+U45+U41+U39+U48+U50+U51+U53 -> 0 | V84: =V36+V54+V46+V47+V38+V49+V42+V43+V45+V41+V39+V48+V50+V51+V53 -> 0 | W84: =W36+W54+W46+W47+W38+W49+W42+W43+W45+W41+W39+W48+W50+W51+W53 -> 0 | X84: =X36+X54+X46+X47+X38+X49+X42+X43+X45+X41+X39+X48+X50+X51+X53 -> 0 | Y84: =Y36+Y54+Y46+Y47+Y38+Y49+Y42+Y43+Y45+Y41+Y39+Y48+Y50+Y51+Y53 -> 0 | Z84: =Z36+Z54+Z46+Z47+Z38+Z49+Z42+Z43+Z45+Z41+Z39+Z48+Z50+Z51+Z53 -> 0
F85: 支払利息 | S85: =+S59 -> 0 | T85: =+T59 -> 0 | U85: =+U59 -> 0 | V85: =+V59 -> 0 | W85: =+W59 -> 0 | X85: =+X59 -> 0 | Y85: =+Y59 -> 0 | Z85: =+Z59 -> 0
F86: ②合計 | G86: =SUM(G81:G85) -> 404397 | H86: =SUM(H81:H85) -> 618202 | I86: =SUM(I81:I85) -> 567923 | J86: =SUM(J81:J85) -> 690135 | K86: =SUM(K81:K85) -> 570135 | L86: =SUM(L81:L85) -> 570135 | M86: =SUM(M81:M85) -> 570135 | N86: =SUM(N81:N85) -> 503469 | ... Z86: =SUM(Z81:Z85) -> 0
E87: B.営業収支(①-②) | G87: =+G80-G86 -> 795603 | H87: =+H80-H86 -> -506420 | I87: =+I80-I86 -> -8081 | J87: =+J80-J86 -> -68253.721 | K87: =+K80-K86 -> 6365.2984 | L87: =+L80-L86 -> -16325.192 | M87: =+M80-M86 -> 6365.2984 | N87: =+N80-N86 -> 102721.79 | ... Z87: =+Z80-Z86 -> 0
E88: 財務収入 | F88: 短期借入
F89: 長期借入
F90: 助成金
F91: 保険積立金
F92: 立替金回収
F93: ③合計 | G93: =SUM(G88:G92) -> 0 | H93: =SUM(H88:H92) -> 0 | I93: =SUM(I88:I92) -> 0 | J93: =SUM(J88:J92) -> 0 | K93: =SUM(K88:K92) -> 0 | L93: =SUM(L88:L92) -> 0 | M93: =SUM(M88:M92) -> 0 | N93: =SUM(N88:N92) -> 0 | ... Z93: =SUM(Z88:Z92) -> 0
E94: 財務支出 | F94: 投資・貸付 | G94: 500000 | S94: 500000 | BL94: 670272
F95: 消費税納付・還付 | H95: 135600 | T95: 135600 | AF95: 526900 | AQ95: 18762 | AR95: 418000 | BD95: 133000
F96: 法人税等 | H96: 70000 | T96: 70000 | AF96: 70000 | AR96: 132800 | BD96: 217700 | CA96: 114185 | CB96: 94185 | CC96: 94775 | CD96: 40300
F97: 納税 | T97: 227 | U97: 230 | V97: 246 | W97: 157 | AM97: 20460 | AN97: 6050 | AO97: 8030 | AP97: 5000 | AQ97: 5000 | AR97: 5000 | AV97: 23100 | AW97: 10210 | BI97: 10210 | BO97: 48480 | BS97: 20000 | BT97: 76300 | BU97: 64385 | BV97: 20000 | CB97: 227700 | CC97: 111600 | CD97: 214882
F98: 消費税 | AI98: -84194 | AM98: 3991 | AO98: 9006 | AP98: 9140 | AR98: 43955 | AS98: 31770 | AV98: 5099 | AW98: 800 | AX98: 9154 | AY98: -2355 | AZ98: -19236 | BA98: -6657 | BB98: -2989 | BC98: 13508 | BD98: 4869 | BE98: 11178 | BG98: -4169 | BH98: -4524 | BK98: 3140 | BL98: -59211 | BM98: 30160 | BO98: 17735 | BP98: 32372 | BQ98: 15000 | BR98: 60550 | BS98: 15000 | BT98: -12350 | BU98: 11181 | BV98: 15000 | BW98: 36238 | CA98: 20018.54 | CB98: -12538 | CC98: 20389 | CD98: -37028 | CE98: 24000 | CF98: 24000 | CG98: 24000 | CH98: 24000 | CI98: 24000 | CJ98: 24000 | CK98: 24000 | CL98: 24000
AZ99: 2780640 | BF99: 3000000
F100: 長期借入金返済 | G100: 0 | H100: 0 | I100: 0 | J100: 0 | K100: 167000 | L100: 167000 | M100: 167000 | N100: 167000 | O100: 167000 | P100: 167000 | Q100: 167000 | R100: 167000 | S100: 1156 | T100: 1156 | U100: 1156 | V100: 1156 | W100: 1156 | AA100: 0 | AB100: 0 | AC100: 0 | AD100: 0 | AE100: 0 | AF100: 0 | AG100: 0 | AH100: 0 | AI100: 0 | AJ100: 0 | AK100: 0 | AL100: 0 | AM100: 0 | AN100: 0 | AO100: 0 | AP100: 0 | AQ100: 0 | AR100: 0 | AS100: 0 | AT100: 0 | AU100: 0 | AV100: 0 | AW100: 0 | AX100: 0 | AY100: 0 | AZ100: 0 | BA100: 0 | BB100: 0 | BC100: 0 | BD100: 0 | BE100: 0 | BF100: 0 | BG100: 0 | BH100: 0 | BI100: 0 | BJ100: 0 | BK100: 0 | BL100: 0 | BM100: 0 | BN100: 0 | BO100: 0 | BP100: 0 | BQ100: 0 | BR100: 0 | BS100: 0 | BT100: 0 | BU100: 0 | BV100: 0 | BW100: 0 | BX100: 0 | BY100: 0 | BZ100: 0 | CA100: 0 | CB100: 0 | CC100: 0 | CD100: 0 | CE100: 0 | CF100: 0 | CG100: 0 | CH100: 0 | CI100: 0 | CJ100: 0 | CK100: 0 | CL100: 0
F101: その他 | S101: 390 | T101: 186 | U101: 190 | V101: 337 | W101: 41 | AL101: 100000
F102: ④合計 | G102: =SUM(G94:G101) -> 500000 | H102: =SUM(H94:H101) -> 205600 | I102: =SUM(I94:I101) -> 0 | J102: =SUM(J94:J101) -> 0 | K102: =SUM(K94:K101) -> 167000 | L102: =SUM(L94:L101) -> 167000 | M102: =SUM(M94:M101) -> 167000 | N102: =SUM(N94:N101) -> 167000 | ... Z102: =SUM(Z94:Z101) -> 0
E103: C.財務収支(③-④) | G103: =+G93-G102 -> -500000 | H103: =+H93-H102 -> -205600 | I103: =+I93-I102 -> 0 | J103: =+J93-J102 -> 0 | K103: =+K93-K102 -> -167000 | L103: =+L93-L102 -> -167000 | M103: =+M93-M102 -> -167000 | N103: =+N93-N102 -> -167000 | ... Z103: =+Z93-Z102 -> 0
E104: D.月次資金収支(B+C) | G104: =+G87+G103 -> 295603 | H104: =+H87+H103 -> -712020 | I104: =+I87+I103 -> -8081 | J104: =+J87+J103 -> -68253.721 | K104: =+K87+K103 -> -160634.7 | L104: =+L87+L103 -> -183325.19 | M104: =+M87+M103 -> -160634.7 | N104: =+N87+N103 -> -64278.211 | ... Z104: =+Z87+Z103 -> 0
E105: E.翌月繰越金(A+D) | G105: =+G76+G104 -> 2644592 | H105: =+H76+H104 -> 1932572 | I105: =+I76+I104 -> 1924491 | J105: =+J76+J104 -> 1856237.3 | K105: =+K76+K104 -> 1695602.6 | L105: =+L76+L104 -> 1512277.4 | M105: =+M76+M104 -> 1351642.7 | N105: =+N76+N104 -> 1287364.5 | ... Z105: =+Z76+Z104 -> -241051.37
E106: 長期償還資源 営業利益+減価償却費-返済 | S106: =S57+S40-S100 -> -1156 | T106: =T57+T40-T100 -> -1156 | U106: =U57+U40-U100 -> -1156 | V106: =V57+V40-V100 -> -1156 | W106: =W57+W40-W100 -> -1156 | X106: =X57+X40-X100 -> 0 | Y106: =Y57+Y40-Y100 -> 0 | Z106: =Z57+Z40-Z100 -> 0
F107: 実際
F108: 差額 | G108: =G105-G107 -> 2644592 | H108: =H105-H107 -> 1932572 | I108: =I105-I107 -> 1924491 | J108: =J105-J107 -> 1856237.3 | K108: =K105-K107 -> 1695602.6 | L108: =L105-L107 -> 1512277.4 | M108: =M105-M107 -> 1351642.7 | N108: =N105-N107 -> 1287364.5 | ... Z108: =Z105-Z107 -> -241051.37
B110: 長期借入金 | D110: 残高 | F110: 月額
B111: ㈱ｅｓエンター | C111: 毎月金額 | D111: 期首残高 | E111: 終了年月 | F111: 備考 | G111: =IF($E111>=G$110,$F111,0) -> 備考 | H111: =IF($E111>=H$110,$F111,0) -> 備考 | I111: =IF($E111>=I$110,$F111,0) -> 備考 | J111: =IF($E111>=J$110,$F111,0) -> 備考 | K111: =IF($E111>=K$110,$F111,0) -> 備考 | L111: =IF($E111>=L$110,$F111,0) -> 備考 | M111: =IF($E111>=M$110,$F111,0) -> 備考 | N111: =IF($E111>=N$110,$F111,0) -> 備考 | ... Z111: =IF($E111>=Z$110,$F111,0) -> 備考
B113: 日本政策金融公庫③2021/03 | C113: 245000 | D113: 23000000 | E113: 48913 | F113: 2026.02.28開始初回のみ215,000円 | N113: 215000 | O113: 245000 | P113: 245000 | Q113: 245000 | R113: 245000 | S113: 245000 | T113: 245000 | U113: 245000 | V113: 245000 | W113: 245000 | X113: 245000 | Y113: 245000 | Z113: 245000
B114: 北洋銀行① | C114: 239000 | D114: 20000000 | E114: 48852 | F114: 2026.11.02開始 | W114: 239000 | X114: 239000 | Y114: 239000 | Z114: 239000
B115: 北洋銀行② | C115: 239000 | D115: 20000000 | E115: 49018 | F115: 2027.04.15開始
B116: 北洋銀行③ | C116: 715000 | D116: 60000000 | E116: 49025 | F116: 2027.04.22開始
B118: 商工中金 | C118: 235000 | D118: 20000000 | E118: 47938 | F118: R6.3/31開始 | G118: 235000 | H118: 235000 | I118: 235000 | J118: 235000 | K118: 235000 | L118: 235000 | M118: 235000 | N118: 235000 | O118: 235000 | P118: 235000 | Q118: 235000 | R118: 235000 | S118: 235000 | T118: 235000 | U118: 235000 | V118: 235000 | W118: 235000 | X118: 235000 | Y118: 235000 | Z118: 235000
B120: 合計 | C120: =SUM(C112:C118) -> 1673000 | D120: =SUM(D112:D119) -> 143000000
B124: グループ合計 | F124: 毎月返済額 | G124: =SUM(G126:G136,G112:G119) -> 235000 | H124: =SUM(H126:H136,H112:H119) -> 335000 | I124: =SUM(I126:I136,I112:I119) -> 335000 | J124: =SUM(J126:J136,J112:J119) -> 452000 | K124: =SUM(K126:K136,K112:K119) -> 452000 | L124: =SUM(L126:L136,L112:L119) -> 452000 | M124: =SUM(M126:M136,M112:M119) -> 536000 | N124: =SUM(N126:N136,N112:N119) -> 751000 | ... Z124: =SUM(Z126:Z136,Z112:Z119) -> 1020000
...
