Workbook

Sheet 月次BS
B1: 勘定科目 | C1: 期首残 | D1: 7月 | E1: 8月 | F1: 9月 | G1: 10月 | H1: 11月 | I1: 12月 | J1: 1月 | K1: 2月 | L1: 3 | M1: 4 | N1: 5月 | O1: 6月
A2: 資産の部
A3: 流動資産
A4: 現金及び預金
B5: 現金 | C5: 2866900 | D5: 1880600
B6: 普通預金 | C6: 31678389 | D6: 33834099
B7: 小口現金 | C7: 356376 | D7: 340879
A8: 現金及び預金合計 | C8: 34901665 | D8: 36055578
A9: 売上債権
B10: 売掛金 | C10: 9122840 | D10: 8860846
A11: 売上債権合計 | C11: =+C10 -> 9122840 | D11: 8860846
A12: 有価証券
A13: 有価証券合計 | C13: 0 | D13: 0
A14: 棚卸資産
B15: 商品 | C15: 1354257 | D15: 1354396
B16: 貯蔵品 | C16: 99474 | D16: 99474
A17: 棚卸資産合計 | C17: 1453731 | D17: 1453870
A18: その他流動資産
B19: 前払費用 | C19: 1742739 | D19: 1742739
B20: 立替金 | C20: 877070 | D20: 874843
B21: 未収入金 | C21: 0 | D21: 0
B22: 仮払金 | C22: 0 | D22: 3946
B23: 仮払消費税 | C23: 0 | D23: 477821
A24: その他流動資産合計 | C24: 2619809 | D24: 3099349
A25: 流動資産合計 | C25: 48098045 | D25: 49469643
A26: 固定資産
A27: 有形固定資産
B28: 建物 | C28: 14805643 | D28: 14805643
B29: 附属設備 | C29: 26376787 | D29: 26376787
B30: 工具器具備品 | C30: 4922553 | D30: 4922553
B31: 一括償却資産 | C31: 263159 | D31: 263159
B32: 減価償却累計額 | C32: 0 | D32: 601448
A33: 有形固定資産合計 | C33: 46368142 | D33: 46969590
A34: 無形固定資産
B35: ソフトウェア | C35: 2553731 | D35: 1205374
A36: 無形固定資産合計 | C36: 2553731 | D36: 1205374
A37: 投資その他の資産
B38: 出資金 | C38: 8825960 | D38: 8825960
B39: 長期前払費用 | C39: 897030 | D39: 897030
B40: 敷金 | C40: 2126486 | D40: 2126486
B41: 保険積立金 | C41: 13367174 | D41: 13370229
A42: 投資その他の資産合計 | C42: 25216650 | D42: 25219705
A43: 固定資産合計 | C43: 74138523 | D43: 73394669
A44: 繰延資産
A45: 繰延資産合計 | C45: 0 | D45: 0
A46: 諸口
A47: 諸口合計 | D47: 0
A48: 資産の部合計 | C48: 122236568 | D48: 122864312
A49: 負債の部
A50: 流動負債
A51: 仕入債務
B52: 買掛金 | C52: 1861886 | D52: 2166409
A53: 仕入債務合計 | C53: 1861886 | D53: 2166409
A54: その他流動負債
B55: 未払金 | C55: 1899214 | D55: 1845934
B56: 未払費用 | C56: 726789 | D56: 717131
B57: 前受金 | C57: 22200 | D57: 22200
B58: 預り金 | C58: 544601 | D58: 265023
B59: 仮受金 | C59: 7540 | D59: 31817
B60: 未払消費税 | C60: 1393800 | D60: 1393800
B61: 未払法人税等 | C61: 70000 | D61: 70000
B62: 仮受消費税 | C62: 0 | D62: 853798
B63: 一年以内返済長期借入金 | C63: 2820000 | D63: 2820000
A64: その他流動負債合計 | C64: 7484144 | D64: 8019703
A65: 流動負債合計 | C65: 9346030 | D65: 10186112
A66: 固定負債
B67: 長期借入金 | C67: 132405000 | D67: 131925000
A68: 固定負債合計 | C68: 132405000 | D68: 131925000
A69: 負債の部合計 | C69: 141751030 | D69: 142111112
A70: 純資産の部
A71: 株主資本
A72: 資本金
B73: 資本金 | C73: 5000000 | D73: 5000000
A74: 資本金合計 | C74: 5000000 | D74: 5000000
A75: 新株式申込証拠金
A76: 新株式申込証拠金合計 | C76: 0 | D76: 0
A77: 資本剰余金
A78: 資本剰余金合計 | C78: 0 | D78: 0
A79: 利益剰余金
A80: 繰越利益剰余金 | C80: -24514462 | D80: -24246800
A81: （うち当期純利益） | C81: 0 | D81: 267662
A82: 利益剰余金合計 | C82: -24514462 | D82: -24246800
A83: 自己株式
A84: 自己株式合計 | C84: 0 | D84: 0
A85: 自己株式申込証拠金
A86: 自己株式申込証拠金合計 | C86: 0 | D86: 0
A87: 株主資本合計 | C87: -19514462 | D87: -19246800
A88: 評価・換算差額等
A89: 評価・換算差額等合計 | C89: 0 | D89: 0
A90: 新株予約権
A91: 新株予約権合計 | C91: 0 | D91: 0
A92: 純資産の部合計 | C92: -19514462 | D92: -19246800
A93: 負債・純資産の部合計 | C93: 122236568 | D93: 122864312
B94: [B/S CK] | C94: =IF(C93<>0,+IF(C48=C93,"OK",C48-C93),"") -> OK | D94: =IF(D93<>0,+IF(D48=D93,"OK",D48-D93),"") -> OK | E94: =IF(E93<>0,+IF(E48=E93,"OK",E48-E93),"") | F94: =IF(F93<>0,+IF(F48=F93,"OK",F48-F93),"") | G94: =IF(G93<>0,+IF(G48=G93,"OK",G48-G93),"") | H94: =IF(H93<>0,+IF(H48=H93,"OK",H48-H93),"") | I94: =IF(I93<>0,+IF(I48=I93,"OK",I48-I93),"") | J94: =IF(J93<>0,+IF(J48=J93,"OK",J48-J93),"") | ... O94: =IF(O93<>0,+IF(O48=O93,"OK",O48-O93),"")

Sheet BS千円
B1: 勘定科目 | C1: 期首残 | D1: 7月 | E1: 8月 | F1: =+月次BS!F1 -> 9月 | G1: =+月次BS!G1 -> 10月 | H1: =+月次BS!H1 -> 11月 | I1: =+月次BS!I1 -> 12月 | J1: =+月次BS!J1 -> 1月 | K1: =+月次BS!K1 -> 2月 | L1: =+月次BS!L1 -> 3 | M1: =+月次BS!M1 -> 4 | ... O1: =+月次BS!O1 -> 6月
A2: =+月次BS!A2 -> 資産の部
A3: =+月次BS!A3 -> 流動資産
A4: =+月次BS!A4 -> 現金及び預金
A5: =+月次BS!A5 -> 0 | B5: =+月次BS!B5 -> 現金 | C5: =+月次BS!C5/1000 -> 2866.9 | D5: =+月次BS!D5/1000 -> 1880.6 | E5: =+月次BS!E5/1000 -> 0 | F5: =+月次BS!F5/1000 -> 0 | G5: =+月次BS!G5/1000 -> 0 | H5: =+月次BS!H5/1000 -> 0 | I5: =+月次BS!I5/1000 -> 0 | J5: =+月次BS!J5/1000 -> 0 | ... O5: =+月次BS!O5/1000 -> 0
A6: =+月次BS!A6 -> 0 | B6: =+月次BS!B6 -> 普通預金 | C6: =+月次BS!C6/1000 -> 31678.389 | D6: =+月次BS!D6/1000 -> 33834.099 | E6: =+月次BS!E6/1000 -> 0 | F6: =+月次BS!F6/1000 -> 0 | G6: =+月次BS!G6/1000 -> 0 | H6: =+月次BS!H6/1000 -> 0 | I6: =+月次BS!I6/1000 -> 0 | J6: =+月次BS!J6/1000 -> 0 | ... O6: =+月次BS!O6/1000 -> 0
A7: =+月次BS!A7 -> 0 | B7: =+月次BS!B7 -> 小口現金 | C7: =+月次BS!C7/1000 -> 356.376 | D7: =+月次BS!D7/1000 -> 340.879 | E7: =+月次BS!E7/1000 -> 0 | F7: =+月次BS!F7/1000 -> 0 | G7: =+月次BS!G7/1000 -> 0 | H7: =+月次BS!H7/1000 -> 0 | I7: =+月次BS!I7/1000 -> 0 | J7: =+月次BS!J7/1000 -> 0 | ... O7: =+月次BS!O7/1000 -> 0
A8: =+月次BS!A8 -> 現金及び預金合計 | B8: =+月次BS!B8 -> 0 | C8: =+月次BS!C8/1000 -> 34901.665 | D8: =+月次BS!D8/1000 -> 36055.578 | E8: =+月次BS!E8/1000 -> 0 | F8: =+月次BS!F8/1000 -> 0 | G8: =+月次BS!G8/1000 -> 0 | H8: =+月次BS!H8/1000 -> 0 | I8: =+月次BS!I8/1000 -> 0 | J8: =+月次BS!J8/1000 -> 0 | ... O8: =+月次BS!O8/1000 -> 0
A9: =+月次BS!A9 -> 売上債権 | B9: =+月次BS!B9 -> 0 | C9: =+月次BS!C9/1000 -> 0 | D9: =+月次BS!D9/1000 -> 0 | E9: =+月次BS!E9/1000 -> 0 | F9: =+月次BS!F9/1000 -> 0 | G9: =+月次BS!G9/1000 -> 0 | H9: =+月次BS!H9/1000 -> 0 | I9: =+月次BS!I9/1000 -> 0 | J9: =+月次BS!J9/1000 -> 0 | ... O9: =+月次BS!O9/1000 -> 0
A10: =+月次BS!A10 -> 0 | B10: =+月次BS!B10 -> 売掛金 | C10: =+月次BS!C10/1000 -> 9122.84 | D10: =+月次BS!D10/1000 -> 8860.846 | E10: =+月次BS!E10/1000 -> 0 | F10: =+月次BS!F10/1000 -> 0 | G10: =+月次BS!G10/1000 -> 0 | H10: =+月次BS!H10/1000 -> 0 | I10: =+月次BS!I10/1000 -> 0 | J10: =+月次BS!J10/1000 -> 0 | ... O10: =+月次BS!O10/1000 -> 0
A11: =+月次BS!A11 -> 売上債権合計 | B11: =+月次BS!B11 -> 0 | C11: =+月次BS!C11/1000 -> 9122.84 | D11: =+月次BS!D11/1000 -> 8860.846 | E11: =+月次BS!E11/1000 -> 0 | F11: =+月次BS!F11/1000 -> 0 | G11: =+月次BS!G11/1000 -> 0 | H11: =+月次BS!H11/1000 -> 0 | I11: =+月次BS!I11/1000 -> 0 | J11: =+月次BS!J11/1000 -> 0 | ... O11: =+月次BS!O11/1000 -> 0
A12: =+月次BS!A12 -> 有価証券 | B12: =+月次BS!B12 -> 0 | C12: =+月次BS!C12/1000 -> 0 | D12: =+月次BS!D12/1000 -> 0 | E12: =+月次BS!E12/1000 -> 0 | F12: =+月次BS!F12/1000 -> 0 | G12: =+月次BS!G12/1000 -> 0 | H12: =+月次BS!H12/1000 -> 0 | I12: =+月次BS!I12/1000 -> 0 | J12: =+月次BS!J12/1000 -> 0 | ... O12: =+月次BS!O12/1000 -> 0
A13: =+月次BS!A13 -> 有価証券合計 | B13: =+月次BS!B13 -> 0 | C13: =+月次BS!C13/1000 -> 0 | D13: =+月次BS!D13/1000 -> 0 | E13: =+月次BS!E13/1000 -> 0 | F13: =+月次BS!F13/1000 -> 0 | G13: =+月次BS!G13/1000 -> 0 | H13: =+月次BS!H13/1000 -> 0 | I13: =+月次BS!I13/1000 -> 0 | J13: =+月次BS!J13/1000 -> 0 | ... O13: =+月次BS!O13/1000 -> 0
A14: =+月次BS!A14 -> 棚卸資産 | B14: =+月次BS!B14 -> 0 | C14: =+月次BS!C14/1000 -> 0 | D14: =+月次BS!D14/1000 -> 0 | E14: =+月次BS!E14/1000 -> 0 | F14: =+月次BS!F14/1000 -> 0 | G14: =+月次BS!G14/1000 -> 0 | H14: =+月次BS!H14/1000 -> 0 | I14: =+月次BS!I14/1000 -> 0 | J14: =+月次BS!J14/1000 -> 0 | ... O14: =+月次BS!O14/1000 -> 0
A15: =+月次BS!A15 -> 0 | B15: =+月次BS!B15 -> 商品 | C15: =+月次BS!C15/1000 -> 1354.257 | D15: =+月次BS!D15/1000 -> 1354.396 | E15: =+月次BS!E15/1000 -> 0 | F15: =+月次BS!F15/1000 -> 0 | G15: =+月次BS!G15/1000 -> 0 | H15: =+月次BS!H15/1000 -> 0 | I15: =+月次BS!I15/1000 -> 0 | J15: =+月次BS!J15/1000 -> 0 | ... O15: =+月次BS!O15/1000 -> 0
A16: =+月次BS!A16 -> 0 | B16: =+月次BS!B16 -> 貯蔵品 | C16: =+月次BS!C16/1000 -> 99.474 | D16: =+月次BS!D16/1000 -> 99.474 | E16: =+月次BS!E16/1000 -> 0 | F16: =+月次BS!F16/1000 -> 0 | G16: =+月次BS!G16/1000 -> 0 | H16: =+月次BS!H16/1000 -> 0 | I16: =+月次BS!I16/1000 -> 0 | J16: =+月次BS!J16/1000 -> 0 | ... O16: =+月次BS!O16/1000 -> 0
... A93: =+月次BS!A93 -> 負債・純資産の部合計 | B93: =+月次BS!B93 -> 0 | C93: =+月次BS!C93/1000 -> 122236.57 | D93: =+月次BS!D93/1000 -> 122864.31 | E93: =+月次BS!E93/1000 -> 0 | F93: =+月次BS!F93/1000 -> 0 | G93: =+月次BS!G93/1000 -> 0 | H93: =+月次BS!H93/1000 -> 0 | I93: =+月次BS!I93/1000 -> 0 | J93: =+月次BS!J93/1000 -> 0 | ... O93: =+月次BS!O93/1000 -> 0
A94: =+月次BS!A95 -> 0 | B94: =+月次BS!B95 -> 0 | C94: =+月次BS!C95/1000 -> 0 | D94: =+月次BS!D95/1000 -> 0 | E94: =+月次BS!E95/1000 -> 0 | F94: =+月次BS!F95/1000 -> 0 | G94: =+月次BS!G95/1000 -> 0 | H94: =+月次BS!H95/1000 -> 0 | I94: =+月次BS!I95/1000 -> 0 | J94: =+月次BS!J95/1000 -> 0 | ... O94: =+月次BS!O95/1000 -> 0
A95: =+月次BS!A96 -> 0 | B95: 買掛未払債務 | C95: =+C52+C55+C56 -> 4487.889 | D95: =+D52+D55+D56 -> 4729.474 | E95: =+E52+E55+E56 -> 0 | F95: =+F52+F55+F56 -> 0 | G95: =+G52+G55+G56 -> 0 | H95: =+H52+H55+H56 -> 0 | I95: =+I52+I55+I56 -> 0 | J95: =+J52+J55+J56 -> 0 | ... O95: =+O52+O55+O56 -> 0
A96: =+月次BS!A97 -> 0 | B96: その他流動負債 | C96: =+C57+C58+C59+C62 -> 574.341 | D96: =+D57+D58+D59+D62 -> 1172.838 | E96: =+E57+E58+E59+E62 -> 0 | F96: =+F57+F58+F59+F62 -> 0 | G96: =+G57+G58+G59+G62 -> 0 | H96: =+H57+H58+H59+H62 -> 0 | I96: =+I57+I58+I59+I62 -> 0 | J96: =+J57+J58+J59+J62 -> 0 | ... O96: =+O57+O58+O59+O62 -> 0
A97: =+月次BS!A98 -> 0 | B97: 有形・無形固定資産 | C97: =+C33+C36 -> 48921.873 | D97: =+D33+D36 -> 48174.964 | E97: =+E33+E36 -> 0 | F97: =+F33+F36 -> 0 | G97: =+G33+G36 -> 0 | H97: =+H33+H36 -> 0 | I97: =+I33+I36 -> 0 | J97: =+J33+J36 -> 0 | ... O97: =+O33+O36 -> 0
A98: =+月次BS!A99 -> 0 | B98: 長期借入金 | C98: =+C63+C67 -> 135225 | D98: =+D63+D67 -> 134745 | E98: =+E63+E67 -> 0 | F98: =+F63+F67 -> 0 | G98: =+G63+G67 -> 0 | H98: =+H63+H67 -> 0 | I98: =+I63+I67 -> 0 | J98: =+J63+J67 -> 0 | ... O98: =+O63+O67 -> 0
A99: =+月次BS!A100 -> 0 | B99: =+月次BS!B100 -> 0 | C99: =+月次BS!C100/1000 -> 0 | D99: =+月次BS!D100/1000 -> 0 | E99: =+月次BS!E100/1000 -> 0 | F99: =+月次BS!F100/1000 -> 0 | G99: =+月次BS!G100/1000 -> 0 | H99: =+月次BS!H100/1000 -> 0 | I99: =+月次BS!I100/1000 -> 0 | J99: =+月次BS!J100/1000 -> 0 | ... O99: =+月次BS!O100/1000 -> 0
A100: =+月次BS!A101 -> 0 | B100: =+月次BS!B101 -> 0 | C100: =+月次BS!C101/1000 -> 0 | D100: =+月次BS!D101/1000 -> 0 | E100: =+月次BS!E101/1000 -> 0 | F100: =+月次BS!F101/1000 -> 0 | G100: =+月次BS!G101/1000 -> 0 | H100: =+月次BS!H101/1000 -> 0 | I100: =+月次BS!I101/1000 -> 0 | J100: =+月次BS!J101/1000 -> 0 | ... O100: =+月次BS!O101/1000 -> 0
A101: =+月次BS!A102 -> 0 | B101: =+月次BS!B102 -> 0 | C101: =+月次BS!C102/1000 -> 0 | D101: =+月次BS!D102/1000 -> 0 | E101: =+月次BS!E102/1000 -> 0 | F101: =+月次BS!F102/1000 -> 0 | G101: =+月次BS!G102/1000 -> 0 | H101: =+月次BS!H102/1000 -> 0 | I101: =+月次BS!I102/1000 -> 0 | J101: =+月次BS!J102/1000 -> 0 | ... O101: =+月次BS!O102/1000 -> 0
A102: =+月次BS!A103 -> 0 | B102: =+月次BS!B103 -> 0 | C102: =+月次BS!C103/1000 -> 0 | D102: =+月次BS!D103/1000 -> 0 | E102: =+月次BS!E103/1000 -> 0 | F102: =+月次BS!F103/1000 -> 0 | G102: =+月次BS!G103/1000 -> 0 | H102: =+月次BS!H103/1000 -> 0 | I102: =+月次BS!I103/1000 -> 0 | J102: =+月次BS!J103/1000 -> 0 | ... O102: =+月次BS!O103/1000 -> 0
A103: =+月次BS!A104 -> 0 | B103: =+月次BS!B104 -> 0 | C103: =+月次BS!C104/1000 -> 0 | D103: =+月次BS!D104/1000 -> 0 | E103: =+月次BS!E104/1000 -> 0 | F103: =+月次BS!F104/1000 -> 0 | G103: =+月次BS!G104/1000 -> 0 | H103: =+月次BS!H104/1000 -> 0 | I103: =+月次BS!I104/1000 -> 0 | J103: =+月次BS!J104/1000 -> 0 | ... O103: =+月次BS!O104/1000 -> 0

Sheet 月次PL
B1: 勘定科目 | C1: =+月次BS!D1 -> 7月 | D1: =+月次BS!E1 -> 8月 | E1: =+月次BS!F1 -> 9月 | F1: =+月次BS!G1 -> 10月 | G1: =+月次BS!H1 -> 11月 | H1: =+月次BS!I1 -> 12月 | I1: =+月次BS!J1 -> 1月 | J1: =+月次BS!K1 -> 2月 | ... N1: =+月次BS!O1 -> 6月 | O1: 累計
A2: 売上高
B3: レストラン売上 | C3: 7101672 | O3: =SUM(C3:N3) -> 7101672
B4: デリバリー売上 | O4: =SUM(C4:N4) -> 0
B5: 売上高 | C5: 883931 | O5: =SUM(C5:N5) -> 883931
B6: 村売上 | C6: 645682 | O6: =SUM(C6:N6) -> 645682
B7: その他売上 | O7: =SUM(C7:N7) -> 0
A8: 売上高合計 | C8: =+SUM(C3:C7) -> 8631285 | D8: =+SUM(D3:D7) -> 0 | E8: =+SUM(E3:E7) -> 0 | F8: =+SUM(F3:F7) -> 0 | G8: =+SUM(G3:G7) -> 0 | H8: =+SUM(H3:H7) -> 0 | I8: =+SUM(I3:I7) -> 0 | J8: =+SUM(J3:J7) -> 0 | ... N8: =+SUM(N3:N7) -> 0 | O8: =SUM(C8:N8) -> 8631285
A9: 売上原価 | O9: =SUM(C9:N9) -> 0
B10: 期首商品棚卸高 | C10: 1323276 | O10: =SUM(C10:N10) -> 1323276
B11: 飲料仕入 | C11: 1027204 | O11: =SUM(C11:N11) -> 1027204
B12: 食材仕入 | C12: 994211 | O12: =SUM(C12:N12) -> 994211
B13: 仕入値引 | O13: =SUM(C13:N13) -> 0
B14: 期末商品棚卸高 | C14: 1323415 | O14: =SUM(C14:N14) -> 1323415
A15: 売上原価 | C15: =+C10+C11+C12-C13-C14 -> 2021276 | D15: =+D10+D11+D12-D13-D14 -> 0 | E15: =+E10+E11+E12-E13-E14 -> 0 | F15: =+F10+F11+F12-F13-F14 -> 0 | G15: =+G10+G11+G12-G13-G14 -> 0 | H15: =+H10+H11+H12-H13-H14 -> 0 | I15: =+I10+I11+I12-I13-I14 -> 0 | J15: =+J10+J11+J12-J13-J14 -> 0 | ... N15: =+N10+N11+N12-N13-N14 -> 0 | O15: =SUM(C15:N15) -> 2021276
A16: 売上総利益 | C16: =+C8-C15 -> 6610009 | D16: =+D8-D15 -> 0 | E16: =+E8-E15 -> 0 | F16: =+F8-F15 -> 0 | G16: =+G8-G15 -> 0 | H16: =+H8-H15 -> 0 | I16: =+I8-I15 -> 0 | J16: =+J8-J15 -> 0 | ... N16: =+N8-N15 -> 0 | O16: =SUM(C16:N16) -> 6610009
A17: 販売費及び一般管理費 | O17: =SUM(C17:N17) -> 0
B18: 役員報酬 | C18: 500000 | O18: =SUM(C18:N18) -> 500000
B19: 給料賃金 | C19: 350000 | O19: =SUM(C19:N19) -> 350000
B20: 賞与 | O20: =SUM(C20:N20) -> 0
B21: 雑給 | C21: 1055055 | O21: =SUM(C21:N21) -> 1055055
B22: 法定福利費 | C22: 219083 | O22: =SUM(C22:N22) -> 219083
B23: 福利厚生費 | O23: =SUM(C23:N23) -> 0
B24: 業務委託費 | C24: 338738 | O24: =SUM(C24:N24) -> 338738
B25: 広告宣伝費 | C25: 124456 | O25: =SUM(C25:N25) -> 124456
B26: 接待交際費 | O26: =SUM(C26:N26) -> 0
B27: 旅費交通費 | C27: 41261 | O27: =SUM(C27:N27) -> 41261
B28: 通信費 | C28: 62422 | O28: =SUM(C28:N28) -> 62422
B29: 水道光熱費 | C29: 659468 | O29: =SUM(C29:N29) -> 659468
B30: 修繕費 | O30: =SUM(C30:N30) -> 0
B31: 消耗品費 | C31: 207018 | O31: =SUM(C31:N31) -> 207018
B32: リース料 | C32: 49700 | O32: =SUM(C32:N32) -> 49700
B33: 地代家賃 | C33: 1295661 | O33: =SUM(C33:N33) -> 1295661
B34: 賃借料 | C34: 30000 | O34: =SUM(C34:N34) -> 30000
B35: 保険料 | C35: 28375 | O35: =SUM(C35:N35) -> 28375
B36: 租税公課 | C36: 124000 | O36: =SUM(C36:N36) -> 124000
B37: 支払手数料 | C37: 208468 | O37: =SUM(C37:N37) -> 208468
B38: 会議費 | C38: 7273 | O38: =SUM(C38:N38) -> 7273
B39: 新聞図書費 | O39: =SUM(C39:N39) -> 0
B40: 減価償却費 | C40: 749954 | O40: =SUM(C40:N40) -> 749954
B41: 雑費 | C41: 74929 | O41: =SUM(C41:N41) -> 74929
B42: 管理諸費 | C42: 70000 | O42: =SUM(C42:N42) -> 70000
B43: 開発費 | O43: =SUM(C43:N43) -> 0
A44: 販売費及び一般管理費合計 | C44: =+SUM(C18:C43) -> 6195861 | D44: =+SUM(D18:D43) -> 0 | E44: =+SUM(E18:E43) -> 0 | F44: =+SUM(F18:F43) -> 0 | G44: =+SUM(G18:G43) -> 0 | H44: =+SUM(H18:H43) -> 0 | I44: =+SUM(I18:I43) -> 0 | J44: =+SUM(J18:J43) -> 0 | ... N44: =+SUM(N18:N43) -> 0 | O44: =SUM(C44:N44) -> 6195861
A45: 営業利益 | C45: =+C16-C44 -> 414148 | D45: =+D16-D44 -> 0 | E45: =+E16-E44 -> 0 | F45: =+F16-F44 -> 0 | G45: =+G16-G44 -> 0 | H45: =+H16-H44 -> 0 | I45: =+I16-I44 -> 0 | J45: =+J16-J44 -> 0 | ... N45: =+N16-N44 -> 0 | O45: =SUM(C45:N45) -> 414148
A46: 営業外収益 | O46: =SUM(C46:N46) -> 0
B47: 受取利息 | O47: =SUM(C47:N47) -> 0
B48: 受取配当金 | O48: =SUM(C48:N48) -> 0
B49: 雑収入 | O49: =SUM(C49:N49) -> 0
A50: 営業外収益合計 | O50: =SUM(C50:N50) -> 0
A51: 営業外費用 | O51: =SUM(C51:N51) -> 0
B52: 支払利息 | C52: 146486 | O52: =SUM(C52:N52) -> 146486
B53: 雑損失 | O53: =SUM(C53:N53) -> 0
B54: 補助事業費 | O54: =SUM(C54:N54) -> 0
A55: 営業外費用合計 | C55: 146486 | O55: =SUM(C55:N55) -> 146486
A56: 経常利益 | C56: =+C45+C50-C55 -> 267662 | D56: =+D45+D50-D55 -> 0 | E56: =+E45+E50-E55 -> 0 | F56: =+F45+F50-F55 -> 0 | G56: =+G45+G50-G55 -> 0 | H56: =+H45+H50-H55 -> 0 | I56: =+I45+I50-I55 -> 0 | J56: =+J45+J50-J55 -> 0 | ... N56: =+N45+N50-N55 -> 0 | O56: =SUM(C56:N56) -> 267662
A57: 特別利益 | O57: =SUM(C57:N57) -> 0
A58: 特別利益合計 | O58: =SUM(C58:N58) -> 0
A59: 特別損失 | O59: =SUM(C59:N59) -> 0
A60: 特別損失合計 | O60: =SUM(C60:N60) -> 0
A61: 当期純損益 | O61: =SUM(C61:N61) -> 0
A62: 税引前当期純利益 | C62: =+C56+C58-C60 -> 267662 | D62: =+D56+D58-D60 -> 0 | E62: =+E56+E58-E60 -> 0 | F62: =+F56+F58-F60 -> 0 | G62: =+G56+G58-G60 -> 0 | H62: =+H56+H58-H60 -> 0 | I62: =+I56+I58-I60 -> 0 | J62: =+J56+J58-J60 -> 0 | ... N62: =+N56+N58-N60 -> 0 | O62: =SUM(C62:N62) -> 267662
B63: 法人税等 | C63: 0 | D63: 0 | E63: 0 | F63: 0 | G63: 0 | H63: 0 | I63: 0 | J63: 0 | O63: =SUM(C63:N63) -> 0
A64: 当期純利益 | C64: =+C62-C63 -> 267662 | D64: =+D62-D63 -> 0 | E64: =+E62-E63 -> 0 | F64: =+F62-F63 -> 0 | G64: =+G62-G63 -> 0 | H64: =+H62-H63 -> 0 | I64: =+I62-I63 -> 0 | J64: =+J62-J63 -> 0 | ... N64: =+N62-N63 -> 0 | O64: =SUM(C64:N64) -> 267662

Sheet PL推移
B2: CK | C2: 売上高 | D2: =IF(D10<>0,IF(D10=月次PL!C8/1000,"OK",PL推移!D10-月次PL!C8/1000),"nd") -> OK | F2: =IF(F10<>0,IF(月次PL!D8/1000=PL推移!F10,"OK",PL推移!F10-月次PL!D8/1000),"nd") -> nd | H2: =IF(H10<>0,IF(月次PL!E8/1000=PL推移!H10,"OK",PL推移!H10-月次PL!E8/1000),"nd") -> nd | J2: =IF(J10<>0,IF(月次PL!F8/1000=PL推移!J10,"OK",PL推移!J10-月次PL!F8/1000),"nd") -> nd | L2: =IF(L10<>0,IF(月次PL!G8/1000=PL推移!L10,"OK",PL推移!L10-月次PL!G8/1000),"nd") -> nd | N2: =IF(N10<>0,IF(月次PL!H8/1000=PL推移!N10,"OK",PL推移!N10-月次PL!H8/1000),"nd") -> nd | P2: =IF(P10<>0,IF(月次PL!I8/1000=PL推移!P10,"OK",PL推移!P10-月次PL!I8/1000),"nd") -> nd | R2: =IF(R10<>0,IF(月次PL!J8/1000=PL推移!R10,"OK",PL推移!R10-月次PL!J8/1000),"nd") -> nd | T2: =IF(T10<>0,IF(月次PL!K8/1000=PL推移!T10,"OK",PL推移!T10-月次PL!K8/1000),"nd") -> 350 | V2: =IF(V10<>0,IF(月次PL!L8/1000=PL推移!V10,"OK",PL推移!V10-月次PL!L8/1000),"nd") -> 8454 | X2: =IF(X10<>0,IF(月次PL!M8/1000=PL推移!X10,"OK",PL推移!X10-月次PL!M8/1000),"nd") -> 9017 | Z2: =IF(Z10<>0,IF(月次PL!N8/1000=PL推移!Z10,"OK",PL推移!Z10-月次PL!N8/1000),"nd") -> 8610
C3: 粗利益 | D3: =IF(D22<>0,IF(D22=月次PL!C16/1000,"OK",PL推移!D22-月次PL!C16/1000),"nd") -> OK | F3: =IF(F22<>0,IF(F22=月次PL!D16/1000,"OK",PL推移!F22-月次PL!D16/1000),"nd") -> nd | H3: =IF(H22<>0,IF(H22=月次PL!E16/1000,"OK",PL推移!H22-月次PL!E16/1000),"nd") -> nd | J3: =IF(J22<>0,IF(J22=月次PL!F16/1000,"OK",PL推移!J22-月次PL!F16/1000),"nd") -> nd | L3: =IF(L22<>0,IF(L22=月次PL!G16/1000,"OK",PL推移!L22-月次PL!G16/1000),"nd") -> nd | N3: =IF(N22<>0,IF(N22=月次PL!H16/1000,"OK",PL推移!N22-月次PL!H16/1000),"nd") -> nd | P3: =IF(P22<>0,IF(P22=月次PL!I16/1000,"OK",PL推移!P22-月次PL!I16/1000),"nd") -> nd | R3: =IF(R22<>0,IF(R22=月次PL!J16/1000,"OK",PL推移!R22-月次PL!J16/1000),"nd") -> nd | T3: =IF(T22<>0,IF(T22=月次PL!K16/1000,"OK",PL推移!T22-月次PL!K16/1000),"nd") -> 350 | V3: =IF(V22<>0,IF(V22=月次PL!L16/1000,"OK",PL推移!V22-月次PL!L16/1000),"nd") -> 8454 | X3: =IF(X22<>0,IF(X22=月次PL!M16/1000,"OK",PL推移!X22-月次PL!M16/1000),"nd") -> 9017 | Z3: =IF(Z22<>0,IF(Z22=月次PL!N16/1000,"OK",PL推移!Z22-月次PL!N16/1000),"nd") -> 8610
C4: 販管費 | D4: =IF(D28<>0,IF(D28=月次PL!C44/1000,"OK",PL推移!D28-月次PL!C44/1000),"nd") -> OK | F4: =IF(F28<>0,IF(F28=月次PL!D44/1000,"OK",PL推移!F28-月次PL!D44/1000),"nd") -> nd | H4: =IF(H28<>0,IF(H28=月次PL!E44/1000,"OK",PL推移!H28-月次PL!E44/1000),"nd") -> nd | J4: =IF(J28<>0,IF(J28=月次PL!F44/1000,"OK",PL推移!J28-月次PL!F44/1000),"nd") -> nd | L4: =IF(L28<>0,IF(L28=月次PL!G44/1000,"OK",PL推移!L28-月次PL!G44/1000),"nd") -> nd | N4: =IF(N28<>0,IF(N28=月次PL!H44/1000,"OK",PL推移!N28-月次PL!H44/1000),"nd") -> nd | P4: =IF(P28<>0,IF(P28=月次PL!I44/1000,"OK",PL推移!P28-月次PL!I44/1000),"nd") -> nd | R4: =IF(R28<>0,IF(R28=月次PL!J44/1000,"OK",PL推移!R28-月次PL!J44/1000),"nd") -> nd | T4: =IF(T28<>0,IF(T28=月次PL!K44/1000,"OK",PL推移!T28-月次PL!K44/1000),"nd") -> nd | V4: =IF(V28<>0,IF(V28=月次PL!L44/1000,"OK",PL推移!V28-月次PL!L44/1000),"nd") -> nd | X4: =IF(X28<>0,IF(X28=月次PL!M44/1000,"OK",PL推移!X28-月次PL!M44/1000),"nd") -> nd | Z4: =IF(Z28<>0,IF(Z28=月次PL!N44/1000,"OK",PL推移!Z28-月次PL!N44/1000),"nd") -> nd
C5: 営業利益 | D5: =IF(D50<>0,IF(D50=月次PL!C45/1000,"OK",PL推移!D50-月次PL!C45/1000),"nd") -> OK | F5: =IF(F50<>0,IF(F50=月次PL!D45/1000,"OK",PL推移!F50-月次PL!D45/1000),"nd") -> nd | H5: =IF(H50<>0,IF(H50=月次PL!E45/1000,"OK",PL推移!H50-月次PL!E45/1000),"nd") -> nd | J5: =IF(J50<>0,IF(J50=月次PL!F45/1000,"OK",PL推移!J50-月次PL!F45/1000),"nd") -> nd | L5: =IF(L50<>0,IF(L50=月次PL!G45/1000,"OK",PL推移!L50-月次PL!G45/1000),"nd") -> nd | N5: =IF(N50<>0,IF(N50=月次PL!H45/1000,"OK",PL推移!N50-月次PL!H45/1000),"nd") -> nd | P5: =IF(P50<>0,IF(P50=月次PL!I45/1000,"OK",PL推移!P50-月次PL!I45/1000),"nd") -> nd | R5: =IF(R50<>0,IF(R50=月次PL!J45/1000,"OK",PL推移!R50-月次PL!J45/1000),"nd") -> nd | T5: =IF(T50<>0,IF(T50=月次PL!K45/1000,"OK",PL推移!T50-月次PL!K45/1000),"nd") -> 350 | V5: =IF(V50<>0,IF(V50=月次PL!L45/1000,"OK",PL推移!V50-月次PL!L45/1000),"nd") -> 8454 | X5: =IF(X50<>0,IF(X50=月次PL!M45/1000,"OK",PL推移!X50-月次PL!M45/1000),"nd") -> 9017 | Z5: =IF(Z50<>0,IF(Z50=月次PL!N45/1000,"OK",PL推移!Z50-月次PL!N45/1000),"nd") -> 8610
C6: 経常利益 | D6: =IF(D54<>0,IF(D54=月次PL!C56/1000,"OK",PL推移!D54-月次PL!C56/1000),"nd") -> OK | F6: =IF(F54<>0,IF(F54=月次PL!D56/1000,"OK",PL推移!F54-月次PL!D56/1000),"nd") -> nd | H6: =IF(H54<>0,IF(H54=月次PL!E56/1000,"OK",PL推移!H54-月次PL!E56/1000),"nd") -> nd | J6: =IF(J54<>0,IF(J54=月次PL!F56/1000,"OK",PL推移!J54-月次PL!F56/1000),"nd") -> nd | L6: =IF(L54<>0,IF(L54=月次PL!G56/1000,"OK",PL推移!L54-月次PL!G56/1000),"nd") -> nd | N6: =IF(N54<>0,IF(N54=月次PL!H56/1000,"OK",PL推移!N54-月次PL!H56/1000),"nd") -> nd | P6: =IF(P54<>0,IF(P54=月次PL!I56/1000,"OK",PL推移!P54-月次PL!I56/1000),"nd") -> nd | R6: =IF(R54<>0,IF(R54=月次PL!J56/1000,"OK",PL推移!R54-月次PL!J56/1000),"nd") -> nd | T6: =IF(T54<>0,IF(T54=月次PL!K56/1000,"OK",PL推移!T54-月次PL!K56/1000),"nd") -> 350 | V6: =IF(V54<>0,IF(V54=月次PL!L56/1000,"OK",PL推移!V54-月次PL!L56/1000),"nd") -> 8454 | X6: =IF(X54<>0,IF(X54=月次PL!M56/1000,"OK",PL推移!X54-月次PL!M56/1000),"nd") -> 9017 | Z6: =IF(Z54<>0,IF(Z54=月次PL!N56/1000,"OK",PL推移!Z54-月次PL!N56/1000),"nd") -> 8610
B7: ■月次報告PL | D7: ㈱ｅｓエンターテイメント | AH7: 注意事項 | AI7: 概算値 | AJ7: 異常値 | AK7: 特記事項 | AL7: 予算検討
B8: 2026 | C8: 年度 | D8: 単位：千円 | F8: 注意事項 | G8: 概算値 | H8: 異常値 | I8: 特記事項 | J8: 予算検討
B9: 項目 | D9: =+月次PL!C1 -> 7月 | F9: =+月次PL!D1 -> 8月 | H9: =+月次PL!E1 -> 9月 | J9: =+月次PL!F1 -> 10月 | L9: =+月次PL!G1 -> 11月 | N9: =+月次PL!H1 -> 12月 | P9: =+月次PL!I1 -> 1月 | R9: =+月次PL!J1 -> 2月 | T9: =+月次PL!K1 -> 3 | V9: =+月次PL!L1 -> 4 | X9: =+月次PL!M1 -> 5月 | Z9: =+月次PL!N1 -> 6月
B10: 売上高 | D10: =+月次PL!C8/1000 -> 8631.285 | E10: =IF(D$10<>0,D10/D$10,0) -> 1 | F10: =+月次PL!D8/1000 -> 0 | G10: =IF(F$10<>0,F10/F$10,0) -> 0 | H10: =+月次PL!E8/1000 -> 0 | I10: =IF(H$10<>0,H10/H$10,0) -> 0 | J10: =+月次PL!F8/1000 -> 0 | K10: =IF(J$10<>0,J10/J$10,0) -> 0 | L10: =SUM(L11:L15) -> 0 | M10: =IF(L$10<>0,L10/L$10,0) -> 0 | N10: =SUM(N11:N15) -> 0 | O10: =IF(N$10<>0,N10/N$10,0) -> 0 | P10: =+月次PL!I8/1000 -> 0 | Q10: =IF(P$10<>0,P10/P$10,0) -> 0 | R10: =+月次PL!J8/1000 -> 0 | S10: =IF(R$10<>0,R10/R$10,0) -> 0 | T10: =SUM(T11:T15)+350 -> 350 | U10: =IF(T$10<>0,T10/T$10,0) -> 1 | V10: =SUM(V11:V15)+350 -> 8454 | W10: =IF(V$10<>0,V10/V$10,0) -> 1 | X10: =SUM(X11:X15)+350 -> 9017 | Y10: =IF(X$10<>0,X10/X$10,0) -> 1 | Z10: 8610 | AA10: =IF(Z$10<>0,Z10/Z$10,0) -> 1
C11: 恵愛 | D11: 6425 | E11: =IF(D$10<>0,D11/D$10,0) -> 0.74438511 | G11: =IF(F$10<>0,F11/F$10,0) -> 0 | I11: =IF(H$10<>0,H11/H$10,0) -> 0 | K11: =IF(J$10<>0,J11/J$10,0) -> 0 | M11: =IF(L$10<>0,L11/L$10,0) -> 0 | O11: =IF(N$10<>0,N11/N$10,0) -> 0 | Q11: =IF(P$10<>0,P11/P$10,0) -> 0 | S11: =IF(R$10<>0,R11/R$10,0) -> 0 | U11: =IF(T$10<>0,T11/T$10,0) -> 0 | V11: 6013 | W11: =IF(V$10<>0,V11/V$10,0) -> 0.71126094 | X11: 6855 | Y11: =IF(X$10<>0,X11/X$10,0) -> 0.76023068 | Z11: 6185 | AA11: =IF(Z$10<>0,Z11/Z$10,0) -> 0.71835075
C12: 村 | D12: 646 | E12: =IF(D$10<>0,D12/D$10,0) -> 0.074844012 | G12: =IF(F$10<>0,F12/F$10,0) -> 0 | I12: =IF(H$10<>0,H12/H$10,0) -> 0 | K12: =IF(J$10<>0,J12/J$10,0) -> 0 | M12: =IF(L$10<>0,L12/L$10,0) -> 0 | O12: =IF(N$10<>0,N12/N$10,0) -> 0 | Q12: =IF(P$10<>0,P12/P$10,0) -> 0 | S12: =IF(R$10<>0,R12/R$10,0) -> 0 | U12: =IF(T$10<>0,T12/T$10,0) -> 0 | V12: 791 | W12: =IF(V$10<>0,V12/V$10,0) -> 0.093565176 | X12: =+月次PL!M6/1000 -> 0 | Y12: =IF(X$10<>0,X12/X$10,0) -> 0 | Z12: =+月次PL!N6/1000 -> 0 | AA12: =IF(Z$10<>0,Z12/Z$10,0) -> 0
C13: 弁当 | D13: 525 | E13: =IF(D$10<>0,D13/D$10,0) -> 0.060825242 | G13: =IF(F$10<>0,F13/F$10,0) -> 0 | I13: =IF(H$10<>0,H13/H$10,0) -> 0 | K13: =IF(J$10<>0,J13/J$10,0) -> 0 | M13: =IF(L$10<>0,L13/L$10,0) -> 0 | O13: =IF(N$10<>0,N13/N$10,0) -> 0 | Q13: =IF(P$10<>0,P13/P$10,0) -> 0 | S13: =IF(R$10<>0,R13/R$10,0) -> 0 | U13: =IF(T$10<>0,T13/T$10,0) -> 0 | V13: 360 | W13: =IF(V$10<>0,V13/V$10,0) -> 0.042583392 | X13: 375 | Y13: =IF(X$10<>0,X13/X$10,0) -> 0.041588111 | Z13: 405 | AA13: =IF(Z$10<>0,Z13/Z$10,0) -> 0.047038328
C14: シェア | D14: 63 | E14: =IF(D$10<>0,D14/D$10,0) -> 0.0072990291 | G14: =IF(F$10<>0,F14/F$10,0) -> 0 | I14: =IF(H$10<>0,H14/H$10,0) -> 0 | K14: =IF(J$10<>0,J14/J$10,0) -> 0 | M14: =IF(L$10<>0,L14/L$10,0) -> 0 | O14: =IF(N$10<>0,N14/N$10,0) -> 0 | Q14: =IF(P$10<>0,P14/P$10,0) -> 0 | S14: =IF(R$10<>0,R14/R$10,0) -> 0 | U14: =IF(T$10<>0,T14/T$10,0) -> 0 | V14: 128 | W14: =IF(V$10<>0,V14/V$10,0) -> 0.015140762 | X14: 108 | Y14: =IF(X$10<>0,X14/X$10,0) -> 0.011977376 | Z14: 122 | AA14: =IF(Z$10<>0,Z14/Z$10,0) -> 0.01416957
C15: サウナ | D15: 973 | E15: =IF(D$10<>0,D15/D$10,0) -> 0.11272945 | G15: =IF(F$10<>0,F15/F$10,0) -> 0 | I15: =IF(H$10<>0,H15/H$10,0) -> 0 | K15: =IF(J$10<>0,J15/J$10,0) -> 0 | M15: =IF(L$10<>0,L15/L$10,0) -> 0 | O15: =IF(N$10<>0,N15/N$10,0) -> 0 | Q15: =IF(P$10<>0,P15/P$10,0) -> 0 | S15: =IF(R$10<>0,R15/R$10,0) -> 0 | U15: =IF(T$10<>0,T15/T$10,0) -> 0 | V15: 812 | W15: =IF(V$10<>0,V15/V$10,0) -> 0.096049207 | X15: 1329 | Y15: =IF(X$10<>0,X15/X$10,0) -> 0.14738827 | Z15: 892 | AA15: =IF(Z$10<>0,Z15/Z$10,0) -> 0.10360046
B16: 売上原価 | D16: =+月次PL!C15/1000 -> 2021.276 | E16: =IF(D$10<>0,D16/D$10,0) -> 0.23418019 | F16: =+月次PL!D15/1000 -> 0 | G16: =IF(F$10<>0,F16/F$10,0) -> 0 | H16: =+月次PL!E15/1000 -> 0 | I16: =IF(H$10<>0,H16/H$10,0) -> 0 | J16: =+月次PL!F15/1000 -> 0 | K16: =IF(J$10<>0,J16/J$10,0) -> 0 | L16: =+月次PL!G15/1000 -> 0 | M16: =IF(L$10<>0,L16/L$10,0) -> 0 | N16: =+月次PL!H15/1000 -> 0 | O16: =IF(N$10<>0,N16/N$10,0) -> 0 | P16: =+月次PL!I15/1000 -> 0 | Q16: =IF(P$10<>0,P16/P$10,0) -> 0 | R16: =+月次PL!J15/1000 -> 0 | S16: =IF(R$10<>0,R16/R$10,0) -> 0 | T16: =+月次PL!K15/1000 -> 0 | U16: =IF(T$10<>0,T16/T$10,0) -> 0 | V16: =+月次PL!L15/1000 -> 0 | W16: =IF(V$10<>0,V16/V$10,0) -> 0 | X16: =+月次PL!M15/1000 -> 0 | Y16: =IF(X$10<>0,X16/X$10,0) -> 0 | Z16: =+月次PL!N15/1000 -> 0 | AA16: =IF(Z$10<>0,Z16/Z$10,0) -> 0
C17: =+C11 -> 恵愛 | D17: 1728 | E17: =IF(D11<>0,D17/D11,0) -> 0.26894942 | G17: =IF(F11<>0,F17/F11,0) -> 0 | I17: =IF(H11<>0,H17/H11,0) -> 0 | K17: =IF(J11<>0,J17/J11,0) -> 0 | M17: =IF(L11<>0,L17/L11,0) -> 0 | O17: =IF(N11<>0,N17/N11,0) -> 0 | Q17: =IF(P11<>0,P17/P11,0) -> 0 | R17: 1634 | S17: =IF(R11<>0,R17/R11,0) -> 0 | T17: 1864 | U17: =IF(T11<>0,T17/T11,0) -> 0 | V17: 1607 | W17: =IF(V11<>0,V17/V11,0) -> 0.26725428 | X17: 1751 | Y17: =IF(X11<>0,X17/X11,0) -> 0.25543399 | Z17: 1643 | AA17: =IF(Z11<>0,Z17/Z11,0) -> 0.26564268
C18: =+C12 -> 村 | D18: 122 | E18: =IF(D12<>0,D18/D12,0) -> 0.18885449 | G18: =IF(F12<>0,F18/F12,0) -> 0 | I18: =IF(H12<>0,H18/H12,0) -> 0 | K18: =IF(J12<>0,J18/J12,0) -> 0 | M18: =IF(L12<>0,L18/L12,0) -> 0 | O18: =IF(N12<>0,N18/N12,0) -> 0 | Q18: =IF(P12<>0,P18/P12,0) -> 0 | R18: 92 | S18: =IF(R12<>0,R18/R12,0) -> 0 | T18: 143 | U18: =IF(T12<>0,T18/T12,0) -> 0 | V18: 82 | W18: =IF(V12<>0,V18/V12,0) -> 0.10366625 | X18: 115 | Y18: =IF(X12<>0,X18/X12,0) -> 0 | Z18: 120 | AA18: =IF(Z12<>0,Z18/Z12,0) -> 0
C19: =+C13 -> 弁当 | D19: 126 | E19: =IF(D13<>0,D19/D13,0) -> 0.24 | G19: =IF(F13<>0,F19/F13,0) -> 0 | I19: =IF(H13<>0,H19/H13,0) -> 0 | K19: =IF(J13<>0,J19/J13,0) -> 0 | M19: =IF(L13<>0,L19/L13,0) -> 0 | O19: =IF(N13<>0,N19/N13,0) -> 0 | Q19: =IF(P13<>0,P19/P13,0) -> 0 | R19: 87 | S19: =IF(R13<>0,R19/R13,0) -> 0 | T19: 154 | U19: =IF(T13<>0,T19/T13,0) -> 0 | V19: 151 | W19: =IF(V13<>0,V19/V13,0) -> 0.41944444 | X19: 167 | Y19: =IF(X13<>0,X19/X13,0) -> 0.44533333 | Z19: 184 | AA19: =IF(Z13<>0,Z19/Z13,0) -> 0.45432099
C20: =+C14 -> シェア | D20: 19 | E20: =IF(D14<>0,D20/D14,0) -> 0.3015873 | G20: =IF(F14<>0,F20/F14,0) -> 0 | I20: =IF(H14<>0,H20/H14,0) -> 0 | K20: =IF(J14<>0,J20/J14,0) -> 0 | M20: =IF(L14<>0,L20/L14,0) -> 0 | O20: =IF(N14<>0,N20/N14,0) -> 0 | Q20: =IF(P14<>0,P20/P14,0) -> 0 | R20: 25 | S20: =IF(R14<>0,R20/R14,0) -> 0 | T20: 73 | U20: =IF(T14<>0,T20/T14,0) -> 0 | V20: 38 | W20: =IF(V14<>0,V20/V14,0) -> 0.296875 | X20: 32 | Y20: =IF(X14<>0,X20/X14,0) -> 0.2962963 | Z20: 37 | AA20: =IF(Z14<>0,Z20/Z14,0) -> 0.30327869
C21: =+C15 -> サウナ | D21: 27 | E21: =IF(D15<>0,D21/D15,0) -> 0.027749229 | G21: =IF(F15<>0,F21/F15,0) -> 0 | I21: =IF(H15<>0,H21/H15,0) -> 0 | K21: =IF(J15<>0,J21/J15,0) -> 0 | M21: =IF(L15<>0,L21/L15,0) -> 0 | O21: =IF(N15<>0,N21/N15,0) -> 0 | Q21: =IF(P15<>0,P21/P15,0) -> 0 | R21: 62 | S21: =IF(R15<>0,R21/R15,0) -> 0 | T21: 32 | U21: =IF(T15<>0,T21/T15,0) -> 0 | V21: 33 | W21: =IF(V15<>0,V21/V15,0) -> 0.040640394 | X21: 52 | Y21: =IF(X15<>0,X21/X15,0) -> 0.039127163 | Z21: 23 | AA21: =IF(Z15<>0,Z21/Z15,0) -> 0.025784753
B22: 粗利益 | D22: =+D10-D16 -> 6610.009 | E22: =IF(D$10<>0,D22/D$10,0) -> 0.76581981 | F22: =+F10-F16 -> 0 | G22: =IF(F$10<>0,F22/F$10,0) -> 0 | H22: =+H10-H16 -> 0 | I22: =IF(H$10<>0,H22/H$10,0) -> 0 | J22: =+J10-J16 -> 0 | K22: =IF(J$10<>0,J22/J$10,0) -> 0 | L22: =+L10-L16 -> 0 | M22: =IF(L$10<>0,L22/L$10,0) -> 0 | N22: =+N10-N16 -> 0 | O22: =IF(N$10<>0,N22/N$10,0) -> 0 | P22: =+P10-P16 -> 0 | Q22: =IF(P$10<>0,P22/P$10,0) -> 0 | R22: =+R10-R16 -> 0 | S22: =IF(R$10<>0,R22/R$10,0) -> 0 | T22: =+T10-T16 -> 350 | U22: =IF(T$10<>0,T22/T$10,0) -> 1 | V22: =+V10-V16 -> 8454 | W22: =IF(V$10<>0,V22/V$10,0) -> 1 | X22: =+X10-X16 -> 9017 | Y22: =IF(X$10<>0,X22/X$10,0) -> 1 | Z22: =+Z10-Z16 -> 8610 | AA22: =IF(Z$10<>0,Z22/Z$10,0) -> 1
C23: =+C17 -> 恵愛 | D23: =+D11-D17 -> 4697 | E23: =IF(D11<>0,D23/D11,0) -> 0.73105058 | F23: =+F11-F17 -> 0 | G23: =IF(F11<>0,F23/F11,0) -> 0 | H23: =+H11-H17 -> 0 | I23: =IF(H11<>0,H23/H11,0) -> 0 | J23: =+J11-J17 -> 0 | K23: =IF(J11<>0,J23/J11,0) -> 0 | L23: =+L11-L17 -> 0 | M23: =IF(L11<>0,L23/L11,0) -> 0 | N23: =+N11-N17 -> 0 | O23: =IF(N11<>0,N23/N11,0) -> 0 | P23: =+P11-P17 -> 0 | Q23: =IF(P11<>0,P23/P11,0) -> 0 | R23: =+R11-R17 -> -1634 | S23: =IF(R11<>0,R23/R11,0) -> 0 | T23: =+T11-T17 -> -1864 | U23: =IF(T11<>0,T23/T11,0) -> 0 | V23: =+V11-V17 -> 4406 | W23: =IF(V11<>0,V23/V11,0) -> 0.73274572 | X23: =+X11-X17 -> 5104 | Y23: =IF(X11<>0,X23/X11,0) -> 0.74456601 | Z23: =+Z11-Z17 -> 4542 | AA23: =IF(Z11<>0,Z23/Z11,0) -> 0.73435732
C24: =+C18 -> 村 | D24: =+D12-D18 -> 524 | E24: =IF(D12<>0,D24/D12,0) -> 0.81114551 | F24: =+F12-F18 -> 0 | G24: =IF(F12<>0,F24/F12,0) -> 0 | H24: =+H12-H18 -> 0 | I24: =IF(H12<>0,H24/H12,0) -> 0 | J24: =+J12-J18 -> 0 | K24: =IF(J12<>0,J24/J12,0) -> 0 | L24: =+L12-L18 -> 0 | M24: =IF(L12<>0,L24/L12,0) -> 0 | N24: =+N12-N18 -> 0 | O24: =IF(N12<>0,N24/N12,0) -> 0 | P24: =+P12-P18 -> 0 | Q24: =IF(P12<>0,P24/P12,0) -> 0 | R24: =+R12-R18 -> -92 | S24: =IF(R12<>0,R24/R12,0) -> 0 | T24: =+T12-T18 -> -143 | U24: =IF(T12<>0,T24/T12,0) -> 0 | V24: =+V12-V18 -> 709 | W24: =IF(V12<>0,V24/V12,0) -> 0.89633375 | X24: =+X12-X18 -> -115 | Y24: =IF(X12<>0,X24/X12,0) -> 0 | Z24: =+Z12-Z18 -> -120 | AA24: =IF(Z12<>0,Z24/Z12,0) -> 0
C25: =+C19 -> 弁当 | D25: =+D13-D19 -> 399 | E25: =IF(D13<>0,D25/D13,0) -> 0.76 | F25: =+F13-F19 -> 0 | G25: =IF(F13<>0,F25/F13,0) -> 0 | H25: =+H13-H19 -> 0 | I25: =IF(H13<>0,H25/H13,0) -> 0 | J25: =+J13-J19 -> 0 | K25: =IF(J13<>0,J25/J13,0) -> 0 | L25: =+L13-L19 -> 0 | M25: =IF(L13<>0,L25/L13,0) -> 0 | N25: =+N13-N19 -> 0 | O25: =IF(N13<>0,N25/N13,0) -> 0 | P25: =+P13-P19 -> 0 | Q25: =IF(P13<>0,P25/P13,0) -> 0 | R25: =+R13-R19 -> -87 | S25: =IF(R13<>0,R25/R13,0) -> 0 | T25: =+T13-T19 -> -154 | U25: =IF(T13<>0,T25/T13,0) -> 0 | V25: =+V13-V19 -> 209 | W25: =IF(V13<>0,V25/V13,0) -> 0.58055556 | X25: =+X13-X19 -> 208 | Y25: =IF(X13<>0,X25/X13,0) -> 0.55466667 | Z25: =+Z13-Z19 -> 221 | AA25: =IF(Z13<>0,Z25/Z13,0) -> 0.54567901
C26: =+C20 -> シェア | D26: =+D14-D20 -> 44 | E26: =IF(D14<>0,D26/D14,0) -> 0.6984127 | F26: =+F14-F20 -> 0 | G26: =IF(F14<>0,F26/F14,0) -> 0 | H26: =+H14-H20 -> 0 | I26: =IF(H14<>0,H26/H14,0) -> 0 | J26: =+J14-J20 -> 0 | K26: =IF(J14<>0,J26/J14,0) -> 0 | L26: =+L14-L20 -> 0 | M26: =IF(L14<>0,L26/L14,0) -> 0 | N26: =+N14-N20 -> 0 | O26: =IF(N14<>0,N26/N14,0) -> 0 | P26: =+P14-P20 -> 0 | Q26: =IF(P14<>0,P26/P14,0) -> 0 | R26: =+R14-R20 -> -25 | S26: =IF(R14<>0,R26/R14,0) -> 0 | T26: =+T14-T20 -> -73 | U26: =IF(T14<>0,T26/T14,0) -> 0 | V26: =+V14-V20 -> 90 | W26: =IF(V14<>0,V26/V14,0) -> 0.703125 | X26: =+X14-X20 -> 76 | Y26: =IF(X14<>0,X26/X14,0) -> 0.7037037 | Z26: =+Z14-Z20 -> 85 | AA26: =IF(Z14<>0,Z26/Z14,0) -> 0.69672131
C27: =+C21 -> サウナ | D27: =+D15-D21 -> 946 | E27: =IF(D15<>0,D27/D15,0) -> 0.97225077 | F27: =+F15-F21 -> 0 | G27: =IF(F15<>0,F27/F15,0) -> 0 | H27: =+H15-H21 -> 0 | I27: =IF(H15<>0,H27/H15,0) -> 0 | J27: =+J15-J21 -> 0 | K27: =IF(J15<>0,J27/J15,0) -> 0 | L27: =+L15-L21 -> 0 | M27: =IF(L15<>0,L27/L15,0) -> 0 | N27: =+N15-N21 -> 0 | O27: =IF(N15<>0,N27/N15,0) -> 0 | P27: =+P15-P21 -> 0 | Q27: =IF(P15<>0,P27/P15,0) -> 0 | R27: =+R15-R21 -> -62 | S27: =IF(R15<>0,R27/R15,0) -> 0 | T27: =+T15-T21 -> -32 | U27: =IF(T15<>0,T27/T15,0) -> 0 | V27: =+V15-V21 -> 779 | W27: =IF(V15<>0,V27/V15,0) -> 0.95935961 | X27: =+X15-X21 -> 1277 | Y27: =IF(X15<>0,X27/X15,0) -> 0.96087284 | Z27: =+Z15-Z21 -> 869 | AA27: =IF(Z15<>0,Z27/Z15,0) -> 0.97421525
B28: 販売管理費 | D28: =SUM(D29:D49) -> 6195.861 | E28: =IF(D$10<>0,D28/D$10,0) -> 0.71783761 | F28: =SUM(F29:F49) -> 0 | G28: =IF(F$10<>0,F28/F$10,0) -> 0 | H28: =SUM(H29:H49) -> 0 | I28: =IF(H$10<>0,H28/H$10,0) -> 0 | J28: =SUM(J29:J49) -> 0 | K28: =IF(J$10<>0,J28/J$10,0) -> 0 | L28: =SUM(L29:L49) -> 0 | M28: =IF(L$10<>0,L28/L$10,0) -> 0 | N28: =SUM(N29:N49) -> 0 | O28: =IF(N$10<>0,N28/N$10,0) -> 0 | P28: =SUM(P29:P49) -> 0 | Q28: =IF(P$10<>0,P28/P$10,0) -> 0 | R28: =SUM(R29:R49) -> 0 | S28: =IF(R$10<>0,R28/R$10,0) -> 0 | T28: =SUM(T29:T49) -> 0 | U28: =IF(T$10<>0,T28/T$10,0) -> 0 | V28: =SUM(V29:V49) -> 0 | W28: =IF(V$10<>0,V28/V$10,0) -> 0 | X28: =SUM(X29:X49) -> 0 | Y28: =IF(X$10<>0,X28/X$10,0) -> 0 | Z28: =SUM(Z29:Z49) -> 0 | AA28: =IF(Z$10<>0,Z28/Z$10,0) -> 0
C29: 人件費 | D29: =SUM(月次PL!C18:C24)/1000 -> 2462.876 | E29: =IF(D$10<>0,D29/D$10,0) -> 0.28534291 | F29: =SUM(月次PL!D18:D24)/1000 -> 0 | G29: =IF(F$10<>0,F29/F$10,0) -> 0 | H29: =SUM(月次PL!E18:E24)/1000 -> 0 | I29: =IF(H$10<>0,H29/H$10,0) -> 0 | J29: =SUM(月次PL!F18:F24)/1000 -> 0 | K29: =IF(J$10<>0,J29/J$10,0) -> 0 | L29: =SUM(月次PL!G18:G24)/1000 -> 0 | M29: =IF(L$10<>0,L29/L$10,0) -> 0 | N29: =SUM(月次PL!H18:H24)/1000 -> 0 | O29: =IF(N$10<>0,N29/N$10,0) -> 0 | P29: =SUM(月次PL!I18:I24)/1000 -> 0 | Q29: =IF(P$10<>0,P29/P$10,0) -> 0 | R29: =SUM(月次PL!J18:J24)/1000 -> 0 | S29: =IF(R$10<>0,R29/R$10,0) -> 0 | T29: =SUM(月次PL!K18:K24)/1000 -> 0 | U29: =IF(T$10<>0,T29/T$10,0) -> 0 | V29: =SUM(月次PL!L18:L24)/1000 -> 0 | W29: =IF(V$10<>0,V29/V$10,0) -> 0 | X29: =SUM(月次PL!M18:M24)/1000 -> 0 | Y29: =IF(X$10<>0,X29/X$10,0) -> 0 | Z29: =SUM(月次PL!N18:N24)/1000 -> 0 | AA29: =IF(Z$10<>0,Z29/Z$10,0) -> 0
C30: 旅費交通費 | D30: =+月次PL!C27/1000 -> 41.261 | E30: =IF(D$10<>0,D30/D$10,0) -> 0.0047804006 | F30: =+月次PL!D27/1000 -> 0 | G30: =IF(F$10<>0,F30/F$10,0) -> 0 | H30: =+月次PL!E27/1000 -> 0 | I30: =IF(H$10<>0,H30/H$10,0) -> 0 | J30: =+月次PL!F27/1000 -> 0 | K30: =IF(J$10<>0,J30/J$10,0) -> 0 | L30: =+月次PL!G27/1000 -> 0 | M30: =IF(L$10<>0,L30/L$10,0) -> 0 | N30: =+月次PL!H27/1000 -> 0 | O30: =IF(N$10<>0,N30/N$10,0) -> 0 | P30: =+月次PL!I27/1000 -> 0 | Q30: =IF(P$10<>0,P30/P$10,0) -> 0 | R30: =+月次PL!J27/1000 -> 0 | S30: =IF(R$10<>0,R30/R$10,0) -> 0 | T30: =+月次PL!K27/1000 -> 0 | U30: =IF(T$10<>0,T30/T$10,0) -> 0 | V30: =+月次PL!L27/1000 -> 0 | W30: =IF(V$10<>0,V30/V$10,0) -> 0 | X30: =+月次PL!M27/1000 -> 0 | Y30: =IF(X$10<>0,X30/X$10,0) -> 0 | Z30: =+月次PL!N27/1000 -> 0 | AA30: =IF(Z$10<>0,Z30/Z$10,0) -> 0
C31: 通信費 | D31: =+月次PL!C28/1000 -> 62.422 | E31: =IF(D$10<>0,D31/D$10,0) -> 0.0072320634 | F31: =+月次PL!D28/1000 -> 0 | G31: =IF(F$10<>0,F31/F$10,0) -> 0 | H31: =+月次PL!E28/1000 -> 0 | I31: =IF(H$10<>0,H31/H$10,0) -> 0 | J31: =+月次PL!F28/1000 -> 0 | K31: =IF(J$10<>0,J31/J$10,0) -> 0 | L31: =+月次PL!G28/1000 -> 0 | M31: =IF(L$10<>0,L31/L$10,0) -> 0 | N31: =+月次PL!H28/1000 -> 0 | O31: =IF(N$10<>0,N31/N$10,0) -> 0 | P31: =+月次PL!I28/1000 -> 0 | Q31: =IF(P$10<>0,P31/P$10,0) -> 0 | R31: =+月次PL!J28/1000 -> 0 | S31: =IF(R$10<>0,R31/R$10,0) -> 0 | T31: =+月次PL!K28/1000 -> 0 | U31: =IF(T$10<>0,T31/T$10,0) -> 0 | V31: =+月次PL!L28/1000 -> 0 | W31: =IF(V$10<>0,V31/V$10,0) -> 0 | X31: =+月次PL!M28/1000 -> 0 | Y31: =IF(X$10<>0,X31/X$10,0) -> 0 | Z31: =+月次PL!N28/1000 -> 0 | AA31: =IF(Z$10<>0,Z31/Z$10,0) -> 0
C32: 開発費 | D32: =+月次PL!C43/1000 -> 0 | E32: =IF(D$10<>0,D32/D$10,0) -> 0 | F32: =+月次PL!D43/1000 -> 0 | G32: =IF(F$10<>0,F32/F$10,0) -> 0 | H32: =+月次PL!E43/1000 -> 0 | I32: =IF(H$10<>0,H32/H$10,0) -> 0 | J32: =+月次PL!F43/1000 -> 0 | K32: =IF(J$10<>0,J32/J$10,0) -> 0 | L32: =+月次PL!G43/1000 -> 0 | M32: =IF(L$10<>0,L32/L$10,0) -> 0 | N32: =+月次PL!H43/1000 -> 0 | O32: =IF(N$10<>0,N32/N$10,0) -> 0 | P32: =+月次PL!I43/1000 -> 0 | Q32: =IF(P$10<>0,P32/P$10,0) -> 0 | R32: =+月次PL!J43/1000 -> 0 | S32: =IF(R$10<>0,R32/R$10,0) -> 0 | T32: =+月次PL!K43/1000 -> 0 | U32: =IF(T$10<>0,T32/T$10,0) -> 0 | V32: =+月次PL!L43/1000 -> 0 | W32: =IF(V$10<>0,V32/V$10,0) -> 0 | X32: =+月次PL!M43/1000 -> 0 | Y32: =IF(X$10<>0,X32/X$10,0) -> 0 | Z32: =+月次PL!N43/1000 -> 0 | AA32: =IF(Z$10<>0,Z32/Z$10,0) -> 0
C33: 交際費 | D33: =+月次PL!C26/1000 -> 0 | E33: =IF(D$10<>0,D33/D$10,0) -> 0 | F33: =+月次PL!D26/1000 -> 0 | G33: =IF(F$10<>0,F33/F$10,0) -> 0 | H33: =+月次PL!E26/1000 -> 0 | I33: =IF(H$10<>0,H33/H$10,0) -> 0 | J33: =+月次PL!F26/1000 -> 0 | K33: =IF(J$10<>0,J33/J$10,0) -> 0 | L33: =+月次PL!G26/1000 -> 0 | M33: =IF(L$10<>0,L33/L$10,0) -> 0 | N33: =+月次PL!H26/1000 -> 0 | O33: =IF(N$10<>0,N33/N$10,0) -> 0 | P33: =+月次PL!I26/1000 -> 0 | Q33: =IF(P$10<>0,P33/P$10,0) -> 0 | R33: =+月次PL!J26/1000 -> 0 | S33: =IF(R$10<>0,R33/R$10,0) -> 0 | T33: =+月次PL!K26/1000 -> 0 | U33: =IF(T$10<>0,T33/T$10,0) -> 0 | V33: =+月次PL!L26/1000 -> 0 | W33: =IF(V$10<>0,V33/V$10,0) -> 0 | X33: =+月次PL!M26/1000 -> 0 | Y33: =IF(X$10<>0,X33/X$10,0) -> 0 | Z33: =+月次PL!N26/1000 -> 0 | AA33: =IF(Z$10<>0,Z33/Z$10,0) -> 0
C34: 会議費 | D34: =+月次PL!C38/1000 -> 7.273 | E34: =IF(D$10<>0,D34/D$10,0) -> 0.00084263235 | F34: =+月次PL!D38/1000 -> 0 | G34: =IF(F$10<>0,F34/F$10,0) -> 0 | H34: =+月次PL!E38/1000 -> 0 | I34: =IF(H$10<>0,H34/H$10,0) -> 0 | J34: =+月次PL!F38/1000 -> 0 | K34: =IF(J$10<>0,J34/J$10,0) -> 0 | L34: =+月次PL!G38/1000 -> 0 | M34: =IF(L$10<>0,L34/L$10,0) -> 0 | N34: =+月次PL!H38/1000 -> 0 | O34: =IF(N$10<>0,N34/N$10,0) -> 0 | P34: =+月次PL!I38/1000 -> 0 | Q34: =IF(P$10<>0,P34/P$10,0) -> 0 | R34: =+月次PL!J38/1000 -> 0 | S34: =IF(R$10<>0,R34/R$10,0) -> 0 | T34: =+月次PL!K38/1000 -> 0 | U34: =IF(T$10<>0,T34/T$10,0) -> 0 | V34: =+月次PL!L38/1000 -> 0 | W34: =IF(V$10<>0,V34/V$10,0) -> 0 | X34: =+月次PL!M38/1000 -> 0 | Y34: =IF(X$10<>0,X34/X$10,0) -> 0 | Z34: =+月次PL!N38/1000 -> 0 | AA34: =IF(Z$10<>0,Z34/Z$10,0) -> 0
C35: 減価償却費 | D35: =+月次PL!C40/1000 -> 749.954 | E35: =IF(D$10<>0,D35/D$10,0) -> 0.086887874 | F35: =+月次PL!D40/1000 -> 0 | G35: =IF(F$10<>0,F35/F$10,0) -> 0 | H35: =+月次PL!E40/1000 -> 0 | I35: =IF(H$10<>0,H35/H$10,0) -> 0 | J35: =+月次PL!F40/1000 -> 0 | K35: =IF(J$10<>0,J35/J$10,0) -> 0 | L35: =+月次PL!G40/1000 -> 0 | M35: =IF(L$10<>0,L35/L$10,0) -> 0 | N35: =+月次PL!H40/1000 -> 0 | O35: =IF(N$10<>0,N35/N$10,0) -> 0 | P35: =+月次PL!I40/1000 -> 0 | Q35: =IF(P$10<>0,P35/P$10,0) -> 0 | R35: =+月次PL!J40/1000 -> 0 | S35: =IF(R$10<>0,R35/R$10,0) -> 0 | T35: =+月次PL!K40/1000 -> 0 | U35: =IF(T$10<>0,T35/T$10,0) -> 0 | V35: =+月次PL!L40/1000 -> 0 | W35: =IF(V$10<>0,V35/V$10,0) -> 0 | X35: =+月次PL!M40/1000 -> 0 | Y35: =IF(X$10<>0,X35/X$10,0) -> 0 | Z35: =+月次PL!N40/1000 -> 0 | AA35: =IF(Z$10<>0,Z35/Z$10,0) -> 0
C36: 賃借料 | D36: =+月次PL!C34/1000 -> 30 | E36: =IF(D$10<>0,D36/D$10,0) -> 0.0034757281 | F36: =+月次PL!D34/1000 -> 0 | G36: =IF(F$10<>0,F36/F$10,0) -> 0 | H36: =+月次PL!E34/1000 -> 0 | I36: =IF(H$10<>0,H36/H$10,0) -> 0 | J36: =+月次PL!F34/1000 -> 0 | K36: =IF(J$10<>0,J36/J$10,0) -> 0 | L36: =+月次PL!G34/1000 -> 0 | M36: =IF(L$10<>0,L36/L$10,0) -> 0 | N36: =+月次PL!H34/1000 -> 0 | O36: =IF(N$10<>0,N36/N$10,0) -> 0 | P36: =+月次PL!I34/1000 -> 0 | Q36: =IF(P$10<>0,P36/P$10,0) -> 0 | R36: =+月次PL!J34/1000 -> 0 | S36: =IF(R$10<>0,R36/R$10,0) -> 0 | T36: =+月次PL!K34/1000 -> 0 | U36: =IF(T$10<>0,T36/T$10,0) -> 0 | V36: =+月次PL!L34/1000 -> 0 | W36: =IF(V$10<>0,V36/V$10,0) -> 0 | X36: =+月次PL!M34/1000 -> 0 | Y36: =IF(X$10<>0,X36/X$10,0) -> 0 | Z36: =+月次PL!N34/1000 -> 0 | AA36: =IF(Z$10<>0,Z36/Z$10,0) -> 0
C37: 地代家賃 | D37: =+月次PL!C33/1000 -> 1295.661 | E37: =IF(D$10<>0,D37/D$10,0) -> 0.15011218 | F37: =+月次PL!D33/1000 -> 0 | G37: =IF(F$10<>0,F37/F$10,0) -> 0 | H37: =+月次PL!E33/1000 -> 0 | I37: =IF(H$10<>0,H37/H$10,0) -> 0 | J37: =+月次PL!F33/1000 -> 0 | K37: =IF(J$10<>0,J37/J$10,0) -> 0 | L37: =+月次PL!G33/1000 -> 0 | M37: =IF(L$10<>0,L37/L$10,0) -> 0 | N37: =+月次PL!H33/1000 -> 0 | O37: =IF(N$10<>0,N37/N$10,0) -> 0 | P37: =+月次PL!I33/1000 -> 0 | Q37: =IF(P$10<>0,P37/P$10,0) -> 0 | R37: =+月次PL!J33/1000 -> 0 | S37: =IF(R$10<>0,R37/R$10,0) -> 0 | T37: =+月次PL!K33/1000 -> 0 | U37: =IF(T$10<>0,T37/T$10,0) -> 0 | V37: =+月次PL!L33/1000 -> 0 | W37: =IF(V$10<>0,V37/V$10,0) -> 0 | X37: =+月次PL!M33/1000 -> 0 | Y37: =IF(X$10<>0,X37/X$10,0) -> 0 | Z37: =+月次PL!N33/1000 -> 0 | AA37: =IF(Z$10<>0,Z37/Z$10,0) -> 0
C38: リース料 | D38: =+月次PL!C32/1000 -> 49.7 | E38: =IF(D$10<>0,D38/D$10,0) -> 0.0057581229 | F38: =+月次PL!D32/1000 -> 0 | G38: =IF(F$10<>0,F38/F$10,0) -> 0 | H38: =+月次PL!E32/1000 -> 0 | I38: =IF(H$10<>0,H38/H$10,0) -> 0 | J38: =+月次PL!F32/1000 -> 0 | K38: =IF(J$10<>0,J38/J$10,0) -> 0 | L38: =+月次PL!G32/1000 -> 0 | M38: =IF(L$10<>0,L38/L$10,0) -> 0 | N38: =+月次PL!H32/1000 -> 0 | O38: =IF(N$10<>0,N38/N$10,0) -> 0 | P38: =+月次PL!I32/1000 -> 0 | Q38: =IF(P$10<>0,P38/P$10,0) -> 0 | R38: =+月次PL!J32/1000 -> 0 | S38: =IF(R$10<>0,R38/R$10,0) -> 0 | T38: =+月次PL!K32/1000 -> 0 | U38: =IF(T$10<>0,T38/T$10,0) -> 0 | V38: =+月次PL!L32/1000 -> 0 | W38: =IF(V$10<>0,V38/V$10,0) -> 0 | X38: =+月次PL!M32/1000 -> 0 | Y38: =IF(X$10<>0,X38/X$10,0) -> 0 | Z38: =+月次PL!N32/1000 -> 0 | AA38: =IF(Z$10<>0,Z38/Z$10,0) -> 0
C39: 修繕費 | D39: =+月次PL!C30/1000 -> 0 | E39: =IF(D$10<>0,D39/D$10,0) -> 0 | F39: =+月次PL!D30/1000 -> 0 | G39: =IF(F$10<>0,F39/F$10,0) -> 0 | H39: =+月次PL!E30/1000 -> 0 | I39: =IF(H$10<>0,H39/H$10,0) -> 0 | J39: =+月次PL!F30/1000 -> 0 | K39: =IF(J$10<>0,J39/J$10,0) -> 0 | L39: =+月次PL!G30/1000 -> 0 | M39: =IF(L$10<>0,L39/L$10,0) -> 0 | N39: =+月次PL!H30/1000 -> 0 | O39: =IF(N$10<>0,N39/N$10,0) -> 0 | P39: =+月次PL!I30/1000 -> 0 | Q39: =IF(P$10<>0,P39/P$10,0) -> 0 | R39: =+月次PL!J30/1000 -> 0 | S39: =IF(R$10<>0,R39/R$10,0) -> 0 | T39: =+月次PL!K30/1000 -> 0 | U39: =IF(T$10<>0,T39/T$10,0) -> 0 | V39: =+月次PL!L30/1000 -> 0 | W39: =IF(V$10<>0,V39/V$10,0) -> 0 | X39: =+月次PL!M30/1000 -> 0 | Y39: =IF(X$10<>0,X39/X$10,0) -> 0 | Z39: =+月次PL!N30/1000 -> 0 | AA39: =IF(Z$10<>0,Z39/Z$10,0) -> 0
C40: 保険料 | D40: =+月次PL!C35/1000 -> 28.375 | E40: =IF(D$10<>0,D40/D$10,0) -> 0.0032874595 | F40: =+月次PL!D35/1000 -> 0 | G40: =IF(F$10<>0,F40/F$10,0) -> 0 | H40: =+月次PL!E35/1000 -> 0 | I40: =IF(H$10<>0,H40/H$10,0) -> 0 | J40: =+月次PL!F35/1000 -> 0 | K40: =IF(J$10<>0,J40/J$10,0) -> 0 | L40: =+月次PL!G35/1000 -> 0 | M40: =IF(L$10<>0,L40/L$10,0) -> 0 | N40: =+月次PL!H35/1000 -> 0 | O40: =IF(N$10<>0,N40/N$10,0) -> 0 | P40: =+月次PL!I35/1000 -> 0 | Q40: =IF(P$10<>0,P40/P$10,0) -> 0 | R40: =+月次PL!J35/1000 -> 0 | S40: =IF(R$10<>0,R40/R$10,0) -> 0 | T40: =+月次PL!K35/1000 -> 0 | U40: =IF(T$10<>0,T40/T$10,0) -> 0 | V40: =+月次PL!L35/1000 -> 0 | W40: =IF(V$10<>0,V40/V$10,0) -> 0 | X40: =+月次PL!M35/1000 -> 0 | Y40: =IF(X$10<>0,X40/X$10,0) -> 0 | Z40: =+月次PL!N35/1000 -> 0 | AA40: =IF(Z$10<>0,Z40/Z$10,0) -> 0
C41: 水道光熱費 | D41: =+月次PL!C29/1000 -> 659.468 | E41: =IF(D$10<>0,D41/D$10,0) -> 0.076404382 | F41: =+月次PL!D29/1000 -> 0 | G41: =IF(F$10<>0,F41/F$10,0) -> 0 | H41: =+月次PL!E29/1000 -> 0 | I41: =IF(H$10<>0,H41/H$10,0) -> 0 | J41: =+月次PL!F29/1000 -> 0 | K41: =IF(J$10<>0,J41/J$10,0) -> 0 | L41: =+月次PL!G29/1000 -> 0 | M41: =IF(L$10<>0,L41/L$10,0) -> 0 | N41: =+月次PL!H29/1000 -> 0 | O41: =IF(N$10<>0,N41/N$10,0) -> 0 | P41: =+月次PL!I29/1000 -> 0 | Q41: =IF(P$10<>0,P41/P$10,0) -> 0 | R41: =+月次PL!J29/1000 -> 0 | S41: =IF(R$10<>0,R41/R$10,0) -> 0 | T41: =+月次PL!K29/1000 -> 0 | U41: =IF(T$10<>0,T41/T$10,0) -> 0 | V41: =+月次PL!L29/1000 -> 0 | W41: =IF(V$10<>0,V41/V$10,0) -> 0 | X41: =+月次PL!M29/1000 -> 0 | Y41: =IF(X$10<>0,X41/X$10,0) -> 0 | Z41: =+月次PL!N29/1000 -> 0 | AA41: =IF(Z$10<>0,Z41/Z$10,0) -> 0
C42: 消耗品費 | D42: =+月次PL!C31/1000 -> 207.018 | E42: =IF(D$10<>0,D42/D$10,0) -> 0.023984609 | F42: =+月次PL!D31/1000 -> 0 | G42: =IF(F$10<>0,F42/F$10,0) -> 0 | H42: =+月次PL!E31/1000 -> 0 | I42: =IF(H$10<>0,H42/H$10,0) -> 0 | J42: =+月次PL!F31/1000 -> 0 | K42: =IF(J$10<>0,J42/J$10,0) -> 0 | L42: =+月次PL!G31/1000 -> 0 | M42: =IF(L$10<>0,L42/L$10,0) -> 0 | N42: =+月次PL!H31/1000 -> 0 | O42: =IF(N$10<>0,N42/N$10,0) -> 0 | P42: =+月次PL!I31/1000 -> 0 | Q42: =IF(P$10<>0,P42/P$10,0) -> 0 | R42: =+月次PL!J31/1000 -> 0 | S42: =IF(R$10<>0,R42/R$10,0) -> 0 | T42: =+月次PL!K31/1000 -> 0 | U42: =IF(T$10<>0,T42/T$10,0) -> 0 | V42: =+月次PL!L31/1000 -> 0 | W42: =IF(V$10<>0,V42/V$10,0) -> 0 | X42: =+月次PL!M31/1000 -> 0 | Y42: =IF(X$10<>0,X42/X$10,0) -> 0 | Z42: =+月次PL!N31/1000 -> 0 | AA42: =IF(Z$10<>0,Z42/Z$10,0) -> 0
C43: 租税公課 | D43: =+月次PL!C36/1000 -> 124 | E43: =IF(D$10<>0,D43/D$10,0) -> 0.014366343 | F43: =+月次PL!D36/1000 -> 0 | G43: =IF(F$10<>0,F43/F$10,0) -> 0 | H43: =+月次PL!E36/1000 -> 0 | I43: =IF(H$10<>0,H43/H$10,0) -> 0 | J43: =+月次PL!F36/1000 -> 0 | K43: =IF(J$10<>0,J43/J$10,0) -> 0 | L43: =+月次PL!G36/1000 -> 0 | M43: =IF(L$10<>0,L43/L$10,0) -> 0 | N43: =+月次PL!H36/1000 -> 0 | O43: =IF(N$10<>0,N43/N$10,0) -> 0 | P43: =+月次PL!I36/1000 -> 0 | Q43: =IF(P$10<>0,P43/P$10,0) -> 0 | R43: =+月次PL!J36/1000 -> 0 | S43: =IF(R$10<>0,R43/R$10,0) -> 0 | T43: =+月次PL!K36/1000 -> 0 | U43: =IF(T$10<>0,T43/T$10,0) -> 0 | V43: =+月次PL!L36/1000 -> 0 | W43: =IF(V$10<>0,V43/V$10,0) -> 0 | X43: =+月次PL!M36/1000 -> 0 | Y43: =IF(X$10<>0,X43/X$10,0) -> 0 | Z43: =+月次PL!N36/1000 -> 0 | AA43: =IF(Z$10<>0,Z43/Z$10,0) -> 0
C44: 広告宣伝費 | D44: =+月次PL!C25/1000 -> 124.456 | E44: =IF(D$10<>0,D44/D$10,0) -> 0.014419174 | F44: =+月次PL!D25/1000 -> 0 | G44: =IF(F$10<>0,F44/F$10,0) -> 0 | H44: =+月次PL!E25/1000 -> 0 | I44: =IF(H$10<>0,H44/H$10,0) -> 0 | J44: =+月次PL!F25/1000 -> 0 | K44: =IF(J$10<>0,J44/J$10,0) -> 0 | L44: =+月次PL!G25/1000 -> 0 | M44: =IF(L$10<>0,L44/L$10,0) -> 0 | N44: =+月次PL!H25/1000 -> 0 | O44: =IF(N$10<>0,N44/N$10,0) -> 0 | P44: =+月次PL!I25/1000 -> 0 | Q44: =IF(P$10<>0,P44/P$10,0) -> 0 | R44: =+月次PL!J25/1000 -> 0 | S44: =IF(R$10<>0,R44/R$10,0) -> 0 | T44: =+月次PL!K25/1000 -> 0 | U44: =IF(T$10<>0,T44/T$10,0) -> 0 | V44: =+月次PL!L25/1000 -> 0 | W44: =IF(V$10<>0,V44/V$10,0) -> 0 | X44: =+月次PL!M25/1000 -> 0 | Y44: =IF(X$10<>0,X44/X$10,0) -> 0 | Z44: =+月次PL!N25/1000 -> 0 | AA44: =IF(Z$10<>0,Z44/Z$10,0) -> 0
C45: 支払手数料 | D45: =+月次PL!C37/1000 -> 208.468 | E45: =IF(D$10<>0,D45/D$10,0) -> 0.024152603 | F45: =+月次PL!D37/1000 -> 0 | G45: =IF(F$10<>0,F45/F$10,0) -> 0 | H45: =+月次PL!E37/1000 -> 0 | I45: =IF(H$10<>0,H45/H$10,0) -> 0 | J45: =+月次PL!F37/1000 -> 0 | K45: =IF(J$10<>0,J45/J$10,0) -> 0 | L45: =+月次PL!G37/1000 -> 0 | M45: =IF(L$10<>0,L45/L$10,0) -> 0 | N45: =+月次PL!H37/1000 -> 0 | O45: =IF(N$10<>0,N45/N$10,0) -> 0 | P45: =+月次PL!I37/1000 -> 0 | Q45: =IF(P$10<>0,P45/P$10,0) -> 0 | R45: =+月次PL!J37/1000 -> 0 | S45: =IF(R$10<>0,R45/R$10,0) -> 0 | T45: =+月次PL!K37/1000 -> 0 | U45: =IF(T$10<>0,T45/T$10,0) -> 0 | V45: =+月次PL!L37/1000 -> 0 | W45: =IF(V$10<>0,V45/V$10,0) -> 0 | X45: =+月次PL!M37/1000 -> 0 | Y45: =IF(X$10<>0,X45/X$10,0) -> 0 | Z45: =+月次PL!N37/1000 -> 0 | AA45: =IF(Z$10<>0,Z45/Z$10,0) -> 0
C46: 新聞図書費 | D46: =+月次PL!C39/1000 -> 0 | E46: =IF(D$10<>0,D46/D$10,0) -> 0 | F46: =+月次PL!D39/1000 -> 0 | G46: =IF(F$10<>0,F46/F$10,0) -> 0 | H46: =+月次PL!E39/1000 -> 0 | I46: =IF(H$10<>0,H46/H$10,0) -> 0 | J46: =+月次PL!F39/1000 -> 0 | K46: =IF(J$10<>0,J46/J$10,0) -> 0 | L46: =+月次PL!G39/1000 -> 0 | M46: =IF(L$10<>0,L46/L$10,0) -> 0 | N46: =+月次PL!H39/1000 -> 0 | O46: =IF(N$10<>0,N46/N$10,0) -> 0 | P46: =+月次PL!I39/1000 -> 0 | Q46: =IF(P$10<>0,P46/P$10,0) -> 0 | R46: =+月次PL!J39/1000 -> 0 | S46: =IF(R$10<>0,R46/R$10,0) -> 0 | T46: =+月次PL!K39/1000 -> 0 | U46: =IF(T$10<>0,T46/T$10,0) -> 0 | V46: =+月次PL!L39/1000 -> 0 | W46: =IF(V$10<>0,V46/V$10,0) -> 0 | X46: =+月次PL!M39/1000 -> 0 | Y46: =IF(X$10<>0,X46/X$10,0) -> 0 | Z46: =+月次PL!N39/1000 -> 0 | AA46: =IF(Z$10<>0,Z46/Z$10,0) -> 0
C47: 管理諸費 | D47: =+月次PL!C42/1000 -> 70 | E47: =IF(D$10<>0,D47/D$10,0) -> 0.0081100323 | F47: =+月次PL!D42/1000 -> 0 | G47: =IF(F$10<>0,F47/F$10,0) -> 0 | H47: =+月次PL!E42/1000 -> 0 | I47: =IF(H$10<>0,H47/H$10,0) -> 0 | J47: =+月次PL!F42/1000 -> 0 | K47: =IF(J$10<>0,J47/J$10,0) -> 0 | L47: =+月次PL!G42/1000 -> 0 | M47: =IF(L$10<>0,L47/L$10,0) -> 0 | N47: =+月次PL!H42/1000 -> 0 | O47: =IF(N$10<>0,N47/N$10,0) -> 0 | P47: =+月次PL!I42/1000 -> 0 | Q47: =IF(P$10<>0,P47/P$10,0) -> 0 | R47: =+月次PL!J42/1000 -> 0 | S47: =IF(R$10<>0,R47/R$10,0) -> 0 | T47: =+月次PL!K42/1000 -> 0 | U47: =IF(T$10<>0,T47/T$10,0) -> 0 | V47: =+月次PL!L42/1000 -> 0 | W47: =IF(V$10<>0,V47/V$10,0) -> 0 | X47: =+月次PL!M42/1000 -> 0 | Y47: =IF(X$10<>0,X47/X$10,0) -> 0 | Z47: =+月次PL!N42/1000 -> 0 | AA47: =IF(Z$10<>0,Z47/Z$10,0) -> 0
C48: 雑費 | D48: =+月次PL!C41/1000 -> 74.929 | E48: =IF(D$10<>0,D48/D$10,0) -> 0.0086810944 | F48: =+月次PL!D41/1000 -> 0 | G48: =IF(F$10<>0,F48/F$10,0) -> 0 | H48: =+月次PL!E41/1000 -> 0 | I48: =IF(H$10<>0,H48/H$10,0) -> 0 | J48: =+月次PL!F41/1000 -> 0 | K48: =IF(J$10<>0,J48/J$10,0) -> 0 | L48: =+月次PL!G41/1000 -> 0 | M48: =IF(L$10<>0,L48/L$10,0) -> 0 | N48: =+月次PL!H41/1000 -> 0 | O48: =IF(N$10<>0,N48/N$10,0) -> 0 | P48: =+月次PL!I41/1000 -> 0 | Q48: =IF(P$10<>0,P48/P$10,0) -> 0 | R48: =+月次PL!J41/1000 -> 0 | S48: =IF(R$10<>0,R48/R$10,0) -> 0 | T48: =+月次PL!K41/1000 -> 0 | U48: =IF(T$10<>0,T48/T$10,0) -> 0 | V48: =+月次PL!L41/1000 -> 0 | W48: =IF(V$10<>0,V48/V$10,0) -> 0 | X48: =+月次PL!M41/1000 -> 0 | Y48: =IF(X$10<>0,X48/X$10,0) -> 0 | Z48: =+月次PL!N41/1000 -> 0 | AA48: =IF(Z$10<>0,Z48/Z$10,0) -> 0
E49: =IF(D$10<>0,D49/D$10,0) -> 0 | G49: =IF(F$10<>0,F49/F$10,0) -> 0 | I49: =IF(H$10<>0,H49/H$10,0) -> 0 | K49: =IF(J$10<>0,J49/J$10,0) -> 0 | M49: =IF(L$10<>0,L49/L$10,0) -> 0 | O49: =IF(N$10<>0,N49/N$10,0) -> 0 | Q49: =IF(P$10<>0,P49/P$10,0) -> 0 | S49: =IF(R$10<>0,R49/R$10,0) -> 0 | U49: =IF(T$10<>0,T49/T$10,0) -> 0 | W49: =IF(V$10<>0,V49/V$10,0) -> 0 | Y49: =IF(X$10<>0,X49/X$10,0) -> 0 | AA49: =IF(Z$10<>0,Z49/Z$10,0) -> 0
B50: 営業損益 | D50: =+D22-D28 -> 414.148 | E50: =IF(D$10<>0,D50/D$10,0) -> 0.047982195 | F50: =+F22-F28 -> 0 | G50: =IF(F$10<>0,F50/F$10,0) -> 0 | H50: =+H22-H28 -> 0 | I50: =IF(H$10<>0,H50/H$10,0) -> 0 | J50: =+J22-J28 -> 0 | K50: =IF(J$10<>0,J50/J$10,0) -> 0 | L50: =+L22-L28 -> 0 | M50: =IF(L$10<>0,L50/L$10,0) -> 0 | N50: =+N22-N28 -> 0 | O50: =IF(N$10<>0,N50/N$10,0) -> 0 | P50: =+P22-P28 -> 0 | Q50: =IF(P$10<>0,P50/P$10,0) -> 0 | R50: =+R22-R28 -> 0 | S50: =IF(R$10<>0,R50/R$10,0) -> 0 | T50: =+T22-T28 -> 350 | U50: =IF(T$10<>0,T50/T$10,0) -> 1 | V50: =+V22-V28 -> 8454 | W50: =IF(V$10<>0,V50/V$10,0) -> 1 | X50: =+X22-X28 -> 9017 | Y50: =IF(X$10<>0,X50/X$10,0) -> 1 | Z50: =+Z22-Z28 -> 8610 | AA50: =IF(Z$10<>0,Z50/Z$10,0) -> 1
C51: 期中累計 | D51: =+D50 -> 414.148 | F51: =+D51+F50 -> 414.148 | H51: =+F51+H50 -> 414.148 | J51: =+H51+J50 -> 414.148 | L51: =+J51+L50 -> 414.148 | N51: =+L51+N50 -> 414.148 | P51: =+N51+P50 -> 414.148 | R51: =+P51+R50 -> 414.148 | T51: =+R51+T50 -> 764.148 | V51: =+T51+V50 -> 9218.148 | X51: =+V51+X50 -> 18235.148 | Z51: =+X51+Z50 -> 26845.148
B52: 営業外収益 | D52: =+月次PL!C50/1000 -> 0 | E52: =IF(D$10<>0,D52/D$10,0) -> 0 | F52: =+月次PL!D50/1000 -> 0 | G52: =IF(F$10<>0,F52/F$10,0) -> 0 | H52: =+月次PL!E50/1000 -> 0 | I52: =IF(H$10<>0,H52/H$10,0) -> 0 | J52: =+月次PL!F50/1000 -> 0 | K52: =IF(J$10<>0,J52/J$10,0) -> 0 | L52: =+月次PL!G50/1000 -> 0 | M52: =IF(L$10<>0,L52/L$10,0) -> 0 | N52: =+月次PL!H50/1000 -> 0 | O52: =IF(N$10<>0,N52/N$10,0) -> 0 | P52: =+月次PL!I50/1000 -> 0 | Q52: =IF(P$10<>0,P52/P$10,0) -> 0 | R52: =+月次PL!J50/1000 -> 0 | S52: =IF(R$10<>0,R52/R$10,0) -> 0 | T52: =+月次PL!K50/1000 -> 0 | U52: =IF(T$10<>0,T52/T$10,0) -> 0 | V52: =+月次PL!L50/1000 -> 0 | W52: =IF(V$10<>0,V52/V$10,0) -> 0 | X52: =+月次PL!M50/1000 -> 0 | Y52: =IF(X$10<>0,X52/X$10,0) -> 0 | Z52: =+月次PL!N50/1000 -> 0 | AA52: =IF(Z$10<>0,Z52/Z$10,0) -> 0
B53: 営業外費用 | D53: =+月次PL!C55/1000 -> 146.486 | E53: =IF(D$10<>0,D53/D$10,0) -> 0.016971517 | F53: =+月次PL!D55/1000 -> 0 | G53: =IF(F$10<>0,F53/F$10,0) -> 0 | H53: =+月次PL!E55/1000 -> 0 | I53: =IF(H$10<>0,H53/H$10,0) -> 0 | J53: =+月次PL!F55/1000 -> 0 | K53: =IF(J$10<>0,J53/J$10,0) -> 0 | L53: =+月次PL!G55/1000 -> 0 | M53: =IF(L$10<>0,L53/L$10,0) -> 0 | N53: =+月次PL!H55/1000 -> 0 | O53: =IF(N$10<>0,N53/N$10,0) -> 0 | P53: =+月次PL!I55/1000 -> 0 | Q53: =IF(P$10<>0,P53/P$10,0) -> 0 | R53: =+月次PL!J55/1000 -> 0 | S53: =IF(R$10<>0,R53/R$10,0) -> 0 | T53: =+月次PL!K55/1000 -> 0 | U53: =IF(T$10<>0,T53/T$10,0) -> 0 | V53: =+月次PL!L55/1000 -> 0 | W53: =IF(V$10<>0,V53/V$10,0) -> 0 | X53: =+月次PL!M55/1000 -> 0 | Y53: =IF(X$10<>0,X53/X$10,0) -> 0 | Z53: =+月次PL!N55/1000 -> 0 | AA53: =IF(Z$10<>0,Z53/Z$10,0) -> 0
B54: 経常損益 | D54: =+D50+D52-D53 -> 267.662 | E54: =IF(D$10<>0,D54/D$10,0) -> 0.031010678 | F54: =+F50+F52-F53 -> 0 | G54: =IF(F$10<>0,F54/F$10,0) -> 0 | H54: =+H50+H52-H53 -> 0 | I54: =IF(H$10<>0,H54/H$10,0) -> 0 | J54: =+J50+J52-J53 -> 0 | K54: =IF(J$10<>0,J54/J$10,0) -> 0 | L54: =+L50+L52-L53 -> 0 | M54: =IF(L$10<>0,L54/L$10,0) -> 0 | N54: =+N50+N52-N53 -> 0 | O54: =IF(N$10<>0,N54/N$10,0) -> 0 | P54: =+P50+P52-P53 -> 0 | Q54: =IF(P$10<>0,P54/P$10,0) -> 0 | R54: =+R50+R52-R53 -> 0 | S54: =IF(R$10<>0,R54/R$10,0) -> 0 | T54: =+T50+T52-T53 -> 350 | U54: =IF(T$10<>0,T54/T$10,0) -> 1 | V54: =+V50+V52-V53 -> 8454 | W54: =IF(V$10<>0,V54/V$10,0) -> 1 | X54: =+X50+X52-X53 -> 9017 | Y54: =IF(X$10<>0,X54/X$10,0) -> 1 | Z54: =+Z50+Z52-Z53 -> 8610 | AA54: =IF(Z$10<>0,Z54/Z$10,0) -> 1
C55: 期中累計 | D55: =+D54 -> 267.662 | F55: =+D55+F54 -> 267.662 | H55: =+F55+H54 -> 267.662 | J55: =+H55+J54 -> 267.662 | L55: =+J55+L54 -> 267.662 | N55: =+L55+N54 -> 267.662 | P55: =+N55+P54 -> 267.662 | R55: =+P55+R54 -> 267.662 | T55: =+R55+T54 -> 617.662 | V55: =+T55+V54 -> 9071.662 | X55: =+V55+X54 -> 18088.662 | Z55: =+X55+Z54 -> 26698.662
B56: 繰越利益剰余金(BS) | D56: =+BS千円!D80 -> -24246.8 | E56: =+D56/BS千円!D93 -> -0.19734616 | F56: =+BS千円!E80 -> 0 | G56: =+F56/BS千円!E93 -> #DIV/0! | H56: =+BS千円!F80 -> 0 | I56: =+H56/BS千円!F93 -> #DIV/0! | J56: =+BS千円!G80 -> 0 | K56: =+J56/BS千円!G93 -> #DIV/0! | L56: =+BS千円!H80 -> 0 | M56: =+L56/BS千円!H93 -> #DIV/0! | N56: =+BS千円!I80 -> 0 | O56: =+N56/BS千円!I93 -> #DIV/0! | P56: =+BS千円!J80 -> 0 | Q56: =+P56/BS千円!J93 -> #DIV/0! | R56: =+BS千円!K80 -> 0 | S56: =+R56/BS千円!K93 -> #DIV/0! | T56: =+BS千円!L80 -> 0 | U56: =+T56/BS千円!L93 -> #DIV/0! | V56: =+BS千円!M80 -> 0 | W56: =+V56/BS千円!M93 -> #DIV/0! | X56: =+BS千円!N80 -> 0 | Y56: =+X56/BS千円!N93 -> #DIV/0! | Z56: =+BS千円!O80 -> 0 | AA56: =+Z56/BS千円!Z92 -> #DIV/0!
C57: FL | D57: =+D16+D29 -> 4484.152 | E57: =+D57/D10 -> 0.51952311 | F57: =+F16+F29 -> 0 | G57: =+F57/F10 -> #DIV/0! | H57: =+H16+H29 -> 0 | I57: =+H57/H10 -> #DIV/0! | J57: =+J16+J29 -> 0 | K57: =+J57/J10 -> #DIV/0! | L57: =+L16+L29 -> 0 | M57: =+L57/L10 -> #DIV/0! | N57: =+N16+N29 -> 0 | O57: =+N57/N10 -> #DIV/0! | P57: =+P16+P29 -> 0 | Q57: =+P57/P10 -> #DIV/0! | R57: =+R16+R29 -> 0 | S57: =+R57/R10 -> #DIV/0! | T57: =+T16+T29 -> 0 | U57: =+T57/T10 -> 0 | V57: =+V16+V29 -> 0 | W57: =+V57/V10 -> 0 | X57: =+X16+X29 -> 0 | Y57: =+X57/X10 -> 0 | Z57: =+Z16+Z29 -> 0 | AA57: =+Z57/Z10 -> 0
C58: FL(除くサウナ) | D58: =+D57-D21 -> 4457.152 | E58: =+D58/D59 -> 0.58200393 | F58: =+F57-F21 -> 0 | G58: =+F58/F59 -> #DIV/0! | H58: =+H57-H21 -> 0 | I58: =+H58/H59 -> #DIV/0! | J58: =+J57-J21 -> 0 | K58: =+J58/J59 -> 0 | L58: =+L57-L21 -> 0 | M58: =+L58/L59 -> 0 | N58: =+N57-N21 -> 0 | O58: =+N58/N59 -> 0 | P58: =+P57-P21 -> 0 | Q58: =+P58/P59 -> 0 | R58: =+R57-R21 -> -62 | S58: =+R58/R59 -> 0.17714286 | T58: =+T57-T21 -> -32 | U58: =+T58/T59 -> #DIV/0! | V58: =+V57-V21 -> -33 | W58: =+V58/V59 -> -0.0045255074 | X58: =+X57-X21 -> -52 | Y58: =+X58/X59 -> -0.0070863996 | Z58: =+Z57-Z21 -> -23 | AA58: =+Z58/Z59 -> -0.0031216069
C59: 売上(除くサウナ・家賃) | D59: =+D10-D15 -> 7658.285 | F59: =+F10-F15 -> 0 | H59: =+H10-H15 -> 0 | J59: =+J10-200-J15 -> -200 | L59: =+L10-L15-350 -> -350 | N59: =+N10-N15-350 -> -350 | P59: =+P10-P15-350 -> -350 | R59: =+R10-R15-350 -> -350 | T59: =+T10-T15-350 -> 0 | V59: =+V10-V15-350 -> 7292 | X59: =+X10-X15-350 -> 7338 | Z59: =+Z10-Z15-350 -> 7368

Sheet PL予実対比
A7: ■月次PL予実対比
A8: =+PL推移!B8 -> 2026 | B8: 年度 | C8: 注意事項 | D8: 概算値 | E8: 異常値 | F8: 特記事項 | G8: 予算検討 | BB8: 単位：千円
A9: 項目 | C9: =+PL推移!D9 -> 7月 | G9: =+PL推移!F9 -> 8月 | K9: =+PL推移!H9 -> 9月 | O9: =+PL推移!J9 -> 10月 | S9: =+PL推移!L9 -> 11月 | W9: =+PL推移!N9 -> 12月 | AA9: =+PL推移!P9 -> 1月 | AE9: =+PL推移!R9 -> 2月 | AI9: =+PL推移!T9 -> 3 | AM9: =+PL推移!V9 -> 4 | AQ9: =+PL推移!X9 -> 5月 | AU9: =+PL推移!Z9 -> 6月 | AY9: 累計 | BC9: =+PL推移!N9 -> 12月 | BE9: =+PL推移!P9 -> 1月 | BG9: =+PL推移!R9 -> 2月 | BI9: =+PL推移!T9 -> 3 | BK9: =+PL推移!V9 -> 4 | BM9: =+PL推移!X9 -> 5月 | BO9: =+PL推移!Z9 -> 6月
C10: 計画 | D10: 実績 | E10: 差異 | F10: 計画比 | G10: 計画 | H10: 実績 | I10: 差異 | J10: 計画比 | K10: 計画 | L10: 実績 | M10: 差異 | N10: 計画比 | O10: 計画 | P10: 実績 | Q10: 差異 | R10: 計画比 | S10: 計画 | T10: 実績 | U10: 差異 | V10: 計画比 | W10: 計画 | X10: 実績 | Y10: 差異 | Z10: 計画比 | AA10: 計画 | AB10: 実績 | AC10: 差異 | AD10: 計画比 | AE10: 計画 | AF10: 実績 | AG10: 差異 | AH10: 計画比 | AI10: 計画 | AJ10: 実績 | AK10: 差異 | AL10: 計画比 | AM10: 計画 | AN10: 実績 | AO10: 差異 | AP10: 計画比 | AQ10: 計画 | AR10: 実績 | AS10: 差異 | AT10: 計画比 | AU10: 計画 | AV10: 実績 | AW10: 差異 | AX10: 計画比 | AY10: 計画 | AZ10: 実績 | BA10: 差異 | BB10: 計画比
A11: 売上高 | C11: =+収支計画!G17/1000 -> 9250 | D11: =+PL推移!D10 -> 8631.285 | E11: =SUM(E12:E16) -> -618 | F11: =IF(C11<>0,D11/C11,"-") -> 0.93311189 | G11: =SUM(G12:G16) -> 9250 | H11: =SUM(H12:H16) -> 0 | I11: =SUM(I12:I16) -> -9250 | J11: =IF(G11<>0,H11/G11,"-") -> 0 | K11: =SUM(K12:K16) -> 10750 | L11: =+PL推移!H10 -> 0 | M11: =SUM(M12:M16) -> -10750 | N11: =IF(K11<>0,L11/K11,"-") -> 0 | O11: =SUM(O12:O16) -> 0 | P11: =+PL推移!J10 -> 0 | Q11: =SUM(Q12:Q16) -> 0 | R11: =IF(O11<>0,P11/O11,"-") -> - | S11: =SUM(S12:S16) -> 0 | T11: =+PL推移!L10 -> 0 | U11: =SUM(U12:U16) -> 0 | V11: =IF(S11<>0,T11/S11,"-") -> - | W11: =SUM(W12:W16) -> 0 | X11: =+PL推移!N10 -> 0 | Y11: =SUM(Y12:Y16) -> 0 | Z11: =IF(W11<>0,X11/W11,"-") -> - | AA11: =SUM(AA12:AA16) -> 0 | AB11: =+PL推移!P10 -> 0 | AC11: =SUM(AC12:AC16) -> 0 | AD11: =IF(AA11<>0,AB11/AA11,"-") -> - | AE11: =SUM(AE12:AE16) -> 0 | AF11: =+PL推移!R10 -> 0 | AG11: =SUM(AG12:AG16) -> 0 | AH11: =IF(AE11<>0,AF11/AE11,"-") -> - | AI11: =SUM(AI12:AI16) -> 0 | AJ11: =+PL推移!T10 -> 350 | AK11: =SUM(AK12:AK16) -> 0 | AL11: =IF(AI11<>0,AJ11/AI11,"-") -> - | AM11: =+収支計画!AE17/1000 -> 0 | AN11: =+PL推移!V10 -> 8454 | AO11: =+AN11-AM11 -> 8454 | AP11: =IF(AM11<>0,AN11/AM11,"-") -> - | AQ11: =+収支計画!AI17/1000 -> 0 | AR11: =+PL推移!X10 -> 9017 | AS11: =+AR11-AQ11 -> 9017 | AT11: =IF(AQ11<>0,AR11/AQ11,"-") -> - | AU11: =+収支計画!AI17/1000 -> 0 | AV11: =+PL推移!Z10 -> 8610 | AW11: =+AV11-AU11 -> 8610 | AX11: =IF(AU11<>0,AV11/AU11,"-") -> - | AY11: =+C11+G11+K11+O11+S11+W11+AA11+AE11+AI11+AM11+AQ11+AU11 -> 29250 | AZ11: =+D11+H11+L11+P11+T11+X11+AB11+AF11+AJ11+AN11+AR11+AV11 -> 35062.285 | BA11: =+AZ11-AY11 -> 5812.285 | BB11: =IF(AY11<>0,AZ11/AY11,"-") -> 1.1987106 | BC11: =+PL推移!N10-収支計画!W17/1000 -> 0 | BD11: =+BC11/(収支計画!W17/1000) -> #DIV/0! | BE11: =+PL推移!P10-収支計画!Y17/1000 -> 0 | BF11: =+BE11/(収支計画!Y17/1000) -> #DIV/0! | BG11: =+PL推移!R10-収支計画!AA17/1000 -> 0 | BH11: =+BG11/(収支計画!AA17/1000) -> #DIV/0! | BI11: =+PL推移!T10-収支計画!AC17/1000 -> 350 | BJ11: =+BI11/(収支計画!AC17/1000) -> #DIV/0! | BK11: =+PL推移!V10-収支計画!AE17/1000 -> 8454 | BL11: =+BK11/(収支計画!AE17/1000) -> #DIV/0! | BM11: =+PL推移!X10-収支計画!AG17/1000 -> 9017 | BN11: =+BM11/(収支計画!AG17/1000) -> #DIV/0! | BO11: =+PL推移!Z10-収支計画!AI17/1000 -> 8610 | BP11: =+BO11/(収支計画!AI17/1000) -> #DIV/0!
B12: 恵愛 | C12: =+収支計画!G11/1000 -> 7000 | D12: =+PL推移!D11 -> 6425 | E12: =+D12-C12 -> -575 | F12: =IF(C12<>0,D12/C12,"-") -> 0.91785714 | G12: =+収支計画!K11/1000 -> 7000 | H12: =+PL推移!F11 -> 0 | I12: =+H12-G12 -> -7000 | J12: =IF(G12<>0,H12/G12,"-") -> 0 | K12: =+収支計画!O11/1000 -> 8500 | L12: =+PL推移!H11 -> 0 | M12: =+L12-K12 -> -8500 | N12: =IF(K12<>0,L12/K12,"-") -> 0 | O12: =+収支計画!S11/1000 -> 0 | P12: =+PL推移!J11 -> 0 | Q12: =+P12-O12 -> 0 | R12: =IF(O12<>0,P12/O12,"-") -> - | S12: =+収支計画!U11/1000 -> 0 | T12: =+PL推移!L11 -> 0 | U12: =+T12-S12 -> 0 | V12: =IF(S12<>0,T12/S12,"-") -> - | W12: =+収支計画!W11/1000 -> 0 | X12: =+PL推移!N11 -> 0 | Y12: =+X12-W12 -> 0 | Z12: =IF(W12<>0,X12/W12,"-") -> - | AA12: =+収支計画!AA11/1000 -> 0 | AB12: =+PL推移!P11 -> 0 | AC12: =+AB12-AA12 -> 0 | AD12: =IF(AA12<>0,AB12/AA12,"-") -> - | AE12: =+収支計画!AA11/1000 -> 0 | AF12: =+PL推移!R11 -> 0 | AG12: =+AF12-AE12 -> 0 | AH12: =IF(AE12<>0,AF12/AE12,"-") -> - | AI12: =+収支計画!AC11/1000 -> 0 | AJ12: =+PL推移!T11 -> 0 | AK12: =+AJ12-AI12 -> 0 | AL12: =IF(AI12<>0,AJ12/AI12,"-") -> - | AM12: =+収支計画!AG11/1000 -> 0 | AN12: =+PL推移!V11 -> 6013 | AO12: =+AN12-AM12 -> 6013 | AP12: =IF(AM12<>0,AN12/AM12,"-") -> - | AQ12: =+収支計画!AG11/1000 -> 0 | AR12: =+PL推移!X11 -> 6855 | AS12: =+AR12-AQ12 -> 6855 | AT12: =IF(AQ12<>0,AR12/AQ12,"-") -> - | AU12: =+収支計画!AI11/1000 -> 0 | AV12: =+PL推移!Z11 -> 6185 | AW12: =+AV12-AU12 -> 6185 | AX12: =IF(AU12<>0,AV12/AU12,"-") -> - | AY12: =+C12+G12+K12+O12+S12+W12+AA12+AE12+AI12+AM12+AQ12+AU12 -> 22500 | AZ12: =+D12+H12+L12+P12+T12+X12+AB12+AF12+AJ12+AN12+AR12+AV12 -> 25478 | BA12: =+AZ12-AY12 -> 2978 | BB12: =IF(AY12<>0,AZ12/AY12,"-") -> 1.1323556 | BC12: =+PL推移!N11-収支計画!W11/1000 -> 0 | BD12: =+BC12/(収支計画!W11/1000) -> #DIV/0! | BE12: =+PL推移!P11-収支計画!Y11/1000 -> 0 | BF12: =+BE12/(収支計画!Y11/1000) -> #DIV/0! | BG12: =+PL推移!R11-収支計画!AA11/1000 -> 0 | BH12: =+BG12/(収支計画!AA11/1000) -> #DIV/0! | BI12: =+PL推移!T11-収支計画!AC11/1000 -> 0 | BJ12: =+BI12/(収支計画!AC11/1000) -> #DIV/0! | BK12: =+PL推移!V11-収支計画!AE11/1000 -> 6013 | BL12: =+BK12/(収支計画!AE11/1000) -> #DIV/0! | BM12: =+PL推移!X11-収支計画!AG11/1000 -> 6855 | BN12: =+BM12/(収支計画!AG11/1000) -> #DIV/0! | BO12: =+PL推移!Z11-収支計画!AI11/1000 -> 6185 | BP12: =+BO12/(収支計画!AI11/1000) -> #DIV/0!
B13: 村 | C13: =+収支計画!G12/1000 -> 750 | D13: =+PL推移!D12 -> 646 | E13: =+D13-C13 -> -104 | F13: =IF(C13<>0,D13/C13,"-") -> 0.86133333 | G13: =+収支計画!K12/1000 -> 750 | H13: =+PL推移!F12 -> 0 | I13: =+H13-G13 -> -750 | J13: =IF(G13<>0,H13/G13,"-") -> 0 | K13: =+収支計画!O12/1000 -> 750 | L13: =+PL推移!H12 -> 0 | M13: =+L13-K13 -> -750 | N13: =IF(K13<>0,L13/K13,"-") -> 0 | O13: =+収支計画!S12/1000 -> 0 | P13: =+PL推移!J12 -> 0 | Q13: =+P13-O13 -> 0 | R13: =IF(O13<>0,P13/O13,"-") -> - | S13: =+収支計画!U12/1000 -> 0 | T13: =+PL推移!L12 -> 0 | U13: =+T13-S13 -> 0 | V13: =IF(S13<>0,T13/S13,"-") -> - | W13: =+収支計画!W12/1000 -> 0 | X13: =+PL推移!N12 -> 0 | Y13: =+X13-W13 -> 0 | Z13: =IF(W13<>0,X13/W13,"-") -> - | AA13: =+収支計画!AA12/1000 -> 0 | AB13: =+PL推移!P12 -> 0 | AC13: =+AB13-AA13 -> 0 | AD13: =IF(AA13<>0,AB13/AA13,"-") -> - | AE13: =+収支計画!AA12/1000 -> 0 | AF13: =+PL推移!R12 -> 0 | AG13: =+AF13-AE13 -> 0 | AH13: =IF(AE13<>0,AF13/AE13,"-") -> - | AI13: =+収支計画!AC12/1000 -> 0 | AJ13: =+PL推移!T12 -> 0 | AK13: =+AJ13-AI13 -> 0 | AL13: =IF(AI13<>0,AJ13/AI13,"-") -> - | AM13: =+収支計画!AG12/1000 -> 0 | AN13: =+PL推移!V12 -> 791 | AO13: =+AN13-AM13 -> 791 | AP13: =IF(AM13<>0,AN13/AM13,"-") -> - | AQ13: =+収支計画!AG12/1000 -> 0 | AR13: =+PL推移!X12 -> 0 | AS13: =+AR13-AQ13 -> 0 | AT13: =IF(AQ13<>0,AR13/AQ13,"-") -> - | AU13: =+収支計画!AI12/1000 -> 0 | AV13: =+PL推移!Z12 -> 0 | AW13: =+AV13-AU13 -> 0 | AX13: =IF(AU13<>0,AV13/AU13,"-") -> - | AY13: =+C13+G13+K13+O13+S13+W13+AA13+AE13+AI13+AM13+AQ13+AU13 -> 2250 | AZ13: =+D13+H13+L13+P13+T13+X13+AB13+AF13+AJ13+AN13+AR13+AV13 -> 1437 | BA13: =+AZ13-AY13 -> -813 | BB13: =IF(AY13<>0,AZ13/AY13,"-") -> 0.63866667 | BC13: =+PL推移!N12-収支計画!W12/1000 -> 0 | BD13: =+BC13/(収支計画!W12/1000) -> #DIV/0! | BE13: =+PL推移!P12-収支計画!Y12/1000 -> 0 | BF13: =+BE13/(収支計画!Y12/1000) -> #DIV/0! | BG13: =+PL推移!R12-収支計画!AA12/1000 -> 0 | BH13: =+BG13/(収支計画!AA12/1000) -> #DIV/0! | BI13: =+PL推移!T12-収支計画!AC12/1000 -> 0 | BJ13: =+BI13/(収支計画!AC12/1000) -> #DIV/0! | BK13: =+PL推移!V12-収支計画!AE12/1000 -> 791 | BL13: =+BK13/(収支計画!AE12/1000) -> #DIV/0! | BM13: =+PL推移!X12-収支計画!AG12/1000 -> 0 | BN13: =+BM13/(収支計画!AG12/1000) -> #DIV/0! | BO13: =+PL推移!Z12-収支計画!AI12/1000 -> 0 | BP13: =+BO13/(収支計画!AI12/1000) -> #DIV/0!
B14: 弁当 | C14: =+収支計画!G13/1000 -> 350 | D14: =+PL推移!D13 -> 525 | E14: =+D14-C14 -> 175 | F14: =IF(C14<>0,D14/C14,"-") -> 1.5 | G14: =+収支計画!K13/1000 -> 350 | H14: =+PL推移!F13 -> 0 | I14: =+H14-G14 -> -350 | J14: =IF(G14<>0,H14/G14,"-") -> 0 | K14: =+収支計画!O13/1000 -> 350 | L14: =+PL推移!H13 -> 0 | M14: =+L14-K14 -> -350 | N14: =IF(K14<>0,L14/K14,"-") -> 0 | O14: =+収支計画!S13/1000 -> 0 | P14: =+PL推移!J13 -> 0 | Q14: =+P14-O14 -> 0 | R14: =IF(O14<>0,P14/O14,"-") -> - | S14: =+収支計画!U13/1000 -> 0 | T14: =+PL推移!L13 -> 0 | U14: =+T14-S14 -> 0 | V14: =IF(S14<>0,T14/S14,"-") -> - | W14: =+収支計画!W13/1000 -> 0 | X14: =+PL推移!N13 -> 0 | Y14: =+X14-W14 -> 0 | Z14: =IF(W14<>0,X14/W14,"-") -> - | AA14: =+収支計画!AA13/1000 -> 0 | AB14: =+PL推移!P13 -> 0 | AC14: =+AB14-AA14 -> 0 | AD14: =IF(AA14<>0,AB14/AA14,"-") -> - | AE14: =+収支計画!AA13/1000 -> 0 | AF14: =+PL推移!R13 -> 0 | AG14: =+AF14-AE14 -> 0 | AH14: =IF(AE14<>0,AF14/AE14,"-") -> - | AI14: =+収支計画!AC13/1000 -> 0 | AJ14: =+PL推移!T13 -> 0 | AK14: =+AJ14-AI14 -> 0 | AL14: =IF(AI14<>0,AJ14/AI14,"-") -> - | AM14: =+収支計画!AG13/1000 -> 0 | AN14: =+PL推移!V13 -> 360 | AO14: =+AN14-AM14 -> 360 | AP14: =IF(AM14<>0,AN14/AM14,"-") -> - | AQ14: =+収支計画!AG13/1000 -> 0 | AR14: =+PL推移!X13 -> 375 | AS14: =+AR14-AQ14 -> 375 | AT14: =IF(AQ14<>0,AR14/AQ14,"-") -> - | AU14: =+収支計画!AI13/1000 -> 0 | AV14: =+PL推移!Z13 -> 405 | AW14: =+AV14-AU14 -> 405 | AX14: =IF(AU14<>0,AV14/AU14,"-") -> - | AY14: =+C14+G14+K14+O14+S14+W14+AA14+AE14+AI14+AM14+AQ14+AU14 -> 1050 | AZ14: =+D14+H14+L14+P14+T14+X14+AB14+AF14+AJ14+AN14+AR14+AV14 -> 1665 | BA14: =+AZ14-AY14 -> 615 | BB14: =IF(AY14<>0,AZ14/AY14,"-") -> 1.5857143 | BC14: =+PL推移!N13-収支計画!W13/1000 -> 0 | BD14: =+BC14/(収支計画!W13/1000) -> #DIV/0! | BE14: =+PL推移!P13-収支計画!Y13/1000 -> 0 | BF14: =+BE14/(収支計画!Y13/1000) -> #DIV/0! | BG14: =+PL推移!R13-収支計画!AA13/1000 -> 0 | BH14: =+BG14/(収支計画!AA13/1000) -> #DIV/0! | BI14: =+PL推移!T13-収支計画!AC13/1000 -> 0 | BJ14: =+BI14/(収支計画!AC13/1000) -> #DIV/0! | BK14: =+PL推移!V13-収支計画!AE13/1000 -> 360 | BL14: =+BK14/(収支計画!AE13/1000) -> #DIV/0! | BM14: =+PL推移!X13-収支計画!AG13/1000 -> 375 | BN14: =+BM14/(収支計画!AG13/1000) -> #DIV/0! | BO14: =+PL推移!Z13-収支計画!AI13/1000 -> 405 | BP14: =+BO14/(収支計画!AI13/1000) -> #DIV/0!
B15: シェア | C15: =+収支計画!G14/1000 -> 150 | D15: =+PL推移!D14 -> 63 | E15: =+D15-C15 -> -87 | F15: =IF(C15<>0,D15/C15,"-") -> 0.42 | G15: =+収支計画!K14/1000 -> 150 | H15: =+PL推移!F14 -> 0 | I15: =+H15-G15 -> -150 | J15: =IF(G15<>0,H15/G15,"-") -> 0 | K15: =+収支計画!O14/1000 -> 150 | L15: =+PL推移!H14 -> 0 | M15: =+L15-K15 -> -150 | N15: =IF(K15<>0,L15/K15,"-") -> 0 | O15: =+収支計画!S14/1000 -> 0 | P15: =+PL推移!J14 -> 0 | Q15: =+P15-O15 -> 0 | R15: =IF(O15<>0,P15/O15,"-") -> - | S15: =+収支計画!U14/1000 -> 0 | T15: =+PL推移!L14 -> 0 | U15: =+T15-S15 -> 0 | V15: =IF(S15<>0,T15/S15,"-") -> - | W15: =+収支計画!W14/1000 -> 0 | X15: =+PL推移!N14 -> 0 | Y15: =+X15-W15 -> 0 | Z15: =IF(W15<>0,X15/W15,"-") -> - | AA15: =+収支計画!AA14/1000 -> 0 | AB15: =+PL推移!P14 -> 0 | AC15: =+AB15-AA15 -> 0 | AD15: =IF(AA15<>0,AB15/AA15,"-") -> - | AE15: =+収支計画!AA14/1000 -> 0 | AF15: =+PL推移!R14 -> 0 | AG15: =+AF15-AE15 -> 0 | AH15: =IF(AE15<>0,AF15/AE15,"-") -> - | AI15: =+収支計画!AC14/1000 -> 0 | AJ15: =+PL推移!T14 -> 0 | AK15: =+AJ15-AI15 -> 0 | AL15: =IF(AI15<>0,AJ15/AI15,"-") -> - | AM15: =+収支計画!AG14/1000 -> 0 | AN15: =+PL推移!V14 -> 128 | AO15: =+AN15-AM15 -> 128 | AP15: =IF(AM15<>0,AN15/AM15,"-") -> - | AQ15: =+収支計画!AG14/1000 -> 0 | AR15: =+PL推移!X14 -> 108 | AS15: =+AR15-AQ15 -> 108 | AT15: =IF(AQ15<>0,AR15/AQ15,"-") -> - | AU15: =+収支計画!AI14/1000 -> 0 | AV15: =+PL推移!Z14 -> 122 | AW15: =+AV15-AU15 -> 122 | AX15: =IF(AU15<>0,AV15/AU15,"-") -> - | AY15: =+C15+G15+K15+O15+S15+W15+AA15+AE15+AI15+AM15+AQ15+AU15 -> 450 | AZ15: =+D15+H15+L15+P15+T15+X15+AB15+AF15+AJ15+AN15+AR15+AV15 -> 421 | BA15: =+AZ15-AY15 -> -29 | BB15: =IF(AY15<>0,AZ15/AY15,"-") -> 0.93555556 | BC15: =+PL推移!N14-収支計画!W14/1000 -> 0 | BD15: =+BC15/(収支計画!W14/1000) -> #DIV/0! | BE15: =+PL推移!P14-収支計画!Y14/1000 -> 0 | BF15: =+BE15/(収支計画!Y14/1000) -> #DIV/0! | BG15: =+PL推移!R14-収支計画!AA14/1000 -> 0 | BH15: =+BG15/(収支計画!AA14/1000) -> #DIV/0! | BI15: =+PL推移!T14-収支計画!AC14/1000 -> 0 | BJ15: =+BI15/(収支計画!AC14/1000) -> #DIV/0! | BK15: =+PL推移!V14-収支計画!AE14/1000 -> 128 | BL15: =+BK15/(収支計画!AE14/1000) -> #DIV/0! | BM15: =+PL推移!X14-収支計画!AG14/1000 -> 108 | BN15: =+BM15/(収支計画!AG14/1000) -> #DIV/0! | BO15: =+PL推移!Z14-収支計画!AI14/1000 -> 122 | BP15: =+BO15/(収支計画!AI14/1000) -> #DIV/0!
B16: サウナ | C16: =+収支計画!G15/1000 -> 1000 | D16: =+PL推移!D15 -> 973 | E16: =+D16-C16 -> -27 | F16: =IF(C16<>0,D16/C16,"-") -> 0.973 | G16: =+収支計画!K15/1000 -> 1000 | H16: =+PL推移!F15 -> 0 | I16: =+H16-G16 -> -1000 | J16: =IF(G16<>0,H16/G16,"-") -> 0 | K16: =+収支計画!O15/1000 -> 1000 | L16: =+PL推移!H15 -> 0 | M16: =+L16-K16 -> -1000 | N16: =IF(K16<>0,L16/K16,"-") -> 0 | O16: =+収支計画!S15/1000 -> 0 | P16: =+PL推移!J15 -> 0 | Q16: =+P16-O16 -> 0 | R16: =IF(O16<>0,P16/O16,"-") -> - | S16: =+収支計画!U15/1000 -> 0 | T16: =+PL推移!L15 -> 0 | U16: =+T16-S16 -> 0 | V16: =IF(S16<>0,T16/S16,"-") -> - | W16: =+収支計画!W15/1000 -> 0 | X16: =+PL推移!N15 -> 0 | Y16: =+X16-W16 -> 0 | Z16: =IF(W16<>0,X16/W16,"-") -> - | AA16: =+収支計画!AA15/1000 -> 0 | AB16: =+PL推移!P15 -> 0 | AC16: =+AB16-AA16 -> 0 | AD16: =IF(AA16<>0,AB16/AA16,"-") -> - | AE16: =+収支計画!AA15/1000 -> 0 | AF16: =+PL推移!R15 -> 0 | AG16: =+AF16-AE16 -> 0 | AH16: =IF(AE16<>0,AF16/AE16,"-") -> - | AI16: =+収支計画!AC15/1000 -> 0 | AJ16: =+PL推移!T15 -> 0 | AK16: =+AJ16-AI16 -> 0 | AL16: =IF(AI16<>0,AJ16/AI16,"-") -> - | AM16: =+収支計画!AG15/1000 -> 0 | AN16: =+PL推移!V15 -> 812 | AO16: =+AN16-AM16 -> 812 | AP16: =IF(AM16<>0,AN16/AM16,"-") -> - | AQ16: =+収支計画!AG15/1000 -> 0 | AR16: =+PL推移!X15 -> 1329 | AS16: =+AR16-AQ16 -> 1329 | AT16: =IF(AQ16<>0,AR16/AQ16,"-") -> - | AU16: =+収支計画!AI15/1000 -> 0 | AV16: =+PL推移!Z15 -> 892 | AW16: =+AV16-AU16 -> 892 | AX16: =IF(AU16<>0,AV16/AU16,"-") -> - | AY16: =+C16+G16+K16+O16+S16+W16+AA16+AE16+AI16+AM16+AQ16+AU16 -> 3000 | AZ16: =+D16+H16+L16+P16+T16+X16+AB16+AF16+AJ16+AN16+AR16+AV16 -> 4006 | BA16: =+AZ16-AY16 -> 1006 | BB16: =IF(AY16<>0,AZ16/AY16,"-") -> 1.3353333 | BC16: =+PL推移!N15-収支計画!W15/1000 -> 0 | BD16: =+BC16/(収支計画!W15/1000) -> #DIV/0! | BE16: =+PL推移!P15-収支計画!Y15/1000 -> 0 | BF16: =+BE16/(収支計画!Y15/1000) -> #DIV/0! | BG16: =+PL推移!R15-収支計画!AA15/1000 -> 0 | BH16: =+BG16/(収支計画!AA15/1000) -> #DIV/0! | BI16: =+PL推移!T15-収支計画!AC15/1000 -> 0 | BJ16: =+BI16/(収支計画!AC15/1000) -> #DIV/0! | BK16: =+PL推移!V15-収支計画!AE15/1000 -> 812 | BL16: =+BK16/(収支計画!AE15/1000) -> #DIV/0! | BM16: =+PL推移!X15-収支計画!AG15/1000 -> 1329 | BN16: =+BM16/(収支計画!AG15/1000) -> #DIV/0! | BO16: =+PL推移!Z15-収支計画!AI15/1000 -> 892 | BP16: =+BO16/(収支計画!AI15/1000) -> #DIV/0!
A17: 売上原価 | C17: =SUM(C18:C22) -> 2200 | D17: =+PL推移!D16 -> 2021.276 | E17: =SUM(E18:E22) -> -178 | F17: =IF(C17<>0,D17/C17,"-") -> 0.91876182 | G17: =SUM(G18:G22) -> 2132.5 | H17: =+PL推移!F16 -> 0 | I17: =SUM(I18:I22) -> -2132.5 | J17: =IF(G17<>0,H17/G17,"-") -> 0 | K17: =SUM(K18:K22) -> 2507.5 | L17: =+PL推移!H16 -> 0 | M17: =SUM(M18:M22) -> -2507.5 | N17: =IF(K17<>0,L17/K17,"-") -> 0 | O17: =SUM(O18:O22) -> 0 | P17: =+PL推移!J16 -> 0 | Q17: =SUM(Q18:Q22) -> 0 | R17: =IF(O17<>0,P17/O17,"-") -> - | S17: =SUM(S18:S22) -> 0 | T17: =+PL推移!L16 -> 0 | U17: =SUM(U18:U22) -> 0 | V17: =IF(S17<>0,T17/S17,"-") -> - | W17: =SUM(W18:W22) -> 0 | X17: =+PL推移!N16 -> 0 | Y17: =SUM(Y18:Y22) -> 0 | Z17: =IF(W17<>0,X17/W17,"-") -> - | AA17: =SUM(AA18:AA22) -> 0 | AB17: =+PL推移!P16 -> 0 | AC17: =SUM(AC18:AC22) -> 0 | AD17: =IF(AA17<>0,AB17/AA17,"-") -> - | AE17: =SUM(AE18:AE22) -> 0 | AF17: =+PL推移!R16 -> 0 | AG17: =SUM(AG18:AG22) -> 1900 | AH17: =IF(AE17<>0,AF17/AE17,"-") -> - | AI17: =SUM(AI18:AI22) -> 0 | AJ17: =+PL推移!T16 -> 0 | AK17: =SUM(AK18:AK22) -> 2266 | AL17: =IF(AI17<>0,AJ17/AI17,"-") -> - | AM17: =SUM(AM18:AM22) -> 0 | AN17: =+PL推移!V16 -> 0 | AO17: =+AN17-AM17 -> 0 | AP17: =IF(AM17<>0,AN17/AM17,"-") -> - | AQ17: =SUM(AQ18:AQ22) -> 0 | AR17: =+PL推移!X16 -> 0 | AS17: =+AR17-AQ17 -> 0 | AT17: =IF(AQ17<>0,AR17/AQ17,"-") -> - | AU17: =+収支計画!AI24/1000 -> 0 | AV17: =+PL推移!Z16 -> 0 | AW17: =+AV17-AU17 -> 0 | AX17: =IF(AU17<>0,AV17/AU17,"-") -> - | AY17: =+C17+G17+K17+O17+S17+W17+AA17+AE17+AI17+AM17+AQ17+AU17 -> 6840 | AZ17: =+D17+H17+L17+P17+T17+X17+AB17+AF17+AJ17+AN17+AR17+AV17 -> 2021.276 | BA17: =+AZ17-AY17 -> -4818.724 | BB17: =IF(AY17<>0,AZ17/AY17,"-") -> 0.29550819 | BC17: =+PL推移!N16-収支計画!W24/1000 -> 0 | BD17: =+BC17/(収支計画!W24/1000) -> #DIV/0! | BE17: =+PL推移!P16-収支計画!Y24/1000 -> 0 | BF17: =+BE17/(収支計画!Y24/1000) -> #DIV/0! | BG17: =+PL推移!R16-収支計画!AA24/1000 -> 0 | BH17: =+BG17/(収支計画!AA24/1000) -> #DIV/0! | BI17: =+PL推移!T16-収支計画!AC24/1000 -> 0 | BJ17: =+BI17/(収支計画!AC24/1000) -> #DIV/0! | BK17: =+PL推移!V16-収支計画!AE24/1000 -> 0 | BL17: =+BK17/(収支計画!AE24/1000) -> #DIV/0! | BM17: =+PL推移!X16-収支計画!AG24/1000 -> 0 | BN17: =+BM17/(収支計画!AG24/1000) -> #DIV/0! | BO17: =+PL推移!Z16-収支計画!AI24/1000 -> 0 | BP17: =+BO17/(収支計画!AI24/1000) -> #DIV/0!
B18: =+B12 -> 恵愛 | C18: =+収支計画!G18/1000 -> 1785 | D18: =+PL推移!D17 -> 1728 | E18: =+D18-C18 -> -57 | F18: =IF(C18<>0,D18/C18,"-") -> 0.96806723 | G18: =+収支計画!K18/1000 -> 1785 | H18: =+PL推移!F17 -> 0 | I18: =+H18-G18 -> -1785 | J18: =IF(G18<>0,H18/G18,"-") -> 0 | K18: =+収支計画!O18/1000 -> 2167.5 | L18: =+PL推移!H17 -> 0 | M18: =+L18-K18 -> -2167.5 | N18: =IF(K18<>0,L18/K18,"-") -> 0 | O18: =+収支計画!S18/1000 -> 0 | P18: =+PL推移!J17 -> 0 | Q18: =+P18-O18 -> 0 | R18: =IF(O18<>0,P18/O18,"-") -> - | S18: =+収支計画!U18/1000 -> 0 | T18: =+PL推移!L17 -> 0 | U18: =+T18-S18 -> 0 | V18: =IF(S18<>0,T18/S18,"-") -> - | W18: =+収支計画!W18/1000 -> 0 | X18: =+PL推移!N17 -> 0 | Y18: =+X18-W18 -> 0 | Z18: =IF(W18<>0,X18/W18,"-") -> - | AA18: =+収支計画!Y18/1000 -> 0 | AB18: =+PL推移!P17 -> 0 | AC18: =+AB18-AA18 -> 0 | AD18: =IF(AA18<>0,AB18/AA18,"-") -> - | AE18: =+収支計画!AA18/1000 -> 0 | AF18: =+PL推移!R17 -> 1634 | AG18: =+AF18-AE18 -> 1634 | AH18: =IF(AE18<>0,AF18/AE18,"-") -> - | AI18: =+収支計画!AC18/1000 -> 0 | AJ18: =+PL推移!T17 -> 1864 | AK18: =+AJ18-AI18 -> 1864 | AL18: =IF(AI18<>0,AJ18/AI18,"-") -> - | AM18: =+収支計画!AG18/1000 -> 0 | AN18: =+PL推移!V17 -> 1607 | AO18: =+AN18-AM18 -> 1607 | AP18: =IF(AM18<>0,AN18/AM18,"-") -> - | AQ18: =+収支計画!AG18/1000 -> 0 | AR18: =+PL推移!X17 -> 1751 | AS18: =+AR18-AQ18 -> 1751 | AT18: =IF(AQ18<>0,AR18/AQ18,"-") -> - | AU18: =+収支計画!AI18/1000 -> 0 | AV18: =+PL推移!Z17 -> 1643 | AW18: =+AV18-AU18 -> 1643 | AX18: =IF(AU18<>0,AV18/AU18,"-") -> - | AY18: =+C18+G18+K18+O18+S18+W18+AA18+AE18+AI18+AM18+AQ18+AU18 -> 5737.5 | AZ18: =+D18+H18+L18+P18+T18+X18+AB18+AF18+AJ18+AN18+AR18+AV18 -> 10227 | BA18: =+AZ18-AY18 -> 4489.5 | BB18: =IF(AY18<>0,AZ18/AY18,"-") -> 1.7824837 | BC18: =+PL推移!N17-収支計画!W18/1000 -> 0 | BD18: =+BC18/(収支計画!W18/1000) -> #DIV/0! | BE18: =+PL推移!P17-収支計画!Y18/1000 -> 0 | BF18: =+BE18/(収支計画!Y18/1000) -> #DIV/0! | BG18: =+PL推移!R17-収支計画!AA18/1000 -> 1634 | BH18: =+BG18/(収支計画!AA18/1000) -> #DIV/0! | BI18: =+PL推移!T17-収支計画!AC18/1000 -> 1864 | BJ18: =+BI18/(収支計画!AC18/1000) -> #DIV/0! | BK18: =+PL推移!V17-収支計画!AE18/1000 -> 1607 | BL18: =+BK18/(収支計画!AE18/1000) -> #DIV/0! | BM18: =+PL推移!X17-収支計画!AG18/1000 -> 1751 | BN18: =+BM18/(収支計画!AG18/1000) -> #DIV/0! | BO18: =+PL推移!Z17-収支計画!AI18/1000 -> 1643 | BP18: =+BO18/(収支計画!AI18/1000) -> #DIV/0!
B19: =+B13 -> 村 | C19: =+収支計画!G19/1000 -> 112.5 | D19: =+PL推移!D18 -> 122 | E19: =+D19-C19 -> 9.5 | F19: =IF(C19<>0,D19/C19,"-") -> 1.0844444 | G19: =+収支計画!K19/1000 -> 112.5 | H19: =+PL推移!F18 -> 0 | I19: =+H19-G19 -> -112.5 | J19: =IF(G19<>0,H19/G19,"-") -> 0 | K19: =+収支計画!O19/1000 -> 112.5 | L19: =+PL推移!H18 -> 0 | M19: =+L19-K19 -> -112.5 | N19: =IF(K19<>0,L19/K19,"-") -> 0 | O19: =+収支計画!S19/1000 -> 0 | P19: =+PL推移!J18 -> 0 | Q19: =+P19-O19 -> 0 | R19: =IF(O19<>0,P19/O19,"-") -> - | S19: =+収支計画!U19/1000 -> 0 | T19: =+PL推移!L18 -> 0 | U19: =+T19-S19 -> 0 | V19: =IF(S19<>0,T19/S19,"-") -> - | W19: =+収支計画!W19/1000 -> 0 | X19: =+PL推移!N18 -> 0 | Y19: =+X19-W19 -> 0 | Z19: =IF(W19<>0,X19/W19,"-") -> - | AA19: =+収支計画!Y19/1000 -> 0 | AB19: =+PL推移!P18 -> 0 | AC19: =+AB19-AA19 -> 0 | AD19: =IF(AA19<>0,AB19/AA19,"-") -> - | AE19: =+収支計画!AA19/1000 -> 0 | AF19: =+PL推移!R18 -> 92 | AG19: =+AF19-AE19 -> 92 | AH19: =IF(AE19<>0,AF19/AE19,"-") -> - | AI19: =+収支計画!AC19/1000 -> 0 | AJ19: =+PL推移!T18 -> 143 | AK19: =+AJ19-AI19 -> 143 | AL19: =IF(AI19<>0,AJ19/AI19,"-") -> - | AM19: =+収支計画!AG19/1000 -> 0 | AN19: =+PL推移!V18 -> 82 | AO19: =+AN19-AM19 -> 82 | AP19: =IF(AM19<>0,AN19/AM19,"-") -> - | AQ19: =+収支計画!AG19/1000 -> 0 | AR19: =+PL推移!X18 -> 115 | AS19: =+AR19-AQ19 -> 115 | AT19: =IF(AQ19<>0,AR19/AQ19,"-") -> - | AU19: =+収支計画!AI19/1000 -> 0 | AV19: =+PL推移!Z18 -> 120 | AW19: =+AV19-AU19 -> 120 | AX19: =IF(AU19<>0,AV19/AU19,"-") -> - | AY19: =+C19+G19+K19+O19+S19+W19+AA19+AE19+AI19+AM19+AQ19+AU19 -> 337.5 | AZ19: =+D19+H19+L19+P19+T19+X19+AB19+AF19+AJ19+AN19+AR19+AV19 -> 674 | BA19: =+AZ19-AY19 -> 336.5 | BB19: =IF(AY19<>0,AZ19/AY19,"-") -> 1.997037 | BC19: =+PL推移!N18-収支計画!W19/1000 -> 0 | BD19: =+BC19/(収支計画!W19/1000) -> #DIV/0! | BE19: =+PL推移!P18-収支計画!Y19/1000 -> 0 | BF19: =+BE19/(収支計画!Y19/1000) -> #DIV/0! | BG19: =+PL推移!R18-収支計画!AA19/1000 -> 92 | BH19: =+BG19/(収支計画!AA19/1000) -> #DIV/0! | BI19: =+PL推移!T18-収支計画!AC19/1000 -> 143 | BJ19: =+BI19/(収支計画!AC19/1000) -> #DIV/0! | BK19: =+PL推移!V18-収支計画!AE19/1000 -> 82 | BL19: =+BK19/(収支計画!AE19/1000) -> #DIV/0! | BM19: =+PL推移!X18-収支計画!AG19/1000 -> 115 | BN19: =+BM19/(収支計画!AG19/1000) -> #DIV/0! | BO19: =+PL推移!Z18-収支計画!AI19/1000 -> 120 | BP19: =+BO19/(収支計画!AI19/1000) -> #DIV/0!
B20: =+B14 -> 弁当 | C20: =+収支計画!G20/1000 -> 157.5 | D20: =+PL推移!D19 -> 126 | E20: =+D20-C20 -> -31.5 | F20: =IF(C20<>0,D20/C20,"-") -> 0.8 | G20: =+収支計画!K20/1000 -> 140 | H20: =+PL推移!F19 -> 0 | I20: =+H20-G20 -> -140 | J20: =IF(G20<>0,H20/G20,"-") -> 0 | K20: =+収支計画!O20/1000 -> 140 | L20: =+PL推移!H19 -> 0 | M20: =+L20-K20 -> -140 | N20: =IF(K20<>0,L20/K20,"-") -> 0 | O20: =+収支計画!S20/1000 -> 0 | P20: =+PL推移!J19 -> 0 | Q20: =+P20-O20 -> 0 | R20: =IF(O20<>0,P20/O20,"-") -> - | S20: =+収支計画!U20/1000 -> 0 | T20: =+PL推移!L19 -> 0 | U20: =+T20-S20 -> 0 | V20: =IF(S20<>0,T20/S20,"-") -> - | W20: =+収支計画!W20/1000 -> 0 | X20: =+PL推移!N19 -> 0 | Y20: =+X20-W20 -> 0 | Z20: =IF(W20<>0,X20/W20,"-") -> - | AA20: =+収支計画!Y20/1000 -> 0 | AB20: =+PL推移!P19 -> 0 | AC20: =+AB20-AA20 -> 0 | AD20: =IF(AA20<>0,AB20/AA20,"-") -> - | AE20: =+収支計画!AA20/1000 -> 0 | AF20: =+PL推移!R19 -> 87 | AG20: =+AF20-AE20 -> 87 | AH20: =IF(AE20<>0,AF20/AE20,"-") -> - | AI20: =+収支計画!AC20/1000 -> 0 | AJ20: =+PL推移!T19 -> 154 | AK20: =+AJ20-AI20 -> 154 | AL20: =IF(AI20<>0,AJ20/AI20,"-") -> - | AM20: =+収支計画!AG20/1000 -> 0 | AN20: =+PL推移!V19 -> 151 | AO20: =+AN20-AM20 -> 151 | AP20: =IF(AM20<>0,AN20/AM20,"-") -> - | AQ20: =+収支計画!AG20/1000 -> 0 | AR20: =+PL推移!X19 -> 167 | AS20: =+AR20-AQ20 -> 167 | AT20: =IF(AQ20<>0,AR20/AQ20,"-") -> - | AU20: =+収支計画!AI20/1000 -> 0 | AV20: =+PL推移!Z19 -> 184 | AW20: =+AV20-AU20 -> 184 | AX20: =IF(AU20<>0,AV20/AU20,"-") -> - | AY20: =+C20+G20+K20+O20+S20+W20+AA20+AE20+AI20+AM20+AQ20+AU20 -> 437.5 | AZ20: =+D20+H20+L20+P20+T20+X20+AB20+AF20+AJ20+AN20+AR20+AV20 -> 869 | BA20: =+AZ20-AY20 -> 431.5 | BB20: =IF(AY20<>0,AZ20/AY20,"-") -> 1.9862857 | BC20: =+PL推移!N19-収支計画!W20/1000 -> 0 | BD20: =+BC20/(収支計画!W20/1000) -> #DIV/0! | BE20: =+PL推移!P19-収支計画!Y20/1000 -> 0 | BF20: =+BE20/(収支計画!Y20/1000) -> #DIV/0! | BG20: =+PL推移!R19-収支計画!AA20/1000 -> 87 | BH20: =+BG20/(収支計画!AA20/1000) -> #DIV/0! | BI20: =+PL推移!T19-収支計画!AC20/1000 -> 154 | BJ20: =+BI20/(収支計画!AC20/1000) -> #DIV/0! | BK20: =+PL推移!V19-収支計画!AE20/1000 -> 151 | BL20: =+BK20/(収支計画!AE20/1000) -> #DIV/0! | BM20: =+PL推移!X19-収支計画!AG20/1000 -> 167 | BN20: =+BM20/(収支計画!AG20/1000) -> #DIV/0! | BO20: =+PL推移!Z19-収支計画!AI20/1000 -> 184 | BP20: =+BO20/(収支計画!AI20/1000) -> #DIV/0!
B21: =+B15 -> シェア | C21: =+収支計画!G21/1000 -> 45 | D21: =+PL推移!D20 -> 19 | E21: =+D21-C21 -> -26 | F21: =IF(C21<>0,D21/C21,"-") -> 0.42222222 | G21: =+収支計画!K21/1000 -> 45 | H21: =+PL推移!F20 -> 0 | I21: =+H21-G21 -> -45 | J21: =IF(G21<>0,H21/G21,"-") -> 0 | K21: =+収支計画!O21/1000 -> 37.5 | L21: =+PL推移!H20 -> 0 | M21: =+L21-K21 -> -37.5 | N21: =IF(K21<>0,L21/K21,"-") -> 0 | O21: =+収支計画!S21/1000 -> 0 | P21: =+PL推移!J20 -> 0 | Q21: =+P21-O21 -> 0 | R21: =IF(O21<>0,P21/O21,"-") -> - | S21: =+収支計画!U21/1000 -> 0 | T21: =+PL推移!L20 -> 0 | U21: =+T21-S21 -> 0 | V21: =IF(S21<>0,T21/S21,"-") -> - | W21: =+収支計画!W21/1000 -> 0 | X21: =+PL推移!N20 -> 0 | Y21: =+X21-W21 -> 0 | Z21: =IF(W21<>0,X21/W21,"-") -> - | AA21: =+収支計画!Y21/1000 -> 0 | AB21: =+PL推移!P20 -> 0 | AC21: =+AB21-AA21 -> 0 | AD21: =IF(AA21<>0,AB21/AA21,"-") -> - | AE21: =+収支計画!AA21/1000 -> 0 | AF21: =+PL推移!R20 -> 25 | AG21: =+AF21-AE21 -> 25 | AH21: =IF(AE21<>0,AF21/AE21,"-") -> - | AI21: =+収支計画!AC21/1000 -> 0 | AJ21: =+PL推移!T20 -> 73 | AK21: =+AJ21-AI21 -> 73 | AL21: =IF(AI21<>0,AJ21/AI21,"-") -> - | AM21: =+収支計画!AG21/1000 -> 0 | AN21: =+PL推移!V20 -> 38 | AO21: =+AN21-AM21 -> 38 | AP21: =IF(AM21<>0,AN21/AM21,"-") -> - | AQ21: =+収支計画!AG21/1000 -> 0 | AR21: =+PL推移!X20 -> 32 | AS21: =+AR21-AQ21 -> 32 | AT21: =IF(AQ21<>0,AR21/AQ21,"-") -> - | AU21: =+収支計画!AI21/1000 -> 0 | AV21: =+PL推移!Z20 -> 37 | AW21: =+AV21-AU21 -> 37 | AX21: =IF(AU21<>0,AV21/AU21,"-") -> - | AY21: =+C21+G21+K21+O21+S21+W21+AA21+AE21+AI21+AM21+AQ21+AU21 -> 127.5 | AZ21: =+D21+H21+L21+P21+T21+X21+AB21+AF21+AJ21+AN21+AR21+AV21 -> 224 | BA21: =+AZ21-AY21 -> 96.5 | BB21: =IF(AY21<>0,AZ21/AY21,"-") -> 1.7568627 | BC21: =+PL推移!N20-収支計画!W21/1000 -> 0 | BD21: =+BC21/(収支計画!W21/1000) -> #DIV/0! | BE21: =+PL推移!P20-収支計画!Y21/1000 -> 0 | BF21: =+BE21/(収支計画!Y21/1000) -> #DIV/0! | BG21: =+PL推移!R20-収支計画!AA21/1000 -> 25 | BH21: =+BG21/(収支計画!AA21/1000) -> #DIV/0! | BI21: =+PL推移!T20-収支計画!AC21/1000 -> 73 | BJ21: =+BI21/(収支計画!AC21/1000) -> #DIV/0! | BK21: =+PL推移!V20-収支計画!AE21/1000 -> 38 | BL21: =+BK21/(収支計画!AE21/1000) -> #DIV/0! | BM21: =+PL推移!X20-収支計画!AG21/1000 -> 32 | BN21: =+BM21/(収支計画!AG21/1000) -> #DIV/0! | BO21: =+PL推移!Z20-収支計画!AI21/1000 -> 37 | BP21: =+BO21/(収支計画!AI21/1000) -> #DIV/0!
B22: =+B16 -> サウナ | C22: =+収支計画!G22/1000 -> 100 | D22: =+PL推移!D21 -> 27 | E22: =+D22-C22 -> -73 | F22: =IF(C22<>0,D22/C22,"-") -> 0.27 | G22: =+収支計画!K22/1000 -> 50 | H22: =+PL推移!F21 -> 0 | I22: =+H22-G22 -> -50 | J22: =IF(G22<>0,H22/G22,"-") -> 0 | K22: =+収支計画!O22/1000 -> 50 | L22: =+PL推移!H21 -> 0 | M22: =+L22-K22 -> -50 | N22: =IF(K22<>0,L22/K22,"-") -> 0 | O22: =+収支計画!S22/1000 -> 0 | P22: =+PL推移!J21 -> 0 | Q22: =+P22-O22 -> 0 | R22: =IF(O22<>0,P22/O22,"-") -> - | S22: =+収支計画!U22/1000 -> 0 | T22: =+PL推移!L21 -> 0 | U22: =+T22-S22 -> 0 | V22: =IF(S22<>0,T22/S22,"-") -> - | W22: =+収支計画!W22/1000 -> 0 | X22: =+PL推移!N21 -> 0 | Y22: =+X22-W22 -> 0 | Z22: =IF(W22<>0,X22/W22,"-") -> - | AA22: =+収支計画!Y22/1000 -> 0 | AB22: =+PL推移!P21 -> 0 | AC22: =+AB22-AA22 -> 0 | AD22: =IF(AA22<>0,AB22/AA22,"-") -> - | AE22: =+収支計画!AA22/1000 -> 0 | AF22: =+PL推移!R21 -> 62 | AG22: =+AF22-AE22 -> 62 | AH22: =IF(AE22<>0,AF22/AE22,"-") -> - | AI22: =+収支計画!AC22/1000 -> 0 | AJ22: =+PL推移!T21 -> 32 | AK22: =+AJ22-AI22 -> 32 | AL22: =IF(AI22<>0,AJ22/AI22,"-") -> - | AM22: =+収支計画!AG22/1000 -> 0 | AN22: =+PL推移!V21 -> 33 | AO22: =+AN22-AM22 -> 33 | AP22: =IF(AM22<>0,AN22/AM22,"-") -> - | AQ22: =+収支計画!AG22/1000 -> 0 | AR22: =+PL推移!X21 -> 52 | AS22: =+AR22-AQ22 -> 52 | AT22: =IF(AQ22<>0,AR22/AQ22,"-") -> - | AU22: =+収支計画!AI22/1000 -> 0 | AV22: =+PL推移!Z21 -> 23 | AW22: =+AV22-AU22 -> 23 | AX22: =IF(AU22<>0,AV22/AU22,"-") -> - | AY22: =+C22+G22+K22+O22+S22+W22+AA22+AE22+AI22+AM22+AQ22+AU22 -> 200 | AZ22: =+D22+H22+L22+P22+T22+X22+AB22+AF22+AJ22+AN22+AR22+AV22 -> 229 | BA22: =+AZ22-AY22 -> 29 | BB22: =IF(AY22<>0,AZ22/AY22,"-") -> 1.145 | BC22: =+PL推移!N21-収支計画!W22/1000 -> 0 | BD22: =+BC22/(収支計画!W22/1000) -> #DIV/0! | BE22: =+PL推移!P21-収支計画!Y22/1000 -> 0 | BF22: =+BE22/(収支計画!Y22/1000) -> #DIV/0! | BG22: =+PL推移!R21-収支計画!AA22/1000 -> 62 | BH22: =+BG22/(収支計画!AA22/1000) -> #DIV/0! | BI22: =+PL推移!T21-収支計画!AC22/1000 -> 32 | BJ22: =+BI22/(収支計画!AC22/1000) -> #DIV/0! | BK22: =+PL推移!V21-収支計画!AE22/1000 -> 33 | BL22: =+BK22/(収支計画!AE22/1000) -> #DIV/0! | BM22: =+PL推移!X21-収支計画!AG22/1000 -> 52 | BN22: =+BM22/(収支計画!AG22/1000) -> #DIV/0! | BO22: =+PL推移!Z21-収支計画!AI22/1000 -> 23 | BP22: =+BO22/(収支計画!AI22/1000) -> #DIV/0!
A23: 粗利益 | C23: =+C11-C17 -> 7050 | D23: =+D11-D17 -> 6610.009 | E23: =+E11-E17 -> -440 | F23: =IF(C23<>0,D23/C23,"-") -> 0.93758993 | G23: =SUM(G24:G28) -> 7117.5 | H23: =+PL推移!F22 -> 0 | I23: =+I11-I17 -> -7117.5 | J23: =IF(G23<>0,H23/G23,"-") -> 0 | K23: =SUM(K24:K28) -> 8242.5 | L23: =+PL推移!H22 -> 0 | M23: =+M11-M17 -> -8242.5 | N23: =IF(K23<>0,L23/K23,"-") -> 0 | O23: =SUM(O24:O28) -> 0 | P23: =+PL推移!J22 -> 0 | Q23: =+Q11-Q17 -> 0 | R23: =IF(O23<>0,P23/O23,"-") -> - | S23: =SUM(S24:S28) -> 0 | T23: =+T11-T17 -> 0 | U23: =+U11-U17 -> 0 | V23: =IF(S23<>0,T23/S23,"-") -> - | W23: =SUM(W24:W28) -> 0 | X23: =+X11-X17 -> 0 | Y23: =+Y11-Y17 -> 0 | Z23: =IF(W23<>0,X23/W23,"-") -> - | AA23: =+AA11-AA17 -> 0 | AB23: =+AB11-AB17 -> 0 | AC23: =+AC11-AC17 -> 0 | AD23: =IF(AA23<>0,AB23/AA23,"-") -> - | AE23: =SUM(AE24:AE28) -> 0 | AF23: =+PL推移!R22 -> 0 | AG23: =+AG11-AG17 -> -1900 | AH23: =IF(AE23<>0,AF23/AE23,"-") -> - | AI23: =SUM(AI24:AI28) -> 0 | AJ23: =+AJ11-AJ17 -> 350 | AK23: =+AK11-AK17 -> -2266 | AL23: =IF(AI23<>0,AJ23/AI23,"-") -> - | AM23: =+AM11-AM17 -> 0 | AN23: =+AN11-AN17 -> 8454 | AO23: =+AN23-AM23 -> 8454 | AP23: =IF(AM23<>0,AN23/AM23,"-") -> - | AQ23: =+AQ11-AQ17 -> 0 | AR23: =+AR11-AR17 -> 9017 | AS23: =+AR23-AQ23 -> 9017 | AT23: =IF(AQ23<>0,AR23/AQ23,"-") -> - | AU23: =+AU11-AU17 -> 0 | AV23: =+AV11-AV17 -> 8610 | AW23: =+AV23-AU23 -> 8610 | AX23: =IF(AU23<>0,AV23/AU23,"-") -> - | AY23: =+C23+G23+K23+O23+S23+W23+AA23+AE23+AI23+AM23+AQ23+AU23 -> 22410 | AZ23: =+D23+H23+L23+P23+T23+X23+AB23+AF23+AJ23+AN23+AR23+AV23 -> 33041.009 | BA23: =+AZ23-AY23 -> 10631.009 | BB23: =IF(AY23<>0,AZ23/AY23,"-") -> 1.4743868 | BC23: =+PL推移!N22-収支計画!W25/1000 -> 0 | BD23: =+BC23/(収支計画!W25/1000) -> #DIV/0! | BE23: =+PL推移!P22-収支計画!Y25/1000 -> 0 | BF23: =+BE23/(収支計画!Y25/1000) -> #DIV/0! | BG23: =+PL推移!R22-収支計画!AA25/1000 -> 0 | BH23: =+BG23/(収支計画!AA25/1000) -> #DIV/0! | BI23: =+PL推移!T22-収支計画!AC25/1000 -> 350 | BJ23: =+BI23/(収支計画!AC25/1000) -> #DIV/0! | BK23: =+PL推移!V22-収支計画!AE25/1000 -> 8454 | BL23: =+BK23/(収支計画!AE25/1000) -> #DIV/0! | BM23: =+PL推移!X22-収支計画!AG25/1000 -> 9017 | BN23: =+BM23/(収支計画!AG25/1000) -> #DIV/0! | BO23: =+PL推移!Z22-収支計画!AI25/1000 -> 8610 | BP23: =+BO23/(収支計画!AI25/1000) -> #DIV/0!
B24: =+B18 -> 恵愛 | C24: =+C12-C18 -> 5215 | D24: =+PL推移!D23 -> 4697 | E24: =+D24-C24 -> -518 | F24: =IF(C24<>0,D24/C24,"-") -> 0.90067114 | G24: =+G12-G18 -> 5215 | H24: =+PL推移!F23 -> 0 | I24: =+H24-G24 -> -5215 | J24: =IF(G24<>0,H24/G24,"-") -> 0 | K24: =+K12-K18 -> 6332.5 | L24: =+PL推移!H23 -> 0 | M24: =+L24-K24 -> -6332.5 | N24: =IF(K24<>0,L24/K24,"-") -> 0 | O24: =+O12-O18 -> 0 | P24: =+PL推移!J23 -> 0 | Q24: =+P24-O24 -> 0 | R24: =IF(O24<>0,P24/O24,"-") -> - | S24: =+S12-S18 -> 0 | T24: =+T12-T18 -> 0 | U24: =+T24-S24 -> 0 | V24: =IF(S24<>0,T24/S24,"-") -> - | W24: =+W12-W18 -> 0 | X24: =+X12-X18 -> 0 | Y24: =+X24-W24 -> 0 | Z24: =IF(W24<>0,X24/W24,"-") -> - | AA24: =+AA12-AA18 -> 0 | AB24: =+AB12-AB18 -> 0 | AC24: =+AB24-AA24 -> 0 | AD24: =IF(AA24<>0,AB24/AA24,"-") -> - | AE24: =+AE12-AE18 -> 0 | AF24: =+PL推移!R23 -> -1634 | AG24: =+AF24-AE24 -> -1634 | AH24: =IF(AE24<>0,AF24/AE24,"-") -> - | AI24: =+AI12-AI18 -> 0 | AJ24: =+AJ12-AJ18 -> -1864 | AK24: =+AJ24-AI24 -> -1864 | AL24: =IF(AI24<>0,AJ24/AI24,"-") -> - | AM24: =+AM12-AM18 -> 0 | AN24: =+AN12-AN18 -> 4406 | AO24: =+AN24-AM24 -> 4406 | AP24: =IF(AM24<>0,AN24/AM24,"-") -> - | AQ24: =+AQ12-AQ18 -> 0 | AR24: =+AR12-AR18 -> 5104 | AS24: =+AR24-AQ24 -> 5104 | AT24: =IF(AQ24<>0,AR24/AQ24,"-") -> - | AU24: =+AU12-AU18 -> 0 | AV24: =+AV12-AV18 -> 4542 | AW24: =+AV24-AU24 -> 4542 | AX24: =IF(AU24<>0,AV24/AU24,"-") -> - | AY24: =+C24+G24+K24+O24+S24+W24+AA24+AE24+AI24+AM24+AQ24+AU24 -> 16762.5 | AZ24: =+D24+H24+L24+P24+T24+X24+AB24+AF24+AJ24+AN24+AR24+AV24 -> 15251 | BA24: =+AZ24-AY24 -> -1511.5 | BB24: =IF(AY24<>0,AZ24/AY24,"-") -> 0.90982849 | BC24: =+PL推移!N23-収支計画!W26/1000 -> #DIV/0! | BD24: =+BC24/(収支計画!W26/1000) -> #DIV/0! | BE24: =+PL推移!P23-収支計画!Y26/1000 -> #DIV/0! | BF24: =+BE24/(収支計画!Y26/1000) -> #DIV/0! | BG24: =+PL推移!R23-収支計画!AA26/1000 -> -1634 | BH24: =+BG24/(収支計画!AA26/1000) -> #DIV/0! | BI24: =+PL推移!T23-収支計画!AC26/1000 -> -1864 | BJ24: =+BI24/(収支計画!AC26/1000) -> #DIV/0! | BK24: =+PL推移!V23-収支計画!AE26/1000 -> 4406 | BL24: =+BK24/(収支計画!AE26/1000) -> #DIV/0! | BM24: =+PL推移!X23-収支計画!AG26/1000 -> 5104 | BN24: =+BM24/(収支計画!AG26/1000) -> #DIV/0! | BO24: =+PL推移!Z23-収支計画!AI26/1000 -> 4542 | BP24: =+BO24/(収支計画!AI26/1000) -> #DIV/0!
B25: =+B19 -> 村 | C25: =+C13-C19 -> 637.5 | D25: =+PL推移!D24 -> 524 | E25: =+D25-C25 -> -113.5 | F25: =IF(C25<>0,D25/C25,"-") -> 0.82196078 | G25: =+G13-G19 -> 637.5 | H25: =+PL推移!F24 -> 0 | I25: =+H25-G25 -> -637.5 | J25: =IF(G25<>0,H25/G25,"-") -> 0 | K25: =+K13-K19 -> 637.5 | L25: =+PL推移!H24 -> 0 | M25: =+L25-K25 -> -637.5 | N25: =IF(K25<>0,L25/K25,"-") -> 0 | O25: =+O13-O19 -> 0 | P25: =+PL推移!J24 -> 0 | Q25: =+P25-O25 -> 0 | R25: =IF(O25<>0,P25/O25,"-") -> - | S25: =+S13-S19 -> 0 | T25: =+T13-T19 -> 0 | U25: =+T25-S25 -> 0 | V25: =IF(S25<>0,T25/S25,"-") -> - | W25: =+W13-W19 -> 0 | X25: =+X13-X19 -> 0 | Y25: =+X25-W25 -> 0 | Z25: =IF(W25<>0,X25/W25,"-") -> - | AA25: =+AA13-AA19 -> 0 | AB25: =+AB13-AB19 -> 0 | AC25: =+AB25-AA25 -> 0 | AD25: =IF(AA25<>0,AB25/AA25,"-") -> - | AE25: =+AE13-AE19 -> 0 | AF25: =+PL推移!R24 -> -92 | AG25: =+AF25-AE25 -> -92 | AH25: =IF(AE25<>0,AF25/AE25,"-") -> - | AI25: =+AI13-AI19 -> 0 | AJ25: =+AJ13-AJ19 -> -143 | AK25: =+AJ25-AI25 -> -143 | AL25: =IF(AI25<>0,AJ25/AI25,"-") -> - | AM25: =+AM13-AM19 -> 0 | AN25: =+AN13-AN19 -> 709 | AO25: =+AN25-AM25 -> 709 | AP25: =IF(AM25<>0,AN25/AM25,"-") -> - | AQ25: =+AQ13-AQ19 -> 0 | AR25: =+AR13-AR19 -> -115 | AS25: =+AR25-AQ25 -> -115 | AT25: =IF(AQ25<>0,AR25/AQ25,"-") -> - | AU25: =+AU13-AU19 -> 0 | AV25: =+AV13-AV19 -> -120 | AW25: =+AV25-AU25 -> -120 | AX25: =IF(AU25<>0,AV25/AU25,"-") -> - | AY25: =+C25+G25+K25+O25+S25+W25+AA25+AE25+AI25+AM25+AQ25+AU25 -> 1912.5 | AZ25: =+D25+H25+L25+P25+T25+X25+AB25+AF25+AJ25+AN25+AR25+AV25 -> 763 | BA25: =+AZ25-AY25 -> -1149.5 | BB25: =IF(AY25<>0,AZ25/AY25,"-") -> 0.39895425 | BC25: =+PL推移!N24-収支計画!W27/1000 -> 0 | BD25: =+BC25/(収支計画!W27/1000) -> #DIV/0! | BE25: =+PL推移!P24-収支計画!Y27/1000 -> 0 | BF25: =+BE25/(収支計画!Y27/1000) -> #DIV/0! | BG25: =+PL推移!R24-収支計画!AA27/1000 -> -92 | BH25: =+BG25/(収支計画!AA27/1000) -> #DIV/0! | BI25: =+PL推移!T24-収支計画!AC27/1000 -> -143 | BJ25: =+BI25/(収支計画!AC27/1000) -> #DIV/0! | BK25: =+PL推移!V24-収支計画!AE27/1000 -> 709 | BL25: =+BK25/(収支計画!AE27/1000) -> #DIV/0! | BM25: =+PL推移!X24-収支計画!AG27/1000 -> -115 | BN25: =+BM25/(収支計画!AG27/1000) -> #DIV/0! | BO25: =+PL推移!Z24-収支計画!AI27/1000 -> -120 | BP25: =+BO25/(収支計画!AI27/1000) -> #DIV/0!
B26: =+B20 -> 弁当 | C26: =+C14-C20 -> 192.5 | D26: =+PL推移!D25 -> 399 | E26: =+D26-C26 -> 206.5 | F26: =IF(C26<>0,D26/C26,"-") -> 2.0727273 | G26: =+G14-G20 -> 210 | H26: =+PL推移!F25 -> 0 | I26: =+H26-G26 -> -210 | J26: =IF(G26<>0,H26/G26,"-") -> 0 | K26: =+K14-K20 -> 210 | L26: =+PL推移!H25 -> 0 | M26: =+L26-K26 -> -210 | N26: =IF(K26<>0,L26/K26,"-") -> 0 | O26: =+O14-O20 -> 0 | P26: =+PL推移!J25 -> 0 | Q26: =+P26-O26 -> 0 | R26: =IF(O26<>0,P26/O26,"-") -> - | S26: =+S14-S20 -> 0 | T26: =+T14-T20 -> 0 | U26: =+T26-S26 -> 0 | V26: =IF(S26<>0,T26/S26,"-") -> - | W26: =+W14-W20 -> 0 | X26: =+X14-X20 -> 0 | Y26: =+X26-W26 -> 0 | Z26: =IF(W26<>0,X26/W26,"-") -> - | AA26: =+AA14-AA20 -> 0 | AB26: =+AB14-AB20 -> 0 | AC26: =+AB26-AA26 -> 0 | AD26: =IF(AA26<>0,AB26/AA26,"-") -> - | AE26: =+AE14-AE20 -> 0 | AF26: =+PL推移!R25 -> -87 | AG26: =+AF26-AE26 -> -87 | AH26: =IF(AE26<>0,AF26/AE26,"-") -> - | AI26: =+AI14-AI20 -> 0 | AJ26: =+AJ14-AJ20 -> -154 | AK26: =+AJ26-AI26 -> -154 | AL26: =IF(AI26<>0,AJ26/AI26,"-") -> - | AM26: =+AM14-AM20 -> 0 | AN26: =+AN14-AN20 -> 209 | AO26: =+AN26-AM26 -> 209 | AP26: =IF(AM26<>0,AN26/AM26,"-") -> - | AQ26: =+AQ14-AQ20 -> 0 | AR26: =+AR14-AR20 -> 208 | AS26: =+AR26-AQ26 -> 208 | AT26: =IF(AQ26<>0,AR26/AQ26,"-") -> - | AU26: =+AU14-AU20 -> 0 | AV26: =+AV14-AV20 -> 221 | AW26: =+AV26-AU26 -> 221 | AX26: =IF(AU26<>0,AV26/AU26,"-") -> - | AY26: =+C26+G26+K26+O26+S26+W26+AA26+AE26+AI26+AM26+AQ26+AU26 -> 612.5 | AZ26: =+D26+H26+L26+P26+T26+X26+AB26+AF26+AJ26+AN26+AR26+AV26 -> 796 | BA26: =+AZ26-AY26 -> 183.5 | BB26: =IF(AY26<>0,AZ26/AY26,"-") -> 1.2995918 | BC26: =+PL推移!N25-収支計画!W28/1000 -> 0 | BD26: =+BC26/(収支計画!W28/1000) -> #DIV/0! | BE26: =+PL推移!P25-収支計画!Y28/1000 -> 0 | BF26: =+BE26/(収支計画!Y28/1000) -> #DIV/0! | BG26: =+PL推移!R25-収支計画!AA28/1000 -> -87 | BH26: =+BG26/(収支計画!AA28/1000) -> #DIV/0! | BI26: =+PL推移!T25-収支計画!AC28/1000 -> -154 | BJ26: =+BI26/(収支計画!AC28/1000) -> #DIV/0! | BK26: =+PL推移!V25-収支計画!AE28/1000 -> 209 | BL26: =+BK26/(収支計画!AE28/1000) -> #DIV/0! | BM26: =+PL推移!X25-収支計画!AG28/1000 -> 208 | BN26: =+BM26/(収支計画!AG28/1000) -> #DIV/0! | BO26: =+PL推移!Z25-収支計画!AI28/1000 -> 221 | BP26: =+BO26/(収支計画!AI28/1000) -> #DIV/0!
B27: =+B21 -> シェア | C27: =+C15-C21 -> 105 | D27: =+PL推移!D26 -> 44 | E27: =+D27-C27 -> -61 | F27: =IF(C27<>0,D27/C27,"-") -> 0.41904762 | G27: =+G15-G21 -> 105 | H27: =+PL推移!F26 -> 0 | I27: =+H27-G27 -> -105 | J27: =IF(G27<>0,H27/G27,"-") -> 0 | K27: =+K15-K21 -> 112.5 | L27: =+PL推移!H26 -> 0 | M27: =+L27-K27 -> -112.5 | N27: =IF(K27<>0,L27/K27,"-") -> 0 | O27: =+O15-O21 -> 0 | P27: =+PL推移!J26 -> 0 | Q27: =+P27-O27 -> 0 | R27: =IF(O27<>0,P27/O27,"-") -> - | S27: =+S15-S21 -> 0 | T27: =+T15-T21 -> 0 | U27: =+T27-S27 -> 0 | V27: =IF(S27<>0,T27/S27,"-") -> - | W27: =+W15-W21 -> 0 | X27: =+X15-X21 -> 0 | Y27: =+X27-W27 -> 0 | Z27: =IF(W27<>0,X27/W27,"-") -> - | AA27: =+AA15-AA21 -> 0 | AB27: =+AB15-AB21 -> 0 | AC27: =+AB27-AA27 -> 0 | AD27: =IF(AA27<>0,AB27/AA27,"-") -> - | AE27: =+AE15-AE21 -> 0 | AF27: =+PL推移!R26 -> -25 | AG27: =+AF27-AE27 -> -25 | AH27: =IF(AE27<>0,AF27/AE27,"-") -> - | AI27: =+AI15-AI21 -> 0 | AJ27: =+AJ15-AJ21 -> -73 | AK27: =+AJ27-AI27 -> -73 | AL27: =IF(AI27<>0,AJ27/AI27,"-") -> - | AM27: =+AM15-AM21 -> 0 | AN27: =+AN15-AN21 -> 90 | AO27: =+AN27-AM27 -> 90 | AP27: =IF(AM27<>0,AN27/AM27,"-") -> - | AQ27: =+AQ15-AQ21 -> 0 | AR27: =+AR15-AR21 -> 76 | AS27: =+AR27-AQ27 -> 76 | AT27: =IF(AQ27<>0,AR27/AQ27,"-") -> - | AU27: =+AU15-AU21 -> 0 | AV27: =+AV15-AV21 -> 85 | AW27: =+AV27-AU27 -> 85 | AX27: =IF(AU27<>0,AV27/AU27,"-") -> - | AY27: =+C27+G27+K27+O27+S27+W27+AA27+AE27+AI27+AM27+AQ27+AU27 -> 322.5 | AZ27: =+D27+H27+L27+P27+T27+X27+AB27+AF27+AJ27+AN27+AR27+AV27 -> 197 | BA27: =+AZ27-AY27 -> -125.5 | BB27: =IF(AY27<>0,AZ27/AY27,"-") -> 0.61085271 | BC27: =+PL推移!N26-収支計画!W29/1000 -> 0 | BD27: =+BC27/(収支計画!W29/1000) -> #DIV/0! | BE27: =+PL推移!P26-収支計画!Y29/1000 -> 0 | BF27: =+BE27/(収支計画!Y29/1000) -> #DIV/0! | BG27: =+PL推移!R26-収支計画!AA29/1000 -> -25 | BH27: =+BG27/(収支計画!AA29/1000) -> #DIV/0! | BI27: =+PL推移!T26-収支計画!AC29/1000 -> -73 | BJ27: =+BI27/(収支計画!AC29/1000) -> #DIV/0! | BK27: =+PL推移!V26-収支計画!AE29/1000 -> 90 | BL27: =+BK27/(収支計画!AE29/1000) -> #DIV/0! | BM27: =+PL推移!X26-収支計画!AG29/1000 -> 76 | BN27: =+BM27/(収支計画!AG29/1000) -> #DIV/0! | BO27: =+PL推移!Z26-収支計画!AI29/1000 -> 85 | BP27: =+BO27/(収支計画!AI29/1000) -> #DIV/0!
B28: =+B22 -> サウナ | C28: =+C16-C22 -> 900 | D28: =+PL推移!D27 -> 946 | E28: =+D28-C28 -> 46 | F28: =IF(C28<>0,D28/C28,"-") -> 1.0511111 | G28: =+G16-G22 -> 950 | H28: =+PL推移!F27 -> 0 | I28: =+H28-G28 -> -950 | J28: =IF(G28<>0,H28/G28,"-") -> 0 | K28: =+K16-K22 -> 950 | L28: =+PL推移!H27 -> 0 | M28: =+L28-K28 -> -950 | N28: =IF(K28<>0,L28/K28,"-") -> 0 | O28: =+O16-O22 -> 0 | P28: =+PL推移!J27 -> 0 | Q28: =+P28-O28 -> 0 | R28: =IF(O28<>0,P28/O28,"-") -> - | S28: =+S16-S22 -> 0 | T28: =+T16-T22 -> 0 | U28: =+T28-S28 -> 0 | V28: =IF(S28<>0,T28/S28,"-") -> - | W28: =+W16-W22 -> 0 | X28: =+X16-X22 -> 0 | Y28: =+X28-W28 -> 0 | Z28: =IF(W28<>0,X28/W28,"-") -> - | AA28: =+AA16-AA22 -> 0 | AB28: =+AB16-AB22 -> 0 | AC28: =+AB28-AA28 -> 0 | AD28: =IF(AA28<>0,AB28/AA28,"-") -> - | AE28: =+AE16-AE22 -> 0 | AF28: =+PL推移!R27 -> -62 | AG28: =+AF28-AE28 -> -62 | AH28: =IF(AE28<>0,AF28/AE28,"-") -> - | AI28: =+AI16-AI22 -> 0 | AJ28: =+AJ16-AJ22 -> -32 | AK28: =+AJ28-AI28 -> -32 | AL28: =IF(AI28<>0,AJ28/AI28,"-") -> - | AM28: =+AM16-AM22 -> 0 | AN28: =+AN16-AN22 -> 779 | AO28: =+AN28-AM28 -> 779 | AP28: =IF(AM28<>0,AN28/AM28,"-") -> - | AQ28: =+AQ16-AQ22 -> 0 | AR28: =+AR16-AR22 -> 1277 | AS28: =+AR28-AQ28 -> 1277 | AT28: =IF(AQ28<>0,AR28/AQ28,"-") -> - | AU28: =+AU16-AU22 -> 0 | AV28: =+AV16-AV22 -> 869 | AW28: =+AV28-AU28 -> 869 | AX28: =IF(AU28<>0,AV28/AU28,"-") -> - | AY28: =+C28+G28+K28+O28+S28+W28+AA28+AE28+AI28+AM28+AQ28+AU28 -> 2800 | AZ28: =+D28+H28+L28+P28+T28+X28+AB28+AF28+AJ28+AN28+AR28+AV28 -> 3777 | BA28: =+AZ28-AY28 -> 977 | BB28: =IF(AY28<>0,AZ28/AY28,"-") -> 1.3489286 | BC28: =+PL推移!N27-収支計画!W30/1000 -> 0 | BD28: =+BC28/(収支計画!W30/1000) -> #DIV/0! | BE28: =+PL推移!P27-収支計画!Y30/1000 -> 0 | BF28: =+BE28/(収支計画!Y30/1000) -> #DIV/0! | BG28: =+PL推移!R27-収支計画!AA30/1000 -> -62 | BH28: =+BG28/(収支計画!AA30/1000) -> #DIV/0! | BI28: =+PL推移!T27-収支計画!AC30/1000 -> -32 | BJ28: =+BI28/(収支計画!AC30/1000) -> #DIV/0! | BK28: =+PL推移!V27-収支計画!AE30/1000 -> 779 | BL28: =+BK28/(収支計画!AE30/1000) -> #DIV/0! | BM28: =+PL推移!X27-収支計画!AG30/1000 -> 1277 | BN28: =+BM28/(収支計画!AG30/1000) -> #DIV/0! | BO28: =+PL推移!Z27-収支計画!AI30/1000 -> 869 | BP28: =+BO28/(収支計画!AI30/1000) -> #DIV/0!
A29: 販売管理費 | C29: =SUM(C30:C50) -> 6560.399 | D29: =SUM(D30:D50) -> 6195.861 | E29: =SUM(E30:E50) -> -364.538 | F29: =IF(C29<>0,D29/C29,"-") -> 0.94443356 | G29: =SUM(G30:G50) -> 14610.58 | H29: =+PL推移!F28 -> 0 | I29: =SUM(I30:I50) -> -14610.58 | J29: =IF(G29<>0,H29/G29,"-") -> 0 | K29: =SUM(K30:K50) -> 16042.82 | L29: =+PL推移!H28 -> 0 | M29: =SUM(M30:M50) -> -16042.82 | N29: =IF(K29<>0,L29/K29,"-") -> 0 | O29: =SUM(O30:O50) -> 7969.11 | P29: =+PL推移!J28 -> 0 | Q29: =SUM(Q30:Q50) -> -7969.11 | R29: =IF(O29<>0,P29/O29,"-") -> 0 | S29: =SUM(S30:S50) -> 0 | T29: =+PL推移!L28 -> 0 | U29: =SUM(U30:U50) -> 0 | V29: =IF(S29<>0,T29/S29,"-") -> - | W29: =SUM(W30:W50) -> 0 | X29: =+PL推移!P28 -> 0 | Y29: =SUM(Y30:Y50) -> 0 | Z29: =IF(W29<>0,X29/W29,"-") -> - | AA29: =SUM(AA30:AA50) -> 0 | AB29: =+PL推移!P28 -> 0 | AC29: =SUM(AC30:AC50) -> 0 | AD29: =IF(AA29<>0,AB29/AA29,"-") -> - | AE29: =+収支計画!AA62/1000 -> 0 | AF29: =+PL推移!R28 -> 0 | AG29: =SUM(AG30:AG50) -> 0 | AH29: =IF(AE29<>0,AF29/AE29,"-") -> - | AI29: =+収支計画!AC62/1000 -> 0 | AJ29: =+PL推移!T28 -> 0 | AK29: =SUM(AK30:AK50) -> 0 | AL29: =IF(AI29<>0,AJ29/AI29,"-") -> - | AM29: =+収支計画!AE62/1000 -> 0 | AN29: =+PL推移!V28 -> 0 | AO29: =+AN29-AM29 -> 0 | AP29: =IF(AM29<>0,AN29/AM29,"-") -> - | AQ29: =SUM(AQ30:AQ50) -> 0 | AR29: =+PL推移!X28 -> 0 | AS29: =+AR29-AQ29 -> 0 | AT29: =IF(AQ29<>0,AR29/AQ29,"-") -> - | AU29: =+収支計画!AI62/1000 -> 0 | AV29: =+PL推移!Z28 -> 0 | AW29: =+AV29-AU29 -> 0 | AX29: =IF(AU29<>0,AV29/AU29,"-") -> - | AY29: =+C29+G29+K29+O29+S29+W29+AA29+AE29+AI29+AM29+AQ29+AU29 -> 45182.909 | AZ29: =+D29+H29+L29+P29+T29+X29+AB29+AF29+AJ29+AN29+AR29+AV29 -> 6195.861 | BA29: =+AZ29-AY29 -> -38987.048 | BB29: =IF(AY29<>0,AZ29/AY29,"-") -> 0.13712842 | BC29: =+PL推移!N28-収支計画!W62/1000 -> 0 | BD29: =+BC29/(収支計画!W62/1000) -> #DIV/0! | BE29: =+PL推移!P28-収支計画!Y62/1000 -> 0 | BF29: =+BE29/(収支計画!Y62/1000) -> #DIV/0! | BG29: =+PL推移!R28-収支計画!AA62/1000 -> 0 | BH29: =+BG29/(収支計画!AA62/1000) -> #DIV/0! | BI29: =+PL推移!T28-収支計画!AC62/1000 -> 0 | BJ29: =+BI29/(収支計画!AC62/1000) -> #DIV/0! | BK29: =+PL推移!V28-収支計画!AE62/1000 -> 0 | BL29: =+BK29/(収支計画!AE62/1000) -> #DIV/0! | BM29: =+PL推移!X28-収支計画!AG62/1000 -> 0 | BN29: =+BM29/(収支計画!AG62/1000) -> #DIV/0! | BO29: =+PL推移!Z28-収支計画!AI62/1000 -> 0 | BP29: =+BO29/(収支計画!AI62/1000) -> #DIV/0!
B30: 人件費 | C30: =+収支計画!G34/1000 -> 2722.319 | D30: =+PL推移!D29 -> 2462.876 | E30: =+D30-C30 -> -259.443 | F30: =IF(C30<>0,D30/C30,"-") -> 0.9046978 | G30: =+収支計画!K40/1000 -> 749.954 | H30: =+PL推移!F29 -> 0 | I30: =+H30-G30 -> -749.954 | J30: =IF(G30<>0,H30/G30,"-") -> 0 | K30: =+収支計画!O40/1000 -> 749.954 | L30: =+PL推移!H29 -> 0 | M30: =+L30-K30 -> -749.954 | N30: =IF(K30<>0,L30/K30,"-") -> 0 | O30: =+収支計画!S40/1000 -> 749.954 | P30: =+PL推移!J29 -> 0 | Q30: =+P30-O30 -> -749.954 | R30: =IF(O30<>0,P30/O30,"-") -> 0 | S30: =+収支計画!U40/1000 -> 0 | T30: =+PL推移!L29 -> 0 | U30: =+T30-S30 -> 0 | V30: =IF(S30<>0,T30/S30,"-") -> - | W30: =+収支計画!W40/1000 -> 0 | X30: =+PL推移!N29 -> 0 | Y30: =+X30-W30 -> 0 | Z30: =IF(W30<>0,X30/W30,"-") -> - | AA30: =+収支計画!Y40/1000 -> 0 | AB30: =+PL推移!P29 -> 0 | AC30: =+AB30-AA30 -> 0 | AD30: =IF(AA30<>0,AB30/AA30,"-") -> - | AE30: =+収支計画!AA40/1000 -> 0 | AF30: =+PL推移!R29 -> 0 | AG30: =+AF30-AE30 -> 0 | AH30: =IF(AE30<>0,AF30/AE30,"-") -> - | AI30: =+収支計画!AC40/1000 -> 0 | AJ30: =+PL推移!T29 -> 0 | AK30: =+AJ30-AI30 -> 0 | AL30: =IF(AI30<>0,AJ30/AI30,"-") -> - | AM30: =+収支計画!AG40/1000 -> 0 | AN30: =+PL推移!V29 -> 0 | AO30: =+AN30-AM30 -> 0 | AP30: =IF(AM30<>0,AN30/AM30,"-") -> - | AQ30: =+収支計画!AG40/1000 -> 0 | AR30: =+PL推移!X29 -> 0 | AS30: =+AR30-AQ30 -> 0 | AT30: =IF(AQ30<>0,AR30/AQ30,"-") -> - | AU30: =+収支計画!AI40/1000 -> 0 | AV30: =+PL推移!Z29 -> 0 | AW30: =+AV30-AU30 -> 0 | AX30: =IF(AU30<>0,AV30/AU30,"-") -> - | AY30: =+C30+G30+K30+O30+S30+W30+AA30+AE30+AI30+AM30+AQ30+AU30 -> 4972.181 | AZ30: =+D30+H30+L30+P30+T30+X30+AB30+AF30+AJ30+AN30+AR30+AV30 -> 2462.876 | BA30: =+AZ30-AY30 -> -2509.305 | BB30: =IF(AY30<>0,AZ30/AY30,"-") -> 0.49533112 | BC30: =+PL推移!N29-収支計画!W40/1000 -> 0 | BD30: =+BC30/(収支計画!W40/1000) -> #DIV/0! | BE30: =+PL推移!P29-収支計画!Y40/1000 -> 0 | BF30: =+BE30/(収支計画!Y40/1000) -> #DIV/0! | BG30: =+PL推移!R29-収支計画!AA40/1000 -> 0 | BH30: =+BG30/(収支計画!AA40/1000) -> #DIV/0! | BI30: =+PL推移!T29-収支計画!AC40/1000 -> 0 | BJ30: =+BI30/(収支計画!AC40/1000) -> #DIV/0! | BK30: =+PL推移!V29-収支計画!AE40/1000 -> 0 | BL30: =+BK30/(収支計画!AE40/1000) -> #DIV/0! | BM30: =+PL推移!X29-収支計画!AG40/1000 -> 0 | BN30: =+BM30/(収支計画!AG40/1000) -> #DIV/0! | BO30: =+PL推移!Z29-収支計画!AI40/1000 -> 0 | BP30: =+BO30/(収支計画!AI40/1000) -> #DIV/0!
B31: 旅費交通費 | C31: =+収支計画!G35/1000 -> 50 | D31: =+PL推移!D30 -> 41.261 | E31: =+D31-C31 -> -8.739 | F31: =IF(C31<>0,D31/C31,"-") -> 0.82522 | G31: =+収支計画!K41/1000 -> 30 | H31: =+PL推移!F30 -> 0 | I31: =+H31-G31 -> -30 | J31: =IF(G31<>0,H31/G31,"-") -> 0 | K31: =+収支計画!O41/1000 -> 30 | L31: =+PL推移!H30 -> 0 | M31: =+L31-K31 -> -30 | N31: =IF(K31<>0,L31/K31,"-") -> 0 | O31: =+収支計画!S41/1000 -> 30 | P31: =+PL推移!J30 -> 0 | Q31: =+P31-O31 -> -30 | R31: =IF(O31<>0,P31/O31,"-") -> 0 | S31: =+収支計画!U41/1000 -> 0 | T31: =+PL推移!L30 -> 0 | U31: =+T31-S31 -> 0 | V31: =IF(S31<>0,T31/S31,"-") -> - | W31: =+収支計画!W41/1000 -> 0 | X31: =+PL推移!N30 -> 0 | Y31: =+X31-W31 -> 0 | Z31: =IF(W31<>0,X31/W31,"-") -> - | AA31: =+収支計画!Y41/1000 -> 0 | AB31: =+PL推移!P30 -> 0 | AC31: =+AB31-AA31 -> 0 | AD31: =IF(AA31<>0,AB31/AA31,"-") -> - | AE31: =+収支計画!AA41/1000 -> 0 | AF31: =+PL推移!R30 -> 0 | AG31: =+AF31-AE31 -> 0 | AH31: =IF(AE31<>0,AF31/AE31,"-") -> - | AI31: =+収支計画!AC41/1000 -> 0 | AJ31: =+PL推移!T30 -> 0 | AK31: =+AJ31-AI31 -> 0 | AL31: =IF(AI31<>0,AJ31/AI31,"-") -> - | AM31: =+収支計画!AG41/1000 -> 0 | AN31: =+PL推移!V30 -> 0 | AO31: =+AN31-AM31 -> 0 | AP31: =IF(AM31<>0,AN31/AM31,"-") -> - | AQ31: =+収支計画!AG41/1000 -> 0 | AR31: =+PL推移!X30 -> 0 | AS31: =+AR31-AQ31 -> 0 | AT31: =IF(AQ31<>0,AR31/AQ31,"-") -> - | AU31: =+収支計画!AI41/1000 -> 0 | AV31: =+PL推移!Z30 -> 0 | AW31: =+AV31-AU31 -> 0 | AX31: =IF(AU31<>0,AV31/AU31,"-") -> - | AY31: =+C31+G31+K31+O31+S31+W31+AA31+AE31+AI31+AM31+AQ31+AU31 -> 140 | AZ31: =+D31+H31+L31+P31+T31+X31+AB31+AF31+AJ31+AN31+AR31+AV31 -> 41.261 | BA31: =+AZ31-AY31 -> -98.739 | BB31: =IF(AY31<>0,AZ31/AY31,"-") -> 0.29472143 | BC31: =+PL推移!N30-収支計画!W41/1000 -> 0 | BD31: =+BC31/(収支計画!W41/1000) -> #DIV/0! | BE31: =+PL推移!P30-収支計画!Y41/1000 -> 0 | BF31: =+BE31/(収支計画!Y41/1000) -> #DIV/0! | BG31: =+PL推移!R30-収支計画!AA41/1000 -> 0 | BH31: =+BG31/(収支計画!AA41/1000) -> #DIV/0! | BI31: =+PL推移!T30-収支計画!AC41/1000 -> 0 | BJ31: =+BI31/(収支計画!AC41/1000) -> #DIV/0! | BK31: =+PL推移!V30-収支計画!AE41/1000 -> 0 | BL31: =+BK31/(収支計画!AE41/1000) -> #DIV/0! | BM31: =+PL推移!X30-収支計画!AG41/1000 -> 0 | BN31: =+BM31/(収支計画!AG41/1000) -> #DIV/0! | BO31: =+PL推移!Z30-収支計画!AI41/1000 -> 0 | BP31: =+BO31/(収支計画!AI41/1000) -> #DIV/0!
B32: 通信費 | C32: =+収支計画!G36/1000 -> 63.05 | D32: =+PL推移!D31 -> 62.422 | E32: =+D32-C32 -> -0.628 | F32: =IF(C32<>0,D32/C32,"-") -> 0.99003965 | G32: =+収支計画!K42/1000 -> 1295.661 | H32: =+PL推移!F31 -> 0 | I32: =+H32-G32 -> -1295.661 | J32: =IF(G32<>0,H32/G32,"-") -> 0 | K32: =+収支計画!O42/1000 -> 1295.661 | L32: =+PL推移!H31 -> 0 | M32: =+L32-K32 -> -1295.661 | N32: =IF(K32<>0,L32/K32,"-") -> 0 | O32: =+収支計画!S42/1000 -> 1295.661 | P32: =+PL推移!J31 -> 0 | Q32: =+P32-O32 -> -1295.661 | R32: =IF(O32<>0,P32/O32,"-") -> 0 | S32: =+収支計画!U42/1000 -> 0 | T32: =+PL推移!L31 -> 0 | U32: =+T32-S32 -> 0 | V32: =IF(S32<>0,T32/S32,"-") -> - | W32: =+収支計画!W42/1000 -> 0 | X32: =+PL推移!N31 -> 0 | Y32: =+X32-W32 -> 0 | Z32: =IF(W32<>0,X32/W32,"-") -> - | AA32: =+収支計画!Y42/1000 -> 0 | AB32: =+PL推移!P31 -> 0 | AC32: =+AB32-AA32 -> 0 | AD32: =IF(AA32<>0,AB32/AA32,"-") -> - | AE32: =+収支計画!AA42/1000 -> 0 | AF32: =+PL推移!R31 -> 0 | AG32: =+AF32-AE32 -> 0 | AH32: =IF(AE32<>0,AF32/AE32,"-") -> - | AI32: =+収支計画!AC42/1000 -> 0 | AJ32: =+PL推移!T31 -> 0 | AK32: =+AJ32-AI32 -> 0 | AL32: =IF(AI32<>0,AJ32/AI32,"-") -> - | AM32: =+収支計画!AG42/1000 -> 0 | AN32: =+PL推移!V31 -> 0 | AO32: =+AN32-AM32 -> 0 | AP32: =IF(AM32<>0,AN32/AM32,"-") -> - | AQ32: =+収支計画!AG42/1000 -> 0 | AR32: =+PL推移!X31 -> 0 | AS32: =+AR32-AQ32 -> 0 | AT32: =IF(AQ32<>0,AR32/AQ32,"-") -> - | AU32: =+収支計画!AI42/1000 -> 0 | AV32: =+PL推移!Z31 -> 0 | AW32: =+AV32-AU32 -> 0 | AX32: =IF(AU32<>0,AV32/AU32,"-") -> - | AY32: =+C32+G32+K32+O32+S32+W32+AA32+AE32+AI32+AM32+AQ32+AU32 -> 3950.033 | AZ32: =+D32+H32+L32+P32+T32+X32+AB32+AF32+AJ32+AN32+AR32+AV32 -> 62.422 | BA32: =+AZ32-AY32 -> -3887.611 | BB32: =IF(AY32<>0,AZ32/AY32,"-") -> 0.015802906 | BC32: =+PL推移!N31-収支計画!W42/1000 -> 0 | BD32: =+BC32/(収支計画!W42/1000) -> #DIV/0! | BE32: =+PL推移!P31-収支計画!Y42/1000 -> 0 | BF32: =+BE32/(収支計画!Y42/1000) -> #DIV/0! | BG32: =+PL推移!R31-収支計画!AA42/1000 -> 0 | BH32: =+BG32/(収支計画!AA42/1000) -> #DIV/0! | BI32: =+PL推移!T31-収支計画!AC42/1000 -> 0 | BJ32: =+BI32/(収支計画!AC42/1000) -> #DIV/0! | BK32: =+PL推移!V31-収支計画!AE42/1000 -> 0 | BL32: =+BK32/(収支計画!AE42/1000) -> #DIV/0! | BM32: =+PL推移!X31-収支計画!AG42/1000 -> 0 | BN32: =+BM32/(収支計画!AG42/1000) -> #DIV/0! | BO32: =+PL推移!Z31-収支計画!AI42/1000 -> 0 | BP32: =+BO32/(収支計画!AI42/1000) -> #DIV/0!
B33: 開発費 | C33: =+収支計画!G37/1000 -> 0 | D33: =+PL推移!D32 -> 0 | E33: =+D33-C33 -> 0 | F33: =IF(C33<>0,D33/C33,"-") -> - | G33: =+収支計画!K43/1000 -> 49.7 | H33: =+PL推移!F32 -> 0 | I33: =+H33-G33 -> -49.7 | J33: =IF(G33<>0,H33/G33,"-") -> 0 | K33: =+収支計画!O43/1000 -> 49.7 | L33: =+PL推移!H32 -> 0 | M33: =+L33-K33 -> -49.7 | N33: =IF(K33<>0,L33/K33,"-") -> 0 | O33: =+収支計画!S43/1000 -> 49.7 | P33: =+PL推移!J32 -> 0 | Q33: =+P33-O33 -> -49.7 | R33: =IF(O33<>0,P33/O33,"-") -> 0 | S33: =+収支計画!U43/1000 -> 0 | T33: =+PL推移!L32 -> 0 | U33: =+T33-S33 -> 0 | V33: =IF(S33<>0,T33/S33,"-") -> - | W33: =+収支計画!W43/1000 -> 0 | X33: =+PL推移!N32 -> 0 | Y33: =+X33-W33 -> 0 | Z33: =IF(W33<>0,X33/W33,"-") -> - | AA33: =+収支計画!Y43/1000 -> 0 | AB33: =+PL推移!P32 -> 0 | AC33: =+AB33-AA33 -> 0 | AD33: =IF(AA33<>0,AB33/AA33,"-") -> - | AE33: =+収支計画!AA43/1000 -> 0 | AF33: =+PL推移!R32 -> 0 | AG33: =+AF33-AE33 -> 0 | AH33: =IF(AE33<>0,AF33/AE33,"-") -> - | AI33: =+収支計画!AC43/1000 -> 0 | AJ33: =+PL推移!T32 -> 0 | AK33: =+AJ33-AI33 -> 0 | AL33: =IF(AI33<>0,AJ33/AI33,"-") -> - | AM33: =+収支計画!AG43/1000 -> 0 | AN33: =+PL推移!V32 -> 0 | AO33: =+AN33-AM33 -> 0 | AP33: =IF(AM33<>0,AN33/AM33,"-") -> - | AQ33: =+収支計画!AG43/1000 -> 0 | AR33: =+PL推移!X32 -> 0 | AS33: =+AR33-AQ33 -> 0 | AT33: =IF(AQ33<>0,AR33/AQ33,"-") -> - | AU33: =+収支計画!AI43/1000 -> 0 | AV33: =+PL推移!Z32 -> 0 | AW33: =+AV33-AU33 -> 0 | AX33: =IF(AU33<>0,AV33/AU33,"-") -> - | AY33: =+C33+G33+K33+O33+S33+W33+AA33+AE33+AI33+AM33+AQ33+AU33 -> 149.1 | AZ33: =+D33+H33+L33+P33+T33+X33+AB33+AF33+AJ33+AN33+AR33+AV33 -> 0 | BA33: =+AZ33-AY33 -> -149.1 | BB33: =IF(AY33<>0,AZ33/AY33,"-") -> 0 | BC33: =+PL推移!N32-収支計画!W43/1000 -> 0 | BD33: =+BC33/(収支計画!W43/1000) -> #DIV/0! | BE33: =+PL推移!P32-収支計画!Y43/1000 -> 0 | BF33: =+BE33/(収支計画!Y43/1000) -> #DIV/0! | BG33: =+PL推移!R32-収支計画!AA43/1000 -> 0 | BH33: =+BG33/(収支計画!AA43/1000) -> #DIV/0! | BI33: =+PL推移!T32-収支計画!AC43/1000 -> 0 | BJ33: =+BI33/(収支計画!AC43/1000) -> #DIV/0! | BK33: =+PL推移!V32-収支計画!AE43/1000 -> 0 | BL33: =+BK33/(収支計画!AE43/1000) -> #DIV/0! | BM33: =+PL推移!X32-収支計画!AG43/1000 -> 0 | BN33: =+BM33/(収支計画!AG43/1000) -> #DIV/0! | BO33: =+PL推移!Z32-収支計画!AI43/1000 -> 0 | BP33: =+BO33/(収支計画!AI43/1000) -> #DIV/0!
B34: 交際費 | C34: =+収支計画!G38/1000 -> 0 | D34: =+PL推移!D33 -> 0 | E34: =+D34-C34 -> 0 | F34: =IF(C34<>0,D34/C34,"-") -> - | G34: =+収支計画!K44/1000 -> 10 | H34: =+PL推移!F33 -> 0 | I34: =+H34-G34 -> -10 | J34: =IF(G34<>0,H34/G34,"-") -> 0 | K34: =+収支計画!O44/1000 -> 10 | L34: =+PL推移!H33 -> 0 | M34: =+L34-K34 -> -10 | N34: =IF(K34<>0,L34/K34,"-") -> 0 | O34: =+収支計画!S44/1000 -> 10 | P34: =+PL推移!J33 -> 0 | Q34: =+P34-O34 -> -10 | R34: =IF(O34<>0,P34/O34,"-") -> 0 | S34: =+収支計画!U44/1000 -> 0 | T34: =+PL推移!L33 -> 0 | U34: =+T34-S34 -> 0 | V34: =IF(S34<>0,T34/S34,"-") -> - | W34: =+収支計画!W44/1000 -> 0 | X34: =+PL推移!N33 -> 0 | Y34: =+X34-W34 -> 0 | Z34: =IF(W34<>0,X34/W34,"-") -> - | AA34: =+収支計画!Y44/1000 -> 0 | AB34: =+PL推移!P33 -> 0 | AC34: =+AB34-AA34 -> 0 | AD34: =IF(AA34<>0,AB34/AA34,"-") -> - | AE34: =+収支計画!AA44/1000 -> 0 | AF34: =+PL推移!R33 -> 0 | AG34: =+AF34-AE34 -> 0 | AH34: =IF(AE34<>0,AF34/AE34,"-") -> - | AI34: =+収支計画!AC44/1000 -> 0 | AJ34: =+PL推移!T33 -> 0 | AK34: =+AJ34-AI34 -> 0 | AL34: =IF(AI34<>0,AJ34/AI34,"-") -> - | AM34: =+収支計画!AG44/1000 -> 0 | AN34: =+PL推移!V33 -> 0 | AO34: =+AN34-AM34 -> 0 | AP34: =IF(AM34<>0,AN34/AM34,"-") -> - | AQ34: =+収支計画!AG44/1000 -> 0 | AR34: =+PL推移!X33 -> 0 | AS34: =+AR34-AQ34 -> 0 | AT34: =IF(AQ34<>0,AR34/AQ34,"-") -> - | AU34: =+収支計画!AI44/1000 -> 0 | AV34: =+PL推移!Z33 -> 0 | AW34: =+AV34-AU34 -> 0 | AX34: =IF(AU34<>0,AV34/AU34,"-") -> - | AY34: =+C34+G34+K34+O34+S34+W34+AA34+AE34+AI34+AM34+AQ34+AU34 -> 30 | AZ34: =+D34+H34+L34+P34+T34+X34+AB34+AF34+AJ34+AN34+AR34+AV34 -> 0 | BA34: =+AZ34-AY34 -> -30 | BB34: =IF(AY34<>0,AZ34/AY34,"-") -> 0 | BC34: =+PL推移!N33-収支計画!W44/1000 -> 0 | BD34: =+BC34/(収支計画!W44/1000) -> #DIV/0! | BE34: =+PL推移!P33-収支計画!Y44/1000 -> 0 | BF34: =+BE34/(収支計画!Y44/1000) -> #DIV/0! | BG34: =+PL推移!R33-収支計画!AA44/1000 -> 0 | BH34: =+BG34/(収支計画!AA44/1000) -> #DIV/0! | BI34: =+PL推移!T33-収支計画!AC44/1000 -> 0 | BJ34: =+BI34/(収支計画!AC44/1000) -> #DIV/0! | BK34: =+PL推移!V33-収支計画!AE44/1000 -> 0 | BL34: =+BK34/(収支計画!AE44/1000) -> #DIV/0! | BM34: =+PL推移!X33-収支計画!AG44/1000 -> 0 | BN34: =+BM34/(収支計画!AG44/1000) -> #DIV/0! | BO34: =+PL推移!Z33-収支計画!AI44/1000 -> 0 | BP34: =+BO34/(収支計画!AI44/1000) -> #DIV/0!
B35: 会議費 | C35: =+収支計画!G39/1000 -> 10 | D35: =+PL推移!D34 -> 7.273 | E35: =+D35-C35 -> -2.727 | F35: =IF(C35<>0,D35/C35,"-") -> 0.7273 | G35: =+収支計画!K45/1000 -> 25.32 | H35: =+PL推移!F34 -> 0 | I35: =+H35-G35 -> -25.32 | J35: =IF(G35<>0,H35/G35,"-") -> 0 | K35: =+収支計画!O45/1000 -> 25.32 | L35: =+PL推移!H34 -> 0 | M35: =+L35-K35 -> -25.32 | N35: =IF(K35<>0,L35/K35,"-") -> 0 | O35: =+収支計画!S45/1000 -> 22.215 | P35: =+PL推移!J34 -> 0 | Q35: =+P35-O35 -> -22.215 | R35: =IF(O35<>0,P35/O35,"-") -> 0 | S35: =+収支計画!W45/1000 -> 0 | T35: =+PL推移!L34 -> 0 | U35: =+T35-S35 -> 0 | V35: =IF(S35<>0,T35/S35,"-") -> - | W35: =+収支計画!W45/1000 -> 0 | X35: =+PL推移!N34 -> 0 | Y35: =+X35-W35 -> 0 | Z35: =IF(W35<>0,X35/W35,"-") -> - | AA35: =+収支計画!Y45/1000 -> 0 | AB35: =+PL推移!P34 -> 0 | AC35: =+AB35-AA35 -> 0 | AD35: =IF(AA35<>0,AB35/AA35,"-") -> - | AE35: =+収支計画!AA45/1000 -> 0 | AF35: =+PL推移!R34 -> 0 | AG35: =+AF35-AE35 -> 0 | AH35: =IF(AE35<>0,AF35/AE35,"-") -> - | AI35: =+収支計画!AC45/1000 -> 0 | AJ35: =+PL推移!T34 -> 0 | AK35: =+AJ35-AI35 -> 0 | AL35: =IF(AI35<>0,AJ35/AI35,"-") -> - | AM35: =+収支計画!AG45/1000 -> 0 | AN35: =+PL推移!V34 -> 0 | AO35: =+AN35-AM35 -> 0 | AP35: =IF(AM35<>0,AN35/AM35,"-") -> - | AQ35: =+収支計画!AG45/1000 -> 0 | AR35: =+PL推移!X34 -> 0 | AS35: =+AR35-AQ35 -> 0 | AT35: =IF(AQ35<>0,AR35/AQ35,"-") -> - | AU35: =+収支計画!AI45/1000 -> 0 | AV35: =+PL推移!Z34 -> 0 | AW35: =+AV35-AU35 -> 0 | AX35: =IF(AU35<>0,AV35/AU35,"-") -> - | AY35: =+C35+G35+K35+O35+S35+W35+AA35+AE35+AI35+AM35+AQ35+AU35 -> 82.855 | AZ35: =+D35+H35+L35+P35+T35+X35+AB35+AF35+AJ35+AN35+AR35+AV35 -> 7.273 | BA35: =+AZ35-AY35 -> -75.582 | BB35: =IF(AY35<>0,AZ35/AY35,"-") -> 0.087779856 | BC35: =+PL推移!N34-収支計画!W45/1000 -> 0 | BD35: =+BC35/(収支計画!W45/1000) -> #DIV/0! | BE35: =+PL推移!P34-収支計画!Y45/1000 -> 0 | BF35: =+BE35/(収支計画!Y45/1000) -> #DIV/0! | BG35: =+PL推移!R34-収支計画!AA45/1000 -> 0 | BH35: =+BG35/(収支計画!AA45/1000) -> #DIV/0! | BI35: =+PL推移!T34-収支計画!AC45/1000 -> 0 | BJ35: =+BI35/(収支計画!AC45/1000) -> #DIV/0! | BK35: =+PL推移!V34-収支計画!AE45/1000 -> 0 | BL35: =+BK35/(収支計画!AE45/1000) -> #DIV/0! | BM35: =+PL推移!X34-収支計画!AG45/1000 -> 0 | BN35: =+BM35/(収支計画!AG45/1000) -> #DIV/0! | BO35: =+PL推移!Z34-収支計画!AI45/1000 -> 0 | BP35: =+BO35/(収支計画!AI45/1000) -> #DIV/0!
B36: 減価償却費 | C36: =+収支計画!G40/1000 -> 749.954 | D36: =+PL推移!D35 -> 749.954 | E36: =+D36-C36 -> 0 | F36: =IF(C36<>0,D36/C36,"-") -> 1 | G36: =+収支計画!K46/1000 -> 660 | H36: =+PL推移!F35 -> 0 | I36: =+H36-G36 -> -660 | J36: =IF(G36<>0,H36/G36,"-") -> 0 | K36: =+収支計画!O46/1000 -> 780 | L36: =+PL推移!H35 -> 0 | M36: =+L36-K36 -> -780 | N36: =IF(K36<>0,L36/K36,"-") -> 0 | O36: =+収支計画!S46/1000 -> 860 | P36: =+PL推移!J35 -> 0 | Q36: =+P36-O36 -> -860 | R36: =IF(O36<>0,P36/O36,"-") -> 0 | S36: =+収支計画!U46/1000 -> 0 | T36: =+PL推移!L35 -> 0 | U36: =+T36-S36 -> 0 | V36: =IF(S36<>0,T36/S36,"-") -> - | W36: =+収支計画!W46/1000 -> 0 | X36: =+PL推移!N35 -> 0 | Y36: =+X36-W36 -> 0 | Z36: =IF(W36<>0,X36/W36,"-") -> - | AA36: =+収支計画!Y46/1000 -> 0 | AB36: =+PL推移!P35 -> 0 | AC36: =+AB36-AA36 -> 0 | AD36: =IF(AA36<>0,AB36/AA36,"-") -> - | AE36: =+収支計画!AA46/1000 -> 0 | AF36: =+PL推移!R35 -> 0 | AG36: =+AF36-AE36 -> 0 | AH36: =IF(AE36<>0,AF36/AE36,"-") -> - | AI36: =+収支計画!AC46/1000 -> 0 | AJ36: =+PL推移!T35 -> 0 | AK36: =+AJ36-AI36 -> 0 | AL36: =IF(AI36<>0,AJ36/AI36,"-") -> - | AM36: =+収支計画!AG46/1000 -> 0 | AN36: =+PL推移!V35 -> 0 | AO36: =+AN36-AM36 -> 0 | AP36: =IF(AM36<>0,AN36/AM36,"-") -> - | AQ36: =+収支計画!AG46/1000 -> 0 | AR36: =+PL推移!X35 -> 0 | AS36: =+AR36-AQ36 -> 0 | AT36: =IF(AQ36<>0,AR36/AQ36,"-") -> - | AU36: =+収支計画!AI46/1000 -> 0 | AV36: =+PL推移!Z35 -> 0 | AW36: =+AV36-AU36 -> 0 | AX36: =IF(AU36<>0,AV36/AU36,"-") -> - | AY36: =+C36+G36+K36+O36+S36+W36+AA36+AE36+AI36+AM36+AQ36+AU36 -> 3049.954 | AZ36: =+D36+H36+L36+P36+T36+X36+AB36+AF36+AJ36+AN36+AR36+AV36 -> 749.954 | BA36: =+AZ36-AY36 -> -2300 | BB36: =IF(AY36<>0,AZ36/AY36,"-") -> 0.24589027 | BC36: =+PL推移!N35-収支計画!W46/1000 -> 0 | BD36: =+BC36/(収支計画!W46/1000) -> #DIV/0! | BE36: =+PL推移!P35-収支計画!Y46/1000 -> 0 | BF36: =+BE36/(収支計画!Y46/1000) -> #DIV/0! | BG36: =+PL推移!R35-収支計画!AA46/1000 -> 0 | BH36: =+BG36/(収支計画!AA46/1000) -> #DIV/0! | BI36: =+PL推移!T35-収支計画!AC46/1000 -> 0 | BJ36: =+BI36/(収支計画!AC46/1000) -> #DIV/0! | BK36: =+PL推移!V35-収支計画!AE46/1000 -> 0 | BL36: =+BK36/(収支計画!AE46/1000) -> #DIV/0! | BM36: =+PL推移!X35-収支計画!AG46/1000 -> 0 | BN36: =+BM36/(収支計画!AG46/1000) -> #DIV/0! | BO36: =+PL推移!Z35-収支計画!AI46/1000 -> 0 | BP36: =+BO36/(収支計画!AI46/1000) -> #DIV/0!
B37: 賃借料 | C37: =+収支計画!G41/1000 -> 30 | D37: =+PL推移!D36 -> 30 | E37: =+D37-C37 -> 0 | F37: =IF(C37<>0,D37/C37,"-") -> 1 | G37: =+収支計画!K47/1000 -> 180 | H37: =+PL推移!F36 -> 0 | I37: =+H37-G37 -> -180 | J37: =IF(G37<>0,H37/G37,"-") -> 0 | K37: =+収支計画!O47/1000 -> 210 | L37: =+PL推移!H36 -> 0 | M37: =+L37-K37 -> -210 | N37: =IF(K37<>0,L37/K37,"-") -> 0 | O37: =+収支計画!S47/1000 -> 200 | P37: =+PL推移!J36 -> 0 | Q37: =+P37-O37 -> -200 | R37: =IF(O37<>0,P37/O37,"-") -> 0 | S37: =+収支計画!U47/1000 -> 0 | T37: =+PL推移!L36 -> 0 | U37: =+T37-S37 -> 0 | V37: =IF(S37<>0,T37/S37,"-") -> - | W37: =+収支計画!W47/1000 -> 0 | X37: =+PL推移!N36 -> 0 | Y37: =+X37-W37 -> 0 | Z37: =IF(W37<>0,X37/W37,"-") -> - | AA37: =+収支計画!Y47/1000 -> 0 | AB37: =+PL推移!P36 -> 0 | AC37: =+AB37-AA37 -> 0 | AD37: =IF(AA37<>0,AB37/AA37,"-") -> - | AE37: =+収支計画!AA47/1000 -> 0 | AF37: =+PL推移!R36 -> 0 | AG37: =+AF37-AE37 -> 0 | AH37: =IF(AE37<>0,AF37/AE37,"-") -> - | AI37: =+収支計画!AC47/1000 -> 0 | AJ37: =+PL推移!T36 -> 0 | AK37: =+AJ37-AI37 -> 0 | AL37: =IF(AI37<>0,AJ37/AI37,"-") -> - | AM37: =+収支計画!AG47/1000 -> 0 | AN37: =+PL推移!V36 -> 0 | AO37: =+AN37-AM37 -> 0 | AP37: =IF(AM37<>0,AN37/AM37,"-") -> - | AQ37: =+収支計画!AG47/1000 -> 0 | AR37: =+PL推移!X36 -> 0 | AS37: =+AR37-AQ37 -> 0 | AT37: =IF(AQ37<>0,AR37/AQ37,"-") -> - | AU37: =+収支計画!AI47/1000 -> 0 | AV37: =+PL推移!Z36 -> 0 | AW37: =+AV37-AU37 -> 0 | AX37: =IF(AU37<>0,AV37/AU37,"-") -> - | AY37: =+C37+G37+K37+O37+S37+W37+AA37+AE37+AI37+AM37+AQ37+AU37 -> 620 | AZ37: =+D37+H37+L37+P37+T37+X37+AB37+AF37+AJ37+AN37+AR37+AV37 -> 30 | BA37: =+AZ37-AY37 -> -590 | BB37: =IF(AY37<>0,AZ37/AY37,"-") -> 0.048387097 | BC37: =+PL推移!N36-収支計画!W47/1000 -> 0 | BD37: =+BC37/(収支計画!W47/1000) -> #DIV/0! | BE37: =+PL推移!P36-収支計画!Y47/1000 -> 0 | BF37: =+BE37/(収支計画!Y47/1000) -> #DIV/0! | BG37: =+PL推移!R36-収支計画!AA47/1000 -> 0 | BH37: =+BG37/(収支計画!AA47/1000) -> #DIV/0! | BI37: =+PL推移!T36-収支計画!AC47/1000 -> 0 | BJ37: =+BI37/(収支計画!AC47/1000) -> #DIV/0! | BK37: =+PL推移!V36-収支計画!AE47/1000 -> 0 | BL37: =+BK37/(収支計画!AE47/1000) -> #DIV/0! | BM37: =+PL推移!X36-収支計画!AG47/1000 -> 0 | BN37: =+BM37/(収支計画!AG47/1000) -> #DIV/0! | BO37: =+PL推移!Z36-収支計画!AI47/1000 -> 0 | BP37: =+BO37/(収支計画!AI47/1000) -> #DIV/0!
B38: 地代家賃 | C38: =+収支計画!G42/1000 -> 1295.661 | D38: =+PL推移!D37 -> 1295.661 | E38: =+D38-C38 -> 0 | F38: =IF(C38<>0,D38/C38,"-") -> 1 | G38: =+収支計画!K48/1000 -> 1 | H38: =+PL推移!F37 -> 0 | I38: =+H38-G38 -> -1 | J38: =IF(G38<>0,H38/G38,"-") -> 0 | K38: =+収支計画!O48/1000 -> 1 | L38: =+PL推移!H37 -> 0 | M38: =+L38-K38 -> -1 | N38: =IF(K38<>0,L38/K38,"-") -> 0 | O38: =+収支計画!S48/1000 -> 1 | P38: =+PL推移!J37 -> 0 | Q38: =+P38-O38 -> -1 | R38: =IF(O38<>0,P38/O38,"-") -> 0 | S38: =+収支計画!U48/1000 -> 0 | T38: =+PL推移!L37 -> 0 | U38: =+T38-S38 -> 0 | V38: =IF(S38<>0,T38/S38,"-") -> - | W38: =+収支計画!W48/1000 -> 0 | X38: =+PL推移!N37 -> 0 | Y38: =+X38-W38 -> 0 | Z38: =IF(W38<>0,X38/W38,"-") -> - | AA38: =+収支計画!Y48/1000 -> 0 | AB38: =+PL推移!P37 -> 0 | AC38: =+AB38-AA38 -> 0 | AD38: =IF(AA38<>0,AB38/AA38,"-") -> - | AE38: =+収支計画!AA48/1000 -> 0 | AF38: =+PL推移!R37 -> 0 | AG38: =+AF38-AE38 -> 0 | AH38: =IF(AE38<>0,AF38/AE38,"-") -> - | AI38: =+収支計画!AC48/1000 -> 0 | AJ38: =+PL推移!T37 -> 0 | AK38: =+AJ38-AI38 -> 0 | AL38: =IF(AI38<>0,AJ38/AI38,"-") -> - | AM38: =+収支計画!AG48/1000 -> 0 | AN38: =+PL推移!V37 -> 0 | AO38: =+AN38-AM38 -> 0 | AP38: =IF(AM38<>0,AN38/AM38,"-") -> - | AQ38: =+収支計画!AG48/1000 -> 0 | AR38: =+PL推移!X37 -> 0 | AS38: =+AR38-AQ38 -> 0 | AT38: =IF(AQ38<>0,AR38/AQ38,"-") -> - | AU38: =+収支計画!AI48/1000 -> 0 | AV38: =+PL推移!Z37 -> 0 | AW38: =+AV38-AU38 -> 0 | AX38: =IF(AU38<>0,AV38/AU38,"-") -> - | AY38: =+C38+G38+K38+O38+S38+W38+AA38+AE38+AI38+AM38+AQ38+AU38 -> 1298.661 | AZ38: =+D38+H38+L38+P38+T38+X38+AB38+AF38+AJ38+AN38+AR38+AV38 -> 1295.661 | BA38: =+AZ38-AY38 -> -3 | BB38: =IF(AY38<>0,AZ38/AY38,"-") -> 0.99768993 | BC38: =+PL推移!N37-収支計画!W48/1000 -> 0 | BD38: =+BC38/(収支計画!W48/1000) -> #DIV/0! | BE38: =+PL推移!P37-収支計画!Y48/1000 -> 0 | BF38: =+BE38/(収支計画!Y48/1000) -> #DIV/0! | BG38: =+PL推移!R37-収支計画!AA48/1000 -> 0 | BH38: =+BG38/(収支計画!AA48/1000) -> #DIV/0! | BI38: =+PL推移!T37-収支計画!AC48/1000 -> 0 | BJ38: =+BI38/(収支計画!AC48/1000) -> #DIV/0! | BK38: =+PL推移!V37-収支計画!AE48/1000 -> 0 | BL38: =+BK38/(収支計画!AE48/1000) -> #DIV/0! | BM38: =+PL推移!X37-収支計画!AG48/1000 -> 0 | BN38: =+BM38/(収支計画!AG48/1000) -> #DIV/0! | BO38: =+PL推移!Z37-収支計画!AI48/1000 -> 0 | BP38: =+BO38/(収支計画!AI48/1000) -> #DIV/0!
B39: リース料 | C39: =+収支計画!G43/1000 -> 49.7 | D39: =+PL推移!D38 -> 49.7 | E39: =+D39-C39 -> 0 | F39: =IF(C39<>0,D39/C39,"-") -> 1 | G39: =+収支計画!K49/1000 -> 165 | H39: =+PL推移!F38 -> 0 | I39: =+H39-G39 -> -165 | J39: =IF(G39<>0,H39/G39,"-") -> 0 | K39: =+収支計画!O49/1000 -> 165 | L39: =+PL推移!H38 -> 0 | M39: =+L39-K39 -> -165 | N39: =IF(K39<>0,L39/K39,"-") -> 0 | O39: =+収支計画!S49/1000 -> 165 | P39: =+PL推移!J38 -> 0 | Q39: =+P39-O39 -> -165 | R39: =IF(O39<>0,P39/O39,"-") -> 0 | S39: =+収支計画!U49/1000 -> 0 | T39: =+PL推移!L38 -> 0 | U39: =+T39-S39 -> 0 | V39: =IF(S39<>0,T39/S39,"-") -> - | W39: =+収支計画!W49/1000 -> 0 | X39: =+PL推移!N38 -> 0 | Y39: =+X39-W39 -> 0 | Z39: =IF(W39<>0,X39/W39,"-") -> - | AA39: =+収支計画!Y49/1000 -> 0 | AB39: =+PL推移!P38 -> 0 | AC39: =+AB39-AA39 -> 0 | AD39: =IF(AA39<>0,AB39/AA39,"-") -> - | AE39: =+収支計画!AA49/1000 -> 0 | AF39: =+PL推移!R38 -> 0 | AG39: =+AF39-AE39 -> 0 | AH39: =IF(AE39<>0,AF39/AE39,"-") -> - | AI39: =+収支計画!AC49/1000 -> 0 | AJ39: =+PL推移!T38 -> 0 | AK39: =+AJ39-AI39 -> 0 | AL39: =IF(AI39<>0,AJ39/AI39,"-") -> - | AM39: =+収支計画!AG49/1000 -> 0 | AN39: =+PL推移!V38 -> 0 | AO39: =+AN39-AM39 -> 0 | AP39: =IF(AM39<>0,AN39/AM39,"-") -> - | AQ39: =+収支計画!AG49/1000 -> 0 | AR39: =+PL推移!X38 -> 0 | AS39: =+AR39-AQ39 -> 0 | AT39: =IF(AQ39<>0,AR39/AQ39,"-") -> - | AU39: =+収支計画!AI49/1000 -> 0 | AV39: =+PL推移!Z38 -> 0 | AW39: =+AV39-AU39 -> 0 | AX39: =IF(AU39<>0,AV39/AU39,"-") -> - | AY39: =+C39+G39+K39+O39+S39+W39+AA39+AE39+AI39+AM39+AQ39+AU39 -> 544.7 | AZ39: =+D39+H39+L39+P39+T39+X39+AB39+AF39+AJ39+AN39+AR39+AV39 -> 49.7 | BA39: =+AZ39-AY39 -> -495 | BB39: =IF(AY39<>0,AZ39/AY39,"-") -> 0.091242886 | BC39: =+PL推移!N38-収支計画!W49/1000 -> 0 | BD39: =+BC39/(収支計画!W49/1000) -> #DIV/0! | BE39: =+PL推移!P38-収支計画!Y49/1000 -> 0 | BF39: =+BE39/(収支計画!Y49/1000) -> #DIV/0! | BG39: =+PL推移!R38-収支計画!AA49/1000 -> 0 | BH39: =+BG39/(収支計画!AA49/1000) -> #DIV/0! | BI39: =+PL推移!T38-収支計画!AC49/1000 -> 0 | BJ39: =+BI39/(収支計画!AC49/1000) -> #DIV/0! | BK39: =+PL推移!V38-収支計画!AE49/1000 -> 0 | BL39: =+BK39/(収支計画!AE49/1000) -> #DIV/0! | BM39: =+PL推移!X38-収支計画!AG49/1000 -> 0 | BN39: =+BM39/(収支計画!AG49/1000) -> #DIV/0! | BO39: =+PL推移!Z38-収支計画!AI49/1000 -> 0 | BP39: =+BO39/(収支計画!AI49/1000) -> #DIV/0!
B40: 修繕費 | C40: =+収支計画!G44/1000 -> 10 | D40: =+PL推移!D39 -> 0 | E40: =+D40-C40 -> -10 | F40: =IF(C40<>0,D40/C40,"-") -> 0 | G40: =+収支計画!K50/1000 -> 292.5 | H40: =+PL推移!F39 -> 0 | I40: =+H40-G40 -> -292.5 | J40: =IF(G40<>0,H40/G40,"-") -> 0 | K40: =+収支計画!O50/1000 -> 324 | L40: =+PL推移!H39 -> 0 | M40: =+L40-K40 -> -324 | N40: =IF(K40<>0,L40/K40,"-") -> 0 | O40: =+収支計画!S50/1000 -> 331.5 | P40: =+PL推移!J39 -> 0 | Q40: =+P40-O40 -> -331.5 | R40: =IF(O40<>0,P40/O40,"-") -> 0 | S40: =+収支計画!U50/1000 -> 0 | T40: =+PL推移!L39 -> 0 | U40: =+T40-S40 -> 0 | V40: =IF(S40<>0,T40/S40,"-") -> - | W40: =+収支計画!W50/1000 -> 0 | X40: =+PL推移!N39 -> 0 | Y40: =+X40-W40 -> 0 | Z40: =IF(W40<>0,X40/W40,"-") -> - | AA40: =+収支計画!Y50/1000 -> 0 | AB40: =+PL推移!P39 -> 0 | AC40: =+AB40-AA40 -> 0 | AD40: =IF(AA40<>0,AB40/AA40,"-") -> - | AE40: =+収支計画!AA50/1000 -> 0 | AF40: =+PL推移!R39 -> 0 | AG40: =+AF40-AE40 -> 0 | AH40: =IF(AE40<>0,AF40/AE40,"-") -> - | AI40: =+収支計画!AC50/1000 -> 0 | AJ40: =+PL推移!T39 -> 0 | AK40: =+AJ40-AI40 -> 0 | AL40: =IF(AI40<>0,AJ40/AI40,"-") -> - | AM40: =+収支計画!AG50/1000 -> 0 | AN40: =+PL推移!V39 -> 0 | AO40: =+AN40-AM40 -> 0 | AP40: =IF(AM40<>0,AN40/AM40,"-") -> - | AQ40: =+収支計画!AG50/1000 -> 0 | AR40: =+PL推移!X39 -> 0 | AS40: =+AR40-AQ40 -> 0 | AT40: =IF(AQ40<>0,AR40/AQ40,"-") -> - | AU40: =+収支計画!AI50/1000 -> 0 | AV40: =+PL推移!Z39 -> 0 | AW40: =+AV40-AU40 -> 0 | AX40: =IF(AU40<>0,AV40/AU40,"-") -> - | AY40: =+C40+G40+K40+O40+S40+W40+AA40+AE40+AI40+AM40+AQ40+AU40 -> 958 | AZ40: =+D40+H40+L40+P40+T40+X40+AB40+AF40+AJ40+AN40+AR40+AV40 -> 0 | BA40: =+AZ40-AY40 -> -958 | BB40: =IF(AY40<>0,AZ40/AY40,"-") -> 0 | BC40: =+PL推移!N39-収支計画!W50/1000 -> 0 | BD40: =+BC40/(収支計画!W50/1000) -> #DIV/0! | BE40: =+PL推移!P39-収支計画!Y50/1000 -> 0 | BF40: =+BE40/(収支計画!Y50/1000) -> #DIV/0! | BG40: =+PL推移!R39-収支計画!AA50/1000 -> 0 | BH40: =+BG40/(収支計画!AA50/1000) -> #DIV/0! | BI40: =+PL推移!T39-収支計画!AC50/1000 -> 0 | BJ40: =+BI40/(収支計画!AC50/1000) -> #DIV/0! | BK40: =+PL推移!V39-収支計画!AE50/1000 -> 0 | BL40: =+BK40/(収支計画!AE50/1000) -> #DIV/0! | BM40: =+PL推移!X39-収支計画!AG50/1000 -> 0 | BN40: =+BM40/(収支計画!AG50/1000) -> #DIV/0! | BO40: =+PL推移!Z39-収支計画!AI50/1000 -> 0 | BP40: =+BO40/(収支計画!AI50/1000) -> #DIV/0!
B41: 保険料 | C41: =+収支計画!G45/1000 -> 22.215 | D41: =+PL推移!D40 -> 28.375 | E41: =+D41-C41 -> 6.16 | F41: =IF(C41<>0,D41/C41,"-") -> 1.2772901 | G41: =+収支計画!K51/1000 -> 0 | H41: =+PL推移!F40 -> 0 | I41: =+H41-G41 -> 0 | J41: =IF(G41<>0,H41/G41,"-") -> - | K41: =+収支計画!O51/1000 -> 0 | L41: =+PL推移!H40 -> 0 | M41: =+L41-K41 -> 0 | N41: =IF(K41<>0,L41/K41,"-") -> - | O41: =+収支計画!S51/1000 -> 5 | P41: =+PL推移!J40 -> 0 | Q41: =+P41-O41 -> -5 | R41: =IF(O41<>0,P41/O41,"-") -> 0 | S41: =+収支計画!U51/1000 -> 0 | T41: =+PL推移!L40 -> 0 | U41: =+T41-S41 -> 0 | V41: =IF(S41<>0,T41/S41,"-") -> - | W41: =+収支計画!W51/1000 -> 0 | X41: =+PL推移!N40 -> 0 | Y41: =+X41-W41 -> 0 | Z41: =IF(W41<>0,X41/W41,"-") -> - | AA41: =+収支計画!Y51/1000 -> 0 | AB41: =+PL推移!P40 -> 0 | AC41: =+AB41-AA41 -> 0 | AD41: =IF(AA41<>0,AB41/AA41,"-") -> - | AE41: =+収支計画!AA51/1000 -> 0 | AF41: =+PL推移!R40 -> 0 | AG41: =+AF41-AE41 -> 0 | AH41: =IF(AE41<>0,AF41/AE41,"-") -> - | AI41: =+収支計画!AC51/1000 -> 0 | AJ41: =+PL推移!T40 -> 0 | AK41: =+AJ41-AI41 -> 0 | AL41: =IF(AI41<>0,AJ41/AI41,"-") -> - | AM41: =+収支計画!AG51/1000 -> 0 | AN41: =+PL推移!V40 -> 0 | AO41: =+AN41-AM41 -> 0 | AP41: =IF(AM41<>0,AN41/AM41,"-") -> - | AQ41: =+収支計画!AG51/1000 -> 0 | AR41: =+PL推移!X40 -> 0 | AS41: =+AR41-AQ41 -> 0 | AT41: =IF(AQ41<>0,AR41/AQ41,"-") -> - | AU41: =+収支計画!AI51/1000 -> 0 | AV41: =+PL推移!Z40 -> 0 | AW41: =+AV41-AU41 -> 0 | AX41: =IF(AU41<>0,AV41/AU41,"-") -> - | AY41: =+C41+G41+K41+O41+S41+W41+AA41+AE41+AI41+AM41+AQ41+AU41 -> 27.215 | AZ41: =+D41+H41+L41+P41+T41+X41+AB41+AF41+AJ41+AN41+AR41+AV41 -> 28.375 | BA41: =+AZ41-AY41 -> 1.16 | BB41: =IF(AY41<>0,AZ41/AY41,"-") -> 1.0426236 | BC41: =+PL推移!N40-収支計画!W51/1000 -> 0 | BD41: =+BC41/(収支計画!W51/1000) -> #DIV/0! | BE41: =+PL推移!P40-収支計画!Y51/1000 -> 0 | BF41: =+BE41/(収支計画!Y51/1000) -> #DIV/0! | BG41: =+PL推移!R40-収支計画!AA51/1000 -> 0 | BH41: =+BG41/(収支計画!AA51/1000) -> #DIV/0! | BI41: =+PL推移!T40-収支計画!AC51/1000 -> 0 | BJ41: =+BI41/(収支計画!AC51/1000) -> #DIV/0! | BK41: =+PL推移!V40-収支計画!AE51/1000 -> 0 | BL41: =+BK41/(収支計画!AE51/1000) -> #DIV/0! | BM41: =+PL推移!X40-収支計画!AG51/1000 -> 0 | BN41: =+BM41/(収支計画!AG51/1000) -> #DIV/0! | BO41: =+PL推移!Z40-収支計画!AI51/1000 -> 0 | BP41: =+BO41/(収支計画!AI51/1000) -> #DIV/0!
B42: 水道光熱費 | C42: =+収支計画!G46/1000 -> 660 | D42: =+PL推移!D41 -> 659.468 | E42: =+D42-C42 -> -0.532 | F42: =IF(C42<>0,D42/C42,"-") -> 0.99919394 | G42: =+収支計画!K52/1000 -> 110 | H42: =+PL推移!F41 -> 0 | I42: =+H42-G42 -> -110 | J42: =IF(G42<>0,H42/G42,"-") -> 0 | K42: =+収支計画!O52/1000 -> 70 | L42: =+PL推移!H41 -> 0 | M42: =+L42-K42 -> -70 | N42: =IF(K42<>0,L42/K42,"-") -> 0 | O42: =+収支計画!S52/1000 -> 70 | P42: =+PL推移!J41 -> 0 | Q42: =+P42-O42 -> -70 | R42: =IF(O42<>0,P42/O42,"-") -> 0 | S42: =+収支計画!U52/1000 -> 0 | T42: =+PL推移!L41 -> 0 | U42: =+T42-S42 -> 0 | V42: =IF(S42<>0,T42/S42,"-") -> - | W42: =+収支計画!W52/1000 -> 0 | X42: =+PL推移!N41 -> 0 | Y42: =+X42-W42 -> 0 | Z42: =IF(W42<>0,X42/W42,"-") -> - | AA42: =+収支計画!Y52/1000 -> 0 | AB42: =+PL推移!P41 -> 0 | AC42: =+AB42-AA42 -> 0 | AD42: =IF(AA42<>0,AB42/AA42,"-") -> - | AE42: =+収支計画!AA52/1000 -> 0 | AF42: =+PL推移!R41 -> 0 | AG42: =+AF42-AE42 -> 0 | AH42: =IF(AE42<>0,AF42/AE42,"-") -> - | AI42: =+収支計画!AC52/1000 -> 0 | AJ42: =+PL推移!T41 -> 0 | AK42: =+AJ42-AI42 -> 0 | AL42: =IF(AI42<>0,AJ42/AI42,"-") -> - | AM42: =+収支計画!AG52/1000 -> 0 | AN42: =+PL推移!V41 -> 0 | AO42: =+AN42-AM42 -> 0 | AP42: =IF(AM42<>0,AN42/AM42,"-") -> - | AQ42: =+収支計画!AG52/1000 -> 0 | AR42: =+PL推移!X41 -> 0 | AS42: =+AR42-AQ42 -> 0 | AT42: =IF(AQ42<>0,AR42/AQ42,"-") -> - | AU42: =+収支計画!AI52/1000 -> 0 | AV42: =+PL推移!Z41 -> 0 | AW42: =+AV42-AU42 -> 0 | AX42: =IF(AU42<>0,AV42/AU42,"-") -> - | AY42: =+C42+G42+K42+O42+S42+W42+AA42+AE42+AI42+AM42+AQ42+AU42 -> 910 | AZ42: =+D42+H42+L42+P42+T42+X42+AB42+AF42+AJ42+AN42+AR42+AV42 -> 659.468 | BA42: =+AZ42-AY42 -> -250.532 | BB42: =IF(AY42<>0,AZ42/AY42,"-") -> 0.72469011 | BC42: =+PL推移!N41-収支計画!W52/1000 -> 0 | BD42: =+BC42/(収支計画!W52/1000) -> #DIV/0! | BE42: =+PL推移!P41-収支計画!Y52/1000 -> 0 | BF42: =+BE42/(収支計画!Y52/1000) -> #DIV/0! | BG42: =+PL推移!R41-収支計画!AA52/1000 -> 0 | BH42: =+BG42/(収支計画!AA52/1000) -> #DIV/0! | BI42: =+PL推移!T41-収支計画!AC52/1000 -> 0 | BJ42: =+BI42/(収支計画!AC52/1000) -> #DIV/0! | BK42: =+PL推移!V41-収支計画!AE52/1000 -> 0 | BL42: =+BK42/(収支計画!AE52/1000) -> #DIV/0! | BM42: =+PL推移!X41-収支計画!AG52/1000 -> 0 | BN42: =+BM42/(収支計画!AG52/1000) -> #DIV/0! | BO42: =+PL推移!Z41-収支計画!AI52/1000 -> 0 | BP42: =+BO42/(収支計画!AI52/1000) -> #DIV/0!
B43: 消耗品費 | C43: =+収支計画!G47/1000 -> 200 | D43: =+PL推移!D42 -> 207.018 | E43: =+D43-C43 -> 7.018 | F43: =IF(C43<>0,D43/C43,"-") -> 1.03509 | G43: =+収支計画!K53/1000 -> 45 | H43: =+PL推移!F42 -> 0 | I43: =+H43-G43 -> -45 | J43: =IF(G43<>0,H43/G43,"-") -> 0 | K43: =+収支計画!O53/1000 -> 45 | L43: =+PL推移!H42 -> 0 | M43: =+L43-K43 -> -45 | N43: =IF(K43<>0,L43/K43,"-") -> 0 | O43: =+収支計画!S53/1000 -> 50 | P43: =+PL推移!J42 -> 0 | Q43: =+P43-O43 -> -50 | R43: =IF(O43<>0,P43/O43,"-") -> 0 | S43: =+収支計画!U53/1000 -> 0 | T43: =+PL推移!L42 -> 0 | U43: =+T43-S43 -> 0 | V43: =IF(S43<>0,T43/S43,"-") -> - | W43: =+収支計画!W53/1000 -> 0 | X43: =+PL推移!N42 -> 0 | Y43: =+X43-W43 -> 0 | Z43: =IF(W43<>0,X43/W43,"-") -> - | AA43: =+収支計画!Y53/1000 -> 0 | AB43: =+PL推移!P42 -> 0 | AC43: =+AB43-AA43 -> 0 | AD43: =IF(AA43<>0,AB43/AA43,"-") -> - | AE43: =+収支計画!AA53/1000 -> 0 | AF43: =+PL推移!R42 -> 0 | AG43: =+AF43-AE43 -> 0 | AH43: =IF(AE43<>0,AF43/AE43,"-") -> - | AI43: =+収支計画!AC53/1000 -> 0 | AJ43: =+PL推移!T42 -> 0 | AK43: =+AJ43-AI43 -> 0 | AL43: =IF(AI43<>0,AJ43/AI43,"-") -> - | AM43: =+収支計画!AG53/1000 -> 0 | AN43: =+PL推移!V42 -> 0 | AO43: =+AN43-AM43 -> 0 | AP43: =IF(AM43<>0,AN43/AM43,"-") -> - | AQ43: =+収支計画!AG53/1000 -> 0 | AR43: =+PL推移!X42 -> 0 | AS43: =+AR43-AQ43 -> 0 | AT43: =IF(AQ43<>0,AR43/AQ43,"-") -> - | AU43: =+収支計画!AI53/1000 -> 0 | AV43: =+PL推移!Z42 -> 0 | AW43: =+AV43-AU43 -> 0 | AX43: =IF(AU43<>0,AV43/AU43,"-") -> - | AY43: =+C43+G43+K43+O43+S43+W43+AA43+AE43+AI43+AM43+AQ43+AU43 -> 340 | AZ43: =+D43+H43+L43+P43+T43+X43+AB43+AF43+AJ43+AN43+AR43+AV43 -> 207.018 | BA43: =+AZ43-AY43 -> -132.982 | BB43: =IF(AY43<>0,AZ43/AY43,"-") -> 0.60887647 | BC43: =+PL推移!N42-収支計画!W53/1000 -> 0 | BD43: =+BC43/(収支計画!W53/1000) -> #DIV/0! | BE43: =+PL推移!P42-収支計画!Y53/1000 -> 0 | BF43: =+BE43/(収支計画!Y53/1000) -> #DIV/0! | BG43: =+PL推移!R42-収支計画!AA53/1000 -> 0 | BH43: =+BG43/(収支計画!AA53/1000) -> #DIV/0! | BI43: =+PL推移!T42-収支計画!AC53/1000 -> 0 | BJ43: =+BI43/(収支計画!AC53/1000) -> #DIV/0! | BK43: =+PL推移!V42-収支計画!AE53/1000 -> 0 | BL43: =+BK43/(収支計画!AE53/1000) -> #DIV/0! | BM43: =+PL推移!X42-収支計画!AG53/1000 -> 0 | BN43: =+BM43/(収支計画!AG53/1000) -> #DIV/0! | BO43: =+PL推移!Z42-収支計画!AI53/1000 -> 0 | BP43: =+BO43/(収支計画!AI53/1000) -> #DIV/0!
B44: 租税公課 | C44: =+収支計画!G48/1000 -> 131 | D44: =+PL推移!D43 -> 124 | E44: =+D44-C44 -> -7 | F44: =IF(C44<>0,D44/C44,"-") -> 0.94656489 | G44: =+収支計画!K54/1000 -> 0 | H44: =+PL推移!F43 -> 0 | I44: =+H44-G44 -> 0 | J44: =IF(G44<>0,H44/G44,"-") -> - | K44: =+収支計画!O54/1000 -> 0 | L44: =+PL推移!H43 -> 0 | M44: =+L44-K44 -> 0 | N44: =IF(K44<>0,L44/K44,"-") -> - | O44: =+収支計画!S54/1000 -> 0 | P44: =+PL推移!J43 -> 0 | Q44: =+P44-O44 -> 0 | R44: =IF(O44<>0,P44/O44,"-") -> - | S44: =+収支計画!U54/1000 -> 0 | T44: =+PL推移!L43 -> 0 | U44: =+T44-S44 -> 0 | V44: =IF(S44<>0,T44/S44,"-") -> - | W44: =+収支計画!W54/1000 -> 0 | X44: =+PL推移!N43 -> 0 | Y44: =+X44-W44 -> 0 | Z44: =IF(W44<>0,X44/W44,"-") -> - | AA44: =+収支計画!Y54/1000 -> 0 | AB44: =+PL推移!P43 -> 0 | AC44: =+AB44-AA44 -> 0 | AD44: =IF(AA44<>0,AB44/AA44,"-") -> - | AE44: =+収支計画!AA54/1000 -> 0 | AF44: =+PL推移!R43 -> 0 | AG44: =+AF44-AE44 -> 0 | AH44: =IF(AE44<>0,AF44/AE44,"-") -> - | AI44: =+収支計画!AC54/1000 -> 0 | AJ44: =+PL推移!T43 -> 0 | AK44: =+AJ44-AI44 -> 0 | AL44: =IF(AI44<>0,AJ44/AI44,"-") -> - | AM44: =+収支計画!AG54/1000 -> 0 | AN44: =+PL推移!V43 -> 0 | AO44: =+AN44-AM44 -> 0 | AP44: =IF(AM44<>0,AN44/AM44,"-") -> - | AQ44: =+収支計画!AG54/1000 -> 0 | AR44: =+PL推移!X43 -> 0 | AS44: =+AR44-AQ44 -> 0 | AT44: =IF(AQ44<>0,AR44/AQ44,"-") -> - | AU44: =+収支計画!AI54/1000 -> 0 | AV44: =+PL推移!Z43 -> 0 | AW44: =+AV44-AU44 -> 0 | AX44: =IF(AU44<>0,AV44/AU44,"-") -> - | AY44: =+C44+G44+K44+O44+S44+W44+AA44+AE44+AI44+AM44+AQ44+AU44 -> 131 | AZ44: =+D44+H44+L44+P44+T44+X44+AB44+AF44+AJ44+AN44+AR44+AV44 -> 124 | BA44: =+AZ44-AY44 -> -7 | BB44: =IF(AY44<>0,AZ44/AY44,"-") -> 0.94656489 | BC44: =+PL推移!N43-収支計画!W54/1000 -> 0 | BD44: =+BC44/(収支計画!W54/1000) -> #DIV/0! | BE44: =+PL推移!P43-収支計画!Y54/1000 -> 0 | BF44: =+BE44/(収支計画!Y54/1000) -> #DIV/0! | BG44: =+PL推移!R43-収支計画!AA54/1000 -> 0 | BH44: =+BG44/(収支計画!AA54/1000) -> #DIV/0! | BI44: =+PL推移!T43-収支計画!AC54/1000 -> 0 | BJ44: =+BI44/(収支計画!AC54/1000) -> #DIV/0! | BK44: =+PL推移!V43-収支計画!AE54/1000 -> 0 | BL44: =+BK44/(収支計画!AE54/1000) -> #DIV/0! | BM44: =+PL推移!X43-収支計画!AG54/1000 -> 0 | BN44: =+BM44/(収支計画!AG54/1000) -> #DIV/0! | BO44: =+PL推移!Z43-収支計画!AI54/1000 -> 0 | BP44: =+BO44/(収支計画!AI54/1000) -> #DIV/0!
B45: 広告宣伝費 | C45: =+収支計画!G49/1000 -> 165 | D45: =+PL推移!D44 -> 124.456 | E45: =+D45-C45 -> -40.544 | F45: =IF(C45<>0,D45/C45,"-") -> 0.75427879 | G45: =+収支計画!K55/1000 -> 3728.185 | H45: =+PL推移!F44 -> 0 | I45: =+H45-G45 -> -3728.185 | J45: =IF(G45<>0,H45/G45,"-") -> 0 | K45: =+収支計画!O55/1000 -> 3894.685 | L45: =+PL推移!H44 -> 0 | M45: =+L45-K45 -> -3894.685 | N45: =IF(K45<>0,L45/K45,"-") -> 0 | O45: =+収支計画!S55/1000 -> 4009.08 | P45: =+PL推移!J44 -> 0 | Q45: =+P45-O45 -> -4009.08 | R45: =IF(O45<>0,P45/O45,"-") -> 0 | S45: =+収支計画!U55/1000 -> 0 | T45: =+PL推移!L44 -> 0 | U45: =+T45-S45 -> 0 | V45: =IF(S45<>0,T45/S45,"-") -> - | W45: =+収支計画!W55/1000 -> 0 | X45: =+PL推移!N44 -> 0 | Y45: =+X45-W45 -> 0 | Z45: =IF(W45<>0,X45/W45,"-") -> - | AA45: =+収支計画!Y55/1000 -> 0 | AB45: =+PL推移!P44 -> 0 | AC45: =+AB45-AA45 -> 0 | AD45: =IF(AA45<>0,AB45/AA45,"-") -> - | AE45: =+収支計画!AA55/1000 -> 0 | AF45: =+PL推移!R44 -> 0 | AG45: =+AF45-AE45 -> 0 | AH45: =IF(AE45<>0,AF45/AE45,"-") -> - | AI45: =+収支計画!AC55/1000 -> 0 | AJ45: =+PL推移!T44 -> 0 | AK45: =+AJ45-AI45 -> 0 | AL45: =IF(AI45<>0,AJ45/AI45,"-") -> - | AM45: =+収支計画!AG55/1000 -> 0 | AN45: =+PL推移!V44 -> 0 | AO45: =+AN45-AM45 -> 0 | AP45: =IF(AM45<>0,AN45/AM45,"-") -> - | AQ45: =+収支計画!AG55/1000 -> 0 | AR45: =+PL推移!X44 -> 0 | AS45: =+AR45-AQ45 -> 0 | AT45: =IF(AQ45<>0,AR45/AQ45,"-") -> - | AU45: =+収支計画!AI55/1000 -> 0 | AV45: =+PL推移!Z44 -> 0 | AW45: =+AV45-AU45 -> 0 | AX45: =IF(AU45<>0,AV45/AU45,"-") -> - | AY45: =+C45+G45+K45+O45+S45+W45+AA45+AE45+AI45+AM45+AQ45+AU45 -> 11796.95 | AZ45: =+D45+H45+L45+P45+T45+X45+AB45+AF45+AJ45+AN45+AR45+AV45 -> 124.456 | BA45: =+AZ45-AY45 -> -11672.494 | BB45: =IF(AY45<>0,AZ45/AY45,"-") -> 0.010549846 | BC45: =+PL推移!N44-収支計画!W55/1000 -> 0 | BD45: =+BC45/(収支計画!W55/1000) -> #DIV/0! | BE45: =+PL推移!P44-収支計画!Y55/1000 -> 0 | BF45: =+BE45/(収支計画!Y55/1000) -> #DIV/0! | BG45: =+PL推移!R44-収支計画!AA55/1000 -> 0 | BH45: =+BG45/(収支計画!AA55/1000) -> #DIV/0! | BI45: =+PL推移!T44-収支計画!AC55/1000 -> 0 | BJ45: =+BI45/(収支計画!AC55/1000) -> #DIV/0! | BK45: =+PL推移!V44-収支計画!AE55/1000 -> 0 | BL45: =+BK45/(収支計画!AE55/1000) -> #DIV/0! | BM45: =+PL推移!X44-収支計画!AG55/1000 -> 0 | BN45: =+BM45/(収支計画!AG55/1000) -> #DIV/0! | BO45: =+PL推移!Z44-収支計画!AI55/1000 -> 0 | BP45: =+BO45/(収支計画!AI55/1000) -> #DIV/0!
B46: 支払手数料 | C46: =+収支計画!G50/1000 -> 281.5 | D46: =+PL推移!D45 -> 208.468 | E46: =+D46-C46 -> -73.032 | F46: =IF(C46<>0,D46/C46,"-") -> 0.74056128 | G46: =+収支計画!K56/1000 -> 6478.93 | H46: =+PL推移!F45 -> 0 | I46: =+H46-G46 -> -6478.93 | J46: =IF(G46<>0,H46/G46,"-") -> 0 | K46: =+収支計画!O56/1000 -> 6870.43 | L46: =+PL推移!H45 -> 0 | M46: =+L46-K46 -> -6870.43 | N46: =IF(K46<>0,L46/K46,"-") -> 0 | O46: =+収支計画!S56/1000 -> 6756.399 | P46: =+PL推移!J45 -> 0 | Q46: =+P46-O46 -> -6756.399 | R46: =IF(O46<>0,P46/O46,"-") -> 0 | S46: =+収支計画!U56/1000 -> 0 | T46: =+PL推移!L45 -> 0 | U46: =+T46-S46 -> 0 | V46: =IF(S46<>0,T46/S46,"-") -> - | W46: =+収支計画!W56/1000 -> 0 | X46: =+PL推移!N45 -> 0 | Y46: =+X46-W46 -> 0 | Z46: =IF(W46<>0,X46/W46,"-") -> - | AA46: =+収支計画!Y56/1000 -> 0 | AB46: =+PL推移!P45 -> 0 | AC46: =+AB46-AA46 -> 0 | AD46: =IF(AA46<>0,AB46/AA46,"-") -> - | AE46: =+収支計画!AA56/1000 -> 0 | AF46: =+PL推移!R45 -> 0 | AG46: =+AF46-AE46 -> 0 | AH46: =IF(AE46<>0,AF46/AE46,"-") -> - | AI46: =+収支計画!AC56/1000 -> 0 | AJ46: =+PL推移!T45 -> 0 | AK46: =+AJ46-AI46 -> 0 | AL46: =IF(AI46<>0,AJ46/AI46,"-") -> - | AM46: =+収支計画!AG56/1000 -> 0 | AN46: =+PL推移!V45 -> 0 | AO46: =+AN46-AM46 -> 0 | AP46: =IF(AM46<>0,AN46/AM46,"-") -> - | AQ46: =+収支計画!AG56/1000 -> 0 | AR46: =+PL推移!X45 -> 0 | AS46: =+AR46-AQ46 -> 0 | AT46: =IF(AQ46<>0,AR46/AQ46,"-") -> - | AU46: =+収支計画!AI56/1000 -> 0 | AV46: =+PL推移!Z45 -> 0 | AW46: =+AV46-AU46 -> 0 | AX46: =IF(AU46<>0,AV46/AU46,"-") -> - | AY46: =+C46+G46+K46+O46+S46+W46+AA46+AE46+AI46+AM46+AQ46+AU46 -> 20387.259 | AZ46: =+D46+H46+L46+P46+T46+X46+AB46+AF46+AJ46+AN46+AR46+AV46 -> 208.468 | BA46: =+AZ46-AY46 -> -20178.791 | BB46: =IF(AY46<>0,AZ46/AY46,"-") -> 0.010225406 | BC46: =+PL推移!N45-収支計画!W56/1000 -> 0 | BD46: =+BC46/(収支計画!W56/1000) -> #DIV/0! | BE46: =+PL推移!P45-収支計画!Y56/1000 -> 0 | BF46: =+BE46/(収支計画!Y56/1000) -> #DIV/0! | BG46: =+PL推移!R45-収支計画!AA56/1000 -> 0 | BH46: =+BG46/(収支計画!AA56/1000) -> #DIV/0! | BI46: =+PL推移!T45-収支計画!AC56/1000 -> 0 | BJ46: =+BI46/(収支計画!AC56/1000) -> #DIV/0! | BK46: =+PL推移!V45-収支計画!AE56/1000 -> 0 | BL46: =+BK46/(収支計画!AE56/1000) -> #DIV/0! | BM46: =+PL推移!X45-収支計画!AG56/1000 -> 0 | BN46: =+BM46/(収支計画!AG56/1000) -> #DIV/0! | BO46: =+PL推移!Z45-収支計画!AI56/1000 -> 0 | BP46: =+BO46/(収支計画!AI56/1000) -> #DIV/0!
B47: 新聞図書費 | C47: =+収支計画!G51/1000 -> 0 | D47: =+PL推移!D46 -> 0 | E47: =+D47-C47 -> 0 | F47: =IF(C47<>0,D47/C47,"-") -> - | G47: =+収支計画!K57/1000 -> 638.57 | H47: =+PL推移!F46 -> 0 | I47: =+H47-G47 -> -638.57 | J47: =IF(G47<>0,H47/G47,"-") -> 0 | K47: =+収支計画!O57/1000 -> 1372.07 | L47: =+PL推移!H46 -> 0 | M47: =+L47-K47 -> -1372.07 | N47: =IF(K47<>0,L47/K47,"-") -> 0 | O47: =+収支計画!S57/1000 -> -6756.399 | P47: =+PL推移!J46 -> 0 | Q47: =+P47-O47 -> 6756.399 | R47: =IF(O47<>0,P47/O47,"-") -> 0 | S47: =+収支計画!U57/1000 -> 0 | T47: =+PL推移!L46 -> 0 | U47: =+T47-S47 -> 0 | V47: =IF(S47<>0,T47/S47,"-") -> - | W47: =+収支計画!W57/1000 -> 0 | X47: =+PL推移!N46 -> 0 | Y47: =+X47-W47 -> 0 | Z47: =IF(W47<>0,X47/W47,"-") -> - | AA47: =+収支計画!Y57/1000 -> 0 | AB47: =+PL推移!P46 -> 0 | AC47: =+AB47-AA47 -> 0 | AD47: =IF(AA47<>0,AB47/AA47,"-") -> - | AE47: =+収支計画!AA57/1000 -> 0 | AF47: =+PL推移!R46 -> 0 | AG47: =+AF47-AE47 -> 0 | AH47: =IF(AE47<>0,AF47/AE47,"-") -> - | AI47: =+収支計画!AC57/1000 -> 0 | AJ47: =+PL推移!T46 -> 0 | AK47: =+AJ47-AI47 -> 0 | AL47: =IF(AI47<>0,AJ47/AI47,"-") -> - | AM47: =+収支計画!AG57/1000 -> 0 | AN47: =+PL推移!V46 -> 0 | AO47: =+AN47-AM47 -> 0 | AP47: =IF(AM47<>0,AN47/AM47,"-") -> - | AQ47: =+収支計画!AG57/1000 -> 0 | AR47: =+PL推移!X46 -> 0 | AS47: =+AR47-AQ47 -> 0 | AT47: =IF(AQ47<>0,AR47/AQ47,"-") -> - | AU47: =+収支計画!AI57/1000 -> 0 | AV47: =+PL推移!Z46 -> 0 | AW47: =+AV47-AU47 -> 0 | AX47: =IF(AU47<>0,AV47/AU47,"-") -> - | AY47: =+C47+G47+K47+O47+S47+W47+AA47+AE47+AI47+AM47+AQ47+AU47 -> -4745.759 | AZ47: =+D47+H47+L47+P47+T47+X47+AB47+AF47+AJ47+AN47+AR47+AV47 -> 0 | BA47: =+AZ47-AY47 -> 4745.759 | BB47: =IF(AY47<>0,AZ47/AY47,"-") -> 0 | BC47: =+PL推移!N46-収支計画!W57/1000 -> 0 | BD47: =+BC47/(収支計画!W57/1000) -> #DIV/0! | BE47: =+PL推移!P46-収支計画!Y57/1000 -> 0 | BF47: =+BE47/(収支計画!Y57/1000) -> #DIV/0! | BG47: =+PL推移!R46-収支計画!AA57/1000 -> 0 | BH47: =+BG47/(収支計画!AA57/1000) -> #DIV/0! | BI47: =+PL推移!T46-収支計画!AC57/1000 -> 0 | BJ47: =+BI47/(収支計画!AC57/1000) -> #DIV/0! | BK47: =+PL推移!V46-収支計画!AE57/1000 -> 0 | BL47: =+BK47/(収支計画!AE57/1000) -> #DIV/0! | BM47: =+PL推移!X46-収支計画!AG57/1000 -> 0 | BN47: =+BM47/(収支計画!AG57/1000) -> #DIV/0! | BO47: =+PL推移!Z46-収支計画!AI57/1000 -> 0 | BP47: =+BO47/(収支計画!AI57/1000) -> #DIV/0!
... B49: 雑費 | C49: =+収支計画!G53/1000 -> 50 | D49: =+PL推移!D48 -> 74.929 | E49: =+D49-C49 -> 24.929 | F49: =IF(C49<>0,D49/C49,"-") -> 1.49858 | G49: =+収支計画!K59/1000 -> 150.76 | H49: =+PL推移!F48 -> 0 | I49: =+H49-G49 -> -150.76 | J49: =IF(G49<>0,H49/G49,"-") -> 0 | K49: =+収支計画!O59/1000 -> 150 | L49: =+PL推移!H48 -> 0 | M49: =+L49-K49 -> -150 | N49: =IF(K49<>0,L49/K49,"-") -> 0 | O49: =+収支計画!S59/1000 -> 120 | P49: =+PL推移!J48 -> 0 | Q49: =+P49-O49 -> -120 | R49: =IF(O49<>0,P49/O49,"-") -> 0 | S49: =+収支計画!U59/1000 -> 0 | T49: =+PL推移!L48 -> 0 | U49: =+T49-S49 -> 0 | V49: =IF(S49<>0,T49/S49,"-") -> - | W49: =+収支計画!W59/1000 -> 0 | X49: =+PL推移!N48 -> 0 | Y49: =+X49-W49 -> 0 | Z49: =IF(W49<>0,X49/W49,"-") -> - | AA49: =+収支計画!Y59/1000 -> 0 | AB49: =+PL推移!P48 -> 0 | AC49: =+AB49-AA49 -> 0 | AD49: =IF(AA49<>0,AB49/AA49,"-") -> - | AE49: =+収支計画!AA59/1000 -> 0 | AF49: =+PL推移!R48 -> 0 | AG49: =+AF49-AE49 -> 0 | AH49: =IF(AE49<>0,AF49/AE49,"-") -> - | AI49: =+収支計画!AC59/1000 -> 0 | AJ49: =+PL推移!T48 -> 0 | AK49: =+AJ49-AI49 -> 0 | AL49: =IF(AI49<>0,AJ49/AI49,"-") -> - | AM49: =+収支計画!AG59/1000 -> 0 | AN49: =+PL推移!V48 -> 0 | AO49: =+AN49-AM49 -> 0 | AP49: =IF(AM49<>0,AN49/AM49,"-") -> - | AQ49: =+収支計画!AG59/1000 -> 0 | AR49: =+PL推移!X48 -> 0 | AS49: =+AR49-AQ49 -> 0 | AT49: =IF(AQ49<>0,AR49/AQ49,"-") -> - | AU49: =+収支計画!AI59/1000 -> 0 | AV49: =+PL推移!Z48 -> 0 | AW49: =+AV49-AU49 -> 0 | AX49: =IF(AU49<>0,AV49/AU49,"-") -> - | AY49: =+C49+G49+K49+O49+S49+W49+AA49+AE49+AI49+AM49+AQ49+AU49 -> 470.76 | AZ49: =+D49+H49+L49+P49+T49+X49+AB49+AF49+AJ49+AN49+AR49+AV49 -> 74.929 | BA49: =+AZ49-AY49 -> -395.831 | BB49: =IF(AY49<>0,AZ49/AY49,"-") -> 0.15916603 | BC49: =+PL推移!N48-収支計画!W59/1000 -> 0 | BD49: =+BC49/(収支計画!W59/1000) -> #DIV/0! | BE49: =+PL推移!P48-収支計画!Y59/1000 -> 0 | BF49: =+BE49/(収支計画!Y59/1000) -> #DIV/0! | BG49: =+PL推移!R48-収支計画!AA59/1000 -> 0 | BH49: =+BG49/(収支計画!AA59/1000) -> #DIV/0! | BI49: =+PL推移!T48-収支計画!AC59/1000 -> 0 | BJ49: =+BI49/(収支計画!AC59/1000) -> #DIV/0! | BK49: =+PL推移!V48-収支計画!AE59/1000 -> 0 | BL49: =+BK49/(収支計画!AE59/1000) -> #DIV/0! | BM49: =+PL推移!X48-収支計画!AG59/1000 -> 0 | BN49: =+BM49/(収支計画!AG59/1000) -> #DIV/0! | BO49: =+PL推移!Z48-収支計画!AI59/1000 -> 0 | BP49: =+BO49/(収支計画!AI59/1000) -> #DIV/0!
F50: =IF(C50<>0,D50/C50,"-") -> - | H50: =+PL推移!F49 -> 0 | J50: =IF(G50<>0,H50/G50,"-") -> - | L50: =+PL推移!H49 -> 0 | N50: =IF(K50<>0,L50/K50,"-") -> - | P50: =+PL推移!J49 -> 0 | R50: =IF(O50<>0,P50/O50,"-") -> - | T50: =+PL推移!N49 -> 0 | V50: =IF(S50<>0,T50/S50,"-") -> - | X50: =+PL推移!R49 -> 0 | Z50: =IF(W50<>0,X50/W50,"-") -> - | AB50: =+PL推移!V49 -> 0 | AD50: =IF(AA50<>0,AB50/AA50,"-") -> - | AF50: =+PL推移!Z49 -> 0 | AH50: =IF(AE50<>0,AF50/AE50,"-") -> - | AJ50: =+PL推移!AD49 -> 0 | AL50: =IF(AI50<>0,AJ50/AI50,"-") -> - | AN50: =+PL推移!AH49 -> 0 | AO50: =+AN50-AM50 -> 0 | AP50: =IF(AM50<>0,AN50/AM50,"-") -> - | AR50: =+PL推移!AL49 -> 0 | AS50: =+AR50-AQ50 -> 0 | AT50: =IF(AQ50<>0,AR50/AQ50,"-") -> - | AV50: =+PL推移!AP49 -> 0 | AW50: =+AV50-AU50 -> 0 | AX50: =IF(AU50<>0,AV50/AU50,"-") -> - | AY50: =+C50+G50+K50+O50+S50+W50+AA50+AE50+AI50+AM50+AQ50+AU50 -> 0 | AZ50: =+D50+H50+L50+P50+T50+X50+AB50+AF50+AJ50+AN50+AR50+AV50 -> 0 | BA50: =+AZ50-AY50 -> 0 | BB50: =IF(AY50<>0,AZ50/AY50,"-") -> -
A51: 営業損益 | C51: =+C23-C29 -> 489.601 | D51: =+D23-D29 -> 414.148 | E51: =+E23-E29 -> -75.462 | F51: =IF(C51<>0,D51/C51,"-") -> 0.8458888 | G51: =+G23-G29 -> -7493.08 | H51: =+PL推移!F50 -> 0 | I51: =+I23-I29 -> 7493.08 | J51: =IF(G51<>0,H51/G51,"-") -> 0 | K51: =+K23-K29 -> -7800.32 | L51: =+PL推移!H50 -> 0 | M51: =+M23-M29 -> 7800.32 | N51: =IF(K51<>0,L51/K51,"-") -> 0 | O51: =+O23-O29 -> -7969.11 | P51: =+PL推移!J50 -> 0 | Q51: =+Q23-Q29 -> 7969.11 | R51: =IF(O51<>0,P51/O51,"-") -> 0 | S51: =+S23-S29 -> 0 | T51: =+PL推移!L50 -> 0 | U51: =+U23-U29 -> 0 | V51: =IF(S51<>0,T51/S51,"-") -> - | W51: =+W23-W29 -> 0 | X51: =+PL推移!N50 -> 0 | Y51: =+Y23-Y29 -> 0 | Z51: =IF(W51<>0,X51/W51,"-") -> - | AA51: =+AA23-AA29 -> 0 | AB51: =+AB23-AB29 -> 0 | AC51: =+AC23-AC29 -> 0 | AD51: =IF(AA51<>0,AB51/AA51,"-") -> - | AE51: =+AE23-AE29 -> 0 | AF51: =+AF23-AF29 -> 0 | AG51: =+AG23-AG29 -> -1900 | AH51: =IF(AE51<>0,AF51/AE51,"-") -> - | AI51: =+AI23-AI29 -> 0 | AJ51: =+AJ23-AJ29 -> 350 | AK51: =+AK23-AK29 -> -2266 | AL51: =IF(AI51<>0,AJ51/AI51,"-") -> - | AM51: =+AM23-AM29 -> 0 | AN51: =+AN23-AN29 -> 8454 | AO51: =+AN51-AM51 -> 8454 | AP51: =IF(AM51<>0,AN51/AM51,"-") -> - | AQ51: =+AQ23-AQ29 -> 0 | AR51: =+AR23-AR29 -> 9017 | AS51: =+AR51-AQ51 -> 9017 | AT51: =IF(AQ51<>0,AR51/AQ51,"-") -> - | AU51: =+AU23-AU29 -> 0 | AV51: =+AV23-AV29 -> 8610 | AW51: =+AV51-AU51 -> 8610 | AX51: =IF(AU51<>0,AV51/AU51,"-") -> - | AY51: =+C51+G51+K51+O51+S51+W51+AA51+AE51+AI51+AM51+AQ51+AU51 -> -22772.909 | AZ51: =+D51+H51+L51+P51+T51+X51+AB51+AF51+AJ51+AN51+AR51+AV51 -> 26845.148 | BA51: =+AZ51-AY51 -> 49618.057 | BB51: =IF(AY51<>0,AZ51/AY51,"-") -> -1.1788194 | BC51: =+PL推移!N50-(収支計画!W63/1000) -> 0 | BD51: =+BC51/(収支計画!W63/1000) -> #DIV/0! | BE51: =+PL推移!P50-(収支計画!Y63/1000) -> 0 | BF51: =+BE51/(収支計画!Y63/1000) -> #DIV/0! | BG51: =+PL推移!R50-(収支計画!AA63/1000) -> 0 | BH51: =+BG51/(収支計画!AA63/1000) -> #DIV/0! | BI51: =+PL推移!T50-(収支計画!AC63/1000) -> 350 | BJ51: =+BI51/(収支計画!AC63/1000) -> #DIV/0! | BK51: =+PL推移!V50-(収支計画!AE63/1000) -> 8454 | BL51: =+BK51/(収支計画!AE63/1000) -> #DIV/0! | BM51: =+PL推移!X50-(収支計画!AG63/1000) -> 9017 | BN51: =+BM51/(収支計画!AG63/1000) -> #DIV/0! | BO51: =+PL推移!Z50-(収支計画!AI63/1000) -> 8610 | BP51: =+BO51/(収支計画!AI63/1000) -> #DIV/0!
B52: 期中累計 | C52: =+C51 -> 489.601 | D52: =+D51 -> 414.148 | E52: =+E51 -> -75.462 | F52: =IF(C52<>0,D52/C52,"-") -> 0.8458888 | G52: =+C52+G51 -> -7003.479 | H52: =+D52+H51 -> 414.148 | I52: =+I51 -> 7493.08 | J52: =IF(G52<>0,H52/G52,"-") -> -0.05913461 | K52: =+G52+K51 -> -14803.799 | L52: =+H52+L51 -> 414.148 | M52: =+M51 -> 7800.32 | N52: =IF(K52<>0,L52/K52,"-") -> -0.027975792 | O52: =+K52+O51 -> -22772.909 | P52: =+L52+P51 -> 414.148 | Q52: =+Q51 -> 7969.11 | R52: =IF(O52<>0,P52/O52,"-") -> -0.018185995 | S52: =+O52+S51 -> -22772.909 | T52: =+P52+T51 -> 414.148 | U52: =+U51 -> 0 | V52: =IF(S52<>0,T52/S52,"-") -> -0.018185995 | W52: =+S52+W51 -> -22772.909 | X52: =+T52+X51 -> 414.148 | Y52: =+X52-W52 -> 23187.057 | Z52: =IF(W52<>0,X52/W52,"-") -> -0.018185995 | AA52: =+W52+AA51 -> -22772.909 | AB52: =+X52+AB51 -> 414.148 | AC52: =+AB52-AA52 -> 23187.057 | AD52: =IF(AA52<>0,AB52/AA52,"-") -> -0.018185995 | AE52: =+AA52+AE51 -> -22772.909 | AF52: =+AB52+AF51 -> 414.148 | AG52: =+AF52-AE52 -> 23187.057 | AH52: =IF(AE52<>0,AF52/AE52,"-") -> -0.018185995 | AI52: =+AE52+AI51 -> -22772.909 | AJ52: =+AF52+AJ51 -> 764.148 | AK52: =+AJ52-AI52 -> 23537.057 | AL52: =IF(AI52<>0,AJ52/AI52,"-") -> -0.033555133 | AM52: =+AI52+AM51 -> -22772.909 | AN52: =+AJ52+AN51 -> 9218.148 | AO52: =+AN52-AM52 -> 31991.057 | AP52: =IF(AM52<>0,AN52/AM52,"-") -> -0.4047857 | AQ52: =+AM52+AQ51 -> -22772.909 | AR52: =+AN52+AR51 -> 18235.148 | AS52: =+AR52-AQ52 -> 41008.057 | AT52: =IF(AQ52<>0,AR52/AQ52,"-") -> -0.80073863 | AU52: =+AQ52+AU51 -> -22772.909 | AV52: =+AR52+AV51 -> 26845.148 | AW52: =+AV52-AU52 -> 49618.057 | AX52: =IF(AU52<>0,AV52/AU52,"-") -> -1.1788194 | BB52: =IF(AY52<>0,AZ52/AY52,"-") -> - | BC52: =+PL推移!N51-収支計画!W64/1000 -> 14166.946 | BD52: =+BC52/(収支計画!W64/1000) -> -1.0301137 | BE52: =+PL推移!P51-収支計画!Y64/1000 -> 14166.946 | BF52: =+BE52/(収支計画!Y64/1000) -> -1.0301137 | BG52: =+PL推移!R51-収支計画!AA64/1000 -> 414.148 | BH52: =+BG52/(収支計画!AA64/1000) -> #DIV/0! | BI52: =+PL推移!T51-収支計画!AC64/1000 -> 764.148 | BJ52: =+BI52/(収支計画!AC64/1000) -> #DIV/0! | BK52: =+PL推移!V51-収支計画!AE64/1000 -> 9218.148 | BL52: =+BK52/(収支計画!AE64/1000) -> #DIV/0! | BM52: =+PL推移!X51-収支計画!AG64/1000 -> 18235.148 | BN52: =+BM52/(収支計画!AG64/1000) -> #DIV/0! | BO52: =+PL推移!Z51-収支計画!AI64/1000 -> 26845.148 | BP52: =+BO52/(収支計画!AI64/1000) -> #DIV/0!
A53: 営業外収益 | C53: =+収支計画!G58/1000 -> 0 | D53: =+PL推移!D52 -> 0 | E53: =+D53-C53 -> 0 | F53: =IF(C53<>0,D53/C53,"-") -> - | G53: =+収支計画!K65/1000 -> 0 | H53: =+PL推移!F52 -> 0 | I53: =+H53-G53 -> 0 | J53: =IF(G53<>0,H53/G53,"-") -> - | K53: =+収支計画!O65/1000 -> 0 | L53: =+PL推移!H52 -> 0 | M53: =+L53-K53 -> 0 | N53: =IF(K53<>0,L53/K53,"-") -> - | O53: =+収支計画!S65/1000 -> 0 | P53: =+PL推移!J52 -> 0 | Q53: =+P53-O53 -> 0 | R53: =IF(O53<>0,P53/O53,"-") -> - | S53: =+収支計画!W65/1000 -> 0 | T53: =+PL推移!L52 -> 0 | U53: =+T53-S53 -> 0 | V53: =IF(S53<>0,T53/S53,"-") -> - | W53: =+収支計画!AA65/1000 -> 0 | X53: =+PL推移!N52 -> 0 | Y53: =+X53-W53 -> 0 | Z53: =IF(W53<>0,X53/W53,"-") -> - | AA53: =+収支計画!AE65/1000 -> 0 | AB53: =+PL推移!P52 -> 0 | AC53: =+AB53-AA53 -> 0 | AD53: =IF(AA53<>0,AB53/AA53,"-") -> - | AE53: =+収支計画!AI65/1000 -> 0 | AF53: =+PL推移!R52 -> 0 | AG53: =+AF53-AE53 -> 0 | AH53: =IF(AE53<>0,AF53/AE53,"-") -> - | AI53: =+収支計画!AM65/1000 -> 0 | AJ53: =+PL推移!T52 -> 0 | AK53: =+AJ53-AI53 -> 0 | AL53: =IF(AI53<>0,AJ53/AI53,"-") -> - | AM53: =+収支計画!AQ65/1000 -> 0 | AN53: =+PL推移!V52 -> 0 | AO53: =+AN53-AM53 -> 0 | AP53: =IF(AM53<>0,AN53/AM53,"-") -> - | AQ53: =+収支計画!AG65/1000 -> 0 | AR53: =+PL推移!X52 -> 0 | AS53: =+AR53-AQ53 -> 0 | AT53: =IF(AQ53<>0,AR53/AQ53,"-") -> - | AU53: =+収支計画!AI65/1000 -> 0 | AV53: =+PL推移!Z52 -> 0 | AW53: =+AV53-AU53 -> 0 | AX53: =IF(AU53<>0,AV53/AU53,"-") -> - | AY53: =+C53+G53+K53+O53+S53+W53+AA53+AE53+AI53+AM53+AQ53+AU53 -> 0 | AZ53: =+D53+H53+L53+P53+T53+X53+AB53+AF53+AJ53+AN53+AR53+AV53 -> 0 | BA53: =+AZ53-AY53 -> 0 | BB53: =IF(AY53<>0,AZ53/AY53,"-") -> - | BC53: =+PL推移!N52-収支計画!W65/1000 -> 0 | BD53: =+BC53/(収支計画!W65/1000) -> #DIV/0! | BE53: =+PL推移!P52-収支計画!Y65/1000 -> 0 | BF53: =+BE53/(収支計画!Y65/1000) -> #DIV/0! | BG53: =+PL推移!R52-収支計画!AA65/1000 -> 0 | BH53: =+BG53/(収支計画!AA65/1000) -> #DIV/0! | BI53: =+PL推移!T52-収支計画!AC65/1000 -> 0 | BJ53: =+BI53/(収支計画!AC65/1000) -> #DIV/0! | BK53: =+PL推移!V52-収支計画!AE65/1000 -> 0 | BL53: =+BK53/(収支計画!AE65/1000) -> #DIV/0! | BM53: =+PL推移!X52-収支計画!AG65/1000 -> 0 | BN53: =+BM53/(収支計画!AG65/1000) -> #DIV/0! | BO53: =+PL推移!Z52-収支計画!AI65/1000 -> 0 | BP53: =+BO53/(収支計画!AI65/1000) -> #DIV/0!
A54: 営業外費用 | C54: =+収支計画!G59/1000 -> 120 | D54: =+PL推移!D53 -> 146.486 | E54: =+D54-C54 -> 26.486 | F54: =IF(C54<>0,D54/C54,"-") -> 1.2207167 | G54: =+収支計画!K66/1000 -> 4883.245 | H54: =+PL推移!F53 -> 0 | I54: =+H54-G54 -> -4883.245 | J54: =IF(G54<>0,H54/G54,"-") -> 0 | K54: =+収支計画!O66/1000 -> 5483.245 | L54: =+PL推移!H53 -> 0 | M54: =+L54-K54 -> -5483.245 | N54: =IF(K54<>0,L54/K54,"-") -> 0 | O54: =+収支計画!S66/1000 -> 2747.319 | P54: =+PL推移!J53 -> 0 | Q54: =+P54-O54 -> -2747.319 | R54: =IF(O54<>0,P54/O54,"-") -> 0 | S54: =+収支計画!U66/1000 -> 0 | T54: =+PL推移!L53 -> 0 | U54: =+T54-S54 -> 0 | V54: =IF(S54<>0,T54/S54,"-") -> - | W54: =+収支計画!Y66/1000 -> 0 | X54: =+PL推移!N53 -> 0 | Y54: =+X54-W54 -> 0 | Z54: =IF(W54<>0,X54/W54,"-") -> - | AA54: =+収支計画!Y66/1000 -> 0 | AB54: =+PL推移!P53 -> 0 | AC54: =+AB54-AA54 -> 0 | AD54: =IF(AA54<>0,AB54/AA54,"-") -> - | AE54: =+収支計画!AA66/1000 -> 0 | AF54: =+PL推移!R53 -> 0 | AG54: =+AF54-AE54 -> 0 | AH54: =IF(AE54<>0,AF54/AE54,"-") -> - | AI54: =+収支計画!AE66/1000 -> 0 | AJ54: =+PL推移!T53 -> 0 | AK54: =+AJ54-AI54 -> 0 | AL54: =IF(AI54<>0,AJ54/AI54,"-") -> - | AM54: =+収支計画!AI66/1000 -> 0 | AN54: =+PL推移!V53 -> 0 | AO54: =+AN54-AM54 -> 0 | AP54: =IF(AM54<>0,AN54/AM54,"-") -> - | AQ54: =+収支計画!AG66/1000 -> 0 | AR54: =+PL推移!X53 -> 0 | AS54: =+AR54-AQ54 -> 0 | AT54: =IF(AQ54<>0,AR54/AQ54,"-") -> - | AU54: =+収支計画!AI66/1000 -> 0 | AV54: =+PL推移!Z53 -> 0 | AW54: =+AV54-AU54 -> 0 | AX54: =IF(AU54<>0,AV54/AU54,"-") -> - | AY54: =+C54+G54+K54+O54+S54+W54+AA54+AE54+AI54+AM54+AQ54+AU54 -> 13233.809 | AZ54: =+D54+H54+L54+P54+T54+X54+AB54+AF54+AJ54+AN54+AR54+AV54 -> 146.486 | BA54: =+AZ54-AY54 -> -13087.323 | BB54: =IF(AY54<>0,AZ54/AY54,"-") -> 0.011069073 | BC54: =+PL推移!N53-収支計画!W66/1000 -> 0 | BD54: =+BC54/(収支計画!W66/1000) -> #DIV/0! | BE54: =+PL推移!P53-収支計画!Y66/1000 -> 0 | BF54: =+BE54/(収支計画!Y66/1000) -> #DIV/0! | BG54: =+PL推移!R53-収支計画!AA66/1000 -> 0 | BH54: =+BG54/(収支計画!AA66/1000) -> #DIV/0! | BI54: =+PL推移!T53-収支計画!AC66/1000 -> 0 | BJ54: =+BI54/(収支計画!AC66/1000) -> #DIV/0! | BK54: =+PL推移!V53-収支計画!AE66/1000 -> 0 | BL54: =+BK54/(収支計画!AE66/1000) -> #DIV/0! | BM54: =+PL推移!X53-収支計画!AG66/1000 -> 0 | BN54: =+BM54/(収支計画!AG66/1000) -> #DIV/0! | BO54: =+PL推移!Z53-収支計画!AI66/1000 -> 0 | BP54: =+BO54/(収支計画!AI66/1000) -> #DIV/0!
A55: 経常損益 | C55: =+C51+C53-C54 -> 369.601 | D55: =+D51+D53-D54 -> 267.662 | E55: =+E51+E53-E54 -> -101.948 | F55: =IF(C55<>0,D55/C55,"-") -> 0.72419176 | G55: =+G51+G53-G54 -> -12376.325 | H55: =+PL推移!F54 -> 0 | I55: =+I51+I53-I54 -> 12376.325 | J55: =IF(G55<>0,H55/G55,"-") -> 0 | K55: =+K51+K53-K54 -> -13283.565 | L55: =+PL推移!H54 -> 0 | M55: =+M51+M53-M54 -> 13283.565 | N55: =IF(K55<>0,L55/K55,"-") -> 0 | O55: =+O51+O53-O54 -> -10716.429 | P55: =+PL推移!J54 -> 0 | Q55: =+Q51+Q53-Q54 -> 10716.429 | R55: =IF(O55<>0,P55/O55,"-") -> 0 | S55: =+S51+S53-S54 -> 0 | T55: =+PL推移!L54 -> 0 | U55: =+U51+U53-U54 -> 0 | V55: =IF(S55<>0,T55/S55,"-") -> - | W55: =+W51+W53-W54 -> 0 | X55: =+PL推移!N54 -> 0 | Y55: =+Y51+Y53-Y54 -> 0 | Z55: =IF(W55<>0,X55/W55,"-") -> - | AA55: =+AA51+AA53-AA54 -> 0 | AB55: =+AB51+AB53-AB54 -> 0 | AC55: =+AC51+AC53-AC54 -> 0 | AD55: =IF(AA55<>0,AB55/AA55,"-") -> - | AE55: =+AE51+AE53-AE54 -> 0 | AF55: =+AF51+AF53-AF54 -> 0 | AG55: =+AG51+AG53-AG54 -> -1900 | AH55: =IF(AE55<>0,AF55/AE55,"-") -> - | AI55: =+AI51+AI53-AI54 -> 0 | AJ55: =+AJ51+AJ53-AJ54 -> 350 | AK55: =+AK51+AK53-AK54 -> -2266 | AL55: =IF(AI55<>0,AJ55/AI55,"-") -> - | AM55: =+AM51+AM53-AM54 -> 0 | AN55: =+AN51+AN53-AN54 -> 8454 | AO55: =+AN55-AM55 -> 8454 | AP55: =IF(AM55<>0,AN55/AM55,"-") -> - | AQ55: =+AQ51+AQ53-AQ54 -> 0 | AR55: =+AR51+AR53-AR54 -> 9017 | AS55: =+AR55-AQ55 -> 9017 | AT55: =IF(AQ55<>0,AR55/AQ55,"-") -> - | AU55: =+AU51+AU53-AU54 -> 0 | AV55: =+AV51+AV53-AV54 -> 8610 | AW55: =+AV55-AU55 -> 8610 | AX55: =IF(AU55<>0,AV55/AU55,"-") -> - | AY55: =+C55+G55+K55+O55+S55+W55+AA55+AE55+AI55+AM55+AQ55+AU55 -> -36006.718 | AZ55: =+D55+H55+L55+P55+T55+X55+AB55+AF55+AJ55+AN55+AR55+AV55 -> 26698.662 | BA55: =+AZ55-AY55 -> 62705.38 | BB55: =IF(AY55<>0,AZ55/AY55,"-") -> -0.74149113 | BC55: =+PL推移!N54-収支計画!W67/1000 -> #DIV/0! | BD55: =+BC55/(収支計画!W67/1000) -> #DIV/0! | BE55: =+PL推移!P54-収支計画!Y67/1000 -> #DIV/0! | BF55: =+BE55/(収支計画!Y67/1000) -> #DIV/0! | BG55: =+PL推移!R54-収支計画!AA67/1000 -> 0 | BH55: =+BG55/(収支計画!AA67/1000) -> #DIV/0! | BI55: =+PL推移!T54-収支計画!AC67/1000 -> 350 | BJ55: =+BI55/(収支計画!AC67/1000) -> #DIV/0! | BK55: =+PL推移!V54-収支計画!AE67/1000 -> 8454 | BL55: =+BK55/(収支計画!AE67/1000) -> #DIV/0! | BM55: =+PL推移!X54-収支計画!AG67/1000 -> 9017 | BN55: =+BM55/(収支計画!AG67/1000) -> #DIV/0! | BO55: =+PL推移!Z54-収支計画!AI67/1000 -> 8610 | BP55: =+BO55/(収支計画!AI67/1000) -> #DIV/0!
B56: 期中累計 | C56: =+C55 -> 369.601 | D56: =+D55 -> 267.662 | E56: =+E55 -> -101.948 | F56: =IF(C56<>0,D56/C56,"-") -> 0.72419176 | G56: =+C56+G55 -> -12006.724 | H56: =+D56+H55 -> 267.662 | I56: =+I55 -> 12376.325 | J56: =IF(G56<>0,H56/G56,"-") -> -0.022292675 | K56: =+G56+K55 -> -25290.289 | L56: =+H56+L55 -> 267.662 | M56: =+M55 -> 13283.565 | N56: =IF(K56<>0,L56/K56,"-") -> -0.010583588 | O56: =+K56+O55 -> -36006.718 | P56: =+PL推移!J55 -> 267.662 | Q56: =+P56-O56 -> 36274.38 | R56: =IF(O56<>0,P56/O56,"-") -> -0.0074336684 | S56: =+O56+S55 -> -36006.718 | T56: =+P56+T55 -> 267.662 | U56: =+T56-S56 -> 36274.38 | V56: =IF(S56<>0,T56/S56,"-") -> -0.0074336684 | W56: =+S56+W55 -> -36006.718 | X56: =+T56+X55 -> 267.662 | Y56: =+X56-W56 -> 36274.38 | Z56: =IF(W56<>0,X56/W56,"-") -> -0.0074336684 | AA56: =+W56+AA55 -> -36006.718 | AB56: =+X56+AB55 -> 267.662 | AC56: =+AB56-AA56 -> 36274.38 | AD56: =IF(AA56<>0,AB56/AA56,"-") -> -0.0074336684 | AE56: =+AA56+AE55 -> -36006.718 | AF56: =+AB56+AF55 -> 267.662 | AG56: =+AF56-AE56 -> 36274.38 | AH56: =IF(AE56<>0,AF56/AE56,"-") -> -0.0074336684 | AI56: =+AE56+AI55 -> -36006.718 | AJ56: =+AF56+AJ55 -> 617.662 | AK56: =+AJ56-AI56 -> 36624.38 | AL56: =IF(AI56<>0,AJ56/AI56,"-") -> -0.017154077 | AM56: =+AI56+AM55 -> -36006.718 | AN56: =+AJ56+AN55 -> 9071.662 | AO56: =+AN56-AM56 -> 45078.38 | AP56: =IF(AM56<>0,AN56/AM56,"-") -> -0.2519436 | AQ56: =+AM56+AQ55 -> -36006.718 | AR56: =+AN56+AR55 -> 18088.662 | AS56: =+AR56-AQ56 -> 54095.38 | AT56: =IF(AQ56<>0,AR56/AQ56,"-") -> -0.50236909 | AU56: =+AQ56+AU55 -> -36006.718 | AV56: =+AR56+AV55 -> 26698.662 | AW56: =+AV56-AU56 -> 62705.38 | AX56: =IF(AU56<>0,AV56/AU56,"-") -> -0.74149113 | BB56: =IF(AY56<>0,AZ56/AY56,"-") -> - | BC56: =+PL推移!N55-収支計画!W68/1000 -> 267.662 | BD56: =+BC56/(収支計画!W68/1000) -> #DIV/0! | BE56: =+PL推移!P55-収支計画!Y68/1000 -> 267.662 | BF56: =+BE56/(収支計画!Y68/1000) -> #DIV/0! | BG56: =+PL推移!R55-収支計画!AA68/1000 -> 267.662 | BH56: =+BG56/(収支計画!AA68/1000) -> #DIV/0! | BI56: =+PL推移!T55-収支計画!AC68/1000 -> 617.662 | BJ56: =+BI56/(収支計画!AC68/1000) -> #DIV/0! | BK56: =+PL推移!V55-収支計画!AE68/1000 -> 9071.662 | BL56: =+BK56/(収支計画!AE68/1000) -> #DIV/0! | BM56: =+PL推移!X55-収支計画!AG68/1000 -> 18088.662 | BN56: =+BM56/(収支計画!AG68/1000) -> #DIV/0! | BO56: =+PL推移!Z55-収支計画!AI68/1000 -> 26698.662 | BP56: =+BO56/(収支計画!AI68/1000) -> #DIV/0!
B57: FL | C57: =+収支計画!G67 -> 0.53214259 | D57: =+(D30+D17)/D11 -> 0.51952311
C58: 売上高 | D58: レストラン売上 | F58: =+E12 -> -575 | S58: 消耗品費 | T58: ﾊﾟｯﾁﾝﾊﾞﾝﾄﾞ | V58: 177 | W58: 売上高 | X58: レストラン売上 | Z58: =+Y12 -> 0 | AA58: 売上高 | AB58: レストラン売上 | AD58: 474 | AE58: 売上高 | AF58: レストラン売上 | AH58: =+AG12 -> 0 | AI58: 売上高 | AJ58: レストラン売上 | AL58: =+AK12 -> 0 | AM58: 売上高 | AN58: レストラン売上 | AP58: =+AO12 -> 6013 | AQ58: 売上高 | AR58: レストラン売上 | AT58: =+AS12 -> 6855 | AU58: 売上高 | AV58: レストラン売上 | AX58: =+AW12 -> 6185
D59: 弁当受注増 | F59: =+E14 -> 175 | T59: ﾁｹｯﾄ制作ﾀｶﾊｼﾓﾄﾋﾛ | V59: 72 | X59: 弁当受注減 | Z59: =+Y14 -> 0 | AB59: 弁当受注減 | AD59: -709 | AF59: 弁当受注減 | AH59: =+AG14 -> 0 | AJ59: 弁当予算差異 | AL59: =+AK14 -> 0 | AN59: サウナ | AP59: =+AO16 -> 812 | AR59: サウナ | AT59: =+AS16 -> 1329 | AV59: サウナ | AX59: =+AW16 -> 892
C60: 原価率 | D60: 対相乗積 | E60: ﾚｽﾄﾗﾝ | F60: +1.1p | S60: 支払手数料 | T60: ｱｹﾙﾝﾌﾟﾛﾚﾝﾀﾙ | V60: 156 | W60: 原価率 | X60: 対相乗積 | Y60: ﾚｽﾄﾗﾝ | Z60: -1.5p | AA60: 原価率 | AB60: 対相乗積 | AC60: ﾚｽﾄﾗﾝ | AD60: -1.0p | AE60: 原価率 | AF60: 対相乗積 | AG60: ﾚｽﾄﾗﾝ | AH60: -1.5p | AI60: 原価率 | AJ60: 対相乗積 | AK60: ﾚｽﾄﾗﾝ | AL60: -2.2p | AM60: 原価率 | AN60: 対相乗積 | AO60: ﾚｽﾄﾗﾝ | AP60: -0.2p | AQ60: 原価率 | AR60: 対相乗積 | AS60: ﾚｽﾄﾗﾝ | AT60: -0.3p | AU60: 原価率 | AV60: 対相乗積 | AW60: ﾚｽﾄﾗﾝ | AX60: -1.4p | AY60: 相乗積28.0%
C61: FL | D61: 計画比 | F61: -1.2p | Y61: 村 | Z61: +4.7p | AC61: 村 | AD61: +2.1p | AG61: 村 | AH61: -19.6p | AK61: 村 | AL61: +0.6p | AO61: 村 | AP61: +9.3p | AS61: 村 | AT61: +14.4p | AW61: 村 | AX61: +18.0p | AY61: 相乗積0.3% | BQ61: 原価率改善効果？
C62: 営業利益 | D62: 計画比 | F62: =+E51 -> -75.462 | Y62: 村 | Z62: +4.7p | AC62: 村 | AD62: +2.1p | AG62: 村 | AH62: -19.6p | AK62: 村 | AL62: +0.6p | AO62: 村 | AP62: +9.3p | AS62: 村 | AT62: +14.4p | AW62: 村 | AX62: +18.0p | AY62: 相乗積0.3% | BQ62: レストラン売上未達が主要因
W63: 租税公課 | X63: 償却資産税 | Z63: 91 | AA63: 租税公課 | AB63: 年間平均予算の為 | AE63: 人件費 | AF63: 要因検討 | AH63: =+AG30 -> 0 | AI63: 人件費 | AJ63: FL改善 | AK63: 対12月比 | AL63: -1.2p | AM63: 人件費 | AN63: ３月から計画比+傾向 | AP63: =+AO30 -> 0 | AQ63: 人件費 | AT63: =+AS30 -> 0 | AU63: 人件費 | AX63: =+AW30 -> 0
W64: 広告宣伝費 | X64: ﾗｲﾌﾜｰｸ | Y64: SNS運用費 | Z64: 120 | AA64: 広告宣伝費 | AB64: ﾗｲﾌﾜｰｸ | AC64: SNS運用費 | AD64: 120 | AE64: 水道光熱費 | AF64: 冬季特殊要因？ | AH64: 193 | AI64: 広告宣伝費 | AJ64: 予算見直し | AK64: +120 | AL64: =+AK45 -> 0 | AM64: 広告宣伝費 | AN64: 予算見直し | AO64: LP制作ｵﾉﾐﾕ | AP64: 100 | AQ64: 広告宣伝費 | AT64: =+AS45 -> 0 | AU64: 広告宣伝費 | AX64: =+AW45 -> 0
AE65: 広告宣伝費 | AF65: ﾗｲﾌﾜｰｸ | AG65: SNS運用費 | AH65: 120 | AI65: 水道光熱費 | AJ65: 締日の影響？ | AL65: =+AK42 -> 0 | AM65: 水道光熱費 | AP65: =+AO42 -> 0 | AQ65: 水道光熱費 | AR65: 次年度計画時再検証 | AT65: =+AS42 -> 0 | AU65: 水道光熱費 | AV65: 次年度計画時再検証 | AX65: =+AW42 -> 0
AE66: 営業利益 | AF66: 3-6月計画値 | AH66: 334 | AI66: 営業利益 | AJ66: 4-6月計画値 | AL66: 141 | AM66: 営業利益 | AN66: 5-6月計画値 | AP66: 61 | AQ66: 営業利益 | AR66: 6月計画値 | AT66: 81 | AU66: 営業利益 | AX66: =+AZ51 -> 26845.148
AF67: R7/6着地見込 | AH67: =-964+AH66 -> -630 | AJ67: R7/6着地見込 | AL67: =263+AL66 -> 404 | AN67: R7/6着地見込 | AP67: =-567+AP66 -> -506 | AR67: R7/6着地見込 | AT67: 203
AQ68: 決算対策 | AR68: 消耗品資産計上 | AT68: 590 | AU68: 決算整理 | AV68: 利子補給振替 | AX68: 184
AR69: 償却費調整 | AT69: -293 | AV69: 償却費調整 | AX69: -453
AR70: R7/6着地見込 | AT70: =SUM(AT67:AT69) -> 500 | AV70: R7/6決算見込 | AX70: =+AX66+AX68+AX69 -> 26576.148 | AY70: =+AX66+AX69 -> 26392.148
AQ72: 6月 | AR72: 4月と同水準？？
AR73: 助成金 | AS73: キャリアアップ | AT73: 200
AR74: 協賛金 | AS74: サッポロビール | AT74: 100

Sheet CF推移
E1: 改善 | F1: 不確定含む | G1: 要検証
B2: ■月次報告CF | E2: =+PL推移!D7 -> ㈱ｅｓエンターテイメント
B4: =+PL推移!B8 -> 2026 | C4: 年度 | D4: 単位：千円 | E4: =+BS千円!D1 -> 7月 | F4: =+BS千円!E1 -> 8月 | G4: =+BS千円!F1 -> 9月 | H4: =+BS千円!G1 -> 10月 | I4: =+BS千円!H1 -> 11月 | J4: =+BS千円!I1 -> 12月 | K4: =+BS千円!J1 -> 1月 | L4: =+BS千円!K1 -> 2月 | ... P4: =+BS千円!O1 -> 6月
B5: １．営業活動CF | E5: =+E6-E7+E8-E9-E10-E11+E12+E13 -> 1637.013 | F5: =+F6-F7+F8-F9-F10-F11+F12+F13 -> 6047.953 | G5: =+G6-G7+G8-G9-G10-G11+G12+G13 -> 0 | H5: =+H6-H7+H8-H9-H10-H11+H12+H13 -> 0 | I5: =+I6-I7+I8-I9-I10-I11+I12+I13 -> 0 | J5: =+J6-J7+J8-J9-J10-J11+J12+J13 -> 0 | K5: =+K6-K7+K8-K9-K10-K11+K12+K13 -> 0 | L5: =+L6-L7+L8-L9-L10-L11+L12+L13 -> 0 | ... P5: =+P6-P7+P8-P9-P10-P11+P12+P13 -> 0
C6: 税引前利益 | D6: ＋ | E6: =+月次PL!C62/1000 -> 267.662 | F6: =+月次PL!D62/1000 -> 0 | G6: =+月次PL!E62/1000 -> 0 | H6: =+月次PL!F62/1000 -> 0 | I6: =+月次PL!G62/1000 -> 0 | J6: =+月次PL!H62/1000 -> 0 | K6: =+月次PL!I62/1000 -> 0 | L6: =+月次PL!J62/1000 -> 0 | ... P6: =+月次PL!N62/1000 -> 0
C7: 決算関係納税 | D7: － | E7: =+月次PL!C63/1000+BS千円!C61-BS千円!D61+BS千円!C60-BS千円!D60 -> 0 | F7: =+月次PL!D63/1000+BS千円!D61-BS千円!E61+BS千円!D60-BS千円!E60 -> 1463.8 | G7: =+月次PL!E63/1000+BS千円!E61-BS千円!F61+BS千円!E60-BS千円!F60 -> 0 | H7: =+月次PL!F63/1000+BS千円!F61-BS千円!G61+BS千円!F60-BS千円!G60 -> 0 | I7: =+月次PL!G63/1000+BS千円!G61-BS千円!H61+BS千円!G60-BS千円!H60 -> 0 | J7: =+月次PL!H63/1000+BS千円!H61-BS千円!I61+BS千円!H60-BS千円!I60 -> 0 | K7: =+月次PL!I63/1000+BS千円!I61-BS千円!J61+BS千円!I60-BS千円!J60 -> 0 | L7: =+月次PL!J63/1000+BS千円!J61-BS千円!K61+BS千円!J60-BS千円!K60 -> 0 | ... P7: =+月次PL!N63/1000+BS千円!N61-BS千円!O61+BS千円!N60-BS千円!O60 -> 0
C8: 減価償却費 | D8: ＋ | E8: =+月次PL!C40/1000-3 -> 746.954 | F8: =+月次PL!D40/1000 -> 0 | G8: =+月次PL!E40/1000 -> 0 | H8: =+月次PL!F40/1000 -> 0 | I8: =+月次PL!G40/1000 -> 0 | J8: =+月次PL!H40/1000 -> 0 | K8: =+月次PL!I40/1000 -> 0 | L8: =+月次PL!J40/1000 -> 0 | M8: =+月次PL!K40/1000 -> 0 | ... P8: =+月次PL!N40/1000 -> 0
C9: 売掛債権 | D9: － | E9: =+BS千円!D11-BS千円!C11 -> -261.994 | F9: =+BS千円!E11-BS千円!D11 -> -8860.846 | G9: =+BS千円!F11-BS千円!E11 -> 0 | H9: =+BS千円!G11-BS千円!F11 -> 0 | I9: =+BS千円!H11-BS千円!G11 -> 0 | J9: =+BS千円!I11-BS千円!H11 -> 0 | K9: =+BS千円!J11-BS千円!I11 -> 0 | L9: =+BS千円!K11-BS千円!J11 -> 0 | ... P9: =+BS千円!O11-BS千円!N11 -> 0
C10: 棚卸資産 | D10: － | E10: =+BS千円!D17-BS千円!C17 -> 0.139 | F10: =+BS千円!E17-BS千円!D17 -> -1453.87 | G10: =+BS千円!F17-BS千円!E17 -> 0 | H10: =+BS千円!G17-BS千円!F17 -> 0 | I10: =+BS千円!H17-BS千円!G17 -> 0 | J10: =+BS千円!I17-BS千円!H17 -> 0 | K10: =+BS千円!J17-BS千円!I17 -> 0 | L10: =+BS千円!K17-BS千円!J17 -> 0 | ... P10: =+BS千円!O17-BS千円!N17 -> 0
C11: その他流動資産 | D11: － | E11: =+BS千円!D24-BS千円!C24 -> 479.54 | F11: =+BS千円!E24-BS千円!D24 -> -3099.349 | G11: =+BS千円!F24-BS千円!E24 -> 0 | H11: =+BS千円!G24-BS千円!F24 -> 0 | I11: =+BS千円!H24-BS千円!G24 -> 0 | J11: =+BS千円!I24-BS千円!H24 -> 0 | K11: =+BS千円!J24-BS千円!I24 -> 0 | L11: =+BS千円!K24-BS千円!J24 -> 0 | ... P11: =+BS千円!O24-BS千円!N24 -> 0
C12: 買掛未払債務 | D12: ＋ | E12: =+BS千円!D95-BS千円!C95 -> 241.585 | F12: =+BS千円!E95-BS千円!D95 -> -4729.474 | G12: =+BS千円!F95-BS千円!E95 -> 0 | H12: =+BS千円!G95-BS千円!F95 -> 0 | I12: =+BS千円!H95-BS千円!G95 -> 0 | J12: =+BS千円!I95-BS千円!H95 -> 0 | K12: =+BS千円!J95-BS千円!I95 -> 0 | L12: =+BS千円!K95-BS千円!J95 -> 0 | ... P12: =+BS千円!O95-BS千円!N95 -> 0
C13: その他流動負債 | D13: ＋ | E13: =+BS千円!D96-BS千円!C96 -> 598.497 | F13: =+BS千円!E96-BS千円!D96 -> -1172.838 | G13: =+BS千円!F96-BS千円!E96 -> 0 | H13: =+BS千円!G96-BS千円!F96 -> 0 | I13: =+BS千円!H96-BS千円!G96 -> 0 | J13: =+BS千円!I96-BS千円!H96 -> 0 | K13: =+BS千円!J96-BS千円!I96 -> 0 | L13: =+BS千円!K96-BS千円!J96 -> 0 | ... P13: =+BS千円!O96-BS千円!N96 -> 0
B14: ２．投資活動CF | E14: =-E15-E16-E17 -> -3.1 | F14: =-F15-F16-F17 -> 73394.669 | G14: =-G15-G16-G17 -> 0 | H14: =-H15-H16-H17 -> 0 | I14: =-I15-I16-I17 -> 0 | J14: =-J15-J16-J17 -> 0 | K14: =-K15-K16-K17 -> 0 | L14: =-L15-L16-L17 -> 0 | ... P14: =-P15-P16-P17 -> 0
C15: 固定資産への投資 | D15: － | E15: =+BS千円!D97-BS千円!C97+CF推移!E8 -> 0.045 | F15: =+BS千円!E97-BS千円!D97+CF推移!F8 -> -48174.964 | G15: =+BS千円!F97-BS千円!E97+CF推移!G8 -> 0 | H15: =+BS千円!G97-BS千円!F97+CF推移!H8 -> 0 | I15: =+BS千円!H97-BS千円!G97+CF推移!I8 -> 0 | J15: =+BS千円!I97-BS千円!H97+CF推移!J8 -> 0 | K15: =+BS千円!J97-BS千円!I97+CF推移!K8 -> 0 | L15: =+BS千円!K97-BS千円!J97+CF推移!L8 -> 0 | ... P15: =+BS千円!O97-BS千円!N97+CF推移!P8 -> 0
C16: 貸付金 | D16: － | E16: 0 | F16: 0 | G16: 0 | H16: 0 | I16: 0 | J16: 0 | K16: 0 | L16: 0 | M16: 0 | N16: 0 | O16: 0 | P16: 0
C17: 投資勘定への支出 | D17: － | E17: =+BS千円!D42-BS千円!C42 -> 3.055 | F17: =+BS千円!E42-BS千円!D42 -> -25219.705 | G17: =+BS千円!F42-BS千円!E42 -> 0 | H17: =+BS千円!G42-BS千円!F42 -> 0 | I17: =+BS千円!H42-BS千円!G42 -> 0 | J17: =+BS千円!I42-BS千円!H42 -> 0 | K17: =+BS千円!J42-BS千円!I42 -> 0 | L17: =+BS千円!K42-BS千円!J42 -> 0 | ... P17: =+BS千円!O42-BS千円!N42 -> 0
B18: ３．財務活動CF | E18: =+E19+E20-E21+E22+E23 -> -480 | F18: =+F19+F20-F21+F22+F23 -> -134745 | G18: =+G19+G20-G21+G22+G23 -> 0 | H18: =+H19+H20-H21+H22+H23 -> 0 | I18: =+I19+I20-I21+I22+I23 -> 0 | J18: =+J19+J20-J21+J22+J23 -> 0 | K18: =+K19+K20-K21+K22+K23 -> 0 | L18: =+L19+L20-L21+L22+L23 -> 0 | ... P18: =+P19+P20-P21+P22+P23 -> 0
C19: 短期借入金 | D19: ＋ | E19: 0 | F19: 0 | G19: 0 | H19: 0 | I19: 0 | J19: 0 | K19: 0 | L19: 0 | M19: 0 | N19: 0 | O19: 0 | P19: 0
C20: 長期借入金調達 | D20: ＋ | E20: 0 | F20: 0 | G20: 0 | H20: 0 | I20: 0 | J20: 0 | K20: 0 | L20: 0 | M20: 0 | N20: 0 | O20: 0 | P20: 0
C21: 長期借入金返済 | D21: － | E21: =+BS千円!C98-BS千円!D98+CF推移!E20 -> 480 | F21: =+BS千円!D98-BS千円!E98+CF推移!F20 -> 134745 | G21: =+BS千円!E98-BS千円!F98+CF推移!G20 -> 0 | H21: =+BS千円!F98-BS千円!G98+CF推移!H20 -> 0 | I21: =+BS千円!G98-BS千円!H98+CF推移!I20 -> 0 | J21: =+BS千円!H98-BS千円!I98+CF推移!J20 -> 0 | K21: =+BS千円!I98-BS千円!J98+CF推移!K20 -> 0 | L21: =+BS千円!J98-BS千円!K98+CF推移!L20 -> 0 | ... P21: =+BS千円!N98-BS千円!O98+CF推移!P20 -> 0
C22: 資本の増減 | D22: ＋ | E22: =+BS千円!D72-BS千円!C72 -> 0 | F22: =+BS千円!E72-BS千円!D72 -> 0 | G22: =+BS千円!F72-BS千円!E72 -> 0 | H22: =+BS千円!G72-BS千円!F72 -> 0 | I22: =+BS千円!H72-BS千円!G72 -> 0 | J22: =+BS千円!I72-BS千円!H72 -> 0 | K22: =+BS千円!J72-BS千円!I72 -> 0 | L22: =+BS千円!K72-BS千円!J72 -> 0 | ... P22: =+BS千円!O72-BS千円!N72 -> 0
C23: その他 | D23: ＋ | E23: 0 | F23: 0 | G23: 0 | H23: 0 | I23: 0 | J23: 0 | K23: 0 | L23: 0 | M23: 0 | N23: 0 | O23: 0 | P23: 0
B24: ４．月次CF | E24: =+E5+E14+E18 -> 1153.913 | F24: =+F5+F14+F18 -> -55302.378 | G24: =+G5+G14+G18 -> 0 | H24: =+H5+H14+H18 -> 0 | I24: =+I5+I14+I18 -> 0 | J24: =+J5+J14+J18 -> 0 | K24: =+K5+K14+K18 -> 0 | L24: =+L5+L14+L18 -> 0 | ... P24: =+P5+P14+P18 -> 0
C26: 現金預金の増減額 | E26: =+BS千円!D8-BS千円!C8 -> 1153.913 | F26: =+BS千円!E8-BS千円!D8 -> -36055.578 | G26: =+BS千円!F8-BS千円!E8 -> 0 | H26: =+BS千円!G8-BS千円!F8 -> 0 | I26: =+BS千円!H8-BS千円!G8 -> 0 | J26: =+BS千円!I8-BS千円!H8 -> 0 | K26: =+BS千円!J8-BS千円!I8 -> 0 | L26: =+BS千円!K8-BS千円!J8 -> 0 | ... P26: =+BS千円!O8-BS千円!N8 -> 0
D27: CF:CK | E27: =+E24-E26 -> 0 | F27: =+F24-F26 -> -19246.8 | G27: =+G24-G26 -> 0 | H27: =+H24-H26 -> 0 | I27: =+I24-I26 -> 0 | J27: =+J24-J26 -> 0 | K27: =+K24-K26 -> 0 | L27: =+L24-L26 -> 0 | ... P27: =+P24-P26 -> 0
B28: □ＣＦ特記事項等
C29: CF計画比
C30: 現金売上・売掛回収
C31: 現金仕入・買掛未払
C32: 経費支出
C33: 納税その他
E34: =+月次BS!D8-月次BS!C8 -> 1153913 | F34: =+月次BS!E8-月次BS!D8 -> -36055578 | G34: =+月次BS!F8-月次BS!E8 -> 0 | H34: =+月次BS!G8-月次BS!F8 -> 0

Sheet 収支計画
E5: 収支予測表
E9: 勘定科目 | S9: 手入力 | T9: 手入力
G10: R8.07 | H10: R8.08 | I10: R8.09 | J10: R8.10 | K10: R8.11 | L10: R8.12 | M10: R9.01 | N10: R9.02 | O10: R9.03 | P10: R9.04 | Q10: R9.05 | R10: R9.06 | S10: R8.07 | T10: R8.08 | U10: R8.09 | V10: R8.10 | W10: R8.11 | X10: R8.12 | Y10: R9.01 | Z10: R9.02
E11: 売上高 | F11: 恵愛 | G11: ='[1]2024.07～恵愛予測'!C3 -> 7000000 | H11: =+[2]収支予測!H11 -> 7000000 | I11: =+[2]収支予測!I11 -> 7000000 | J11: =+[2]収支予測!J11 -> 7000000 | K11: =+[2]収支予測!K11 -> 7000000 | L11: =+[2]収支予測!L11 -> 9500000 | M11: =+[2]収支予測!M11 -> 7000000 | N11: =+[2]収支予測!N11 -> 7000000 | O11: =+[2]収支予測!O11 -> 8500000 | ... R11: =+[2]収支予測!R11 -> 7000000
F12: 村 | G12: ='[1]2024.7~村予測'!C3 -> 750000 | H12: =+[2]収支予測!H12 -> 750000 | I12: =+[2]収支予測!I12 -> 750000 | J12: =+[2]収支予測!J12 -> 750000 | K12: =+[2]収支予測!K12 -> 750000 | L12: =+[2]収支予測!L12 -> 750000 | M12: =+[2]収支予測!M12 -> 750000 | N12: =+[2]収支予測!N12 -> 750000 | O12: =+[2]収支予測!O12 -> 750000 | ... R12: =+[2]収支予測!R12 -> 750000
F13: 弁当事業 | G13: ='[1]2024.7~弁当予測'!C3 -> 350000 | H13: =+[2]収支予測!H13 -> 350000 | I13: =+[2]収支予測!I13 -> 350000 | J13: =+[2]収支予測!J13 -> 350000 | K13: =+[2]収支予測!K13 -> 350000 | L13: =+[2]収支予測!L13 -> 350000 | M13: =+[2]収支予測!M13 -> 350000 | N13: =+[2]収支予測!N13 -> 350000 | O13: =+[2]収支予測!O13 -> 350000 | ... R13: =+[2]収支予測!R13 -> 350000
F14: シェア | G14: ='[1]2024.7~シェアバー予測'!C3 -> 150000 | H14: =+[2]収支予測!H14 -> 150000 | I14: =+[2]収支予測!I14 -> 150000 | J14: =+[2]収支予測!J14 -> 150000 | K14: =+[2]収支予測!K14 -> 150000 | L14: =+[2]収支予測!L14 -> 150000 | M14: =+[2]収支予測!M14 -> 150000 | N14: =+[2]収支予測!N14 -> 150000 | O14: =+[2]収支予測!O14 -> 150000 | ... R14: =+[2]収支予測!R14 -> 150000
F15: サウナ | G15: ='[1]2024.7~サウナ予測'!C3 -> 1000000 | H15: =+[2]収支予測!H15 -> 2620000 | I15: =+[2]収支予測!I15 -> 1000000 | J15: =+[2]収支予測!J15 -> 1000000 | K15: =+[2]収支予測!K15 -> 1000000 | L15: =+[2]収支予測!L15 -> 1000000 | M15: =+[2]収支予測!M15 -> 1000000 | N15: =+[2]収支予測!N15 -> 1000000 | O15: =+[2]収支予測!O15 -> 1000000 | ... R15: =+[2]収支予測!R15 -> 1000000
B16: 月末売掛残高割合 | C16: 現金割合 | F16: 本部
A17: 原価率 | B17: 0.34 | C17: =1-B17 -> 0.66 | F17: 合計 | G17: =SUM(G11:G16) -> 9250000 | H17: =SUM(H11:H16) -> 10870000 | I17: =SUM(I11:I16) -> 9250000 | J17: =SUM(J11:J16) -> 9250000 | K17: =SUM(K11:K16) -> 9250000 | L17: =SUM(L11:L16) -> 11750000 | M17: =SUM(M11:M16) -> 9250000 | N17: =SUM(N11:N16) -> 9250000 | ... Z17: =SUM(Z11:Z16) -> 0
A18: 0.3 | E18: 売上原価 | F18: 恵愛 | G18: ='[1]2024.07～恵愛予測'!C4 -> 1785000 | H18: =+[2]収支予測!H18 -> 1785000 | I18: =+[2]収支予測!I18 -> 1785000 | J18: =+[2]収支予測!J18 -> 1785000 | K18: =+[2]収支予測!K18 -> 1785000 | L18: =+[2]収支予測!L18 -> 2422500 | M18: =+[2]収支予測!M18 -> 1785000 | N18: =+[2]収支予測!N18 -> 1785000 | O18: =+[2]収支予測!O18 -> 2167500 | ... R18: =+[2]収支予測!R18 -> 1785000
A19: 0.34 | F19: 村 | G19: ='[1]2024.7~村予測'!C4 -> 112500 | H19: =+[2]収支予測!H19 -> 112500 | I19: =+[2]収支予測!I19 -> 112500 | J19: =+[2]収支予測!J19 -> 112500 | K19: =+[2]収支予測!K19 -> 112500 | L19: =+[2]収支予測!L19 -> 112500 | M19: =+[2]収支予測!M19 -> 112500 | N19: =+[2]収支予測!N19 -> 112500 | O19: =+[2]収支予測!O19 -> 112500 | ... R19: =+[2]収支予測!R19 -> 112500
F20: 弁当事業 | G20: ='[1]2024.7~弁当予測'!C4 -> 157500 | H20: =+[2]収支予測!H20 -> 140000 | I20: =+[2]収支予測!I20 -> 140000 | J20: =+[2]収支予測!J20 -> 140000 | K20: =+[2]収支予測!K20 -> 140000 | L20: =+[2]収支予測!L20 -> 140000 | M20: =+[2]収支予測!M20 -> 140000 | N20: =+[2]収支予測!N20 -> 140000 | O20: =+[2]収支予測!O20 -> 140000 | ... R20: =+[2]収支予測!R20 -> 140000
A21: 0.32 | F21: シェア | G21: ='[1]2024.7~シェアバー予測'!C4 -> 45000 | H21: =+[2]収支予測!H21 -> 45000 | I21: =+[2]収支予測!I21 -> 45000 | J21: =+[2]収支予測!J21 -> 84350 | K21: =+[2]収支予測!K21 -> 45000 | L21: =+[2]収支予測!L21 -> 43879 | M21: =+[2]収支予測!M21 -> 45000 | N21: =+[2]収支予測!N21 -> 45000 | O21: =+[2]収支予測!O21 -> 37500 | ... R21: =+[2]収支予測!R21 -> 45000
F22: サウナ | G22: ='[1]2024.7~サウナ予測'!C4 -> 100000 | H22: =+[2]収支予測!H22 -> 50000 | I22: =+[2]収支予測!I22 -> 50000 | J22: =+[2]収支予測!J22 -> 50000 | K22: =+[2]収支予測!K22 -> 50000 | L22: =+[2]収支予測!L22 -> 50000 | M22: =+[2]収支予測!M22 -> 50000 | N22: =+[2]収支予測!N22 -> 50000 | O22: =+[2]収支予測!O22 -> 50000 | ... R22: =+[2]収支予測!R22 -> 50000
A23: 0.34 | B23: 掛割合 | C23: 現金割合 | F23: 本部 | G23: ='[1]2024.07~本部予測'!C4 -> 0 | H23: ='[1]2024.07~本部予測'!D4 -> 0 | I23: 0 | J23: 0 | K23: 0 | L23: 0 | M23: 0 | N23: 0 | O23: 0 | P23: 0 | Q23: 0 | R23: 0
B24: 0.99 | C24: =1-B24 -> 0.01 | F24: 合計 | G24: =SUM(G18:G23) -> 2200000 | H24: =SUM(H18:H23) -> 2132500 | I24: =SUM(I18:I23) -> 2132500 | J24: =SUM(J18:J23) -> 2171850 | K24: =SUM(K18:K23) -> 2132500 | L24: =SUM(L18:L23) -> 2768879 | M24: =SUM(M18:M23) -> 2132500 | N24: =SUM(N18:N23) -> 2132500 | ... Z24: =SUM(Z18:Z23) -> 0
E25: 粗利益 | G25: =G17-G24 -> 7050000 | H25: =H17-H24 -> 8737500 | I25: =I17-I24 -> 7117500 | J25: =J17-J24 -> 7078150 | K25: =K17-K24 -> 7117500 | L25: =L17-L24 -> 8981121 | M25: =M17-M24 -> 7117500 | N25: =N17-N24 -> 7117500 | ... Z25: =Z17-Z24 -> 0
A26: 予測値 | G26: =G25/G17 -> 0.76216216 | H26: =H25/H17 -> 0.80381785 | I26: =I25/I17 -> 0.76945946 | J26: =J25/J17 -> 0.76520541 | K26: =K25/K17 -> 0.76945946 | L26: =L25/L17 -> 0.76435072 | M26: =M25/M17 -> 0.76945946 | N26: =N25/N17 -> 0.76945946 | ... Z26: =Z25/Z17 -> #DIV/0!
A27: 590 | E27: 人件費 | F27: 役員報酬 | G27: ='[1]2024.07～恵愛予測'!C7+'[1]2024.7~村予測'!C7+'[1]2024.7~弁当予測'!C7+'[1]2024.7~シェアバー予測'!C7+'[1]2024.7~サウナ予測'!C7+'[1]2024.07~本部予測'!C7 -> 500000 | H27: =+[2]収支予測!H27 -> 500000 | I27: =+[2]収支予測!I27 -> 500000 | J27: =+[2]収支予測!J27 -> 500000 | K27: =+[2]収支予測!K27 -> 500000 | L27: =+[2]収支予測!L27 -> 500000 | M27: =+[2]収支予測!M27 -> 500000 | N27: =+[2]収支予測!N27 -> 500000 | O27: =+[2]収支予測!O27 -> 500000 | ... R27: =+[2]収支予測!R27 -> 500000 | S27: 500000 | T27: 500000
F28: 給与手当 | G28: ='[1]2024.07～恵愛予測'!C8+'[1]2024.7~村予測'!C8+'[1]2024.7~弁当予測'!C8+'[1]2024.7~シェアバー予測'!C8+'[1]2024.7~サウナ予測'!C8+'[1]2024.07~本部予測'!C8 -> 570000 | H28: =+[2]収支予測!H28 -> 570000 | I28: =+[2]収支予測!I28 -> 570000 | J28: =+[2]収支予測!J28 -> 570000 | K28: =+[2]収支予測!K28 -> 570000 | L28: =+[2]収支予測!L28 -> 570000 | M28: =+[2]収支予測!M28 -> 570000 | N28: =+[2]収支予測!N28 -> 570000 | O28: =+[2]収支予測!O28 -> 570000 | ... R28: =+[2]収支予測!R28 -> 570000 | S28: 570000 | T28: 570000
A29: ＊＊＊＊ | F29: 雑給 | G29: ='[1]2024.07～恵愛予測'!C9+'[1]2024.7~村予測'!C9+'[1]2024.7~弁当予測'!C9+'[1]2024.7~シェアバー予測'!C9+'[1]2024.7~サウナ予測'!C9+'[1]2024.07~本部予測'!C9 -> 1130000 | H29: =+[2]収支予測!H29 -> 1110000 | I29: =+[2]収支予測!I29 -> 1110000 | J29: =+[2]収支予測!J29 -> 1110000 | K29: =+[2]収支予測!K29 -> 1110000 | L29: =+[2]収支予測!L29 -> 1485000 | M29: =+[2]収支予測!M29 -> 1110000 | N29: =+[2]収支予測!N29 -> 1110000 | O29: =+[2]収支予測!O29 -> 1335000 | ... R29: =+[2]収支予測!R29 -> 1110000 | S29: 1130000 | T29: 1130000
A30: ＊＊＊＊ | F30: 法定福利費 | G30: ='[1]2024.07～恵愛予測'!C10+'[1]2024.7~村予測'!C10+'[1]2024.7~弁当予測'!C10+'[1]2024.7~シェアバー予測'!C10+'[1]2024.7~サウナ予測'!C10+'[1]2024.07~本部予測'!C10 -> 160500 | H30: =+[2]収支予測!H30 -> 205500 | I30: =+[2]収支予測!I30 -> 205500 | J30: =+[2]収支予測!J30 -> 205500 | K30: =+[2]収支予測!K30 -> 205500 | L30: =+[2]収支予測!L30 -> 205500 | M30: =+[2]収支予測!M30 -> 205500 | N30: =+[2]収支予測!N30 -> 205500 | O30: =+[2]収支予測!O30 -> 205500 | ... R30: =+[2]収支予測!R30 -> 205500 | S30: 160500 | T30: 160500
F31: 福利厚生費 | G31: ='[1]2024.07～恵愛予測'!C11+'[1]2024.7~村予測'!C11+'[1]2024.7~弁当予測'!C11+'[1]2024.7~シェアバー予測'!C11+'[1]2024.7~サウナ予測'!C11+'[1]2024.07~本部予測'!C11 -> 0 | H31: =+[2]収支予測!H31 -> 0 | I31: =+[2]収支予測!I31 -> 0 | J31: =+[2]収支予測!J31 -> 0 | K31: =+[2]収支予測!K31 -> 0 | L31: =+[2]収支予測!L31 -> 0 | M31: =+[2]収支予測!M31 -> 0 | N31: =+[2]収支予測!N31 -> 0 | O31: =+[2]収支予測!O31 -> 0 | ... R31: =+[2]収支予測!R31 -> 0 | S31: 0 | T31: 0
F32: 業務委託費（グループ） | G32: ='[1]2024.07～恵愛予測'!C12+'[1]2024.7~村予測'!C12+'[1]2024.7~弁当予測'!C12+'[1]2024.7~シェアバー予測'!C12+'[1]2024.7~サウナ予測'!C12+'[1]2024.07~本部予測'!C12 -> 260000 | H32: =+[2]収支予測!H32 -> 285682 | I32: =+[2]収支予測!I32 -> 251021 | J32: =+[2]収支予測!J32 -> 314059 | K32: =+[2]収支予測!K32 -> 263426 | L32: =+[2]収支予測!L32 -> 256657 | M32: =+[2]収支予測!M32 -> 252206 | N32: =+[2]収支予測!N32 -> 238391 | O32: =+[2]収支予測!O32 -> 263426 | ... R32: =+[2]収支予測!R32 -> 260000 | S32: 285000 | T32: 285000
A33: 3780 | F33: 労務委託費（個人） | G33: ='[1]2024.07～恵愛予測'!C13+'[1]2024.7~村予測'!C13+'[1]2024.7~弁当予測'!C13+'[1]2024.7~シェアバー予測'!C13+'[1]2024.7~サウナ予測'!C13+'[1]2024.07~本部予測'!C13 -> 101819 | H33: =+[2]収支予測!H33 -> 101819 | I33: =+[2]収支予測!I33 -> 101819 | J33: =+[2]収支予測!J33 -> 124819 | K33: =+[2]収支予測!K33 -> 101819 | L33: =+[2]収支予測!L33 -> 102109 | M33: =+[2]収支予測!M33 -> 101819 | N33: =+[2]収支予測!N33 -> 102329 | O33: =+[2]収支予測!O33 -> 101819 | ... R33: =+[2]収支予測!R33 -> 101819 | S33: 101819 | T33: 101819
A34: 予測値 | F34: 合計 | G34: =SUM(G27:G33) -> 2722319 | H34: =SUM(H27:H33) -> 2773001 | I34: =SUM(I27:I33) -> 2738340 | J34: =SUM(J27:J33) -> 2824378 | K34: =SUM(K27:K33) -> 2750745 | L34: =SUM(L27:L33) -> 3119266 | M34: =SUM(M27:M33) -> 2739525 | N34: =SUM(N27:N33) -> 2726220 | ... Z34: =SUM(Z27:Z33) -> 0
A35: 661 | E35: 販売費管理費 | F35: 旅費交通費 | G35: ='[1]2024.07～恵愛予測'!C14+'[1]2024.7~村予測'!C14+'[1]2024.7~弁当予測'!C14+'[1]2024.7~シェアバー予測'!C14+'[1]2024.7~サウナ予測'!C14+'[1]2024.07~本部予測'!C14 -> 50000 | H35: =+[2]収支予測!H35 -> 50000 | I35: =+[2]収支予測!I35 -> 50000 | J35: =+[2]収支予測!J35 -> 50000 | K35: =+[2]収支予測!K35 -> 50000 | L35: =+[2]収支予測!L35 -> 55000 | M35: =+[2]収支予測!M35 -> 55000 | N35: =+[2]収支予測!N35 -> 55000 | O35: =+[2]収支予測!O35 -> 55000 | ... R35: =+[2]収支予測!R35 -> 50000 | S35: 50000 | T35: 50000
A36: ＊＊＊＊ | F36: 通信費 | G36: ='[1]2024.07～恵愛予測'!C15+'[1]2024.7~村予測'!C15+'[1]2024.7~弁当予測'!C15+'[1]2024.7~シェアバー予測'!C15+'[1]2024.7~サウナ予測'!C15+'[1]2024.07~本部予測'!C15 -> 63050 | H36: =+[2]収支予測!H36 -> 54050 | I36: =+[2]収支予測!I36 -> 54050 | J36: =+[2]収支予測!J36 -> 54050 | K36: =+[2]収支予測!K36 -> 54050 | L36: =+[2]収支予測!L36 -> 54050 | M36: =+[2]収支予測!M36 -> 54050 | N36: =+[2]収支予測!N36 -> 54050 | O36: =+[2]収支予測!O36 -> 54050 | ... R36: =+[2]収支予測!R36 -> 54050 | S36: 69050 | T36: 69050
A37: ＊＊＊＊ | F37: 開発費 | G37: ='[1]2024.07～恵愛予測'!C16+'[1]2024.7~村予測'!C16+'[1]2024.7~弁当予測'!C16+'[1]2024.7~シェアバー予測'!C16+'[1]2024.7~サウナ予測'!C16+'[1]2024.07~本部予測'!C16 -> 0 | H37: =+[2]収支予測!H37 -> 0 | I37: =+[2]収支予測!I37 -> 0 | J37: =+[2]収支予測!J37 -> 0 | K37: =+[2]収支予測!K37 -> 0 | L37: =+[2]収支予測!L37 -> 0 | M37: =+[2]収支予測!M37 -> 0 | N37: =+[2]収支予測!N37 -> 0 | O37: =+[2]収支予測!O37 -> 0 | ... R37: =+[2]収支予測!R37 -> 0 | S37: 0 | T37: 0
F38: 交際費 | G38: ='[1]2024.07～恵愛予測'!C17+'[1]2024.7~村予測'!C17+'[1]2024.7~弁当予測'!C17+'[1]2024.7~シェアバー予測'!C17+'[1]2024.7~サウナ予測'!C17+'[1]2024.07~本部予測'!C17 -> 0 | H38: =+[2]収支予測!H38 -> 0 | I38: =+[2]収支予測!I38 -> 0 | J38: =+[2]収支予測!J38 -> 0 | K38: =+[2]収支予測!K38 -> 0 | L38: =+[2]収支予測!L38 -> 0 | M38: =+[2]収支予測!M38 -> 0 | N38: =+[2]収支予測!N38 -> 0 | O38: =+[2]収支予測!O38 -> 0 | ... R38: =+[2]収支予測!R38 -> 0 | S38: 50000 | T38: 50000
F39: 会議費 | G39: ='[1]2024.07～恵愛予測'!C18+'[1]2024.7~村予測'!C18+'[1]2024.7~弁当予測'!C18+'[1]2024.7~シェアバー予測'!C18+'[1]2024.7~サウナ予測'!C18+'[1]2024.07~本部予測'!C18 -> 10000 | H39: =+[2]収支予測!H39 -> 10000 | I39: =+[2]収支予測!I39 -> 10000 | J39: =+[2]収支予測!J39 -> 10000 | K39: =+[2]収支予測!K39 -> 10000 | L39: =+[2]収支予測!L39 -> 30000 | M39: =+[2]収支予測!M39 -> 10000 | N39: =+[2]収支予測!N39 -> 10000 | O39: =+[2]収支予測!O39 -> 30000 | ... R39: =+[2]収支予測!R39 -> 10000 | S39: 0 | T39: 0
F40: 減価償却費 | G40: ='[1]2024.07～恵愛予測'!C19+'[1]2024.7~村予測'!C19+'[1]2024.7~弁当予測'!C19+'[1]2024.7~シェアバー予測'!C19+'[1]2024.7~サウナ予測'!C19+'[1]2024.07~本部予測'!C19 -> 749954 | H40: =+[2]収支予測!H40 -> 749954 | I40: =+[2]収支予測!I40 -> 749954 | J40: =+[2]収支予測!J40 -> 749954 | K40: =+[2]収支予測!K40 -> 749954 | L40: =+[2]収支予測!L40 -> 749954 | M40: =+[2]収支予測!M40 -> 749954 | N40: =+[2]収支予測!N40 -> 749954 | O40: =+[2]収支予測!O40 -> 749954 | ... R40: =+[2]収支予測!R40 -> 749954 | S40: 749954 | T40: 749954
F41: 賃借料 | G41: ='[1]2024.07～恵愛予測'!C20+'[1]2024.7~村予測'!C20+'[1]2024.7~弁当予測'!C20+'[1]2024.7~シェアバー予測'!C20+'[1]2024.7~サウナ予測'!C20+'[1]2024.07~本部予測'!C20 -> 30000 | H41: =+[2]収支予測!H41 -> 30000 | I41: =+[2]収支予測!I41 -> 30000 | J41: =+[2]収支予測!J41 -> 30000 | K41: =+[2]収支予測!K41 -> 30000 | L41: =+[2]収支予測!L41 -> 30000 | M41: =+[2]収支予測!M41 -> 30000 | N41: =+[2]収支予測!N41 -> 30000 | O41: =+[2]収支予測!O41 -> 30000 | ... R41: =+[2]収支予測!R41 -> 30000 | S41: 30000 | T41: 30000
F42: 地代家賃 | G42: =1645661-350000 -> 1295661 | H42: =+[2]収支予測!H42-350000 -> 1295661 | I42: =+[2]収支予測!I42-350000 -> 1295661 | J42: =+[2]収支予測!J42-350000 -> 1295661 | K42: =+[2]収支予測!K42-350000 -> 1295661 | L42: =+[2]収支予測!L42-350000 -> 1295661 | M42: =+[2]収支予測!M42-350000 -> 1295661 | N42: =+[2]収支予測!N42-350000 -> 1295661 | O42: =+[2]収支予測!O42-350000 -> 1295661 | ... R42: =+[2]収支予測!R42-350000 -> 1295661 | S42: =+R42 -> 1295661 | T42: =+S42 -> 1295661
F43: リース料 | G43: ='[1]2024.07～恵愛予測'!C22+'[1]2024.7~村予測'!C22+'[1]2024.7~弁当予測'!C22+'[1]2024.7~シェアバー予測'!C22+'[1]2024.7~サウナ予測'!C22+'[1]2024.07~本部予測'!C22 -> 49700 | H43: =+[2]収支予測!H43 -> 49700 | I43: =+[2]収支予測!I43 -> 49700 | J43: =+[2]収支予測!J43 -> 49700 | K43: =+[2]収支予測!K43 -> 49700 | L43: =+[2]収支予測!L43 -> 49700 | M43: =+[2]収支予測!M43 -> 49700 | N43: =+[2]収支予測!N43 -> 49700 | O43: =+[2]収支予測!O43 -> 49700 | ... R43: =+[2]収支予測!R43 -> 49700 | S43: 49700 | T43: 49700
F44: 修繕費 | G44: ='[1]2024.07～恵愛予測'!C23+'[1]2024.7~村予測'!C23+'[1]2024.7~弁当予測'!C23+'[1]2024.7~シェアバー予測'!C23+'[1]2024.7~サウナ予測'!C23+'[1]2024.07~本部予測'!C23 -> 10000 | H44: =+[2]収支予測!H44 -> 10000 | I44: =+[2]収支予測!I44 -> 10000 | J44: =+[2]収支予測!J44 -> 10000 | K44: =+[2]収支予測!K44 -> 10000 | L44: =+[2]収支予測!L44 -> 10000 | M44: =+[2]収支予測!M44 -> 10000 | N44: =+[2]収支予測!N44 -> 10000 | O44: =+[2]収支予測!O44 -> 10000 | ... R44: =+[2]収支予測!R44 -> 10000 | S44: 10000 | T44: 10000
F45: 保険料 | G45: ='[1]2024.07～恵愛予測'!C24+'[1]2024.7~村予測'!C24+'[1]2024.7~弁当予測'!C24+'[1]2024.7~シェアバー予測'!C24+'[1]2024.7~サウナ予測'!C24+'[1]2024.07~本部予測'!C24 -> 22215 | H45: =+[2]収支予測!H45 -> 25320 | I45: =+[2]収支予測!I45 -> 25320 | J45: =+[2]収支予測!J45 -> 25320 | K45: =+[2]収支予測!K45 -> 25320 | L45: =+[2]収支予測!L45 -> 25320 | M45: =+[2]収支予測!M45 -> 25320 | N45: =+[2]収支予測!N45 -> 25320 | O45: =+[2]収支予測!O45 -> 25320 | ... R45: =+[2]収支予測!R45 -> 25320 | S45: 22215 | T45: 22215
F46: 水道光熱費 | G46: 660000 | H46: =+[2]収支予測!H46-200000 -> 660000 | I46: =+[2]収支予測!I46-200000 -> 660000 | J46: =+[2]収支予測!J46-200000 -> 660000 | K46: =+[2]収支予測!K46-200000 -> 660000 | L46: =+[2]収支予測!L46-200000 -> 860000 | M46: =+[2]収支予測!M46-200000 -> 660000 | N46: =+[2]収支予測!N46-200000 -> 660000 | O46: =+[2]収支予測!O46-200000 -> 780000 | ... R46: =+[2]収支予測!R46-200000 -> 660000 | S46: 860000 | T46: 860000
F47: 消耗品費 | G47: ='[1]2024.07～恵愛予測'!C26+'[1]2024.7~村予測'!C26+'[1]2024.7~弁当予測'!C26+'[1]2024.7~シェアバー予測'!C26+'[1]2024.7~サウナ予測'!C26+'[1]2024.07~本部予測'!C26 -> 200000 | H47: =+[2]収支予測!H47 -> 180000 | I47: =+[2]収支予測!I47 -> 180000 | J47: =+[2]収支予測!J47 -> 180000 | K47: =+[2]収支予測!K47 -> 180000 | L47: =+[2]収支予測!L47 -> 230000 | M47: =+[2]収支予測!M47 -> 180000 | N47: =+[2]収支予測!N47 -> 180000 | O47: =+[2]収支予測!O47 -> 210000 | ... R47: =+[2]収支予測!R47 -> 180000 | S47: 200000 | T47: 200000
F48: 租税公課 | G48: ='[1]2024.07～恵愛予測'!C27+'[1]2024.7~村予測'!C27+'[1]2024.7~弁当予測'!C27+'[1]2024.7~シェアバー予測'!C27+'[1]2024.7~サウナ予測'!C27+'[1]2024.07~本部予測'!C27 -> 131000 | H48: =+[2]収支予測!H48 -> 1000 | I48: =+[2]収支予測!I48 -> 147000 | J48: =+[2]収支予測!J48 -> 1000 | K48: =+[2]収支予測!K48 -> 1000 | L48: =+[2]収支予測!L48 -> 147000 | M48: =+[2]収支予測!M48 -> 1000 | N48: =+[2]収支予測!N48 -> 1000 | O48: =+[2]収支予測!O48 -> 1000 | ... R48: =+[2]収支予測!R48 -> 1000 | S48: 1000 | T48: 1000
A49: 1750 | F49: 広告宣伝費 | G49: ='[1]2024.07～恵愛予測'!C28+'[1]2024.7~村予測'!C28+'[1]2024.7~弁当予測'!C28+'[1]2024.7~シェアバー予測'!C28+'[1]2024.7~サウナ予測'!C28+'[1]2024.07~本部予測'!C28 -> 165000 | H49: =+[2]収支予測!H49 -> 165000 | I49: =+[2]収支予測!I49 -> 165000 | J49: =+[2]収支予測!J49 -> 165000 | K49: =+[2]収支予測!K49 -> 165000 | L49: =+[2]収支予測!L49 -> 165000 | M49: =+[2]収支予測!M49 -> 165000 | N49: =+[2]収支予測!N49 -> 165000 | O49: =+[2]収支予測!O49 -> 165000 | ... R49: =+[2]収支予測!R49 -> 165000 | S49: 165000 | T49: 165000
F50: 支払手数料 | G50: ='[1]2024.07～恵愛予測'!C29+'[1]2024.7~村予測'!C29+'[1]2024.7~弁当予測'!C29+'[1]2024.7~シェアバー予測'!C29+'[1]2024.7~サウナ予測'!C29+'[1]2024.07~本部予測'!C29 -> 281500 | H50: =+[2]収支予測!H50 -> 292500 | I50: =+[2]収支予測!I50 -> 292500 | J50: =+[2]収支予測!J50 -> 292500 | K50: =+[2]収支予測!K50 -> 292500 | L50: =+[2]収支予測!L50 -> 345000 | M50: =+[2]収支予測!M50 -> 292500 | N50: =+[2]収支予測!N50 -> 292500 | O50: =+[2]収支予測!O50 -> 324000 | ... R50: =+[2]収支予測!R50 -> 292500 | S50: 331500 | T50: 331500
F51: 新聞図書費 | G51: ='[1]2024.07～恵愛予測'!C30+'[1]2024.7~村予測'!C30+'[1]2024.7~弁当予測'!C30+'[1]2024.7~シェアバー予測'!C30+'[1]2024.7~サウナ予測'!C30+'[1]2024.07~本部予測'!C30 -> 0 | H51: =+[2]収支予測!H51 -> 0 | I51: =+[2]収支予測!I51 -> 0 | J51: =+[2]収支予測!J51 -> 0 | K51: =+[2]収支予測!K51 -> 0 | L51: =+[2]収支予測!L51 -> 0 | M51: =+[2]収支予測!M51 -> 0 | N51: =+[2]収支予測!N51 -> 0 | O51: =+[2]収支予測!O51 -> 0 | ... R51: =+[2]収支予測!R51 -> 0 | S51: 5000 | T51: 5000
F52: 管理諸費 | G52: ='[1]2024.07～恵愛予測'!C31+'[1]2024.7~村予測'!C31+'[1]2024.7~弁当予測'!C31+'[1]2024.7~シェアバー予測'!C31+'[1]2024.7~サウナ予測'!C31+'[1]2024.07~本部予測'!C31 -> 70000 | H52: =+[2]収支予測!H52 -> 70000 | I52: =+[2]収支予測!I52 -> 280000 | J52: =+[2]収支予測!J52 -> 70000 | K52: =+[2]収支予測!K52 -> 110000 | L52: =+[2]収支予測!L52 -> 70000 | M52: =+[2]収支予測!M52 -> 70000 | N52: =+[2]収支予測!N52 -> 70000 | O52: =+[2]収支予測!O52 -> 70000 | ... R52: =+[2]収支予測!R52 -> 70000 | S52: 70000 | T52: 70000
F53: 雑費 | G53: ='[1]2024.07～恵愛予測'!C32+'[1]2024.7~村予測'!C32+'[1]2024.7~弁当予測'!C32+'[1]2024.7~シェアバー予測'!C32+'[1]2024.7~サウナ予測'!C32+'[1]2024.07~本部予測'!C32 -> 50000 | H53: =+[2]収支予測!H53 -> 45000 | I53: =+[2]収支予測!I53 -> 45000 | J53: =+[2]収支予測!J53 -> 45000 | K53: =+[2]収支予測!K53 -> 45000 | L53: =+[2]収支予測!L53 -> 45000 | M53: =+[2]収支予測!M53 -> 45000 | N53: =+[2]収支予測!N53 -> 45000 | O53: =+[2]収支予測!O53 -> 45000 | ... R53: =+[2]収支予測!R53 -> 45000 | S53: 50000 | T53: 50000
A54: 2758 | H54: =+[2]収支予測!H54 -> 0 | I54: =+[2]収支予測!I54 -> 0 | J54: =+[2]収支予測!J54 -> 0 | K54: =+[2]収支予測!K54 -> 0 | L54: =+[2]収支予測!L54 -> 0 | M54: =+[2]収支予測!M54 -> 0 | N54: =+[2]収支予測!N54 -> 0 | O54: =+[2]収支予測!O54 -> 0 | ... R54: =+[2]収支予測!R54 -> 0
F55: 合計 | G55: =SUM(G35:G54) -> 3838080 | H55: =SUM(H35:H54) -> 3688185 | I55: =SUM(I35:I54) -> 4044185 | J55: =SUM(J35:J54) -> 3688185 | K55: =SUM(K35:K54) -> 3728185 | L55: =SUM(L35:L54) -> 4161685 | M55: =SUM(M35:M54) -> 3693185 | N55: =SUM(N35:N54) -> 3693185 | ... Z55: =SUM(Z35:Z54) -> 0
E56: 経費合計 | G56: =G34+G55 -> 6560399 | H56: =H34+H55 -> 6461186 | I56: =I34+I55 -> 6782525 | J56: =J34+J55 -> 6512563 | K56: =K34+K55 -> 6478930 | L56: =L34+L55 -> 7280951 | M56: =M34+M55 -> 6432710 | N56: =N34+N55 -> 6419405 | ... Z56: =Z34+Z55 -> 0
A57: 予測値 | E57: 営業利益 | G57: =G25-G56 -> 489601 | H57: =H25-H56 -> 2276314 | I57: =I25-I56 -> 334975 | J57: =J25-J56 -> 565587 | K57: =K25-K56 -> 638570 | L57: =L25-L56 -> 1700170 | M57: =M25-M56 -> 684790 | N57: =N25-N56 -> 698095 | ... Z57: =Z25-Z56 -> 0
E58: 営業外収益 | G58: 0 | H58: =+[2]収支予測!H58 -> 0 | I58: =+[2]収支予測!I58 -> 0 | J58: =+[2]収支予測!J58 -> 0 | K58: =+[2]収支予測!K58 -> 0 | L58: =+[2]収支予測!L58 -> 0 | M58: =+[2]収支予測!M58 -> 0 | N58: =+[2]収支予測!N58 -> 0 | O58: =+[2]収支予測!O58 -> 0 | ... R58: =+[2]収支予測!R58 -> 0
A59: 76 | E59: 営業外費用 | G59: ='[1]2024.07～恵愛予測'!C36+'[1]2024.07～恵愛予測'!C37+'[1]2024.7~村予測'!C36+'[1]2024.7~村予測'!C37+'[1]2024.7~弁当予測'!C36+'[1]2024.7~弁当予測'!C37+'[1]2024.7~シェアバー予測'!C36+'[1]2024.7~シェアバー予測'!C37+'[1]2024.7~サウナ予測'!C36+'[1]2024.7~サウナ予測'!C37+'[1]2024.07~本部予測'!C36+'[1]2024.07~本部予測'!C37 -> 120000 | H59: =+[2]収支予測!H59 -> 150000 | I59: =+[2]収支予測!I59 -> 150000 | J59: =+[2]収支予測!J59 -> 150000 | K59: =+[2]収支予測!K59 -> 150760 | L59: =+[2]収支予測!L59 -> 150000 | M59: =+[2]収支予測!M59 -> 150000 | N59: =+[2]収支予測!N59 -> 150000 | O59: =+[2]収支予測!O59 -> 150000 | ... R59: =+[2]収支予測!R59 -> 150000 | S59: 120000 | T59: 120000
A60: 予測値 | E60: 経常利益 | G60: =G57+G58-G59 -> 369601 | H60: =H57+H58-H59 -> 2126314 | I60: =I57+I58-I59 -> 184975 | J60: =J57+J58-J59 -> 415587 | K60: =K57+K58-K59 -> 487810 | L60: =L57+L58-L59 -> 1550170 | M60: =M57+M58-M59 -> 534790 | N60: =N57+N58-N59 -> 548095 | ... Z60: =Z57+Z58-Z59 -> 0
E61: 特別利益
E62: 特別損失
E63: 税引前当期利益 | G63: =G60+G61-G62 -> 369601 | H63: =H60+H61-H62 -> 2126314 | I63: =I60+I61-I62 -> 184975 | J63: =J60+J61-J62 -> 415587 | K63: =K60+K61-K62 -> 487810 | L63: =L60+L61-L62 -> 1550170 | M63: =M60+M61-M62 -> 534790 | N63: =N60+N61-N62 -> 548095 | ... Z63: =Z60+Z61-Z62 -> 0
E64: 期間累計 | G64: =G63 -> 369601 | H64: =+G64+H63 -> 2495915 | I64: =+H64+I63 -> 2680890 | J64: =+I64+J63 -> 3096477 | K64: =+J64+K63 -> 3584287 | L64: =+K64+L63 -> 5134457 | M64: =+L64+M63 -> 5669247 | N64: =+M64+N63 -> 6217342 | O64: =+N64+O63 -> 7439412 | ... R64: =+Q64+R63 -> 8905400 | S64: =S63 -> -6876399 | T64: =+S64+T63 -> -13752798 | U64: =+T64+U63 -> -13752798 | V64: =+U64+V63 -> -13752798 | W64: =+V64+W63 -> -13752798 | X64: =+W64+X63 -> -13752798 | Y64: =+X64+Y63 -> -13752798 | Z64: =+Y64+Z63 -> -13752798
E66: ＦＬ | G66: =+G24+G34 -> 4922319 | H66: =+H24+H34 -> 4905501 | I66: =+I24+I34 -> 4870840 | J66: =+J24+J34 -> 4996228 | K66: =+K24+K34 -> 4883245 | L66: =+L24+L34 -> 5888145 | M66: =+M24+M34 -> 4872025 | N66: =+N24+N34 -> 4858720 | ... Z66: =+Z24+Z34 -> 0
G67: =+G66/G17 -> 0.53214259 | H67: =+H66/H17 -> 0.45128804 | I67: =+I66/I17 -> 0.5265773 | J67: =+J66/J17 -> 0.54013276 | K67: =+K66/K17 -> 0.52791838 | L67: =+L66/L17 -> 0.50111872 | M67: =+M66/M17 -> 0.52670541 | N67: =+N66/N17 -> 0.52526703 | ... Z67: =+Z66/Z17 -> #DIV/0!
E73: 【資金収支予測】
E74: 項目 | G74: =+G9 -> 0 | H74: =+H9 -> 0 | I74: =+I9 -> 0 | J74: =+J9 -> 0 | K74: =+K9 -> 0 | L74: =+L9 -> 0 | M74: =+M9 -> 0 | N74: =+N9 -> 0 | ... Z74: =+Z9 -> 0
G75: =G10 -> R8.07 | H75: =H10 -> R8.08 | I75: =I10 -> R8.09 | J75: =J10 -> R8.10 | K75: =K10 -> R8.11 | L75: =L10 -> R8.12 | M75: =M10 -> R9.01 | N75: =N10 -> R9.02 | ... Z75: =Z10 -> R9.02
E76: A.前月繰越金 | G76: 34901665 | H76: =+G105 -> 36117672 | I76: =+H105 -> 37408525 | J76: =+I105 -> 36821753 | K76: =+J105 -> 36725608 | L76: =+K105 -> 38011242 | M76: =+L105 -> 39626012 | N76: =+M105 -> 39295303 | O76: =+N105 -> 37173890 | ... S76: =+R105 -> 37684895 | AA76: =Z105 -> 0
E77: 営業収入 | F77: 現金売上 | G77: 4404630 | H77: 4483340 | I77: 3551970 | J77: 3709140 | K77: =4189500+103200 -> 4292700 | L77: 6407140 | M77: =+M17*$C17 -> 6105000 | N77: 3566980 | O77: 4535740 | P77: =+P17*$C17 -> 6105000 | Q77: =+Q17*$C17 -> 6105000 | R77: =+R17*$C17 -> 6105000 | AA77: =+AA17*$C17 -> 0
F78: 売掛金入金 | G78: 5710627 | H78: 5596401 | I78: 5575843 | J78: 3993875 | K78: =6676752-2187510 -> 4489242 | L78: 3984396 | M78: =+L17*$B17 -> 3995000 | N78: 4716296 | O78: 4155311 | P78: =+O17*$B17 -> 3655000 | Q78: =+P17*$B17 -> 3145000 | R78: =+Q17*$B17 -> 3145000 | AA78: =+Z17*$B17 -> 0
F79: 営業外収益 | G79: =+G58 -> 0 | H79: =+H58 -> 0 | I79: =+I58 -> 0 | J79: =+J58 -> 0 | K79: =+K58 -> 0 | L79: 0 | M79: =+M58 -> 0 | N79: =+N58 -> 0 | O79: =+O58 -> 0 | P79: =+P58 -> 0 | Q79: =+Q58 -> 0 | R79: =+R58 -> 0 | AA79: =+AA58 -> 0
F80: ①合計 | G80: =SUM(G77:G79) -> 10115257 | H80: =SUM(H77:H79) -> 10079741 | I80: =SUM(I77:I79) -> 9127813 | J80: =SUM(J77:J79) -> 7703015 | K80: =SUM(K77:K79) -> 8781942 | L80: =SUM(L77:L79) -> 10391536 | M80: =SUM(M77:M79) -> 10100000 | N80: =SUM(N77:N79) -> 8283276 | ... R80: =SUM(R77:R79) -> 9250000 | AA80: =SUM(AA77:AA79) -> 0
E81: 営業支出 | F81: 現金仕入 | G81: 133139 | H81: =+H24*$C24 -> 21325 | I81: =+I24*$C24 -> 21325 | J81: =+J24*$C24 -> 21718.5 | K81: 135773 | L81: 142310 | M81: =+M24*$C24 -> 21325 | N81: =+N24*$C24 -> 21325 | O81: =+O24*$C24 -> 25075 | P81: =+P24*$C24 -> 21325 | Q81: =+Q24*$C24 -> 21325 | R81: =+R24*$C24 -> 21325 | AA81: =+AA24*$C24 -> 0
F82: 買掛金支払 | G82: 1861886 | H82: 2756954 | I82: 2127052 | J82: 2001114 | K82: 1850037 | L82: 2104183 | M82: =+L24*$B24 -> 2741190.2 | N82: 1688264 | O82: 2090236 | P82: =+O24*$B24 -> 2482425 | Q82: =+P24*$B24 -> 2111175 | R82: =+Q24*$B24 -> 2111175 | AA82: =+Z24*$B24 -> 0
F83: 未払金支払 | G83: =2075200+3978677-3074798 -> 2979079 | H83: =1934531+3688023-3106827 -> 2515727 | I83: 3660733 | J83: 2726363 | K83: 2320083 | L83: 4085440 | M83: =L34+L55-L84-L40 -> 4471908 | N83: 3126353 | O83: 4143958 | P83: =O34+O55-O84-O40 -> 2846348 | Q83: =P34+P55-P84-P40 -> 2877319 | R83: =Q34+Q55-Q84-Q40 -> 2877319 | AA83: =Z34+Z55-Z84-Z40 -> 0
F84: 現金経費 | G84: =3074798+225923+49700+30000+146000+12708 -> 3539129 | H84: =3106827 -> 3106827 | I84: =2955112+194554+280000+147000 -> 3576666 | J84: =2923775-214331 -> 2709444 | K84: =K36+K54+K46+K47+K38+K49+K42+K43+K45+K41+K39+K48+K50+K51+K53 -> 2808231 | L84: 2059089 | M84: =M36+M54+M46+M47+M38+M49+M42+M43+M45+M41+M39+M48+M50+M51+M53 -> 2808231 | N84: =N36+N54+N46+N47+N38+N49+N42+N43+N45+N41+N39+N48+N50+N51+N53+213961 -> 3022192 | O84: 3274128 | P84: =P36+P54+P46+P47+P38+P49+P42+P43+P45+P41+P39+P48+P50+P51+P53 -> 2938231 | Q84: =Q36+Q54+Q46+Q47+Q38+Q49+Q42+Q43+Q45+Q41+Q39+Q48+Q50+Q51+Q53 -> 2808231 | R84: =R36+R54+R46+R47+R38+R49+R42+R43+R45+R41+R39+R48+R50+R51+R53 -> 2808231 | AA84: =AA36+AA54+AA46+AA47+AA38+AA49+AA42+AA43+AA45+AA41+AA39+AA48+AA50+AA51+AA53 -> 0
F85: 支払利息 | G85: 147962 | H85: =+H59 -> 150000 | I85: =+I59 -> 150000 | J85: =+J59 -> 150000 | K85: =+K59 -> 150760 | L85: =+L59 -> 150000 | M85: =+M59 -> 150000 | N85: =+N59 -> 150000 | O85: =+O59 -> 150000 | ... R85: =+R59 -> 150000 | AA85: =+AA59 -> 0
F86: ②合計 | G86: =SUM(G81:G85) -> 8661195 | H86: =SUM(H81:H85) -> 8550833 | I86: =SUM(I81:I85) -> 9535776 | J86: =SUM(J81:J85) -> 7608639.5 | K86: =SUM(K81:K85) -> 7264884 | L86: =SUM(L81:L85) -> 8541022 | M86: =SUM(M81:M85) -> 10192654 | N86: =SUM(N81:N85) -> 8008134 | ... R86: =SUM(R81:R85) -> 7968050 | AA86: =SUM(AA81:AA85) -> 0
E87: B.営業収支(①-②) | G87: =+G80-G86 -> 1454062 | H87: =+H80-H86 -> 1528908 | I87: =+I80-I86 -> -407963 | J87: =+J80-J86 -> 94375.5 | K87: =+K80-K86 -> 1517058 | L87: =+L80-L86 -> 1850514 | M87: =+M80-M86 -> -92654.21 | N87: =+N80-N86 -> 275142 | ... R87: =+R80-R86 -> 1281950 | AA87: =+AA80-AA86 -> 0
E88: 財務収入 | F88: 短期借入
F89: 長期借入
F90: 助成金
F91: 保険積立金
F92: 立替金回収 | I92: 59246 | J92: 47535 | K92: 6631 | L92: 2311
F93: ③合計 | G93: =SUM(G88:G92) -> 0 | H93: =SUM(H88:H92) -> 0 | I93: =SUM(I88:I92) -> 59246 | J93: =SUM(J88:J92) -> 47535 | K93: =SUM(K88:K92) -> 6631 | L93: =SUM(L88:L92) -> 2311 | M93: =SUM(M88:M92) -> 0 | N93: =SUM(N88:N92) -> 0 | ... R93: =SUM(R88:R92) -> 0 | AA93: =SUM(AA88:AA92) -> 0
E94: 財務支出 | F94: 投資・株式
F95: 保険積立金 | G95: 3055 | H95: 3055 | I95: 3055 | J95: 3055 | K95: 3055 | L95: 3055 | M95: 3055 | N95: 3055 | O95: 3055 | P95: 3055 | Q95: 3055 | R95: 3055 | AA95: 3055
F96: 法人税予測
F97: 消費税予測 | N97: 1943500
F98: 立替金
F99: 仮払仮受消費税
F100: 長期借入金返済 | G100: =SUM(G111:G118) -> 235000 | H100: =SUM(H111:H118) -> 235000 | I100: =SUM(I111:I118) -> 235000 | J100: =SUM(J111:J118) -> 235000 | K100: =SUM(K111:K118) -> 235000 | L100: 235000 | M100: =SUM(M111:M118) -> 235000 | N100: =SUM(N111:N118) -> 450000 | O100: 930000 | P100: =SUM(P111:P118) -> 480000 | Q100: =SUM(Q111:Q118) -> 480000 | R100: =SUM(R111:R118) -> 480000 | AA100: =SUM(AA111:AA118) -> 0
F102: ④合計 | G102: =SUM(G94:G101) -> 238055 | H102: =SUM(H94:H101) -> 238055 | I102: =SUM(I94:I101) -> 238055 | J102: =SUM(J94:J101) -> 238055 | K102: =SUM(K94:K101) -> 238055 | L102: =SUM(L94:L101) -> 238055 | M102: =SUM(M94:M101) -> 238055 | N102: =SUM(N94:N101) -> 2396555 | ... R102: =SUM(R94:R101) -> 483055 | AA102: =SUM(AA94:AA101) -> 3055
E103: C.財務収支(③-④) | G103: =+G93-G102 -> -238055 | H103: =+H93-H102 -> -238055 | I103: =+I93-I102 -> -178809 | J103: =+J93-J102 -> -190520 | K103: =+K93-K102 -> -231424 | L103: =+L93-L102 -> -235744 | M103: =+M93-M102 -> -238055 | N103: =+N93-N102 -> -2396555 | ... AA103: =+AA93-AA102 -> -3055
E104: D.月次資金収支(B+C) | G104: =+G87+G103 -> 1216007 | H104: =+H87+H103 -> 1290853 | I104: =+I87+I103 -> -586772 | J104: =+J87+J103 -> -96144.5 | K104: =+K87+K103 -> 1285634 | L104: =+L87+L103 -> 1614770 | M104: =+M87+M103 -> -330709.21 | N104: =+N87+N103 -> -2121413 | ... AA104: =+AA87+AA103 -> -3055
E105: E.翌月繰越金(A+D) | G105: =+G76+G104 -> 36117672 | H105: =+H76+H104 -> 37408525 | I105: =+I76+I104 -> 36821753 | J105: =+J76+J104 -> 36725608 | K105: =+K76+K104 -> 38011242 | L105: =+L76+L104 -> 39626012 | M105: =+M76+M104 -> 39295303 | N105: =+N76+N104 -> 37173890 | ... AA105: =+AA76+AA104 -> -3055
E106: 長期償還資源 営業利益+減価償却費-返済 | G106: =G63+G40-G100 -> 884555 | H106: =H63+H40-H100 -> 2641268 | I106: =I63+I40-I100 -> 699929 | J106: =J63+J40-J100 -> 930541 | K106: =K63+K40-K100 -> 1002764 | L106: =L63+L40-L100 -> 2065124 | M106: =M63+M40-M100 -> 1049744 | N106: =N63+N40-N100 -> 848049 | ... AA106: =AA63+AA40-AA100 -> 0
F107: 実際
F108: 差額 | G108: =G105-G107 -> 36117672 | H108: =H105-H107 -> 37408525 | I108: =I105-I107 -> 36821753 | J108: =J105-J107 -> 36725608 | K108: =K105-K107 -> 38011242 | L108: =L105-L107 -> 39626012 | M108: =M105-M107 -> 39295303 | N108: =N105-N107 -> 37173890 | ... Z108: =Z105-Z107 -> 0
B110: 長期借入金 | D110: 残高 | F110: 月額
B111: ㈱ｅｓエンター | C111: 毎月金額 | D111: 期首残高 | E111: 終了年月 | F111: 備考 | G111: =IF($E111>=G$110,$F111,0) -> 備考 | H111: =IF($E111>=H$110,$F111,0) -> 備考 | I111: =IF($E111>=I$110,$F111,0) -> 備考 | J111: =IF($E111>=J$110,$F111,0) -> 備考 | K111: =IF($E111>=K$110,$F111,0) -> 備考 | L111: =IF($E111>=L$110,$F111,0) -> 備考 | M111: =IF($E111>=M$110,$F111,0) -> 備考 | N111: =IF($E111>=N$110,$F111,0) -> 備考 | ... Z111: =IF($E111>=Z$110,$F111,0) -> 備考
B113: 日本政策金融公庫③2021/03 | C113: 245000 | D113: 23000000 | E113: 48913 | F113: 2026.02.28開始初回のみ215,000円 | N113: 215000 | O113: 245000 | P113: 245000 | Q113: 245000 | R113: 245000 | S113: 245000 | T113: 245000 | U113: 245000 | V113: 245000 | W113: 245000 | X113: 245000 | Y113: 245000 | Z113: 245000
B114: 北洋銀行① | C114: 239000 | D114: 20000000 | E114: 48852 | F114: 2026.11.02開始 | W114: 239000 | X114: 239000 | Y114: 239000 | Z114: 239000
B115: 北洋銀行② | C115: 239000 | D115: 20000000 | E115: 49018 | F115: 2027.04.15開始
B116: 北洋銀行③ | C116: 715000 | D116: 60000000 | E116: 49025 | F116: 2027.04.22開始
...
