Workbook

Sheet 月次BS
B1: 勘定科目 | C1: 期首残 | D1: 7月 | E1: 8月 | F1: 9月 | G1: 10月 | H1: 11月 | I1: 12月 | J1: 1月 | K1: 2月 | L1: 3 | M1: 4 | N1: 5月 | O1: 6月
A2: 資産の部
A3: 流動資産
A4: 現金及び預金
B5: 現金 | C5: 2646681 | D5: 2692031 | E5: 2697851 | F5: 2121031 | G5: 2255351 | H5: 2791061 | I5: 3237871 | J5: 2181771 | K5: 1832611 | L5: 2866171 | M5: 2205981 | N5: 2181191 | O5: 2906811
B6: 普通預金 | C6: 37905465 | D6: 37560836 | E6: 35756047 | F6: 35600198 | G6: 35188952 | H6: 35645955 | I6: 36227527 | J6: 35625770 | K6: 31193217 | L6: 29192910 | M6: 27892281 | N6: 27810336 | O6: 31678389
B7: 小口現金 | C7: 213497 | D7: 31415 | E7: -19488 | F7: 92694 | G7: 163098 | H7: 61084 | I7: 162213 | J7: 368643 | K7: 384155 | L7: 324462 | M7: 312171 | N7: 351796 | O7: 316465
A8: 現金及び預金合計 | C8: 40765643 | D8: 40284282 | E8: 38434410 | F8: 37813923 | G8: 37607401 | H8: 38498100 | I8: 39627611 | J8: 38176184 | K8: 33409983 | L8: 32383543 | M8: 30410433 | N8: 30343323 | O8: 34901665
A9: 売上債権
B10: 売掛金 | C10: 8953308 | D10: 9906965 | E10: 10752692 | F10: 10434641 | G10: 11510344 | H10: 11809720 | I10: 13589176 | J10: 13035142 | K10: 13691148 | L10: 14752238 | M10: 15273355 | N10: 16433660 | O10: 9716690
A11: 売上債権合計 | C11: 8953308 | D11: 9906965 | E11: 10752692 | F11: 10434641 | G11: 11510344 | H11: 11809720 | I11: 13589176 | J11: 13035142 | K11: 13691148 | L11: 14752238 | M11: 15273355 | N11: 16433660 | O11: 9716690
A12: 有価証券
A13: 有価証券合計 | C13: 0 | D13: 0 | E13: 0 | F13: 0 | G13: 0 | H13: 0 | I13: 0 | J13: 0 | K13: 0 | L13: 0 | M13: 0 | N13: 0 | O13: 0
A14: 棚卸資産
B15: 商品 | C15: 1324285 | D15: 1460296 | E15: 1288670 | F15: 1317901 | G15: 1280808 | H15: 1439855 | I15: 1677027 | J15: 1505883 | K15: 1584538 | L15: 1653458 | M15: 1664854 | N15: 1432987 | O15: 1319258
B16: 貯蔵品 | C16: 288654 | D16: 288654 | E16: 288654 | F16: 288654 | G16: 288654 | H16: 288654 | I16: 288654 | J16: 288654 | K16: 288654 | L16: 288654 | M16: 288654 | N16: 288654 | O16: 150450
A17: 棚卸資産合計 | C17: 1612939 | D17: 1748950 | E17: 1577324 | F17: 1606555 | G17: 1569462 | H17: 1728509 | I17: 1965681 | J17: 1794537 | K17: 1873192 | L17: 1942112 | M17: 1953508 | N17: 1721641 | O17: 1469708
A18: その他流動資産
B19: 前払費用 | C19: 1742739 | D19: 1728439 | E19: 1714139 | F19: 1699839 | G19: 1685539 | H19: 1828539 | I19: 1814239 | J19: 1799939 | K19: 1785639 | L19: 1771339 | M19: 1757039 | N19: 1742739 | O19: 1742739
B20: 立替金 | C20: 626802 | D20: 815496 | E20: 609227 | F20: 781038 | G20: 789246 | H20: 794149 | I20: 816594 | J20: 534339 | K20: 528396 | L20: 357837 | M20: 507497 | N20: 664615 | O20: 866085
B21: 未収入金 | C21: 26813 | D21: 0 | E21: 0 | F21: 0 | G21: 0 | H21: 0 | I21: 0 | J21: 0 | K21: 0 | L21: 0 | M21: 0 | N21: 0 | O21: 0
B22: 仮払金 | C22: 0 | D22: 0 | E22: 0 | F22: 12943 | G22: 0 | H22: 0 | I22: 0 | J22: 0 | K22: 0 | L22: 13150 | M22: 0 | N22: 0 | O22: 0
B23: 仮払消費税 | C23: 0 | D23: 602181 | E23: 1181263 | F23: 1723683 | G23: 2238998 | H23: 2785358 | I23: 3451329 | J23: 3971010 | K23: 4699700 | L23: 5271705 | M23: 5800805 | N23: 6308184 | O23: 6820350
A24: その他流動資産合計 | C24: 2396354 | D24: 3146116 | E24: 3504629 | F24: 4217503 | G24: 4713783 | H24: 5408046 | I24: 6082162 | J24: 6305288 | K24: 7013735 | L24: 7414031 | M24: 8065341 | N24: 8715538 | O24: 9429174
A25: 流動資産合計 | C25: 53728244 | D25: 55086313 | E25: 54269055 | F25: 54072622 | G25: 55400990 | H25: 57444375 | I25: 61264630 | J25: 59311151 | K25: 55988058 | L25: 56491924 | M25: 55702637 | N25: 57214162 | O25: 55517237
A26: 固定資産
A27: 有形固定資産
B28: 建物 | C28: 16345912 | D28: 16345912 | E28: 16345912 | F28: 16345912 | G28: 16345912 | H28: 16345912 | I28: 16345912 | J28: 16345912 | K28: 16345912 | L28: 16345912 | M28: 16345912 | N28: 16345912 | O28: 16345912
B29: 附属設備 | C29: 29167466 | D29: 29167466 | E29: 29167466 | F29: 29167466 | G29: 29167466 | H29: 29167466 | I29: 29167466 | J29: 29167466 | K29: 29167466 | L29: 29167466 | M29: 29167466 | N29: 29167466 | O29: 29167466
B30: 工具器具備品 | C30: 7249232 | D30: 7249232 | E30: 7249232 | F30: 7249232 | G30: 7249232 | H30: 7249232 | I30: 7404232 | J30: 7404232 | K30: 7404232 | L30: 7404232 | M30: 7404232 | N30: 7404232 | O30: 7404232
B31: 一括償却資産 | C31: 526316 | D31: 526316 | E31: 526316 | F31: 526316 | G31: 526316 | H31: 526316 | I31: 526316 | J31: 526316 | K31: 526316 | L31: 526316 | M31: 526316 | N31: 526316 | O31: 526316
B32: 減価償却累計額 | C32: 0 | D32: -586635 | E32: -1173270 | F32: -1759905 | G32: -2346540 | H32: -2933175 | I32: -3519810 | J32: -4106445 | K32: -4693080 | L32: -5279715 | M32: -5866350 | N32: -6452985 | O32: -7039620
A33: 有形固定資産合計 | C33: 53288926 | D33: 52702291 | E33: 52115656 | F33: 51529021 | G33: 50942386 | H33: 50355751 | I33: 49924116 | J33: 49337481 | K33: 48750846 | L33: 48164211 | M33: 47577576 | N33: 46990941 | O33: 46404306
A34: 無形固定資産
B35: ソフトウェア | C35: 3801185 | D35: 3697231 | E35: 3593277 | F35: 3489323 | G35: 3385369 | H35: 3281415 | I35: 3177461 | J35: 3073507 | K35: 2969553 | L35: 2865599 | M35: 2761645 | N35: 2657691 | O35: 2553737
A36: 無形固定資産合計 | C36: 3801185 | D36: 3697231 | E36: 3593277 | F36: 3489323 | G36: 3385369 | H36: 3281415 | I36: 3177461 | J36: 3073507 | K36: 2969553 | L36: 2865599 | M36: 2761645 | N36: 2657691 | O36: 2553737
A37: 投資その他の資産
B38: 出資金 | C38: 8825960 | D38: 8825960 | E38: 8825960 | F38: 8825960 | G38: 8825960 | H38: 8825960 | I38: 8825960 | J38: 8825960 | K38: 8825960 | L38: 8825960 | M38: 8825960 | N38: 8825960 | O38: 8825960
B39: 長期前払費用 | C39: 1092742 | D39: 1092742 | E39: 1092742 | F39: 1092742 | G39: 1092742 | H39: 1092742 | I39: 1092742 | J39: 1092742 | K39: 1092742 | L39: 1092742 | M39: 1092742 | N39: 1092742 | O39: 1092742
B40: 敷金 | C40: 2126486 | D40: 2126486 | E40: 2126486 | F40: 2126486 | G40: 2126486 | H40: 2126486 | I40: 2126486 | J40: 2126486 | K40: 2126486 | L40: 2126486 | M40: 2126486 | N40: 2126486 | O40: 2126486
B41: 保険積立金 | C41: 13330514 | D41: 13333569 | E41: 13336624 | F41: 13339679 | G41: 13342734 | H41: 13345789 | I41: 13348844 | J41: 13351899 | K41: 13354954 | L41: 13358009 | M41: 13361064 | N41: 13364119 | O41: 13367174
A42: 投資その他の資産合計 | C42: 25375702 | D42: 25378757 | E42: 25381812 | F42: 25384867 | G42: 25387922 | H42: 25390977 | I42: 25394032 | J42: 25397087 | K42: 25400142 | L42: 25403197 | M42: 25406252 | N42: 25409307 | O42: 25412362
A43: 固定資産合計 | C43: 82465813 | D43: 81778279 | E43: 81090745 | F43: 80403211 | G43: 79715677 | H43: 79028143 | I43: 78495609 | J43: 77808075 | K43: 77120541 | L43: 76433007 | M43: 75745473 | N43: 75057939 | O43: 74370405
A44: 繰延資産
A45: 繰延資産合計 | C45: 0 | D45: 0 | E45: 0 | F45: 0 | G45: 0 | H45: 0 | I45: 0 | J45: 0 | K45: 0 | L45: 0 | M45: 0 | N45: 0 | O45: 0
A46: 諸口
A47: 諸口合計 | D47: 0 | E47: 0 | F47: 0 | G47: 0 | H47: 0 | I47: 0 | J47: 0 | K47: 0 | L47: 0 | M47: 0 | N47: 0 | O47: 0
A48: 資産の部合計 | C48: 136194057 | D48: 136864592 | E48: 135359800 | F48: 134475833 | G48: 135116667 | H48: 136472518 | I48: 139760239 | J48: 137119226 | K48: 133108599 | L48: 132924931 | M48: 131448110 | N48: 132272101 | O48: 129887642
A49: 負債の部
A50: 流動負債
A51: 仕入債務
B52: 買掛金 | C52: 2376878 | D52: 2756954 | E52: 2121552 | F52: 2001114 | G52: 1850037 | H52: 2104093 | I52: 3201488 | J52: 1688264 | K52: 2103386 | L52: 2282310 | M52: 2152706 | N52: 1880645 | O52: 1861886
A53: 仕入債務合計 | C53: 2376878 | D53: 2756954 | E53: 2121552 | F53: 2001114 | G53: 1850037 | H53: 2104093 | I53: 3201488 | J53: 1688264 | K53: 2103386 | L53: 2282310 | M53: 2152706 | N53: 1880645 | O53: 1861886
A54: その他流動負債
B55: 未払金 | C55: 2309203 | D55: 2268358 | E55: 2367983 | F55: 1849965 | G55: 1955664 | H55: 2059728 | I55: 2472595 | J55: 2307651 | K55: 2266708 | L55: 2219258 | M55: 2153565 | N55: 2466486 | O55: 2493064
B56: 未払費用 | C56: 718349 | D56: 770689 | E56: 1021439 | F56: 809818 | G56: 643765 | H56: 1370914 | I56: 1433570 | J56: 1134350 | K56: 1215135 | L56: 689102 | M56: 806989 | N56: 1338511 | O56: 726789
B57: 前受金 | C57: 23400 | D57: 22800 | E57: 22800 | F57: 22800 | G57: 22200 | H57: 22200 | I57: 22200 | J57: 22200 | K57: 22200 | L57: 22200 | M57: 22200 | N57: 22200 | O57: 22200
B58: 預り金 | C58: 531601 | D58: 369626 | E58: 512853 | F58: 676661 | G58: 829318 | H58: 836931 | I58: 427545 | J58: 443228 | K58: 623445 | L58: 850738 | M58: 1019965 | N58: 1130992 | O58: 544601
B59: 仮受金 | C59: 239046 | D59: 33139 | E59: 214940 | F59: 191786 | G59: 427368 | H59: 214004 | I59: 0 | J59: 13961 | K59: 0 | L59: 73266 | M59: 8994 | N59: 0 | O59: 7540
B60: 未払消費税 | C60: 3385500 | D60: 3385500 | E60: 0 | F60: 0 | G60: 0 | H60: 0 | I60: 0 | J60: 0 | K60: -1943500 | L60: -1943500 | M60: -1943500 | N60: -1943500 | O60: -1943500
B61: 未払法人税等 | C61: 70000 | D61: 70000 | E61: 0 | F61: 0 | G61: 0 | H61: 0 | I61: 0 | J61: 0 | K61: 0 | L61: 0 | M61: 0 | N61: 0 | O61: 0
B62: 仮受消費税 | C62: 0 | D62: 920133 | E62: 1910425 | F62: 2693123 | G62: 3519305 | H62: 4332684 | I62: 5492929 | J62: 6266069 | K62: 7069319 | L62: 7937456 | M62: 8649396 | N62: 9400740 | O62: 10161136
B63: 一年以内返済長期借入金 | C63: 3120000 | D63: 2585000 | E63: 2585000 | F63: 2115000 | G63: 1880000 | H63: 1880000 | I63: 1645000 | J63: 1410000 | K63: 1175000 | L63: 705000 | M63: 470000 | N63: 470000 | O63: 0
A64: その他流動負債合計 | C64: 10397099 | D64: 10425245 | E64: 8635440 | F64: 8359153 | G64: 9277620 | H64: 10716461 | I64: 11493839 | J64: 11597459 | K64: 10428307 | L64: 10553520 | M64: 11187609 | N64: 12885429 | O64: 12011830
A65: 流動負債合計 | C65: 12773977 | D65: 13182199 | E65: 10756992 | F65: 10360267 | G65: 11127657 | H65: 12820554 | I65: 14695327 | J65: 13285723 | K65: 12531693 | L65: 12835830 | M65: 13340315 | N65: 14766074 | O65: 13873716
A66: 固定負債
B67: 長期借入金 | C67: 136120000 | D67: 136420000 | E67: 136420000 | F67: 136420000 | G67: 136420000 | H67: 136420000 | I67: 136420000 | J67: 136420000 | K67: 136420000 | L67: 135960000 | M67: 135715000 | N67: 135715000 | O67: 135225000
A68: 固定負債合計 | C68: 136120000 | D68: 136420000 | E68: 136420000 | F68: 136420000 | G68: 136420000 | H68: 136420000 | I68: 136420000 | J68: 136420000 | K68: 136420000 | L68: 135960000 | M68: 135715000 | N68: 135715000 | O68: 135225000
A69: 負債の部合計 | C69: 148893977 | D69: 149602199 | E69: 147176992 | F69: 146780267 | G69: 147547657 | H69: 149240554 | I69: 151115327 | J69: 149705723 | K69: 148951693 | L69: 148795830 | M69: 149055315 | N69: 150481074 | O69: 149098716
A70: 純資産の部
A71: 株主資本
A72: 資本金
B73: 資本金 | C73: 5000000 | D73: 5000000 | E73: 5000000 | F73: 5000000 | G73: 5000000 | H73: 5000000 | I73: 5000000 | J73: 5000000 | K73: 5000000 | L73: 5000000 | M73: 5000000 | N73: 5000000 | O73: 5000000
A74: 資本金合計 | C74: 5000000 | D74: 5000000 | E74: 5000000 | F74: 5000000 | G74: 5000000 | H74: 5000000 | I74: 5000000 | J74: 5000000 | K74: 5000000 | L74: 5000000 | M74: 5000000 | N74: 5000000 | O74: 5000000
A75: 新株式申込証拠金
A76: 新株式申込証拠金合計 | C76: 0 | D76: 0 | E76: 0 | F76: 0 | G76: 0 | H76: 0 | I76: 0 | J76: 0 | K76: 0 | L76: 0 | M76: 0 | N76: 0 | O76: 0
A77: 資本剰余金
A78: 資本剰余金合計 | C78: 0 | D78: 0 | E78: 0 | F78: 0 | G78: 0 | H78: 0 | I78: 0 | J78: 0 | K78: 0 | L78: 0 | M78: 0 | N78: 0 | O78: 0
A79: 利益剰余金
A80: 繰越利益剰余金 | C80: -17699920 | D80: -17737607 | E80: -16817192 | F80: -17304434 | G80: -17430990 | H80: -17768036 | I80: -16355088 | J80: -17586497 | K80: -20843094 | L80: -20870899 | M80: -22607205 | N80: -23208973 | O80: -24211074
A81: （うち当期純利益） | C81: 0 | D81: -37687 | E81: 882728 | F81: 395486 | G81: 268930 | H81: -68116 | I81: 1344832 | J81: 113423 | K81: -3143174 | L81: -3170979 | M81: -4907285 | N81: -5509053 | O81: -6511154
A82: 利益剰余金合計 | C82: -17699920 | D82: -17737607 | E82: -16817192 | F82: -17304434 | G82: -17430990 | H82: -17768036 | I82: -16355088 | J82: -17586497 | K82: -20843094 | L82: -20870899 | M82: -22607205 | N82: -23208973 | O82: -24211074
A83: 自己株式
A84: 自己株式合計 | C84: 0 | D84: 0 | E84: 0 | F84: 0 | G84: 0 | H84: 0 | I84: 0 | J84: 0 | K84: 0 | L84: 0 | M84: 0 | N84: 0 | O84: 0
A85: 自己株式申込証拠金
A86: 自己株式申込証拠金合計 | C86: 0 | D86: 0 | E86: 0 | F86: 0 | G86: 0 | H86: 0 | I86: 0 | J86: 0 | K86: 0 | L86: 0 | M86: 0 | N86: 0 | O86: 0
A87: 株主資本合計 | C87: -12699920 | D87: -12737607 | E87: -11817192 | F87: -12304434 | G87: -12430990 | H87: -12768036 | I87: -11355088 | J87: -12586497 | K87: -15843094 | L87: -15870899 | M87: -17607205 | N87: -18208973 | O87: -19211074
A88: 評価・換算差額等
A89: 評価・換算差額等合計 | C89: 0 | D89: 0 | E89: 0 | F89: 0 | G89: 0 | H89: 0 | I89: 0 | J89: 0 | K89: 0 | L89: 0 | M89: 0 | N89: 0 | O89: 0
A90: 新株予約権
A91: 新株予約権合計 | C91: 0 | D91: 0 | E91: 0 | F91: 0 | G91: 0 | H91: 0 | I91: 0 | J91: 0 | K91: 0 | L91: 0 | M91: 0 | N91: 0 | O91: 0
A92: 純資産の部合計 | C92: -12699920 | D92: -12737607 | E92: -11817192 | F92: -12304434 | G92: -12430990 | H92: -12768036 | I92: -11355088 | J92: -12586497 | K92: -15843094 | L92: -15870899 | M92: -17607205 | N92: -18208973 | O92: -19211074
A93: 負債・純資産の部合計 | C93: 136194057 | D93: 136864592 | E93: 135359800 | F93: 134475833 | G93: 135116667 | H93: 136472518 | I93: 139760239 | J93: 137119226 | K93: 133108599 | L93: 132924931 | M93: 131448110 | N93: 132272101 | O93: 129887642
B94: [B/S CK] | C94: =IF(C93<>0,+IF(C48=C93,"OK",C48-C93),"") -> OK | D94: =IF(D93<>0,+IF(D48=D93,"OK",D48-D93),"") -> OK | E94: =IF(E93<>0,+IF(E48=E93,"OK",E48-E93),"") -> OK | F94: =IF(F93<>0,+IF(F48=F93,"OK",F48-F93),"") -> OK | G94: =IF(G93<>0,+IF(G48=G93,"OK",G48-G93),"") -> OK | H94: =IF(H93<>0,+IF(H48=H93,"OK",H48-H93),"") -> OK | I94: =IF(I93<>0,+IF(I48=I93,"OK",I48-I93),"") -> OK | J94: =IF(J93<>0,+IF(J48=J93,"OK",J48-J93),"") -> OK | ... O94: =IF(O93<>0,+IF(O48=O93,"OK",O48-O93),"") -> OK

Sheet BS千円
B1: 勘定科目 | C1: 期首残 | D1: 7月 | E1: 8月 | F1: =+月次BS!F1 -> 9月 | G1: =+月次BS!G1 -> 10月 | H1: =+月次BS!H1 -> 11月 | I1: =+月次BS!I1 -> 12月 | J1: =+月次BS!J1 -> 1月 | K1: =+月次BS!K1 -> 2月 | L1: =+月次BS!L1 -> 3 | M1: =+月次BS!M1 -> 4 | ... O1: =+月次BS!O1 -> 6月
A2: =+月次BS!A2 -> 資産の部
A3: =+月次BS!A3 -> 流動資産
A4: =+月次BS!A4 -> 現金及び預金
A5: =+月次BS!A5 -> 0 | B5: =+月次BS!B5 -> 現金 | C5: =+月次BS!C5/1000 -> 2646.681 | D5: =+月次BS!D5/1000 -> 2692.031 | E5: =+月次BS!E5/1000 -> 2697.851 | F5: =+月次BS!F5/1000 -> 2121.031 | G5: =+月次BS!G5/1000 -> 2255.351 | H5: =+月次BS!H5/1000 -> 2791.061 | I5: =+月次BS!I5/1000 -> 3237.871 | J5: =+月次BS!J5/1000 -> 2181.771 | ... O5: =+月次BS!O5/1000 -> 2906.811
A6: =+月次BS!A6 -> 0 | B6: =+月次BS!B6 -> 普通預金 | C6: =+月次BS!C6/1000 -> 37905.465 | D6: =+月次BS!D6/1000 -> 37560.836 | E6: =+月次BS!E6/1000 -> 35756.047 | F6: =+月次BS!F6/1000 -> 35600.198 | G6: =+月次BS!G6/1000 -> 35188.952 | H6: =+月次BS!H6/1000 -> 35645.955 | I6: =+月次BS!I6/1000 -> 36227.527 | J6: =+月次BS!J6/1000 -> 35625.77 | ... O6: =+月次BS!O6/1000 -> 31678.389
A7: =+月次BS!A7 -> 0 | B7: =+月次BS!B7 -> 小口現金 | C7: =+月次BS!C7/1000 -> 213.497 | D7: =+月次BS!D7/1000 -> 31.415 | E7: =+月次BS!E7/1000 -> -19.488 | F7: =+月次BS!F7/1000 -> 92.694 | G7: =+月次BS!G7/1000 -> 163.098 | H7: =+月次BS!H7/1000 -> 61.084 | I7: =+月次BS!I7/1000 -> 162.213 | J7: =+月次BS!J7/1000 -> 368.643 | ... O7: =+月次BS!O7/1000 -> 316.465
A8: =+月次BS!A8 -> 現金及び預金合計 | B8: =+月次BS!B8 -> 0 | C8: =+月次BS!C8/1000 -> 40765.643 | D8: =+月次BS!D8/1000 -> 40284.282 | E8: =+月次BS!E8/1000 -> 38434.41 | F8: =+月次BS!F8/1000 -> 37813.923 | G8: =+月次BS!G8/1000 -> 37607.401 | H8: =+月次BS!H8/1000 -> 38498.1 | I8: =+月次BS!I8/1000 -> 39627.611 | J8: =+月次BS!J8/1000 -> 38176.184 | ... O8: =+月次BS!O8/1000 -> 34901.665
A9: =+月次BS!A9 -> 売上債権 | B9: =+月次BS!B9 -> 0 | C9: =+月次BS!C9/1000 -> 0 | D9: =+月次BS!D9/1000 -> 0 | E9: =+月次BS!E9/1000 -> 0 | F9: =+月次BS!F9/1000 -> 0 | G9: =+月次BS!G9/1000 -> 0 | H9: =+月次BS!H9/1000 -> 0 | I9: =+月次BS!I9/1000 -> 0 | J9: =+月次BS!J9/1000 -> 0 | ... O9: =+月次BS!O9/1000 -> 0
A10: =+月次BS!A10 -> 0 | B10: =+月次BS!B10 -> 売掛金 | C10: =+月次BS!C10/1000 -> 8953.308 | D10: =+月次BS!D10/1000 -> 9906.965 | E10: =+月次BS!E10/1000 -> 10752.692 | F10: =+月次BS!F10/1000 -> 10434.641 | G10: =+月次BS!G10/1000 -> 11510.344 | H10: =+月次BS!H10/1000 -> 11809.72 | I10: =+月次BS!I10/1000 -> 13589.176 | J10: =+月次BS!J10/1000 -> 13035.142 | ... O10: =+月次BS!O10/1000 -> 9716.69
A11: =+月次BS!A11 -> 売上債権合計 | B11: =+月次BS!B11 -> 0 | C11: =+月次BS!C11/1000 -> 8953.308 | D11: =+月次BS!D11/1000 -> 9906.965 | E11: =+月次BS!E11/1000 -> 10752.692 | F11: =+月次BS!F11/1000 -> 10434.641 | G11: =+月次BS!G11/1000 -> 11510.344 | H11: =+月次BS!H11/1000 -> 11809.72 | I11: =+月次BS!I11/1000 -> 13589.176 | J11: =+月次BS!J11/1000 -> 13035.142 | ... O11: =+月次BS!O11/1000 -> 9716.69
A12: =+月次BS!A12 -> 有価証券 | B12: =+月次BS!B12 -> 0 | C12: =+月次BS!C12/1000 -> 0 | D12: =+月次BS!D12/1000 -> 0 | E12: =+月次BS!E12/1000 -> 0 | F12: =+月次BS!F12/1000 -> 0 | G12: =+月次BS!G12/1000 -> 0 | H12: =+月次BS!H12/1000 -> 0 | I12: =+月次BS!I12/1000 -> 0 | J12: =+月次BS!J12/1000 -> 0 | ... O12: =+月次BS!O12/1000 -> 0
A13: =+月次BS!A13 -> 有価証券合計 | B13: =+月次BS!B13 -> 0 | C13: =+月次BS!C13/1000 -> 0 | D13: =+月次BS!D13/1000 -> 0 | E13: =+月次BS!E13/1000 -> 0 | F13: =+月次BS!F13/1000 -> 0 | G13: =+月次BS!G13/1000 -> 0 | H13: =+月次BS!H13/1000 -> 0 | I13: =+月次BS!I13/1000 -> 0 | J13: =+月次BS!J13/1000 -> 0 | ... O13: =+月次BS!O13/1000 -> 0
A14: =+月次BS!A14 -> 棚卸資産 | B14: =+月次BS!B14 -> 0 | C14: =+月次BS!C14/1000 -> 0 | D14: =+月次BS!D14/1000 -> 0 | E14: =+月次BS!E14/1000 -> 0 | F14: =+月次BS!F14/1000 -> 0 | G14: =+月次BS!G14/1000 -> 0 | H14: =+月次BS!H14/1000 -> 0 | I14: =+月次BS!I14/1000 -> 0 | J14: =+月次BS!J14/1000 -> 0 | ... O14: =+月次BS!O14/1000 -> 0
A15: =+月次BS!A15 -> 0 | B15: =+月次BS!B15 -> 商品 | C15: =+月次BS!C15/1000 -> 1324.285 | D15: =+月次BS!D15/1000 -> 1460.296 | E15: =+月次BS!E15/1000 -> 1288.67 | F15: =+月次BS!F15/1000 -> 1317.901 | G15: =+月次BS!G15/1000 -> 1280.808 | H15: =+月次BS!H15/1000 -> 1439.855 | I15: =+月次BS!I15/1000 -> 1677.027 | J15: =+月次BS!J15/1000 -> 1505.883 | ... O15: =+月次BS!O15/1000 -> 1319.258
A16: =+月次BS!A16 -> 0 | B16: =+月次BS!B16 -> 貯蔵品 | C16: =+月次BS!C16/1000 -> 288.654 | D16: =+月次BS!D16/1000 -> 288.654 | E16: =+月次BS!E16/1000 -> 288.654 | F16: =+月次BS!F16/1000 -> 288.654 | G16: =+月次BS!G16/1000 -> 288.654 | H16: =+月次BS!H16/1000 -> 288.654 | I16: =+月次BS!I16/1000 -> 288.654 | J16: =+月次BS!J16/1000 -> 288.654 | ... O16: =+月次BS!O16/1000 -> 150.45
... A93: =+月次BS!A93 -> 負債・純資産の部合計 | B93: =+月次BS!B93 -> 0 | C93: =+月次BS!C93/1000 -> 136194.06 | D93: =+月次BS!D93/1000 -> 136864.59 | E93: =+月次BS!E93/1000 -> 135359.8 | F93: =+月次BS!F93/1000 -> 134475.83 | G93: =+月次BS!G93/1000 -> 135116.67 | H93: =+月次BS!H93/1000 -> 136472.52 | I93: =+月次BS!I93/1000 -> 139760.24 | J93: =+月次BS!J93/1000 -> 137119.23 | ... O93: =+月次BS!O93/1000 -> 129887.64
A94: =+月次BS!A95 -> 0 | B94: =+月次BS!B95 -> 0 | C94: =+月次BS!C95/1000 -> 0 | D94: =+月次BS!D95/1000 -> 0 | E94: =+月次BS!E95/1000 -> 0 | F94: =+月次BS!F95/1000 -> 0 | G94: =+月次BS!G95/1000 -> 0 | H94: =+月次BS!H95/1000 -> 0 | I94: =+月次BS!I95/1000 -> 0 | J94: =+月次BS!J95/1000 -> 0 | ... O94: =+月次BS!O95/1000 -> 0
A95: =+月次BS!A96 -> 0 | B95: 買掛未払債務 | C95: =+C52+C55+C56 -> 5404.43 | D95: =+D52+D55+D56 -> 5796.001 | E95: =+E52+E55+E56 -> 5510.974 | F95: =+F52+F55+F56 -> 4660.897 | G95: =+G52+G55+G56 -> 4449.466 | H95: =+H52+H55+H56 -> 5534.735 | I95: =+I52+I55+I56 -> 7107.653 | J95: =+J52+J55+J56 -> 5130.265 | ... O95: =+O52+O55+O56 -> 5081.739
A96: =+月次BS!A97 -> 0 | B96: その他流動負債 | C96: =+C57+C58+C59+C62 -> 794.047 | D96: =+D57+D58+D59+D62 -> 1345.698 | E96: =+E57+E58+E59+E62 -> 2661.018 | F96: =+F57+F58+F59+F62 -> 3584.37 | G96: =+G57+G58+G59+G62 -> 4798.191 | H96: =+H57+H58+H59+H62 -> 5405.819 | I96: =+I57+I58+I59+I62 -> 5942.674 | J96: =+J57+J58+J59+J62 -> 6745.458 | ... O96: =+O57+O58+O59+O62 -> 10735.477
A97: =+月次BS!A98 -> 0 | B97: 有形・無形固定資産 | C97: =+C33+C36 -> 57090.111 | D97: =+D33+D36 -> 56399.522 | E97: =+E33+E36 -> 55708.933 | F97: =+F33+F36 -> 55018.344 | G97: =+G33+G36 -> 54327.755 | H97: =+H33+H36 -> 53637.166 | I97: =+I33+I36 -> 53101.577 | J97: =+J33+J36 -> 52410.988 | ... O97: =+O33+O36 -> 48958.043
A98: =+月次BS!A99 -> 0 | B98: 長期借入金 | C98: =+C63+C67 -> 139240 | D98: =+D63+D67 -> 139005 | E98: =+E63+E67 -> 139005 | F98: =+F63+F67 -> 138535 | G98: =+G63+G67 -> 138300 | H98: =+H63+H67 -> 138300 | I98: =+I63+I67 -> 138065 | J98: =+J63+J67 -> 137830 | ... O98: =+O63+O67 -> 135225
A99: =+月次BS!A100 -> 0 | B99: =+月次BS!B100 -> 0 | C99: =+月次BS!C100/1000 -> 0 | D99: =+月次BS!D100/1000 -> 0 | E99: =+月次BS!E100/1000 -> 0 | F99: =+月次BS!F100/1000 -> 0 | G99: =+月次BS!G100/1000 -> 0 | H99: =+月次BS!H100/1000 -> 0 | I99: =+月次BS!I100/1000 -> 0 | J99: =+月次BS!J100/1000 -> 0 | ... O99: =+月次BS!O100/1000 -> 0
A100: =+月次BS!A101 -> 0 | B100: =+月次BS!B101 -> 0 | C100: =+月次BS!C101/1000 -> 0 | D100: =+月次BS!D101/1000 -> 0 | E100: =+月次BS!E101/1000 -> 0 | F100: =+月次BS!F101/1000 -> 0 | G100: =+月次BS!G101/1000 -> 0 | H100: =+月次BS!H101/1000 -> 0 | I100: =+月次BS!I101/1000 -> 0 | J100: =+月次BS!J101/1000 -> 0 | ... O100: =+月次BS!O101/1000 -> 0
A101: =+月次BS!A102 -> 0 | B101: =+月次BS!B102 -> 0 | C101: =+月次BS!C102/1000 -> 0 | D101: =+月次BS!D102/1000 -> 0 | E101: =+月次BS!E102/1000 -> 0 | F101: =+月次BS!F102/1000 -> 0 | G101: =+月次BS!G102/1000 -> 0 | H101: =+月次BS!H102/1000 -> 0 | I101: =+月次BS!I102/1000 -> 0 | J101: =+月次BS!J102/1000 -> 0 | ... O101: =+月次BS!O102/1000 -> 0
A102: =+月次BS!A103 -> 0 | B102: =+月次BS!B103 -> 0 | C102: =+月次BS!C103/1000 -> 0 | D102: =+月次BS!D103/1000 -> 0 | E102: =+月次BS!E103/1000 -> 0 | F102: =+月次BS!F103/1000 -> 0 | G102: =+月次BS!G103/1000 -> 0 | H102: =+月次BS!H103/1000 -> 0 | I102: =+月次BS!I103/1000 -> 0 | J102: =+月次BS!J103/1000 -> 0 | ... O102: =+月次BS!O103/1000 -> 0
A103: =+月次BS!A104 -> 0 | B103: =+月次BS!B104 -> 0 | C103: =+月次BS!C104/1000 -> 0 | D103: =+月次BS!D104/1000 -> 0 | E103: =+月次BS!E104/1000 -> 0 | F103: =+月次BS!F104/1000 -> 0 | G103: =+月次BS!G104/1000 -> 0 | H103: =+月次BS!H104/1000 -> 0 | I103: =+月次BS!I104/1000 -> 0 | J103: =+月次BS!J104/1000 -> 0 | ... O103: =+月次BS!O104/1000 -> 0

Sheet 月次PL
B1: 勘定科目 | C1: =+月次BS!D1 -> 7月 | D1: =+月次BS!E1 -> 8月 | E1: =+月次BS!F1 -> 9月 | F1: =+月次BS!G1 -> 10月 | G1: =+月次BS!H1 -> 11月 | H1: =+月次BS!I1 -> 12月 | I1: =+月次BS!J1 -> 1月 | J1: =+月次BS!K1 -> 2月 | ... N1: =+月次BS!O1 -> 6月 | O1: 累計
A2: 売上高
B3: レストラン売上 | C3: 7355981 | D3: 7304280 | E3: 6074830 | F3: 6161257 | G3: 6585842 | H3: 9980134 | I3: 6090480 | J3: 6446164 | K3: 6978449 | L3: 5291210 | M3: 5672033 | N3: 5536466 | O3: =SUM(C3:N3) -> 79477126
B4: 売上高 | C4: 1345240 | D4: 2064194 | E4: 1191395 | F4: 1562343 | G4: 1064084 | H4: 1117278 | I4: 1121936 | J4: 1038818 | K4: 1159845 | L4: 1371265 | M4: 1312243 | N4: 1560958 | O4: =SUM(C4:N4) -> 15909599
B5: 村売上 | C5: 573353 | D5: 597444 | E5: 601738 | F5: 580314 | G5: 531055 | H5: 557864 | I5: 589775 | J5: 596428 | K5: 606000 | L5: 541519 | M5: 611604 | N5: 599819 | O5: =SUM(C5:N5) -> 6986913
O6: =SUM(C6:N6) -> 0
B7: その他売上 | O7: =SUM(C7:N7) -> 0
A8: 売上高合計 | C8: =+SUM(C3:C7) -> 9274574 | D8: =+SUM(D3:D7) -> 9965918 | E8: =+SUM(E3:E7) -> 7867963 | F8: =+SUM(F3:F7) -> 8303914 | G8: =+SUM(G3:G7) -> 8180981 | H8: =+SUM(H3:H7) -> 11655276 | I8: =+SUM(I3:I7) -> 7802191 | J8: =+SUM(J3:J7) -> 8081410 | ... N8: =+SUM(N3:N7) -> 7697243 | O8: =SUM(C8:N8) -> 102373638
A9: 売上原価 | O9: =SUM(C9:N9) -> 0
B10: 期首商品棚卸高 | C10: 1324285 | D10: 0 | E10: 0 | F10: 0 | G10: 0 | H10: 0 | I10: 0 | J10: 0 | K10: 0 | L10: 0 | M10: 0 | N10: 0 | O10: =SUM(C10:N10) -> 1324285
B11: 飲料仕入 | C11: 1214302 | D11: 1229321 | E11: 954132 | F11: 932212 | G11: 1169442 | H11: 1618009 | I11: 930283 | J11: 1125121 | K11: 1394928 | L11: 1139680 | M11: 917541 | N11: 962022 | O11: =SUM(C11:N11) -> 13586993
B12: 食材仕入 | C12: 1056629 | D12: 718469 | E12: 681656 | F12: 731299 | G12: 770565 | H12: 1354437 | I12: 629051 | J12: 823087 | K12: 701327 | L12: 850444 | M12: 833116 | N12: 790187 | O12: =SUM(C12:N12) -> 9940267
B13: 仕入値引 | O13: =SUM(C13:N13) -> 0
B14: 期末商品棚卸高 | C14: 1460296 | D14: -171626 | E14: 29231 | F14: -37093 | G14: 159047 | H14: 237172 | I14: -171144 | J14: 78655 | K14: 68920 | L14: 11396 | M14: -231867 | N14: -113729 | O14: =SUM(C14:N14) -> 1319258
A15: 売上原価 | C15: =+C10+C11+C12-C13-C14 -> 2134920 | D15: =+D10+D11+D12-D13-D14 -> 2119416 | E15: =+E10+E11+E12-E13-E14 -> 1606557 | F15: =+F10+F11+F12-F13-F14 -> 1700604 | G15: =+G10+G11+G12-G13-G14 -> 1780960 | H15: =+H10+H11+H12-H13-H14 -> 2735274 | I15: =+I10+I11+I12-I13-I14 -> 1730478 | J15: =+J10+J11+J12-J13-J14 -> 1869553 | ... N15: =+N10+N11+N12-N13-N14 -> 1865938 | O15: =SUM(C15:N15) -> 23532287
A16: 売上総利益 | C16: =+C8-C15 -> 7139654 | D16: =+D8-D15 -> 7846502 | E16: =+E8-E15 -> 6261406 | F16: =+F8-F15 -> 6603310 | G16: =+G8-G15 -> 6400021 | H16: =+H8-H15 -> 8920002 | I16: =+I8-I15 -> 6071713 | J16: =+J8-J15 -> 6211857 | ... N16: =+N8-N15 -> 5831305 | O16: =SUM(C16:N16) -> 78841351
A17: 販売費及び一般管理費 | O17: =SUM(C17:N17) -> 0
B18: 役員報酬 | C18: 500000 | D18: 500000 | E18: 500000 | F18: 500000 | G18: 500000 | H18: 500000 | I18: 500000 | J18: 500000 | K18: 500000 | L18: 500000 | M18: 500000 | N18: 500000 | O18: =SUM(C18:N18) -> 6000000
B19: 給料賃金 | C19: 570000 | D19: 570000 | E19: 586976 | F19: 350000 | G19: 373907 | H19: 365819 | I19: 361841 | J19: 350000 | K19: 350000 | L19: 350000 | M19: 350000 | N19: 350000 | O19: =SUM(C19:N19) -> 4928543
B20: 賞与 | C20: 118179 | D20: 0 | E20: 0 | F20: 0 | G20: 0 | H20: 97731 | I20: 0 | J20: 0 | K20: 522000 | L20: 0 | M20: 0 | N20: 47416 | O20: =SUM(C20:N20) -> 785326
B21: 雑給 | C21: 647091 | D21: 807714 | E21: 675463 | F21: 959800 | G21: 956908 | H21: 1380581 | I21: 1454580 | J21: 1424401 | K21: 1277171 | L21: 1170281 | M21: 1166205 | N21: 1008651 | O21: =SUM(C21:N21) -> 12928846
B22: 法定福利費 | C22: 137656 | D22: 94370 | E22: 233530 | F22: 207842 | G22: 225657 | H22: 167438 | I22: 182465 | J22: 243096 | K22: 184662 | L22: 257785 | M22: 136927 | N22: 249802 | O22: =SUM(C22:N22) -> 2321230
B23: 福利厚生費 | C23: 0 | D23: 0 | E23: 0 | F23: 0 | G23: 50500 | H23: 5000 | I23: 0 | J23: 0 | K23: 0 | L23: 0 | M23: 0 | N23: 0 | O23: =SUM(C23:N23) -> 55500
B24: 業務委託費 | C24: 399020 | D24: 380774 | E24: 270522 | F24: 357924 | G24: 290836 | H24: 300039 | I24: 305298 | J24: 273130 | K24: 355882 | L24: 371731 | M24: 517264 | N24: 366911 | O24: =SUM(C24:N24) -> 4189331
B25: 広告宣伝費 | C25: 186903 | D25: 179400 | E25: 177560 | F25: 176503 | G25: 215303 | H25: 210153 | I25: 112000 | J25: 2162421 | K25: 108000 | L25: 100654 | M25: 134400 | N25: 123402 | O25: =SUM(C25:N25) -> 3886699
B26: 接待交際費 | O26: =SUM(C26:N26) -> 0
B27: 旅費交通費 | C27: 42401 | D27: 43147 | E27: 27646 | F27: 41601 | G27: 47715 | H27: 40511 | I27: 34183 | J27: 42182 | K27: 54459 | L27: 46858 | M27: 52253 | N27: 42731 | O27: =SUM(C27:N27) -> 515687
B28: 通信費 | C28: 45779 | D28: 55395 | E28: 45570 | F28: 44794 | G28: 52175 | H28: 40364 | I28: 54262 | J28: 70983 | K28: 54590 | L28: 122039 | M28: 54629 | N28: 51282 | O28: =SUM(C28:N28) -> 691862
B29: 水道光熱費 | C29: 1055015 | D29: 1104210 | E29: 968209 | F29: 757600 | G29: 878364 | H29: 1110021 | I29: 1144612 | J29: 1235761 | K29: 1093647 | L29: 804331 | M29: 719828 | N29: 852493 | O29: =SUM(C29:N29) -> 11724091
B30: 修繕費 | C30: 13500 | D30: 57300 | E30: 15000 | F30: 0 | G30: 20000 | H30: 19000 | I30: 17000 | J30: 90910 | K30: 0 | L30: 0 | M30: 0 | N30: 15000 | O30: =SUM(C30:N30) -> 247710
B31: 消耗品費 | C31: 332272 | D31: 162804 | E31: 154474 | F31: 229112 | G31: 153400 | H31: 227238 | I31: 157253 | J31: 203697 | K31: 158297 | L31: 160095 | M31: 127598 | N31: 280820 | O31: =SUM(C31:N31) -> 2347060
B32: リース料 | C32: 49700 | D32: 49700 | E32: 49700 | F32: 49700 | G32: 49700 | H32: 49700 | I32: 49700 | J32: 49700 | K32: 49700 | L32: 49700 | M32: 77900 | N32: 49700 | O32: =SUM(C32:N32) -> 624600
B33: 地代家賃 | C33: 1645661 | D33: 1645661 | E33: 1645661 | F33: 1645661 | G33: 1645661 | H33: 1645661 | I33: 1645661 | J33: 1645661 | K33: 1645661 | L33: 1645661 | M33: 1645661 | N33: 1645661 | O33: =SUM(C33:N33) -> 19747932
B34: 賃借料 | C34: 30000 | D34: 30000 | E34: 30000 | F34: 30000 | G34: 30000 | H34: 30000 | I34: 30000 | J34: 30000 | K34: 30000 | L34: 30000 | M34: 30000 | N34: 30000 | O34: =SUM(C34:N34) -> 360000
B35: 保険料 | C35: 22215 | D35: 22215 | E35: 22215 | F35: 22215 | G35: 22215 | H35: 28375 | I35: 28375 | J35: 28375 | K35: 28375 | L35: 28375 | M35: 28375 | N35: 28375 | O35: =SUM(C35:N35) -> 309700
B36: 租税公課 | C36: 146000 | D36: 1000 | E36: 147000 | F36: 0 | G36: 2450 | H36: 148000 | I36: 0 | J36: 0 | K36: 1000 | L36: 125900 | M36: 0 | N36: 1000 | O36: =SUM(C36:N36) -> 572350
B37: 支払手数料 | C37: 238917 | D37: 268309 | E37: 276554 | F37: 224363 | G37: 226852 | H37: 264110 | I37: 245928 | J37: 218075 | K37: 308807 | L37: 185840 | M37: 193092 | N37: 243661 | O37: =SUM(C37:N37) -> 2894508
B38: 会議費 | C38: 0 | D38: 0 | E38: 0 | F38: 0 | G38: 0 | H38: 0 | I38: 0 | J38: 0 | K38: 0 | O38: =SUM(C38:N38) -> 0
B39: 新聞図書費 | C39: 2593 | D39: 0 | E39: 0 | F39: 0 | G39: 0 | H39: 0 | I39: 0 | J39: 0 | K39: 0 | L39: 0 | M39: 0 | O39: =SUM(C39:N39) -> 2593
B40: 減価償却費 | C40: 690589 | D40: 690589 | E40: 690589 | F40: 690589 | G40: 690589 | H40: 690589 | I40: 690589 | J40: 690589 | K40: 690589 | L40: 690589 | M40: 690589 | N40: 690589 | O40: =SUM(C40:N40) -> 8287068
B41: 雑費 | C41: 64599 | D41: 47521 | E41: 42600 | F41: 71639 | G41: 42720 | H41: 42240 | I41: 71158 | J41: 41880 | K41: 62280 | L41: 108288 | M41: 38870 | N41: 58990 | O41: =SUM(C41:N41) -> 692785
B42: 管理諸費 | C42: 70000 | D42: 70000 | E42: 280000 | F42: 70000 | G42: 110000 | H42: 70000 | I42: 70000 | J42: 70000 | K42: 70000 | L42: 70000 | M42: 70000 | N42: 70000 | O42: =SUM(C42:N42) -> 1090000
B43: 開発費 | C43: 21289 | D43: 97177 | E43: 106992 | F43: 148075 | G43: 79685 | H43: 0 | I43: 0 | J43: 0 | K43: 0 | L43: 0 | M43: 0 | N43: 0 | O43: =SUM(C43:N43) -> 453218
A44: 販売費及び一般管理費合計 | C44: =SUM(C18:C43) -> 7029379 | D44: =SUM(D18:D43) -> 6877286 | E44: =SUM(E18:E43) -> 6946261 | F44: =SUM(F18:F43) -> 6577418 | G44: =SUM(G18:G43) -> 6664637 | H44: =SUM(H18:H43) -> 7432570 | I44: =SUM(I18:I43) -> 7154905 | J44: =SUM(J18:J43) -> 9370861 | ... N44: =SUM(N18:N43) -> 6706484 | O44: =SUM(C44:N44) -> 85656639
A45: 営業利益 | C45: =+C16-C44 -> 110275 | D45: =+D16-D44 -> 969216 | E45: =+E16-E44 -> -684855 | F45: =+F16-F44 -> 25892 | G45: =+G16-G44 -> -264616 | H45: =+H16-H44 -> 1487432 | I45: =+I16-I44 -> -1083192 | J45: =+J16-J44 -> -3159004 | ... N45: =+N16-N44 -> -875179 | O45: =SUM(C45:N45) -> -6815288
A46: 営業外収益 | O46: =SUM(C46:N46) -> 0
B47: 受取利息 | C47: 0 | D47: 33390 | E47: 1 | F47: 0 | G47: 0 | H47: 0 | I47: 0 | J47: 33136 | K47: 1 | L47: 0 | M47: 0 | N47: 0 | O47: =SUM(C47:N47) -> 66528
B48: 受取配当金 | C48: 0 | D48: 0 | E48: 0 | F48: 0 | G48: 0 | H48: 0 | I48: 0 | J48: 0 | K48: 0 | L48: 0 | M48: 0 | N48: 239 | O48: =SUM(C48:N48) -> 239
B49: 雑収入 | C49: 0 | D49: 0 | E49: 403668 | F49: 0 | G49: 0 | H49: 0 | I49: 0 | J49: 0 | K49: 1000000 | L49: 0 | M49: 400000 | N49: 0 | O49: =SUM(C49:N49) -> 1803668
A50: 営業外収益合計 | C50: 0 | D50: 33390 | E50: 403669 | F50: 0 | G50: 0 | H50: 0 | I50: 0 | J50: 33136 | K50: 1000001 | L50: 0 | M50: 400000 | N50: 239 | O50: =SUM(C50:N50) -> 1870435
A51: 営業外費用 | O51: =SUM(C51:N51) -> 0
B52: 支払利息 | C52: 147962 | D52: 82191 | E52: 206056 | F52: 152448 | G52: 71670 | H52: 62784 | I52: 148217 | J52: 130729 | K52: 199645 | L52: 140445 | M52: 81533 | N52: 120911 | O52: =SUM(C52:N52) -> 1544591
B53: 雑損失 | C53: 0 | D53: 0 | E53: 0 | F53: 0 | G53: 760 | H53: 11700 | I53: 0 | J53: 0 | K53: 0 | L53: 3000 | M53: 0 | N53: 6250 | O53: =SUM(C53:N53) -> 21710
B54: 補助事業費 | O54: =SUM(C54:N54) -> 0
A55: 営業外費用合計 | C55: 147962 | D55: 82191 | E55: 206056 | F55: 152448 | G55: 72430 | H55: 74484 | I55: 148217 | J55: 130729 | K55: 199645 | L55: 143445 | M55: 81533 | N55: 127161 | O55: =SUM(C55:N55) -> 1566301
A56: 経常利益 | C56: =+C45+C50-C55 -> -37687 | D56: =+D45+D50-D55 -> 920415 | E56: =+E45+E50-E55 -> -487242 | F56: =+F45+F50-F55 -> -126556 | G56: =+G45+G50-G55 -> -337046 | H56: =+H45+H50-H55 -> 1412948 | I56: =+I45+I50-I55 -> -1231409 | J56: =+J45+J50-J55 -> -3256597 | ... N56: =+N45+N50-N55 -> -1002101 | O56: =SUM(C56:N56) -> -6511154
A57: 特別利益 | O57: =SUM(C57:N57) -> 0
A58: 特別利益合計 | O58: =SUM(C58:N58) -> 0
A59: 特別損失 | O59: =SUM(C59:N59) -> 0
A60: 特別損失合計 | O60: =SUM(C60:N60) -> 0
A61: 当期純損益 | O61: =SUM(C61:N61) -> 0
A62: 税引前当期純利益 | C62: =+C56+C58-C60 -> -37687 | D62: =+D56+D58-D60 -> 920415 | E62: =+E56+E58-E60 -> -487242 | F62: =+F56+F58-F60 -> -126556 | G62: =+G56+G58-G60 -> -337046 | H62: =+H56+H58-H60 -> 1412948 | I62: =+I56+I58-I60 -> -1231409 | J62: =+J56+J58-J60 -> -3256597 | ... N62: =+N56+N58-N60 -> -1002101 | O62: =SUM(C62:N62) -> -6511154
B63: 法人税等 | C63: 0 | D63: 0 | E63: 0 | F63: 0 | G63: 0 | H63: 0 | I63: 0 | J63: 0 | O63: =SUM(C63:N63) -> 0
A64: 当期純利益 | C64: =+C62-C63 -> -37687 | D64: =+D62-D63 -> 920415 | E64: =+E62-E63 -> -487242 | F64: =+F62-F63 -> -126556 | G64: =+G62-G63 -> -337046 | H64: =+H62-H63 -> 1412948 | I64: =+I62-I63 -> -1231409 | J64: =+J62-J63 -> -3256597 | ... N64: =+N62-N63 -> -1002101 | O64: =SUM(C64:N64) -> -6511154

Sheet PL推移
B2: CK | C2: 売上高 | D2: =IF(D10<>0,IF(D10=月次PL!C8/1000,"OK",PL推移!D10-月次PL!C8/1000),"nd") -> OK | F2: =IF(F10<>0,IF(月次PL!D8/1000=PL推移!F10,"OK",PL推移!F10-月次PL!D8/1000),"nd") -> OK | H2: =IF(H10<>0,IF(月次PL!E8/1000=PL推移!H10,"OK",PL推移!H10-月次PL!E8/1000),"nd") -> OK | J2: =IF(J10<>0,IF(月次PL!F8/1000=PL推移!J10,"OK",PL推移!J10-月次PL!F8/1000),"nd") -> OK | L2: =IF(L10<>0,IF(月次PL!G8/1000=PL推移!L10,"OK",PL推移!L10-月次PL!G8/1000),"nd") -> OK | N2: =IF(N10<>0,IF(月次PL!H8/1000=PL推移!N10,"OK",PL推移!N10-月次PL!H8/1000),"nd") -> OK | P2: =IF(P10<>0,IF(月次PL!I8/1000=PL推移!P10,"OK",PL推移!P10-月次PL!I8/1000),"nd") -> OK | R2: =IF(R10<>0,IF(月次PL!J8/1000=PL推移!R10,"OK",PL推移!R10-月次PL!J8/1000),"nd") -> OK | T2: =IF(T10<>0,IF(月次PL!K8/1000=PL推移!T10,"OK",PL推移!T10-月次PL!K8/1000),"nd") -> 1.706 | V2: =IF(V10<>0,IF(月次PL!L8/1000=PL推移!V10,"OK",PL推移!V10-月次PL!L8/1000),"nd") -> OK | X2: =IF(X10<>0,IF(月次PL!M8/1000=PL推移!X10,"OK",PL推移!X10-月次PL!M8/1000),"nd") -> OK | Z2: =IF(Z10<>0,IF(月次PL!N8/1000=PL推移!Z10,"OK",PL推移!Z10-月次PL!N8/1000),"nd") -> OK
C3: 粗利益 | D3: =IF(D22<>0,IF(D22=月次PL!C16/1000,"OK",PL推移!D22-月次PL!C16/1000),"nd") -> OK | F3: =IF(F22<>0,IF(F22=月次PL!D16/1000,"OK",PL推移!F22-月次PL!D16/1000),"nd") -> OK | H3: =IF(H22<>0,IF(H22=月次PL!E16/1000,"OK",PL推移!H22-月次PL!E16/1000),"nd") -> OK | J3: =IF(J22<>0,IF(J22=月次PL!F16/1000,"OK",PL推移!J22-月次PL!F16/1000),"nd") -> OK | L3: =IF(L22<>0,IF(L22=月次PL!G16/1000,"OK",PL推移!L22-月次PL!G16/1000),"nd") -> OK | N3: =IF(N22<>0,IF(N22=月次PL!H16/1000,"OK",PL推移!N22-月次PL!H16/1000),"nd") -> OK | P3: =IF(P22<>0,IF(P22=月次PL!I16/1000,"OK",PL推移!P22-月次PL!I16/1000),"nd") -> OK | R3: =IF(R22<>0,IF(R22=月次PL!J16/1000,"OK",PL推移!R22-月次PL!J16/1000),"nd") -> OK | T3: =IF(T22<>0,IF(T22=月次PL!K16/1000,"OK",PL推移!T22-月次PL!K16/1000),"nd") -> 1.706 | V3: =IF(V22<>0,IF(V22=月次PL!L16/1000,"OK",PL推移!V22-月次PL!L16/1000),"nd") -> OK | X3: =IF(X22<>0,IF(X22=月次PL!M16/1000,"OK",PL推移!X22-月次PL!M16/1000),"nd") -> OK | Z3: =IF(Z22<>0,IF(Z22=月次PL!N16/1000,"OK",PL推移!Z22-月次PL!N16/1000),"nd") -> OK
C4: 販管費 | D4: =IF(D28<>0,IF(D28=月次PL!C44/1000,"OK",PL推移!D28-月次PL!C44/1000),"nd") -> OK | F4: =IF(F28<>0,IF(F28=月次PL!D44/1000,"OK",PL推移!F28-月次PL!D44/1000),"nd") -> OK | H4: =IF(H28<>0,IF(H28=月次PL!E44/1000,"OK",PL推移!H28-月次PL!E44/1000),"nd") -> OK | J4: =IF(J28<>0,IF(J28=月次PL!F44/1000,"OK",PL推移!J28-月次PL!F44/1000),"nd") -> OK | L4: =IF(L28<>0,IF(L28=月次PL!G44/1000,"OK",PL推移!L28-月次PL!G44/1000),"nd") -> OK | N4: =IF(N28<>0,IF(N28=月次PL!H44/1000,"OK",PL推移!N28-月次PL!H44/1000),"nd") -> OK | P4: =IF(P28<>0,IF(P28=月次PL!I44/1000,"OK",PL推移!P28-月次PL!I44/1000),"nd") -> OK | R4: =IF(R28<>0,IF(R28=月次PL!J44/1000,"OK",PL推移!R28-月次PL!J44/1000),"nd") -> OK | T4: =IF(T28<>0,IF(T28=月次PL!K44/1000,"OK",PL推移!T28-月次PL!K44/1000),"nd") -> OK | V4: =IF(V28<>0,IF(V28=月次PL!L44/1000,"OK",PL推移!V28-月次PL!L44/1000),"nd") -> OK | X4: =IF(X28<>0,IF(X28=月次PL!M44/1000,"OK",PL推移!X28-月次PL!M44/1000),"nd") -> OK | Z4: =IF(Z28<>0,IF(Z28=月次PL!N44/1000,"OK",PL推移!Z28-月次PL!N44/1000),"nd") -> OK
C5: 営業利益 | D5: =IF(D50<>0,IF(D50=月次PL!C45/1000,"OK",PL推移!D50-月次PL!C45/1000),"nd") -> OK | F5: =IF(F50<>0,IF(F50=月次PL!D45/1000,"OK",PL推移!F50-月次PL!D45/1000),"nd") -> -5.6843419e-13 | H5: =IF(H50<>0,IF(H50=月次PL!E45/1000,"OK",PL推移!H50-月次PL!E45/1000),"nd") -> -1.3642421e-12 | J5: =IF(J50<>0,IF(J50=月次PL!F45/1000,"OK",PL推移!J50-月次PL!F45/1000),"nd") -> -1.7408297e-13 | L5: =IF(L50<>0,IF(L50=月次PL!G45/1000,"OK",PL推移!L50-月次PL!G45/1000),"nd") -> OK | N5: =IF(N50<>0,IF(N50=月次PL!H45/1000,"OK",PL推移!N50-月次PL!H45/1000),"nd") -> OK | P5: =IF(P50<>0,IF(P50=月次PL!I45/1000,"OK",PL推移!P50-月次PL!I45/1000),"nd") -> OK | R5: =IF(R50<>0,IF(R50=月次PL!J45/1000,"OK",PL推移!R50-月次PL!J45/1000),"nd") -> OK | T5: =IF(T50<>0,IF(T50=月次PL!K45/1000,"OK",PL推移!T50-月次PL!K45/1000),"nd") -> 1.706 | V5: =IF(V50<>0,IF(V50=月次PL!L45/1000,"OK",PL推移!V50-月次PL!L45/1000),"nd") -> OK | X5: =IF(X50<>0,IF(X50=月次PL!M45/1000,"OK",PL推移!X50-月次PL!M45/1000),"nd") -> 1.2505552e-12 | Z5: =IF(Z50<>0,IF(Z50=月次PL!N45/1000,"OK",PL推移!Z50-月次PL!N45/1000),"nd") -> OK
C6: 経常利益 | D6: =IF(D54<>0,IF(D54=月次PL!C56/1000,"OK",PL推移!D54-月次PL!C56/1000),"nd") -> -3.5527137e-13 | F6: =IF(F54<>0,IF(F54=月次PL!D56/1000,"OK",PL推移!F54-月次PL!D56/1000),"nd") -> -5.6843419e-13 | H6: =IF(H54<>0,IF(H54=月次PL!E56/1000,"OK",PL推移!H54-月次PL!E56/1000),"nd") -> -1.4210855e-12 | J6: =IF(J54<>0,IF(J54=月次PL!F56/1000,"OK",PL推移!J54-月次PL!F56/1000),"nd") -> OK | L6: =IF(L54<>0,IF(L54=月次PL!G56/1000,"OK",PL推移!L54-月次PL!G56/1000),"nd") -> OK | N6: =IF(N54<>0,IF(N54=月次PL!H56/1000,"OK",PL推移!N54-月次PL!H56/1000),"nd") -> OK | P6: =IF(P54<>0,IF(P54=月次PL!I56/1000,"OK",PL推移!P54-月次PL!I56/1000),"nd") -> OK | R6: =IF(R54<>0,IF(R54=月次PL!J56/1000,"OK",PL推移!R54-月次PL!J56/1000),"nd") -> OK | T6: =IF(T54<>0,IF(T54=月次PL!K56/1000,"OK",PL推移!T54-月次PL!K56/1000),"nd") -> 1.706 | V6: =IF(V54<>0,IF(V54=月次PL!L56/1000,"OK",PL推移!V54-月次PL!L56/1000),"nd") -> OK | X6: =IF(X54<>0,IF(X54=月次PL!M56/1000,"OK",PL推移!X54-月次PL!M56/1000),"nd") -> 1.2505552e-12 | Z6: =IF(Z54<>0,IF(Z54=月次PL!N56/1000,"OK",PL推移!Z54-月次PL!N56/1000),"nd") -> OK
B7: ■月次報告PL | D7: ㈱ｅｓエンターテイメント
B8: 2025 | C8: 年度 | D8: 単位：千円 | F8: 注意事項 | G8: 概算値 | H8: 異常値 | I8: 処理検討 | J8: 予算検討
B9: 項目 | D9: =+月次PL!C1 -> 7月 | F9: =+月次PL!D1 -> 8月 | H9: =+月次PL!E1 -> 9月 | J9: =+月次PL!F1 -> 10月 | L9: =+月次PL!G1 -> 11月 | N9: =+月次PL!H1 -> 12月 | P9: =+月次PL!I1 -> 1月 | R9: =+月次PL!J1 -> 2月 | T9: =+月次PL!K1 -> 3 | V9: =+月次PL!L1 -> 4 | X9: =+月次PL!M1 -> 5月 | Z9: =+月次PL!N1 -> 6月
B10: 売上高 | D10: =+月次PL!C8/1000 -> 9274.574 | E10: =IF(D$10<>0,D10/D$10,0) -> 1 | F10: =+月次PL!D8/1000 -> 9965.918 | G10: =IF(F$10<>0,F10/F$10,0) -> 1 | H10: =+月次PL!E8/1000 -> 7867.963 | I10: =IF(H$10<>0,H10/H$10,0) -> 1 | J10: =+月次PL!F8/1000 -> 8303.914 | K10: =IF(J$10<>0,J10/J$10,0) -> 1 | L10: =+月次PL!G8/1000 -> 8180.981 | M10: =IF(L$10<>0,L10/L$10,0) -> 1 | N10: =+月次PL!H8/1000 -> 11655.276 | O10: =IF(N$10<>0,N10/N$10,0) -> 1 | P10: =+月次PL!I8/1000 -> 7802.191 | Q10: =IF(P$10<>0,P10/P$10,0) -> 1 | R10: =+月次PL!J8/1000 -> 8081.41 | S10: =IF(R$10<>0,R10/R$10,0) -> 1 | T10: =SUM(T11:T15)+350-11 -> 8746 | U10: =IF(T$10<>0,T10/T$10,0) -> 1 | V10: =+月次PL!L8/1000 -> 7203.994 | W10: =IF(V$10<>0,V10/V$10,0) -> 1 | X10: =+月次PL!M8/1000 -> 7595.88 | Y10: =IF(X$10<>0,X10/X$10,0) -> 1 | Z10: =+月次PL!N8/1000 -> 7697.243 | AA10: =IF(Z$10<>0,Z10/Z$10,0) -> 1
C11: 恵愛 | D11: 6973 | E11: =IF(D$10<>0,D11/D$10,0) -> 0.75184046 | F11: 6864 | G11: =IF(F$10<>0,F11/F$10,0) -> 0.68874739 | H11: 5812 | I11: =IF(H$10<>0,H11/H$10,0) -> 0.73869183 | J11: 5700 | K11: =IF(J$10<>0,J11/J$10,0) -> 0.68642329 | L11: 6255 | M11: =IF(L$10<>0,L11/L$10,0) -> 0.76457823 | N11: 9574 | O11: =IF(N$10<>0,N11/N$10,0) -> 0.82143057 | P11: 5703 | Q11: =IF(P$10<>0,P11/P$10,0) -> 0.73094852 | R11: 6142 | S11: =IF(R$10<>0,R11/R$10,0) -> 0.76001589 | T11: 6615 | U11: =IF(T$10<>0,T11/T$10,0) -> 0.75634576 | V11: 4998 | W11: =IF(V$10<>0,V11/V$10,0) -> 0.69378181 | X11: 5401 | Y11: =IF(X$10<>0,X11/X$10,0) -> 0.71104336 | Z11: 5367 | AA11: =IF(Z$10<>0,Z11/Z$10,0) -> 0.69726264
C12: 村 | D12: 573 | E12: =IF(D$10<>0,D12/D$10,0) -> 0.061781813 | F12: 597 | G12: =IF(F$10<>0,F12/F$10,0) -> 0.059904165 | H12: 602 | I12: =IF(H$10<>0,H12/H$10,0) -> 0.076512815 | J12: 580 | K12: =IF(J$10<>0,J12/J$10,0) -> 0.069846581 | L12: 531 | M12: =IF(L$10<>0,L12/L$10,0) -> 0.064906641 | N12: 558 | O12: =IF(N$10<>0,N12/N$10,0) -> 0.047875314 | P12: 590 | Q12: =IF(P$10<>0,P12/P$10,0) -> 0.075619784 | R12: 596 | S12: =IF(R$10<>0,R12/R$10,0) -> 0.073749507 | T12: 606 | U12: =IF(T$10<>0,T12/T$10,0) -> 0.069288818 | V12: 541 | W12: =IF(V$10<>0,V12/V$10,0) -> 0.075097231 | X12: 611 | Y12: =IF(X$10<>0,X12/X$10,0) -> 0.080438343 | Z12: 600 | AA12: =IF(Z$10<>0,Z12/Z$10,0) -> 0.077949988
C13: 弁当 | D13: 464 | E13: =IF(D$10<>0,D13/D$10,0) -> 0.050029252 | F13: 361 | G13: =IF(F$10<>0,F13/F$10,0) -> 0.036223457 | H13: 266 | I13: =IF(H$10<>0,H13/H$10,0) -> 0.033807988 | J13: 209 | K13: =IF(J$10<>0,J13/J$10,0) -> 0.025168854 | L13: 279 | M13: =IF(L$10<>0,L13/L$10,0) -> 0.03410349 | N13: 318 | O13: =IF(N$10<>0,N13/N$10,0) -> 0.027283781 | P13: 337 | Q13: =IF(P$10<>0,P13/P$10,0) -> 0.043192995 | R13: 243 | S13: =IF(R$10<>0,R13/R$10,0) -> 0.03006901 | T13: 371 | U13: =IF(T$10<>0,T13/T$10,0) -> 0.042419392 | V13: 421 | W13: =IF(V$10<>0,V13/V$10,0) -> 0.058439804 | X13: 460 | Y13: =IF(X$10<>0,X13/X$10,0) -> 0.060559145 | Z13: 444 | AA13: =IF(Z$10<>0,Z13/Z$10,0) -> 0.057682991 | AB13: =+D13+F13+H13+J13+L13+N13+P13+R13+T13 -> 2848
C14: シェア | D14: 129 | E14: =IF(D$10<>0,D14/D$10,0) -> 0.013908995 | F14: 180 | G14: =IF(F$10<>0,F14/F$10,0) -> 0.018061557 | H14: 72 | I14: =IF(H$10<>0,H14/H$10,0) -> 0.0091510344 | J14: 283 | K14: =IF(J$10<>0,J14/J$10,0) -> 0.034080314 | L14: 123 | M14: =IF(L$10<>0,L14/L$10,0) -> 0.015034872 | N14: 131 | O14: =IF(N$10<>0,N14/N$10,0) -> 0.011239545 | P14: 106 | Q14: =IF(P$10<>0,P14/P$10,0) -> 0.013585927 | R14: 90 | S14: =IF(R$10<>0,R14/R$10,0) -> 0.01113667 | T14: 125 | U14: =IF(T$10<>0,T14/T$10,0) -> 0.014292248 | V14: 100 | W14: =IF(V$10<>0,V14/V$10,0) -> 0.013881189 | X14: 83 | Y14: =IF(X$10<>0,X14/X$10,0) -> 0.010926976 | Z14: 75 | AA14: =IF(Z$10<>0,Z14/Z$10,0) -> 0.0097437485
C15: サウナ | D15: 786 | E15: =IF(D$10<>0,D15/D$10,0) -> 0.084747828 | F15: 1614 | G15: =IF(F$10<>0,F15/F$10,0) -> 0.16195196 | H15: 765 | I15: =IF(H$10<>0,H15/H$10,0) -> 0.09722974 | J15: 1191 | K15: =IF(J$10<>0,J15/J$10,0) -> 0.14342634 | L15: 643 | M15: =IF(L$10<>0,L15/L$10,0) -> 0.078596931 | N15: 1021 | O15: =IF(N$10<>0,N15/N$10,0) -> 0.087599813 | P15: 716 | Q15: =IF(P$10<>0,P15/P$10,0) -> 0.091769094 | R15: 646 | S15: =IF(R$10<>0,R15/R$10,0) -> 0.079936546 | T15: 690 | U15: =IF(T$10<>0,T15/T$10,0) -> 0.078893208 | V15: 604 | W15: =IF(V$10<>0,V15/V$10,0) -> 0.08384238 | X15: 553 | Y15: =IF(X$10<>0,X15/X$10,0) -> 0.072802625 | Z15: 565 | AA15: =IF(Z$10<>0,Z15/Z$10,0) -> 0.073402905
B16: 売上原価 | D16: =+月次PL!C15/1000 -> 2134.92 | E16: =IF(D$10<>0,D16/D$10,0) -> 0.23019063 | F16: =+月次PL!D15/1000 -> 2119.416 | G16: =IF(F$10<>0,F16/F$10,0) -> 0.21266641 | H16: =+月次PL!E15/1000 -> 1606.557 | I16: =IF(H$10<>0,H16/H$10,0) -> 0.2041897 | J16: =+月次PL!F15/1000 -> 1700.604 | K16: =IF(J$10<>0,J16/J$10,0) -> 0.20479547 | L16: =+月次PL!G15/1000 -> 1780.96 | M16: =IF(L$10<>0,L16/L$10,0) -> 0.21769516 | N16: =+月次PL!H15/1000 -> 2735.274 | O16: =IF(N$10<>0,N16/N$10,0) -> 0.23468119 | P16: =+月次PL!I15/1000 -> 1730.478 | Q16: =IF(P$10<>0,P16/P$10,0) -> 0.22179385 | R16: =+月次PL!J15/1000 -> 1869.553 | S16: =IF(R$10<>0,R16/R$10,0) -> 0.23133995 | T16: =+月次PL!K15/1000 -> 2027.335 | U16: =IF(T$10<>0,T16/T$10,0) -> 0.23180139 | V16: =+月次PL!L15/1000 -> 1978.728 | W16: =IF(V$10<>0,V16/V$10,0) -> 0.27467097 | X16: =+月次PL!M15/1000 -> 1982.524 | Y16: =IF(X$10<>0,X16/X$10,0) -> 0.26099991 | Z16: =+月次PL!N15/1000 -> 1865.938 | AA16: =IF(Z$10<>0,Z16/Z$10,0) -> 0.24241641
C17: =+C11 -> 恵愛 | D17: 1815 | E17: =IF(D11<>0,D17/D11,0) -> 0.26028969 | F17: 1783 | G17: =IF(F11<>0,F17/F11,0) -> 0.25976107 | H17: 1374 | I17: =IF(H11<>0,H17/H11,0) -> 0.23640743 | J17: 1329 | K17: =IF(J11<>0,J17/J11,0) -> 0.23315789 | L17: 1535 | M17: =IF(L11<>0,L17/L11,0) -> 0.24540368 | N17: 2301 | O17: =IF(N11<>0,N17/N11,0) -> 0.24033842 | P17: 1459 | Q17: =IF(P11<>0,P17/P11,0) -> 0.25583026 | R17: 1573 | S17: =IF(R11<>0,R17/R11,0) -> 0.2561055 | T17: 1698 | U17: =IF(T11<>0,T17/T11,0) -> 0.25668934 | V17: 1609 | W17: =IF(V11<>0,V17/V11,0) -> 0.32192877 | X17: 1737 | Y17: =IF(X11<>0,X17/X11,0) -> 0.32160711 | Z17: 1556 | AA17: =IF(Z11<>0,Z17/Z11,0) -> 0.28991988
C18: =+C12 -> 村 | D18: 65 | E18: =IF(D12<>0,D18/D12,0) -> 0.11343805 | F18: 78 | G18: =IF(F12<>0,F18/F12,0) -> 0.13065327 | H18: 59 | I18: =IF(H12<>0,H18/H12,0) -> 0.098006645 | J18: 145 | K18: =IF(J12<>0,J18/J12,0) -> 0.25 | L18: 69 | M18: =IF(L12<>0,L18/L12,0) -> 0.1299435 | N18: 142 | O18: =IF(N12<>0,N18/N12,0) -> 0.25448029 | P18: 87 | Q18: =IF(P12<>0,P18/P12,0) -> 0.14745763 | R18: 100 | S18: =IF(R12<>0,R18/R12,0) -> 0.16778523 | T18: 110 | U18: =IF(T12<>0,T18/T12,0) -> 0.18151815 | V18: 135 | W18: =IF(V12<>0,V18/V12,0) -> 0.24953789 | X18: 102 | Y18: =IF(X12<>0,X18/X12,0) -> 0.16693944 | Z18: 66 | AA18: =IF(Z12<>0,Z18/Z12,0) -> 0.11
C19: =+C13 -> 弁当 | D19: 148 | E19: =IF(D13<>0,D19/D13,0) -> 0.31896552 | F19: 158 | G19: =IF(F13<>0,F19/F13,0) -> 0.43767313 | H19: 135 | I19: =IF(H13<>0,H19/H13,0) -> 0.5075188 | J19: 100 | K19: =IF(J13<>0,J19/J13,0) -> 0.4784689 | L19: 133 | M19: =IF(L13<>0,L19/L13,0) -> 0.47670251 | N19: 129 | O19: =IF(N13<>0,N19/N13,0) -> 0.40566038 | P19: 148 | Q19: =IF(P13<>0,P19/P13,0) -> 0.43916914 | R19: 130 | S19: =IF(R13<>0,R19/R13,0) -> 0.53497942 | T19: 148 | U19: =IF(T13<>0,T19/T13,0) -> 0.39892183 | V19: 163 | W19: =IF(V13<>0,V19/V13,0) -> 0.3871734 | X19: 131 | Y19: =IF(X13<>0,X19/X13,0) -> 0.28478261 | Z19: 197 | AA19: =IF(Z13<>0,Z19/Z13,0) -> 0.44369369 | AB19: =+D19+F19+H19+J19+L19+N19+P19+R19+T19 -> 1229 | AC19: =+AB19/AB13 -> 0.4315309
C20: =+C14 -> シェア | D20: 39 | E20: =IF(D14<>0,D20/D14,0) -> 0.30232558 | F20: 54 | G20: =IF(F14<>0,F20/F14,0) -> 0.3 | H20: 22 | I20: =IF(H14<>0,H20/H14,0) -> 0.30555556 | J20: 84 | K20: =IF(J14<>0,J20/J14,0) -> 0.29681979 | L20: 37 | M20: =IF(L14<>0,L20/L14,0) -> 0.30081301 | N20: 44 | O20: =IF(N14<>0,N20/N14,0) -> 0.33587786 | P20: 32 | Q20: =IF(P14<>0,P20/P14,0) -> 0.30188679 | R20: 27 | S20: =IF(R14<>0,R20/R14,0) -> 0.3 | T20: 38 | U20: =IF(T14<>0,T20/T14,0) -> 0.304 | V20: 30 | W20: =IF(V14<>0,V20/V14,0) -> 0.3 | X20: 25 | Y20: =IF(X14<>0,X20/X14,0) -> 0.30120482 | Z20: 22 | AA20: =IF(Z14<>0,Z20/Z14,0) -> 0.29333333
C21: =+C15 -> サウナ | D21: 67 | E21: =IF(D15<>0,D21/D15,0) -> 0.08524173 | F21: 45 | G21: =IF(F15<>0,F21/F15,0) -> 0.027881041 | H21: 6 | I21: =IF(H15<>0,H21/H15,0) -> 0.0078431373 | J21: 41 | K21: =IF(J15<>0,J21/J15,0) -> 0.034424853 | L21: 6 | M21: =IF(L15<>0,L21/L15,0) -> 0.0093312597 | N21: 28 | O21: =IF(N15<>0,N21/N15,0) -> 0.027424094 | P21: 4 | Q21: =IF(P15<>0,P21/P15,0) -> 0.0055865922 | R21: 39 | S21: =IF(R15<>0,R21/R15,0) -> 0.060371517 | T21: 35 | U21: =IF(T15<>0,T21/T15,0) -> 0.050724638 | V21: 23 | W21: =IF(V15<>0,V21/V15,0) -> 0.03807947 | X21: 21 | Y21: =IF(X15<>0,X21/X15,0) -> 0.037974684 | Z21: 24 | AA21: =IF(Z15<>0,Z21/Z15,0) -> 0.042477876
B22: 粗利益 | D22: =+D10-D16 -> 7139.654 | E22: =IF(D$10<>0,D22/D$10,0) -> 0.76980937 | F22: =+F10-F16 -> 7846.502 | G22: =IF(F$10<>0,F22/F$10,0) -> 0.78733359 | H22: =+H10-H16 -> 6261.406 | I22: =IF(H$10<>0,H22/H$10,0) -> 0.7958103 | J22: =+J10-J16 -> 6603.31 | K22: =IF(J$10<>0,J22/J$10,0) -> 0.79520453 | L22: =+L10-L16 -> 6400.021 | M22: =IF(L$10<>0,L22/L$10,0) -> 0.78230484 | N22: =+N10-N16 -> 8920.002 | O22: =IF(N$10<>0,N22/N$10,0) -> 0.76531881 | P22: =+P10-P16 -> 6071.713 | Q22: =IF(P$10<>0,P22/P$10,0) -> 0.77820615 | R22: =+R10-R16 -> 6211.857 | S22: =IF(R$10<>0,R22/R$10,0) -> 0.76866005 | T22: =+T10-T16 -> 6718.665 | U22: =IF(T$10<>0,T22/T$10,0) -> 0.76819861 | V22: =+V10-V16 -> 5225.266 | W22: =IF(V$10<>0,V22/V$10,0) -> 0.72532903 | X22: =+X10-X16 -> 5613.356 | Y22: =IF(X$10<>0,X22/X$10,0) -> 0.73900009 | Z22: =+Z10-Z16 -> 5831.305 | AA22: =IF(Z$10<>0,Z22/Z$10,0) -> 0.75758359
C23: =+C17 -> 恵愛 | D23: =+D11-D17 -> 5158 | E23: =IF(D11<>0,D23/D11,0) -> 0.73971031 | F23: =+F11-F17 -> 5081 | G23: =IF(F11<>0,F23/F11,0) -> 0.74023893 | H23: =+H11-H17 -> 4438 | I23: =IF(H11<>0,H23/H11,0) -> 0.76359257 | J23: =+J11-J17 -> 4371 | K23: =IF(J11<>0,J23/J11,0) -> 0.76684211 | L23: =+L11-L17 -> 4720 | M23: =IF(L11<>0,L23/L11,0) -> 0.75459632 | N23: =+N11-N17 -> 7273 | O23: =IF(N11<>0,N23/N11,0) -> 0.75966158 | P23: =+P11-P17 -> 4244 | Q23: =IF(P11<>0,P23/P11,0) -> 0.74416974 | R23: =+R11-R17 -> 4569 | S23: =IF(R11<>0,R23/R11,0) -> 0.7438945 | T23: =+T11-T17 -> 4917 | U23: =IF(T11<>0,T23/T11,0) -> 0.74331066 | V23: =+V11-V17 -> 3389 | W23: =IF(V11<>0,V23/V11,0) -> 0.67807123 | X23: =+X11-X17 -> 3664 | Y23: =IF(X11<>0,X23/X11,0) -> 0.67839289 | Z23: =+Z11-Z17 -> 3811 | AA23: =IF(Z11<>0,Z23/Z11,0) -> 0.71008012
C24: =+C18 -> 村 | D24: =+D12-D18 -> 508 | E24: =IF(D12<>0,D24/D12,0) -> 0.88656195 | F24: =+F12-F18 -> 519 | G24: =IF(F12<>0,F24/F12,0) -> 0.86934673 | H24: =+H12-H18 -> 543 | I24: =IF(H12<>0,H24/H12,0) -> 0.90199336 | J24: =+J12-J18 -> 435 | K24: =IF(J12<>0,J24/J12,0) -> 0.75 | L24: =+L12-L18 -> 462 | M24: =IF(L12<>0,L24/L12,0) -> 0.8700565 | N24: =+N12-N18 -> 416 | O24: =IF(N12<>0,N24/N12,0) -> 0.74551971 | P24: =+P12-P18 -> 503 | Q24: =IF(P12<>0,P24/P12,0) -> 0.85254237 | R24: =+R12-R18 -> 496 | S24: =IF(R12<>0,R24/R12,0) -> 0.83221477 | T24: =+T12-T18 -> 496 | U24: =IF(T12<>0,T24/T12,0) -> 0.81848185 | V24: =+V12-V18 -> 406 | W24: =IF(V12<>0,V24/V12,0) -> 0.75046211 | X24: =+X12-X18 -> 509 | Y24: =IF(X12<>0,X24/X12,0) -> 0.83306056 | Z24: =+Z12-Z18 -> 534 | AA24: =IF(Z12<>0,Z24/Z12,0) -> 0.89
C25: =+C19 -> 弁当 | D25: =+D13-D19 -> 316 | E25: =IF(D13<>0,D25/D13,0) -> 0.68103448 | F25: =+F13-F19 -> 203 | G25: =IF(F13<>0,F25/F13,0) -> 0.56232687 | H25: =+H13-H19 -> 131 | I25: =IF(H13<>0,H25/H13,0) -> 0.4924812 | J25: =+J13-J19 -> 109 | K25: =IF(J13<>0,J25/J13,0) -> 0.5215311 | L25: =+L13-L19 -> 146 | M25: =IF(L13<>0,L25/L13,0) -> 0.52329749 | N25: =+N13-N19 -> 189 | O25: =IF(N13<>0,N25/N13,0) -> 0.59433962 | P25: =+P13-P19 -> 189 | Q25: =IF(P13<>0,P25/P13,0) -> 0.56083086 | R25: =+R13-R19 -> 113 | S25: =IF(R13<>0,R25/R13,0) -> 0.46502058 | T25: =+T13-T19 -> 223 | U25: =IF(T13<>0,T25/T13,0) -> 0.60107817 | V25: =+V13-V19 -> 258 | W25: =IF(V13<>0,V25/V13,0) -> 0.6128266 | X25: =+X13-X19 -> 329 | Y25: =IF(X13<>0,X25/X13,0) -> 0.71521739 | Z25: =+Z13-Z19 -> 247 | AA25: =IF(Z13<>0,Z25/Z13,0) -> 0.55630631
C26: =+C20 -> シェア | D26: =+D14-D20 -> 90 | E26: =IF(D14<>0,D26/D14,0) -> 0.69767442 | F26: =+F14-F20 -> 126 | G26: =IF(F14<>0,F26/F14,0) -> 0.7 | H26: =+H14-H20 -> 50 | I26: =IF(H14<>0,H26/H14,0) -> 0.69444444 | J26: =+J14-J20 -> 199 | K26: =IF(J14<>0,J26/J14,0) -> 0.70318021 | L26: =+L14-L20 -> 86 | M26: =IF(L14<>0,L26/L14,0) -> 0.69918699 | N26: =+N14-N20 -> 87 | O26: =IF(N14<>0,N26/N14,0) -> 0.66412214 | P26: =+P14-P20 -> 74 | Q26: =IF(P14<>0,P26/P14,0) -> 0.69811321 | R26: =+R14-R20 -> 63 | S26: =IF(R14<>0,R26/R14,0) -> 0.7 | T26: =+T14-T20 -> 87 | U26: =IF(T14<>0,T26/T14,0) -> 0.696 | V26: =+V14-V20 -> 70 | W26: =IF(V14<>0,V26/V14,0) -> 0.7 | X26: =+X14-X20 -> 58 | Y26: =IF(X14<>0,X26/X14,0) -> 0.69879518 | Z26: =+Z14-Z20 -> 53 | AA26: =IF(Z14<>0,Z26/Z14,0) -> 0.70666667
C27: =+C21 -> サウナ | D27: =+D15-D21 -> 719 | E27: =IF(D15<>0,D27/D15,0) -> 0.91475827 | F27: =+F15-F21 -> 1569 | G27: =IF(F15<>0,F27/F15,0) -> 0.97211896 | H27: =+H15-H21 -> 759 | I27: =IF(H15<>0,H27/H15,0) -> 0.99215686 | J27: =+J15-J21 -> 1150 | K27: =IF(J15<>0,J27/J15,0) -> 0.96557515 | L27: =+L15-L21 -> 637 | M27: =IF(L15<>0,L27/L15,0) -> 0.99066874 | N27: =+N15-N21 -> 993 | O27: =IF(N15<>0,N27/N15,0) -> 0.97257591 | P27: =+P15-P21 -> 712 | Q27: =IF(P15<>0,P27/P15,0) -> 0.99441341 | R27: =+R15-R21 -> 607 | S27: =IF(R15<>0,R27/R15,0) -> 0.93962848 | T27: =+T15-T21 -> 655 | U27: =IF(T15<>0,T27/T15,0) -> 0.94927536 | V27: =+V15-V21 -> 581 | W27: =IF(V15<>0,V27/V15,0) -> 0.96192053 | X27: =+X15-X21 -> 532 | Y27: =IF(X15<>0,X27/X15,0) -> 0.96202532 | Z27: =+Z15-Z21 -> 541 | AA27: =IF(Z15<>0,Z27/Z15,0) -> 0.95752212
B28: 販売管理費 | D28: =SUM(D29:D49) -> 7029.379 | E28: =IF(D$10<>0,D28/D$10,0) -> 0.75791934 | F28: =SUM(F29:F49) -> 6877.286 | G28: =IF(F$10<>0,F28/F$10,0) -> 0.69008053 | H28: =SUM(H29:H49) -> 6946.261 | I28: =IF(H$10<>0,H28/H$10,0) -> 0.8828538 | J28: =SUM(J29:J49) -> 6577.418 | K28: =IF(J$10<>0,J28/J$10,0) -> 0.79208648 | L28: =SUM(L29:L49) -> 6664.637 | M28: =IF(L$10<>0,L28/L$10,0) -> 0.8146501 | N28: =SUM(N29:N49) -> 7432.57 | O28: =IF(N$10<>0,N28/N$10,0) -> 0.63770004 | P28: =SUM(P29:P49) -> 7154.905 | Q28: =IF(P$10<>0,P28/P$10,0) -> 0.91703792 | R28: =SUM(R29:R49) -> 9370.861 | S28: =IF(R$10<>0,R28/R$10,0) -> 1.1595577 | T28: =SUM(T29:T49) -> 7545.12 | U28: =IF(T$10<>0,T28/T$10,0) -> 0.8626938 | V28: =SUM(V29:V49) -> 6818.127 | W28: =IF(V$10<>0,V28/V$10,0) -> 0.94643707 | X28: =SUM(X29:X49) -> 6533.591 | Y28: =IF(X$10<>0,X28/X$10,0) -> 0.86014932 | Z28: =SUM(Z29:Z49) -> 6706.484 | AA28: =IF(Z$10<>0,Z28/Z$10,0) -> 0.87128391
C29: 人件費 | D29: =SUM(月次PL!C18:C24)/1000 -> 2371.946 | E29: =IF(D$10<>0,D29/D$10,0) -> 0.25574716 | F29: =SUM(月次PL!D18:D24)/1000 -> 2352.858 | G29: =IF(F$10<>0,F29/F$10,0) -> 0.23609044 | H29: =SUM(月次PL!E18:E24)/1000 -> 2266.491 | I29: =IF(H$10<>0,H29/H$10,0) -> 0.28806579 | J29: =SUM(月次PL!F18:F24)/1000 -> 2375.566 | K29: =IF(J$10<>0,J29/J$10,0) -> 0.28607787 | L29: =SUM(月次PL!G18:G24)/1000 -> 2397.808 | M29: =IF(L$10<>0,L29/L$10,0) -> 0.29309541 | N29: =SUM(月次PL!H18:H24)/1000 -> 2816.608 | O29: =IF(N$10<>0,N29/N$10,0) -> 0.24165949 | P29: =SUM(月次PL!I18:I24)/1000 -> 2804.184 | Q29: =IF(P$10<>0,P29/P$10,0) -> 0.35940981 | R29: =SUM(月次PL!J18:J24)/1000 -> 2790.627 | S29: =IF(R$10<>0,R29/R$10,0) -> 0.34531437 | T29: =SUM(月次PL!K18:K24)/1000 -> 3189.715 | U29: =IF(T$10<>0,T29/T$10,0) -> 0.36470558 | V29: =SUM(月次PL!L18:L24)/1000 -> 2649.797 | W29: =IF(V$10<>0,V29/V$10,0) -> 0.36782332 | X29: =SUM(月次PL!M18:M24)/1000 -> 2670.396 | Y29: =IF(X$10<>0,X29/X$10,0) -> 0.35155848 | Z29: =SUM(月次PL!N18:N24)/1000 -> 2522.78 | AA29: =IF(Z$10<>0,Z29/Z$10,0) -> 0.32775112
C30: 旅費交通費 | D30: =+月次PL!C27/1000 -> 42.401 | E30: =IF(D$10<>0,D30/D$10,0) -> 0.0045717464 | F30: =+月次PL!D27/1000 -> 43.147 | G30: =IF(F$10<>0,F30/F$10,0) -> 0.0043294557 | H30: =+月次PL!E27/1000 -> 27.646 | I30: =IF(H$10<>0,H30/H$10,0) -> 0.003513743 | J30: =+月次PL!F27/1000 -> 41.601 | K30: =IF(J$10<>0,J30/J$10,0) -> 0.0050098062 | L30: =+月次PL!G27/1000 -> 47.715 | M30: =IF(L$10<>0,L30/L$10,0) -> 0.0058324301 | N30: =+月次PL!H27/1000 -> 40.511 | O30: =IF(N$10<>0,N30/N$10,0) -> 0.003475765 | P30: =+月次PL!I27/1000 -> 34.183 | Q30: =IF(P$10<>0,P30/P$10,0) -> 0.0043812052 | R30: =+月次PL!J27/1000 -> 42.182 | S30: =IF(R$10<>0,R30/R$10,0) -> 0.0052196337 | T30: =+月次PL!K27/1000 -> 54.459 | U30: =IF(T$10<>0,T30/T$10,0) -> 0.0062267322 | V30: =+月次PL!L27/1000 -> 46.858 | W30: =IF(V$10<>0,V30/V$10,0) -> 0.0065044474 | X30: =+月次PL!M27/1000 -> 52.253 | Y30: =IF(X$10<>0,X30/X$10,0) -> 0.0068791239 | Z30: =+月次PL!N27/1000 -> 42.731 | AA30: =IF(Z$10<>0,Z30/Z$10,0) -> 0.0055514682
C31: 通信費 | D31: =+月次PL!C28/1000 -> 45.779 | E31: =IF(D$10<>0,D31/D$10,0) -> 0.0049359679 | F31: =+月次PL!D28/1000 -> 55.395 | G31: =IF(F$10<>0,F31/F$10,0) -> 0.0055584443 | H31: =+月次PL!E28/1000 -> 45.57 | I31: =IF(H$10<>0,H31/H$10,0) -> 0.0057918422 | J31: =+月次PL!F28/1000 -> 44.794 | K31: =IF(J$10<>0,J31/J$10,0) -> 0.0053943237 | L31: =+月次PL!G28/1000 -> 52.175 | M31: =IF(L$10<>0,L31/L$10,0) -> 0.006377597 | N31: =+月次PL!H28/1000 -> 40.364 | O31: =IF(N$10<>0,N31/N$10,0) -> 0.0034631527 | P31: =+月次PL!I28/1000 -> 54.262 | Q31: =IF(P$10<>0,P31/P$10,0) -> 0.0069547131 | R31: =+月次PL!J28/1000 -> 70.983 | S31: =IF(R$10<>0,R31/R$10,0) -> 0.008783492 | T31: =+月次PL!K28/1000 -> 54.59 | U31: =IF(T$10<>0,T31/T$10,0) -> 0.0062417105 | V31: =+月次PL!L28/1000 -> 122.039 | W31: =IF(V$10<>0,V31/V$10,0) -> 0.016940464 | X31: =+月次PL!M28/1000 -> 54.629 | Y31: =IF(X$10<>0,X31/X$10,0) -> 0.0071919251 | Z31: =+月次PL!N28/1000 -> 51.282 | AA31: =IF(Z$10<>0,Z31/Z$10,0) -> 0.0066623855
C32: 開発費 | D32: =+月次PL!C43/1000 -> 21.289 | E32: =IF(D$10<>0,D32/D$10,0) -> 0.0022954154 | F32: =+月次PL!D43/1000 -> 97.177 | G32: =IF(F$10<>0,F32/F$10,0) -> 0.0097509331 | H32: =+月次PL!E43/1000 -> 106.992 | I32: =IF(H$10<>0,H32/H$10,0) -> 0.013598437 | J32: =+月次PL!F43/1000 -> 148.075 | K32: =IF(J$10<>0,J32/J$10,0) -> 0.017831952 | L32: =+月次PL!G43/1000 -> 79.685 | M32: =IF(L$10<>0,L32/L$10,0) -> 0.0097402744 | N32: =+月次PL!H43/1000 -> 0 | O32: =IF(N$10<>0,N32/N$10,0) -> 0 | P32: =+月次PL!I43/1000 -> 0 | Q32: =IF(P$10<>0,P32/P$10,0) -> 0 | R32: =+月次PL!J43/1000 -> 0 | S32: =IF(R$10<>0,R32/R$10,0) -> 0 | T32: =+月次PL!K43/1000 -> 0 | U32: =IF(T$10<>0,T32/T$10,0) -> 0 | V32: =+月次PL!L43/1000 -> 0 | W32: =IF(V$10<>0,V32/V$10,0) -> 0 | X32: =+月次PL!M43/1000 -> 0 | Y32: =IF(X$10<>0,X32/X$10,0) -> 0 | Z32: =+月次PL!N43/1000 -> 0 | AA32: =IF(Z$10<>0,Z32/Z$10,0) -> 0
C33: 交際費 | D33: =+月次PL!C26/1000 -> 0 | E33: =IF(D$10<>0,D33/D$10,0) -> 0 | F33: =+月次PL!D26/1000 -> 0 | G33: =IF(F$10<>0,F33/F$10,0) -> 0 | H33: =+月次PL!E26/1000 -> 0 | I33: =IF(H$10<>0,H33/H$10,0) -> 0 | J33: =+月次PL!F26/1000 -> 0 | K33: =IF(J$10<>0,J33/J$10,0) -> 0 | L33: =+月次PL!G26/1000 -> 0 | M33: =IF(L$10<>0,L33/L$10,0) -> 0 | N33: =+月次PL!H26/1000 -> 0 | O33: =IF(N$10<>0,N33/N$10,0) -> 0 | P33: =+月次PL!I26/1000 -> 0 | Q33: =IF(P$10<>0,P33/P$10,0) -> 0 | R33: =+月次PL!J26/1000 -> 0 | S33: =IF(R$10<>0,R33/R$10,0) -> 0 | T33: =+月次PL!K26/1000 -> 0 | U33: =IF(T$10<>0,T33/T$10,0) -> 0 | V33: =+月次PL!L26/1000 -> 0 | W33: =IF(V$10<>0,V33/V$10,0) -> 0 | X33: =+月次PL!M26/1000 -> 0 | Y33: =IF(X$10<>0,X33/X$10,0) -> 0 | Z33: =+月次PL!N26/1000 -> 0 | AA33: =IF(Z$10<>0,Z33/Z$10,0) -> 0
C34: 会議費 | D34: =+月次PL!C38/1000 -> 0 | E34: =IF(D$10<>0,D34/D$10,0) -> 0 | F34: =+月次PL!D38/1000 -> 0 | G34: =IF(F$10<>0,F34/F$10,0) -> 0 | H34: =+月次PL!E38/1000 -> 0 | I34: =IF(H$10<>0,H34/H$10,0) -> 0 | J34: =+月次PL!F38/1000 -> 0 | K34: =IF(J$10<>0,J34/J$10,0) -> 0 | L34: =+月次PL!G38/1000 -> 0 | M34: =IF(L$10<>0,L34/L$10,0) -> 0 | N34: =+月次PL!H38/1000 -> 0 | O34: =IF(N$10<>0,N34/N$10,0) -> 0 | P34: =+月次PL!I38/1000 -> 0 | Q34: =IF(P$10<>0,P34/P$10,0) -> 0 | R34: =+月次PL!J38/1000 -> 0 | S34: =IF(R$10<>0,R34/R$10,0) -> 0 | T34: =+月次PL!K38/1000 -> 0 | U34: =IF(T$10<>0,T34/T$10,0) -> 0 | V34: =+月次PL!L38/1000 -> 0 | W34: =IF(V$10<>0,V34/V$10,0) -> 0 | X34: =+月次PL!M38/1000 -> 0 | Y34: =IF(X$10<>0,X34/X$10,0) -> 0 | Z34: =+月次PL!N38/1000 -> 0 | AA34: =IF(Z$10<>0,Z34/Z$10,0) -> 0
C35: 減価償却費 | D35: =+月次PL!C40/1000 -> 690.589 | E35: =IF(D$10<>0,D35/D$10,0) -> 0.074460455 | F35: =+月次PL!D40/1000 -> 690.589 | G35: =IF(F$10<>0,F35/F$10,0) -> 0.069295071 | H35: =+月次PL!E40/1000 -> 690.589 | I35: =IF(H$10<>0,H35/H$10,0) -> 0.087772273 | J35: =+月次PL!F40/1000 -> 690.589 | K35: =IF(J$10<>0,J35/J$10,0) -> 0.083164277 | L35: =+月次PL!G40/1000 -> 690.589 | M35: =IF(L$10<>0,L35/L$10,0) -> 0.08441396 | N35: =+月次PL!H40/1000 -> 690.589 | O35: =IF(N$10<>0,N35/N$10,0) -> 0.059251192 | P35: =+月次PL!I40/1000 -> 690.589 | Q35: =IF(P$10<>0,P35/P$10,0) -> 0.088512188 | R35: =+月次PL!J40/1000 -> 690.589 | S35: =IF(R$10<>0,R35/R$10,0) -> 0.085454023 | T35: =+月次PL!K40/1000 -> 690.589 | U35: =IF(T$10<>0,T35/T$10,0) -> 0.078960553 | V35: =+月次PL!L40/1000 -> 690.589 | W35: =IF(V$10<>0,V35/V$10,0) -> 0.095861962 | X35: =+月次PL!M40/1000 -> 690.589 | Y35: =IF(X$10<>0,X35/X$10,0) -> 0.09091626 | Z35: =+月次PL!N40/1000 -> 690.589 | AA35: =IF(Z$10<>0,Z35/Z$10,0) -> 0.089719007
C36: 賃借料 | D36: =+月次PL!C34/1000 -> 30 | E36: =IF(D$10<>0,D36/D$10,0) -> 0.0032346499 | F36: =+月次PL!D34/1000 -> 30 | G36: =IF(F$10<>0,F36/F$10,0) -> 0.0030102596 | H36: =+月次PL!E34/1000 -> 30 | I36: =IF(H$10<>0,H36/H$10,0) -> 0.003812931 | J36: =+月次PL!F34/1000 -> 30 | K36: =IF(J$10<>0,J36/J$10,0) -> 0.0036127542 | L36: =+月次PL!G34/1000 -> 30 | M36: =IF(L$10<>0,L36/L$10,0) -> 0.0036670419 | N36: =+月次PL!H34/1000 -> 30 | O36: =IF(N$10<>0,N36/N$10,0) -> 0.0025739416 | P36: =+月次PL!I34/1000 -> 30 | Q36: =IF(P$10<>0,P36/P$10,0) -> 0.0038450738 | R36: =+月次PL!J34/1000 -> 30 | S36: =IF(R$10<>0,R36/R$10,0) -> 0.0037122235 | T36: =+月次PL!K34/1000 -> 30 | U36: =IF(T$10<>0,T36/T$10,0) -> 0.0034301395 | V36: =+月次PL!L34/1000 -> 30 | W36: =IF(V$10<>0,V36/V$10,0) -> 0.0041643566 | X36: =+月次PL!M34/1000 -> 30 | Y36: =IF(X$10<>0,X36/X$10,0) -> 0.0039495095 | Z36: =+月次PL!N34/1000 -> 30 | AA36: =IF(Z$10<>0,Z36/Z$10,0) -> 0.0038974994
C37: 地代家賃 | D37: =+月次PL!C33/1000 -> 1645.661 | E37: =IF(D$10<>0,D37/D$10,0) -> 0.17743791 | F37: =+月次PL!D33/1000 -> 1645.661 | G37: =IF(F$10<>0,F37/F$10,0) -> 0.16512889 | H37: =+月次PL!E33/1000 -> 1645.661 | I37: =IF(H$10<>0,H37/H$10,0) -> 0.20915973 | J37: =+月次PL!F33/1000 -> 1645.661 | K37: =IF(J$10<>0,J37/J$10,0) -> 0.19817896 | L37: =+月次PL!G33/1000 -> 1645.661 | M37: =IF(L$10<>0,L37/L$10,0) -> 0.20115693 | N37: =+月次PL!H33/1000 -> 1645.661 | O37: =IF(N$10<>0,N37/N$10,0) -> 0.14119451 | P37: =+月次PL!I33/1000 -> 1645.661 | Q37: =IF(P$10<>0,P37/P$10,0) -> 0.21092293 | R37: =+月次PL!J33/1000 -> 1645.661 | S37: =IF(R$10<>0,R37/R$10,0) -> 0.20363538 | T37: =+月次PL!K33/1000 -> 1645.661 | U37: =IF(T$10<>0,T37/T$10,0) -> 0.18816156 | V37: =+月次PL!L33/1000 -> 1645.661 | W37: =IF(V$10<>0,V37/V$10,0) -> 0.22843731 | X37: =+月次PL!M33/1000 -> 1645.661 | Y37: =IF(X$10<>0,X37/X$10,0) -> 0.21665179 | Z37: =+月次PL!N33/1000 -> 1645.661 | AA37: =IF(Z$10<>0,Z37/Z$10,0) -> 0.21379876
C38: リース料 | D38: =+月次PL!C32/1000 -> 49.7 | E38: =IF(D$10<>0,D38/D$10,0) -> 0.0053587367 | F38: =+月次PL!D32/1000 -> 49.7 | G38: =IF(F$10<>0,F38/F$10,0) -> 0.0049869967 | H38: =+月次PL!E32/1000 -> 49.7 | I38: =IF(H$10<>0,H38/H$10,0) -> 0.0063167557 | J38: =+月次PL!F32/1000 -> 49.7 | K38: =IF(J$10<>0,J38/J$10,0) -> 0.0059851294 | L38: =+月次PL!G32/1000 -> 49.7 | M38: =IF(L$10<>0,L38/L$10,0) -> 0.0060750661 | N38: =+月次PL!H32/1000 -> 49.7 | O38: =IF(N$10<>0,N38/N$10,0) -> 0.0042641633 | P38: =+月次PL!I32/1000 -> 49.7 | Q38: =IF(P$10<>0,P38/P$10,0) -> 0.0063700056 | R38: =+月次PL!J32/1000 -> 49.7 | S38: =IF(R$10<>0,R38/R$10,0) -> 0.0061499169 | T38: =+月次PL!K32/1000 -> 49.7 | U38: =IF(T$10<>0,T38/T$10,0) -> 0.0056825978 | V38: =+月次PL!L32/1000 -> 49.7 | W38: =IF(V$10<>0,V38/V$10,0) -> 0.0068989508 | X38: =+月次PL!M32/1000 -> 77.9 | Y38: =IF(X$10<>0,X38/X$10,0) -> 0.01025556 | Z38: =+月次PL!N32/1000 -> 49.7 | AA38: =IF(Z$10<>0,Z38/Z$10,0) -> 0.0064568573
C39: 修繕費 | D39: =+月次PL!C30/1000 -> 13.5 | E39: =IF(D$10<>0,D39/D$10,0) -> 0.0014555925 | F39: =+月次PL!D30/1000 -> 57.3 | G39: =IF(F$10<>0,F39/F$10,0) -> 0.0057495958 | H39: =+月次PL!E30/1000 -> 15 | I39: =IF(H$10<>0,H39/H$10,0) -> 0.0019064655 | J39: =+月次PL!F30/1000 -> 0 | K39: =IF(J$10<>0,J39/J$10,0) -> 0 | L39: =+月次PL!G30/1000 -> 20 | M39: =IF(L$10<>0,L39/L$10,0) -> 0.0024446946 | N39: =+月次PL!H30/1000 -> 19 | O39: =IF(N$10<>0,N39/N$10,0) -> 0.001630163 | P39: =+月次PL!I30/1000 -> 17 | Q39: =IF(P$10<>0,P39/P$10,0) -> 0.0021788751 | R39: =+月次PL!J30/1000 -> 90.91 | S39: =IF(R$10<>0,R39/R$10,0) -> 0.011249275 | T39: =+月次PL!K30/1000 -> 0 | U39: =IF(T$10<>0,T39/T$10,0) -> 0 | V39: =+月次PL!L30/1000 -> 0 | W39: =IF(V$10<>0,V39/V$10,0) -> 0 | X39: =+月次PL!M30/1000 -> 0 | Y39: =IF(X$10<>0,X39/X$10,0) -> 0 | Z39: =+月次PL!N30/1000 -> 15 | AA39: =IF(Z$10<>0,Z39/Z$10,0) -> 0.0019487497
C40: 保険料 | D40: =+月次PL!C35/1000 -> 22.215 | E40: =IF(D$10<>0,D40/D$10,0) -> 0.0023952583 | F40: =+月次PL!D35/1000 -> 22.215 | G40: =IF(F$10<>0,F40/F$10,0) -> 0.0022290972 | H40: =+月次PL!E35/1000 -> 22.215 | I40: =IF(H$10<>0,H40/H$10,0) -> 0.0028234754 | J40: =+月次PL!F35/1000 -> 22.215 | K40: =IF(J$10<>0,J40/J$10,0) -> 0.0026752445 | L40: =+月次PL!G35/1000 -> 22.215 | M40: =IF(L$10<>0,L40/L$10,0) -> 0.0027154445 | N40: =+月次PL!H35/1000 -> 28.375 | O40: =IF(N$10<>0,N40/N$10,0) -> 0.0024345198 | P40: =+月次PL!I35/1000 -> 28.375 | Q40: =IF(P$10<>0,P40/P$10,0) -> 0.0036367989 | R40: =+月次PL!J35/1000 -> 28.375 | S40: =IF(R$10<>0,R40/R$10,0) -> 0.0035111447 | T40: =+月次PL!K35/1000 -> 28.375 | U40: =IF(T$10<>0,T40/T$10,0) -> 0.0032443403 | V40: =+月次PL!L35/1000 -> 28.375 | W40: =IF(V$10<>0,V40/V$10,0) -> 0.0039387873 | X40: =+月次PL!M35/1000 -> 28.375 | Y40: =IF(X$10<>0,X40/X$10,0) -> 0.0037355777 | Z40: =+月次PL!N35/1000 -> 28.375 | AA40: =IF(Z$10<>0,Z40/Z$10,0) -> 0.0036863849
C41: 水道光熱費 | D41: =+月次PL!C29/1000 -> 1055.015 | E41: =IF(D$10<>0,D41/D$10,0) -> 0.11375347 | F41: =+月次PL!D29/1000 -> 1104.21 | G41: =IF(F$10<>0,F41/F$10,0) -> 0.11079862 | H41: =+月次PL!E29/1000 -> 968.209 | I41: =IF(H$10<>0,H41/H$10,0) -> 0.12305714 | J41: =+月次PL!F29/1000 -> 757.6 | K41: =IF(J$10<>0,J41/J$10,0) -> 0.091234086 | L41: =+月次PL!G29/1000 -> 878.364 | M41: =IF(L$10<>0,L41/L$10,0) -> 0.10736659 | N41: =+月次PL!H29/1000 -> 1110.021 | O41: =IF(N$10<>0,N41/N$10,0) -> 0.095237642 | P41: =+月次PL!I29/1000 -> 1144.612 | Q41: =IF(P$10<>0,P41/P$10,0) -> 0.14670392 | R41: =+月次PL!J29/1000 -> 1235.761 | S41: =IF(R$10<>0,R41/R$10,0) -> 0.15291403 | T41: =+月次PL!K29/1000 -> 1093.647 | U41: =IF(T$10<>0,T41/T$10,0) -> 0.12504539 | V41: =+月次PL!L29/1000 -> 804.331 | W41: =IF(V$10<>0,V41/V$10,0) -> 0.1116507 | X41: =+月次PL!M29/1000 -> 719.828 | Y41: =IF(X$10<>0,X41/X$10,0) -> 0.094765583 | Z41: =+月次PL!N29/1000 -> 852.493 | AA41: =IF(Z$10<>0,Z41/Z$10,0) -> 0.11075303
C42: 消耗品費 | D42: =+月次PL!C31/1000 -> 332.272 | E42: =IF(D$10<>0,D42/D$10,0) -> 0.03582612 | F42: =+月次PL!D31/1000 -> 162.804 | G42: =IF(F$10<>0,F42/F$10,0) -> 0.016336077 | H42: =+月次PL!E31/1000 -> 154.474 | I42: =IF(H$10<>0,H42/H$10,0) -> 0.01963329 | J42: =+月次PL!F31/1000 -> 229.112 | K42: =IF(J$10<>0,J42/J$10,0) -> 0.027590845 | L42: =+月次PL!G31/1000 -> 153.4 | M42: =IF(L$10<>0,L42/L$10,0) -> 0.018750808 | N42: =+月次PL!H31/1000 -> 227.238 | O42: =IF(N$10<>0,N42/N$10,0) -> 0.019496578 | P42: =+月次PL!I31/1000 -> 157.253 | Q42: =IF(P$10<>0,P42/P$10,0) -> 0.02015498 | R42: =+月次PL!J31/1000 -> 203.697 | S42: =IF(R$10<>0,R42/R$10,0) -> 0.025205626 | T42: =+月次PL!K31/1000 -> 158.297 | U42: =IF(T$10<>0,T42/T$10,0) -> 0.01809936 | V42: =+月次PL!L31/1000 -> 160.095 | W42: =IF(V$10<>0,V42/V$10,0) -> 0.022223089 | X42: =+月次PL!M31/1000 -> 127.598 | Y42: =IF(X$10<>0,X42/X$10,0) -> 0.016798317 | Z42: =+月次PL!N31/1000 -> 280.82 | AA42: =IF(Z$10<>0,Z42/Z$10,0) -> 0.036483193
C43: 租税公課 | D43: =+月次PL!C36/1000 -> 146 | E43: =IF(D$10<>0,D43/D$10,0) -> 0.015741963 | F43: =+月次PL!D36/1000 -> 1 | G43: =IF(F$10<>0,F43/F$10,0) -> 0.00010034199 | H43: =+月次PL!E36/1000 -> 147 | I43: =IF(H$10<>0,H43/H$10,0) -> 0.018683362 | J43: =+月次PL!F36/1000 -> 0 | K43: =IF(J$10<>0,J43/J$10,0) -> 0 | L43: =+月次PL!G36/1000 -> 2.45 | M43: =IF(L$10<>0,L43/L$10,0) -> 0.00029947509 | N43: =+月次PL!H36/1000 -> 148 | O43: =IF(N$10<>0,N43/N$10,0) -> 0.012698112 | P43: =+月次PL!I36/1000 -> 0 | Q43: =IF(P$10<>0,P43/P$10,0) -> 0 | R43: =+月次PL!J36/1000 -> 0 | S43: =IF(R$10<>0,R43/R$10,0) -> 0 | T43: =+月次PL!K36/1000 -> 1 | U43: =IF(T$10<>0,T43/T$10,0) -> 0.00011433798 | V43: =+月次PL!L36/1000 -> 125.9 | W43: =IF(V$10<>0,V43/V$10,0) -> 0.017476417 | X43: =+月次PL!M36/1000 -> 0 | Y43: =IF(X$10<>0,X43/X$10,0) -> 0 | Z43: =+月次PL!N36/1000 -> 1 | AA43: =IF(Z$10<>0,Z43/Z$10,0) -> 0.00012991665
C44: 広告宣伝費 | D44: =+月次PL!C25/1000 -> 186.903 | E44: =IF(D$10<>0,D44/D$10,0) -> 0.020152192 | F44: =+月次PL!D25/1000 -> 179.4 | G44: =IF(F$10<>0,F44/F$10,0) -> 0.018001352 | H44: =+月次PL!E25/1000 -> 177.56 | I44: =IF(H$10<>0,H44/H$10,0) -> 0.022567468 | J44: =+月次PL!F25/1000 -> 176.503 | K44: =IF(J$10<>0,J44/J$10,0) -> 0.021255398 | L44: =+月次PL!G25/1000 -> 215.303 | M44: =IF(L$10<>0,L44/L$10,0) -> 0.026317504 | N44: =+月次PL!H25/1000 -> 210.153 | O44: =IF(N$10<>0,N44/N$10,0) -> 0.018030718 | P44: =+月次PL!I25/1000 -> 112 | Q44: =IF(P$10<>0,P44/P$10,0) -> 0.014354942 | R44: =+月次PL!J25/1000 -> 2162.421 | S44: =IF(R$10<>0,R44/R$10,0) -> 0.26757967 | T44: =+月次PL!K25/1000 -> 108 | U44: =IF(T$10<>0,T44/T$10,0) -> 0.012348502 | V44: =+月次PL!L25/1000 -> 100.654 | W44: =IF(V$10<>0,V44/V$10,0) -> 0.013971972 | X44: =+月次PL!M25/1000 -> 134.4 | Y44: =IF(X$10<>0,X44/X$10,0) -> 0.017693802 | Z44: =+月次PL!N25/1000 -> 123.402 | AA44: =IF(Z$10<>0,Z44/Z$10,0) -> 0.016031974
C45: 支払手数料 | D45: =+月次PL!C37/1000 -> 238.917 | E45: =IF(D$10<>0,D45/D$10,0) -> 0.025760428 | F45: =+月次PL!D37/1000 -> 268.309 | G45: =IF(F$10<>0,F45/F$10,0) -> 0.026922658 | H45: =+月次PL!E37/1000 -> 276.554 | I45: =IF(H$10<>0,H45/H$10,0) -> 0.035149377 | J45: =+月次PL!F37/1000 -> 224.363 | K45: =IF(J$10<>0,J45/J$10,0) -> 0.027018946 | L45: =+月次PL!G37/1000 -> 226.852 | M45: =IF(L$10<>0,L45/L$10,0) -> 0.027729193 | N45: =+月次PL!H37/1000 -> 264.11 | O45: =IF(N$10<>0,N45/N$10,0) -> 0.022660124 | P45: =+月次PL!I37/1000 -> 245.928 | Q45: =IF(P$10<>0,P45/P$10,0) -> 0.031520377 | R45: =+月次PL!J37/1000 -> 218.075 | S45: =IF(R$10<>0,R45/R$10,0) -> 0.026984771 | T45: =+月次PL!K37/1000 -> 308.807 | U45: =IF(T$10<>0,T45/T$10,0) -> 0.03530837 | V45: =+月次PL!L37/1000 -> 185.84 | W45: =IF(V$10<>0,V45/V$10,0) -> 0.025796801 | X45: =+月次PL!M37/1000 -> 193.092 | Y45: =IF(X$10<>0,X45/X$10,0) -> 0.025420623 | Z45: =+月次PL!N37/1000 -> 243.661 | AA45: =IF(Z$10<>0,Z45/Z$10,0) -> 0.03165562 | AB45: らくしふ利用料 8月から1年分 72
C46: 新聞図書費 | D46: =+月次PL!C39/1000 -> 2.593 | E46: =IF(D$10<>0,D46/D$10,0) -> 0.00027958157 | F46: =+月次PL!D39/1000 -> 0 | G46: =IF(F$10<>0,F46/F$10,0) -> 0 | H46: =+月次PL!E39/1000 -> 0 | I46: =IF(H$10<>0,H46/H$10,0) -> 0 | J46: =+月次PL!F39/1000 -> 0 | K46: =IF(J$10<>0,J46/J$10,0) -> 0 | L46: =+月次PL!G39/1000 -> 0 | M46: =IF(L$10<>0,L46/L$10,0) -> 0 | N46: =+月次PL!H39/1000 -> 0 | O46: =IF(N$10<>0,N46/N$10,0) -> 0 | P46: =+月次PL!I39/1000 -> 0 | Q46: =IF(P$10<>0,P46/P$10,0) -> 0 | R46: =+月次PL!J39/1000 -> 0 | S46: =IF(R$10<>0,R46/R$10,0) -> 0 | T46: =+月次PL!K39/1000 -> 0 | U46: =IF(T$10<>0,T46/T$10,0) -> 0 | V46: =+月次PL!L39/1000 -> 0 | W46: =IF(V$10<>0,V46/V$10,0) -> 0 | X46: =+月次PL!M39/1000 -> 0 | Y46: =IF(X$10<>0,X46/X$10,0) -> 0 | Z46: =+月次PL!N39/1000 -> 0 | AA46: =IF(Z$10<>0,Z46/Z$10,0) -> 0
C47: 管理諸費 | D47: =+月次PL!C42/1000 -> 70 | E47: =IF(D$10<>0,D47/D$10,0) -> 0.0075475165 | F47: =+月次PL!D42/1000 -> 70 | G47: =IF(F$10<>0,F47/F$10,0) -> 0.007023939 | H47: =+月次PL!E42/1000 -> 280 | I47: =IF(H$10<>0,H47/H$10,0) -> 0.035587356 | J47: =+月次PL!F42/1000 -> 70 | K47: =IF(J$10<>0,J47/J$10,0) -> 0.0084297597 | L47: =+月次PL!G42/1000 -> 110 | M47: =IF(L$10<>0,L47/L$10,0) -> 0.01344582 | N47: =+月次PL!H42/1000 -> 70 | O47: =IF(N$10<>0,N47/N$10,0) -> 0.0060058638 | P47: =+月次PL!I42/1000 -> 70 | Q47: =IF(P$10<>0,P47/P$10,0) -> 0.0089718388 | R47: =+月次PL!J42/1000 -> 70 | S47: =IF(R$10<>0,R47/R$10,0) -> 0.0086618548 | T47: =+月次PL!K42/1000 -> 70 | U47: =IF(T$10<>0,T47/T$10,0) -> 0.0080036588 | V47: =+月次PL!L42/1000 -> 70 | W47: =IF(V$10<>0,V47/V$10,0) -> 0.0097168321 | X47: =+月次PL!M42/1000 -> 70 | Y47: =IF(X$10<>0,X47/X$10,0) -> 0.0092155221 | Z47: =+月次PL!N42/1000 -> 70 | AA47: =IF(Z$10<>0,Z47/Z$10,0) -> 0.0090941653
C48: 雑費 | D48: =+月次PL!C41/1000 -> 64.599 | E48: =IF(D$10<>0,D48/D$10,0) -> 0.0069651717 | F48: =+月次PL!D41/1000 -> 47.521 | G48: =IF(F$10<>0,F48/F$10,0) -> 0.0047683515 | H48: =+月次PL!E41/1000 -> 42.6 | I48: =IF(H$10<>0,H48/H$10,0) -> 0.005414362 | J48: =+月次PL!F41/1000 -> 71.639 | K48: =IF(J$10<>0,J48/J$10,0) -> 0.0086271366 | L48: =+月次PL!G41/1000 -> 42.72 | M48: =IF(L$10<>0,L48/L$10,0) -> 0.0052218676 | N48: =+月次PL!H41/1000 -> 42.24 | O48: =IF(N$10<>0,N48/N$10,0) -> 0.0036241098 | P48: =+月次PL!I41/1000 -> 71.158 | Q48: =IF(P$10<>0,P48/P$10,0) -> 0.0091202587 | R48: =+月次PL!J41/1000 -> 41.88 | S48: =IF(R$10<>0,R48/R$10,0) -> 0.005182264 | T48: =+月次PL!K41/1000 -> 62.28 | U48: =IF(T$10<>0,T48/T$10,0) -> 0.0071209696 | V48: =+月次PL!L41/1000 -> 108.288 | W48: =IF(V$10<>0,V48/V$10,0) -> 0.015031662 | X48: =+月次PL!M41/1000 -> 38.87 | Y48: =IF(X$10<>0,X48/X$10,0) -> 0.0051172478 | Z48: =+月次PL!N41/1000 -> 58.99 | AA48: =IF(Z$10<>0,Z48/Z$10,0) -> 0.007663783
E49: =IF(D$10<>0,D49/D$10,0) -> 0 | G49: =IF(F$10<>0,F49/F$10,0) -> 0 | I49: =IF(H$10<>0,H49/H$10,0) -> 0 | K49: =IF(J$10<>0,J49/J$10,0) -> 0 | M49: =IF(L$10<>0,L49/L$10,0) -> 0 | O49: =IF(N$10<>0,N49/N$10,0) -> 0 | Q49: =IF(P$10<>0,P49/P$10,0) -> 0 | S49: =IF(R$10<>0,R49/R$10,0) -> 0 | U49: =IF(T$10<>0,T49/T$10,0) -> 0 | W49: =IF(V$10<>0,V49/V$10,0) -> 0 | Y49: =IF(X$10<>0,X49/X$10,0) -> 0 | AA49: =IF(Z$10<>0,Z49/Z$10,0) -> 0
B50: 営業損益 | D50: =+D22-D28 -> 110.275 | E50: =IF(D$10<>0,D50/D$10,0) -> 0.011890034 | F50: =+F22-F28 -> 969.216 | G50: =IF(F$10<>0,F50/F$10,0) -> 0.097253058 | H50: =+H22-H28 -> -684.855 | I50: =IF(H$10<>0,H50/H$10,0) -> -0.087043495 | J50: =+J22-J28 -> 25.892 | K50: =IF(J$10<>0,J50/J$10,0) -> 0.0031180477 | L50: =+L22-L28 -> -264.616 | M50: =IF(L$10<>0,L50/L$10,0) -> -0.032345265 | N50: =+N22-N28 -> 1487.432 | O50: =IF(N$10<>0,N50/N$10,0) -> 0.12761877 | P50: =+P22-P28 -> -1083.192 | Q50: =IF(P$10<>0,P50/P$10,0) -> -0.13883177 | R50: =+R22-R28 -> -3159.004 | S50: =IF(R$10<>0,R50/R$10,0) -> -0.39089763 | T50: =+T22-T28 -> -826.455 | U50: =IF(T$10<>0,T50/T$10,0) -> -0.094495198 | V50: =+V22-V28 -> -1592.861 | W50: =IF(V$10<>0,V50/V$10,0) -> -0.22110804 | X50: =+X22-X28 -> -920.235 | Y50: =IF(X$10<>0,X50/X$10,0) -> -0.12114923 | Z50: =+Z22-Z28 -> -875.179 | AA50: =IF(Z$10<>0,Z50/Z$10,0) -> -0.11370032
C51: 期中累計 | D51: =+D50 -> 110.275 | F51: =+D51+F50 -> 1079.491 | H51: =+F51+H50 -> 394.636 | J51: =+H51+J50 -> 420.528 | L51: =+J51+L50 -> 155.912 | N51: =+L51+N50 -> 1643.344 | P51: =+N51+P50 -> 560.152 | R51: =+P51+R50 -> -2598.852 | T51: =+R51+T50 -> -3425.307 | V51: =+T51+V50 -> -5018.168 | X51: =+V51+X50 -> -5938.403 | Z51: =+X51+Z50 -> -6813.582
B52: 営業外収益 | D52: =+月次PL!C50/1000 -> 0 | E52: =IF(D$10<>0,D52/D$10,0) -> 0 | F52: =+月次PL!D50/1000 -> 33.39 | G52: =IF(F$10<>0,F52/F$10,0) -> 0.0033504189 | H52: =+月次PL!E50/1000 -> 403.669 | I52: =IF(H$10<>0,H52/H$10,0) -> 0.051305401 | J52: =+月次PL!F50/1000 -> 0 | K52: =IF(J$10<>0,J52/J$10,0) -> 0 | L52: =+月次PL!G50/1000 -> 0 | M52: =IF(L$10<>0,L52/L$10,0) -> 0 | N52: =+月次PL!H50/1000 -> 0 | O52: =IF(N$10<>0,N52/N$10,0) -> 0 | P52: =+月次PL!I50/1000 -> 0 | Q52: =IF(P$10<>0,P52/P$10,0) -> 0 | R52: =+月次PL!J50/1000 -> 33.136 | S52: =IF(R$10<>0,R52/R$10,0) -> 0.0041002746 | T52: =+月次PL!K50/1000 -> 1000.001 | U52: =IF(T$10<>0,T52/T$10,0) -> 0.1143381 | V52: =+月次PL!L50/1000 -> 0 | W52: =IF(V$10<>0,V52/V$10,0) -> 0 | X52: =+月次PL!M50/1000 -> 400 | Y52: =IF(X$10<>0,X52/X$10,0) -> 0.052660126 | Z52: =+月次PL!N50/1000 -> 0.239 | AA52: =IF(Z$10<>0,Z52/Z$10,0) -> 3.1050079e-05
B53: 営業外費用 | D53: =+月次PL!C55/1000 -> 147.962 | E53: =IF(D$10<>0,D53/D$10,0) -> 0.015953509 | F53: =+月次PL!D55/1000 -> 82.191 | G53: =IF(F$10<>0,F53/F$10,0) -> 0.0082472081 | H53: =+月次PL!E55/1000 -> 206.056 | I53: =IF(H$10<>0,H53/H$10,0) -> 0.026189244 | J53: =+月次PL!F55/1000 -> 152.448 | K53: =IF(J$10<>0,J53/J$10,0) -> 0.018358572 | L53: =+月次PL!G55/1000 -> 72.43 | M53: =IF(L$10<>0,L53/L$10,0) -> 0.0088534615 | N53: =+月次PL!H55/1000 -> 74.484 | O53: =IF(N$10<>0,N53/N$10,0) -> 0.0063905823 | P53: =+月次PL!I55/1000 -> 148.217 | Q53: =IF(P$10<>0,P53/P$10,0) -> 0.018996843 | R53: =+月次PL!J55/1000 -> 130.729 | S53: =IF(R$10<>0,R53/R$10,0) -> 0.016176509 | T53: =+月次PL!K55/1000 -> 199.645 | U53: =IF(T$10<>0,T53/T$10,0) -> 0.022827007 | V53: =+月次PL!L55/1000 -> 143.445 | W53: =IF(V$10<>0,V53/V$10,0) -> 0.019911871 | X53: =+月次PL!M55/1000 -> 81.533 | Y53: =IF(X$10<>0,X53/X$10,0) -> 0.010733845 | Z53: =+月次PL!N55/1000 -> 127.161 | AA53: =IF(Z$10<>0,Z53/Z$10,0) -> 0.016520331
B54: 経常損益 | D54: =+D50+D52-D53 -> -37.687 | E54: =IF(D$10<>0,D54/D$10,0) -> -0.004063475 | F54: =+F50+F52-F53 -> 920.415 | G54: =IF(F$10<>0,F54/F$10,0) -> 0.092356269 | H54: =+H50+H52-H53 -> -487.242 | I54: =IF(H$10<>0,H54/H$10,0) -> -0.061927337 | J54: =+J50+J52-J53 -> -126.556 | K54: =IF(J$10<>0,J54/J$10,0) -> -0.015240524 | L54: =+L50+L52-L53 -> -337.046 | M54: =IF(L$10<>0,L54/L$10,0) -> -0.041198727 | N54: =+N50+N52-N53 -> 1412.948 | O54: =IF(N$10<>0,N54/N$10,0) -> 0.12122819 | P54: =+P50+P52-P53 -> -1231.409 | Q54: =IF(P$10<>0,P54/P$10,0) -> -0.15782862 | R54: =+R50+R52-R53 -> -3256.597 | S54: =IF(R$10<>0,R54/R$10,0) -> -0.40297386 | T54: =+T50+T52-T53 -> -26.099 | U54: =IF(T$10<>0,T54/T$10,0) -> -0.002984107 | V54: =+V50+V52-V53 -> -1736.306 | W54: =IF(V$10<>0,V54/V$10,0) -> -0.24101991 | X54: =+X50+X52-X53 -> -601.768 | Y54: =IF(X$10<>0,X54/X$10,0) -> -0.079222947 | Z54: =+Z50+Z52-Z53 -> -1002.101 | AA54: =IF(Z$10<>0,Z54/Z$10,0) -> -0.1301896
C55: 期中累計 | D55: =+D54 -> -37.687 | F55: =+D55+F54 -> 882.728 | H55: =+F55+H54 -> 395.486 | J55: =+H55+J54 -> 268.93 | L55: =+J55+L54 -> -68.116 | N55: =+L55+N54 -> 1344.832 | P55: =+N55+P54 -> 113.423 | R55: =+P55+R54 -> -3143.174 | T55: =+R55+T54 -> -3169.273 | V55: =+T55+V54 -> -4905.579 | X55: =+V55+X54 -> -5507.347 | Z55: =+X55+Z54 -> -6509.448
B56: 繰越利益剰余金(BS) | D56: =+BS千円!D80 -> -17737.607 | E56: =+D56/BS千円!D93 -> -0.12959968 | F56: =+BS千円!E80 -> -16817.192 | G56: =+F56/BS千円!E93 -> -0.12424067 | H56: =+BS千円!F80 -> -17304.434 | I56: =+H56/BS千円!F93 -> -0.12868062 | J56: =+BS千円!G80 -> -17430.99 | K56: =+J56/BS千円!G93 -> -0.12900696 | L56: =+BS千円!H80 -> -17768.036 | M56: =+L56/BS千円!H93 -> -0.13019497 | N56: =+BS千円!I80 -> -16355.088 | O56: =+N56/BS千円!I93 -> -0.11702247 | P56: =+BS千円!J80 -> -17586.497 | Q56: =+P56/BS千円!J93 -> -0.12825697 | R56: =+BS千円!K80 -> -20843.094 | S56: =+R56/BS千円!K93 -> -0.15658713 | T56: =+BS千円!L80 -> -20870.899 | U56: =+T56/BS千円!L93 -> -0.15701268 | V56: =+BS千円!M80 -> -22607.205 | W56: =+V56/BS千円!M93 -> -0.17198577 | X56: =+BS千円!N80 -> -23208.973 | Y56: =+X56/BS千円!N93 -> -0.17546386 | Z56: =+BS千円!O80 -> -24211.074 | AA56: =+Z56/BS千円!Z92 -> #DIV/0!
C57: FL | D57: =+D16+D29 -> 4506.866 | E57: =+D57/D10 -> 0.48593779 | F57: =+F16+F29 -> 4472.274 | G57: =+F57/F10 -> 0.44875685 | H57: =+H16+H29 -> 3873.048 | I57: =+H57/H10 -> 0.49225549 | J57: =+J16+J29 -> 4076.17 | K57: =+J57/J10 -> 0.49087334 | L57: =+L16+L29 -> 4178.768 | M57: =+L57/L10 -> 0.51079058 | N57: =+N16+N29 -> 5551.882 | O57: =+N57/N10 -> 0.47634067 | P57: =+P16+P29 -> 4534.662 | Q57: =+P57/P10 -> 0.58120366 | R57: =+R16+R29 -> 4660.18 | S57: =+R57/R10 -> 0.57665432 | T57: =+T16+T29 -> 5217.05 | U57: =+T57/T10 -> 0.59650697 | V57: =+V16+V29 -> 4628.525 | W57: =+V57/V10 -> 0.64249429 | X57: =+X16+X29 -> 4652.92 | Y57: =+X57/X10 -> 0.61255839 | Z57: =+Z16+Z29 -> 4388.718 | AA57: =+Z57/Z10 -> 0.57016753
C58: FL(除くサウナ) | D58: =+D57-D21 -> 4439.866 | E58: =+D58/D59 -> 0.53566102 | F58: =+F57-F21 -> 4427.274 | G58: =+F58/F59 -> 0.54309599 | H58: =+H57-H21 -> 3867.048 | I58: =+H58/H59 -> 0.56020118 | J58: =+J57-J21 -> 4035.17 | K58: =+J58/J59 -> 0.58371477 | L58: =+L57-L21 -> 4172.768 | M58: =+L58/L59 -> 0.58052018 | N58: =+N57-N21 -> 5523.882 | O58: =+N58/N59 -> 0.53711919 | P58: =+P57-P21 -> 4530.662 | Q58: =+P58/P59 -> 0.67258514 | R58: =+R57-R21 -> 4621.18 | S58: =+R58/R59 -> 0.65221067 | T58: =+T57-T21 -> 5182.05 | U58: =+T58/T59 -> 0.6724695 | V58: =+V57-V21 -> 4605.525 | W58: =+V58/V59 -> 0.73688471 | X58: =+X57-X21 -> 4631.92 | Y58: =+X58/X59 -> 0.69206679 | Z58: =+Z57-Z21 -> 4364.718 | AA58: =+Z58/Z59 -> 0.64355081 | AB58: =+D58+F58+H58+J58 -> 16769.358 | AC58: =+AB58/AB59 -> 0.55424225
C59: 売上(除くサウナ・家賃) | D59: =+D10-200-D15 -> 8288.574 | F59: =+F10-200-F15 -> 8151.918 | H59: =+H10-200-H15 -> 6902.963 | J59: =+J10-200-J15 -> 6912.914 | L59: =+L10-L15-350 -> 7187.981 | N59: =+N10-N15-350 -> 10284.276 | P59: =+P10-P15-350 -> 6736.191 | R59: =+R10-R15-350 -> 7085.41 | T59: =+T10-T15-350 -> 7706 | V59: =+V10-V15-350 -> 6249.994 | X59: =+X10-X15-350 -> 6692.88 | Z59: =+Z10-Z15-350 -> 6782.243 | AB59: =+D59+F59+H59+J59 -> 30256.369

Sheet PL予実対比
A7: ■月次PL予実対比 | BB7: =+PL推移!D7 -> ㈱ｅｓエンターテイメント
A8: =+PL推移!B8 -> 2025 | B8: 年度 | BB8: 単位：千円
A9: 項目 | C9: =+PL推移!D9 -> 7月 | G9: =+PL推移!F9 -> 8月 | K9: =+PL推移!H9 -> 9月 | O9: =+PL推移!J9 -> 10月 | S9: =+PL推移!L9 -> 11月 | W9: =+PL推移!N9 -> 12月 | AA9: =+PL推移!P9 -> 1月 | AE9: =+PL推移!R9 -> 2月 | AI9: =+PL推移!T9 -> 3 | AM9: =+PL推移!V9 -> 4 | AQ9: =+PL推移!X9 -> 5月 | AU9: =+PL推移!Z9 -> 6月 | AY9: 累計
C10: 計画 | D10: 実績 | E10: 差異 | F10: 計画比 | G10: 計画 | H10: 実績 | I10: 差異 | J10: 計画比 | K10: 計画 | L10: 実績 | M10: 差異 | N10: 計画比 | O10: 計画 | P10: 実績 | Q10: 差異 | R10: 計画比 | S10: 計画 | T10: 実績 | U10: 差異 | V10: 計画比 | W10: 計画 | X10: 実績 | Y10: 差異 | Z10: 計画比 | AA10: 計画 | AB10: 実績 | AC10: 差異 | AD10: 計画比 | AE10: 計画 | AF10: 実績 | AG10: 差異 | AH10: 計画比 | AI10: 計画 | AJ10: 実績 | AK10: 差異 | AL10: 計画比 | AM10: 計画 | AN10: 実績 | AO10: 差異 | AP10: 計画比 | AQ10: 計画 | AR10: 実績 | AS10: 差異 | AT10: 計画比 | AU10: 計画 | AV10: 実績 | AW10: 差異 | AX10: 計画比 | AY10: 計画 | AZ10: 実績 | BA10: 差異 | BB10: 計画比
A11: 売上高 | C11: =+収支計画!G17/1000 -> 9600 | D11: =+PL推移!D10 -> 9274.574 | E11: =SUM(E12:E16) -> -325 | F11: =IF(C11<>0,D11/C11,"-") -> 0.96610146 | G11: =+収支計画!H17/1000 -> 11220 | H11: =SUM(H12:H16) -> 9616 | I11: =SUM(I12:I16) -> -1254 | J11: =IF(G11<>0,H11/G11,"-") -> 0.857041 | K11: =+収支計画!I17/1000 -> 9600 | L11: =+PL推移!H10 -> 7867.963 | M11: =SUM(M12:M16) -> -1733 | N11: =IF(K11<>0,L11/K11,"-") -> 0.81957948 | O11: =+収支計画!J17/1000 -> 9600 | P11: =+PL推移!J10 -> 8303.914 | Q11: =SUM(Q12:Q16) -> -1287 | R11: =IF(O11<>0,P11/O11,"-") -> 0.86499104 | S11: =+収支計画!K17/1000 -> 9600 | T11: =+PL推移!L10 -> 8180.981 | U11: =SUM(U12:U16) -> -1419 | V11: =IF(S11<>0,T11/S11,"-") -> 0.85218552 | W11: =+収支計画!L17/1000 -> 12100 | X11: =+PL推移!N10 -> 11655.276 | Y11: =SUM(Y12:Y16) -> -148 | Z11: =IF(W11<>0,X11/W11,"-") -> 0.96324595 | AA11: =+収支計画!M17/1000 -> 9600 | AB11: =+PL推移!P10 -> 7802.191 | AC11: =SUM(AC12:AC16) -> -1798 | AD11: =IF(AA11<>0,AB11/AA11,"-") -> 0.81272823 | AE11: =+収支計画!N17/1000 -> 9600 | AF11: =+PL推移!R10 -> 8081.41 | AG11: =SUM(AG12:AG16) -> -1533 | AH11: =IF(AE11<>0,AF11/AE11,"-") -> 0.84181354 | AI11: =+収支計画!O17/1000 -> 11100 | AJ11: =+PL推移!T10 -> 8746 | AK11: =SUM(AK12:AK16) -> -2343 | AL11: =IF(AI11<>0,AJ11/AI11,"-") -> 0.78792793 | AM11: =+収支計画!P17/1000 -> 9600 | AN11: =+PL推移!V10 -> 7203.994 | AO11: =+AN11-AM11 -> -2396.006 | AP11: =IF(AM11<>0,AN11/AM11,"-") -> 0.75041604 | AQ11: =+収支計画!Q17/1000 -> 9600 | AR11: =+PL推移!X10 -> 7595.88 | AS11: =+AR11-AQ11 -> -2004.12 | AT11: =IF(AQ11<>0,AR11/AQ11,"-") -> 0.7912375 | AU11: =+収支計画!R17/1000 -> 9600 | AV11: =+PL推移!Z10 -> 7697.243 | AW11: =+AV11-AU11 -> -1902.757 | AX11: =IF(AU11<>0,AV11/AU11,"-") -> 0.80179615 | AY11: =+C11+G11+K11+O11+S11+W11+AA11+AE11+AI11+AM11+AQ11+AU11 -> 120820 | AZ11: =+D11+H11+L11+P11+T11+X11+AB11+AF11+AJ11+AN11+AR11+AV11 -> 102025.43 | BA11: =+AZ11-AY11 -> -18794.574 | BB11: =IF(AY11<>0,AZ11/AY11,"-") -> 0.84444153
B12: 恵愛 | C12: =+収支計画!G11/1000 -> 7000 | D12: =+PL推移!D11 -> 6973 | E12: =+D12-C12 -> -27 | F12: =IF(C12<>0,D12/C12,"-") -> 0.99614286 | G12: =+収支計画!H11/1000 -> 7000 | H12: =+PL推移!F11 -> 6864 | I12: =+H12-G12 -> -136 | J12: =IF(G12<>0,H12/G12,"-") -> 0.98057143 | K12: =+収支計画!I11/1000 -> 7000 | L12: =+PL推移!H11 -> 5812 | M12: =+L12-K12 -> -1188 | N12: =IF(K12<>0,L12/K12,"-") -> 0.83028571 | O12: =+収支計画!S11/1000 -> 7000 | P12: =+PL推移!J11 -> 5700 | Q12: =+P12-O12 -> -1300 | R12: =IF(O12<>0,P12/O12,"-") -> 0.81428571 | S12: =+収支計画!K11/1000 -> 7000 | T12: =+PL推移!L11 -> 6255 | U12: =+T12-S12 -> -745 | V12: =IF(S12<>0,T12/S12,"-") -> 0.89357143 | W12: =+収支計画!L11/1000 -> 9500 | X12: =+PL推移!N11 -> 9574 | Y12: =+X12-W12 -> 74 | Z12: =IF(W12<>0,X12/W12,"-") -> 1.0077895 | AA12: =+収支計画!M11/1000 -> 7000 | AB12: =+PL推移!P11 -> 5703 | AC12: =+AB12-AA12 -> -1297 | AD12: =IF(AA12<>0,AB12/AA12,"-") -> 0.81471429 | AE12: =+収支計画!N11/1000 -> 7000 | AF12: =+PL推移!R11 -> 6142 | AG12: =+AF12-AE12 -> -858 | AH12: =IF(AE12<>0,AF12/AE12,"-") -> 0.87742857 | AI12: =+収支計画!O11/1000 -> 8500 | AJ12: =+PL推移!T11 -> 6615 | AK12: =+AJ12-AI12 -> -1885 | AL12: =IF(AI12<>0,AJ12/AI12,"-") -> 0.77823529 | AM12: =+収支計画!P11/1000 -> 7000 | AN12: =+PL推移!V11 -> 4998 | AO12: =+AN12-AM12 -> -2002 | AP12: =IF(AM12<>0,AN12/AM12,"-") -> 0.714 | AQ12: =+収支計画!Q11/1000 -> 7000 | AR12: =+PL推移!X11 -> 5401 | AS12: =+AR12-AQ12 -> -1599 | AT12: =IF(AQ12<>0,AR12/AQ12,"-") -> 0.77157143 | AU12: =+収支計画!R11/1000 -> 7000 | AV12: =+PL推移!Z11 -> 5367 | AW12: =+AV12-AU12 -> -1633 | AX12: =IF(AU12<>0,AV12/AU12,"-") -> 0.76671429 | AY12: =+C12+G12+K12+O12+S12+W12+AA12+AE12+AI12+AM12+AQ12+AU12 -> 88000 | AZ12: =+D12+H12+L12+P12+T12+X12+AB12+AF12+AJ12+AN12+AR12+AV12 -> 75404 | BA12: =+AZ12-AY12 -> -12596 | BB12: =IF(AY12<>0,AZ12/AY12,"-") -> 0.85686364
B13: 村 | C13: =+収支計画!G12/1000 -> 750 | D13: =+PL推移!D12 -> 573 | E13: =+D13-C13 -> -177 | F13: =IF(C13<>0,D13/C13,"-") -> 0.764 | G13: =+収支計画!H12/1000 -> 750 | H13: =+PL推移!F12 -> 597 | I13: =+H13-G13 -> -153 | J13: =IF(G13<>0,H13/G13,"-") -> 0.796 | K13: =+収支計画!I12/1000 -> 750 | L13: =+PL推移!H12 -> 602 | M13: =+L13-K13 -> -148 | N13: =IF(K13<>0,L13/K13,"-") -> 0.80266667 | O13: =+収支計画!S12/1000 -> 750 | P13: =+PL推移!J12 -> 580 | Q13: =+P13-O13 -> -170 | R13: =IF(O13<>0,P13/O13,"-") -> 0.77333333 | S13: =+収支計画!K12/1000 -> 750 | T13: =+PL推移!L12 -> 531 | U13: =+T13-S13 -> -219 | V13: =IF(S13<>0,T13/S13,"-") -> 0.708 | W13: =+収支計画!L12/1000 -> 750 | X13: =+PL推移!N12 -> 558 | Y13: =+X13-W13 -> -192 | Z13: =IF(W13<>0,X13/W13,"-") -> 0.744 | AA13: =+収支計画!M12/1000 -> 750 | AB13: =+PL推移!P12 -> 590 | AC13: =+AB13-AA13 -> -160 | AD13: =IF(AA13<>0,AB13/AA13,"-") -> 0.78666667 | AE13: =+収支計画!N12/1000 -> 750 | AF13: =+PL推移!R12 -> 596 | AG13: =+AF13-AE13 -> -154 | AH13: =IF(AE13<>0,AF13/AE13,"-") -> 0.79466667 | AI13: =+収支計画!O12/1000 -> 750 | AJ13: =+PL推移!T12 -> 606 | AK13: =+AJ13-AI13 -> -144 | AL13: =IF(AI13<>0,AJ13/AI13,"-") -> 0.808 | AM13: =+収支計画!P12/1000 -> 750 | AN13: =+PL推移!V12 -> 541 | AO13: =+AN13-AM13 -> -209 | AP13: =IF(AM13<>0,AN13/AM13,"-") -> 0.72133333 | AQ13: =+収支計画!Q12/1000 -> 750 | AR13: =+PL推移!X12 -> 611 | AS13: =+AR13-AQ13 -> -139 | AT13: =IF(AQ13<>0,AR13/AQ13,"-") -> 0.81466667 | AU13: =+収支計画!R12/1000 -> 750 | AV13: =+PL推移!Z12 -> 600 | AW13: =+AV13-AU13 -> -150 | AX13: =IF(AU13<>0,AV13/AU13,"-") -> 0.8 | AY13: =+C13+G13+K13+O13+S13+W13+AA13+AE13+AI13+AM13+AQ13+AU13 -> 9000 | AZ13: =+D13+H13+L13+P13+T13+X13+AB13+AF13+AJ13+AN13+AR13+AV13 -> 6985 | BA13: =+AZ13-AY13 -> -2015 | BB13: =IF(AY13<>0,AZ13/AY13,"-") -> 0.77611111
B14: 弁当 | C14: =+収支計画!G13/1000 -> 350 | D14: =+PL推移!D13 -> 464 | E14: =+D14-C14 -> 114 | F14: =IF(C14<>0,D14/C14,"-") -> 1.3257143 | G14: =+収支計画!H13/1000 -> 350 | H14: =+PL推移!F13 -> 361 | I14: =+H14-G14 -> 11 | J14: =IF(G14<>0,H14/G14,"-") -> 1.0314286 | K14: =+収支計画!I13/1000 -> 350 | L14: =+PL推移!H13 -> 266 | M14: =+L14-K14 -> -84 | N14: =IF(K14<>0,L14/K14,"-") -> 0.76 | O14: =+収支計画!S13/1000 -> 350 | P14: =+PL推移!J13 -> 209 | Q14: =+P14-O14 -> -141 | R14: =IF(O14<>0,P14/O14,"-") -> 0.59714286 | S14: =+収支計画!K13/1000 -> 350 | T14: =+PL推移!L13 -> 279 | U14: =+T14-S14 -> -71 | V14: =IF(S14<>0,T14/S14,"-") -> 0.79714286 | W14: =+収支計画!L13/1000 -> 350 | X14: =+PL推移!N13 -> 318 | Y14: =+X14-W14 -> -32 | Z14: =IF(W14<>0,X14/W14,"-") -> 0.90857143 | AA14: =+収支計画!M13/1000 -> 350 | AB14: =+PL推移!P13 -> 337 | AC14: =+AB14-AA14 -> -13 | AD14: =IF(AA14<>0,AB14/AA14,"-") -> 0.96285714 | AE14: =+収支計画!N13/1000 -> 350 | AF14: =+PL推移!R13 -> 243 | AG14: =+AF14-AE14 -> -107 | AH14: =IF(AE14<>0,AF14/AE14,"-") -> 0.69428571 | AI14: =+収支計画!O13/1000 -> 350 | AJ14: =+PL推移!T13 -> 371 | AK14: =+AJ14-AI14 -> 21 | AL14: =IF(AI14<>0,AJ14/AI14,"-") -> 1.06 | AM14: =+収支計画!P13/1000 -> 350 | AN14: =+PL推移!V13 -> 421 | AO14: =+AN14-AM14 -> 71 | AP14: =IF(AM14<>0,AN14/AM14,"-") -> 1.2028571 | AQ14: =+収支計画!Q13/1000 -> 350 | AR14: =+PL推移!X13 -> 460 | AS14: =+AR14-AQ14 -> 110 | AT14: =IF(AQ14<>0,AR14/AQ14,"-") -> 1.3142857 | AU14: =+収支計画!R13/1000 -> 350 | AV14: =+PL推移!Z13 -> 444 | AW14: =+AV14-AU14 -> 94 | AX14: =IF(AU14<>0,AV14/AU14,"-") -> 1.2685714 | AY14: =+C14+G14+K14+O14+S14+W14+AA14+AE14+AI14+AM14+AQ14+AU14 -> 4200 | AZ14: =+D14+H14+L14+P14+T14+X14+AB14+AF14+AJ14+AN14+AR14+AV14 -> 4173 | BA14: =+AZ14-AY14 -> -27 | BB14: =IF(AY14<>0,AZ14/AY14,"-") -> 0.99357143
B15: シェア | C15: =+収支計画!G14/1000 -> 150 | D15: =+PL推移!D14 -> 129 | E15: =+D15-C15 -> -21 | F15: =IF(C15<>0,D15/C15,"-") -> 0.86 | G15: =+収支計画!H14/1000 -> 150 | H15: =+PL推移!F14 -> 180 | I15: =+H15-G15 -> 30 | J15: =IF(G15<>0,H15/G15,"-") -> 1.2 | K15: =+収支計画!I14/1000 -> 150 | L15: =+PL推移!H14 -> 72 | M15: =+L15-K15 -> -78 | N15: =IF(K15<>0,L15/K15,"-") -> 0.48 | O15: =+収支計画!S14/1000 -> 150 | P15: =+PL推移!J14 -> 283 | Q15: =+P15-O15 -> 133 | R15: =IF(O15<>0,P15/O15,"-") -> 1.8866667 | S15: =+収支計画!K14/1000 -> 150 | T15: =+PL推移!L14 -> 123 | U15: =+T15-S15 -> -27 | V15: =IF(S15<>0,T15/S15,"-") -> 0.82 | W15: =+収支計画!L14/1000 -> 150 | X15: =+PL推移!N14 -> 131 | Y15: =+X15-W15 -> -19 | Z15: =IF(W15<>0,X15/W15,"-") -> 0.87333333 | AA15: =+収支計画!M14/1000 -> 150 | AB15: =+PL推移!P14 -> 106 | AC15: =+AB15-AA15 -> -44 | AD15: =IF(AA15<>0,AB15/AA15,"-") -> 0.70666667 | AE15: =+収支計画!N14/1000 -> 150 | AF15: =+PL推移!R14 -> 90 | AG15: =+AF15-AE15 -> -60 | AH15: =IF(AE15<>0,AF15/AE15,"-") -> 0.6 | AI15: =+収支計画!O14/1000 -> 150 | AJ15: =+PL推移!T14 -> 125 | AK15: =+AJ15-AI15 -> -25 | AL15: =IF(AI15<>0,AJ15/AI15,"-") -> 0.83333333 | AM15: =+収支計画!P14/1000 -> 150 | AN15: =+PL推移!V14 -> 100 | AO15: =+AN15-AM15 -> -50 | AP15: =IF(AM15<>0,AN15/AM15,"-") -> 0.66666667 | AQ15: =+収支計画!Q14/1000 -> 150 | AR15: =+PL推移!X14 -> 83 | AS15: =+AR15-AQ15 -> -67 | AT15: =IF(AQ15<>0,AR15/AQ15,"-") -> 0.55333333 | AU15: =+収支計画!R14/1000 -> 150 | AV15: =+PL推移!Z14 -> 75 | AW15: =+AV15-AU15 -> -75 | AX15: =IF(AU15<>0,AV15/AU15,"-") -> 0.5 | AY15: =+C15+G15+K15+O15+S15+W15+AA15+AE15+AI15+AM15+AQ15+AU15 -> 1800 | AZ15: =+D15+H15+L15+P15+T15+X15+AB15+AF15+AJ15+AN15+AR15+AV15 -> 1497 | BA15: =+AZ15-AY15 -> -303 | BB15: =IF(AY15<>0,AZ15/AY15,"-") -> 0.83166667
B16: サウナ | C16: =+収支計画!G15/1000 -> 1000 | D16: =+PL推移!D15 -> 786 | E16: =+D16-C16 -> -214 | F16: =IF(C16<>0,D16/C16,"-") -> 0.786 | G16: =+収支計画!H15/1000 -> 2620 | H16: =+PL推移!F15 -> 1614 | I16: =+H16-G16 -> -1006 | J16: =IF(G16<>0,H16/G16,"-") -> 0.61603053 | K16: =+収支計画!I15/1000 -> 1000 | L16: =+PL推移!H15 -> 765 | M16: =+L16-K16 -> -235 | N16: =IF(K16<>0,L16/K16,"-") -> 0.765 | O16: =+収支計画!S15/1000 -> 1000 | P16: =+PL推移!J15 -> 1191 | Q16: =+P16-O16 -> 191 | R16: =IF(O16<>0,P16/O16,"-") -> 1.191 | S16: =+収支計画!K15/1000 -> 1000 | T16: =+PL推移!L15 -> 643 | U16: =+T16-S16 -> -357 | V16: =IF(S16<>0,T16/S16,"-") -> 0.643 | W16: =+収支計画!L15/1000 -> 1000 | X16: =+PL推移!N15 -> 1021 | Y16: =+X16-W16 -> 21 | Z16: =IF(W16<>0,X16/W16,"-") -> 1.021 | AA16: =+収支計画!M15/1000 -> 1000 | AB16: =+PL推移!P15 -> 716 | AC16: =+AB16-AA16 -> -284 | AD16: =IF(AA16<>0,AB16/AA16,"-") -> 0.716 | AE16: =+収支計画!N15/1000 -> 1000 | AF16: =+PL推移!R15 -> 646 | AG16: =+AF16-AE16 -> -354 | AH16: =IF(AE16<>0,AF16/AE16,"-") -> 0.646 | AI16: =+収支計画!O15/1000 -> 1000 | AJ16: =+PL推移!T15 -> 690 | AK16: =+AJ16-AI16 -> -310 | AL16: =IF(AI16<>0,AJ16/AI16,"-") -> 0.69 | AM16: =+収支計画!P15/1000 -> 1000 | AN16: =+PL推移!V15 -> 604 | AO16: =+AN16-AM16 -> -396 | AP16: =IF(AM16<>0,AN16/AM16,"-") -> 0.604 | AQ16: =+収支計画!Q15/1000 -> 1000 | AR16: =+PL推移!X15 -> 553 | AS16: =+AR16-AQ16 -> -447 | AT16: =IF(AQ16<>0,AR16/AQ16,"-") -> 0.553 | AU16: =+収支計画!R15/1000 -> 1000 | AV16: =+PL推移!Z15 -> 565 | AW16: =+AV16-AU16 -> -435 | AX16: =IF(AU16<>0,AV16/AU16,"-") -> 0.565 | AY16: =+C16+G16+K16+O16+S16+W16+AA16+AE16+AI16+AM16+AQ16+AU16 -> 13620 | AZ16: =+D16+H16+L16+P16+T16+X16+AB16+AF16+AJ16+AN16+AR16+AV16 -> 9794 | BA16: =+AZ16-AY16 -> -3826 | BB16: =IF(AY16<>0,AZ16/AY16,"-") -> 0.71908957
A17: 売上原価 | C17: =SUM(C18:C22) -> 2200 | D17: =+PL推移!D16 -> 2134.92 | E17: =SUM(E18:E22) -> -66 | F17: =IF(C17<>0,D17/C17,"-") -> 0.97041818 | G17: =+収支計画!H24/1000 -> 2200 | H17: =+PL推移!F16 -> 2119.416 | I17: =SUM(I18:I22) -> -82 | J17: =IF(G17<>0,H17/G17,"-") -> 0.96337091 | K17: =SUM(K18:K22) -> 2200 | L17: =+PL推移!H16 -> 1606.557 | M17: =SUM(M18:M22) -> -604 | N17: =IF(K17<>0,L17/K17,"-") -> 0.73025318 | O17: =SUM(O18:O22) -> 2200 | P17: =+PL推移!J16 -> 1700.604 | Q17: =SUM(Q18:Q22) -> -501 | R17: =IF(O17<>0,P17/O17,"-") -> 0.77300182 | S17: =SUM(S18:S22) -> 2200 | T17: =+PL推移!L16 -> 1780.96 | U17: =SUM(U18:U22) -> -420 | V17: =IF(S17<>0,T17/S17,"-") -> 0.80952727 | W17: =SUM(W18:W22) -> 2837.5 | X17: =+PL推移!N16 -> 2735.274 | Y17: =SUM(Y18:Y22) -> -193.5 | Z17: =IF(W17<>0,X17/W17,"-") -> 0.96397322 | AA17: =+収支計画!M24/1000 -> 2200 | AB17: =+PL推移!P16 -> 1730.478 | AC17: =SUM(AC18:AC22) -> -470 | AD17: =IF(AA17<>0,AB17/AA17,"-") -> 0.78658091 | AE17: =+収支計画!N24/1000 -> 2200 | AF17: =+PL推移!R16 -> 1869.553 | AG17: =SUM(AG18:AG22) -> -331 | AH17: =IF(AE17<>0,AF17/AE17,"-") -> 0.84979682 | AI17: =+収支計画!O24/1000 -> 2582.5 | AJ17: =+PL推移!T16 -> 2027.335 | AK17: =SUM(AK18:AK22) -> -553.5 | AL17: =IF(AI17<>0,AJ17/AI17,"-") -> 0.78502807 | AM17: =+収支計画!P24/1000 -> 2182.5 | AN17: =+PL推移!V16 -> 1978.728 | AO17: =+AN17-AM17 -> -203.772 | AP17: =IF(AM17<>0,AN17/AM17,"-") -> 0.90663368 | AQ17: =+収支計画!Q24/1000 -> 2182.5 | AR17: =+PL推移!X16 -> 1982.524 | AS17: =+AR17-AQ17 -> -199.976 | AT17: =IF(AQ17<>0,AR17/AQ17,"-") -> 0.90837297 | AU17: =+収支計画!R24/1000 -> 2182.5 | AV17: =+PL推移!Z16 -> 1865.938 | AW17: =+AV17-AU17 -> -316.562 | AX17: =IF(AU17<>0,AV17/AU17,"-") -> 0.85495441 | AY17: =+C17+G17+K17+O17+S17+W17+AA17+AE17+AI17+AM17+AQ17+AU17 -> 27367.5 | AZ17: =+D17+H17+L17+P17+T17+X17+AB17+AF17+AJ17+AN17+AR17+AV17 -> 23532.287 | BA17: =+AZ17-AY17 -> -3835.213 | BB17: =IF(AY17<>0,AZ17/AY17,"-") -> 0.8598625
B18: =+B12 -> 恵愛 | C18: =+収支計画!G18/1000 -> 1785 | D18: =+PL推移!D17 -> 1815 | E18: =+D18-C18 -> 30 | F18: =IF(C18<>0,D18/C18,"-") -> 1.0168067 | G18: =+収支計画!H18/1000 -> 1785 | H18: =+PL推移!F17 -> 1783 | I18: =+H18-G18 -> -2 | J18: =IF(G18<>0,H18/G18,"-") -> 0.99887955 | K18: =+収支計画!I18/1000 -> 1785 | L18: =+PL推移!H17 -> 1374 | M18: =+L18-K18 -> -411 | N18: =IF(K18<>0,L18/K18,"-") -> 0.7697479 | O18: =+収支計画!J18/1000 -> 1785 | P18: =+PL推移!J17 -> 1329 | Q18: =+P18-O18 -> -456 | R18: =IF(O18<>0,P18/O18,"-") -> 0.74453782 | S18: =+収支計画!K18/1000 -> 1785 | T18: =+PL推移!L17 -> 1535 | U18: =+T18-S18 -> -250 | V18: =IF(S18<>0,T18/S18,"-") -> 0.85994398 | W18: =+収支計画!L18/1000 -> 2422.5 | X18: =+PL推移!N17 -> 2301 | Y18: =+X18-W18 -> -121.5 | Z18: =IF(W18<>0,X18/W18,"-") -> 0.9498452 | AA18: =+収支計画!M18/1000 -> 1785 | AB18: =+PL推移!P17 -> 1459 | AC18: =+AB18-AA18 -> -326 | AD18: =IF(AA18<>0,AB18/AA18,"-") -> 0.81736695 | AE18: =+収支計画!N18/1000 -> 1785 | AF18: =+PL推移!R17 -> 1573 | AG18: =+AF18-AE18 -> -212 | AH18: =IF(AE18<>0,AF18/AE18,"-") -> 0.88123249 | AI18: =+収支計画!O18/1000 -> 2167.5 | AJ18: =+PL推移!T17 -> 1698 | AK18: =+AJ18-AI18 -> -469.5 | AL18: =IF(AI18<>0,AJ18/AI18,"-") -> 0.783391 | AM18: =+収支計画!P18/1000 -> 1785 | AN18: =+PL推移!V17 -> 1609 | AO18: =+AN18-AM18 -> -176 | AP18: =IF(AM18<>0,AN18/AM18,"-") -> 0.90140056 | AQ18: =+収支計画!Q18/1000 -> 1785 | AR18: =+PL推移!X17 -> 1737 | AS18: =+AR18-AQ18 -> -48 | AT18: =IF(AQ18<>0,AR18/AQ18,"-") -> 0.97310924 | AU18: =+収支計画!R18/1000 -> 1785 | AV18: =+PL推移!Z17 -> 1556 | AW18: =+AV18-AU18 -> -229 | AX18: =IF(AU18<>0,AV18/AU18,"-") -> 0.87170868 | AY18: =+C18+G18+K18+O18+S18+W18+AA18+AE18+AI18+AM18+AQ18+AU18 -> 22440 | AZ18: =+D18+H18+L18+P18+T18+X18+AB18+AF18+AJ18+AN18+AR18+AV18 -> 19769 | BA18: =+AZ18-AY18 -> -2671 | BB18: =IF(AY18<>0,AZ18/AY18,"-") -> 0.88097148
B19: =+B13 -> 村 | C19: =+収支計画!G19/1000 -> 112.5 | D19: =+PL推移!D18 -> 65 | E19: =+D19-C19 -> -47.5 | F19: =IF(C19<>0,D19/C19,"-") -> 0.57777778 | G19: =+収支計画!H19/1000 -> 112.5 | H19: =+PL推移!F18 -> 78 | I19: =+H19-G19 -> -34.5 | J19: =IF(G19<>0,H19/G19,"-") -> 0.69333333 | K19: =+収支計画!I19/1000 -> 112.5 | L19: =+PL推移!H18 -> 59 | M19: =+L19-K19 -> -53.5 | N19: =IF(K19<>0,L19/K19,"-") -> 0.52444444 | O19: =+収支計画!S19/1000 -> 112.5 | P19: =+PL推移!J18 -> 145 | Q19: =+P19-O19 -> 32.5 | R19: =IF(O19<>0,P19/O19,"-") -> 1.2888889 | S19: =+収支計画!K19/1000 -> 112.5 | T19: =+PL推移!L18 -> 69 | U19: =+T19-S19 -> -43.5 | V19: =IF(S19<>0,T19/S19,"-") -> 0.61333333 | W19: =+収支計画!L19/1000 -> 112.5 | X19: =+PL推移!N18 -> 142 | Y19: =+X19-W19 -> 29.5 | Z19: =IF(W19<>0,X19/W19,"-") -> 1.2622222 | AA19: =+収支計画!M19/1000 -> 112.5 | AB19: =+PL推移!P18 -> 87 | AC19: =+AB19-AA19 -> -25.5 | AD19: =IF(AA19<>0,AB19/AA19,"-") -> 0.77333333 | AE19: =+収支計画!N19/1000 -> 112.5 | AF19: =+PL推移!R18 -> 100 | AG19: =+AF19-AE19 -> -12.5 | AH19: =IF(AE19<>0,AF19/AE19,"-") -> 0.88888889 | AI19: =+収支計画!O19/1000 -> 112.5 | AJ19: =+PL推移!T18 -> 110 | AK19: =+AJ19-AI19 -> -2.5 | AL19: =IF(AI19<>0,AJ19/AI19,"-") -> 0.97777778 | AM19: =+収支計画!P19/1000 -> 112.5 | AN19: =+PL推移!V18 -> 135 | AO19: =+AN19-AM19 -> 22.5 | AP19: =IF(AM19<>0,AN19/AM19,"-") -> 1.2 | AQ19: =+収支計画!Q19/1000 -> 112.5 | AR19: =+PL推移!X18 -> 102 | AS19: =+AR19-AQ19 -> -10.5 | AT19: =IF(AQ19<>0,AR19/AQ19,"-") -> 0.90666667 | AU19: =+収支計画!R19/1000 -> 112.5 | AV19: =+PL推移!Z18 -> 66 | AW19: =+AV19-AU19 -> -46.5 | AX19: =IF(AU19<>0,AV19/AU19,"-") -> 0.58666667 | AY19: =+C19+G19+K19+O19+S19+W19+AA19+AE19+AI19+AM19+AQ19+AU19 -> 1350 | AZ19: =+D19+H19+L19+P19+T19+X19+AB19+AF19+AJ19+AN19+AR19+AV19 -> 1158 | BA19: =+AZ19-AY19 -> -192 | BB19: =IF(AY19<>0,AZ19/AY19,"-") -> 0.85777778
B20: =+B14 -> 弁当 | C20: =+収支計画!G20/1000 -> 157.5 | D20: =+PL推移!D19 -> 148 | E20: =+D20-C20 -> -9.5 | F20: =IF(C20<>0,D20/C20,"-") -> 0.93968254 | G20: =+収支計画!H20/1000 -> 157.5 | H20: =+PL推移!F19 -> 158 | I20: =+H20-G20 -> 0.5 | J20: =IF(G20<>0,H20/G20,"-") -> 1.0031746 | K20: =+収支計画!I20/1000 -> 157.5 | L20: =+PL推移!H19 -> 135 | M20: =+L20-K20 -> -22.5 | N20: =IF(K20<>0,L20/K20,"-") -> 0.85714286 | O20: =+収支計画!S20/1000 -> 157.5 | P20: =+PL推移!J19 -> 100 | Q20: =+P20-O20 -> -57.5 | R20: =IF(O20<>0,P20/O20,"-") -> 0.63492063 | S20: =+収支計画!K20/1000 -> 157.5 | T20: =+PL推移!L19 -> 133 | U20: =+T20-S20 -> -24.5 | V20: =IF(S20<>0,T20/S20,"-") -> 0.84444444 | W20: =+収支計画!L20/1000 -> 157.5 | X20: =+PL推移!N19 -> 129 | Y20: =+X20-W20 -> -28.5 | Z20: =IF(W20<>0,X20/W20,"-") -> 0.81904762 | AA20: =+収支計画!M20/1000 -> 157.5 | AB20: =+PL推移!P19 -> 148 | AC20: =+AB20-AA20 -> -9.5 | AD20: =IF(AA20<>0,AB20/AA20,"-") -> 0.93968254 | AE20: =+収支計画!N20/1000 -> 157.5 | AF20: =+PL推移!R19 -> 130 | AG20: =+AF20-AE20 -> -27.5 | AH20: =IF(AE20<>0,AF20/AE20,"-") -> 0.82539683 | AI20: =+収支計画!O20/1000 -> 157.5 | AJ20: =+PL推移!T19 -> 148 | AK20: =+AJ20-AI20 -> -9.5 | AL20: =IF(AI20<>0,AJ20/AI20,"-") -> 0.93968254 | AM20: =+収支計画!P20/1000 -> 140 | AN20: =+PL推移!V19 -> 163 | AO20: =+AN20-AM20 -> 23 | AP20: =IF(AM20<>0,AN20/AM20,"-") -> 1.1642857 | AQ20: =+収支計画!Q20/1000 -> 140 | AR20: =+PL推移!X19 -> 131 | AS20: =+AR20-AQ20 -> -9 | AT20: =IF(AQ20<>0,AR20/AQ20,"-") -> 0.93571429 | AU20: =+収支計画!R20/1000 -> 140 | AV20: =+PL推移!Z19 -> 197 | AW20: =+AV20-AU20 -> 57 | AX20: =IF(AU20<>0,AV20/AU20,"-") -> 1.4071429 | AY20: =+C20+G20+K20+O20+S20+W20+AA20+AE20+AI20+AM20+AQ20+AU20 -> 1837.5 | AZ20: =+D20+H20+L20+P20+T20+X20+AB20+AF20+AJ20+AN20+AR20+AV20 -> 1720 | BA20: =+AZ20-AY20 -> -117.5 | BB20: =IF(AY20<>0,AZ20/AY20,"-") -> 0.93605442
B21: =+B15 -> シェア | C21: =+収支計画!G21/1000 -> 45 | D21: =+PL推移!D20 -> 39 | E21: =+D21-C21 -> -6 | F21: =IF(C21<>0,D21/C21,"-") -> 0.86666667 | G21: =+収支計画!H21/1000 -> 45 | H21: =+PL推移!F20 -> 54 | I21: =+H21-G21 -> 9 | J21: =IF(G21<>0,H21/G21,"-") -> 1.2 | K21: =+収支計画!I21/1000 -> 45 | L21: =+PL推移!H20 -> 22 | M21: =+L21-K21 -> -23 | N21: =IF(K21<>0,L21/K21,"-") -> 0.48888889 | O21: =+収支計画!S21/1000 -> 45 | P21: =+PL推移!J20 -> 84 | Q21: =+P21-O21 -> 39 | R21: =IF(O21<>0,P21/O21,"-") -> 1.8666667 | S21: =+収支計画!K21/1000 -> 45 | T21: =+PL推移!L20 -> 37 | U21: =+T21-S21 -> -8 | V21: =IF(S21<>0,T21/S21,"-") -> 0.82222222 | W21: =+収支計画!L21/1000 -> 45 | X21: =+PL推移!N20 -> 44 | Y21: =+X21-W21 -> -1 | Z21: =IF(W21<>0,X21/W21,"-") -> 0.97777778 | AA21: =+収支計画!M21/1000 -> 45 | AB21: =+PL推移!P20 -> 32 | AC21: =+AB21-AA21 -> -13 | AD21: =IF(AA21<>0,AB21/AA21,"-") -> 0.71111111 | AE21: =+収支計画!N21/1000 -> 45 | AF21: =+PL推移!R20 -> 27 | AG21: =+AF21-AE21 -> -18 | AH21: =IF(AE21<>0,AF21/AE21,"-") -> 0.6 | AI21: =+収支計画!O21/1000 -> 45 | AJ21: =+PL推移!T20 -> 38 | AK21: =+AJ21-AI21 -> -7 | AL21: =IF(AI21<>0,AJ21/AI21,"-") -> 0.84444444 | AM21: =+収支計画!P21/1000 -> 45 | AN21: =+PL推移!V20 -> 30 | AO21: =+AN21-AM21 -> -15 | AP21: =IF(AM21<>0,AN21/AM21,"-") -> 0.66666667 | AQ21: =+収支計画!Q21/1000 -> 45 | AR21: =+PL推移!X20 -> 25 | AS21: =+AR21-AQ21 -> -20 | AT21: =IF(AQ21<>0,AR21/AQ21,"-") -> 0.55555556 | AU21: =+収支計画!R21/1000 -> 45 | AV21: =+PL推移!Z20 -> 22 | AW21: =+AV21-AU21 -> -23 | AX21: =IF(AU21<>0,AV21/AU21,"-") -> 0.48888889 | AY21: =+C21+G21+K21+O21+S21+W21+AA21+AE21+AI21+AM21+AQ21+AU21 -> 540 | AZ21: =+D21+H21+L21+P21+T21+X21+AB21+AF21+AJ21+AN21+AR21+AV21 -> 454 | BA21: =+AZ21-AY21 -> -86 | BB21: =IF(AY21<>0,AZ21/AY21,"-") -> 0.84074074
B22: =+B16 -> サウナ | C22: =+収支計画!G22/1000 -> 100 | D22: =+PL推移!D21 -> 67 | E22: =+D22-C22 -> -33 | F22: =IF(C22<>0,D22/C22,"-") -> 0.67 | G22: =+収支計画!H22/1000 -> 100 | H22: =+PL推移!F21 -> 45 | I22: =+H22-G22 -> -55 | J22: =IF(G22<>0,H22/G22,"-") -> 0.45 | K22: =+収支計画!I22/1000 -> 100 | L22: =+PL推移!H21 -> 6 | M22: =+L22-K22 -> -94 | N22: =IF(K22<>0,L22/K22,"-") -> 0.06 | O22: =+収支計画!S22/1000 -> 100 | P22: =+PL推移!J21 -> 41 | Q22: =+P22-O22 -> -59 | R22: =IF(O22<>0,P22/O22,"-") -> 0.41 | S22: =+収支計画!K22/1000 -> 100 | T22: =+PL推移!L21 -> 6 | U22: =+T22-S22 -> -94 | V22: =IF(S22<>0,T22/S22,"-") -> 0.06 | W22: =+収支計画!L22/1000 -> 100 | X22: =+PL推移!N21 -> 28 | Y22: =+X22-W22 -> -72 | Z22: =IF(W22<>0,X22/W22,"-") -> 0.28 | AA22: =+収支計画!M22/1000 -> 100 | AB22: =+PL推移!P21 -> 4 | AC22: =+AB22-AA22 -> -96 | AD22: =IF(AA22<>0,AB22/AA22,"-") -> 0.04 | AE22: =+収支計画!N22/1000 -> 100 | AF22: =+PL推移!R21 -> 39 | AG22: =+AF22-AE22 -> -61 | AH22: =IF(AE22<>0,AF22/AE22,"-") -> 0.39 | AI22: =+収支計画!O22/1000 -> 100 | AJ22: =+PL推移!T21 -> 35 | AK22: =+AJ22-AI22 -> -65 | AL22: =IF(AI22<>0,AJ22/AI22,"-") -> 0.35 | AM22: =+収支計画!P22/1000 -> 100 | AN22: =+PL推移!V21 -> 23 | AO22: =+AN22-AM22 -> -77 | AP22: =IF(AM22<>0,AN22/AM22,"-") -> 0.23 | AQ22: =+収支計画!Q22/1000 -> 100 | AR22: =+PL推移!X21 -> 21 | AS22: =+AR22-AQ22 -> -79 | AT22: =IF(AQ22<>0,AR22/AQ22,"-") -> 0.21 | AU22: =+収支計画!R22/1000 -> 100 | AV22: =+PL推移!Z21 -> 24 | AW22: =+AV22-AU22 -> -76 | AX22: =IF(AU22<>0,AV22/AU22,"-") -> 0.24 | AY22: =+C22+G22+K22+O22+S22+W22+AA22+AE22+AI22+AM22+AQ22+AU22 -> 1200 | AZ22: =+D22+H22+L22+P22+T22+X22+AB22+AF22+AJ22+AN22+AR22+AV22 -> 339 | BA22: =+AZ22-AY22 -> -861 | BB22: =IF(AY22<>0,AZ22/AY22,"-") -> 0.2825
A23: 粗利益 | C23: =+C11-C17 -> 7400 | D23: =+D11-D17 -> 7139.654 | E23: =+E11-E17 -> -259 | F23: =IF(C23<>0,D23/C23,"-") -> 0.96481811 | G23: =+収支計画!H25/1000 -> 9020 | H23: =+PL推移!F22 -> 7846.502 | I23: =+I11-I17 -> -1172 | J23: =IF(G23<>0,H23/G23,"-") -> 0.86990044 | K23: =+K11-K17 -> 7400 | L23: =+PL推移!H22 -> 6261.406 | M23: =+M11-M17 -> -1129 | N23: =IF(K23<>0,L23/K23,"-") -> 0.84613595 | O23: =+O11-O17 -> 7400 | P23: =+PL推移!J22 -> 6603.31 | Q23: =+Q11-Q17 -> -786 | R23: =IF(O23<>0,P23/O23,"-") -> 0.89233919 | S23: =+S11-S17 -> 7400 | T23: =+T11-T17 -> 6400.021 | U23: =+U11-U17 -> -999 | V23: =IF(S23<>0,T23/S23,"-") -> 0.8648677 | W23: =+W11-W17 -> 9262.5 | X23: =+X11-X17 -> 8920.002 | Y23: =+Y11-Y17 -> 45.5 | Z23: =IF(W23<>0,X23/W23,"-") -> 0.96302316 | AA23: =+AA11-AA17 -> 7400 | AB23: =+AB11-AB17 -> 6071.713 | AC23: =+AC11-AC17 -> -1328 | AD23: =IF(AA23<>0,AB23/AA23,"-") -> 0.82050176 | AE23: =SUM(AE24:AE28) -> 7050 | AF23: =+PL推移!R22 -> 6211.857 | AG23: =+AG11-AG17 -> -1202 | AH23: =IF(AE23<>0,AF23/AE23,"-") -> 0.88111447 | AI23: =+AI11-AI17 -> 8517.5 | AJ23: =+AJ11-AJ17 -> 6718.665 | AK23: =+AK11-AK17 -> -1789.5 | AL23: =IF(AI23<>0,AJ23/AI23,"-") -> 0.78880716 | AM23: =+AM11-AM17 -> 7417.5 | AN23: =+AN11-AN17 -> 5225.266 | AO23: =+AN23-AM23 -> -2192.234 | AP23: =IF(AM23<>0,AN23/AM23,"-") -> 0.7044511 | AQ23: =+AQ11-AQ17 -> 7417.5 | AR23: =+AR11-AR17 -> 5613.356 | AS23: =+AR23-AQ23 -> -1804.144 | AT23: =IF(AQ23<>0,AR23/AQ23,"-") -> 0.75677196 | AU23: =+AU11-AU17 -> 7417.5 | AV23: =+AV11-AV17 -> 5831.305 | AW23: =+AV23-AU23 -> -1586.195 | AX23: =IF(AU23<>0,AV23/AU23,"-") -> 0.78615504 | AY23: =+C23+G23+K23+O23+S23+W23+AA23+AE23+AI23+AM23+AQ23+AU23 -> 93102.5 | AZ23: =+D23+H23+L23+P23+T23+X23+AB23+AF23+AJ23+AN23+AR23+AV23 -> 78843.057 | BA23: =+AZ23-AY23 -> -14259.443 | BB23: =IF(AY23<>0,AZ23/AY23,"-") -> 0.84684146
B24: =+B18 -> 恵愛 | C24: =+C12-C18 -> 5215 | D24: =+PL推移!D23 -> 5158 | E24: =+D24-C24 -> -57 | F24: =IF(C24<>0,D24/C24,"-") -> 0.98906999 | G24: =+G12-G18 -> 5215 | H24: =+PL推移!F23 -> 5081 | I24: =+H24-G24 -> -134 | J24: =IF(G24<>0,H24/G24,"-") -> 0.97430489 | K24: =+K12-K18 -> 5215 | L24: =+PL推移!H23 -> 4438 | M24: =+L24-K24 -> -777 | N24: =IF(K24<>0,L24/K24,"-") -> 0.85100671 | O24: =+O12-O18 -> 5215 | P24: =+PL推移!J23 -> 4371 | Q24: =+P24-O24 -> -844 | R24: =IF(O24<>0,P24/O24,"-") -> 0.83815916 | S24: =+S12-S18 -> 5215 | T24: =+T12-T18 -> 4720 | U24: =+T24-S24 -> -495 | V24: =IF(S24<>0,T24/S24,"-") -> 0.9050815 | W24: =+W12-W18 -> 7077.5 | X24: =+X12-X18 -> 7273 | Y24: =+X24-W24 -> 195.5 | Z24: =IF(W24<>0,X24/W24,"-") -> 1.0276227 | AA24: =+AA12-AA18 -> 5215 | AB24: =+AB12-AB18 -> 4244 | AC24: =+AB24-AA24 -> -971 | AD24: =IF(AA24<>0,AB24/AA24,"-") -> 0.81380633 | AE24: =+AE12-AE18 -> 5215 | AF24: =+PL推移!R23 -> 4569 | AG24: =+AF24-AE24 -> -646 | AH24: =IF(AE24<>0,AF24/AE24,"-") -> 0.87612656 | AI24: =+AI12-AI18 -> 6332.5 | AJ24: =+AJ12-AJ18 -> 4917 | AK24: =+AJ24-AI24 -> -1415.5 | AL24: =IF(AI24<>0,AJ24/AI24,"-") -> 0.77647059 | AM24: =+AM12-AM18 -> 5215 | AN24: =+AN12-AN18 -> 3389 | AO24: =+AN24-AM24 -> -1826 | AP24: =IF(AM24<>0,AN24/AM24,"-") -> 0.64985618 | AQ24: =+AQ12-AQ18 -> 5215 | AR24: =+AR12-AR18 -> 3664 | AS24: =+AR24-AQ24 -> -1551 | AT24: =IF(AQ24<>0,AR24/AQ24,"-") -> 0.70258869 | AU24: =+AU12-AU18 -> 5215 | AV24: =+AV12-AV18 -> 3811 | AW24: =+AV24-AU24 -> -1404 | AX24: =IF(AU24<>0,AV24/AU24,"-") -> 0.73077661 | AY24: =+C24+G24+K24+O24+S24+W24+AA24+AE24+AI24+AM24+AQ24+AU24 -> 65560 | AZ24: =+D24+H24+L24+P24+T24+X24+AB24+AF24+AJ24+AN24+AR24+AV24 -> 55635 | BA24: =+AZ24-AY24 -> -9925 | BB24: =IF(AY24<>0,AZ24/AY24,"-") -> 0.84861196
B25: =+B19 -> 村 | C25: =+C13-C19 -> 637.5 | D25: =+PL推移!D24 -> 508 | E25: =+D25-C25 -> -129.5 | F25: =IF(C25<>0,D25/C25,"-") -> 0.79686275 | G25: =+G13-G19 -> 637.5 | H25: =+PL推移!F24 -> 519 | I25: =+H25-G25 -> -118.5 | J25: =IF(G25<>0,H25/G25,"-") -> 0.81411765 | K25: =+K13-K19 -> 637.5 | L25: =+PL推移!H24 -> 543 | M25: =+L25-K25 -> -94.5 | N25: =IF(K25<>0,L25/K25,"-") -> 0.85176471 | O25: =+O13-O19 -> 637.5 | P25: =+PL推移!J24 -> 435 | Q25: =+P25-O25 -> -202.5 | R25: =IF(O25<>0,P25/O25,"-") -> 0.68235294 | S25: =+S13-S19 -> 637.5 | T25: =+T13-T19 -> 462 | U25: =+T25-S25 -> -175.5 | V25: =IF(S25<>0,T25/S25,"-") -> 0.72470588 | W25: =+W13-W19 -> 637.5 | X25: =+X13-X19 -> 416 | Y25: =+X25-W25 -> -221.5 | Z25: =IF(W25<>0,X25/W25,"-") -> 0.65254902 | AA25: =+AA13-AA19 -> 637.5 | AB25: =+AB13-AB19 -> 503 | AC25: =+AB25-AA25 -> -134.5 | AD25: =IF(AA25<>0,AB25/AA25,"-") -> 0.78901961 | AE25: =+AE13-AE19 -> 637.5 | AF25: =+PL推移!R24 -> 496 | AG25: =+AF25-AE25 -> -141.5 | AH25: =IF(AE25<>0,AF25/AE25,"-") -> 0.77803922 | AI25: =+AI13-AI19 -> 637.5 | AJ25: =+AJ13-AJ19 -> 496 | AK25: =+AJ25-AI25 -> -141.5 | AL25: =IF(AI25<>0,AJ25/AI25,"-") -> 0.77803922 | AM25: =+AM13-AM19 -> 637.5 | AN25: =+AN13-AN19 -> 406 | AO25: =+AN25-AM25 -> -231.5 | AP25: =IF(AM25<>0,AN25/AM25,"-") -> 0.63686275 | AQ25: =+AQ13-AQ19 -> 637.5 | AR25: =+AR13-AR19 -> 509 | AS25: =+AR25-AQ25 -> -128.5 | AT25: =IF(AQ25<>0,AR25/AQ25,"-") -> 0.79843137 | AU25: =+AU13-AU19 -> 637.5 | AV25: =+AV13-AV19 -> 534 | AW25: =+AV25-AU25 -> -103.5 | AX25: =IF(AU25<>0,AV25/AU25,"-") -> 0.83764706 | AY25: =+C25+G25+K25+O25+S25+W25+AA25+AE25+AI25+AM25+AQ25+AU25 -> 7650 | AZ25: =+D25+H25+L25+P25+T25+X25+AB25+AF25+AJ25+AN25+AR25+AV25 -> 5827 | BA25: =+AZ25-AY25 -> -1823 | BB25: =IF(AY25<>0,AZ25/AY25,"-") -> 0.76169935
B26: =+B20 -> 弁当 | C26: =+C14-C20 -> 192.5 | D26: =+PL推移!D25 -> 316 | E26: =+D26-C26 -> 123.5 | F26: =IF(C26<>0,D26/C26,"-") -> 1.6415584 | G26: =+G14-G20 -> 192.5 | H26: =+PL推移!F25 -> 203 | I26: =+H26-G26 -> 10.5 | J26: =IF(G26<>0,H26/G26,"-") -> 1.0545455 | K26: =+K14-K20 -> 192.5 | L26: =+PL推移!H25 -> 131 | M26: =+L26-K26 -> -61.5 | N26: =IF(K26<>0,L26/K26,"-") -> 0.68051948 | O26: =+O14-O20 -> 192.5 | P26: =+PL推移!J25 -> 109 | Q26: =+P26-O26 -> -83.5 | R26: =IF(O26<>0,P26/O26,"-") -> 0.56623377 | S26: =+S14-S20 -> 192.5 | T26: =+T14-T20 -> 146 | U26: =+T26-S26 -> -46.5 | V26: =IF(S26<>0,T26/S26,"-") -> 0.75844156 | W26: =+W14-W20 -> 192.5 | X26: =+X14-X20 -> 189 | Y26: =+X26-W26 -> -3.5 | Z26: =IF(W26<>0,X26/W26,"-") -> 0.98181818 | AA26: =+AA14-AA20 -> 192.5 | AB26: =+AB14-AB20 -> 189 | AC26: =+AB26-AA26 -> -3.5 | AD26: =IF(AA26<>0,AB26/AA26,"-") -> 0.98181818 | AE26: =+AE14-AE20 -> 192.5 | AF26: =+PL推移!R25 -> 113 | AG26: =+AF26-AE26 -> -79.5 | AH26: =IF(AE26<>0,AF26/AE26,"-") -> 0.58701299 | AI26: =+AI14-AI20 -> 192.5 | AJ26: =+AJ14-AJ20 -> 223 | AK26: =+AJ26-AI26 -> 30.5 | AL26: =IF(AI26<>0,AJ26/AI26,"-") -> 1.1584416 | AM26: =+AM14-AM20 -> 210 | AN26: =+AN14-AN20 -> 258 | AO26: =+AN26-AM26 -> 48 | AP26: =IF(AM26<>0,AN26/AM26,"-") -> 1.2285714 | AQ26: =+AQ14-AQ20 -> 210 | AR26: =+AR14-AR20 -> 329 | AS26: =+AR26-AQ26 -> 119 | AT26: =IF(AQ26<>0,AR26/AQ26,"-") -> 1.5666667 | AU26: =+AU14-AU20 -> 210 | AV26: =+AV14-AV20 -> 247 | AW26: =+AV26-AU26 -> 37 | AX26: =IF(AU26<>0,AV26/AU26,"-") -> 1.1761905 | AY26: =+C26+G26+K26+O26+S26+W26+AA26+AE26+AI26+AM26+AQ26+AU26 -> 2362.5 | AZ26: =+D26+H26+L26+P26+T26+X26+AB26+AF26+AJ26+AN26+AR26+AV26 -> 2453 | BA26: =+AZ26-AY26 -> 90.5 | BB26: =IF(AY26<>0,AZ26/AY26,"-") -> 1.0383069
B27: =+B21 -> シェア | C27: =+C15-C21 -> 105 | D27: =+PL推移!D26 -> 90 | E27: =+D27-C27 -> -15 | F27: =IF(C27<>0,D27/C27,"-") -> 0.85714286 | G27: =+G15-G21 -> 105 | H27: =+PL推移!F26 -> 126 | I27: =+H27-G27 -> 21 | J27: =IF(G27<>0,H27/G27,"-") -> 1.2 | K27: =+K15-K21 -> 105 | L27: =+PL推移!H26 -> 50 | M27: =+L27-K27 -> -55 | N27: =IF(K27<>0,L27/K27,"-") -> 0.47619048 | O27: =+O15-O21 -> 105 | P27: =+PL推移!J26 -> 199 | Q27: =+P27-O27 -> 94 | R27: =IF(O27<>0,P27/O27,"-") -> 1.8952381 | S27: =+S15-S21 -> 105 | T27: =+T15-T21 -> 86 | U27: =+T27-S27 -> -19 | V27: =IF(S27<>0,T27/S27,"-") -> 0.81904762 | W27: =+W15-W21 -> 105 | X27: =+X15-X21 -> 87 | Y27: =+X27-W27 -> -18 | Z27: =IF(W27<>0,X27/W27,"-") -> 0.82857143 | AA27: =+AA15-AA21 -> 105 | AB27: =+AB15-AB21 -> 74 | AC27: =+AB27-AA27 -> -31 | AD27: =IF(AA27<>0,AB27/AA27,"-") -> 0.7047619 | AE27: =+AE15-AE21 -> 105 | AF27: =+PL推移!R26 -> 63 | AG27: =+AF27-AE27 -> -42 | AH27: =IF(AE27<>0,AF27/AE27,"-") -> 0.6 | AI27: =+AI15-AI21 -> 105 | AJ27: =+AJ15-AJ21 -> 87 | AK27: =+AJ27-AI27 -> -18 | AL27: =IF(AI27<>0,AJ27/AI27,"-") -> 0.82857143 | AM27: =+AM15-AM21 -> 105 | AN27: =+AN15-AN21 -> 70 | AO27: =+AN27-AM27 -> -35 | AP27: =IF(AM27<>0,AN27/AM27,"-") -> 0.66666667 | AQ27: =+AQ15-AQ21 -> 105 | AR27: =+AR15-AR21 -> 58 | AS27: =+AR27-AQ27 -> -47 | AT27: =IF(AQ27<>0,AR27/AQ27,"-") -> 0.55238095 | AU27: =+AU15-AU21 -> 105 | AV27: =+AV15-AV21 -> 53 | AW27: =+AV27-AU27 -> -52 | AX27: =IF(AU27<>0,AV27/AU27,"-") -> 0.5047619 | AY27: =+C27+G27+K27+O27+S27+W27+AA27+AE27+AI27+AM27+AQ27+AU27 -> 1260 | AZ27: =+D27+H27+L27+P27+T27+X27+AB27+AF27+AJ27+AN27+AR27+AV27 -> 1043 | BA27: =+AZ27-AY27 -> -217 | BB27: =IF(AY27<>0,AZ27/AY27,"-") -> 0.82777778
B28: =+B22 -> サウナ | C28: =+C16-C22 -> 900 | D28: =+PL推移!D27 -> 719 | E28: =+D28-C28 -> -181 | F28: =IF(C28<>0,D28/C28,"-") -> 0.79888889 | G28: =+G16-G22 -> 2520 | H28: =+PL推移!F27 -> 1569 | I28: =+H28-G28 -> -951 | J28: =IF(G28<>0,H28/G28,"-") -> 0.62261905 | K28: =+K16-K22 -> 900 | L28: =+PL推移!H27 -> 759 | M28: =+L28-K28 -> -141 | N28: =IF(K28<>0,L28/K28,"-") -> 0.84333333 | O28: =+O16-O22 -> 900 | P28: =+PL推移!J27 -> 1150 | Q28: =+P28-O28 -> 250 | R28: =IF(O28<>0,P28/O28,"-") -> 1.2777778 | S28: =+S16-S22 -> 900 | T28: =+T16-T22 -> 637 | U28: =+T28-S28 -> -263 | V28: =IF(S28<>0,T28/S28,"-") -> 0.70777778 | W28: =+W16-W22 -> 900 | X28: =+X16-X22 -> 993 | Y28: =+X28-W28 -> 93 | Z28: =IF(W28<>0,X28/W28,"-") -> 1.1033333 | AA28: =+AA16-AA22 -> 900 | AB28: =+AB16-AB22 -> 712 | AC28: =+AB28-AA28 -> -188 | AD28: =IF(AA28<>0,AB28/AA28,"-") -> 0.79111111 | AE28: =+AE16-AE22 -> 900 | AF28: =+PL推移!R27 -> 607 | AG28: =+AF28-AE28 -> -293 | AH28: =IF(AE28<>0,AF28/AE28,"-") -> 0.67444444 | AI28: =+AI16-AI22 -> 900 | AJ28: =+AJ16-AJ22 -> 655 | AK28: =+AJ28-AI28 -> -245 | AL28: =IF(AI28<>0,AJ28/AI28,"-") -> 0.72777778 | AM28: =+AM16-AM22 -> 900 | AN28: =+AN16-AN22 -> 581 | AO28: =+AN28-AM28 -> -319 | AP28: =IF(AM28<>0,AN28/AM28,"-") -> 0.64555556 | AQ28: =+AQ16-AQ22 -> 900 | AR28: =+AR16-AR22 -> 532 | AS28: =+AR28-AQ28 -> -368 | AT28: =IF(AQ28<>0,AR28/AQ28,"-") -> 0.59111111 | AU28: =+AU16-AU22 -> 900 | AV28: =+AV16-AV22 -> 541 | AW28: =+AV28-AU28 -> -359 | AX28: =IF(AU28<>0,AV28/AU28,"-") -> 0.60111111 | AY28: =+C28+G28+K28+O28+S28+W28+AA28+AE28+AI28+AM28+AQ28+AU28 -> 12420 | AZ28: =+D28+H28+L28+P28+T28+X28+AB28+AF28+AJ28+AN28+AR28+AV28 -> 9455 | BA28: =+AZ28-AY28 -> -2965 | BB28: =IF(AY28<>0,AZ28/AY28,"-") -> 0.76127214
A29: 販売管理費 | C29: =SUM(C30:C50) -> 7110.399 | D29: =SUM(D30:D50) -> 7029.379 | E29: =SUM(E30:E50) -> -81.02 | F29: =IF(C29<>0,D29/C29,"-") -> 0.98860542 | G29: =SUM(G30:G50) -> 6970.399 | H29: =+PL推移!F28 -> 6877.286 | I29: =SUM(I30:I50) -> -93.113 | J29: =IF(G29<>0,H29/G29,"-") -> 0.98664165 | K29: =SUM(K30:K50) -> 7236.034 | L29: =+PL推移!H28 -> 6946.261 | M29: =SUM(M30:M50) -> -289.773 | N29: =IF(K29<>0,L29/K29,"-") -> 0.95995417 | O29: =SUM(O30:O50) -> 6896.034 | P29: =+PL推移!J28 -> 6577.418 | Q29: =SUM(Q30:Q50) -> -318.616 | R29: =IF(O29<>0,P29/O29,"-") -> 0.95379721 | S29: =SUM(S30:S50) -> 6784.514 | T29: =+PL推移!L28 -> 6664.637 | U29: =SUM(U30:U50) -> -119.877 | V29: =IF(S29<>0,T29/S29,"-") -> 0.98233079 | W29: =SUM(W30:W50) -> 7667.014 | X29: =+PL推移!P28 -> 7154.905 | Y29: =SUM(Y30:Y50) -> -234.444 | Z29: =IF(W29<>0,X29/W29,"-") -> 0.9332062 | AA29: =+収支計画!M56/1000 -> 6789.514 | AB29: =+PL推移!P28 -> 7154.905 | AC29: =SUM(AC30:AC50) -> 365.391 | AD29: =IF(AA29<>0,AB29/AA29,"-") -> 1.053817 | AE29: =+収支計画!N56/1000 -> 6789.514 | AF29: =+PL推移!R28 -> 9370.861 | AG29: =SUM(AG30:AG50) -> 2581.347 | AH29: =IF(AE29<>0,AF29/AE29,"-") -> 1.3801961 | AI29: =+収支計画!O56/1000 -> 7270.014 | AJ29: =+PL推移!T28 -> 7545.12 | AK29: =SUM(AK30:AK50) -> 275.106 | AL29: =IF(AI29<>0,AJ29/AI29,"-") -> 1.0378412 | AM29: =+収支計画!P56/1000 -> 7019.014 | AN29: =+PL推移!V28 -> 6818.127 | AO29: =+AN29-AM29 -> -200.887 | AP29: =IF(AM29<>0,AN29/AM29,"-") -> 0.9713796 | AQ29: =SUM(AQ30:AQ50) -> 6792.014 | AR29: =+PL推移!X28 -> 6533.591 | AS29: =+AR29-AQ29 -> -258.423 | AT29: =IF(AQ29<>0,AR29/AQ29,"-") -> 0.96195193 | AU29: =+収支計画!R56/1000 -> 6842.014 | AV29: =+PL推移!Z28 -> 6706.484 | AW29: =+AV29-AU29 -> -135.53 | AX29: =IF(AU29<>0,AV29/AU29,"-") -> 0.98019151 | AY29: =+C29+G29+K29+O29+S29+W29+AA29+AE29+AI29+AM29+AQ29+AU29 -> 84166.478 | AZ29: =+D29+H29+L29+P29+T29+X29+AB29+AF29+AJ29+AN29+AR29+AV29 -> 85378.974 | BA29: =+AZ29-AY29 -> 1212.496 | BB29: =IF(AY29<>0,AZ29/AY29,"-") -> 1.0144059
B30: 人件費 | C30: =+収支計画!G34/1000 -> 2722.319 | D30: =+PL推移!D29 -> 2371.946 | E30: =+D30-C30 -> -350.373 | F30: =IF(C30<>0,D30/C30,"-") -> 0.87129613 | G30: =+収支計画!H34/1000 -> 2722.319 | H30: =+PL推移!F29 -> 2352.858 | I30: =+H30-G30 -> -369.461 | J30: =IF(G30<>0,H30/G30,"-") -> 0.86428446 | K30: =+収支計画!I34/1000 -> 2707.319 | L30: =+PL推移!H29 -> 2266.491 | M30: =+L30-K30 -> -440.828 | N30: =IF(K30<>0,L30/K30,"-") -> 0.83717176 | O30: =+収支計画!J34/1000 -> 2707.319 | P30: =+PL推移!J29 -> 2375.566 | Q30: =+P30-O30 -> -331.753 | R30: =IF(O30<>0,P30/O30,"-") -> 0.87746069 | S30: =+収支計画!K34/1000 -> 2594.319 | T30: =+PL推移!L29 -> 2397.808 | U30: =+T30-S30 -> -196.511 | V30: =IF(S30<>0,T30/S30,"-") -> 0.92425334 | W30: =+収支計画!L34/1000 -> 3019.319 | X30: =+PL推移!N29 -> 2816.608 | Y30: =+X30-W30 -> -202.711 | Z30: =IF(W30<>0,X30/W30,"-") -> 0.93286201 | AA30: =+収支計画!M34/1000 -> 2594.319 | AB30: =+PL推移!P29 -> 2804.184 | AC30: =+AB30-AA30 -> 209.865 | AD30: =IF(AA30<>0,AB30/AA30,"-") -> 1.0808941 | AE30: =+収支計画!N34/1000 -> 2594.319 | AF30: =+PL推移!R29 -> 2790.627 | AG30: =+AF30-AE30 -> 196.308 | AH30: =IF(AE30<>0,AF30/AE30,"-") -> 1.0756684 | AI30: =+収支計画!O34/1000 -> 2849.319 | AJ30: =+PL推移!T29 -> 3189.715 | AK30: =+AJ30-AI30 -> 340.396 | AL30: =IF(AI30<>0,AJ30/AI30,"-") -> 1.1194657 | AM30: =+収支計画!P34/1000 -> 2601.819 | AN30: =+PL推移!V29 -> 2649.797 | AO30: =+AN30-AM30 -> 47.978 | AP30: =IF(AM30<>0,AN30/AM30,"-") -> 1.0184402 | AQ30: =+収支計画!Q34/1000 -> 2601.819 | AR30: =+PL推移!X29 -> 2670.396 | AS30: =+AR30-AQ30 -> 68.577 | AT30: =IF(AQ30<>0,AR30/AQ30,"-") -> 1.0263573 | AU30: =+収支計画!R34/1000 -> 2601.819 | AV30: =+PL推移!Z29 -> 2522.78 | AW30: =+AV30-AU30 -> -79.039 | AX30: =IF(AU30<>0,AV30/AU30,"-") -> 0.96962164 | AY30: =+C30+G30+K30+O30+S30+W30+AA30+AE30+AI30+AM30+AQ30+AU30 -> 32316.328 | AZ30: =+D30+H30+L30+P30+T30+X30+AB30+AF30+AJ30+AN30+AR30+AV30 -> 31208.776 | BA30: =+AZ30-AY30 -> -1107.552 | BB30: =IF(AY30<>0,AZ30/AY30,"-") -> 0.96572779
B31: 旅費交通費 | C31: =+収支計画!G35/1000 -> 50 | D31: =+PL推移!D30 -> 42.401 | E31: =+D31-C31 -> -7.599 | F31: =IF(C31<>0,D31/C31,"-") -> 0.84802 | G31: =+収支計画!H35/1000 -> 50 | H31: =+PL推移!F30 -> 43.147 | I31: =+H31-G31 -> -6.853 | J31: =IF(G31<>0,H31/G31,"-") -> 0.86294 | K31: =+収支計画!I35/1000 -> 50 | L31: =+PL推移!H30 -> 27.646 | M31: =+L31-K31 -> -22.354 | N31: =IF(K31<>0,L31/K31,"-") -> 0.55292 | O31: =+収支計画!J35/1000 -> 50 | P31: =+PL推移!J30 -> 41.601 | Q31: =+P31-O31 -> -8.399 | R31: =IF(O31<>0,P31/O31,"-") -> 0.83202 | S31: =+収支計画!K35/1000 -> 50 | T31: =+PL推移!L30 -> 47.715 | U31: =+T31-S31 -> -2.285 | V31: =IF(S31<>0,T31/S31,"-") -> 0.9543 | W31: =+収支計画!L35/1000 -> 55 | X31: =+PL推移!N30 -> 40.511 | Y31: =+X31-W31 -> -14.489 | Z31: =IF(W31<>0,X31/W31,"-") -> 0.73656364 | AA31: =+収支計画!M35/1000 -> 55 | AB31: =+PL推移!P30 -> 34.183 | AC31: =+AB31-AA31 -> -20.817 | AD31: =IF(AA31<>0,AB31/AA31,"-") -> 0.62150909 | AE31: =+収支計画!N35/1000 -> 55 | AF31: =+PL推移!R30 -> 42.182 | AG31: =+AF31-AE31 -> -12.818 | AH31: =IF(AE31<>0,AF31/AE31,"-") -> 0.76694545 | AI31: =+収支計画!O35/1000 -> 55 | AJ31: =+PL推移!T30 -> 54.459 | AK31: =+AJ31-AI31 -> -0.541 | AL31: =IF(AI31<>0,AJ31/AI31,"-") -> 0.99016364 | AM31: =+収支計画!P35/1000 -> 50 | AN31: =+PL推移!V30 -> 46.858 | AO31: =+AN31-AM31 -> -3.142 | AP31: =IF(AM31<>0,AN31/AM31,"-") -> 0.93716 | AQ31: =+収支計画!Q35/1000 -> 50 | AR31: =+PL推移!X30 -> 52.253 | AS31: =+AR31-AQ31 -> 2.253 | AT31: =IF(AQ31<>0,AR31/AQ31,"-") -> 1.04506 | AU31: =+収支計画!R35/1000 -> 50 | AV31: =+PL推移!Z30 -> 42.731 | AW31: =+AV31-AU31 -> -7.269 | AX31: =IF(AU31<>0,AV31/AU31,"-") -> 0.85462 | AY31: =+C31+G31+K31+O31+S31+W31+AA31+AE31+AI31+AM31+AQ31+AU31 -> 620 | AZ31: =+D31+H31+L31+P31+T31+X31+AB31+AF31+AJ31+AN31+AR31+AV31 -> 515.687 | BA31: =+AZ31-AY31 -> -104.313 | BB31: =IF(AY31<>0,AZ31/AY31,"-") -> 0.83175323
B32: 通信費 | C32: =+収支計画!G36/1000 -> 63.05 | D32: =+PL推移!D31 -> 45.779 | E32: =+D32-C32 -> -17.271 | F32: =IF(C32<>0,D32/C32,"-") -> 0.72607454 | G32: =+収支計画!H36/1000 -> 63.05 | H32: =+PL推移!F31 -> 55.395 | I32: =+H32-G32 -> -7.655 | J32: =IF(G32<>0,H32/G32,"-") -> 0.87858842 | K32: =+収支計画!I36/1000 -> 63.05 | L32: =+PL推移!H31 -> 45.57 | M32: =+L32-K32 -> -17.48 | N32: =IF(K32<>0,L32/K32,"-") -> 0.72275971 | O32: =+収支計画!J36/1000 -> 63.05 | P32: =+PL推移!J31 -> 44.794 | Q32: =+P32-O32 -> -18.256 | R32: =IF(O32<>0,P32/O32,"-") -> 0.71045202 | S32: =+収支計画!K36/1000 -> 64.53 | T32: =+PL推移!L31 -> 52.175 | U32: =+T32-S32 -> -12.355 | V32: =IF(S32<>0,T32/S32,"-") -> 0.80853866 | W32: =+収支計画!L36/1000 -> 64.53 | X32: =+PL推移!N31 -> 40.364 | Y32: =+X32-W32 -> -24.166 | Z32: =IF(W32<>0,X32/W32,"-") -> 0.62550752 | AA32: =+収支計画!M36/1000 -> 64.53 | AB32: =+PL推移!P31 -> 54.262 | AC32: =+AB32-AA32 -> -10.268 | AD32: =IF(AA32<>0,AB32/AA32,"-") -> 0.84088021 | AE32: =+収支計画!N36/1000 -> 64.53 | AF32: =+PL推移!R31 -> 70.983 | AG32: =+AF32-AE32 -> 6.453 | AH32: =IF(AE32<>0,AF32/AE32,"-") -> 1.1 | AI32: =+収支計画!O36/1000 -> 64.53 | AJ32: =+PL推移!T31 -> 54.59 | AK32: =+AJ32-AI32 -> -9.94 | AL32: =IF(AI32<>0,AJ32/AI32,"-") -> 0.84596312 | AM32: =+収支計画!P36/1000 -> 64.53 | AN32: =+PL推移!V31 -> 122.039 | AO32: =+AN32-AM32 -> 57.509 | AP32: =IF(AM32<>0,AN32/AM32,"-") -> 1.8911979 | AQ32: =+収支計画!Q36/1000 -> 64.53 | AR32: =+PL推移!X31 -> 54.629 | AS32: =+AR32-AQ32 -> -9.901 | AT32: =IF(AQ32<>0,AR32/AQ32,"-") -> 0.84656749 | AU32: =+収支計画!R36/1000 -> 64.53 | AV32: =+PL推移!Z31 -> 51.282 | AW32: =+AV32-AU32 -> -13.248 | AX32: =IF(AU32<>0,AV32/AU32,"-") -> 0.79470014 | AY32: =+C32+G32+K32+O32+S32+W32+AA32+AE32+AI32+AM32+AQ32+AU32 -> 768.44 | AZ32: =+D32+H32+L32+P32+T32+X32+AB32+AF32+AJ32+AN32+AR32+AV32 -> 691.862 | BA32: =+AZ32-AY32 -> -76.578 | BB32: =IF(AY32<>0,AZ32/AY32,"-") -> 0.90034616
B33: 開発費 | C33: =+収支計画!G37/1000 -> 0 | D33: =+PL推移!D32 -> 21.289 | E33: =+D33-C33 -> 21.289 | F33: =IF(C33<>0,D33/C33,"-") -> - | G33: =+収支計画!H37/1000 -> 0 | H33: =+PL推移!F32 -> 97.177 | I33: =+H33-G33 -> 97.177 | J33: =IF(G33<>0,H33/G33,"-") -> - | K33: =+収支計画!I37/1000 -> 0 | L33: =+PL推移!H32 -> 106.992 | M33: =+L33-K33 -> 106.992 | N33: =IF(K33<>0,L33/K33,"-") -> - | O33: =+収支計画!J37/1000 -> 0 | P33: =+PL推移!J32 -> 148.075 | Q33: =+P33-O33 -> 148.075 | R33: =IF(O33<>0,P33/O33,"-") -> - | S33: =+収支計画!K37/1000 -> 0 | T33: =+PL推移!L32 -> 79.685 | U33: =+T33-S33 -> 79.685 | V33: =IF(S33<>0,T33/S33,"-") -> - | W33: =+収支計画!L37/1000 -> 0 | X33: =+PL推移!N32 -> 0 | Y33: =+X33-W33 -> 0 | Z33: =IF(W33<>0,X33/W33,"-") -> - | AA33: =+収支計画!M37/1000 -> 0 | AB33: =+PL推移!P32 -> 0 | AC33: =+AB33-AA33 -> 0 | AD33: =IF(AA33<>0,AB33/AA33,"-") -> - | AE33: =+収支計画!N37/1000 -> 0 | AF33: =+PL推移!R32 -> 0 | AG33: =+AF33-AE33 -> 0 | AH33: =IF(AE33<>0,AF33/AE33,"-") -> - | AI33: =+収支計画!O37/1000 -> 0 | AJ33: =+PL推移!T32 -> 0 | AK33: =+AJ33-AI33 -> 0 | AL33: =IF(AI33<>0,AJ33/AI33,"-") -> - | AM33: =+収支計画!P37/1000 -> 0 | AN33: =+PL推移!V32 -> 0 | AO33: =+AN33-AM33 -> 0 | AP33: =IF(AM33<>0,AN33/AM33,"-") -> - | AQ33: =+収支計画!Q37/1000 -> 0 | AR33: =+PL推移!X32 -> 0 | AS33: =+AR33-AQ33 -> 0 | AT33: =IF(AQ33<>0,AR33/AQ33,"-") -> - | AU33: =+収支計画!R37/1000 -> 0 | AV33: =+PL推移!Z32 -> 0 | AW33: =+AV33-AU33 -> 0 | AX33: =IF(AU33<>0,AV33/AU33,"-") -> - | AY33: =+C33+G33+K33+O33+S33+W33+AA33+AE33+AI33+AM33+AQ33+AU33 -> 0 | AZ33: =+D33+H33+L33+P33+T33+X33+AB33+AF33+AJ33+AN33+AR33+AV33 -> 453.218 | BA33: =+AZ33-AY33 -> 453.218 | BB33: =IF(AY33<>0,AZ33/AY33,"-") -> -
B34: 交際費 | C34: =+収支計画!G38/1000 -> 0 | D34: =+PL推移!D33 -> 0 | E34: =+D34-C34 -> 0 | F34: =IF(C34<>0,D34/C34,"-") -> - | G34: =+収支計画!H38/1000 -> 0 | H34: =+PL推移!F33 -> 0 | I34: =+H34-G34 -> 0 | J34: =IF(G34<>0,H34/G34,"-") -> - | K34: =+収支計画!I38/1000 -> 0 | L34: =+PL推移!H33 -> 0 | M34: =+L34-K34 -> 0 | N34: =IF(K34<>0,L34/K34,"-") -> - | O34: =+収支計画!J38/1000 -> 0 | P34: =+PL推移!J33 -> 0 | Q34: =+P34-O34 -> 0 | R34: =IF(O34<>0,P34/O34,"-") -> - | S34: =+収支計画!K38/1000 -> 0 | T34: =+PL推移!L33 -> 0 | U34: =+T34-S34 -> 0 | V34: =IF(S34<>0,T34/S34,"-") -> - | W34: =+収支計画!L38/1000 -> 0 | X34: =+PL推移!N33 -> 0 | Y34: =+X34-W34 -> 0 | Z34: =IF(W34<>0,X34/W34,"-") -> - | AA34: =+収支計画!M38/1000 -> 0 | AB34: =+PL推移!P33 -> 0 | AC34: =+AB34-AA34 -> 0 | AD34: =IF(AA34<>0,AB34/AA34,"-") -> - | AE34: =+収支計画!N38/1000 -> 0 | AF34: =+PL推移!R33 -> 0 | AG34: =+AF34-AE34 -> 0 | AH34: =IF(AE34<>0,AF34/AE34,"-") -> - | AI34: =+収支計画!O38/1000 -> 0 | AJ34: =+PL推移!T33 -> 0 | AK34: =+AJ34-AI34 -> 0 | AL34: =IF(AI34<>0,AJ34/AI34,"-") -> - | AM34: =+収支計画!P38/1000 -> 0 | AN34: =+PL推移!V33 -> 0 | AO34: =+AN34-AM34 -> 0 | AP34: =IF(AM34<>0,AN34/AM34,"-") -> - | AQ34: =+収支計画!Q38/1000 -> 0 | AR34: =+PL推移!X33 -> 0 | AS34: =+AR34-AQ34 -> 0 | AT34: =IF(AQ34<>0,AR34/AQ34,"-") -> - | AU34: =+収支計画!R38/1000 -> 0 | AV34: =+PL推移!Z33 -> 0 | AW34: =+AV34-AU34 -> 0 | AX34: =IF(AU34<>0,AV34/AU34,"-") -> - | AY34: =+C34+G34+K34+O34+S34+W34+AA34+AE34+AI34+AM34+AQ34+AU34 -> 0 | AZ34: =+D34+H34+L34+P34+T34+X34+AB34+AF34+AJ34+AN34+AR34+AV34 -> 0 | BA34: =+AZ34-AY34 -> 0 | BB34: =IF(AY34<>0,AZ34/AY34,"-") -> -
B35: 会議費 | C35: =+収支計画!G39/1000 -> 10 | D35: =+PL推移!D34 -> 0 | E35: =+D35-C35 -> -10 | F35: =IF(C35<>0,D35/C35,"-") -> 0 | G35: =+収支計画!H39/1000 -> 0 | H35: =+PL推移!F34 -> 0 | I35: =+H35-G35 -> 0 | J35: =IF(G35<>0,H35/G35,"-") -> - | K35: =+収支計画!I39/1000 -> 0 | L35: =+PL推移!H34 -> 0 | M35: =+L35-K35 -> 0 | N35: =IF(K35<>0,L35/K35,"-") -> - | O35: =+収支計画!J39/1000 -> 0 | P35: =+PL推移!J34 -> 0 | Q35: =+P35-O35 -> 0 | R35: =IF(O35<>0,P35/O35,"-") -> - | S35: =+収支計画!K39/1000 -> 0 | T35: =+PL推移!L34 -> 0 | U35: =+T35-S35 -> 0 | V35: =IF(S35<>0,T35/S35,"-") -> - | W35: =+収支計画!L39/1000 -> 20 | X35: =+PL推移!N34 -> 0 | Y35: =+X35-W35 -> -20 | Z35: =IF(W35<>0,X35/W35,"-") -> 0 | AA35: =+収支計画!M39/1000 -> 0 | AB35: =+PL推移!P34 -> 0 | AC35: =+AB35-AA35 -> 0 | AD35: =IF(AA35<>0,AB35/AA35,"-") -> - | AE35: =+収支計画!N39/1000 -> 0 | AF35: =+PL推移!R34 -> 0 | AG35: =+AF35-AE35 -> 0 | AH35: =IF(AE35<>0,AF35/AE35,"-") -> - | AI35: =+収支計画!O39/1000 -> 20 | AJ35: =+PL推移!T34 -> 0 | AK35: =+AJ35-AI35 -> -20 | AL35: =IF(AI35<>0,AJ35/AI35,"-") -> 0 | AM35: =+収支計画!P39/1000 -> 0 | AN35: =+PL推移!V34 -> 0 | AO35: =+AN35-AM35 -> 0 | AP35: =IF(AM35<>0,AN35/AM35,"-") -> - | AQ35: =+収支計画!Q39/1000 -> 0 | AR35: =+PL推移!X34 -> 0 | AS35: =+AR35-AQ35 -> 0 | AT35: =IF(AQ35<>0,AR35/AQ35,"-") -> - | AU35: =+収支計画!R39/1000 -> 0 | AV35: =+PL推移!Z34 -> 0 | AW35: =+AV35-AU35 -> 0 | AX35: =IF(AU35<>0,AV35/AU35,"-") -> - | AY35: =+C35+G35+K35+O35+S35+W35+AA35+AE35+AI35+AM35+AQ35+AU35 -> 50 | AZ35: =+D35+H35+L35+P35+T35+X35+AB35+AF35+AJ35+AN35+AR35+AV35 -> 0 | BA35: =+AZ35-AY35 -> -50 | BB35: =IF(AY35<>0,AZ35/AY35,"-") -> 0
B36: 減価償却費 | C36: =+収支計画!G40/1000 -> 749.954 | D36: =+PL推移!D35 -> 690.589 | E36: =+D36-C36 -> -59.365 | F36: =IF(C36<>0,D36/C36,"-") -> 0.92084181 | G36: =+収支計画!H40/1000 -> 749.954 | H36: =+PL推移!F35 -> 690.589 | I36: =+H36-G36 -> -59.365 | J36: =IF(G36<>0,H36/G36,"-") -> 0.92084181 | K36: =+収支計画!I40/1000 -> 690.589 | L36: =+PL推移!H35 -> 690.589 | M36: =+L36-K36 -> 0 | N36: =IF(K36<>0,L36/K36,"-") -> 1 | O36: =+収支計画!J40/1000 -> 690.589 | P36: =+PL推移!J35 -> 690.589 | Q36: =+P36-O36 -> 0 | R36: =IF(O36<>0,P36/O36,"-") -> 1 | S36: =+収支計画!K40/1000 -> 690.589 | T36: =+PL推移!L35 -> 690.589 | U36: =+T36-S36 -> 0 | V36: =IF(S36<>0,T36/S36,"-") -> 1 | W36: =+収支計画!L40/1000 -> 690.589 | X36: =+PL推移!N35 -> 690.589 | Y36: =+X36-W36 -> 0 | Z36: =IF(W36<>0,X36/W36,"-") -> 1 | AA36: =+収支計画!M40/1000 -> 690.589 | AB36: =+PL推移!P35 -> 690.589 | AC36: =+AB36-AA36 -> 0 | AD36: =IF(AA36<>0,AB36/AA36,"-") -> 1 | AE36: =+収支計画!N40/1000 -> 690.589 | AF36: =+PL推移!R35 -> 690.589 | AG36: =+AF36-AE36 -> 0 | AH36: =IF(AE36<>0,AF36/AE36,"-") -> 1 | AI36: =+収支計画!O40/1000 -> 690.589 | AJ36: =+PL推移!T35 -> 690.589 | AK36: =+AJ36-AI36 -> 0 | AL36: =IF(AI36<>0,AJ36/AI36,"-") -> 1 | AM36: =+収支計画!P40/1000 -> 690.589 | AN36: =+PL推移!V35 -> 690.589 | AO36: =+AN36-AM36 -> 0 | AP36: =IF(AM36<>0,AN36/AM36,"-") -> 1 | AQ36: =+収支計画!Q40/1000 -> 690.589 | AR36: =+PL推移!X35 -> 690.589 | AS36: =+AR36-AQ36 -> 0 | AT36: =IF(AQ36<>0,AR36/AQ36,"-") -> 1 | AU36: =+収支計画!R40/1000 -> 690.589 | AV36: =+PL推移!Z35 -> 690.589 | AW36: =+AV36-AU36 -> 0 | AX36: =IF(AU36<>0,AV36/AU36,"-") -> 1 | AY36: =+C36+G36+K36+O36+S36+W36+AA36+AE36+AI36+AM36+AQ36+AU36 -> 8405.798 | AZ36: =+D36+H36+L36+P36+T36+X36+AB36+AF36+AJ36+AN36+AR36+AV36 -> 8287.068 | BA36: =+AZ36-AY36 -> -118.73 | BB36: =IF(AY36<>0,AZ36/AY36,"-") -> 0.98587523
B37: 賃借料 | C37: =+収支計画!G41/1000 -> 30 | D37: =+PL推移!D36 -> 30 | E37: =+D37-C37 -> 0 | F37: =IF(C37<>0,D37/C37,"-") -> 1 | G37: =+収支計画!H41/1000 -> 30 | H37: =+PL推移!F36 -> 30 | I37: =+H37-G37 -> 0 | J37: =IF(G37<>0,H37/G37,"-") -> 1 | K37: =+収支計画!I41/1000 -> 30 | L37: =+PL推移!H36 -> 30 | M37: =+L37-K37 -> 0 | N37: =IF(K37<>0,L37/K37,"-") -> 1 | O37: =+収支計画!J41/1000 -> 30 | P37: =+PL推移!J36 -> 30 | Q37: =+P37-O37 -> 0 | R37: =IF(O37<>0,P37/O37,"-") -> 1 | S37: =+収支計画!K41/1000 -> 30 | T37: =+PL推移!L36 -> 30 | U37: =+T37-S37 -> 0 | V37: =IF(S37<>0,T37/S37,"-") -> 1 | W37: =+収支計画!L41/1000 -> 30 | X37: =+PL推移!N36 -> 30 | Y37: =+X37-W37 -> 0 | Z37: =IF(W37<>0,X37/W37,"-") -> 1 | AA37: =+収支計画!M41/1000 -> 30 | AB37: =+PL推移!P36 -> 30 | AC37: =+AB37-AA37 -> 0 | AD37: =IF(AA37<>0,AB37/AA37,"-") -> 1 | AE37: =+収支計画!N41/1000 -> 30 | AF37: =+PL推移!R36 -> 30 | AG37: =+AF37-AE37 -> 0 | AH37: =IF(AE37<>0,AF37/AE37,"-") -> 1 | AI37: =+収支計画!O41/1000 -> 30 | AJ37: =+PL推移!T36 -> 30 | AK37: =+AJ37-AI37 -> 0 | AL37: =IF(AI37<>0,AJ37/AI37,"-") -> 1 | AM37: =+収支計画!P41/1000 -> 30 | AN37: =+PL推移!V36 -> 30 | AO37: =+AN37-AM37 -> 0 | AP37: =IF(AM37<>0,AN37/AM37,"-") -> 1 | AQ37: =+収支計画!Q41/1000 -> 30 | AR37: =+PL推移!X36 -> 30 | AS37: =+AR37-AQ37 -> 0 | AT37: =IF(AQ37<>0,AR37/AQ37,"-") -> 1 | AU37: =+収支計画!R41/1000 -> 30 | AV37: =+PL推移!Z36 -> 30 | AW37: =+AV37-AU37 -> 0 | AX37: =IF(AU37<>0,AV37/AU37,"-") -> 1 | AY37: =+C37+G37+K37+O37+S37+W37+AA37+AE37+AI37+AM37+AQ37+AU37 -> 360 | AZ37: =+D37+H37+L37+P37+T37+X37+AB37+AF37+AJ37+AN37+AR37+AV37 -> 360 | BA37: =+AZ37-AY37 -> 0 | BB37: =IF(AY37<>0,AZ37/AY37,"-") -> 1
B38: 地代家賃 | C38: =+収支計画!G42/1000 -> 1645.661 | D38: =+PL推移!D37 -> 1645.661 | E38: =+D38-C38 -> 0 | F38: =IF(C38<>0,D38/C38,"-") -> 1 | G38: =+収支計画!H42/1000 -> 1645.661 | H38: =+PL推移!F37 -> 1645.661 | I38: =+H38-G38 -> 0 | J38: =IF(G38<>0,H38/G38,"-") -> 1 | K38: =+収支計画!I42/1000 -> 1645.661 | L38: =+PL推移!H37 -> 1645.661 | M38: =+L38-K38 -> 0 | N38: =IF(K38<>0,L38/K38,"-") -> 1 | O38: =+収支計画!J42/1000 -> 1645.661 | P38: =+PL推移!J37 -> 1645.661 | Q38: =+P38-O38 -> 0 | R38: =IF(O38<>0,P38/O38,"-") -> 1 | S38: =+収支計画!K42/1000 -> 1645.661 | T38: =+PL推移!L37 -> 1645.661 | U38: =+T38-S38 -> 0 | V38: =IF(S38<>0,T38/S38,"-") -> 1 | W38: =+収支計画!L42/1000 -> 1645.661 | X38: =+PL推移!N37 -> 1645.661 | Y38: =+X38-W38 -> 0 | Z38: =IF(W38<>0,X38/W38,"-") -> 1 | AA38: =+収支計画!M42/1000 -> 1645.661 | AB38: =+PL推移!P37 -> 1645.661 | AC38: =+AB38-AA38 -> 0 | AD38: =IF(AA38<>0,AB38/AA38,"-") -> 1 | AE38: =+収支計画!N42/1000 -> 1645.661 | AF38: =+PL推移!R37 -> 1645.661 | AG38: =+AF38-AE38 -> 0 | AH38: =IF(AE38<>0,AF38/AE38,"-") -> 1 | AI38: =+収支計画!O42/1000 -> 1645.661 | AJ38: =+PL推移!T37 -> 1645.661 | AK38: =+AJ38-AI38 -> 0 | AL38: =IF(AI38<>0,AJ38/AI38,"-") -> 1 | AM38: =+収支計画!P42/1000 -> 1645.661 | AN38: =+PL推移!V37 -> 1645.661 | AO38: =+AN38-AM38 -> 0 | AP38: =IF(AM38<>0,AN38/AM38,"-") -> 1 | AQ38: =+収支計画!Q42/1000 -> 1645.661 | AR38: =+PL推移!X37 -> 1645.661 | AS38: =+AR38-AQ38 -> 0 | AT38: =IF(AQ38<>0,AR38/AQ38,"-") -> 1 | AU38: =+収支計画!R42/1000 -> 1645.661 | AV38: =+PL推移!Z37 -> 1645.661 | AW38: =+AV38-AU38 -> 0 | AX38: =IF(AU38<>0,AV38/AU38,"-") -> 1 | AY38: =+C38+G38+K38+O38+S38+W38+AA38+AE38+AI38+AM38+AQ38+AU38 -> 19747.932 | AZ38: =+D38+H38+L38+P38+T38+X38+AB38+AF38+AJ38+AN38+AR38+AV38 -> 19747.932 | BA38: =+AZ38-AY38 -> 0 | BB38: =IF(AY38<>0,AZ38/AY38,"-") -> 1
B39: リース料 | C39: =+収支計画!G43/1000 -> 49.7 | D39: =+PL推移!D38 -> 49.7 | E39: =+D39-C39 -> 0 | F39: =IF(C39<>0,D39/C39,"-") -> 1 | G39: =+収支計画!H43/1000 -> 49.7 | H39: =+PL推移!F38 -> 49.7 | I39: =+H39-G39 -> 0 | J39: =IF(G39<>0,H39/G39,"-") -> 1 | K39: =+収支計画!I43/1000 -> 49.7 | L39: =+PL推移!H38 -> 49.7 | M39: =+L39-K39 -> 0 | N39: =IF(K39<>0,L39/K39,"-") -> 1 | O39: =+収支計画!J43/1000 -> 49.7 | P39: =+PL推移!J38 -> 49.7 | Q39: =+P39-O39 -> 0 | R39: =IF(O39<>0,P39/O39,"-") -> 1 | S39: =+収支計画!K43/1000 -> 49.7 | T39: =+PL推移!L38 -> 49.7 | U39: =+T39-S39 -> 0 | V39: =IF(S39<>0,T39/S39,"-") -> 1 | W39: =+収支計画!L43/1000 -> 49.7 | X39: =+PL推移!N38 -> 49.7 | Y39: =+X39-W39 -> 0 | Z39: =IF(W39<>0,X39/W39,"-") -> 1 | AA39: =+収支計画!M43/1000 -> 49.7 | AB39: =+PL推移!P38 -> 49.7 | AC39: =+AB39-AA39 -> 0 | AD39: =IF(AA39<>0,AB39/AA39,"-") -> 1 | AE39: =+収支計画!N43/1000 -> 49.7 | AF39: =+PL推移!R38 -> 49.7 | AG39: =+AF39-AE39 -> 0 | AH39: =IF(AE39<>0,AF39/AE39,"-") -> 1 | AI39: =+収支計画!O43/1000 -> 49.7 | AJ39: =+PL推移!T38 -> 49.7 | AK39: =+AJ39-AI39 -> 0 | AL39: =IF(AI39<>0,AJ39/AI39,"-") -> 1 | AM39: =+収支計画!P43/1000 -> 49.7 | AN39: =+PL推移!V38 -> 49.7 | AO39: =+AN39-AM39 -> 0 | AP39: =IF(AM39<>0,AN39/AM39,"-") -> 1 | AQ39: =+収支計画!Q43/1000 -> 49.7 | AR39: =+PL推移!X38 -> 77.9 | AS39: =+AR39-AQ39 -> 28.2 | AT39: =IF(AQ39<>0,AR39/AQ39,"-") -> 1.5674044 | AU39: =+収支計画!R43/1000 -> 49.7 | AV39: =+PL推移!Z38 -> 49.7 | AW39: =+AV39-AU39 -> 0 | AX39: =IF(AU39<>0,AV39/AU39,"-") -> 1 | AY39: =+C39+G39+K39+O39+S39+W39+AA39+AE39+AI39+AM39+AQ39+AU39 -> 596.4 | AZ39: =+D39+H39+L39+P39+T39+X39+AB39+AF39+AJ39+AN39+AR39+AV39 -> 624.6 | BA39: =+AZ39-AY39 -> 28.2 | BB39: =IF(AY39<>0,AZ39/AY39,"-") -> 1.0472837
B40: 修繕費 | C40: =+収支計画!G44/1000 -> 10 | D40: =+PL推移!D39 -> 13.5 | E40: =+D40-C40 -> 3.5 | F40: =IF(C40<>0,D40/C40,"-") -> 1.35 | G40: =+収支計画!H44/1000 -> 10 | H40: =+PL推移!F39 -> 57.3 | I40: =+H40-G40 -> 47.3 | J40: =IF(G40<>0,H40/G40,"-") -> 5.73 | K40: =+収支計画!I44/1000 -> 10 | L40: =+PL推移!H39 -> 15 | M40: =+L40-K40 -> 5 | N40: =IF(K40<>0,L40/K40,"-") -> 1.5 | O40: =+収支計画!J44/1000 -> 10 | P40: =+PL推移!J39 -> 0 | Q40: =+P40-O40 -> -10 | R40: =IF(O40<>0,P40/O40,"-") -> 0 | S40: =+収支計画!K44/1000 -> 10 | T40: =+PL推移!L39 -> 20 | U40: =+T40-S40 -> 10 | V40: =IF(S40<>0,T40/S40,"-") -> 2 | W40: =+収支計画!L44/1000 -> 10 | X40: =+PL推移!N39 -> 19 | Y40: =+X40-W40 -> 9 | Z40: =IF(W40<>0,X40/W40,"-") -> 1.9 | AA40: =+収支計画!M44/1000 -> 10 | AB40: =+PL推移!P39 -> 17 | AC40: =+AB40-AA40 -> 7 | AD40: =IF(AA40<>0,AB40/AA40,"-") -> 1.7 | AE40: =+収支計画!N44/1000 -> 10 | AF40: =+PL推移!R39 -> 90.91 | AG40: =+AF40-AE40 -> 80.91 | AH40: =IF(AE40<>0,AF40/AE40,"-") -> 9.091 | AI40: =+収支計画!O44/1000 -> 10 | AJ40: =+PL推移!T39 -> 0 | AK40: =+AJ40-AI40 -> -10 | AL40: =IF(AI40<>0,AJ40/AI40,"-") -> 0 | AM40: =+収支計画!P44/1000 -> 10 | AN40: =+PL推移!V39 -> 0 | AO40: =+AN40-AM40 -> -10 | AP40: =IF(AM40<>0,AN40/AM40,"-") -> 0 | AQ40: =+収支計画!Q44/1000 -> 10 | AR40: =+PL推移!X39 -> 0 | AS40: =+AR40-AQ40 -> -10 | AT40: =IF(AQ40<>0,AR40/AQ40,"-") -> 0 | AU40: =+収支計画!R44/1000 -> 10 | AV40: =+PL推移!Z39 -> 15 | AW40: =+AV40-AU40 -> 5 | AX40: =IF(AU40<>0,AV40/AU40,"-") -> 1.5 | AY40: =+C40+G40+K40+O40+S40+W40+AA40+AE40+AI40+AM40+AQ40+AU40 -> 120 | AZ40: =+D40+H40+L40+P40+T40+X40+AB40+AF40+AJ40+AN40+AR40+AV40 -> 247.71 | BA40: =+AZ40-AY40 -> 127.71 | BB40: =IF(AY40<>0,AZ40/AY40,"-") -> 2.06425
B41: 保険料 | C41: =+収支計画!G45/1000 -> 22.215 | D41: =+PL推移!D40 -> 22.215 | E41: =+D41-C41 -> 0 | F41: =IF(C41<>0,D41/C41,"-") -> 1 | G41: =+収支計画!H45/1000 -> 22.215 | H41: =+PL推移!F40 -> 22.215 | I41: =+H41-G41 -> 0 | J41: =IF(G41<>0,H41/G41,"-") -> 1 | K41: =+収支計画!I45/1000 -> 22.215 | L41: =+PL推移!H40 -> 22.215 | M41: =+L41-K41 -> 0 | N41: =IF(K41<>0,L41/K41,"-") -> 1 | O41: =+収支計画!J45/1000 -> 22.215 | P41: =+PL推移!J40 -> 22.215 | Q41: =+P41-O41 -> 0 | R41: =IF(O41<>0,P41/O41,"-") -> 1 | S41: =+収支計画!K45/1000 -> 22.215 | T41: =+PL推移!L40 -> 22.215 | U41: =+T41-S41 -> 0 | V41: =IF(S41<>0,T41/S41,"-") -> 1 | W41: =+収支計画!L45/1000 -> 22.215 | X41: =+PL推移!N40 -> 28.375 | Y41: =+X41-W41 -> 6.16 | Z41: =IF(W41<>0,X41/W41,"-") -> 1.2772901 | AA41: =+収支計画!M45/1000 -> 22.215 | AB41: =+PL推移!P40 -> 28.375 | AC41: =+AB41-AA41 -> 6.16 | AD41: =IF(AA41<>0,AB41/AA41,"-") -> 1.2772901 | AE41: =+収支計画!N45/1000 -> 22.215 | AF41: =+PL推移!R40 -> 28.375 | AG41: =+AF41-AE41 -> 6.16 | AH41: =IF(AE41<>0,AF41/AE41,"-") -> 1.2772901 | AI41: =+収支計画!O45/1000 -> 22.215 | AJ41: =+PL推移!T40 -> 28.375 | AK41: =+AJ41-AI41 -> 6.16 | AL41: =IF(AI41<>0,AJ41/AI41,"-") -> 1.2772901 | AM41: =+収支計画!P45/1000 -> 22.215 | AN41: =+PL推移!V40 -> 28.375 | AO41: =+AN41-AM41 -> 6.16 | AP41: =IF(AM41<>0,AN41/AM41,"-") -> 1.2772901 | AQ41: =+収支計画!Q45/1000 -> 22.215 | AR41: =+PL推移!X40 -> 28.375 | AS41: =+AR41-AQ41 -> 6.16 | AT41: =IF(AQ41<>0,AR41/AQ41,"-") -> 1.2772901 | AU41: =+収支計画!R45/1000 -> 22.215 | AV41: =+PL推移!Z40 -> 28.375 | AW41: =+AV41-AU41 -> 6.16 | AX41: =IF(AU41<>0,AV41/AU41,"-") -> 1.2772901 | AY41: =+C41+G41+K41+O41+S41+W41+AA41+AE41+AI41+AM41+AQ41+AU41 -> 266.58 | AZ41: =+D41+H41+L41+P41+T41+X41+AB41+AF41+AJ41+AN41+AR41+AV41 -> 309.7 | BA41: =+AZ41-AY41 -> 43.12 | BB41: =IF(AY41<>0,AZ41/AY41,"-") -> 1.1617526
B42: 水道光熱費 | C42: =+収支計画!G46/1000 -> 860 | D42: =+PL推移!D41 -> 1055.015 | E42: =+D42-C42 -> 195.015 | F42: =IF(C42<>0,D42/C42,"-") -> 1.2267616 | G42: =+収支計画!H46/1000 -> 860 | H42: =+PL推移!F41 -> 1104.21 | I42: =+H42-G42 -> 244.21 | J42: =IF(G42<>0,H42/G42,"-") -> 1.2839651 | K42: =+収支計画!I46/1000 -> 860 | L42: =+PL推移!H41 -> 968.209 | M42: =+L42-K42 -> 108.209 | N42: =IF(K42<>0,L42/K42,"-") -> 1.1258244 | O42: =+収支計画!J46/1000 -> 860 | P42: =+PL推移!J41 -> 757.6 | Q42: =+P42-O42 -> -102.4 | R42: =IF(O42<>0,P42/O42,"-") -> 0.88093023 | S42: =+収支計画!K46/1000 -> 860 | T42: =+PL推移!L41 -> 878.364 | U42: =+T42-S42 -> 18.364 | V42: =IF(S42<>0,T42/S42,"-") -> 1.0213535 | W42: =+収支計画!L46/1000 -> 1060 | X42: =+PL推移!N41 -> 1110.021 | Y42: =+X42-W42 -> 50.021 | Z42: =IF(W42<>0,X42/W42,"-") -> 1.0471896 | AA42: =+収支計画!M46/1000 -> 860 | AB42: =+PL推移!P41 -> 1144.612 | AC42: =+AB42-AA42 -> 284.612 | AD42: =IF(AA42<>0,AB42/AA42,"-") -> 1.3309442 | AE42: =+収支計画!N46/1000 -> 860 | AF42: =+PL推移!R41 -> 1235.761 | AG42: =+AF42-AE42 -> 375.761 | AH42: =IF(AE42<>0,AF42/AE42,"-") -> 1.4369314 | AI42: =+収支計画!O46/1000 -> 980 | AJ42: =+PL推移!T41 -> 1093.647 | AK42: =+AJ42-AI42 -> 113.647 | AL42: =IF(AI42<>0,AJ42/AI42,"-") -> 1.1159663 | AM42: =+収支計画!P46/1000 -> 860 | AN42: =+PL推移!V41 -> 804.331 | AO42: =+AN42-AM42 -> -55.669 | AP42: =IF(AM42<>0,AN42/AM42,"-") -> 0.9352686 | AQ42: =+収支計画!Q46/1000 -> 860 | AR42: =+PL推移!X41 -> 719.828 | AS42: =+AR42-AQ42 -> -140.172 | AT42: =IF(AQ42<>0,AR42/AQ42,"-") -> 0.8370093 | AU42: =+収支計画!R46/1000 -> 860 | AV42: =+PL推移!Z41 -> 852.493 | AW42: =+AV42-AU42 -> -7.507 | AX42: =IF(AU42<>0,AV42/AU42,"-") -> 0.99127093 | AY42: =+C42+G42+K42+O42+S42+W42+AA42+AE42+AI42+AM42+AQ42+AU42 -> 10640 | AZ42: =+D42+H42+L42+P42+T42+X42+AB42+AF42+AJ42+AN42+AR42+AV42 -> 11724.091 | BA42: =+AZ42-AY42 -> 1084.091 | BB42: =IF(AY42<>0,AZ42/AY42,"-") -> 1.1018883 | BC42: うち約20%はLW負担
B43: 消耗品費 | C43: =+収支計画!G47/1000 -> 200 | D43: =+PL推移!D42 -> 332.272 | E43: =+D43-C43 -> 132.272 | F43: =IF(C43<>0,D43/C43,"-") -> 1.66136 | G43: =+収支計画!H47/1000 -> 200 | H43: =+PL推移!F42 -> 162.804 | I43: =+H43-G43 -> -37.196 | J43: =IF(G43<>0,H43/G43,"-") -> 0.81402 | K43: =+収支計画!I47/1000 -> 200 | L43: =+PL推移!H42 -> 154.474 | M43: =+L43-K43 -> -45.526 | N43: =IF(K43<>0,L43/K43,"-") -> 0.77237 | O43: =+収支計画!J47/1000 -> 200 | P43: =+PL推移!J42 -> 229.112 | Q43: =+P43-O43 -> 29.112 | R43: =IF(O43<>0,P43/O43,"-") -> 1.14556 | S43: =+収支計画!K47/1000 -> 200 | T43: =+PL推移!L42 -> 153.4 | U43: =+T43-S43 -> -46.6 | V43: =IF(S43<>0,T43/S43,"-") -> 0.767 | W43: =+収支計画!L47/1000 -> 250 | X43: =+PL推移!N42 -> 227.238 | Y43: =+X43-W43 -> -22.762 | Z43: =IF(W43<>0,X43/W43,"-") -> 0.908952 | AA43: =+収支計画!M47/1000 -> 200 | AB43: =+PL推移!P42 -> 157.253 | AC43: =+AB43-AA43 -> -42.747 | AD43: =IF(AA43<>0,AB43/AA43,"-") -> 0.786265 | AE43: =+収支計画!N47/1000 -> 200 | AF43: =+PL推移!R42 -> 203.697 | AG43: =+AF43-AE43 -> 3.697 | AH43: =IF(AE43<>0,AF43/AE43,"-") -> 1.018485 | AI43: =+収支計画!O47/1000 -> 230 | AJ43: =+PL推移!T42 -> 158.297 | AK43: =+AJ43-AI43 -> -71.703 | AL43: =IF(AI43<>0,AJ43/AI43,"-") -> 0.68824783 | AM43: =+収支計画!P47/1000 -> 200 | AN43: =+PL推移!V42 -> 160.095 | AO43: =+AN43-AM43 -> -39.905 | AP43: =IF(AM43<>0,AN43/AM43,"-") -> 0.800475 | AQ43: =+収支計画!Q47/1000 -> 200 | AR43: =+PL推移!X42 -> 127.598 | AS43: =+AR43-AQ43 -> -72.402 | AT43: =IF(AQ43<>0,AR43/AQ43,"-") -> 0.63799 | AU43: =+収支計画!R47/1000 -> 200 | AV43: =+PL推移!Z42 -> 280.82 | AW43: =+AV43-AU43 -> 80.82 | AX43: =IF(AU43<>0,AV43/AU43,"-") -> 1.4041 | AY43: =+C43+G43+K43+O43+S43+W43+AA43+AE43+AI43+AM43+AQ43+AU43 -> 2480 | AZ43: =+D43+H43+L43+P43+T43+X43+AB43+AF43+AJ43+AN43+AR43+AV43 -> 2347.06 | BA43: =+AZ43-AY43 -> -132.94 | BB43: =IF(AY43<>0,AZ43/AY43,"-") -> 0.94639516
B44: 租税公課 | C44: =+収支計画!G48/1000 -> 131 | D44: =+PL推移!D43 -> 146 | E44: =+D44-C44 -> 15 | F44: =IF(C44<>0,D44/C44,"-") -> 1.1145038 | G44: =+収支計画!H48/1000 -> 1 | H44: =+PL推移!F43 -> 1 | I44: =+H44-G44 -> 0 | J44: =IF(G44<>0,H44/G44,"-") -> 1 | K44: =+収支計画!I48/1000 -> 131 | L44: =+PL推移!H43 -> 147 | M44: =+L44-K44 -> 16 | N44: =IF(K44<>0,L44/K44,"-") -> 1.1221374 | O44: =+収支計画!J48/1000 -> 1 | P44: =+PL推移!J43 -> 0 | Q44: =+P44-O44 -> -1 | R44: =IF(O44<>0,P44/O44,"-") -> 0 | S44: =+収支計画!K48/1000 -> 1 | T44: =+PL推移!L43 -> 2.45 | U44: =+T44-S44 -> 1.45 | V44: =IF(S44<>0,T44/S44,"-") -> 2.45 | W44: =+収支計画!L48/1000 -> 131 | X44: =+PL推移!N43 -> 148 | Y44: =+X44-W44 -> 17 | Z44: =IF(W44<>0,X44/W44,"-") -> 1.129771 | AA44: =+収支計画!M48/1000 -> 1 | AB44: =+PL推移!P43 -> 0 | AC44: =+AB44-AA44 -> -1 | AD44: =IF(AA44<>0,AB44/AA44,"-") -> 0 | AE44: =+収支計画!N48/1000 -> 1 | AF44: =+PL推移!R43 -> 0 | AG44: =+AF44-AE44 -> -1 | AH44: =IF(AE44<>0,AF44/AE44,"-") -> 0 | AI44: =+収支計画!O48/1000 -> 1 | AJ44: =+PL推移!T43 -> 1 | AK44: =+AJ44-AI44 -> 0 | AL44: =IF(AI44<>0,AJ44/AI44,"-") -> 1 | AM44: =+収支計画!P48/1000 -> 131 | AN44: =+PL推移!V43 -> 125.9 | AO44: =+AN44-AM44 -> -5.1 | AP44: =IF(AM44<>0,AN44/AM44,"-") -> 0.9610687 | AQ44: =+収支計画!Q48/1000 -> 1 | AR44: =+PL推移!X43 -> 0 | AS44: =+AR44-AQ44 -> -1 | AT44: =IF(AQ44<>0,AR44/AQ44,"-") -> 0 | AU44: =+収支計画!R48/1000 -> 1 | AV44: =+PL推移!Z43 -> 1 | AW44: =+AV44-AU44 -> 0 | AX44: =IF(AU44<>0,AV44/AU44,"-") -> 1 | AY44: =+C44+G44+K44+O44+S44+W44+AA44+AE44+AI44+AM44+AQ44+AU44 -> 532 | AZ44: =+D44+H44+L44+P44+T44+X44+AB44+AF44+AJ44+AN44+AR44+AV44 -> 572.35 | BA44: =+AZ44-AY44 -> 40.35 | BB44: =IF(AY44<>0,AZ44/AY44,"-") -> 1.0758459
B45: 広告宣伝費 | C45: =+収支計画!G49/1000 -> 165 | D45: =+PL推移!D44 -> 186.903 | E45: =+D45-C45 -> 21.903 | F45: =IF(C45<>0,D45/C45,"-") -> 1.1327455 | G45: =+収支計画!H49/1000 -> 165 | H45: =+PL推移!F44 -> 179.4 | I45: =+H45-G45 -> 14.4 | J45: =IF(G45<>0,H45/G45,"-") -> 1.0872727 | K45: =+収支計画!I49/1000 -> 165 | L45: =+PL推移!H44 -> 177.56 | M45: =+L45-K45 -> 12.56 | N45: =IF(K45<>0,L45/K45,"-") -> 1.0761212 | O45: =+収支計画!J49/1000 -> 165 | P45: =+PL推移!J44 -> 176.503 | Q45: =+P45-O45 -> 11.503 | R45: =IF(O45<>0,P45/O45,"-") -> 1.0697152 | S45: =+収支計画!K49/1000 -> 165 | T45: =+PL推移!L44 -> 215.303 | U45: =+T45-S45 -> 50.303 | V45: =IF(S45<>0,T45/S45,"-") -> 1.3048667 | W45: =+収支計画!L49/1000 -> 165 | X45: =+PL推移!N44 -> 210.153 | Y45: =+X45-W45 -> 45.153 | Z45: =IF(W45<>0,X45/W45,"-") -> 1.2736545 | AA45: =+収支計画!M49/1000 -> 165 | AB45: =+PL推移!P44 -> 112 | AC45: =+AB45-AA45 -> -53 | AD45: =IF(AA45<>0,AB45/AA45,"-") -> 0.67878788 | AE45: =+収支計画!N49/1000 -> 165 | AF45: =+PL推移!R44 -> 2162.421 | AG45: =+AF45-AE45 -> 1997.421 | AH45: =IF(AE45<>0,AF45/AE45,"-") -> 13.105582 | AI45: =+収支計画!O49/1000 -> 165 | AJ45: =+PL推移!T44 -> 108 | AK45: =+AJ45-AI45 -> -57 | AL45: =IF(AI45<>0,AJ45/AI45,"-") -> 0.65454545 | AM45: =+収支計画!P49/1000 -> 165 | AN45: =+PL推移!V44 -> 100.654 | AO45: =+AN45-AM45 -> -64.346 | AP45: =IF(AM45<>0,AN45/AM45,"-") -> 0.61002424 | AQ45: =+収支計画!Q49/1000 -> 165 | AR45: =+PL推移!X44 -> 134.4 | AS45: =+AR45-AQ45 -> -30.6 | AT45: =IF(AQ45<>0,AR45/AQ45,"-") -> 0.81454545 | AU45: =+収支計画!R49/1000 -> 165 | AV45: =+PL推移!Z44 -> 123.402 | AW45: =+AV45-AU45 -> -41.598 | AX45: =IF(AU45<>0,AV45/AU45,"-") -> 0.74789091 | AY45: =+C45+G45+K45+O45+S45+W45+AA45+AE45+AI45+AM45+AQ45+AU45 -> 1980 | AZ45: =+D45+H45+L45+P45+T45+X45+AB45+AF45+AJ45+AN45+AR45+AV45 -> 3886.699 | BA45: =+AZ45-AY45 -> 1906.699 | BB45: =IF(AY45<>0,AZ45/AY45,"-") -> 1.9629793 | BC45: 補助対象経費2,046千円含む
B46: 支払手数料 | C46: =+収支計画!G50/1000 -> 281.5 | D46: =+PL推移!D45 -> 238.917 | E46: =+D46-C46 -> -42.583 | F46: =IF(C46<>0,D46/C46,"-") -> 0.84872824 | G46: =+収支計画!H50/1000 -> 281.5 | H46: =+PL推移!F45 -> 268.309 | I46: =+H46-G46 -> -13.191 | J46: =IF(G46<>0,H46/G46,"-") -> 0.95314032 | K46: =+収支計画!I50/1000 -> 281.5 | L46: =+PL推移!H45 -> 276.554 | M46: =+L46-K46 -> -4.946 | N46: =IF(K46<>0,L46/K46,"-") -> 0.98242984 | O46: =+収支計画!J50/1000 -> 281.5 | P46: =+PL推移!J45 -> 224.363 | Q46: =+P46-O46 -> -57.137 | R46: =IF(O46<>0,P46/O46,"-") -> 0.79702664 | S46: =+収支計画!K50/1000 -> 281.5 | T46: =+PL推移!L45 -> 226.852 | U46: =+T46-S46 -> -54.648 | V46: =IF(S46<>0,T46/S46,"-") -> 0.80586856 | W46: =+収支計画!L50/1000 -> 334 | X46: =+PL推移!N45 -> 264.11 | Y46: =+X46-W46 -> -69.89 | Z46: =IF(W46<>0,X46/W46,"-") -> 0.7907485 | AA46: =+収支計画!M50/1000 -> 281.5 | AB46: =+PL推移!P45 -> 245.928 | AC46: =+AB46-AA46 -> -35.572 | AD46: =IF(AA46<>0,AB46/AA46,"-") -> 0.8736341 | AE46: =+収支計画!N50/1000 -> 281.5 | AF46: =+PL推移!R45 -> 218.075 | AG46: =+AF46-AE46 -> -63.425 | AH46: =IF(AE46<>0,AF46/AE46,"-") -> 0.77468917 | AI46: =+収支計画!O50/1000 -> 313 | AJ46: =+PL推移!T45 -> 308.807 | AK46: =+AJ46-AI46 -> -4.193 | AL46: =IF(AI46<>0,AJ46/AI46,"-") -> 0.98660383 | AM46: =+収支計画!P50/1000 -> 341.5 | AN46: =+PL推移!V45 -> 185.84 | AO46: =+AN46-AM46 -> -155.66 | AP46: =IF(AM46<>0,AN46/AM46,"-") -> 0.54418741 | AQ46: =+収支計画!Q50/1000 -> 281.5 | AR46: =+PL推移!X45 -> 193.092 | AS46: =+AR46-AQ46 -> -88.408 | AT46: =IF(AQ46<>0,AR46/AQ46,"-") -> 0.68593961 | AU46: =+収支計画!R50/1000 -> 331.5 | AV46: =+PL推移!Z45 -> 243.661 | AW46: =+AV46-AU46 -> -87.839 | AX46: =IF(AU46<>0,AV46/AU46,"-") -> 0.73502564 | AY46: =+C46+G46+K46+O46+S46+W46+AA46+AE46+AI46+AM46+AQ46+AU46 -> 3572 | AZ46: =+D46+H46+L46+P46+T46+X46+AB46+AF46+AJ46+AN46+AR46+AV46 -> 2894.508 | BA46: =+AZ46-AY46 -> -677.492 | BB46: =IF(AY46<>0,AZ46/AY46,"-") -> 0.81033259
B47: 新聞図書費 | C47: =+収支計画!G51/1000 -> 0 | D47: =+PL推移!D46 -> 2.593 | E47: =+D47-C47 -> 2.593 | F47: =IF(C47<>0,D47/C47,"-") -> - | G47: =+収支計画!H51/1000 -> 0 | H47: =+PL推移!F46 -> 0 | I47: =+H47-G47 -> 0 | J47: =IF(G47<>0,H47/G47,"-") -> - | K47: =+収支計画!I51/1000 -> 0 | L47: =+PL推移!H46 -> 0 | M47: =+L47-K47 -> 0 | N47: =IF(K47<>0,L47/K47,"-") -> - | O47: =+収支計画!J51/1000 -> 0 | P47: =+PL推移!J46 -> 0 | Q47: =+P47-O47 -> 0 | R47: =IF(O47<>0,P47/O47,"-") -> - | S47: =+収支計画!K51/1000 -> 0 | T47: =+PL推移!L46 -> 0 | U47: =+T47-S47 -> 0 | V47: =IF(S47<>0,T47/S47,"-") -> - | W47: =+収支計画!L51/1000 -> 0 | X47: =+PL推移!N46 -> 0 | Y47: =+X47-W47 -> 0 | Z47: =IF(W47<>0,X47/W47,"-") -> - | AA47: =+収支計画!M51/1000 -> 0 | AB47: =+PL推移!P46 -> 0 | AC47: =+AB47-AA47 -> 0 | AD47: =IF(AA47<>0,AB47/AA47,"-") -> - | AE47: =+収支計画!N51/1000 -> 0 | AF47: =+PL推移!R46 -> 0 | AG47: =+AF47-AE47 -> 0 | AH47: =IF(AE47<>0,AF47/AE47,"-") -> - | AI47: =+収支計画!O51/1000 -> 0 | AJ47: =+PL推移!T46 -> 0 | AK47: =+AJ47-AI47 -> 0 | AL47: =IF(AI47<>0,AJ47/AI47,"-") -> - | AM47: =+収支計画!P51/1000 -> 0 | AN47: =+PL推移!V46 -> 0 | AO47: =+AN47-AM47 -> 0 | AP47: =IF(AM47<>0,AN47/AM47,"-") -> - | AQ47: =+収支計画!Q51/1000 -> 0 | AR47: =+PL推移!X46 -> 0 | AS47: =+AR47-AQ47 -> 0 | AT47: =IF(AQ47<>0,AR47/AQ47,"-") -> - | AU47: =+収支計画!R51/1000 -> 0 | AV47: =+PL推移!Z46 -> 0 | AW47: =+AV47-AU47 -> 0 | AX47: =IF(AU47<>0,AV47/AU47,"-") -> - | AY47: =+C47+G47+K47+O47+S47+W47+AA47+AE47+AI47+AM47+AQ47+AU47 -> 0 | AZ47: =+D47+H47+L47+P47+T47+X47+AB47+AF47+AJ47+AN47+AR47+AV47 -> 2.593 | BA47: =+AZ47-AY47 -> 2.593 | BB47: =IF(AY47<>0,AZ47/AY47,"-") -> -
B48: 管理諸費 | C48: =+収支計画!G52/1000 -> 70 | D48: =+PL推移!D47 -> 70 | E48: =+D48-C48 -> 0 | F48: =IF(C48<>0,D48/C48,"-") -> 1 | G48: =+収支計画!H52/1000 -> 70 | H48: =+PL推移!F47 -> 70 | I48: =+H48-G48 -> 0 | J48: =IF(G48<>0,H48/G48,"-") -> 1 | K48: =+収支計画!I52/1000 -> 280 | L48: =+PL推移!H47 -> 280 | M48: =+L48-K48 -> 0 | N48: =IF(K48<>0,L48/K48,"-") -> 1 | O48: =+収支計画!J52/1000 -> 70 | P48: =+PL推移!J47 -> 70 | Q48: =+P48-O48 -> 0 | R48: =IF(O48<>0,P48/O48,"-") -> 1 | S48: =+収支計画!K52/1000 -> 70 | T48: =+PL推移!L47 -> 110 | U48: =+T48-S48 -> 40 | V48: =IF(S48<>0,T48/S48,"-") -> 1.5714286 | W48: =+収支計画!L52/1000 -> 70 | X48: =+PL推移!N47 -> 70 | Y48: =+X48-W48 -> 0 | Z48: =IF(W48<>0,X48/W48,"-") -> 1 | AA48: =+収支計画!M52/1000 -> 70 | AB48: =+PL推移!P47 -> 70 | AC48: =+AB48-AA48 -> 0 | AD48: =IF(AA48<>0,AB48/AA48,"-") -> 1 | AE48: =+収支計画!N52/1000 -> 70 | AF48: =+PL推移!R47 -> 70 | AG48: =+AF48-AE48 -> 0 | AH48: =IF(AE48<>0,AF48/AE48,"-") -> 1 | AI48: =+収支計画!O52/1000 -> 70 | AJ48: =+PL推移!T47 -> 70 | AK48: =+AJ48-AI48 -> 0 | AL48: =IF(AI48<>0,AJ48/AI48,"-") -> 1 | AM48: =+収支計画!P52/1000 -> 70 | AN48: =+PL推移!V47 -> 70 | AO48: =+AN48-AM48 -> 0 | AP48: =IF(AM48<>0,AN48/AM48,"-") -> 1 | AQ48: =+収支計画!Q52/1000 -> 70 | AR48: =+PL推移!X47 -> 70 | AS48: =+AR48-AQ48 -> 0 | AT48: =IF(AQ48<>0,AR48/AQ48,"-") -> 1 | AU48: =+収支計画!R52/1000 -> 70 | AV48: =+PL推移!Z47 -> 70 | AW48: =+AV48-AU48 -> 0 | AX48: =IF(AU48<>0,AV48/AU48,"-") -> 1 | AY48: =+C48+G48+K48+O48+S48+W48+AA48+AE48+AI48+AM48+AQ48+AU48 -> 1050 | AZ48: =+D48+H48+L48+P48+T48+X48+AB48+AF48+AJ48+AN48+AR48+AV48 -> 1090 | BA48: =+AZ48-AY48 -> 40 | BB48: =IF(AY48<>0,AZ48/AY48,"-") -> 1.0380952
B49: 雑費 | C49: =+収支計画!G53/1000 -> 50 | D49: =+PL推移!D48 -> 64.599 | E49: =+D49-C49 -> 14.599 | F49: =IF(C49<>0,D49/C49,"-") -> 1.29198 | G49: =+収支計画!H53/1000 -> 50 | H49: =+PL推移!F48 -> 47.521 | I49: =+H49-G49 -> -2.479 | J49: =IF(G49<>0,H49/G49,"-") -> 0.95042 | K49: =+収支計画!I53/1000 -> 50 | L49: =+PL推移!H48 -> 42.6 | M49: =+L49-K49 -> -7.4 | N49: =IF(K49<>0,L49/K49,"-") -> 0.852 | O49: =+収支計画!J53/1000 -> 50 | P49: =+PL推移!J48 -> 71.639 | Q49: =+P49-O49 -> 21.639 | R49: =IF(O49<>0,P49/O49,"-") -> 1.43278 | S49: =+収支計画!K53/1000 -> 50 | T49: =+PL推移!L48 -> 42.72 | U49: =+T49-S49 -> -7.28 | V49: =IF(S49<>0,T49/S49,"-") -> 0.8544 | W49: =+収支計画!L53/1000 -> 50 | X49: =+PL推移!N48 -> 42.24 | Y49: =+X49-W49 -> -7.76 | Z49: =IF(W49<>0,X49/W49,"-") -> 0.8448 | AA49: =+収支計画!M53/1000 -> 50 | AB49: =+PL推移!P48 -> 71.158 | AC49: =+AB49-AA49 -> 21.158 | AD49: =IF(AA49<>0,AB49/AA49,"-") -> 1.42316 | AE49: =+収支計画!N53/1000 -> 50 | AF49: =+PL推移!R48 -> 41.88 | AG49: =+AF49-AE49 -> -8.12 | AH49: =IF(AE49<>0,AF49/AE49,"-") -> 0.8376 | AI49: =+収支計画!O53/1000 -> 74 | AJ49: =+PL推移!T48 -> 62.28 | AK49: =+AJ49-AI49 -> -11.72 | AL49: =IF(AI49<>0,AJ49/AI49,"-") -> 0.84162162 | AM49: =+収支計画!P53/1000 -> 87 | AN49: =+PL推移!V48 -> 108.288 | AO49: =+AN49-AM49 -> 21.288 | AP49: =IF(AM49<>0,AN49/AM49,"-") -> 1.2446897 | AQ49: =+収支計画!Q53/1000 -> 50 | AR49: =+PL推移!X48 -> 38.87 | AS49: =+AR49-AQ49 -> -11.13 | AT49: =IF(AQ49<>0,AR49/AQ49,"-") -> 0.7774 | AU49: =+収支計画!R53/1000 -> 50 | AV49: =+PL推移!Z48 -> 58.99 | AW49: =+AV49-AU49 -> 8.99 | AX49: =IF(AU49<>0,AV49/AU49,"-") -> 1.1798 | AY49: =+C49+G49+K49+O49+S49+W49+AA49+AE49+AI49+AM49+AQ49+AU49 -> 661 | AZ49: =+D49+H49+L49+P49+T49+X49+AB49+AF49+AJ49+AN49+AR49+AV49 -> 692.785 | BA49: =+AZ49-AY49 -> 31.785 | BB49: =IF(AY49<>0,AZ49/AY49,"-") -> 1.0480862
F50: =IF(C50<>0,D50/C50,"-") -> - | H50: =+PL推移!F49 -> 0 | J50: =IF(G50<>0,H50/G50,"-") -> - | L50: =+PL推移!H49 -> 0 | N50: =IF(K50<>0,L50/K50,"-") -> - | P50: =+PL推移!J49 -> 0 | R50: =IF(O50<>0,P50/O50,"-") -> - | T50: =+PL推移!N49 -> 0 | V50: =IF(S50<>0,T50/S50,"-") -> - | X50: =+PL推移!R49 -> 0 | Z50: =IF(W50<>0,X50/W50,"-") -> - | AB50: =+PL推移!V49 -> 0 | AD50: =IF(AA50<>0,AB50/AA50,"-") -> - | AF50: =+PL推移!Z49 -> 0 | AH50: =IF(AE50<>0,AF50/AE50,"-") -> - | AJ50: =+PL推移!AD49 -> 0 | AL50: =IF(AI50<>0,AJ50/AI50,"-") -> - | AN50: =+PL推移!AH49 -> 0 | AO50: =+AN50-AM50 -> 0 | AP50: =IF(AM50<>0,AN50/AM50,"-") -> - | AR50: =+PL推移!AL49 -> 0 | AS50: =+AR50-AQ50 -> 0 | AT50: =IF(AQ50<>0,AR50/AQ50,"-") -> - | AU50: =+収支計画!R54/1000 -> 0 | AV50: =+PL推移!AP49 -> 0 | AW50: =+AV50-AU50 -> 0 | AX50: =IF(AU50<>0,AV50/AU50,"-") -> - | AY50: =+C50+G50+K50+O50+S50+W50+AA50+AE50+AI50+AM50+AQ50+AU50 -> 0 | AZ50: =+D50+H50+L50+P50+T50+X50+AB50+AF50+AJ50+AN50+AR50+AV50 -> 0 | BA50: =+AZ50-AY50 -> 0 | BB50: =IF(AY50<>0,AZ50/AY50,"-") -> -
A51: 営業損益 | C51: =+C23-C29 -> 289.601 | D51: =+D23-D29 -> 110.275 | E51: =+E23-E29 -> -177.98 | F51: =IF(C51<>0,D51/C51,"-") -> 0.38078252 | G51: =+G23-G29 -> 2049.601 | H51: =+PL推移!F50 -> 969.216 | I51: =+I23-I29 -> -1078.887 | J51: =IF(G51<>0,H51/G51,"-") -> 0.47288033 | K51: =+K23-K29 -> 163.966 | L51: =+PL推移!H50 -> -684.855 | M51: =+M23-M29 -> -839.227 | N51: =IF(K51<>0,L51/K51,"-") -> -4.176811 | O51: =+O23-O29 -> 503.966 | P51: =+PL推移!J50 -> 25.892 | Q51: =+Q23-Q29 -> -467.384 | R51: =IF(O51<>0,P51/O51,"-") -> 0.051376482 | S51: =+S23-S29 -> 615.486 | T51: =+PL推移!L50 -> -264.616 | U51: =+U23-U29 -> -879.123 | V51: =IF(S51<>0,T51/S51,"-") -> -0.42993017 | W51: =+W23-W29 -> 1595.486 | X51: =+PL推移!N50 -> 1487.432 | Y51: =+Y23-Y29 -> 279.944 | Z51: =IF(W51<>0,X51/W51,"-") -> 0.93227518 | AA51: =+AA23-AA29 -> 610.486 | AB51: =+AB23-AB29 -> -1083.192 | AC51: =+AC23-AC29 -> -1693.391 | AD51: =IF(AA51<>0,AB51/AA51,"-") -> -1.774311 | AE51: =+AE23-AE29 -> 260.486 | AF51: =+AF23-AF29 -> -3159.004 | AG51: =+AG23-AG29 -> -3783.347 | AH51: =IF(AE51<>0,AF51/AE51,"-") -> -12.127347 | AI51: =+AI23-AI29 -> 1247.486 | AJ51: =+AJ23-AJ29 -> -826.455 | AK51: =+AK23-AK29 -> -2064.606 | AL51: =IF(AI51<>0,AJ51/AI51,"-") -> -0.66249641 | AM51: =+AM23-AM29 -> 398.486 | AN51: =+AN23-AN29 -> -1592.861 | AO51: =+AN51-AM51 -> -1991.347 | AP51: =IF(AM51<>0,AN51/AM51,"-") -> -3.9972822 | AQ51: =+AQ23-AQ29 -> 625.486 | AR51: =+AR23-AR29 -> -920.235 | AS51: =+AR51-AQ51 -> -1545.721 | AT51: =IF(AQ51<>0,AR51/AQ51,"-") -> -1.471232 | AU51: =+AU23-AU29 -> 575.486 | AV51: =+AV23-AV29 -> -875.179 | AW51: =+AV51-AU51 -> -1450.665 | AX51: =IF(AU51<>0,AV51/AU51,"-") -> -1.5207651 | AY51: =+C51+G51+K51+O51+S51+W51+AA51+AE51+AI51+AM51+AQ51+AU51 -> 8936.022 | AZ51: =+D51+H51+L51+P51+T51+X51+AB51+AF51+AJ51+AN51+AR51+AV51 -> -6813.582 | BA51: =+AZ51-AY51 -> -15749.604 | BB51: =IF(AY51<>0,AZ51/AY51,"-") -> -0.76248492
B52: 期中累計 | C52: =+C51 -> 289.601 | D52: =+D51 -> 110.275 | E52: =+E51 -> -177.98 | F52: =IF(C52<>0,D52/C52,"-") -> 0.38078252 | G52: =+C52+G51 -> 2339.202 | H52: =+D52+H51 -> 1079.491 | I52: =+I51 -> -1078.887 | J52: =IF(G52<>0,H52/G52,"-") -> 0.46147832 | K52: =+G52+K51 -> 2503.168 | L52: =+H52+L51 -> 394.636 | M52: =+M51 -> -839.227 | N52: =IF(K52<>0,L52/K52,"-") -> 0.15765462 | O52: =+K52+O51 -> 3007.134 | P52: =+L52+P51 -> 420.528 | Q52: =+Q51 -> -467.384 | R52: =IF(O52<>0,P52/O52,"-") -> 0.13984345 | S52: =+O52+S51 -> 3622.62 | T52: =+P52+T51 -> 155.912 | U52: =+U51 -> -879.123 | V52: =IF(S52<>0,T52/S52,"-") -> 0.043038464 | W52: =+S52+W51 -> 5218.106 | X52: =+T52+X51 -> 1643.344 | Y52: =+X52-W52 -> -3574.762 | Z52: =IF(W52<>0,X52/W52,"-") -> 0.31493113 | AA52: =+W52+AA51 -> 5828.592 | AB52: =+X52+AB51 -> 560.152 | AC52: =+AB52-AA52 -> -5268.44 | AD52: =IF(AA52<>0,AB52/AA52,"-") -> 0.096104171 | AE52: =+AA52+AE51 -> 6089.078 | AF52: =+AB52+AF51 -> -2598.852 | AG52: =+AF52-AE52 -> -8687.93 | AH52: =IF(AE52<>0,AF52/AE52,"-") -> -0.4268055 | AI52: =+AE52+AI51 -> 7336.564 | AJ52: =+AF52+AJ51 -> -3425.307 | AK52: =+AJ52-AI52 -> -10761.871 | AL52: =IF(AI52<>0,AJ52/AI52,"-") -> -0.46688164 | AM52: =+AI52+AM51 -> 7735.05 | AN52: =+AJ52+AN51 -> -5018.168 | AO52: =+AN52-AM52 -> -12753.218 | AP52: =IF(AM52<>0,AN52/AM52,"-") -> -0.64875702 | AQ52: =+AM52+AQ51 -> 8360.536 | AR52: =+AN52+AR51 -> -5938.403 | AS52: =+AR52-AQ52 -> -14298.939 | AT52: =IF(AQ52<>0,AR52/AQ52,"-") -> -0.71028975 | AU52: =+AQ52+AU51 -> 8936.022 | AV52: =+AR52+AV51 -> -6813.582 | AW52: =+AV52-AU52 -> -15749.604 | AX52: =IF(AU52<>0,AV52/AU52,"-") -> -0.76248492 | BB52: =IF(AY52<>0,AZ52/AY52,"-") -> -
A53: 営業外収益 | C53: =+収支計画!G58/1000 -> 200 | D53: =+PL推移!D52 -> 0 | E53: =+D53-C53 -> -200 | F53: =IF(C53<>0,D53/C53,"-") -> 0 | G53: =+収支計画!H58/1000 -> 0 | H53: =+PL推移!F52 -> 33.39 | I53: =+H53-G53 -> 33.39 | J53: =IF(G53<>0,H53/G53,"-") -> - | K53: =+収支計画!O65/1000 -> 0 | L53: =+PL推移!H52 -> 403.669 | M53: =+L53-K53 -> 403.669 | N53: =IF(K53<>0,L53/K53,"-") -> - | O53: =+収支計画!J58/1000 -> 0 | P53: =+PL推移!J52 -> 0 | Q53: =+P53-O53 -> 0 | R53: =IF(O53<>0,P53/O53,"-") -> - | S53: =+収支計画!W65/1000 -> 0 | T53: =+PL推移!L52 -> 0 | U53: =+T53-S53 -> 0 | V53: =IF(S53<>0,T53/S53,"-") -> - | W53: =+収支計画!L58/1000 -> 200 | X53: =+PL推移!N52 -> 0 | Y53: =+X53-W53 -> -200 | Z53: =IF(W53<>0,X53/W53,"-") -> 0 | AA53: =+収支計画!AE65/1000 -> 0 | AB53: =+PL推移!P52 -> 0 | AC53: =+AB53-AA53 -> 0 | AD53: =IF(AA53<>0,AB53/AA53,"-") -> - | AE53: =+収支計画!AI65/1000 -> 0 | AF53: =+PL推移!R52 -> 33.136 | AG53: =+AF53-AE53 -> 33.136 | AH53: =IF(AE53<>0,AF53/AE53,"-") -> - | AI53: =+収支計画!AM65/1000 -> 0 | AJ53: =+PL推移!T52 -> 1000.001 | AK53: =+AJ53-AI53 -> 1000.001 | AL53: =IF(AI53<>0,AJ53/AI53,"-") -> - | AM53: =+収支計画!AQ65/1000 -> 0 | AN53: =+PL推移!V52 -> 0 | AO53: =+AN53-AM53 -> 0 | AP53: =IF(AM53<>0,AN53/AM53,"-") -> - | AQ53: =+収支計画!AG65/1000 -> 0 | AR53: =+PL推移!X52 -> 400 | AS53: =+AR53-AQ53 -> 400 | AT53: =IF(AQ53<>0,AR53/AQ53,"-") -> - | AU53: =+収支計画!AI65/1000 -> 0 | AV53: =+PL推移!Z52 -> 0.239 | AW53: =+AV53-AU53 -> 0.239 | AX53: =IF(AU53<>0,AV53/AU53,"-") -> - | AY53: =+C53+G53+K53+O53+S53+W53+AA53+AE53+AI53+AM53+AQ53+AU53 -> 400 | AZ53: =+D53+H53+L53+P53+T53+X53+AB53+AF53+AJ53+AN53+AR53+AV53 -> 1870.435 | BA53: =+AZ53-AY53 -> 1470.435 | BB53: =IF(AY53<>0,AZ53/AY53,"-") -> 4.6760875
A54: 営業外費用 | C54: =+収支計画!G59/1000 -> 120 | D54: =+PL推移!D53 -> 147.962 | E54: =+D54-C54 -> 27.962 | F54: =IF(C54<>0,D54/C54,"-") -> 1.2330167 | G54: =+収支計画!H59/1000 -> 120 | H54: =+PL推移!F53 -> 82.191 | I54: =+H54-G54 -> -37.809 | J54: =IF(G54<>0,H54/G54,"-") -> 0.684925 | K54: =+収支計画!I59/1000 -> 120 | L54: =+PL推移!H53 -> 206.056 | M54: =+L54-K54 -> 86.056 | N54: =IF(K54<>0,L54/K54,"-") -> 1.7171333 | O54: =+収支計画!J59/1000 -> 120 | P54: =+PL推移!J53 -> 152.448 | Q54: =+P54-O54 -> 32.448 | R54: =IF(O54<>0,P54/O54,"-") -> 1.2704 | S54: =+収支計画!K59/1000 -> 120 | T54: =+PL推移!L53 -> 72.43 | U54: =+T54-S54 -> -47.57 | V54: =IF(S54<>0,T54/S54,"-") -> 0.60358333 | W54: =+収支計画!L59/1000 -> 120 | X54: =+PL推移!N53 -> 74.484 | Y54: =+X54-W54 -> -45.516 | Z54: =IF(W54<>0,X54/W54,"-") -> 0.6207 | AA54: =+収支計画!M59/1000 -> 120 | AB54: =+PL推移!P53 -> 148.217 | AC54: =+AB54-AA54 -> 28.217 | AD54: =IF(AA54<>0,AB54/AA54,"-") -> 1.2351417 | AE54: =+収支計画!AA66/1000 -> 0 | AF54: =+PL推移!R53 -> 130.729 | AG54: =+AF54-AE54 -> 130.729 | AH54: =IF(AE54<>0,AF54/AE54,"-") -> - | AI54: =+収支計画!AE66/1000 -> 0 | AJ54: =+PL推移!T53 -> 199.645 | AK54: =+AJ54-AI54 -> 199.645 | AL54: =IF(AI54<>0,AJ54/AI54,"-") -> - | AM54: =+収支計画!P59/1000 -> 120 | AN54: =+PL推移!V53 -> 143.445 | AO54: =+AN54-AM54 -> 23.445 | AP54: =IF(AM54<>0,AN54/AM54,"-") -> 1.195375 | AQ54: =+収支計画!AG66/1000 -> 0 | AR54: =+PL推移!X53 -> 81.533 | AS54: =+AR54-AQ54 -> 81.533 | AT54: =IF(AQ54<>0,AR54/AQ54,"-") -> - | AU54: =+収支計画!AI66/1000 -> 0 | AV54: =+PL推移!Z53 -> 127.161 | AW54: =+AV54-AU54 -> 127.161 | AX54: =IF(AU54<>0,AV54/AU54,"-") -> - | AY54: =+C54+G54+K54+O54+S54+W54+AA54+AE54+AI54+AM54+AQ54+AU54 -> 960 | AZ54: =+D54+H54+L54+P54+T54+X54+AB54+AF54+AJ54+AN54+AR54+AV54 -> 1566.301 | BA54: =+AZ54-AY54 -> 606.301 | BB54: =IF(AY54<>0,AZ54/AY54,"-") -> 1.6315635
A55: 経常損益 | C55: =+C51+C53-C54 -> 369.601 | D55: =+D51+D53-D54 -> -37.687 | E55: =+E51+E53-E54 -> -405.942 | F55: =IF(C55<>0,D55/C55,"-") -> -0.10196672 | G55: =+G51+G53-G54 -> 1929.601 | H55: =+PL推移!F54 -> 920.415 | I55: =+I51+I53-I54 -> -1007.688 | J55: =IF(G55<>0,H55/G55,"-") -> 0.47699758 | K55: =+K51+K53-K54 -> 43.966 | L55: =+PL推移!H54 -> -487.242 | M55: =+M51+M53-M54 -> -521.614 | N55: =IF(K55<>0,L55/K55,"-") -> -11.082245 | O55: =+O51+O53-O54 -> 383.966 | P55: =+PL推移!J54 -> -126.556 | Q55: =+Q51+Q53-Q54 -> -499.832 | R55: =IF(O55<>0,P55/O55,"-") -> -0.3296021 | S55: =+S51+S53-S54 -> 495.486 | T55: =+PL推移!L54 -> -337.046 | U55: =+U51+U53-U54 -> -831.553 | V55: =IF(S55<>0,T55/S55,"-") -> -0.68023314 | W55: =+W51+W53-W54 -> 1675.486 | X55: =+PL推移!N54 -> 1412.948 | Y55: =+Y51+Y53-Y54 -> 125.46 | Z55: =IF(W55<>0,X55/W55,"-") -> 0.84330636 | AA55: =+AA51+AA53-AA54 -> 490.486 | AB55: =+AB51+AB53-AB54 -> -1231.409 | AC55: =+AC51+AC53-AC54 -> -1721.608 | AD55: =IF(AA55<>0,AB55/AA55,"-") -> -2.5105895 | AE55: =+AE51+AE53-AE54 -> 260.486 | AF55: =+AF51+AF53-AF54 -> -3256.597 | AG55: =+AG51+AG53-AG54 -> -3880.94 | AH55: =IF(AE55<>0,AF55/AE55,"-") -> -12.502004 | AI55: =+AI51+AI53-AI54 -> 1247.486 | AJ55: =+AJ51+AJ53-AJ54 -> -26.099 | AK55: =+AK51+AK53-AK54 -> -1264.25 | AL55: =IF(AI55<>0,AJ55/AI55,"-") -> -0.020921277 | AM55: =+AM51+AM53-AM54 -> 278.486 | AN55: =+AN51+AN53-AN54 -> -1736.306 | AO55: =+AN55-AM55 -> -2014.792 | AP55: =IF(AM55<>0,AN55/AM55,"-") -> -6.2348053 | AQ55: =+AQ51+AQ53-AQ54 -> 625.486 | AR55: =+AR51+AR53-AR54 -> -601.768 | AS55: =+AR55-AQ55 -> -1227.254 | AT55: =IF(AQ55<>0,AR55/AQ55,"-") -> -0.96208069 | AU55: =+AU51+AU53-AU54 -> 575.486 | AV55: =+AV51+AV53-AV54 -> -1002.101 | AW55: =+AV55-AU55 -> -1577.587 | AX55: =IF(AU55<>0,AV55/AU55,"-") -> -1.7413126 | AY55: =+C55+G55+K55+O55+S55+W55+AA55+AE55+AI55+AM55+AQ55+AU55 -> 8376.022 | AZ55: =+D55+H55+L55+P55+T55+X55+AB55+AF55+AJ55+AN55+AR55+AV55 -> -6509.448 | BA55: =+AZ55-AY55 -> -14885.47 | BB55: =IF(AY55<>0,AZ55/AY55,"-") -> -0.77715269
B56: 期中累計 | C56: =+C55 -> 369.601 | D56: =+D55 -> -37.687 | E56: =+E55 -> -405.942 | F56: =IF(C56<>0,D56/C56,"-") -> -0.10196672 | G56: =+C56+G55 -> 2299.202 | H56: =+D56+H55 -> 882.728 | I56: =+I55 -> -1007.688 | J56: =IF(G56<>0,H56/G56,"-") -> 0.38392799 | K56: =+G56+K55 -> 2343.168 | L56: =+H56+L55 -> 395.486 | M56: =+M55 -> -521.614 | N56: =IF(K56<>0,L56/K56,"-") -> 0.16878261 | O56: =+K56+O55 -> 2727.134 | P56: =+PL推移!J55 -> 268.93 | Q56: =+P56-O56 -> -2458.204 | R56: =IF(O56<>0,P56/O56,"-") -> 0.098612683 | S56: =+O56+S55 -> 3222.62 | T56: =+P56+T55 -> -68.116 | U56: =+T56-S56 -> -3290.736 | V56: =IF(S56<>0,T56/S56,"-") -> -0.021136839 | W56: =+S56+W55 -> 4898.106 | X56: =+T56+X55 -> 1344.832 | Y56: =+X56-W56 -> -3553.274 | Z56: =IF(W56<>0,X56/W56,"-") -> 0.27456164 | AA56: =+W56+AA55 -> 5388.592 | AB56: =+X56+AB55 -> 113.423 | AC56: =+AB56-AA56 -> -5275.169 | AD56: =IF(AA56<>0,AB56/AA56,"-") -> 0.021048727 | AE56: =+AA56+AE55 -> 5649.078 | AF56: =+AB56+AF55 -> -3143.174 | AG56: =+AF56-AE56 -> -8792.252 | AH56: =IF(AE56<>0,AF56/AE56,"-") -> -0.55640478 | AI56: =+AE56+AI55 -> 6896.564 | AJ56: =+AF56+AJ55 -> -3169.273 | AK56: =+AJ56-AI56 -> -10065.837 | AL56: =IF(AI56<>0,AJ56/AI56,"-") -> -0.45954377 | AM56: =+AI56+AM55 -> 7175.05 | AN56: =+AJ56+AN55 -> -4905.579 | AO56: =+AN56-AM56 -> -12080.629 | AP56: =IF(AM56<>0,AN56/AM56,"-") -> -0.68369963 | AQ56: =+AM56+AQ55 -> 7800.536 | AR56: =+AN56+AR55 -> -5507.347 | AS56: =+AR56-AQ56 -> -13307.883 | AT56: =IF(AQ56<>0,AR56/AQ56,"-") -> -0.70602161 | AU56: =+AQ56+AU55 -> 8376.022 | AV56: =+AR56+AV55 -> -6509.448 | AW56: =+AV56-AU56 -> -14885.47 | AX56: =IF(AU56<>0,AV56/AU56,"-") -> -0.77715269 | BB56: =IF(AY56<>0,AZ56/AY56,"-") -> -
C58: 売上高 | D58: レストラン売上 | F58: =+E12 -> -27 | G58: 売上高 | H58: レストラン売上 | J58: =+I12 -> -136 | K58: 売上高 | L58: レストラン売上 | N58: =+M12 -> -1188 | O58: 売上高 | P58: レストラン売上 | R58: =+Q12 -> -1300 | S58: 売上高 | T58: レストラン売上 | V58: =+U12 -> -745 | W58: 売上高 | X58: レストラン売上 | Z58: =+Y12 -> 74 | AA58: 売上高 | AB58: レストラン売上 | AD58: =+AC12 -> -1297 | AE58: 売上高 | AF58: レストラン売上 | AH58: =+AG12 -> -858 | AI58: 売上高 | AJ58: 全体予実比 | AL58: =+AK11 -> -2343 | AM58: 売上高 | AN58: 全体予実比 | AP58: =+AO11 -> -2396.006 | AQ58: 売上高 | AR58: レストラン売上 | AT58: =+AS12 -> -1599 | AU58: 売上高 | AV58: レストラン売上 | AX58: =+AW12 -> -1633
D59: 弁当受注増 | F59: =+E14 -> 114 | H59: サウナ | J59: =+I16 -> -1006 | L59: サウナ | N59: =+M16 -> -235 | P59: サウナ | R59: =+Q16 -> 191 | T59: サウナ | V59: =+U16 -> -357 | X59: 弁当受注減 | Z59: =+Y14 -> -32 | AB59: 弁当受注減 | AD59: =+AC14 -> -13 | AF59: 弁当受注減 | AH59: =+AG14 -> -107 | AJ59: レストラン売上 | AL59: =+AK12 -> -1885 | AN59: レストラン売上 | AP59: =+AO12 -> -2002 | AR59: サウナ | AT59: =+AS16 -> -447 | AV59: サウナ | AX59: =+AW16 -> -435
C60: 原価率 | D60: 対相乗積 | E60: ﾚｽﾄﾗﾝ | F60: +1.2p | G60: 原価率 | H60: 対相乗積 | I60: ﾚｽﾄﾗﾝ | J60: △1.8p | K60: 原価率 | L60: 対相乗積 | M60: ﾚｽﾄﾗﾝ | N60: △1.9p | O60: 原価率 | P60: 対相乗積 | Q60: ﾚｽﾄﾗﾝ | S60: 原価率 | T60: 対相乗積 | U60: ﾚｽﾄﾗﾝ | V60: △0.6p | W60: 原価率 | X60: 対相乗積 | Y60: ﾚｽﾄﾗﾝ | Z60: -1.5p | AA60: 原価率 | AB60: 対相乗積 | AC60: ﾚｽﾄﾗﾝ | AD60: +0.4p | AE60: 原価率 | AF60: レストラン | AG60: 対相乗積 | AH60: -0.8p | AI60: 原価率 | AJ60: レストラン | AK60: 対相乗積 | AL60: -2.9p | AM60: 原価率 | AN60: 対相乗積 | AO60: ﾚｽﾄﾗﾝ | AP60: +6.1p | AQ60: 原価率 | AR60: レストラン | AT60: =+PL推移!Y17 -> 0.32160711 | AU60: 原価率 | AV60: 対相乗積 | AW60: ﾚｽﾄﾗﾝ | AX60: +2.2p
E61: 村 | F61: +11.2p | H61: 対設定率 | I61: 弁当 | J61: △11.7p | L61: 対設定率 | M61: 弁当 | N61: ＋5.8p | P61: 対設定率 | Q61: 弁当 | R61: ＋2.8p | T61: 対設定率 | U61: 弁当 | V61: ＋2.7p | Y61: 村 | Z61: +4.7p | AB61: 弁当事業 | AD61: =+PL推移!Q19 -> 0.43916914 | AF61: 弁当事業 | AG61: 対設定原価率 | AH61: +8.5p | AJ61: 弁当事業 | AK61: 今期累計 | AL61: 0.432 | AN61: 弁当事業 | AO61: 設定比 | AP61: -1.3p | AR61: 弁当事業 | AT61: =+PL推移!Y19 -> 0.28478261 | AV61: 弁当事業 | AW61: 設定比 | AX61: -0.6p
D62: 弁当事業 | F62: △8.1% | G62: FL | H62: 除くサウナ | J62: △2.9p | K62: FL | L62: 除くサウナ | N62: △2.3p | O62: FL | P62: 除くサウナ | R62: +4.0p | S62: FL | T62: 除くサウナ | V62: +0.3p | X62: 弁当事業 | Y62: 11月平均 | Z62: 0.376 | AA62: 水道光熱費 | AB62: 計画比 | AD62: =+AC42 -> 284.612 | AE62: 水道光熱費 | AF62: 冬季特殊要因？ | AH62: =+AG42 -> 375.761 | AI62: 人件費 | AJ62: 予実比 | AL62: =+AK30 -> 340.396 | AM62: 支払手数料 | AN62: 予実比 | AP62: =+AO46 -> -155.66 | AQ62: 人件費 | AR62: ３月から計画比+傾向 | AT62: =+AS30 -> 68.577 | AU62: 人件費 | AX62: =+AW30 -> -79.039
C63: 租税公課 | D63: 償却資産税 | F63: 146 | G63: 人件費 | I63: 累計 | J63: =+E30+I30 -> -719.834 | K63: 人件費 | M63: 累計 | N63: -1314 | O63: 人件費 | Q63: 累計 | R63: -1384 | S63: 人件費 | U63: 累計 | V63: =+BA30 -> -1107.552 | W63: 租税公課 | X63: 償却資産税 | Z63: 91 | AE63: 支払手数料 | AF63: 多言語対応費用 | AH63: 2006 | AI63: 水道光熱費 | AJ63: 予実比 | AL63: =+AK42 -> 113.647 | AQ63: FL | AR63: 除くサウナ | AT63: =+PL推移!Y58 -> 0.69206679 | AW63: FL | AX63: =+PL推移!AA58 -> 0.64355081 | AY63: 1-5月平均 68.5p
C64: 広告宣伝費 | D64: ﾗｲﾌﾜｰｸ | E64: SNS運用費 | F64: 120 | G64: 水道光熱費 | I64: 累計 | J64: =+E42+I42 -> 439.225 | K64: 水道光熱費 | M64: 累計 | N64: 547 | O64: 水道光熱費 | Q64: 累計 | R64: 445 | S64: 水道光熱費 | U64: 累計 | V64: =+BA42 -> 1084.091 | W64: 広告宣伝費 | X64: ﾗｲﾌﾜｰｸ | Y64: SNS運用費 | Z64: 120 | AI64: 雑収入 | AJ64: 助成金 | AL64: 1000 | AU64: 水道光熱費 | AV64: LW負担分 | AW64: 4-6月 | AX64: 475 | AY64: 売上高計上、経費戻しか雑収入が相当

Sheet CF推移
E1: 改善 | F1: 不確定含む | G1: 要検証
B2: ■月次報告CF | E2: =+PL推移!D7 -> ㈱ｅｓエンターテイメント
B4: =+PL推移!B8 -> 2025 | C4: 年度 | D4: 単位：千円 | E4: =+BS千円!D1 -> 7月 | F4: =+BS千円!E1 -> 8月 | G4: =+BS千円!F1 -> 9月 | H4: =+BS千円!G1 -> 10月 | I4: =+BS千円!H1 -> 11月 | J4: =+BS千円!I1 -> 12月 | K4: =+BS千円!J1 -> 1月 | L4: =+BS千円!K1 -> 2月 | ... P4: =+BS千円!O1 -> 6月
B5: １．営業活動CF | E5: =+E6-E7+E8-E9-E10-E11+E12+E13 -> -243.306 | F5: =+F6-F7+F8-F9-F10-F11+F12+F13 -> -1846.817 | G5: =+G6-G7+G8-G9-G10-G11+G12+G13 -> -147.432 | H5: =+H6-H7+H8-H9-H10-H11+H12+H13 -> 31.533 | I5: =+I6-I7+I8-I9-I10-I11+I12+I13 -> 893.754 | J5: =+J6-J7+J8-J9-J10-J11+J12+J13 -> 1522.566 | K5: =+K6-K7+K8-K9-K10-K11+K12+K13 -> -1213.372 | L5: =+L6-L7+L8-L9-L10-L11+L12+L13 -> -4528.146 | ... P5: =+P6-P7+P8-P9-P10-P11+P12+P13 -> 5521.397
C6: 税引前利益 | D6: ＋ | E6: =+月次PL!C62/1000 -> -37.687 | F6: =+月次PL!D62/1000 -> 920.415 | G6: =+月次PL!E62/1000 -> -487.242 | H6: =+月次PL!F62/1000 -> -126.556 | I6: =+月次PL!G62/1000 -> -337.046 | J6: =+月次PL!H62/1000 -> 1412.948 | K6: =+月次PL!I62/1000 -> -1231.409 | L6: =+月次PL!J62/1000 -> -3256.597 | ... P6: =+月次PL!N62/1000 -> -1002.101
C7: 決算関係納税 | D7: － | E7: =+月次PL!C63/1000+BS千円!C61-BS千円!D61+BS千円!C60-BS千円!D60 -> 0 | F7: =+月次PL!D63/1000+BS千円!D61-BS千円!E61+BS千円!D60-BS千円!E60 -> 3455.5 | G7: =+月次PL!E63/1000+BS千円!E61-BS千円!F61+BS千円!E60-BS千円!F60 -> 0 | H7: =+月次PL!F63/1000+BS千円!F61-BS千円!G61+BS千円!F60-BS千円!G60 -> 0 | I7: =+月次PL!G63/1000+BS千円!G61-BS千円!H61+BS千円!G60-BS千円!H60 -> 0 | J7: =+月次PL!H63/1000+BS千円!H61-BS千円!I61+BS千円!H60-BS千円!I60 -> 0 | K7: =+月次PL!I63/1000+BS千円!I61-BS千円!J61+BS千円!I60-BS千円!J60 -> 0 | L7: =+月次PL!J63/1000+BS千円!J61-BS千円!K61+BS千円!J60-BS千円!K60 -> 1943.5 | ... P7: =+月次PL!N63/1000+BS千円!N61-BS千円!O61+BS千円!N60-BS千円!O60 -> 0
C8: 減価償却費 | D8: ＋ | E8: =+月次PL!C40/1000 -> 690.589 | F8: =+月次PL!D40/1000 -> 690.589 | G8: =+月次PL!E40/1000 -> 690.589 | H8: =+月次PL!F40/1000 -> 690.589 | I8: =+月次PL!G40/1000 -> 690.589 | J8: =+月次PL!H40/1000 -> 690.589 | K8: =+月次PL!I40/1000 -> 690.589 | L8: =+月次PL!J40/1000 -> 690.589 | ... P8: =+月次PL!N40/1000 -> 690.589
C9: 売掛債権 | D9: － | E9: =+BS千円!D11-BS千円!C11 -> 953.657 | F9: =+BS千円!E11-BS千円!D11 -> 845.727 | G9: =+BS千円!F11-BS千円!E11 -> -318.051 | H9: =+BS千円!G11-BS千円!F11 -> 1075.703 | I9: =+BS千円!H11-BS千円!G11 -> 299.376 | J9: =+BS千円!I11-BS千円!H11 -> 1779.456 | K9: =+BS千円!J11-BS千円!I11 -> -554.034 | L9: =+BS千円!K11-BS千円!J11 -> 656.006 | ... P9: =+BS千円!O11-BS千円!N11 -> -6716.97
C10: 棚卸資産 | D10: － | E10: =+BS千円!D17-BS千円!C17 -> 136.011 | F10: =+BS千円!E17-BS千円!D17 -> -171.626 | G10: =+BS千円!F17-BS千円!E17 -> 29.231 | H10: =+BS千円!G17-BS千円!F17 -> -37.093 | I10: =+BS千円!H17-BS千円!G17 -> 159.047 | J10: =+BS千円!I17-BS千円!H17 -> 237.172 | K10: =+BS千円!J17-BS千円!I17 -> -171.144 | L10: =+BS千円!K17-BS千円!J17 -> 78.655 | ... P10: =+BS千円!O17-BS千円!N17 -> -251.933
C11: その他流動資産 | D11: － | E11: =+BS千円!D24-BS千円!C24 -> 749.762 | F11: =+BS千円!E24-BS千円!D24 -> 358.513 | G11: =+BS千円!F24-BS千円!E24 -> 712.874 | H11: =+BS千円!G24-BS千円!F24 -> 496.28 | I11: =+BS千円!H24-BS千円!G24 -> 694.263 | J11: =+BS千円!I24-BS千円!H24 -> 674.116 | K11: =+BS千円!J24-BS千円!I24 -> 223.126 | L11: =+BS千円!K24-BS千円!J24 -> 708.447 | ... P11: =+BS千円!O24-BS千円!N24 -> 713.636
C12: 買掛未払債務 | D12: ＋ | E12: =+BS千円!D95-BS千円!C95 -> 391.571 | F12: =+BS千円!E95-BS千円!D95 -> -285.027 | G12: =+BS千円!F95-BS千円!E95 -> -850.077 | H12: =+BS千円!G95-BS千円!F95 -> -211.431 | I12: =+BS千円!H95-BS千円!G95 -> 1085.269 | J12: =+BS千円!I95-BS千円!H95 -> 1572.918 | K12: =+BS千円!J95-BS千円!I95 -> -1977.388 | L12: =+BS千円!K95-BS千円!J95 -> 454.964 | ... P12: =+BS千円!O95-BS千円!N95 -> -603.903
C13: その他流動負債 | D13: ＋ | E13: =+BS千円!D96-BS千円!C96 -> 551.651 | F13: =+BS千円!E96-BS千円!D96 -> 1315.32 | G13: =+BS千円!F96-BS千円!E96 -> 923.352 | H13: =+BS千円!G96-BS千円!F96 -> 1213.821 | I13: =+BS千円!H96-BS千円!G96 -> 607.628 | J13: =+BS千円!I96-BS千円!H96 -> 536.855 | K13: =+BS千円!J96-BS千円!I96 -> 802.784 | L13: =+BS千円!K96-BS千円!J96 -> 969.506 | ... P13: =+BS千円!O96-BS千円!N96 -> 181.545
B14: ２．投資活動CF | E14: =-E15-E16-E17 -> -3.055 | F14: =-F15-F16-F17 -> -3.055 | G14: =-G15-G16-G17 -> -3.055 | H14: =-H15-H16-H17 -> -3.055 | I14: =-I15-I16-I17 -> -3.055 | J14: =-J15-J16-J17 -> -158.055 | K14: =-K15-K16-K17 -> -3.055 | L14: =-L15-L16-L17 -> -3.055 | ... P14: =-P15-P16-P17 -> -3.055
C15: 固定資産への投資 | D15: － | E15: =+BS千円!D97-BS千円!C97+CF推移!E8 -> 0 | F15: =+BS千円!E97-BS千円!D97+CF推移!F8 -> 7.3896445e-12 | G15: =+BS千円!F97-BS千円!E97+CF推移!G8 -> -7.1622708e-12 | H15: =+BS千円!G97-BS千円!F97+CF推移!H8 -> 0 | I15: =+BS千円!H97-BS千円!G97+CF推移!I8 -> 0 | J15: =+BS千円!I97-BS千円!H97+CF推移!J8 -> 155 | K15: =+BS千円!J97-BS千円!I97+CF推移!K8 -> -7.1622708e-12 | L15: =+BS千円!K97-BS千円!J97+CF推移!L8 -> 0 | ... P15: =+BS千円!O97-BS千円!N97+CF推移!P8 -> 0
C16: 貸付金 | D16: － | E16: 0 | F16: 0 | G16: 0 | H16: 0 | I16: 0 | J16: 0 | K16: 0 | L16: 0 | M16: 0 | N16: 0 | O16: 0 | P16: 0
C17: 投資勘定への支出 | D17: － | E17: =+BS千円!D42-BS千円!C42 -> 3.055 | F17: =+BS千円!E42-BS千円!D42 -> 3.055 | G17: =+BS千円!F42-BS千円!E42 -> 3.055 | H17: =+BS千円!G42-BS千円!F42 -> 3.055 | I17: =+BS千円!H42-BS千円!G42 -> 3.055 | J17: =+BS千円!I42-BS千円!H42 -> 3.055 | K17: =+BS千円!J42-BS千円!I42 -> 3.055 | L17: =+BS千円!K42-BS千円!J42 -> 3.055 | ... P17: =+BS千円!O42-BS千円!N42 -> 3.055
B18: ３．財務活動CF | E18: =+E19+E20-E21+E22+E23 -> -235 | F18: =+F19+F20-F21+F22+F23 -> 0 | G18: =+G19+G20-G21+G22+G23 -> -470 | H18: =+H19+H20-H21+H22+H23 -> -235 | I18: =+I19+I20-I21+I22+I23 -> 0 | J18: =+J19+J20-J21+J22+J23 -> -235 | K18: =+K19+K20-K21+K22+K23 -> -235 | L18: =+L19+L20-L21+L22+L23 -> -235 | ... P18: =+P19+P20-P21+P22+P23 -> -960
C19: 短期借入金 | D19: ＋ | E19: 0 | F19: 0 | G19: 0 | H19: 0 | I19: 0 | J19: 0 | K19: 0 | L19: 0 | M19: 0 | N19: 0 | O19: 0 | P19: 0
C20: 長期借入金調達 | D20: ＋ | E20: 0 | F20: 0 | G20: 0 | H20: 0 | I20: 0 | J20: 0 | K20: 0 | L20: 0 | M20: 0 | N20: 0 | O20: 0 | P20: 0
C21: 長期借入金返済 | D21: － | E21: =+BS千円!C98-BS千円!D98+CF推移!E20 -> 235 | F21: =+BS千円!D98-BS千円!E98+CF推移!F20 -> 0 | G21: =+BS千円!E98-BS千円!F98+CF推移!G20 -> 470 | H21: =+BS千円!F98-BS千円!G98+CF推移!H20 -> 235 | I21: =+BS千円!G98-BS千円!H98+CF推移!I20 -> 0 | J21: =+BS千円!H98-BS千円!I98+CF推移!J20 -> 235 | K21: =+BS千円!I98-BS千円!J98+CF推移!K20 -> 235 | L21: =+BS千円!J98-BS千円!K98+CF推移!L20 -> 235 | ... P21: =+BS千円!N98-BS千円!O98+CF推移!P20 -> 960
C22: 資本の増減 | D22: ＋ | E22: =+BS千円!D72-BS千円!C72 -> 0 | F22: =+BS千円!E72-BS千円!D72 -> 0 | G22: =+BS千円!F72-BS千円!E72 -> 0 | H22: =+BS千円!G72-BS千円!F72 -> 0 | I22: =+BS千円!H72-BS千円!G72 -> 0 | J22: =+BS千円!I72-BS千円!H72 -> 0 | K22: =+BS千円!J72-BS千円!I72 -> 0 | L22: =+BS千円!K72-BS千円!J72 -> 0 | ... P22: =+BS千円!O72-BS千円!N72 -> 0
C23: その他 | D23: ＋ | E23: 0 | F23: 0 | G23: 0 | H23: 0 | I23: 0 | J23: 0 | K23: 0 | L23: 0 | M23: 0 | N23: 0 | O23: 0 | P23: 0
B24: ４．月次CF | E24: =+E5+E14+E18 -> -481.361 | F24: =+F5+F14+F18 -> -1849.872 | G24: =+G5+G14+G18 -> -620.487 | H24: =+H5+H14+H18 -> -206.522 | I24: =+I5+I14+I18 -> 890.699 | J24: =+J5+J14+J18 -> 1129.511 | K24: =+K5+K14+K18 -> -1451.427 | L24: =+L5+L14+L18 -> -4766.201 | ... P24: =+P5+P14+P18 -> 4558.342
C26: 現金預金の増減額 | E26: =+BS千円!D8-BS千円!C8 -> -481.361 | F26: =+BS千円!E8-BS千円!D8 -> -1849.872 | G26: =+BS千円!F8-BS千円!E8 -> -620.487 | H26: =+BS千円!G8-BS千円!F8 -> -206.522 | I26: =+BS千円!H8-BS千円!G8 -> 890.699 | J26: =+BS千円!I8-BS千円!H8 -> 1129.511 | K26: =+BS千円!J8-BS千円!I8 -> -1451.427 | L26: =+BS千円!K8-BS千円!J8 -> -4766.201 | ... P26: =+BS千円!O8-BS千円!N8 -> 4558.342
D27: CF:CK | E27: =+E24-E26 -> -2.5011104e-12 | F27: =+F24-F26 -> -1.0913936e-11 | G27: =+G24-G26 -> 1.080025e-11 | H27: =+H24-H26 -> 4.5474735e-12 | I27: =+I24-I26 -> -9.094947e-13 | J27: =+J24-J26 -> -6.8212103e-12 | K27: =+K24-K26 -> 4.0927262e-12 | L27: =+L24-L26 -> 0 | ... P27: =+P24-P26 -> 0
B28: □ＣＦ特記事項等
C29: CF計画比 | E29: =+E26-収支計画!G104/1000 -> -425.847 | F29: =+F26-収支計画!H104/1000 -> -3740.572 | G29: =+G26-収支計画!I104/1000 -> -1862.787 | H29: =+H26-収支計画!J104/1000 -> -833.022 | I29: =+I26-835 -> 55.699 | J29: =+CF推移!J26-収支計画!L104/1000 -> -1209.634 | K29: =+K26-収支計画!M104/1000 -> -807.144 | L29: =+L26-収支計画!N104/1000 -> -4113.043 | M29: =+CF推移!M26-収支計画!O104/1000 -> -1103.957 | N29: =+N26-収支計画!Q104/1000 -> -2686.13 | O29: =+O26-収支計画!Q104/1000 -> -780.13 | P29: =+P26-収支計画!R104/1000 -> 3895.322
D30: 税前利益差 | M30: -1256 | N30: =+PL予実対比!AO55 -> -2014.792 | O30: =+PL予実対比!AS55 -> -1227.254 | P30: =+PL予実対比!AW55 -> -1577.587
C31: 現金売上・売掛回収 | G31: =+PL予実対比!M23 -> -1129 | H31: =+PL予実対比!Q12 -> -1300 | J31: -1430 | K31: -611 | M31: -571 | P31: 7500 | Q31: LW回収
C32: 現金仕入・買掛未払 | M32: -377
C33: 経費支出
C34: 納税その他 | F34: 3455 | G34: 235 | M34: -450
C35: 助成金等 | H35: 400 | M35: 1000

Sheet 収支計画
E5: 収支予測表
F8: 更新日 | I8: 45917
E9: 勘定科目 | S9: 手入力 | T9: 手入力
G10: R7.07 | H10: R7.08 | I10: R7.09 | J10: R7.10 | K10: R7.11 | L10: R7.12 | M10: R8.01 | N10: R8.02 | O10: R8.03 | P10: R8.04 | Q10: R8.05 | R10: R8.06 | S10: R8.07 | T10: R8.08 | U10: R8.09 | V10: R8.10 | W10: R8.11 | X10: R8.12 | Y10: R9.01 | Z10: R9.02
E11: 売上高 | F11: 恵愛 | G11: ='[1]2024.07～恵愛予測'!C3 -> 7000000 | H11: ='[1]2024.07～恵愛予測'!D3 -> 7000000 | I11: 7000000 | J11: 7000000 | K11: 7000000 | L11: 9500000 | M11: 7000000 | N11: 7000000 | O11: 8500000 | P11: ='[2]2024.07～恵愛予測'!L3 -> 7000000 | Q11: ='[2]2024.07～恵愛予測'!M3 -> 7000000 | R11: ='[2]2024.07～恵愛予測'!N3 -> 7000000 | S11: 7000000 | T11: 7000000
F12: 村 | G12: ='[1]2024.7~村予測'!C3 -> 750000 | H12: ='[1]2024.7~村予測'!D3 -> 750000 | I12: 750000 | J12: 750000 | K12: 750000 | L12: 750000 | M12: 750000 | N12: 750000 | O12: 750000 | P12: ='[2]2024.7~村予測'!L3 -> 750000 | Q12: ='[2]2024.7~村予測'!M3 -> 750000 | R12: ='[2]2024.7~村予測'!N3 -> 750000 | S12: 750000 | T12: 750000
F13: 弁当事業 | G13: ='[1]2024.7~弁当予測'!C3 -> 350000 | H13: ='[1]2024.7~弁当予測'!D3 -> 350000 | I13: 350000 | J13: 350000 | K13: 350000 | L13: 350000 | M13: 350000 | N13: 350000 | O13: 350000 | P13: ='[2]2024.7~弁当予測'!L3 -> 350000 | Q13: ='[2]2024.7~弁当予測'!M3 -> 350000 | R13: ='[2]2024.7~弁当予測'!N3 -> 350000 | S13: 350000 | T13: 350000
F14: シェア | G14: ='[1]2024.7~シェアバー予測'!C3 -> 150000 | H14: ='[1]2024.7~シェアバー予測'!D3 -> 150000 | I14: 150000 | J14: 150000 | K14: 150000 | L14: 150000 | M14: 150000 | N14: 150000 | O14: 150000 | P14: ='[2]2024.7~シェアバー予測'!L3 -> 150000 | Q14: ='[2]2024.7~シェアバー予測'!M3 -> 150000 | R14: ='[2]2024.7~シェアバー予測'!N3 -> 150000 | S14: 150000 | T14: 150000
F15: サウナ | G15: ='[1]2024.7~サウナ予測'!C3 -> 1000000 | H15: ='[1]2024.7~サウナ予測'!D3 -> 2620000 | I15: 1000000 | J15: 1000000 | K15: 1000000 | L15: 1000000 | M15: 1000000 | N15: 1000000 | O15: 1000000 | P15: ='[2]2024.7~サウナ予測'!L3 -> 1000000 | Q15: ='[2]2024.7~サウナ予測'!M3 -> 1000000 | R15: ='[2]2024.7~サウナ予測'!N3 -> 1000000 | S15: 1000000 | T15: 1000000
B16: 月末売掛残高割合 | C16: 現金割合 | F16: 本部 | G16: ='[1]2024.07~本部予測'!C3 -> 350000 | H16: ='[1]2024.07~本部予測'!D3 -> 350000 | I16: 350000 | J16: 350000 | K16: 350000 | L16: 350000 | M16: 350000 | N16: 350000 | O16: 350000 | P16: ='[2]2024.07~本部予測'!L3 -> 350000 | Q16: ='[2]2024.07~本部予測'!M3 -> 350000 | R16: ='[2]2024.07~本部予測'!N3 -> 350000 | S16: 350000 | T16: 350000
A17: 原価率 | B17: 0.34 | C17: =1-B17 -> 0.66 | F17: 合計 | G17: =SUM(G11:G16) -> 9600000 | H17: =SUM(H11:H16) -> 11220000 | I17: =SUM(I11:I16) -> 9600000 | J17: =SUM(J11:J16) -> 9600000 | K17: =SUM(K11:K16) -> 9600000 | L17: =SUM(L11:L16) -> 12100000 | M17: =SUM(M11:M16) -> 9600000 | N17: =SUM(N11:N16) -> 9600000 | ... Z17: =SUM(Z11:Z16) -> 0
A18: 0.3 | E18: 売上原価 | F18: 恵愛 | G18: ='[1]2024.07～恵愛予測'!C4 -> 1785000 | H18: ='[1]2024.07～恵愛予測'!D4 -> 1785000 | I18: ='[1]2024.07～恵愛予測'!E4 -> 1785000 | J18: ='[1]2024.07～恵愛予測'!F4 -> 1785000 | K18: ='[1]2024.07～恵愛予測'!G4 -> 1785000 | L18: ='[1]2024.07～恵愛予測'!H4 -> 2422500 | M18: ='[1]2024.07～恵愛予測'!I4 -> 1785000 | N18: ='[1]2024.07～恵愛予測'!J4 -> 1785000 | O18: ='[1]2024.07～恵愛予測'!K4 -> 2167500 | P18: ='[2]2024.07～恵愛予測'!L4 -> 1785000 | Q18: ='[2]2024.07～恵愛予測'!M4 -> 1785000 | R18: ='[2]2024.07～恵愛予測'!N4 -> 1785000 | S18: 1750000 | T18: 1750000
A19: 0.34 | F19: 村 | G19: ='[1]2024.7~村予測'!C4 -> 112500 | H19: ='[1]2024.7~村予測'!D4 -> 112500 | I19: ='[1]2024.7~村予測'!E4 -> 112500 | J19: ='[1]2024.7~村予測'!F4 -> 112500 | K19: ='[1]2024.7~村予測'!G4 -> 112500 | L19: ='[1]2024.7~村予測'!H4 -> 112500 | M19: ='[1]2024.7~村予測'!I4 -> 112500 | N19: ='[1]2024.7~村予測'!J4 -> 112500 | O19: ='[1]2024.7~村予測'!K4 -> 112500 | P19: ='[2]2024.7~村予測'!L4 -> 112500 | Q19: ='[2]2024.7~村予測'!M4 -> 112500 | R19: ='[2]2024.7~村予測'!N4 -> 112500 | S19: 112500 | T19: 112500
F20: 弁当事業 | G20: ='[1]2024.7~弁当予測'!C4 -> 157500 | H20: ='[1]2024.7~弁当予測'!D4 -> 157500 | I20: ='[1]2024.7~弁当予測'!E4 -> 157500 | J20: ='[1]2024.7~弁当予測'!F4 -> 157500 | K20: ='[1]2024.7~弁当予測'!G4 -> 157500 | L20: ='[1]2024.7~弁当予測'!H4 -> 157500 | M20: ='[1]2024.7~弁当予測'!I4 -> 157500 | N20: ='[1]2024.7~弁当予測'!J4 -> 157500 | O20: ='[1]2024.7~弁当予測'!K4 -> 157500 | P20: ='[2]2024.7~弁当予測'!L4 -> 140000 | Q20: ='[2]2024.7~弁当予測'!M4 -> 140000 | R20: ='[2]2024.7~弁当予測'!N4 -> 140000 | S20: 157500 | T20: 157500
A21: 0.32 | F21: シェア | G21: ='[1]2024.7~シェアバー予測'!C4 -> 45000 | H21: ='[1]2024.7~シェアバー予測'!D4 -> 45000 | I21: ='[1]2024.7~シェアバー予測'!E4 -> 45000 | J21: ='[1]2024.7~シェアバー予測'!F4 -> 45000 | K21: ='[1]2024.7~シェアバー予測'!G4 -> 45000 | L21: ='[1]2024.7~シェアバー予測'!H4 -> 45000 | M21: ='[1]2024.7~シェアバー予測'!I4 -> 45000 | N21: ='[1]2024.7~シェアバー予測'!J4 -> 45000 | O21: ='[1]2024.7~シェアバー予測'!K4 -> 45000 | P21: ='[2]2024.7~シェアバー予測'!L4 -> 45000 | Q21: ='[2]2024.7~シェアバー予測'!M4 -> 45000 | R21: ='[2]2024.7~シェアバー予測'!N4 -> 45000 | S21: 45000 | T21: 45000
F22: サウナ | G22: ='[1]2024.7~サウナ予測'!C4 -> 100000 | H22: ='[1]2024.7~サウナ予測'!D4 -> 100000 | I22: ='[1]2024.7~サウナ予測'!E4 -> 100000 | J22: ='[1]2024.7~サウナ予測'!F4 -> 100000 | K22: ='[1]2024.7~サウナ予測'!G4 -> 100000 | L22: ='[1]2024.7~サウナ予測'!H4 -> 100000 | M22: ='[1]2024.7~サウナ予測'!I4 -> 100000 | N22: ='[1]2024.7~サウナ予測'!J4 -> 100000 | O22: ='[1]2024.7~サウナ予測'!K4 -> 100000 | P22: ='[2]2024.7~サウナ予測'!L4 -> 100000 | Q22: ='[2]2024.7~サウナ予測'!M4 -> 100000 | R22: ='[2]2024.7~サウナ予測'!N4 -> 100000 | S22: 100000 | T22: 100000
A23: 0.34 | B23: 掛割合 | C23: 現金割合 | F23: 本部 | G23: ='[1]2024.07~本部予測'!C4 -> 0 | H23: ='[1]2024.07~本部予測'!D4 -> 0 | I23: ='[1]2024.07~本部予測'!E4 -> 0 | J23: ='[1]2024.07~本部予測'!F4 -> 0 | K23: ='[1]2024.07~本部予測'!G4 -> 0 | L23: ='[1]2024.07~本部予測'!H4 -> 0 | M23: ='[1]2024.07~本部予測'!I4 -> 0 | N23: ='[1]2024.07~本部予測'!J4 -> 0 | O23: ='[1]2024.07~本部予測'!K4 -> 0 | P23: ='[2]2024.07~本部予測'!L4 -> 0 | Q23: ='[2]2024.07~本部予測'!M4 -> 0 | R23: ='[2]2024.07~本部予測'!N4 -> 0 | S23: 0 | T23: 0
B24: 0.99 | C24: =1-B24 -> 0.01 | F24: 合計 | G24: =SUM(G18:G23) -> 2200000 | H24: =SUM(H18:H23) -> 2200000 | I24: =SUM(I18:I23) -> 2200000 | J24: =SUM(J18:J23) -> 2200000 | K24: =SUM(K18:K23) -> 2200000 | L24: =SUM(L18:L23) -> 2837500 | M24: =SUM(M18:M23) -> 2200000 | N24: =SUM(N18:N23) -> 2200000 | ... Z24: =SUM(Z18:Z23) -> 0
E25: 粗利益 | G25: =G17-G24 -> 7400000 | H25: =H17-H24 -> 9020000 | I25: =I17-I24 -> 7400000 | J25: =J17-J24 -> 7400000 | K25: =K17-K24 -> 7400000 | L25: =L17-L24 -> 9262500 | M25: =M17-M24 -> 7400000 | N25: =N17-N24 -> 7400000 | ... Z25: =Z17-Z24 -> 0
A26: 予測値 | G26: =G25/G17 -> 0.77083333 | H26: =H25/H17 -> 0.80392157 | I26: =I25/I17 -> 0.77083333 | J26: =J25/J17 -> 0.77083333 | K26: =K25/K17 -> 0.77083333 | L26: =L25/L17 -> 0.76549587 | M26: =M25/M17 -> 0.77083333 | N26: =N25/N17 -> 0.77083333 | ... Z26: =Z25/Z17 -> #DIV/0!
A27: 590 | E27: 人件費 | F27: 役員報酬 | G27: ='[1]2024.07～恵愛予測'!C7+'[1]2024.7~村予測'!C7+'[1]2024.7~弁当予測'!C7+'[1]2024.7~シェアバー予測'!C7+'[1]2024.7~サウナ予測'!C7+'[1]2024.07~本部予測'!C7 -> 500000 | H27: ='[1]2024.07～恵愛予測'!D7+'[1]2024.7~村予測'!D7+'[1]2024.7~弁当予測'!D7+'[1]2024.7~シェアバー予測'!D7+'[1]2024.7~サウナ予測'!D7+'[1]2024.07~本部予測'!D7 -> 500000 | I27: 500000 | J27: 500000 | K27: 500000 | L27: 500000 | M27: 500000 | N27: 500000 | O27: 500000 | P27: ='[2]2024.07～恵愛予測'!L7+'[2]2024.7~村予測'!L7+'[2]2024.7~弁当予測'!L7+'[2]2024.7~シェアバー予測'!L7+'[2]2024.7~サウナ予測'!L7+'[2]2024.07~本部予測'!L7 -> 500000 | Q27: ='[2]2024.07～恵愛予測'!M7+'[2]2024.7~村予測'!M7+'[2]2024.7~弁当予測'!M7+'[2]2024.7~シェアバー予測'!M7+'[2]2024.7~サウナ予測'!M7+'[2]2024.07~本部予測'!M7 -> 500000 | R27: ='[2]2024.07～恵愛予測'!N7+'[2]2024.7~村予測'!N7+'[2]2024.7~弁当予測'!N7+'[2]2024.7~シェアバー予測'!N7+'[2]2024.7~サウナ予測'!N7+'[2]2024.07~本部予測'!N7 -> 500000 | S27: 500000 | T27: 500000
F28: 給与手当 | G28: ='[1]2024.07～恵愛予測'!C8+'[1]2024.7~村予測'!C8+'[1]2024.7~弁当予測'!C8+'[1]2024.7~シェアバー予測'!C8+'[1]2024.7~サウナ予測'!C8+'[1]2024.07~本部予測'!C8 -> 570000 | H28: ='[1]2024.07～恵愛予測'!D8+'[1]2024.7~村予測'!D8+'[1]2024.7~弁当予測'!D8+'[1]2024.7~シェアバー予測'!D8+'[1]2024.7~サウナ予測'!D8+'[1]2024.07~本部予測'!D8 -> 570000 | I28: 570000 | J28: 570000 | K28: 350000 | L28: 350000 | M28: 350000 | N28: 350000 | O28: 350000 | P28: ='[2]2024.07～恵愛予測'!L8+'[2]2024.7~村予測'!L8+'[2]2024.7~弁当予測'!L8+'[2]2024.7~シェアバー予測'!L8+'[2]2024.7~サウナ予測'!L8+'[2]2024.07~本部予測'!L8 -> 350000 | Q28: ='[2]2024.07～恵愛予測'!M8+'[2]2024.7~村予測'!M8+'[2]2024.7~弁当予測'!M8+'[2]2024.7~シェアバー予測'!M8+'[2]2024.7~サウナ予測'!M8+'[2]2024.07~本部予測'!M8 -> 350000 | R28: ='[2]2024.07～恵愛予測'!N8+'[2]2024.7~村予測'!N8+'[2]2024.7~弁当予測'!N8+'[2]2024.7~シェアバー予測'!N8+'[2]2024.7~サウナ予測'!N8+'[2]2024.07~本部予測'!N8 -> 350000 | S28: 570000 | T28: 570000
A29: ＊＊＊＊ | F29: 雑給 | G29: ='[1]2024.07～恵愛予測'!C9+'[1]2024.7~村予測'!C9+'[1]2024.7~弁当予測'!C9+'[1]2024.7~シェアバー予測'!C9+'[1]2024.7~サウナ予測'!C9+'[1]2024.07~本部予測'!C9 -> 1130000 | H29: ='[1]2024.07～恵愛予測'!D9+'[1]2024.7~村予測'!D9+'[1]2024.7~弁当予測'!D9+'[1]2024.7~シェアバー予測'!D9+'[1]2024.7~サウナ予測'!D9+'[1]2024.07~本部予測'!D9 -> 1130000 | I29: 1130000 | J29: 1130000 | K29: 1270000 | L29: 1695000 | M29: 1270000 | N29: 1270000 | O29: 1525000 | P29: ='[2]2024.07～恵愛予測'!L9+'[2]2024.7~村予測'!L9+'[2]2024.7~弁当予測'!L9+'[2]2024.7~シェアバー予測'!L9+'[2]2024.7~サウナ予測'!L9+'[2]2024.07~本部予測'!L9 -> 1250000 | Q29: ='[2]2024.07～恵愛予測'!M9+'[2]2024.7~村予測'!M9+'[2]2024.7~弁当予測'!M9+'[2]2024.7~シェアバー予測'!M9+'[2]2024.7~サウナ予測'!M9+'[2]2024.07~本部予測'!M9 -> 1250000 | R29: ='[2]2024.07～恵愛予測'!N9+'[2]2024.7~村予測'!N9+'[2]2024.7~弁当予測'!N9+'[2]2024.7~シェアバー予測'!N9+'[2]2024.7~サウナ予測'!N9+'[2]2024.07~本部予測'!N9 -> 1250000 | S29: 1130000 | T29: 1130000
A30: ＊＊＊＊ | F30: 法定福利費 | G30: ='[1]2024.07～恵愛予測'!C10+'[1]2024.7~村予測'!C10+'[1]2024.7~弁当予測'!C10+'[1]2024.7~シェアバー予測'!C10+'[1]2024.7~サウナ予測'!C10+'[1]2024.07~本部予測'!C10 -> 160500 | H30: ='[1]2024.07～恵愛予測'!D10+'[1]2024.7~村予測'!D10+'[1]2024.7~弁当予測'!D10+'[1]2024.7~シェアバー予測'!D10+'[1]2024.7~サウナ予測'!D10+'[1]2024.07~本部予測'!D10 -> 160500 | I30: 145500 | J30: 145500 | K30: 112500 | L30: 112500 | M30: 112500 | N30: 112500 | O30: 112500 | P30: ='[2]2024.07～恵愛予測'!L10+'[2]2024.7~村予測'!L10+'[2]2024.7~弁当予測'!L10+'[2]2024.7~シェアバー予測'!L10+'[2]2024.7~サウナ予測'!L10+'[2]2024.07~本部予測'!L10 -> 140000 | Q30: ='[2]2024.07～恵愛予測'!M10+'[2]2024.7~村予測'!M10+'[2]2024.7~弁当予測'!M10+'[2]2024.7~シェアバー予測'!M10+'[2]2024.7~サウナ予測'!M10+'[2]2024.07~本部予測'!M10 -> 140000 | R30: ='[2]2024.07～恵愛予測'!N10+'[2]2024.7~村予測'!N10+'[2]2024.7~弁当予測'!N10+'[2]2024.7~シェアバー予測'!N10+'[2]2024.7~サウナ予測'!N10+'[2]2024.07~本部予測'!N10 -> 140000 | S30: 160500 | T30: 160500
F31: 福利厚生費 | G31: ='[1]2024.07～恵愛予測'!C11+'[1]2024.7~村予測'!C11+'[1]2024.7~弁当予測'!C11+'[1]2024.7~シェアバー予測'!C11+'[1]2024.7~サウナ予測'!C11+'[1]2024.07~本部予測'!C11 -> 0 | H31: ='[1]2024.07～恵愛予測'!D11+'[1]2024.7~村予測'!D11+'[1]2024.7~弁当予測'!D11+'[1]2024.7~シェアバー予測'!D11+'[1]2024.7~サウナ予測'!D11+'[1]2024.07~本部予測'!D11 -> 0 | I31: 0 | J31: 0 | K31: 0 | L31: 0 | M31: 0 | N31: 0 | O31: 0 | P31: ='[2]2024.07～恵愛予測'!L11+'[2]2024.7~村予測'!L11+'[2]2024.7~弁当予測'!L11+'[2]2024.7~シェアバー予測'!L11+'[2]2024.7~サウナ予測'!L11+'[2]2024.07~本部予測'!L11 -> 0 | Q31: ='[2]2024.07～恵愛予測'!M11+'[2]2024.7~村予測'!M11+'[2]2024.7~弁当予測'!M11+'[2]2024.7~シェアバー予測'!M11+'[2]2024.7~サウナ予測'!M11+'[2]2024.07~本部予測'!M11 -> 0 | R31: ='[2]2024.07～恵愛予測'!N11+'[2]2024.7~村予測'!N11+'[2]2024.7~弁当予測'!N11+'[2]2024.7~シェアバー予測'!N11+'[2]2024.7~サウナ予測'!N11+'[2]2024.07~本部予測'!N11 -> 0 | S31: 0 | T31: 0
F32: 業務委託費（グループ） | G32: ='[1]2024.07～恵愛予測'!C12+'[1]2024.7~村予測'!C12+'[1]2024.7~弁当予測'!C12+'[1]2024.7~シェアバー予測'!C12+'[1]2024.7~サウナ予測'!C12+'[1]2024.07~本部予測'!C12 -> 260000 | H32: ='[1]2024.07～恵愛予測'!D12+'[1]2024.7~村予測'!D12+'[1]2024.7~弁当予測'!D12+'[1]2024.7~シェアバー予測'!D12+'[1]2024.7~サウナ予測'!D12+'[1]2024.07~本部予測'!D12 -> 260000 | I32: 260000 | J32: 260000 | K32: 260000 | L32: 260000 | M32: 260000 | N32: 260000 | O32: 260000 | P32: ='[2]2024.07～恵愛予測'!L12+'[2]2024.7~村予測'!L12+'[2]2024.7~弁当予測'!L12+'[2]2024.7~シェアバー予測'!L12+'[2]2024.7~サウナ予測'!L12+'[2]2024.07~本部予測'!L12 -> 260000 | Q32: ='[2]2024.07～恵愛予測'!M12+'[2]2024.7~村予測'!M12+'[2]2024.7~弁当予測'!M12+'[2]2024.7~シェアバー予測'!M12+'[2]2024.7~サウナ予測'!M12+'[2]2024.07~本部予測'!M12 -> 260000 | R32: ='[2]2024.07～恵愛予測'!N12+'[2]2024.7~村予測'!N12+'[2]2024.7~弁当予測'!N12+'[2]2024.7~シェアバー予測'!N12+'[2]2024.7~サウナ予測'!N12+'[2]2024.07~本部予測'!N12 -> 260000 | S32: 285000 | T32: 285000
A33: 3780 | F33: 労務委託費（個人） | G33: ='[1]2024.07～恵愛予測'!C13+'[1]2024.7~村予測'!C13+'[1]2024.7~弁当予測'!C13+'[1]2024.7~シェアバー予測'!C13+'[1]2024.7~サウナ予測'!C13+'[1]2024.07~本部予測'!C13 -> 101819 | H33: ='[1]2024.07～恵愛予測'!D13+'[1]2024.7~村予測'!D13+'[1]2024.7~弁当予測'!D13+'[1]2024.7~シェアバー予測'!D13+'[1]2024.7~サウナ予測'!D13+'[1]2024.07~本部予測'!D13 -> 101819 | I33: 101819 | J33: 101819 | K33: 101819 | L33: 101819 | M33: 101819 | N33: 101819 | O33: 101819 | P33: ='[2]2024.07～恵愛予測'!L13+'[2]2024.7~村予測'!L13+'[2]2024.7~弁当予測'!L13+'[2]2024.7~シェアバー予測'!L13+'[2]2024.7~サウナ予測'!L13+'[2]2024.07~本部予測'!L13 -> 101819 | Q33: ='[2]2024.07～恵愛予測'!M13+'[2]2024.7~村予測'!M13+'[2]2024.7~弁当予測'!M13+'[2]2024.7~シェアバー予測'!M13+'[2]2024.7~サウナ予測'!M13+'[2]2024.07~本部予測'!M13 -> 101819 | R33: ='[2]2024.07～恵愛予測'!N13+'[2]2024.7~村予測'!N13+'[2]2024.7~弁当予測'!N13+'[2]2024.7~シェアバー予測'!N13+'[2]2024.7~サウナ予測'!N13+'[2]2024.07~本部予測'!N13 -> 101819 | S33: 101819 | T33: 101819
A34: 予測値 | F34: 合計 | G34: =SUM(G27:G33) -> 2722319 | H34: =SUM(H27:H33) -> 2722319 | I34: =SUM(I27:I33) -> 2707319 | J34: =SUM(J27:J33) -> 2707319 | K34: =SUM(K27:K33) -> 2594319 | L34: =SUM(L27:L33) -> 3019319 | M34: =SUM(M27:M33) -> 2594319 | N34: =SUM(N27:N33) -> 2594319 | ... Z34: =SUM(Z27:Z33) -> 0
A35: 661 | E35: 販売費管理費 | F35: 旅費交通費 | G35: ='[1]2024.07～恵愛予測'!C14+'[1]2024.7~村予測'!C14+'[1]2024.7~弁当予測'!C14+'[1]2024.7~シェアバー予測'!C14+'[1]2024.7~サウナ予測'!C14+'[1]2024.07~本部予測'!C14 -> 50000 | H35: ='[1]2024.07～恵愛予測'!D14+'[1]2024.7~村予測'!D14+'[1]2024.7~弁当予測'!D14+'[1]2024.7~シェアバー予測'!D14+'[1]2024.7~サウナ予測'!D14+'[1]2024.07~本部予測'!D14 -> 50000 | I35: 50000 | J35: 50000 | K35: ='[3]2024.07～恵愛予測'!G14+'[3]2024.7~村予測'!G14+'[3]2024.7~弁当予測'!G14+'[3]2024.7~シェアバー予測'!G14+'[3]2024.7~サウナ予測'!G14+'[3]2024.07~本部予測'!G14 -> 50000 | L35: ='[3]2024.07～恵愛予測'!H14+'[3]2024.7~村予測'!H14+'[3]2024.7~弁当予測'!H14+'[3]2024.7~シェアバー予測'!H14+'[3]2024.7~サウナ予測'!H14+'[3]2024.07~本部予測'!H14 -> 55000 | M35: ='[3]2024.07～恵愛予測'!I14+'[3]2024.7~村予測'!I14+'[3]2024.7~弁当予測'!I14+'[3]2024.7~シェアバー予測'!I14+'[3]2024.7~サウナ予測'!I14+'[3]2024.07~本部予測'!I14 -> 55000 | N35: ='[3]2024.07～恵愛予測'!J14+'[3]2024.7~村予測'!J14+'[3]2024.7~弁当予測'!J14+'[3]2024.7~シェアバー予測'!J14+'[3]2024.7~サウナ予測'!J14+'[3]2024.07~本部予測'!J14 -> 55000 | O35: ='[3]2024.07～恵愛予測'!K14+'[3]2024.7~村予測'!K14+'[3]2024.7~弁当予測'!K14+'[3]2024.7~シェアバー予測'!K14+'[3]2024.7~サウナ予測'!K14+'[3]2024.07~本部予測'!K14 -> 55000 | P35: ='[2]2024.07～恵愛予測'!L14+'[2]2024.7~村予測'!L14+'[2]2024.7~弁当予測'!L14+'[2]2024.7~シェアバー予測'!L14+'[2]2024.7~サウナ予測'!L14+'[2]2024.07~本部予測'!L14 -> 50000 | Q35: ='[2]2024.07～恵愛予測'!M14+'[2]2024.7~村予測'!M14+'[2]2024.7~弁当予測'!M14+'[2]2024.7~シェアバー予測'!M14+'[2]2024.7~サウナ予測'!M14+'[2]2024.07~本部予測'!M14 -> 50000 | R35: ='[2]2024.07～恵愛予測'!N14+'[2]2024.7~村予測'!N14+'[2]2024.7~弁当予測'!N14+'[2]2024.7~シェアバー予測'!N14+'[2]2024.7~サウナ予測'!N14+'[2]2024.07~本部予測'!N14 -> 50000 | S35: 50000 | T35: 50000
A36: ＊＊＊＊ | F36: 通信費 | G36: ='[1]2024.07～恵愛予測'!C15+'[1]2024.7~村予測'!C15+'[1]2024.7~弁当予測'!C15+'[1]2024.7~シェアバー予測'!C15+'[1]2024.7~サウナ予測'!C15+'[1]2024.07~本部予測'!C15 -> 63050 | H36: ='[1]2024.07～恵愛予測'!D15+'[1]2024.7~村予測'!D15+'[1]2024.7~弁当予測'!D15+'[1]2024.7~シェアバー予測'!D15+'[1]2024.7~サウナ予測'!D15+'[1]2024.07~本部予測'!D15 -> 63050 | I36: 63050 | J36: 63050 | K36: ='[3]2024.07～恵愛予測'!G15+'[3]2024.7~村予測'!G15+'[3]2024.7~弁当予測'!G15+'[3]2024.7~シェアバー予測'!G15+'[3]2024.7~サウナ予測'!G15+'[3]2024.07~本部予測'!G15 -> 64530 | L36: ='[3]2024.07～恵愛予測'!H15+'[3]2024.7~村予測'!H15+'[3]2024.7~弁当予測'!H15+'[3]2024.7~シェアバー予測'!H15+'[3]2024.7~サウナ予測'!H15+'[3]2024.07~本部予測'!H15 -> 64530 | M36: ='[3]2024.07～恵愛予測'!I15+'[3]2024.7~村予測'!I15+'[3]2024.7~弁当予測'!I15+'[3]2024.7~シェアバー予測'!I15+'[3]2024.7~サウナ予測'!I15+'[3]2024.07~本部予測'!I15 -> 64530 | N36: ='[3]2024.07～恵愛予測'!J15+'[3]2024.7~村予測'!J15+'[3]2024.7~弁当予測'!J15+'[3]2024.7~シェアバー予測'!J15+'[3]2024.7~サウナ予測'!J15+'[3]2024.07~本部予測'!J15 -> 64530 | O36: ='[3]2024.07～恵愛予測'!K15+'[3]2024.7~村予測'!K15+'[3]2024.7~弁当予測'!K15+'[3]2024.7~シェアバー予測'!K15+'[3]2024.7~サウナ予測'!K15+'[3]2024.07~本部予測'!K15 -> 64530 | P36: ='[2]2024.07～恵愛予測'!L15+'[2]2024.7~村予測'!L15+'[2]2024.7~弁当予測'!L15+'[2]2024.7~シェアバー予測'!L15+'[2]2024.7~サウナ予測'!L15+'[2]2024.07~本部予測'!L15 -> 64530 | Q36: ='[2]2024.07～恵愛予測'!M15+'[2]2024.7~村予測'!M15+'[2]2024.7~弁当予測'!M15+'[2]2024.7~シェアバー予測'!M15+'[2]2024.7~サウナ予測'!M15+'[2]2024.07~本部予測'!M15 -> 64530 | R36: ='[2]2024.07～恵愛予測'!N15+'[2]2024.7~村予測'!N15+'[2]2024.7~弁当予測'!N15+'[2]2024.7~シェアバー予測'!N15+'[2]2024.7~サウナ予測'!N15+'[2]2024.07~本部予測'!N15 -> 64530 | S36: 69050 | T36: 69050
A37: ＊＊＊＊ | F37: 開発費 | G37: ='[1]2024.07～恵愛予測'!C16+'[1]2024.7~村予測'!C16+'[1]2024.7~弁当予測'!C16+'[1]2024.7~シェアバー予測'!C16+'[1]2024.7~サウナ予測'!C16+'[1]2024.07~本部予測'!C16 -> 0 | H37: ='[1]2024.07～恵愛予測'!D16+'[1]2024.7~村予測'!D16+'[1]2024.7~弁当予測'!D16+'[1]2024.7~シェアバー予測'!D16+'[1]2024.7~サウナ予測'!D16+'[1]2024.07~本部予測'!D16 -> 0 | I37: 0 | J37: 0 | K37: ='[3]2024.07～恵愛予測'!G16+'[3]2024.7~村予測'!G16+'[3]2024.7~弁当予測'!G16+'[3]2024.7~シェアバー予測'!G16+'[3]2024.7~サウナ予測'!G16+'[3]2024.07~本部予測'!G16 -> 0 | L37: ='[3]2024.07～恵愛予測'!H16+'[3]2024.7~村予測'!H16+'[3]2024.7~弁当予測'!H16+'[3]2024.7~シェアバー予測'!H16+'[3]2024.7~サウナ予測'!H16+'[3]2024.07~本部予測'!H16 -> 0 | M37: ='[3]2024.07～恵愛予測'!I16+'[3]2024.7~村予測'!I16+'[3]2024.7~弁当予測'!I16+'[3]2024.7~シェアバー予測'!I16+'[3]2024.7~サウナ予測'!I16+'[3]2024.07~本部予測'!I16 -> 0 | N37: ='[3]2024.07～恵愛予測'!J16+'[3]2024.7~村予測'!J16+'[3]2024.7~弁当予測'!J16+'[3]2024.7~シェアバー予測'!J16+'[3]2024.7~サウナ予測'!J16+'[3]2024.07~本部予測'!J16 -> 0 | O37: ='[3]2024.07～恵愛予測'!K16+'[3]2024.7~村予測'!K16+'[3]2024.7~弁当予測'!K16+'[3]2024.7~シェアバー予測'!K16+'[3]2024.7~サウナ予測'!K16+'[3]2024.07~本部予測'!K16 -> 0 | P37: ='[2]2024.07～恵愛予測'!L16+'[2]2024.7~村予測'!L16+'[2]2024.7~弁当予測'!L16+'[2]2024.7~シェアバー予測'!L16+'[2]2024.7~サウナ予測'!L16+'[2]2024.07~本部予測'!L16 -> 0 | Q37: ='[2]2024.07～恵愛予測'!M16+'[2]2024.7~村予測'!M16+'[2]2024.7~弁当予測'!M16+'[2]2024.7~シェアバー予測'!M16+'[2]2024.7~サウナ予測'!M16+'[2]2024.07~本部予測'!M16 -> 0 | R37: ='[2]2024.07～恵愛予測'!N16+'[2]2024.7~村予測'!N16+'[2]2024.7~弁当予測'!N16+'[2]2024.7~シェアバー予測'!N16+'[2]2024.7~サウナ予測'!N16+'[2]2024.07~本部予測'!N16 -> 0 | S37: 0 | T37: 0
F38: 交際費 | G38: ='[1]2024.07～恵愛予測'!C17+'[1]2024.7~村予測'!C17+'[1]2024.7~弁当予測'!C17+'[1]2024.7~シェアバー予測'!C17+'[1]2024.7~サウナ予測'!C17+'[1]2024.07~本部予測'!C17 -> 0 | H38: ='[1]2024.07～恵愛予測'!D17+'[1]2024.7~村予測'!D17+'[1]2024.7~弁当予測'!D17+'[1]2024.7~シェアバー予測'!D17+'[1]2024.7~サウナ予測'!D17+'[1]2024.07~本部予測'!D17 -> 0 | I38: 0 | J38: 0 | K38: ='[3]2024.07～恵愛予測'!G17+'[3]2024.7~村予測'!G17+'[3]2024.7~弁当予測'!G17+'[3]2024.7~シェアバー予測'!G17+'[3]2024.7~サウナ予測'!G17+'[3]2024.07~本部予測'!G17 -> 0 | L38: ='[3]2024.07～恵愛予測'!H17+'[3]2024.7~村予測'!H17+'[3]2024.7~弁当予測'!H17+'[3]2024.7~シェアバー予測'!H17+'[3]2024.7~サウナ予測'!H17+'[3]2024.07~本部予測'!H17 -> 0 | M38: ='[3]2024.07～恵愛予測'!I17+'[3]2024.7~村予測'!I17+'[3]2024.7~弁当予測'!I17+'[3]2024.7~シェアバー予測'!I17+'[3]2024.7~サウナ予測'!I17+'[3]2024.07~本部予測'!I17 -> 0 | N38: ='[3]2024.07～恵愛予測'!J17+'[3]2024.7~村予測'!J17+'[3]2024.7~弁当予測'!J17+'[3]2024.7~シェアバー予測'!J17+'[3]2024.7~サウナ予測'!J17+'[3]2024.07~本部予測'!J17 -> 0 | O38: ='[3]2024.07～恵愛予測'!K17+'[3]2024.7~村予測'!K17+'[3]2024.7~弁当予測'!K17+'[3]2024.7~シェアバー予測'!K17+'[3]2024.7~サウナ予測'!K17+'[3]2024.07~本部予測'!K17 -> 0 | P38: ='[2]2024.07～恵愛予測'!L17+'[2]2024.7~村予測'!L17+'[2]2024.7~弁当予測'!L17+'[2]2024.7~シェアバー予測'!L17+'[2]2024.7~サウナ予測'!L17+'[2]2024.07~本部予測'!L17 -> 0 | Q38: ='[2]2024.07～恵愛予測'!M17+'[2]2024.7~村予測'!M17+'[2]2024.7~弁当予測'!M17+'[2]2024.7~シェアバー予測'!M17+'[2]2024.7~サウナ予測'!M17+'[2]2024.07~本部予測'!M17 -> 0 | R38: ='[2]2024.07～恵愛予測'!N17+'[2]2024.7~村予測'!N17+'[2]2024.7~弁当予測'!N17+'[2]2024.7~シェアバー予測'!N17+'[2]2024.7~サウナ予測'!N17+'[2]2024.07~本部予測'!N17 -> 0 | S38: 50000 | T38: 50000
F39: 会議費 | G39: ='[1]2024.07～恵愛予測'!C18+'[1]2024.7~村予測'!C18+'[1]2024.7~弁当予測'!C18+'[1]2024.7~シェアバー予測'!C18+'[1]2024.7~サウナ予測'!C18+'[1]2024.07~本部予測'!C18 -> 10000 | H39: ='[1]2024.07～恵愛予測'!D18+'[1]2024.7~村予測'!D18+'[1]2024.7~弁当予測'!D18+'[1]2024.7~シェアバー予測'!D18+'[1]2024.7~サウナ予測'!D18+'[1]2024.07~本部予測'!D18 -> 0 | I39: 0 | J39: 0 | K39: ='[3]2024.07～恵愛予測'!G18+'[3]2024.7~村予測'!G18+'[3]2024.7~弁当予測'!G18+'[3]2024.7~シェアバー予測'!G18+'[3]2024.7~サウナ予測'!G18+'[3]2024.07~本部予測'!G18 -> 0 | L39: ='[3]2024.07～恵愛予測'!H18+'[3]2024.7~村予測'!H18+'[3]2024.7~弁当予測'!H18+'[3]2024.7~シェアバー予測'!H18+'[3]2024.7~サウナ予測'!H18+'[3]2024.07~本部予測'!H18 -> 20000 | M39: ='[3]2024.07～恵愛予測'!I18+'[3]2024.7~村予測'!I18+'[3]2024.7~弁当予測'!I18+'[3]2024.7~シェアバー予測'!I18+'[3]2024.7~サウナ予測'!I18+'[3]2024.07~本部予測'!I18 -> 0 | N39: ='[3]2024.07～恵愛予測'!J18+'[3]2024.7~村予測'!J18+'[3]2024.7~弁当予測'!J18+'[3]2024.7~シェアバー予測'!J18+'[3]2024.7~サウナ予測'!J18+'[3]2024.07~本部予測'!J18 -> 0 | O39: ='[3]2024.07～恵愛予測'!K18+'[3]2024.7~村予測'!K18+'[3]2024.7~弁当予測'!K18+'[3]2024.7~シェアバー予測'!K18+'[3]2024.7~サウナ予測'!K18+'[3]2024.07~本部予測'!K18 -> 20000 | P39: ='[2]2024.07～恵愛予測'!L18+'[2]2024.7~村予測'!L18+'[2]2024.7~弁当予測'!L18+'[2]2024.7~シェアバー予測'!L18+'[2]2024.7~サウナ予測'!L18+'[2]2024.07~本部予測'!L18 -> 0 | Q39: ='[2]2024.07～恵愛予測'!M18+'[2]2024.7~村予測'!M18+'[2]2024.7~弁当予測'!M18+'[2]2024.7~シェアバー予測'!M18+'[2]2024.7~サウナ予測'!M18+'[2]2024.07~本部予測'!M18 -> 0 | R39: ='[2]2024.07～恵愛予測'!N18+'[2]2024.7~村予測'!N18+'[2]2024.7~弁当予測'!N18+'[2]2024.7~シェアバー予測'!N18+'[2]2024.7~サウナ予測'!N18+'[2]2024.07~本部予測'!N18 -> 0 | S39: 0 | T39: 0
F40: 減価償却費 | G40: ='[1]2024.07～恵愛予測'!C19+'[1]2024.7~村予測'!C19+'[1]2024.7~弁当予測'!C19+'[1]2024.7~シェアバー予測'!C19+'[1]2024.7~サウナ予測'!C19+'[1]2024.07~本部予測'!C19 -> 749954 | H40: ='[1]2024.07～恵愛予測'!D19+'[1]2024.7~村予測'!D19+'[1]2024.7~弁当予測'!D19+'[1]2024.7~シェアバー予測'!D19+'[1]2024.7~サウナ予測'!D19+'[1]2024.07~本部予測'!D19 -> 749954 | I40: 690589 | J40: 690589 | K40: ='[3]2024.07～恵愛予測'!G19+'[3]2024.7~村予測'!G19+'[3]2024.7~弁当予測'!G19+'[3]2024.7~シェアバー予測'!G19+'[3]2024.7~サウナ予測'!G19+'[3]2024.07~本部予測'!G19 -> 690589 | L40: ='[3]2024.07～恵愛予測'!H19+'[3]2024.7~村予測'!H19+'[3]2024.7~弁当予測'!H19+'[3]2024.7~シェアバー予測'!H19+'[3]2024.7~サウナ予測'!H19+'[3]2024.07~本部予測'!H19 -> 690589 | M40: ='[3]2024.07～恵愛予測'!I19+'[3]2024.7~村予測'!I19+'[3]2024.7~弁当予測'!I19+'[3]2024.7~シェアバー予測'!I19+'[3]2024.7~サウナ予測'!I19+'[3]2024.07~本部予測'!I19 -> 690589 | N40: ='[3]2024.07～恵愛予測'!J19+'[3]2024.7~村予測'!J19+'[3]2024.7~弁当予測'!J19+'[3]2024.7~シェアバー予測'!J19+'[3]2024.7~サウナ予測'!J19+'[3]2024.07~本部予測'!J19 -> 690589 | O40: ='[3]2024.07～恵愛予測'!K19+'[3]2024.7~村予測'!K19+'[3]2024.7~弁当予測'!K19+'[3]2024.7~シェアバー予測'!K19+'[3]2024.7~サウナ予測'!K19+'[3]2024.07~本部予測'!K19 -> 690589 | P40: ='[2]2024.07～恵愛予測'!L19+'[2]2024.7~村予測'!L19+'[2]2024.7~弁当予測'!L19+'[2]2024.7~シェアバー予測'!L19+'[2]2024.7~サウナ予測'!L19+'[2]2024.07~本部予測'!L19 -> 690589 | Q40: ='[2]2024.07～恵愛予測'!M19+'[2]2024.7~村予測'!M19+'[2]2024.7~弁当予測'!M19+'[2]2024.7~シェアバー予測'!M19+'[2]2024.7~サウナ予測'!M19+'[2]2024.07~本部予測'!M19 -> 690589 | R40: ='[2]2024.07～恵愛予測'!N19+'[2]2024.7~村予測'!N19+'[2]2024.7~弁当予測'!N19+'[2]2024.7~シェアバー予測'!N19+'[2]2024.7~サウナ予測'!N19+'[2]2024.07~本部予測'!N19 -> 690589 | S40: 749954 | T40: 749954
F41: 賃借料 | G41: ='[1]2024.07～恵愛予測'!C20+'[1]2024.7~村予測'!C20+'[1]2024.7~弁当予測'!C20+'[1]2024.7~シェアバー予測'!C20+'[1]2024.7~サウナ予測'!C20+'[1]2024.07~本部予測'!C20 -> 30000 | H41: ='[1]2024.07～恵愛予測'!D20+'[1]2024.7~村予測'!D20+'[1]2024.7~弁当予測'!D20+'[1]2024.7~シェアバー予測'!D20+'[1]2024.7~サウナ予測'!D20+'[1]2024.07~本部予測'!D20 -> 30000 | I41: 30000 | J41: 30000 | K41: ='[3]2024.07～恵愛予測'!G20+'[3]2024.7~村予測'!G20+'[3]2024.7~弁当予測'!G20+'[3]2024.7~シェアバー予測'!G20+'[3]2024.7~サウナ予測'!G20+'[3]2024.07~本部予測'!G20 -> 30000 | L41: ='[3]2024.07～恵愛予測'!H20+'[3]2024.7~村予測'!H20+'[3]2024.7~弁当予測'!H20+'[3]2024.7~シェアバー予測'!H20+'[3]2024.7~サウナ予測'!H20+'[3]2024.07~本部予測'!H20 -> 30000 | M41: ='[3]2024.07～恵愛予測'!I20+'[3]2024.7~村予測'!I20+'[3]2024.7~弁当予測'!I20+'[3]2024.7~シェアバー予測'!I20+'[3]2024.7~サウナ予測'!I20+'[3]2024.07~本部予測'!I20 -> 30000 | N41: ='[3]2024.07～恵愛予測'!J20+'[3]2024.7~村予測'!J20+'[3]2024.7~弁当予測'!J20+'[3]2024.7~シェアバー予測'!J20+'[3]2024.7~サウナ予測'!J20+'[3]2024.07~本部予測'!J20 -> 30000 | O41: ='[3]2024.07～恵愛予測'!K20+'[3]2024.7~村予測'!K20+'[3]2024.7~弁当予測'!K20+'[3]2024.7~シェアバー予測'!K20+'[3]2024.7~サウナ予測'!K20+'[3]2024.07~本部予測'!K20 -> 30000 | P41: ='[2]2024.07～恵愛予測'!L20+'[2]2024.7~村予測'!L20+'[2]2024.7~弁当予測'!L20+'[2]2024.7~シェアバー予測'!L20+'[2]2024.7~サウナ予測'!L20+'[2]2024.07~本部予測'!L20 -> 30000 | Q41: ='[2]2024.07～恵愛予測'!M20+'[2]2024.7~村予測'!M20+'[2]2024.7~弁当予測'!M20+'[2]2024.7~シェアバー予測'!M20+'[2]2024.7~サウナ予測'!M20+'[2]2024.07~本部予測'!M20 -> 30000 | R41: ='[2]2024.07～恵愛予測'!N20+'[2]2024.7~村予測'!N20+'[2]2024.7~弁当予測'!N20+'[2]2024.7~シェアバー予測'!N20+'[2]2024.7~サウナ予測'!N20+'[2]2024.07~本部予測'!N20 -> 30000 | S41: 30000 | T41: 30000
F42: 地代家賃 | G42: ='[1]2024.07～恵愛予測'!C21+'[1]2024.7~村予測'!C21+'[1]2024.7~弁当予測'!C21+'[1]2024.7~シェアバー予測'!C21+'[1]2024.7~サウナ予測'!C21+'[1]2024.07~本部予測'!C21 -> 1645661 | H42: ='[1]2024.07～恵愛予測'!D21+'[1]2024.7~村予測'!D21+'[1]2024.7~弁当予測'!D21+'[1]2024.7~シェアバー予測'!D21+'[1]2024.7~サウナ予測'!D21+'[1]2024.07~本部予測'!D21 -> 1645661 | I42: 1645661 | J42: 1645661 | K42: ='[3]2024.07～恵愛予測'!G21+'[3]2024.7~村予測'!G21+'[3]2024.7~弁当予測'!G21+'[3]2024.7~シェアバー予測'!G21+'[3]2024.7~サウナ予測'!G21+'[3]2024.07~本部予測'!G21 -> 1645661 | L42: ='[3]2024.07～恵愛予測'!H21+'[3]2024.7~村予測'!H21+'[3]2024.7~弁当予測'!H21+'[3]2024.7~シェアバー予測'!H21+'[3]2024.7~サウナ予測'!H21+'[3]2024.07~本部予測'!H21 -> 1645661 | M42: ='[3]2024.07～恵愛予測'!I21+'[3]2024.7~村予測'!I21+'[3]2024.7~弁当予測'!I21+'[3]2024.7~シェアバー予測'!I21+'[3]2024.7~サウナ予測'!I21+'[3]2024.07~本部予測'!I21 -> 1645661 | N42: ='[3]2024.07～恵愛予測'!J21+'[3]2024.7~村予測'!J21+'[3]2024.7~弁当予測'!J21+'[3]2024.7~シェアバー予測'!J21+'[3]2024.7~サウナ予測'!J21+'[3]2024.07~本部予測'!J21 -> 1645661 | O42: ='[3]2024.07～恵愛予測'!K21+'[3]2024.7~村予測'!K21+'[3]2024.7~弁当予測'!K21+'[3]2024.7~シェアバー予測'!K21+'[3]2024.7~サウナ予測'!K21+'[3]2024.07~本部予測'!K21 -> 1645661 | P42: ='[2]2024.07～恵愛予測'!L21+'[2]2024.7~村予測'!L21+'[2]2024.7~弁当予測'!L21+'[2]2024.7~シェアバー予測'!L21+'[2]2024.7~サウナ予測'!L21+'[2]2024.07~本部予測'!L21 -> 1645661 | Q42: ='[2]2024.07～恵愛予測'!M21+'[2]2024.7~村予測'!M21+'[2]2024.7~弁当予測'!M21+'[2]2024.7~シェアバー予測'!M21+'[2]2024.7~サウナ予測'!M21+'[2]2024.07~本部予測'!M21 -> 1645661 | R42: ='[2]2024.07～恵愛予測'!N21+'[2]2024.7~村予測'!N21+'[2]2024.7~弁当予測'!N21+'[2]2024.7~シェアバー予測'!N21+'[2]2024.7~サウナ予測'!N21+'[2]2024.07~本部予測'!N21 -> 1645661 | S42: 1645662 | T42: 1645662
F43: リース料 | G43: ='[1]2024.07～恵愛予測'!C22+'[1]2024.7~村予測'!C22+'[1]2024.7~弁当予測'!C22+'[1]2024.7~シェアバー予測'!C22+'[1]2024.7~サウナ予測'!C22+'[1]2024.07~本部予測'!C22 -> 49700 | H43: ='[1]2024.07～恵愛予測'!D22+'[1]2024.7~村予測'!D22+'[1]2024.7~弁当予測'!D22+'[1]2024.7~シェアバー予測'!D22+'[1]2024.7~サウナ予測'!D22+'[1]2024.07~本部予測'!D22 -> 49700 | I43: 49700 | J43: 49700 | K43: ='[3]2024.07～恵愛予測'!G22+'[3]2024.7~村予測'!G22+'[3]2024.7~弁当予測'!G22+'[3]2024.7~シェアバー予測'!G22+'[3]2024.7~サウナ予測'!G22+'[3]2024.07~本部予測'!G22 -> 49700 | L43: ='[3]2024.07～恵愛予測'!H22+'[3]2024.7~村予測'!H22+'[3]2024.7~弁当予測'!H22+'[3]2024.7~シェアバー予測'!H22+'[3]2024.7~サウナ予測'!H22+'[3]2024.07~本部予測'!H22 -> 49700 | M43: ='[3]2024.07～恵愛予測'!I22+'[3]2024.7~村予測'!I22+'[3]2024.7~弁当予測'!I22+'[3]2024.7~シェアバー予測'!I22+'[3]2024.7~サウナ予測'!I22+'[3]2024.07~本部予測'!I22 -> 49700 | N43: ='[3]2024.07～恵愛予測'!J22+'[3]2024.7~村予測'!J22+'[3]2024.7~弁当予測'!J22+'[3]2024.7~シェアバー予測'!J22+'[3]2024.7~サウナ予測'!J22+'[3]2024.07~本部予測'!J22 -> 49700 | O43: ='[3]2024.07～恵愛予測'!K22+'[3]2024.7~村予測'!K22+'[3]2024.7~弁当予測'!K22+'[3]2024.7~シェアバー予測'!K22+'[3]2024.7~サウナ予測'!K22+'[3]2024.07~本部予測'!K22 -> 49700 | P43: ='[2]2024.07～恵愛予測'!L22+'[2]2024.7~村予測'!L22+'[2]2024.7~弁当予測'!L22+'[2]2024.7~シェアバー予測'!L22+'[2]2024.7~サウナ予測'!L22+'[2]2024.07~本部予測'!L22 -> 49700 | Q43: ='[2]2024.07～恵愛予測'!M22+'[2]2024.7~村予測'!M22+'[2]2024.7~弁当予測'!M22+'[2]2024.7~シェアバー予測'!M22+'[2]2024.7~サウナ予測'!M22+'[2]2024.07~本部予測'!M22 -> 49700 | R43: ='[2]2024.07～恵愛予測'!N22+'[2]2024.7~村予測'!N22+'[2]2024.7~弁当予測'!N22+'[2]2024.7~シェアバー予測'!N22+'[2]2024.7~サウナ予測'!N22+'[2]2024.07~本部予測'!N22 -> 49700 | S43: 49700 | T43: 49700
